Workbook
Name _: '[1]1999 BUDGET'!#REF!
Name __: '[1]1999 BUDGET'!#REF!
Name ___: '[1]1999 BUDGET'!#REF!
Name ____: '[1]1999 BUDGET'!#REF!
Name ________________TX3: {#N/A,#N/A,FALSE,"Aging Summary";#N/A,#N/A,FALSE,"Ratio Analysis";#N/A,#N/A,FALSE,"Test 120 Day Accts";#N/A,#N/A,FALSE,"Tickmarks"}
Name ________________TX3: {#N/A,#N/A,FALSE,"Aging Summary";#N/A,#N/A,FALSE,"Ratio Analysis";#N/A,#N/A,FALSE,"Test 120 Day Accts";#N/A,#N/A,FALSE,"Tickmarks"}
Name ________________TX3: {#N/A,#N/A,FALSE,"Aging Summary";#N/A,#N/A,FALSE,"Ratio Analysis";#N/A,#N/A,FALSE,"Test 120 Day Accts";#N/A,#N/A,FALSE,"Tickmarks"}
Name ________________TX3: {#N/A,#N/A,FALSE,"Aging Summary";#N/A,#N/A,FALSE,"Ratio Analysis";#N/A,#N/A,FALSE,"Test 120 Day Accts";#N/A,#N/A,FALSE,"Tickmarks"}
Name _______________TX2: {#N/A,#N/A,FALSE,"Aging Summary";#N/A,#N/A,FALSE,"Ratio Analysis";#N/A,#N/A,FALSE,"Test 120 Day Accts";#N/A,#N/A,FALSE,"Tickmarks"}
Name _______________TX2: {#N/A,#N/A,FALSE,"Aging Summary";#N/A,#N/A,FALSE,"Ratio Analysis";#N/A,#N/A,FALSE,"Test 120 Day Accts";#N/A,#N/A,FALSE,"Tickmarks"}
Name _______________TX2: {#N/A,#N/A,FALSE,"Aging Summary";#N/A,#N/A,FALSE,"Ratio Analysis";#N/A,#N/A,FALSE,"Test 120 Day Accts";#N/A,#N/A,FALSE,"Tickmarks"}
Name _______________TX2: {#N/A,#N/A,FALSE,"Aging Summary";#N/A,#N/A,FALSE,"Ratio Analysis";#N/A,#N/A,FALSE,"Test 120 Day Accts";#N/A,#N/A,FALSE,"Tickmarks"}
Name ____________OK2: {#N/A,#N/A,FALSE,"Cover";#N/A,#N/A,FALSE,"LUMI";#N/A,#N/A,FALSE,"COMD";#N/A,#N/A,FALSE,"Valuation";#N/A,#N/A,FALSE,"Assumptions";#N/A,#N/A,FALSE,"Pooling";#N/A,#N/A,FALSE,"BalanceSheet"}
Name ____________OK2: {#N/A,#N/A,FALSE,"Cover";#N/A,#N/A,FALSE,"LUMI";#N/A,#N/A,FALSE,"COMD";#N/A,#N/A,FALSE,"Valuation";#N/A,#N/A,FALSE,"Assumptions";#N/A,#N/A,FALSE,"Pooling";#N/A,#N/A,FALSE,"BalanceSheet"}
Name ____________OK2: {#N/A,#N/A,FALSE,"Cover";#N/A,#N/A,FALSE,"LUMI";#N/A,#N/A,FALSE,"COMD";#N/A,#N/A,FALSE,"Valuation";#N/A,#N/A,FALSE,"Assumptions";#N/A,#N/A,FALSE,"Pooling";#N/A,#N/A,FALSE,"BalanceSheet"}
Name ____________OK2: {#N/A,#N/A,FALSE,"Cover";#N/A,#N/A,FALSE,"LUMI";#N/A,#N/A,FALSE,"COMD";#N/A,#N/A,FALSE,"Valuation";#N/A,#N/A,FALSE,"Assumptions";#N/A,#N/A,FALSE,"Pooling";#N/A,#N/A,FALSE,"BalanceSheet"}
Name ___________k: {#N/A,#N/A,TRUE,"A-site";#N/A,#N/A,TRUE,"B-Buildings";#N/A,#N/A,TRUE,"c-out-of-fence";#N/A,#N/A,TRUE,"d-proj.infr.";#N/A,#N/A,TRUE,"e- land"}
Name ___________k: {#N/A,#N/A,TRUE,"A-site";#N/A,#N/A,TRUE,"B-Buildings";#N/A,#N/A,TRUE,"c-out-of-fence";#N/A,#N/A,TRUE,"d-proj.infr.";#N/A,#N/A,TRUE,"e- land"}
Name ___________k: {#N/A,#N/A,TRUE,"A-site";#N/A,#N/A,TRUE,"B-Buildings";#N/A,#N/A,TRUE,"c-out-of-fence";#N/A,#N/A,TRUE,"d-proj.infr.";#N/A,#N/A,TRUE,"e- land"}
Name ___________k: {#N/A,#N/A,TRUE,"A-site";#N/A,#N/A,TRUE,"B-Buildings";#N/A,#N/A,TRUE,"c-out-of-fence";#N/A,#N/A,TRUE,"d-proj.infr.";#N/A,#N/A,TRUE,"e- land"}
Name ___________OK2: {#N/A,#N/A,FALSE,"Cover";#N/A,#N/A,FALSE,"LUMI";#N/A,#N/A,FALSE,"COMD";#N/A,#N/A,FALSE,"Valuation";#N/A,#N/A,FALSE,"Assumptions";#N/A,#N/A,FALSE,"Pooling";#N/A,#N/A,FALSE,"BalanceSheet"}
Name ___________OK2: {#N/A,#N/A,FALSE,"Cover";#N/A,#N/A,FALSE,"LUMI";#N/A,#N/A,FALSE,"COMD";#N/A,#N/A,FALSE,"Valuation";#N/A,#N/A,FALSE,"Assumptions";#N/A,#N/A,FALSE,"Pooling";#N/A,#N/A,FALSE,"BalanceSheet"}
Name ___________OK2: {#N/A,#N/A,FALSE,"Cover";#N/A,#N/A,FALSE,"LUMI";#N/A,#N/A,FALSE,"COMD";#N/A,#N/A,FALSE,"Valuation";#N/A,#N/A,FALSE,"Assumptions";#N/A,#N/A,FALSE,"Pooling";#N/A,#N/A,FALSE,"BalanceSheet"}
Name ___________OK2: {#N/A,#N/A,FALSE,"Cover";#N/A,#N/A,FALSE,"LUMI";#N/A,#N/A,FALSE,"COMD";#N/A,#N/A,FALSE,"Valuation";#N/A,#N/A,FALSE,"Assumptions";#N/A,#N/A,FALSE,"Pooling";#N/A,#N/A,FALSE,"BalanceSheet"}
Name ___________w: {#N/A,#N/A,TRUE,"A-site";#N/A,#N/A,TRUE,"B-Buildings";#N/A,#N/A,TRUE,"c-out-of-fence";#N/A,#N/A,TRUE,"d-proj.infr.";#N/A,#N/A,TRUE,"e- land"}
Name ___________w: {#N/A,#N/A,TRUE,"A-site";#N/A,#N/A,TRUE,"B-Buildings";#N/A,#N/A,TRUE,"c-out-of-fence";#N/A,#N/A,TRUE,"d-proj.infr.";#N/A,#N/A,TRUE,"e- land"}
Name ___________w: {#N/A,#N/A,TRUE,"A-site";#N/A,#N/A,TRUE,"B-Buildings";#N/A,#N/A,TRUE,"c-out-of-fence";#N/A,#N/A,TRUE,"d-proj.infr.";#N/A,#N/A,TRUE,"e- land"}
Name ___________w: {#N/A,#N/A,TRUE,"A-site";#N/A,#N/A,TRUE,"B-Buildings";#N/A,#N/A,TRUE,"c-out-of-fence";#N/A,#N/A,TRUE,"d-proj.infr.";#N/A,#N/A,TRUE,"e- land"}
Name __________OK2: {#N/A,#N/A,FALSE,"Cover";#N/A,#N/A,FALSE,"LUMI";#N/A,#N/A,FALSE,"COMD";#N/A,#N/A,FALSE,"Valuation";#N/A,#N/A,FALSE,"Assumptions";#N/A,#N/A,FALSE,"Pooling";#N/A,#N/A,FALSE,"BalanceSheet"}
Name __________OK2: {#N/A,#N/A,FALSE,"Cover";#N/A,#N/A,FALSE,"LUMI";#N/A,#N/A,FALSE,"COMD";#N/A,#N/A,FALSE,"Valuation";#N/A,#N/A,FALSE,"Assumptions";#N/A,#N/A,FALSE,"Pooling";#N/A,#N/A,FALSE,"BalanceSheet"}
Name __________OK2: {#N/A,#N/A,FALSE,"Cover";#N/A,#N/A,FALSE,"LUMI";#N/A,#N/A,FALSE,"COMD";#N/A,#N/A,FALSE,"Valuation";#N/A,#N/A,FALSE,"Assumptions";#N/A,#N/A,FALSE,"Pooling";#N/A,#N/A,FALSE,"BalanceSheet"}
Name __________OK2: {#N/A,#N/A,FALSE,"Cover";#N/A,#N/A,FALSE,"LUMI";#N/A,#N/A,FALSE,"COMD";#N/A,#N/A,FALSE,"Valuation";#N/A,#N/A,FALSE,"Assumptions";#N/A,#N/A,FALSE,"Pooling";#N/A,#N/A,FALSE,"BalanceSheet"}
Name _________key1: '[2]Inc & Exp Assump (1)'!#REF!
Name _________key1: '[2]Inc & Exp Assump (1)'!#REF!
Name _________key2: '[2]Inc & Exp Assump (1)'!#REF!
Name _________key2: '[2]Inc & Exp Assump (1)'!#REF!
Name _________OK2: {#N/A,#N/A,FALSE,"Cover";#N/A,#N/A,FALSE,"LUMI";#N/A,#N/A,FALSE,"COMD";#N/A,#N/A,FALSE,"Valuation";#N/A,#N/A,FALSE,"Assumptions";#N/A,#N/A,FALSE,"Pooling";#N/A,#N/A,FALSE,"BalanceSheet"}
Name _________OK2: {#N/A,#N/A,FALSE,"Cover";#N/A,#N/A,FALSE,"LUMI";#N/A,#N/A,FALSE,"COMD";#N/A,#N/A,FALSE,"Valuation";#N/A,#N/A,FALSE,"Assumptions";#N/A,#N/A,FALSE,"Pooling";#N/A,#N/A,FALSE,"BalanceSheet"}
Name _________OK2: {#N/A,#N/A,FALSE,"Cover";#N/A,#N/A,FALSE,"LUMI";#N/A,#N/A,FALSE,"COMD";#N/A,#N/A,FALSE,"Valuation";#N/A,#N/A,FALSE,"Assumptions";#N/A,#N/A,FALSE,"Pooling";#N/A,#N/A,FALSE,"BalanceSheet"}
Name _________OK2: {#N/A,#N/A,FALSE,"Cover";#N/A,#N/A,FALSE,"LUMI";#N/A,#N/A,FALSE,"COMD";#N/A,#N/A,FALSE,"Valuation";#N/A,#N/A,FALSE,"Assumptions";#N/A,#N/A,FALSE,"Pooling";#N/A,#N/A,FALSE,"BalanceSheet"}
Name ________key1: '[2]Inc & Exp Assump (1)'!#REF!
Name ________key1: '[2]Inc & Exp Assump (1)'!#REF!
Name ________key2: '[2]Inc & Exp Assump (1)'!#REF!
Name ________key2: '[2]Inc & Exp Assump (1)'!#REF!
Name ________OK2: {#N/A,#N/A,FALSE,"Cover";#N/A,#N/A,FALSE,"LUMI";#N/A,#N/A,FALSE,"COMD";#N/A,#N/A,FALSE,"Valuation";#N/A,#N/A,FALSE,"Assumptions";#N/A,#N/A,FALSE,"Pooling";#N/A,#N/A,FALSE,"BalanceSheet"}
Name ________OK2: {#N/A,#N/A,FALSE,"Cover";#N/A,#N/A,FALSE,"LUMI";#N/A,#N/A,FALSE,"COMD";#N/A,#N/A,FALSE,"Valuation";#N/A,#N/A,FALSE,"Assumptions";#N/A,#N/A,FALSE,"Pooling";#N/A,#N/A,FALSE,"BalanceSheet"}
Name ________OK2: {#N/A,#N/A,FALSE,"Cover";#N/A,#N/A,FALSE,"LUMI";#N/A,#N/A,FALSE,"COMD";#N/A,#N/A,FALSE,"Valuation";#N/A,#N/A,FALSE,"Assumptions";#N/A,#N/A,FALSE,"Pooling";#N/A,#N/A,FALSE,"BalanceSheet"}
Name ________OK2: {#N/A,#N/A,FALSE,"Cover";#N/A,#N/A,FALSE,"LUMI";#N/A,#N/A,FALSE,"COMD";#N/A,#N/A,FALSE,"Valuation";#N/A,#N/A,FALSE,"Assumptions";#N/A,#N/A,FALSE,"Pooling";#N/A,#N/A,FALSE,"BalanceSheet"}
Name _______a1: {"Assump",#N/A,TRUE,"Proforma";"first",#N/A,TRUE,"Proforma";"second",#N/A,TRUE,"Proforma";"lease1",#N/A,TRUE,"Proforma";"lease2",#N/A,TRUE,"Proforma"}
Name _______a1: {"Assump",#N/A,TRUE,"Proforma";"first",#N/A,TRUE,"Proforma";"second",#N/A,TRUE,"Proforma";"lease1",#N/A,TRUE,"Proforma";"lease2",#N/A,TRUE,"Proforma"}
Name _______a1: {"Assump",#N/A,TRUE,"Proforma";"first",#N/A,TRUE,"Proforma";"second",#N/A,TRUE,"Proforma";"lease1",#N/A,TRUE,"Proforma";"lease2",#N/A,TRUE,"Proforma"}
Name _______a1: {"Assump",#N/A,TRUE,"Proforma";"first",#N/A,TRUE,"Proforma";"second",#N/A,TRUE,"Proforma";"lease1",#N/A,TRUE,"Proforma";"lease2",#N/A,TRUE,"Proforma"}
Name _______key1: '[2]Inc & Exp Assump (1)'!#REF!
Name _______key1: '[2]Inc & Exp Assump (1)'!#REF!
Name _______key2: '[2]Inc & Exp Assump (1)'!#REF!
Name _______key2: '[2]Inc & Exp Assump (1)'!#REF!
Name _______OK2: {#N/A,#N/A,FALSE,"Cover";#N/A,#N/A,FALSE,"LUMI";#N/A,#N/A,FALSE,"COMD";#N/A,#N/A,FALSE,"Valuation";#N/A,#N/A,FALSE,"Assumptions";#N/A,#N/A,FALSE,"Pooling";#N/A,#N/A,FALSE,"BalanceSheet"}
Name _______OK2: {#N/A,#N/A,FALSE,"Cover";#N/A,#N/A,FALSE,"LUMI";#N/A,#N/A,FALSE,"COMD";#N/A,#N/A,FALSE,"Valuation";#N/A,#N/A,FALSE,"Assumptions";#N/A,#N/A,FALSE,"Pooling";#N/A,#N/A,FALSE,"BalanceSheet"}
Name _______OK2: {#N/A,#N/A,FALSE,"Cover";#N/A,#N/A,FALSE,"LUMI";#N/A,#N/A,FALSE,"COMD";#N/A,#N/A,FALSE,"Valuation";#N/A,#N/A,FALSE,"Assumptions";#N/A,#N/A,FALSE,"Pooling";#N/A,#N/A,FALSE,"BalanceSheet"}
Name _______OK2: {#N/A,#N/A,FALSE,"Cover";#N/A,#N/A,FALSE,"LUMI";#N/A,#N/A,FALSE,"COMD";#N/A,#N/A,FALSE,"Valuation";#N/A,#N/A,FALSE,"Assumptions";#N/A,#N/A,FALSE,"Pooling";#N/A,#N/A,FALSE,"BalanceSheet"}

Sheet Summary & Assumptions
C1: 425 Colorado Street - Glendale, CA
C4: Property Information | J4: Sources & Uses
C5: Name | H5: Glendale Office Multi Conversion | J5: Sources | K5: At Close | L5: Post Close | M5: Total | N5: $/Unit | O5: $/GSF | P5: % Total
C6: Address | H6: 425 Colorado Ave | J6: Acquisition Loan | K6: =L24 -> 15840000 | L6: =-K6 -> -15840000 | M6: =K6+L6 -> 0
C7: City, State | H7: Glendale, CA | J7: Senior Construction Loan | K7: 0 | L7: =L29 -> 32469958 | M7: =K7+L7 -> 32469958 | N7: =$M7/$D$34 -> 225485.82 | O7: =$M7/$H$16 -> 318.58279 | P7: =M7/$M$19 -> 0.551227
C8: Zip | H8: 91205 | J8: Equity | K8: =K19-SUM(K6:K7) -> 13905817 | L8: =M8-K8 -> 12529100 | M8: =M19-SUM(M6:M7) -> 26434917 | N8: =$M8/$D$34 -> 183575.82 | O8: =$M8/$H$16 -> 259.36928 | P8: =M8/$M$19 -> 0.448773
J9: Total Sources | K9: =SUM(K6:K8) -> 29745817 | L9: =SUM(L6:L8) -> 29159058 | M9: =SUM(M6:M8) -> 58904875 | N9: =M9/$D$34 -> 409061.63 | O9: =$M9/$H$16 -> 577.95207 | P9: =SUM(P7:P8) -> 1
C10: Project Size | J10: Uses | K10: At Close | L10: Post Close | M10: Total | P10: % Total
C11: Total Gross SF | H11: =SUM(H12:H15) -> 132765 | J11: Land Costs | K11: ='Budget & Draw Schedule'!W13 -> 28800000 | L11: 0 | M11: =K11+L11 -> 28800000 | N11: =$M11/$D$34 -> 200000 | O11: =$M11/$H$16 -> 282.57457 | P11: =M11/$M$19 -> 0.48892388
C12: Gross Unit SF | H12: 110465 | J12: Hard Costs | K12: ='Budget & Draw Schedule'!W23 -> 0 | L12: ='Budget & Draw Schedule'!G23 -> 19954574 | M12: =K12+L12 -> 19954574 | N12: =$M12/$D$34 -> 138573.43 | O12: =$M12/$H$16 -> 195.78663 | P12: =M12/$M$19 -> 0.33875929
C13: Gross Amenity SF | H13: 7500 | J13: Soft Costs | K13: ='Budget & Draw Schedule'!W39 -> 497817.29 | L13: ='Budget & Draw Schedule'!G39-'Summary & Assumptions'!K13 -> 4864205.3 | M13: =K13+L13 -> 5362022.6 | N13: =$M13/$D$34 -> 37236.268 | O13: =$M13/$H$16 -> 52.610112 | P13: =M13/$M$19 -> 0.091028503
C14: Gross Outdoor/Circulation SF | H14: 14800 | J14: Total Unlevered Uses | K14: =SUM(K11:K13) -> 29297817 | L14: =SUM(L11:L13) -> 24818779 | M14: =M11+M12+M13 -> 54116596 | N14: =$M14/$D$34 -> 375809.7 | O14: =$M14/$H$16 -> 530.97131 | P14: =SUM(P11:P13) -> 0.91871167
C15: Ground Floor Retail SF | H15: 0 | J15: Financing Costs | K15: ='Budget & Draw Schedule'!W50 -> 448000 | L15: =M15-K15 -> 324699.58 | M15: ='Budget & Draw Schedule'!G50-SUM('Budget & Draw Schedule'!G48:G49) -> 772699.58 | P15: =M15/$M$19 -> 0.013117753
C16: Net Residential Square Feet | H16: =E34 -> 101920 | J16: Net Interest Reserve | K16: =SUM(K17:K18) -> 0 | L16: =SUM(L17:L18) -> 4015579.3 | M16: =SUM(M17:M18) -> 4015579.3 | P16: =SUM(P17:P18) -> 0.068170577
C17: Parking Spaces | H17: 365 | J17: Gross Senior Debt Interest | K17: ='Budget & Draw Schedule'!W48 -> 0 | L17: =M17-K17 -> 6505033.1 | M17: ='Budget & Draw Schedule'!G48 -> 6505033.1 | P17: =M17/$M$19 -> 0.11043285
C18: Parking Ratio | H18: =H17/'Unit Mix'!F19 -> 2.3856209 | J18: NOI to Offset Interest | K18: ='Budget & Draw Schedule'!W49 -> 0 | L18: =M18-K18 -> -2489453.8 | M18: ='Budget & Draw Schedule'!G49 -> -2489453.8 | P18: =M18/$M$19 -> -0.042262271
J19: Total Uses | K19: =SUM(K14:K16) -> 29745817 | L19: =SUM(L14:L16) -> 29159058 | M19: =SUM(M14:M16) -> 58904875 | N19: =M19/$D$34 -> 409061.63 | P19: =SUM(P14:P16) -> 1
C20: Unit Mix Summary
C21: Type | D21: # of Units | E21: NSF | F21: NSF/Unit | G21: $/Unit | H21: $/NSF | J21: Acquisition Loan Assumptions | N21: Sale Assumptions
C22: ='Unit Mix'!C7 -> Studio A | D22: ='Unit Mix'!D7 -> 8 | E22: ='Unit Mix'!H7 -> 4480 | F22: =E22/D22 -> 560 | G22: =SUMPRODUCT('Unit Mix'!I7,'Unit Mix'!D7)/SUM('Unit Mix'!D7) -> 2500 | H22: =SUMPRODUCT('Unit Mix'!K7,'Unit Mix'!H7)/SUM('Unit Mix'!H7) -> 4.4642857 | J22: Purchase Price | L22: 28800000 | N22: Inputs
C23: ='Unit Mix'!C8 -> Studio A - Affordable | D23: ='Unit Mix'!D8 -> 12 | E23: ='Unit Mix'!H8 -> 6720 | F23: =E23/D23 -> 560 | G23: =SUMPRODUCT('Unit Mix'!I8,'Unit Mix'!D8)/SUM('Unit Mix'!D8) -> 1400 | H23: =SUMPRODUCT('Unit Mix'!K8,'Unit Mix'!H8)/SUM('Unit Mix'!H8) -> 2.5 | J23: LTC | L23: 0.55 | N23: Hold Period | P23: =H52 -> 5.0833333
C24: ='Unit Mix'!C9 -> Studio B | D24: ='Unit Mix'!D9 -> 30 | E24: ='Unit Mix'!H9 -> 16800 | F24: =E24/D24 -> 560 | G24: =SUMPRODUCT('Unit Mix'!I9,'Unit Mix'!D9)/SUM('Unit Mix'!D9) -> 2600 | H24: =SUMPRODUCT('Unit Mix'!K9,'Unit Mix'!H9)/SUM('Unit Mix'!H9) -> 4.6428571 | J24: Acquisition Loan Proceeds | L24: =L22*L23 -> 15840000 | N24: Exit | P24: =H51 -> 46599
C25: ='Unit Mix'!C10 -> Studio B - Affordable | D25: ='Unit Mix'!D10 -> 10 | E25: ='Unit Mix'!H10 -> 5600 | F25: =E25/D25 -> 560 | G25: =SUMPRODUCT('Unit Mix'!I10,'Unit Mix'!D10)/SUM('Unit Mix'!D10) -> 1400 | H25: =SUMPRODUCT('Unit Mix'!K10,'Unit Mix'!H10)/SUM('Unit Mix'!H10) -> 2.5 | J25: Interest Rate | L25: 0.0575 | N25: Exit Cap Rate | P25: 0.0475
C26: ='Unit Mix'!C11 -> Studio C | D26: ='Unit Mix'!D11 -> 30 | E26: ='Unit Mix'!H11 -> 18000 | F26: =E26/D26 -> 600 | G26: =SUMPRODUCT('Unit Mix'!I11,'Unit Mix'!D11)/SUM('Unit Mix'!D11) -> 2700 | H26: =SUMPRODUCT('Unit Mix'!K11,'Unit Mix'!H11)/SUM('Unit Mix'!H11) -> 4.5 | N26: Sales Cost | P26: 0.01
C27: ='Unit Mix'!C12 -> 1 Bed / 1 Bath | D27: ='Unit Mix'!D12 -> 6 | E27: ='Unit Mix'!H12 -> 4710 | F27: =E27/D27 -> 785 | G27: =SUMPRODUCT('Unit Mix'!I12,'Unit Mix'!D12)/SUM('Unit Mix'!D12) -> 2800 | H27: =SUMPRODUCT('Unit Mix'!K12,'Unit Mix'!H12)/SUM('Unit Mix'!H12) -> 3.566879 | J27: Construction Loan Assumptions | N27: Outputs
C28: ='Unit Mix'!C13 -> 1 Bed / 1 Bath - A (Corner unit) | D28: ='Unit Mix'!D13 -> 13 | E28: ='Unit Mix'!H13 -> 12610 | F28: =E28/D28 -> 970 | G28: =SUMPRODUCT('Unit Mix'!I13,'Unit Mix'!D13)/SUM('Unit Mix'!D13) -> 3000 | H28: =SUMPRODUCT('Unit Mix'!K13,'Unit Mix'!H13)/SUM('Unit Mix'!H13) -> 3.0927835 | J28: LTC | L28: 0.6 | N28: Forward 12 Mo. NOI at Sale | P28: =SUMIF('Annual CFs'!$I$6:$S$6,ROUNDDOWN('Summary & Assumptions'!P23,1)+2,'Annual CFs'!$I$46:$S$46) -> 4266430.9
C29: ='Unit Mix'!C14 -> 1 Bed / 1 Bath - B (Regular Unit) | D29: ='Unit Mix'!D14 -> 16 | E29: ='Unit Mix'!H14 -> 14380 | F29: =E29/D29 -> 898.75 | G29: =SUMPRODUCT('Unit Mix'!I14,'Unit Mix'!D14)/SUM('Unit Mix'!D14) -> 2900 | H29: =SUMPRODUCT('Unit Mix'!K14,'Unit Mix'!H14)/SUM('Unit Mix'!H14) -> 3.2267038 | J29: Construction Loan Proceeds | L29: =M14*L28 -> 32469958 | M29: =M14*L28 -> 32469958 | N29: Sale Value | P29: =P28/P25 -> 89819599
C30: ='Unit Mix'!C15 -> 2 Bed / 2 Bath | D30: ='Unit Mix'!D15 -> 8 | E30: ='Unit Mix'!H15 -> 8800 | F30: =E30/D30 -> 1100 | G30: =SUMPRODUCT('Unit Mix'!I15,'Unit Mix'!D15)/SUM('Unit Mix'!D15) -> 3800 | H30: =SUMPRODUCT('Unit Mix'!K15,'Unit Mix'!H15)/SUM('Unit Mix'!H15) -> 3.4545455 | J30: Libor | L30: {=INDEX(LIBOR!$F$10:$F$130,MATCH('Summary & Assumptions'!H38,LIBOR!$D$10:$D$130,0))} -> 0.0010088 | N30: Sale Price | P30: =P29-(P29*$P$26) -> 88921403
C31: ='Unit Mix'!C16 -> Live Work Loft - A | D31: ='Unit Mix'!D16 -> 3 | E31: ='Unit Mix'!H16 -> 3300 | F31: =E31/D31 -> 1100 | G31: =SUMPRODUCT('Unit Mix'!I16,'Unit Mix'!D16)/SUM('Unit Mix'!D16) -> 3850 | H31: =SUMPRODUCT('Unit Mix'!K16,'Unit Mix'!H16)/SUM('Unit Mix'!H16) -> 3.5 | J31: Libor Cap | L31: 0.03 | T31: Return Sensitivity
C32: ='Unit Mix'!C17 -> Live Work Loft - B | D32: ='Unit Mix'!D17 -> 7 | E32: ='Unit Mix'!H17 -> 5420 | F32: =E32/D32 -> 774.28571 | G32: =SUMPRODUCT('Unit Mix'!I17,'Unit Mix'!D17)/SUM('Unit Mix'!D17) -> 3000 | H32: =SUMPRODUCT('Unit Mix'!K17,'Unit Mix'!H17)/SUM('Unit Mix'!H17) -> 3.8745387 | J32: Libor Floor | L32: 0.0025 | N32: Equity Return Summary | T32: Avg. Rent | U32: Exit Cap
C33: ='Unit Mix'!C18 -> Live Work Loft - C | D33: ='Unit Mix'!D18 -> 1 | E33: ='Unit Mix'!H18 -> 1100 | F33: =E33/D33 -> 1100 | G33: =SUMPRODUCT('Unit Mix'!I18,'Unit Mix'!D18)/SUM('Unit Mix'!D18) -> 4000 | H33: =SUMPRODUCT('Unit Mix'!K18,'Unit Mix'!H18)/SUM('Unit Mix'!H18) -> 3.6363636 | J33: Effective Libor | L33: =IF(L30>L31,L31,IF(L30<L32,L32,L30)) -> 0.0025 | N33: Contributions | P33: ='Budget & Draw Schedule'!P101 -> 26434917 | T33: =+TEXT(P36,"0.0%")&"/"&TEXT(P37,"0.0x") -> 20.5%/1.3x | U33: 0.04 | V33: =U33+0.0025 -> 0.0425 | W33: =V33+0.0025 -> 0.045 | X33: =W33+0.0025 -> 0.0475 | Y33: =X33+0.0025 -> 0.05
C34: Total / Wtd. Avg. | D34: =SUM(D22:D33) -> 144 | E34: =SUM(E22:E33) -> 101920 | F34: =E34/D34 -> 707.77778 | G34: =SUMPRODUCT(G22:G33,D22:D33)/D34 -> 2631.5972 | H34: =G34/F34 -> 3.7181122 | J34: Spread | L34: 0.04 | N34: Distributions | P34: ='Budget & Draw Schedule'!P102 -> 59870612 | T34: =+T35-0.05 -> 3.65 | U34: 26.9%/2.0x | V34: 24.5%/1.7x | W34: 22.3%/1.5x | X34: 20.1%/1.3x | Y34: 18.0%/1.1x
C35: Live | H35: =H34 -> 3.7181122 | J35: Interest Rate | L35: =L33+L34 -> 0.0425 | N35: Profit | P35: ='Budget & Draw Schedule'!P103 -> 33435695 | T35: =+T36-0.05 -> 3.7 | U35: 27.6%/2.1x | V35: 25.2%/1.8x | W35: 22.9%/1.6x | X35: 20.8%/1.4x | Y35: 18.7%/1.2x
N36: IRR | P36: ='Budget & Draw Schedule'!P104 -> 0.2045109 | T36: 3.75 | U36: 28.2%/2.1x | V36: 25.9%/1.9x | W36: 23.6%/1.6x | X36: 21.4%/1.4x | Y36: 19.4%/1.2x
C37: Timing Assumptions | J37: Return Metrics | N37: Equity Multiple | P37: ='Budget & Draw Schedule'!P105 -> 1.2648307 | T37: =+T36+0.05 -> 3.8 | U37: 28.9%/2.2x | V37: 26.5%/2.0x | W37: 24.3%/1.7x | X37: 22.1%/1.5x | Y37: 20.0%/1.3x
C38: Model Start | H38: 44713 | K38: Stabilized | L38: Stabilized | T38: =+T37+0.05 -> 3.85 | U38: 29.5%/2.3x | V38: 27.1%/2.0x | W38: 24.9%/1.8x | X38: 22.8%/1.6x | Y38: 20.7%/1.4x
C39: Predevelopment Period | H39: 24 | K39: Untrended | L39: Trended (Yr 5) | T39: =+T38+0.05 -> 3.9 | U39: 30.1%/2.4x | V39: 27.8%/2.1x | W39: 25.5%/1.8x | X39: 23.4%/1.6x | Y39: 21.3%/1.4x
C40: Land Close | H40: 44713 | J40: Net Operating Income | K40: ='Annual CFs'!G46 -> 3520935.5 | L40: ='Annual CFs'!M46 -> 4021520.3 | T40: =+T39+0.05 -> 3.95 | U40: 30.7%/2.4x | V40: 28.4%/2.2x | W40: 26.1%/1.9x | X40: 24.0%/1.7x | Y40: 22.0%/1.5x
C41: Construction Start Date | H41: =EOMONTH(H38,H39)+1 -> 45474 | J41: Return on Cost | K41: =K40/$M$19 -> 0.059773244 | L41: =L40/$M$19 -> 0.068271435
C42: Construction Period | H42: 18 | J42: Debt Yield | K42: =K40/$M$7 -> 0.10843671 | L42: =L40/$M$7 -> 0.12385358
C43: Construction End Date | H43: =EOMONTH(H41,H42-1) -> 46022
C44: Lease-Up Start | H44: =H43+1 -> 46023 | J44: Real Estate Tax Analysis
C45: Lease-Up Period | H45: 6 | J45: Millage Rate/As-Is Property Taxes | K45: 0.01088042 | L45: =K45*L22 -> 313356.1
C46: # Units Leased at Opening | H46: =D34*60% -> 86.4 | J46: Stabilized Property Taxes | L46: 548294
C47: # Unit Lease-Up Per Month | H47: 12 | J47: RET Per Unit | L47: =L46/D34 -> 3807.5972
C48: Lease-Up End | H48: =EOMONTH(H44,H45-1) -> 46203 | J48: RET Per NRSF | L48: =L46/H16 -> 5.3796507
C49: Stabilization Date | H49: =H48+1 -> 46204
C50: Stabilization Hold Period | H50: 12
C51: Disposition Date | H51: =EOMONTH(H49,H50) -> 46599
C52: Total Project Timeline | H52: =DATEDIF(H38,H51,"m")/12 -> 5.0833333

Sheet Annual CFs
C4: Annual Cash Flow Proforma
G5: Stabilized | I5: 2022 | J5: 2023 | K5: 2024 | L5: 2025 | M5: 2026 | N5: 2027 | O5: 2028 | P5: 2029 | Q5: 2030 | R5: 2031 | S5: 2032
C6: Year | G6: Untrended | I6: 1 | J6: =I6+1 -> 2 | K6: =J6+1 -> 3 | L6: =K6+1 -> 4 | M6: =L6+1 -> 5 | N6: =M6+1 -> 6 | O6: =N6+1 -> 7 | P6: =O6+1 -> 8 | Q6: =P6+1 -> 9 | ... S6: =R6+1 -> 11
C8: Income
C9: Rental Income | G9: ='Unit Mix'!M19 -> 4547400 | I9: =SUMIF('Monthly CFs'!$G$5:$EI$5,'Annual CFs'!I$6,'Monthly CFs'!$G38:$EI38) -> 0 | J9: =SUMIF('Monthly CFs'!$G$5:$EI$5,'Annual CFs'!J$6,'Monthly CFs'!$G38:$EI38) -> 0 | K9: =SUMIF('Monthly CFs'!$G$5:$EI$5,'Annual CFs'!K$6,'Monthly CFs'!$G38:$EI38) -> 0 | L9: =SUMIF('Monthly CFs'!$G$5:$EI$5,'Annual CFs'!L$6,'Monthly CFs'!$G38:$EI38) -> 2001429.7 | M9: =SUMIF('Monthly CFs'!$G$5:$EI$5,'Annual CFs'!M$6,'Monthly CFs'!$G38:$EI38) -> 5118138.8 | N9: =SUMIF('Monthly CFs'!$G$5:$EI$5,'Annual CFs'!N$6,'Monthly CFs'!$G38:$EI38) -> 5271682.9 | O9: =SUMIF('Monthly CFs'!$G$5:$EI$5,'Annual CFs'!O$6,'Monthly CFs'!$G38:$EI38) -> 5429833.4 | P9: =SUMIF('Monthly CFs'!$G$5:$EI$5,'Annual CFs'!P$6,'Monthly CFs'!$G38:$EI38) -> 5592728.4 | ... S9: =SUMIF('Monthly CFs'!$G$5:$EI$5,'Annual CFs'!S$6,'Monthly CFs'!$G38:$EI38) -> 6111325.3
C10: Potential Gross Rent | G10: =SUM(G9) -> 4547400 | I10: =SUM(I9) -> 0 | J10: =SUM(J9) -> 0 | K10: =SUM(K9) -> 0 | L10: =SUM(L9) -> 2001429.7 | M10: =SUM(M9) -> 5118138.8 | N10: =SUM(N9) -> 5271682.9 | O10: =SUM(O9) -> 5429833.4 | P10: =SUM(P9) -> 5592728.4 | ... S10: =SUM(S9) -> 6111325.3
C12: Losses to GPR
C13: Market Vacancy | E13: ='Growth Rates'!G20 -> 0.05 | G13: =-$G$10*E13 -> -227370 | I13: =SUMIF('Monthly CFs'!$G$5:$EI$5,'Annual CFs'!I$6,'Monthly CFs'!$G42:$EI42) -> 0 | J13: =SUMIF('Monthly CFs'!$G$5:$EI$5,'Annual CFs'!J$6,'Monthly CFs'!$G42:$EI42) -> 0 | K13: =SUMIF('Monthly CFs'!$G$5:$EI$5,'Annual CFs'!K$6,'Monthly CFs'!$G42:$EI42) -> 0 | L13: =SUMIF('Monthly CFs'!$G$5:$EI$5,'Annual CFs'!L$6,'Monthly CFs'!$G42:$EI42) -> -20704.445 | M13: =SUMIF('Monthly CFs'!$G$5:$EI$5,'Annual CFs'!M$6,'Monthly CFs'!$G42:$EI42) -> -255906.94 | N13: =SUMIF('Monthly CFs'!$G$5:$EI$5,'Annual CFs'!N$6,'Monthly CFs'!$G42:$EI42) -> -263584.15 | O13: =SUMIF('Monthly CFs'!$G$5:$EI$5,'Annual CFs'!O$6,'Monthly CFs'!$G42:$EI42) -> -271491.67 | P13: =SUMIF('Monthly CFs'!$G$5:$EI$5,'Annual CFs'!P$6,'Monthly CFs'!$G42:$EI42) -> -279636.42 | ... S13: =SUMIF('Monthly CFs'!$G$5:$EI$5,'Annual CFs'!S$6,'Monthly CFs'!$G42:$EI42) -> -305566.27
C14: Non-Rev Beds | E14: ='Growth Rates'!I20 -> 0.0025 | G14: =-$G$10*E14 -> -11368.5 | I14: =SUMIF('Monthly CFs'!$G$5:$EI$5,'Annual CFs'!I$6,'Monthly CFs'!$G43:$EI43) -> 0 | J14: =SUMIF('Monthly CFs'!$G$5:$EI$5,'Annual CFs'!J$6,'Monthly CFs'!$G43:$EI43) -> 0 | K14: =SUMIF('Monthly CFs'!$G$5:$EI$5,'Annual CFs'!K$6,'Monthly CFs'!$G43:$EI43) -> 0 | L14: =SUMIF('Monthly CFs'!$G$5:$EI$5,'Annual CFs'!L$6,'Monthly CFs'!$G43:$EI43) -> -5003.5742 | M14: =SUMIF('Monthly CFs'!$G$5:$EI$5,'Annual CFs'!M$6,'Monthly CFs'!$G43:$EI43) -> -12795.347 | N14: =SUMIF('Monthly CFs'!$G$5:$EI$5,'Annual CFs'!N$6,'Monthly CFs'!$G43:$EI43) -> -13179.207 | O14: =SUMIF('Monthly CFs'!$G$5:$EI$5,'Annual CFs'!O$6,'Monthly CFs'!$G43:$EI43) -> -13574.584 | P14: =SUMIF('Monthly CFs'!$G$5:$EI$5,'Annual CFs'!P$6,'Monthly CFs'!$G43:$EI43) -> -13981.821 | ... S14: =SUMIF('Monthly CFs'!$G$5:$EI$5,'Annual CFs'!S$6,'Monthly CFs'!$G43:$EI43) -> -15278.313
C15: Bad Debt | E15: ='Growth Rates'!J20 -> 0.0075 | G15: =-$G$10*E15 -> -34105.5 | I15: =SUMIF('Monthly CFs'!$G$5:$EI$5,'Annual CFs'!I$6,'Monthly CFs'!$G44:$EI44) -> 0 | J15: =SUMIF('Monthly CFs'!$G$5:$EI$5,'Annual CFs'!J$6,'Monthly CFs'!$G44:$EI44) -> 0 | K15: =SUMIF('Monthly CFs'!$G$5:$EI$5,'Annual CFs'!K$6,'Monthly CFs'!$G44:$EI44) -> 0 | L15: =SUMIF('Monthly CFs'!$G$5:$EI$5,'Annual CFs'!L$6,'Monthly CFs'!$G44:$EI44) -> -15010.723 | M15: =SUMIF('Monthly CFs'!$G$5:$EI$5,'Annual CFs'!M$6,'Monthly CFs'!$G44:$EI44) -> -38386.041 | N15: =SUMIF('Monthly CFs'!$G$5:$EI$5,'Annual CFs'!N$6,'Monthly CFs'!$G44:$EI44) -> -39537.622 | O15: =SUMIF('Monthly CFs'!$G$5:$EI$5,'Annual CFs'!O$6,'Monthly CFs'!$G44:$EI44) -> -40723.751 | P15: =SUMIF('Monthly CFs'!$G$5:$EI$5,'Annual CFs'!P$6,'Monthly CFs'!$G44:$EI44) -> -41945.463 | ... S15: =SUMIF('Monthly CFs'!$G$5:$EI$5,'Annual CFs'!S$6,'Monthly CFs'!$G44:$EI44) -> -45834.94
C16: Concessions | E16: ='Growth Rates'!K20 -> 0.0025 | G16: =-$G$10*E16 -> -11368.5 | I16: =SUMIF('Monthly CFs'!$G$5:$EI$5,'Annual CFs'!I$6,'Monthly CFs'!$G45:$EI45) -> 0 | J16: =SUMIF('Monthly CFs'!$G$5:$EI$5,'Annual CFs'!J$6,'Monthly CFs'!$G45:$EI45) -> 0 | K16: =SUMIF('Monthly CFs'!$G$5:$EI$5,'Annual CFs'!K$6,'Monthly CFs'!$G45:$EI45) -> 0 | L16: =SUMIF('Monthly CFs'!$G$5:$EI$5,'Annual CFs'!L$6,'Monthly CFs'!$G45:$EI45) -> -20014.297 | M16: =SUMIF('Monthly CFs'!$G$5:$EI$5,'Annual CFs'!M$6,'Monthly CFs'!$G45:$EI45) -> -12795.347 | N16: =SUMIF('Monthly CFs'!$G$5:$EI$5,'Annual CFs'!N$6,'Monthly CFs'!$G45:$EI45) -> -13179.207 | O16: =SUMIF('Monthly CFs'!$G$5:$EI$5,'Annual CFs'!O$6,'Monthly CFs'!$G45:$EI45) -> -13574.584 | P16: =SUMIF('Monthly CFs'!$G$5:$EI$5,'Annual CFs'!P$6,'Monthly CFs'!$G45:$EI45) -> -13981.821 | ... S16: =SUMIF('Monthly CFs'!$G$5:$EI$5,'Annual CFs'!S$6,'Monthly CFs'!$G45:$EI45) -> -15278.313
C17: Total Losses to GPR | G17: =SUM(G13:G16) -> -284212.5 | I17: =SUM(I13:I16) -> 0 | J17: =SUM(J13:J16) -> 0 | K17: =SUM(K13:K16) -> 0 | L17: =SUM(L13:L16) -> -60733.038 | M17: =SUM(M13:M16) -> -319883.67 | N17: =SUM(N13:N16) -> -329480.18 | O17: =SUM(O13:O16) -> -339364.59 | P17: =SUM(P13:P16) -> -349545.53 | ... S17: =SUM(S13:S16) -> -381957.83
C19: Effective Rental Income | G19: =G17+G10 -> 4263187.5 | I19: =I17+I10 -> 0 | J19: =J17+J10 -> 0 | K19: =K17+K10 -> 0 | L19: =L17+L10 -> 1940696.6 | M19: =M17+M10 -> 4798255.1 | N19: =N17+N10 -> 4942202.7 | O19: =O17+O10 -> 5090468.8 | P19: =P17+P10 -> 5243182.9 | ... S19: =S17+S10 -> 5729367.5
C21: Other Income
C22: Parking Permit Fees | G22: ='OI & Expense Growth'!F7 -> 438000 | I22: =SUMIF('Monthly CFs'!$G$5:$EI$5,'Annual CFs'!I$6,'Monthly CFs'!$G51:$EI51) -> 0 | J22: =SUMIF('Monthly CFs'!$G$5:$EI$5,'Annual CFs'!J$6,'Monthly CFs'!$G51:$EI51) -> 0 | K22: =SUMIF('Monthly CFs'!$G$5:$EI$5,'Annual CFs'!K$6,'Monthly CFs'!$G51:$EI51) -> 0 | L22: =SUMIF('Monthly CFs'!$G$5:$EI$5,'Annual CFs'!L$6,'Monthly CFs'!$G51:$EI51) -> 176416.67 | M22: =SUMIF('Monthly CFs'!$G$5:$EI$5,'Annual CFs'!M$6,'Monthly CFs'!$G51:$EI51) -> 451140 | N22: =SUMIF('Monthly CFs'!$G$5:$EI$5,'Annual CFs'!N$6,'Monthly CFs'!$G51:$EI51) -> 464674.2 | O22: =SUMIF('Monthly CFs'!$G$5:$EI$5,'Annual CFs'!O$6,'Monthly CFs'!$G51:$EI51) -> 478614.43 | P22: =SUMIF('Monthly CFs'!$G$5:$EI$5,'Annual CFs'!P$6,'Monthly CFs'!$G51:$EI51) -> 492972.86 | ... S22: =SUMIF('Monthly CFs'!$G$5:$EI$5,'Annual CFs'!S$6,'Monthly CFs'!$G51:$EI51) -> 538684.75
C23: Utility Charge | G23: ='OI & Expense Growth'!F8 -> 129600 | I23: =SUMIF('Monthly CFs'!$G$5:$EI$5,'Annual CFs'!I$6,'Monthly CFs'!$G52:$EI52) -> 0 | J23: =SUMIF('Monthly CFs'!$G$5:$EI$5,'Annual CFs'!J$6,'Monthly CFs'!$G52:$EI52) -> 0 | K23: =SUMIF('Monthly CFs'!$G$5:$EI$5,'Annual CFs'!K$6,'Monthly CFs'!$G52:$EI52) -> 0 | L23: =SUMIF('Monthly CFs'!$G$5:$EI$5,'Annual CFs'!L$6,'Monthly CFs'!$G52:$EI52) -> 52200 | M23: =SUMIF('Monthly CFs'!$G$5:$EI$5,'Annual CFs'!M$6,'Monthly CFs'!$G52:$EI52) -> 133488 | N23: =SUMIF('Monthly CFs'!$G$5:$EI$5,'Annual CFs'!N$6,'Monthly CFs'!$G52:$EI52) -> 137492.64 | O23: =SUMIF('Monthly CFs'!$G$5:$EI$5,'Annual CFs'!O$6,'Monthly CFs'!$G52:$EI52) -> 141617.42 | P23: =SUMIF('Monthly CFs'!$G$5:$EI$5,'Annual CFs'!P$6,'Monthly CFs'!$G52:$EI52) -> 145865.94 | ... S23: =SUMIF('Monthly CFs'!$G$5:$EI$5,'Annual CFs'!S$6,'Monthly CFs'!$G52:$EI52) -> 159391.65
C24: Utility Billing Income | G24: ='OI & Expense Growth'!F9 -> 60480 | I24: =SUMIF('Monthly CFs'!$G$5:$EI$5,'Annual CFs'!I$6,'Monthly CFs'!$G53:$EI53) -> 0 | J24: =SUMIF('Monthly CFs'!$G$5:$EI$5,'Annual CFs'!J$6,'Monthly CFs'!$G53:$EI53) -> 0 | K24: =SUMIF('Monthly CFs'!$G$5:$EI$5,'Annual CFs'!K$6,'Monthly CFs'!$G53:$EI53) -> 0 | L24: =SUMIF('Monthly CFs'!$G$5:$EI$5,'Annual CFs'!L$6,'Monthly CFs'!$G53:$EI53) -> 24360 | M24: =SUMIF('Monthly CFs'!$G$5:$EI$5,'Annual CFs'!M$6,'Monthly CFs'!$G53:$EI53) -> 62294.4 | N24: =SUMIF('Monthly CFs'!$G$5:$EI$5,'Annual CFs'!N$6,'Monthly CFs'!$G53:$EI53) -> 64163.232 | O24: =SUMIF('Monthly CFs'!$G$5:$EI$5,'Annual CFs'!O$6,'Monthly CFs'!$G53:$EI53) -> 66088.129 | P24: =SUMIF('Monthly CFs'!$G$5:$EI$5,'Annual CFs'!P$6,'Monthly CFs'!$G53:$EI53) -> 68070.773 | ... S24: =SUMIF('Monthly CFs'!$G$5:$EI$5,'Annual CFs'!S$6,'Monthly CFs'!$G53:$EI53) -> 74382.771
C25: Retail Income (NNN) | G25: ='OI & Expense Growth'!F10 -> 0 | I25: =SUMIF('Monthly CFs'!$G$5:$EI$5,'Annual CFs'!I$6,'Monthly CFs'!$G54:$EI54) -> 0 | J25: =SUMIF('Monthly CFs'!$G$5:$EI$5,'Annual CFs'!J$6,'Monthly CFs'!$G54:$EI54) -> 0 | K25: =SUMIF('Monthly CFs'!$G$5:$EI$5,'Annual CFs'!K$6,'Monthly CFs'!$G54:$EI54) -> 0 | L25: =SUMIF('Monthly CFs'!$G$5:$EI$5,'Annual CFs'!L$6,'Monthly CFs'!$G54:$EI54) -> 0 | M25: =SUMIF('Monthly CFs'!$G$5:$EI$5,'Annual CFs'!M$6,'Monthly CFs'!$G54:$EI54) -> 0 | N25: =SUMIF('Monthly CFs'!$G$5:$EI$5,'Annual CFs'!N$6,'Monthly CFs'!$G54:$EI54) -> 0 | O25: =SUMIF('Monthly CFs'!$G$5:$EI$5,'Annual CFs'!O$6,'Monthly CFs'!$G54:$EI54) -> 0 | P25: =SUMIF('Monthly CFs'!$G$5:$EI$5,'Annual CFs'!P$6,'Monthly CFs'!$G54:$EI54) -> 0 | ... S25: =SUMIF('Monthly CFs'!$G$5:$EI$5,'Annual CFs'!S$6,'Monthly CFs'!$G54:$EI54) -> 0
C26: Total Other Income | G26: =SUM(G22:G25) -> 628080 | I26: =SUM(I22:I25) -> 0 | J26: =SUM(J22:J25) -> 0 | K26: =SUM(K22:K25) -> 0 | L26: =SUM(L22:L25) -> 252976.67 | M26: =SUM(M22:M25) -> 646922.4 | N26: =SUM(N22:N25) -> 666330.07 | O26: =SUM(O22:O25) -> 686319.97 | P26: =SUM(P22:P25) -> 706909.57 | ... S26: =SUM(S22:S25) -> 772459.18
C28: Effective Gross Income | G28: =G19+G26 -> 4891267.5 | I28: =I19+I26 -> 0 | J28: =J19+J26 -> 0 | K28: =K19+K26 -> 0 | L28: =L19+L26 -> 2193673.3 | M28: =M19+M26 -> 5445177.5 | N28: =N19+N26 -> 5608532.8 | O28: =O19+O26 -> 5776788.8 | P28: =P19+P26 -> 5950092.5 | ... S28: =S19+S26 -> 6501826.7
C30: Controllable Expenses
C31: Payroll | G31: ='OI & Expense Growth'!F13 -> 115200 | I31: =SUMIF('Monthly CFs'!$G$5:$EI$5,'Annual CFs'!I$6,'Monthly CFs'!$G60:$EI60) -> 0 | J31: =SUMIF('Monthly CFs'!$G$5:$EI$5,'Annual CFs'!J$6,'Monthly CFs'!$G60:$EI60) -> 0 | K31: =SUMIF('Monthly CFs'!$G$5:$EI$5,'Annual CFs'!K$6,'Monthly CFs'!$G60:$EI60) -> 0 | L31: =SUMIF('Monthly CFs'!$G$5:$EI$5,'Annual CFs'!L$6,'Monthly CFs'!$G60:$EI60) -> 46400 | M31: =SUMIF('Monthly CFs'!$G$5:$EI$5,'Annual CFs'!M$6,'Monthly CFs'!$G60:$EI60) -> 118656 | N31: =SUMIF('Monthly CFs'!$G$5:$EI$5,'Annual CFs'!N$6,'Monthly CFs'!$G60:$EI60) -> 122215.68 | O31: =SUMIF('Monthly CFs'!$G$5:$EI$5,'Annual CFs'!O$6,'Monthly CFs'!$G60:$EI60) -> 125882.15 | P31: =SUMIF('Monthly CFs'!$G$5:$EI$5,'Annual CFs'!P$6,'Monthly CFs'!$G60:$EI60) -> 129658.61 | ... S31: =SUMIF('Monthly CFs'!$G$5:$EI$5,'Annual CFs'!S$6,'Monthly CFs'!$G60:$EI60) -> 141681.47
C32: Marketing & Advertising | G32: ='OI & Expense Growth'!F14 -> 64800 | I32: =SUMIF('Monthly CFs'!$G$5:$EI$5,'Annual CFs'!I$6,'Monthly CFs'!$G61:$EI61) -> 0 | J32: =SUMIF('Monthly CFs'!$G$5:$EI$5,'Annual CFs'!J$6,'Monthly CFs'!$G61:$EI61) -> 0 | K32: =SUMIF('Monthly CFs'!$G$5:$EI$5,'Annual CFs'!K$6,'Monthly CFs'!$G61:$EI61) -> 0 | L32: =SUMIF('Monthly CFs'!$G$5:$EI$5,'Annual CFs'!L$6,'Monthly CFs'!$G61:$EI61) -> 26100 | M32: =SUMIF('Monthly CFs'!$G$5:$EI$5,'Annual CFs'!M$6,'Monthly CFs'!$G61:$EI61) -> 66744 | N32: =SUMIF('Monthly CFs'!$G$5:$EI$5,'Annual CFs'!N$6,'Monthly CFs'!$G61:$EI61) -> 68746.32 | O32: =SUMIF('Monthly CFs'!$G$5:$EI$5,'Annual CFs'!O$6,'Monthly CFs'!$G61:$EI61) -> 70808.71 | P32: =SUMIF('Monthly CFs'!$G$5:$EI$5,'Annual CFs'!P$6,'Monthly CFs'!$G61:$EI61) -> 72932.971 | ... S32: =SUMIF('Monthly CFs'!$G$5:$EI$5,'Annual CFs'!S$6,'Monthly CFs'!$G61:$EI61) -> 79695.826
C33: Repairs & Maintenance | G33: ='OI & Expense Growth'!F15 -> 61200 | I33: =SUMIF('Monthly CFs'!$G$5:$EI$5,'Annual CFs'!I$6,'Monthly CFs'!$G62:$EI62) -> 0 | J33: =SUMIF('Monthly CFs'!$G$5:$EI$5,'Annual CFs'!J$6,'Monthly CFs'!$G62:$EI62) -> 0 | K33: =SUMIF('Monthly CFs'!$G$5:$EI$5,'Annual CFs'!K$6,'Monthly CFs'!$G62:$EI62) -> 0 | L33: =SUMIF('Monthly CFs'!$G$5:$EI$5,'Annual CFs'!L$6,'Monthly CFs'!$G62:$EI62) -> 24650 | M33: =SUMIF('Monthly CFs'!$G$5:$EI$5,'Annual CFs'!M$6,'Monthly CFs'!$G62:$EI62) -> 63036 | N33: =SUMIF('Monthly CFs'!$G$5:$EI$5,'Annual CFs'!N$6,'Monthly CFs'!$G62:$EI62) -> 64927.08 | O33: =SUMIF('Monthly CFs'!$G$5:$EI$5,'Annual CFs'!O$6,'Monthly CFs'!$G62:$EI62) -> 66874.892 | P33: =SUMIF('Monthly CFs'!$G$5:$EI$5,'Annual CFs'!P$6,'Monthly CFs'!$G62:$EI62) -> 68881.139 | ... S33: =SUMIF('Monthly CFs'!$G$5:$EI$5,'Annual CFs'!S$6,'Monthly CFs'!$G62:$EI62) -> 75268.281
C34: Turnover | G34: ='OI & Expense Growth'!F16 -> 88500 | I34: =SUMIF('Monthly CFs'!$G$5:$EI$5,'Annual CFs'!I$6,'Monthly CFs'!$G63:$EI63) -> 0 | J34: =SUMIF('Monthly CFs'!$G$5:$EI$5,'Annual CFs'!J$6,'Monthly CFs'!$G63:$EI63) -> 0 | K34: =SUMIF('Monthly CFs'!$G$5:$EI$5,'Annual CFs'!K$6,'Monthly CFs'!$G63:$EI63) -> 0 | L34: =SUMIF('Monthly CFs'!$G$5:$EI$5,'Annual CFs'!L$6,'Monthly CFs'!$G63:$EI63) -> 35645.833 | M34: =SUMIF('Monthly CFs'!$G$5:$EI$5,'Annual CFs'!M$6,'Monthly CFs'!$G63:$EI63) -> 91155 | N34: =SUMIF('Monthly CFs'!$G$5:$EI$5,'Annual CFs'!N$6,'Monthly CFs'!$G63:$EI63) -> 93889.65 | O34: =SUMIF('Monthly CFs'!$G$5:$EI$5,'Annual CFs'!O$6,'Monthly CFs'!$G63:$EI63) -> 96706.34 | P34: =SUMIF('Monthly CFs'!$G$5:$EI$5,'Annual CFs'!P$6,'Monthly CFs'!$G63:$EI63) -> 99607.53 | ... S34: =SUMIF('Monthly CFs'!$G$5:$EI$5,'Annual CFs'!S$6,'Monthly CFs'!$G63:$EI63) -> 108843.84
C35: General & Administrative | G35: ='OI & Expense Growth'!F17 -> 50400 | I35: =SUMIF('Monthly CFs'!$G$5:$EI$5,'Annual CFs'!I$6,'Monthly CFs'!$G64:$EI64) -> 0 | J35: =SUMIF('Monthly CFs'!$G$5:$EI$5,'Annual CFs'!J$6,'Monthly CFs'!$G64:$EI64) -> 0 | K35: =SUMIF('Monthly CFs'!$G$5:$EI$5,'Annual CFs'!K$6,'Monthly CFs'!$G64:$EI64) -> 0 | L35: =SUMIF('Monthly CFs'!$G$5:$EI$5,'Annual CFs'!L$6,'Monthly CFs'!$G64:$EI64) -> 20300 | M35: =SUMIF('Monthly CFs'!$G$5:$EI$5,'Annual CFs'!M$6,'Monthly CFs'!$G64:$EI64) -> 51912 | N35: =SUMIF('Monthly CFs'!$G$5:$EI$5,'Annual CFs'!N$6,'Monthly CFs'!$G64:$EI64) -> 53469.36 | O35: =SUMIF('Monthly CFs'!$G$5:$EI$5,'Annual CFs'!O$6,'Monthly CFs'!$G64:$EI64) -> 55073.441 | P35: =SUMIF('Monthly CFs'!$G$5:$EI$5,'Annual CFs'!P$6,'Monthly CFs'!$G64:$EI64) -> 56725.644 | ... S35: =SUMIF('Monthly CFs'!$G$5:$EI$5,'Annual CFs'!S$6,'Monthly CFs'!$G64:$EI64) -> 61985.643
C36: Total Controllable Expenses | G36: =SUM(G31:G35) -> 380100 | I36: =SUM(I31:I35) -> 0 | J36: =SUM(J31:J35) -> 0 | K36: =SUM(K31:K35) -> 0 | L36: =SUM(L31:L35) -> 153095.83 | M36: =SUM(M31:M35) -> 391503 | N36: =SUM(N31:N35) -> 403248.09 | O36: =SUM(O31:O35) -> 415345.53 | P36: =SUM(P31:P35) -> 427805.9 | ... S36: =SUM(S31:S35) -> 467475.06
C38: Non-Controllable Expenses
C39: Real Estate Taxes | G39: ='OI & Expense Growth'!F20 -> 548294 | I39: =SUMIF('Monthly CFs'!$G$5:$EI$5,'Annual CFs'!I$6,'Monthly CFs'!$G68:$EI68) -> 313356.1 | J39: =SUMIF('Monthly CFs'!$G$5:$EI$5,'Annual CFs'!J$6,'Monthly CFs'!$G68:$EI68) -> 313356.1 | K39: =SUMIF('Monthly CFs'!$G$5:$EI$5,'Annual CFs'!K$6,'Monthly CFs'!$G68:$EI68) -> 313356.1 | L39: =SUMIF('Monthly CFs'!$G$5:$EI$5,'Annual CFs'!L$6,'Monthly CFs'!$G68:$EI68) -> 430825.05 | M39: =SUMIF('Monthly CFs'!$G$5:$EI$5,'Annual CFs'!M$6,'Monthly CFs'!$G68:$EI68) -> 564742.82 | N39: =SUMIF('Monthly CFs'!$G$5:$EI$5,'Annual CFs'!N$6,'Monthly CFs'!$G68:$EI68) -> 581685.1 | O39: =SUMIF('Monthly CFs'!$G$5:$EI$5,'Annual CFs'!O$6,'Monthly CFs'!$G68:$EI68) -> 599135.66 | P39: =SUMIF('Monthly CFs'!$G$5:$EI$5,'Annual CFs'!P$6,'Monthly CFs'!$G68:$EI68) -> 617109.73 | ... S39: =SUMIF('Monthly CFs'!$G$5:$EI$5,'Annual CFs'!S$6,'Monthly CFs'!$G68:$EI68) -> 674332.46
C40: Insurance | G40: ='OI & Expense Growth'!F21 -> 79200 | I40: =SUMIF('Monthly CFs'!$G$5:$EI$5,'Annual CFs'!I$6,'Monthly CFs'!$G69:$EI69) -> 39600 | J40: =SUMIF('Monthly CFs'!$G$5:$EI$5,'Annual CFs'!J$6,'Monthly CFs'!$G69:$EI69) -> 39600 | K40: =SUMIF('Monthly CFs'!$G$5:$EI$5,'Annual CFs'!K$6,'Monthly CFs'!$G69:$EI69) -> 39600 | L40: =SUMIF('Monthly CFs'!$G$5:$EI$5,'Annual CFs'!L$6,'Monthly CFs'!$G69:$EI69) -> 59400 | M40: =SUMIF('Monthly CFs'!$G$5:$EI$5,'Annual CFs'!M$6,'Monthly CFs'!$G69:$EI69) -> 81576 | N40: =SUMIF('Monthly CFs'!$G$5:$EI$5,'Annual CFs'!N$6,'Monthly CFs'!$G69:$EI69) -> 84023.28 | O40: =SUMIF('Monthly CFs'!$G$5:$EI$5,'Annual CFs'!O$6,'Monthly CFs'!$G69:$EI69) -> 86543.978 | P40: =SUMIF('Monthly CFs'!$G$5:$EI$5,'Annual CFs'!P$6,'Monthly CFs'!$G69:$EI69) -> 89140.298 | ... S40: =SUMIF('Monthly CFs'!$G$5:$EI$5,'Annual CFs'!S$6,'Monthly CFs'!$G69:$EI69) -> 97406.01
C41: Utilities | G41: ='OI & Expense Growth'!F22 -> 216000 | I41: =SUMIF('Monthly CFs'!$G$5:$EI$5,'Annual CFs'!I$6,'Monthly CFs'!$G70:$EI70) -> 0 | J41: =SUMIF('Monthly CFs'!$G$5:$EI$5,'Annual CFs'!J$6,'Monthly CFs'!$G70:$EI70) -> 0 | K41: =SUMIF('Monthly CFs'!$G$5:$EI$5,'Annual CFs'!K$6,'Monthly CFs'!$G70:$EI70) -> 0 | L41: =SUMIF('Monthly CFs'!$G$5:$EI$5,'Annual CFs'!L$6,'Monthly CFs'!$G70:$EI70) -> 87000 | M41: =SUMIF('Monthly CFs'!$G$5:$EI$5,'Annual CFs'!M$6,'Monthly CFs'!$G70:$EI70) -> 222480 | N41: =SUMIF('Monthly CFs'!$G$5:$EI$5,'Annual CFs'!N$6,'Monthly CFs'!$G70:$EI70) -> 229154.4 | O41: =SUMIF('Monthly CFs'!$G$5:$EI$5,'Annual CFs'!O$6,'Monthly CFs'!$G70:$EI70) -> 236029.03 | P41: =SUMIF('Monthly CFs'!$G$5:$EI$5,'Annual CFs'!P$6,'Monthly CFs'!$G70:$EI70) -> 243109.9 | ... S41: =SUMIF('Monthly CFs'!$G$5:$EI$5,'Annual CFs'!S$6,'Monthly CFs'!$G70:$EI70) -> 265652.75
C42: Management Fee | E42: ='Growth Rates'!O20 -> 0.03 | G42: =E42*G28 -> 146738.02 | I42: =SUMIF('Monthly CFs'!$G$5:$EI$5,'Annual CFs'!I$6,'Monthly CFs'!$G71:$EI71) -> 0 | J42: =SUMIF('Monthly CFs'!$G$5:$EI$5,'Annual CFs'!J$6,'Monthly CFs'!$G71:$EI71) -> 0 | K42: =SUMIF('Monthly CFs'!$G$5:$EI$5,'Annual CFs'!K$6,'Monthly CFs'!$G71:$EI71) -> 0 | L42: =SUMIF('Monthly CFs'!$G$5:$EI$5,'Annual CFs'!L$6,'Monthly CFs'!$G71:$EI71) -> 65810.199 | M42: =SUMIF('Monthly CFs'!$G$5:$EI$5,'Annual CFs'!M$6,'Monthly CFs'!$G71:$EI71) -> 163355.32 | N42: =SUMIF('Monthly CFs'!$G$5:$EI$5,'Annual CFs'!N$6,'Monthly CFs'!$G71:$EI71) -> 168255.98 | O42: =SUMIF('Monthly CFs'!$G$5:$EI$5,'Annual CFs'!O$6,'Monthly CFs'!$G71:$EI71) -> 173303.66 | P42: =SUMIF('Monthly CFs'!$G$5:$EI$5,'Annual CFs'!P$6,'Monthly CFs'!$G71:$EI71) -> 178502.77 | ... S42: =SUMIF('Monthly CFs'!$G$5:$EI$5,'Annual CFs'!S$6,'Monthly CFs'!$G71:$EI71) -> 195054.8
C43: Total Non-Controllable Expenses | G43: =SUM(G39:G42) -> 990232.03 | I43: =SUM(I39:I42) -> 352956.1 | J43: =SUM(J39:J42) -> 352956.1 | K43: =SUM(K39:K42) -> 352956.1 | L43: =SUM(L39:L42) -> 643035.25 | M43: =SUM(M39:M42) -> 1032154.1 | N43: =SUM(N39:N42) -> 1063118.8 | O43: =SUM(O39:O42) -> 1095012.3 | P43: =SUM(P39:P42) -> 1127862.7 | ... S43: =SUM(S39:S42) -> 1232446
C44: Total Operating Expenses | G44: =G43+G36 -> 1370332 | I44: =I43+I36 -> 352956.1 | J44: =J43+J36 -> 352956.1 | K44: =K43+K36 -> 352956.1 | L44: =L43+L36 -> 796131.08 | M44: =M43+M36 -> 1423657.1 | N44: =N43+N36 -> 1466366.9 | O44: =O43+O36 -> 1510357.9 | P44: =P43+P36 -> 1555668.6 | ... S44: =S43+S36 -> 1699921.1 | V44: =G44/G28 -> 0.28015888
C46: Net Operating Income | G46: =G28-G44 -> 3520935.5 | I46: =I28-I44 -> -352956.1 | J46: =J28-J44 -> -352956.1 | K46: =K28-K44 -> -352956.1 | L46: =L28-L44 -> 1397542.2 | M46: =M28-M44 -> 4021520.3 | N46: =N28-N44 -> 4142166 | O46: =O28-O44 -> 4266430.9 | P46: =P28-P44 -> 4394423.9 | ... S46: =S28-S44 -> 4801905.6
C48: Capital Reserves | E48: ='Growth Rates'!P10 -> 150 | G48: =$E48*'Summary & Assumptions'!$D$34 -> 21600 | I48: =SUMIF('Monthly CFs'!$G$5:$EI$5,'Annual CFs'!I$6,'Monthly CFs'!$G77:$EI77) -> 0 | J48: =SUMIF('Monthly CFs'!$G$5:$EI$5,'Annual CFs'!J$6,'Monthly CFs'!$G77:$EI77) -> 0 | K48: =SUMIF('Monthly CFs'!$G$5:$EI$5,'Annual CFs'!K$6,'Monthly CFs'!$G77:$EI77) -> 0 | L48: =SUMIF('Monthly CFs'!$G$5:$EI$5,'Annual CFs'!L$6,'Monthly CFs'!$G77:$EI77) -> 8700 | M48: =SUMIF('Monthly CFs'!$G$5:$EI$5,'Annual CFs'!M$6,'Monthly CFs'!$G77:$EI77) -> 21600 | N48: =SUMIF('Monthly CFs'!$G$5:$EI$5,'Annual CFs'!N$6,'Monthly CFs'!$G77:$EI77) -> 21600 | O48: =SUMIF('Monthly CFs'!$G$5:$EI$5,'Annual CFs'!O$6,'Monthly CFs'!$G77:$EI77) -> 21600 | P48: =SUMIF('Monthly CFs'!$G$5:$EI$5,'Annual CFs'!P$6,'Monthly CFs'!$G77:$EI77) -> 21600 | ... S48: =SUMIF('Monthly CFs'!$G$5:$EI$5,'Annual CFs'!S$6,'Monthly CFs'!$G77:$EI77) -> 21600
C49: Cash Flows From Operations | G49: =G46-G48 -> 3499335.5 | I49: =I46-I48 -> -352956.1 | J49: =J46-J48 -> -352956.1 | K49: =K46-K48 -> -352956.1 | L49: =L46-L48 -> 1388842.2 | M49: =M46-M48 -> 3999920.3 | N49: =N46-N48 -> 4120566 | O49: =O46-O48 -> 4244830.9 | P49: =P46-P48 -> 4372823.9 | ... S49: =S46-S48 -> 4780305.6 | V49: =SUM(I49:S49)-SUM('Monthly CFs'!G78:EI78) -> 0
C51: Stabilized ROC / NOI (Untrended) | E51: ='Summary & Assumptions'!K41 -> 0.059773244 | G51: =G46 -> 3520935.5
C52: Required ROC / NOI (Untrended) | E52: 0.06 | G52: =E52*'Summary & Assumptions'!M19 -> 3534292.5
C53: (Discount)/Premium to Stab. Untrended NOI | G53: =G52-G46 -> 13357.03

Sheet Monthly CFs
C4: Monthly CFs | F4: Year | G4: =YEAR(G7) -> 2022 | H4: =YEAR(H7) -> 2022 | I4: =YEAR(I7) -> 2022 | J4: =YEAR(J7) -> 2022 | K4: =YEAR(K7) -> 2022 | L4: =YEAR(L7) -> 2022 | M4: =YEAR(M7) -> 2022 | N4: =YEAR(N7) -> 2023 | ... EI4: =YEAR(EI7) -> 2033
F5: Year | G5: =ROUNDUP(G6/12,0) -> 0 | H5: =ROUNDUP(H6/12,0) -> 1 | I5: =ROUNDUP(I6/12,0) -> 1 | J5: =ROUNDUP(J6/12,0) -> 1 | K5: =ROUNDUP(K6/12,0) -> 1 | L5: =ROUNDUP(L6/12,0) -> 1 | M5: =ROUNDUP(M6/12,0) -> 1 | N5: =ROUNDUP(N6/12,0) -> 1 | ... EI5: =ROUNDUP(EI6/12,0) -> 11
F6: Month | G6: 0 | H6: =+G6+1 -> 1 | I6: =+H6+1 -> 2 | J6: =+I6+1 -> 3 | K6: =+J6+1 -> 4 | L6: =+K6+1 -> 5 | M6: =+L6+1 -> 6 | N6: =+M6+1 -> 7 | O6: =+N6+1 -> 8 | ... EI6: =+EH6+1 -> 132
F7: Date | G7: ='Summary & Assumptions'!H38 -> 44713 | H7: =+EOMONTH(G7,1) -> 44773 | I7: =+EOMONTH(H7,1) -> 44804 | J7: =+EOMONTH(I7,1) -> 44834 | K7: =+EOMONTH(J7,1) -> 44865 | L7: =+EOMONTH(K7,1) -> 44895 | M7: =+EOMONTH(L7,1) -> 44926 | N7: =+EOMONTH(M7,1) -> 44957 | O7: =+EOMONTH(N7,1) -> 44985 | ... EI7: =+EOMONTH(EH7,1) -> 48760
C9: Assumptions
C11: Unit Assumptions
C12: Rent/SF | H12: {=INDEX('Growth Rates'!$F$10:$F$20,MATCH(H5,'Growth Rates'!$C$10:$C$20,0))} -> 3.7181122 | I12: {=INDEX('Growth Rates'!$F$10:$F$20,MATCH(I5,'Growth Rates'!$C$10:$C$20,0))} -> 3.7181122 | J12: {=INDEX('Growth Rates'!$F$10:$F$20,MATCH(J5,'Growth Rates'!$C$10:$C$20,0))} -> 3.7181122 | K12: {=INDEX('Growth Rates'!$F$10:$F$20,MATCH(K5,'Growth Rates'!$C$10:$C$20,0))} -> 3.7181122 | L12: {=INDEX('Growth Rates'!$F$10:$F$20,MATCH(L5,'Growth Rates'!$C$10:$C$20,0))} -> 3.7181122 | M12: {=INDEX('Growth Rates'!$F$10:$F$20,MATCH(M5,'Growth Rates'!$C$10:$C$20,0))} -> 3.7181122 | N12: {=INDEX('Growth Rates'!$F$10:$F$20,MATCH(N5,'Growth Rates'!$C$10:$C$20,0))} -> 3.7181122 | O12: {=INDEX('Growth Rates'!$F$10:$F$20,MATCH(O5,'Growth Rates'!$C$10:$C$20,0))} -> 3.7181122 | ... EI12: {=INDEX('Growth Rates'!$F$10:$F$20,MATCH(EI5,'Growth Rates'!$C$10:$C$20,0))} -> 4.9968319
C13: Effective Annual Rent | H13: =H17*H12*'Summary & Assumptions'!$E$34 -> 0 | I13: =I17*I12*'Summary & Assumptions'!$E$34 -> 0 | J13: =J17*J12*'Summary & Assumptions'!$E$34 -> 0 | K13: =K17*K12*'Summary & Assumptions'!$E$34 -> 0 | L13: =L17*L12*'Summary & Assumptions'!$E$34 -> 0 | M13: =M17*M12*'Summary & Assumptions'!$E$34 -> 0 | N13: =N17*N12*'Summary & Assumptions'!$E$34 -> 0 | O13: =O17*O12*'Summary & Assumptions'!$E$34 -> 0 | ... EI13: =EI17*EI12*'Summary & Assumptions'!$E$34 -> 509277.11
C15: Units Delivered In Month | G15: =IF(F16='Summary & Assumptions'!$D$34,0,IF(F16+'Summary & Assumptions'!$H$47>'Summary & Assumptions'!$D$34,'Summary & Assumptions'!$D$34-F16,IF(G7=EOMONTH('Summary & Assumptions'!$H$44,0),'Summary & Assumptions'!$H$46,IF(AND(G7>EOMONTH('Summary & Assumptions'!$H$44,0),G7<='Summary & Assumptions'!$H$48),'Summary & Assumptions'!$H$47,0)))) -> 0 | H15: =IF(G16='Summary & Assumptions'!$D$34,0,IF(G16+'Summary & Assumptions'!$H$47>'Summary & Assumptions'!$D$34,'Summary & Assumptions'!$D$34-G16,IF(H7=EOMONTH('Summary & Assumptions'!$H$44,0),'Summary & Assumptions'!$H$46,IF(AND(H7>EOMONTH('Summary & Assumptions'!$H$44,0),H7<='Summary & Assumptions'!$H$48),'Summary & Assumptions'!$H$47,0)))) -> 0 | I15: =IF(H16='Summary & Assumptions'!$D$34,0,IF(H16+'Summary & Assumptions'!$H$47>'Summary & Assumptions'!$D$34,'Summary & Assumptions'!$D$34-H16,IF(I7=EOMONTH('Summary & Assumptions'!$H$44,0),'Summary & Assumptions'!$H$46,IF(AND(I7>EOMONTH('Summary & Assumptions'!$H$44,0),I7<='Summary & Assumptions'!$H$48),'Summary & Assumptions'!$H$47,0)))) -> 0 | J15: =IF(I16='Summary & Assumptions'!$D$34,0,IF(I16+'Summary & Assumptions'!$H$47>'Summary & Assumptions'!$D$34,'Summary & Assumptions'!$D$34-I16,IF(J7=EOMONTH('Summary & Assumptions'!$H$44,0),'Summary & Assumptions'!$H$46,IF(AND(J7>EOMONTH('Summary & Assumptions'!$H$44,0),J7<='Summary & Assumptions'!$H$48),'Summary & Assumptions'!$H$47,0)))) -> 0 | K15: =IF(J16='Summary & Assumptions'!$D$34,0,IF(J16+'Summary & Assumptions'!$H$47>'Summary & Assumptions'!$D$34,'Summary & Assumptions'!$D$34-J16,IF(K7=EOMONTH('Summary & Assumptions'!$H$44,0),'Summary & Assumptions'!$H$46,IF(AND(K7>EOMONTH('Summary & Assumptions'!$H$44,0),K7<='Summary & Assumptions'!$H$48),'Summary & Assumptions'!$H$47,0)))) -> 0 | L15: =IF(K16='Summary & Assumptions'!$D$34,0,IF(K16+'Summary & Assumptions'!$H$47>'Summary & Assumptions'!$D$34,'Summary & Assumptions'!$D$34-K16,IF(L7=EOMONTH('Summary & Assumptions'!$H$44,0),'Summary & Assumptions'!$H$46,IF(AND(L7>EOMONTH('Summary & Assumptions'!$H$44,0),L7<='Summary & Assumptions'!$H$48),'Summary & Assumptions'!$H$47,0)))) -> 0 | M15: =IF(L16='Summary & Assumptions'!$D$34,0,IF(L16+'Summary & Assumptions'!$H$47>'Summary & Assumptions'!$D$34,'Summary & Assumptions'!$D$34-L16,IF(M7=EOMONTH('Summary & Assumptions'!$H$44,0),'Summary & Assumptions'!$H$46,IF(AND(M7>EOMONTH('Summary & Assumptions'!$H$44,0),M7<='Summary & Assumptions'!$H$48),'Summary & Assumptions'!$H$47,0)))) -> 0 | N15: =IF(M16='Summary & Assumptions'!$D$34,0,IF(M16+'Summary & Assumptions'!$H$47>'Summary & Assumptions'!$D$34,'Summary & Assumptions'!$D$34-M16,IF(N7=EOMONTH('Summary & Assumptions'!$H$44,0),'Summary & Assumptions'!$H$46,IF(AND(N7>EOMONTH('Summary & Assumptions'!$H$44,0),N7<='Summary & Assumptions'!$H$48),'Summary & Assumptions'!$H$47,0)))) -> 0 | ... EI15: =IF(EH16='Summary & Assumptions'!$D$34,0,IF(EH16+'Summary & Assumptions'!$H$47>'Summary & Assumptions'!$D$34,'Summary & Assumptions'!$D$34-EH16,IF(EI7=EOMONTH('Summary & Assumptions'!$H$44,0),'Summary & Assumptions'!$H$46,IF(AND(EI7>EOMONTH('Summary & Assumptions'!$H$44,0),EI7<='Summary & Assumptions'!$H$48),'Summary & Assumptions'!$H$47,0)))) -> 0
C16: Cumulative Units Delivered | G16: =SUM($F$15:G15) -> 0 | H16: =SUM($F$15:H15) -> 0 | I16: =SUM($F$15:I15) -> 0 | J16: =SUM($F$15:J15) -> 0 | K16: =SUM($F$15:K15) -> 0 | L16: =SUM($F$15:L15) -> 0 | M16: =SUM($F$15:M15) -> 0 | N16: =SUM($F$15:N15) -> 0 | ... EI16: =SUM($F$15:EI15) -> 144
C17: % Occupied | G17: =G16/'Summary & Assumptions'!$D$34 -> 0 | H17: =H16/'Summary & Assumptions'!$D$34 -> 0 | I17: =I16/'Summary & Assumptions'!$D$34 -> 0 | J17: =J16/'Summary & Assumptions'!$D$34 -> 0 | K17: =K16/'Summary & Assumptions'!$D$34 -> 0 | L17: =L16/'Summary & Assumptions'!$D$34 -> 0 | M17: =M16/'Summary & Assumptions'!$D$34 -> 0 | N17: =N16/'Summary & Assumptions'!$D$34 -> 0 | ... EI17: =EI16/'Summary & Assumptions'!$D$34 -> 1
C19: Market Vacancy | G19: {=IFERROR(INDEX('Growth Rates'!$G$10:$G$20,MATCH(G$5,'Growth Rates'!$C$10:$C$20,0)),0)} -> 0 | H19: {=IFERROR(INDEX('Growth Rates'!$G$10:$G$20,MATCH(H$5,'Growth Rates'!$C$10:$C$20,0)),0)} -> 0.05 | I19: {=IFERROR(INDEX('Growth Rates'!$G$10:$G$20,MATCH(I$5,'Growth Rates'!$C$10:$C$20,0)),0)} -> 0.05 | J19: {=IFERROR(INDEX('Growth Rates'!$G$10:$G$20,MATCH(J$5,'Growth Rates'!$C$10:$C$20,0)),0)} -> 0.05 | K19: {=IFERROR(INDEX('Growth Rates'!$G$10:$G$20,MATCH(K$5,'Growth Rates'!$C$10:$C$20,0)),0)} -> 0.05 | L19: {=IFERROR(INDEX('Growth Rates'!$G$10:$G$20,MATCH(L$5,'Growth Rates'!$C$10:$C$20,0)),0)} -> 0.05 | M19: {=IFERROR(INDEX('Growth Rates'!$G$10:$G$20,MATCH(M$5,'Growth Rates'!$C$10:$C$20,0)),0)} -> 0.05 | N19: {=IFERROR(INDEX('Growth Rates'!$G$10:$G$20,MATCH(N$5,'Growth Rates'!$C$10:$C$20,0)),0)} -> 0.05 | ... EI19: {=IFERROR(INDEX('Growth Rates'!$G$10:$G$20,MATCH(EI$5,'Growth Rates'!$C$10:$C$20,0)),0)} -> 0.05
C20: Retail Vacancy | G20: {=IFERROR(INDEX('Growth Rates'!$H$10:$H$20,MATCH(G$5,'Growth Rates'!$C$10:$C$20,0)),0)} -> 0 | H20: {=IFERROR(INDEX('Growth Rates'!$H$10:$H$20,MATCH(H$5,'Growth Rates'!$C$10:$C$20,0)),0)} -> 0.1 | I20: {=IFERROR(INDEX('Growth Rates'!$H$10:$H$20,MATCH(I$5,'Growth Rates'!$C$10:$C$20,0)),0)} -> 0.1 | J20: {=IFERROR(INDEX('Growth Rates'!$H$10:$H$20,MATCH(J$5,'Growth Rates'!$C$10:$C$20,0)),0)} -> 0.1 | K20: {=IFERROR(INDEX('Growth Rates'!$H$10:$H$20,MATCH(K$5,'Growth Rates'!$C$10:$C$20,0)),0)} -> 0.1 | L20: {=IFERROR(INDEX('Growth Rates'!$H$10:$H$20,MATCH(L$5,'Growth Rates'!$C$10:$C$20,0)),0)} -> 0.1 | M20: {=IFERROR(INDEX('Growth Rates'!$H$10:$H$20,MATCH(M$5,'Growth Rates'!$C$10:$C$20,0)),0)} -> 0.1 | N20: {=IFERROR(INDEX('Growth Rates'!$H$10:$H$20,MATCH(N$5,'Growth Rates'!$C$10:$C$20,0)),0)} -> 0.1 | ... EI20: {=IFERROR(INDEX('Growth Rates'!$H$10:$H$20,MATCH(EI$5,'Growth Rates'!$C$10:$C$20,0)),0)} -> 0.1
C22: Losses to GPR
C23: Non-Rev Beds | G23: {=IFERROR(INDEX('Growth Rates'!$I$10:$I$20,MATCH(G$5,'Growth Rates'!$C$10:$C$20,0)),0)} -> 0 | H23: {=IFERROR(INDEX('Growth Rates'!$I$10:$I$20,MATCH(H$5,'Growth Rates'!$C$10:$C$20,0)),0)} -> 0.0025 | I23: {=IFERROR(INDEX('Growth Rates'!$I$10:$I$20,MATCH(I$5,'Growth Rates'!$C$10:$C$20,0)),0)} -> 0.0025 | J23: {=IFERROR(INDEX('Growth Rates'!$I$10:$I$20,MATCH(J$5,'Growth Rates'!$C$10:$C$20,0)),0)} -> 0.0025 | K23: {=IFERROR(INDEX('Growth Rates'!$I$10:$I$20,MATCH(K$5,'Growth Rates'!$C$10:$C$20,0)),0)} -> 0.0025 | L23: {=IFERROR(INDEX('Growth Rates'!$I$10:$I$20,MATCH(L$5,'Growth Rates'!$C$10:$C$20,0)),0)} -> 0.0025 | M23: {=IFERROR(INDEX('Growth Rates'!$I$10:$I$20,MATCH(M$5,'Growth Rates'!$C$10:$C$20,0)),0)} -> 0.0025 | N23: {=IFERROR(INDEX('Growth Rates'!$I$10:$I$20,MATCH(N$5,'Growth Rates'!$C$10:$C$20,0)),0)} -> 0.0025 | ... EI23: {=IFERROR(INDEX('Growth Rates'!$I$10:$I$20,MATCH(EI$5,'Growth Rates'!$C$10:$C$20,0)),0)} -> 0.0025
C24: Bad Debt | G24: {=IFERROR(INDEX('Growth Rates'!$J$10:$J$20,MATCH(G$5,'Growth Rates'!$C$10:$C$20,0)),0)} -> 0 | H24: {=IFERROR(INDEX('Growth Rates'!$J$10:$J$20,MATCH(H$5,'Growth Rates'!$C$10:$C$20,0)),0)} -> 0.0075 | I24: {=IFERROR(INDEX('Growth Rates'!$J$10:$J$20,MATCH(I$5,'Growth Rates'!$C$10:$C$20,0)),0)} -> 0.0075 | J24: {=IFERROR(INDEX('Growth Rates'!$J$10:$J$20,MATCH(J$5,'Growth Rates'!$C$10:$C$20,0)),0)} -> 0.0075 | K24: {=IFERROR(INDEX('Growth Rates'!$J$10:$J$20,MATCH(K$5,'Growth Rates'!$C$10:$C$20,0)),0)} -> 0.0075 | L24: {=IFERROR(INDEX('Growth Rates'!$J$10:$J$20,MATCH(L$5,'Growth Rates'!$C$10:$C$20,0)),0)} -> 0.0075 | M24: {=IFERROR(INDEX('Growth Rates'!$J$10:$J$20,MATCH(M$5,'Growth Rates'!$C$10:$C$20,0)),0)} -> 0.0075 | N24: {=IFERROR(INDEX('Growth Rates'!$J$10:$J$20,MATCH(N$5,'Growth Rates'!$C$10:$C$20,0)),0)} -> 0.0075 | ... EI24: {=IFERROR(INDEX('Growth Rates'!$J$10:$J$20,MATCH(EI$5,'Growth Rates'!$C$10:$C$20,0)),0)} -> 0.0075
C25: Concessions | G25: {=IFERROR(INDEX('Growth Rates'!$K$10:$K$20,MATCH(G$5,'Growth Rates'!$C$10:$C$20,0)),0)} -> 0 | H25: {=IFERROR(INDEX('Growth Rates'!$K$10:$K$20,MATCH(H$5,'Growth Rates'!$C$10:$C$20,0)),0)} -> 0.01 | I25: {=IFERROR(INDEX('Growth Rates'!$K$10:$K$20,MATCH(I$5,'Growth Rates'!$C$10:$C$20,0)),0)} -> 0.01 | J25: {=IFERROR(INDEX('Growth Rates'!$K$10:$K$20,MATCH(J$5,'Growth Rates'!$C$10:$C$20,0)),0)} -> 0.01 | K25: {=IFERROR(INDEX('Growth Rates'!$K$10:$K$20,MATCH(K$5,'Growth Rates'!$C$10:$C$20,0)),0)} -> 0.01 | L25: {=IFERROR(INDEX('Growth Rates'!$K$10:$K$20,MATCH(L$5,'Growth Rates'!$C$10:$C$20,0)),0)} -> 0.01 | M25: {=IFERROR(INDEX('Growth Rates'!$K$10:$K$20,MATCH(M$5,'Growth Rates'!$C$10:$C$20,0)),0)} -> 0.01 | N25: {=IFERROR(INDEX('Growth Rates'!$K$10:$K$20,MATCH(N$5,'Growth Rates'!$C$10:$C$20,0)),0)} -> 0.01 | ... EI25: {=IFERROR(INDEX('Growth Rates'!$K$10:$K$20,MATCH(EI$5,'Growth Rates'!$C$10:$C$20,0)),0)} -> 0.0025
C27: Other Income
C28: Other Income Growth | G28: {=IFERROR(INDEX('Growth Rates'!$L$10:$L$20,MATCH(G$5,'Growth Rates'!$C$10:$C$20,0)),0)} -> 0 | H28: {=IFERROR(INDEX('Growth Rates'!$L$10:$L$20,MATCH(H$5,'Growth Rates'!$C$10:$C$20,0)),0)} -> 0 | I28: {=IFERROR(INDEX('Growth Rates'!$L$10:$L$20,MATCH(I$5,'Growth Rates'!$C$10:$C$20,0)),0)} -> 0 | J28: {=IFERROR(INDEX('Growth Rates'!$L$10:$L$20,MATCH(J$5,'Growth Rates'!$C$10:$C$20,0)),0)} -> 0 | K28: {=IFERROR(INDEX('Growth Rates'!$L$10:$L$20,MATCH(K$5,'Growth Rates'!$C$10:$C$20,0)),0)} -> 0 | L28: {=IFERROR(INDEX('Growth Rates'!$L$10:$L$20,MATCH(L$5,'Growth Rates'!$C$10:$C$20,0)),0)} -> 0 | M28: {=IFERROR(INDEX('Growth Rates'!$L$10:$L$20,MATCH(M$5,'Growth Rates'!$C$10:$C$20,0)),0)} -> 0 | N28: {=IFERROR(INDEX('Growth Rates'!$L$10:$L$20,MATCH(N$5,'Growth Rates'!$C$10:$C$20,0)),0)} -> 0 | ... EI28: {=IFERROR(INDEX('Growth Rates'!$L$10:$L$20,MATCH(EI$5,'Growth Rates'!$C$10:$C$20,0)),0)} -> 0.03
C30: Expenses
C31: Controllable Expense Growth | G31: {=IFERROR(INDEX('Growth Rates'!$M$10:$M$20,MATCH(G$5,'Growth Rates'!$C$10:$C$20,0)),0)} -> 0 | H31: {=IFERROR(INDEX('Growth Rates'!$M$10:$M$20,MATCH(H$5,'Growth Rates'!$C$10:$C$20,0)),0)} -> 0 | I31: {=IFERROR(INDEX('Growth Rates'!$M$10:$M$20,MATCH(I$5,'Growth Rates'!$C$10:$C$20,0)),0)} -> 0 | J31: {=IFERROR(INDEX('Growth Rates'!$M$10:$M$20,MATCH(J$5,'Growth Rates'!$C$10:$C$20,0)),0)} -> 0 | K31: {=IFERROR(INDEX('Growth Rates'!$M$10:$M$20,MATCH(K$5,'Growth Rates'!$C$10:$C$20,0)),0)} -> 0 | L31: {=IFERROR(INDEX('Growth Rates'!$M$10:$M$20,MATCH(L$5,'Growth Rates'!$C$10:$C$20,0)),0)} -> 0 | M31: {=IFERROR(INDEX('Growth Rates'!$M$10:$M$20,MATCH(M$5,'Growth Rates'!$C$10:$C$20,0)),0)} -> 0 | N31: {=IFERROR(INDEX('Growth Rates'!$M$10:$M$20,MATCH(N$5,'Growth Rates'!$C$10:$C$20,0)),0)} -> 0 | ... EI31: {=IFERROR(INDEX('Growth Rates'!$M$10:$M$20,MATCH(EI$5,'Growth Rates'!$C$10:$C$20,0)),0)} -> 0.03
C32: Non-Controllable Expense Growth | G32: {=IFERROR(INDEX('Growth Rates'!$N$10:$N$20,MATCH(G$5,'Growth Rates'!$C$10:$C$20,0)),0)} -> 0 | H32: {=IFERROR(INDEX('Growth Rates'!$N$10:$N$20,MATCH(H$5,'Growth Rates'!$C$10:$C$20,0)),0)} -> 0 | I32: {=IFERROR(INDEX('Growth Rates'!$N$10:$N$20,MATCH(I$5,'Growth Rates'!$C$10:$C$20,0)),0)} -> 0 | J32: {=IFERROR(INDEX('Growth Rates'!$N$10:$N$20,MATCH(J$5,'Growth Rates'!$C$10:$C$20,0)),0)} -> 0 | K32: {=IFERROR(INDEX('Growth Rates'!$N$10:$N$20,MATCH(K$5,'Growth Rates'!$C$10:$C$20,0)),0)} -> 0 | L32: {=IFERROR(INDEX('Growth Rates'!$N$10:$N$20,MATCH(L$5,'Growth Rates'!$C$10:$C$20,0)),0)} -> 0 | M32: {=IFERROR(INDEX('Growth Rates'!$N$10:$N$20,MATCH(M$5,'Growth Rates'!$C$10:$C$20,0)),0)} -> 0 | N32: {=IFERROR(INDEX('Growth Rates'!$N$10:$N$20,MATCH(N$5,'Growth Rates'!$C$10:$C$20,0)),0)} -> 0 | ... EI32: {=IFERROR(INDEX('Growth Rates'!$N$10:$N$20,MATCH(EI$5,'Growth Rates'!$C$10:$C$20,0)),0)} -> 0.03
C33: Management Fee Growth | G33: {=IFERROR(INDEX('Growth Rates'!$O$10:$O$20,MATCH(G$5,'Growth Rates'!$C$10:$C$20,0)),0)} -> 0 | H33: {=IFERROR(INDEX('Growth Rates'!$O$10:$O$20,MATCH(H$5,'Growth Rates'!$C$10:$C$20,0)),0)} -> 0.03 | I33: {=IFERROR(INDEX('Growth Rates'!$O$10:$O$20,MATCH(I$5,'Growth Rates'!$C$10:$C$20,0)),0)} -> 0.03 | J33: {=IFERROR(INDEX('Growth Rates'!$O$10:$O$20,MATCH(J$5,'Growth Rates'!$C$10:$C$20,0)),0)} -> 0.03 | K33: {=IFERROR(INDEX('Growth Rates'!$O$10:$O$20,MATCH(K$5,'Growth Rates'!$C$10:$C$20,0)),0)} -> 0.03 | L33: {=IFERROR(INDEX('Growth Rates'!$O$10:$O$20,MATCH(L$5,'Growth Rates'!$C$10:$C$20,0)),0)} -> 0.03 | M33: {=IFERROR(INDEX('Growth Rates'!$O$10:$O$20,MATCH(M$5,'Growth Rates'!$C$10:$C$20,0)),0)} -> 0.03 | N33: {=IFERROR(INDEX('Growth Rates'!$O$10:$O$20,MATCH(N$5,'Growth Rates'!$C$10:$C$20,0)),0)} -> 0.03 | ... EI33: {=IFERROR(INDEX('Growth Rates'!$O$10:$O$20,MATCH(EI$5,'Growth Rates'!$C$10:$C$20,0)),0)} -> 0.03
C35: Income & Expenses
C37: Income
C38: Rental Income | G38: =G13 -> 0 | H38: =H13 -> 0 | I38: =I13 -> 0 | J38: =J13 -> 0 | K38: =K13 -> 0 | L38: =L13 -> 0 | M38: =M13 -> 0 | N38: =N13 -> 0 | ... EI38: =EI13 -> 509277.11
C39: Gross Potential Rent | G39: =SUM(G38) -> 0 | H39: =SUM(H38) -> 0 | I39: =SUM(I38) -> 0 | J39: =SUM(J38) -> 0 | K39: =SUM(K38) -> 0 | L39: =SUM(L38) -> 0 | M39: =SUM(M38) -> 0 | N39: =SUM(N38) -> 0 | ... EI39: =SUM(EI38) -> 509277.11
C41: Losses to GPR
C42: Market Vacancy | G42: =IF(G17>(1-G19),-G39*G19,0) -> 0 | H42: =IF(H17>(1-H19),-H39*H19,0) -> 0 | I42: =IF(I17>(1-I19),-I39*I19,0) -> 0 | J42: =IF(J17>(1-J19),-J39*J19,0) -> 0 | K42: =IF(K17>(1-K19),-K39*K19,0) -> 0 | L42: =IF(L17>(1-L19),-L39*L19,0) -> 0 | M42: =IF(M17>(1-M19),-M39*M19,0) -> 0 | N42: =IF(N17>(1-N19),-N39*N19,0) -> 0 | ... EI42: =IF(EI17>(1-EI19),-EI39*EI19,0) -> -25463.856
C43: Non-Rev Beds | G43: =G$39*-G23 -> 0 | H43: =H$39*-H23 -> 0 | I43: =I$39*-I23 -> 0 | J43: =J$39*-J23 -> 0 | K43: =K$39*-K23 -> 0 | L43: =L$39*-L23 -> 0 | M43: =M$39*-M23 -> 0 | N43: =N$39*-N23 -> 0 | ... EI43: =EI$39*-EI23 -> -1273.1928
C44: Bad Debt | G44: =G$39*-G24 -> 0 | H44: =H$39*-H24 -> 0 | I44: =I$39*-I24 -> 0 | J44: =J$39*-J24 -> 0 | K44: =K$39*-K24 -> 0 | L44: =L$39*-L24 -> 0 | M44: =M$39*-M24 -> 0 | N44: =N$39*-N24 -> 0 | ... EI44: =EI$39*-EI24 -> -3819.5783
C45: Concessions | G45: =G$39*-G25 -> 0 | H45: =H$39*-H25 -> 0 | I45: =I$39*-I25 -> 0 | J45: =J$39*-J25 -> 0 | K45: =K$39*-K25 -> 0 | L45: =L$39*-L25 -> 0 | M45: =M$39*-M25 -> 0 | N45: =N$39*-N25 -> 0 | ... EI45: =EI$39*-EI25 -> -1273.1928
C46: Total Losses to GPR | G46: =SUM(G42:G45) -> 0 | H46: =SUM(H42:H45) -> 0 | I46: =SUM(I42:I45) -> 0 | J46: =SUM(J42:J45) -> 0 | K46: =SUM(K42:K45) -> 0 | L46: =SUM(L42:L45) -> 0 | M46: =SUM(M42:M45) -> 0 | N46: =SUM(N42:N45) -> 0 | ... EI46: =SUM(EI42:EI45) -> -31829.819
C48: Effective Rental Income | G48: =+G39+G46 -> 0 | H48: =+H39+H46 -> 0 | I48: =+I39+I46 -> 0 | J48: =+J39+J46 -> 0 | K48: =+K39+K46 -> 0 | L48: =+L39+L46 -> 0 | M48: =+M39+M46 -> 0 | N48: =+N39+N46 -> 0 | ... EI48: =+EI39+EI46 -> 477447.29
C50: Other Income
C51: Parking Permit Fees | G51: {=IFERROR(INDEX('OI & Expense Growth'!$F7:$P7,MATCH('Monthly CFs'!G$5,'OI & Expense Growth'!$F$4:$P$4,0))*G$17/12,0)} -> 0 | H51: {=IFERROR(INDEX('OI & Expense Growth'!$F7:$P7,MATCH('Monthly CFs'!H$5,'OI & Expense Growth'!$F$4:$P$4,0))*H$17/12,0)} -> 0 | I51: {=IFERROR(INDEX('OI & Expense Growth'!$F7:$P7,MATCH('Monthly CFs'!I$5,'OI & Expense Growth'!$F$4:$P$4,0))*I$17/12,0)} -> 0 | J51: {=IFERROR(INDEX('OI & Expense Growth'!$F7:$P7,MATCH('Monthly CFs'!J$5,'OI & Expense Growth'!$F$4:$P$4,0))*J$17/12,0)} -> 0 | K51: {=IFERROR(INDEX('OI & Expense Growth'!$F7:$P7,MATCH('Monthly CFs'!K$5,'OI & Expense Growth'!$F$4:$P$4,0))*K$17/12,0)} -> 0 | L51: {=IFERROR(INDEX('OI & Expense Growth'!$F7:$P7,MATCH('Monthly CFs'!L$5,'OI & Expense Growth'!$F$4:$P$4,0))*L$17/12,0)} -> 0 | M51: {=IFERROR(INDEX('OI & Expense Growth'!$F7:$P7,MATCH('Monthly CFs'!M$5,'OI & Expense Growth'!$F$4:$P$4,0))*M$17/12,0)} -> 0 | N51: {=IFERROR(INDEX('OI & Expense Growth'!$F7:$P7,MATCH('Monthly CFs'!N$5,'OI & Expense Growth'!$F$4:$P$4,0))*N$17/12,0)} -> 0 | ... EI51: {=IFERROR(INDEX('OI & Expense Growth'!$F7:$P7,MATCH('Monthly CFs'!EI$5,'OI & Expense Growth'!$F$4:$P$4,0))*EI$17/12,0)} -> 44890.396
C52: Utility Charge | G52: {=IFERROR(INDEX('OI & Expense Growth'!$F8:$P8,MATCH('Monthly CFs'!G$5,'OI & Expense Growth'!$F$4:$P$4,0))*G$17/12,0)} -> 0 | H52: {=IFERROR(INDEX('OI & Expense Growth'!$F8:$P8,MATCH('Monthly CFs'!H$5,'OI & Expense Growth'!$F$4:$P$4,0))*H$17/12,0)} -> 0 | I52: {=IFERROR(INDEX('OI & Expense Growth'!$F8:$P8,MATCH('Monthly CFs'!I$5,'OI & Expense Growth'!$F$4:$P$4,0))*I$17/12,0)} -> 0 | J52: {=IFERROR(INDEX('OI & Expense Growth'!$F8:$P8,MATCH('Monthly CFs'!J$5,'OI & Expense Growth'!$F$4:$P$4,0))*J$17/12,0)} -> 0 | K52: {=IFERROR(INDEX('OI & Expense Growth'!$F8:$P8,MATCH('Monthly CFs'!K$5,'OI & Expense Growth'!$F$4:$P$4,0))*K$17/12,0)} -> 0 | L52: {=IFERROR(INDEX('OI & Expense Growth'!$F8:$P8,MATCH('Monthly CFs'!L$5,'OI & Expense Growth'!$F$4:$P$4,0))*L$17/12,0)} -> 0 | M52: {=IFERROR(INDEX('OI & Expense Growth'!$F8:$P8,MATCH('Monthly CFs'!M$5,'OI & Expense Growth'!$F$4:$P$4,0))*M$17/12,0)} -> 0 | N52: {=IFERROR(INDEX('OI & Expense Growth'!$F8:$P8,MATCH('Monthly CFs'!N$5,'OI & Expense Growth'!$F$4:$P$4,0))*N$17/12,0)} -> 0 | ... EI52: {=IFERROR(INDEX('OI & Expense Growth'!$F8:$P8,MATCH('Monthly CFs'!EI$5,'OI & Expense Growth'!$F$4:$P$4,0))*EI$17/12,0)} -> 13282.638
C53: Utility Billing Income | G53: {=IFERROR(INDEX('OI & Expense Growth'!$F9:$P9,MATCH('Monthly CFs'!G$5,'OI & Expense Growth'!$F$4:$P$4,0))*G$17/12,0)} -> 0 | H53: {=IFERROR(INDEX('OI & Expense Growth'!$F9:$P9,MATCH('Monthly CFs'!H$5,'OI & Expense Growth'!$F$4:$P$4,0))*H$17/12,0)} -> 0 | I53: {=IFERROR(INDEX('OI & Expense Growth'!$F9:$P9,MATCH('Monthly CFs'!I$5,'OI & Expense Growth'!$F$4:$P$4,0))*I$17/12,0)} -> 0 | J53: {=IFERROR(INDEX('OI & Expense Growth'!$F9:$P9,MATCH('Monthly CFs'!J$5,'OI & Expense Growth'!$F$4:$P$4,0))*J$17/12,0)} -> 0 | K53: {=IFERROR(INDEX('OI & Expense Growth'!$F9:$P9,MATCH('Monthly CFs'!K$5,'OI & Expense Growth'!$F$4:$P$4,0))*K$17/12,0)} -> 0 | L53: {=IFERROR(INDEX('OI & Expense Growth'!$F9:$P9,MATCH('Monthly CFs'!L$5,'OI & Expense Growth'!$F$4:$P$4,0))*L$17/12,0)} -> 0 | M53: {=IFERROR(INDEX('OI & Expense Growth'!$F9:$P9,MATCH('Monthly CFs'!M$5,'OI & Expense Growth'!$F$4:$P$4,0))*M$17/12,0)} -> 0 | N53: {=IFERROR(INDEX('OI & Expense Growth'!$F9:$P9,MATCH('Monthly CFs'!N$5,'OI & Expense Growth'!$F$4:$P$4,0))*N$17/12,0)} -> 0 | ... EI53: {=IFERROR(INDEX('OI & Expense Growth'!$F9:$P9,MATCH('Monthly CFs'!EI$5,'OI & Expense Growth'!$F$4:$P$4,0))*EI$17/12,0)} -> 6198.5643
C54: Retail Income (NNN) | G54: {=IF(G$17>0,IFERROR(INDEX('OI & Expense Growth'!$F10:$P10,MATCH('Monthly CFs'!G$5,'OI & Expense Growth'!$F$4:$P$4,0))*(1-G$20)/12,0),0)} -> 0 | H54: {=IF(H$17>0,IFERROR(INDEX('OI & Expense Growth'!$F10:$P10,MATCH('Monthly CFs'!H$5,'OI & Expense Growth'!$F$4:$P$4,0))*(1-H$20)/12,0),0)} -> 0 | I54: {=IF(I$17>0,IFERROR(INDEX('OI & Expense Growth'!$F10:$P10,MATCH('Monthly CFs'!I$5,'OI & Expense Growth'!$F$4:$P$4,0))*(1-I$20)/12,0),0)} -> 0 | J54: {=IF(J$17>0,IFERROR(INDEX('OI & Expense Growth'!$F10:$P10,MATCH('Monthly CFs'!J$5,'OI & Expense Growth'!$F$4:$P$4,0))*(1-J$20)/12,0),0)} -> 0 | K54: {=IF(K$17>0,IFERROR(INDEX('OI & Expense Growth'!$F10:$P10,MATCH('Monthly CFs'!K$5,'OI & Expense Growth'!$F$4:$P$4,0))*(1-K$20)/12,0),0)} -> 0 | L54: {=IF(L$17>0,IFERROR(INDEX('OI & Expense Growth'!$F10:$P10,MATCH('Monthly CFs'!L$5,'OI & Expense Growth'!$F$4:$P$4,0))*(1-L$20)/12,0),0)} -> 0 | M54: {=IF(M$17>0,IFERROR(INDEX('OI & Expense Growth'!$F10:$P10,MATCH('Monthly CFs'!M$5,'OI & Expense Growth'!$F$4:$P$4,0))*(1-M$20)/12,0),0)} -> 0 | N54: {=IF(N$17>0,IFERROR(INDEX('OI & Expense Growth'!$F10:$P10,MATCH('Monthly CFs'!N$5,'OI & Expense Growth'!$F$4:$P$4,0))*(1-N$20)/12,0),0)} -> 0 | ... EI54: {=IF(EI$17>0,IFERROR(INDEX('OI & Expense Growth'!$F10:$P10,MATCH('Monthly CFs'!EI$5,'OI & Expense Growth'!$F$4:$P$4,0))*(1-EI$20)/12,0),0)} -> 0
C55: Total Other Income | G55: =SUM(G51:G54) -> 0 | H55: =SUM(H51:H54) -> 0 | I55: =SUM(I51:I54) -> 0 | J55: =SUM(J51:J54) -> 0 | K55: =SUM(K51:K54) -> 0 | L55: =SUM(L51:L54) -> 0 | M55: =SUM(M51:M54) -> 0 | N55: =SUM(N51:N54) -> 0 | ... EI55: =SUM(EI51:EI54) -> 64371.598
C57: Effective Gross Income | G57: =G48+G55 -> 0 | H57: =H48+H55 -> 0 | I57: =I48+I55 -> 0 | J57: =J48+J55 -> 0 | K57: =K48+K55 -> 0 | L57: =L48+L55 -> 0 | M57: =M48+M55 -> 0 | N57: =N48+N55 -> 0 | ... EI57: =EI48+EI55 -> 541818.89
C59: Controllable Expenses
C60: Payroll | G60: {=IFERROR(INDEX('OI & Expense Growth'!$F13:$P13,MATCH('Monthly CFs'!G$5,'OI & Expense Growth'!$F$4:$P$4,0))*G$17/12,0)} -> 0 | H60: {=IFERROR(INDEX('OI & Expense Growth'!$F13:$P13,MATCH('Monthly CFs'!H$5,'OI & Expense Growth'!$F$4:$P$4,0))*H$17/12,0)} -> 0 | I60: {=IFERROR(INDEX('OI & Expense Growth'!$F13:$P13,MATCH('Monthly CFs'!I$5,'OI & Expense Growth'!$F$4:$P$4,0))*I$17/12,0)} -> 0 | J60: {=IFERROR(INDEX('OI & Expense Growth'!$F13:$P13,MATCH('Monthly CFs'!J$5,'OI & Expense Growth'!$F$4:$P$4,0))*J$17/12,0)} -> 0 | K60: {=IFERROR(INDEX('OI & Expense Growth'!$F13:$P13,MATCH('Monthly CFs'!K$5,'OI & Expense Growth'!$F$4:$P$4,0))*K$17/12,0)} -> 0 | L60: {=IFERROR(INDEX('OI & Expense Growth'!$F13:$P13,MATCH('Monthly CFs'!L$5,'OI & Expense Growth'!$F$4:$P$4,0))*L$17/12,0)} -> 0 | M60: {=IFERROR(INDEX('OI & Expense Growth'!$F13:$P13,MATCH('Monthly CFs'!M$5,'OI & Expense Growth'!$F$4:$P$4,0))*M$17/12,0)} -> 0 | N60: {=IFERROR(INDEX('OI & Expense Growth'!$F13:$P13,MATCH('Monthly CFs'!N$5,'OI & Expense Growth'!$F$4:$P$4,0))*N$17/12,0)} -> 0 | ... EI60: {=IFERROR(INDEX('OI & Expense Growth'!$F13:$P13,MATCH('Monthly CFs'!EI$5,'OI & Expense Growth'!$F$4:$P$4,0))*EI$17/12,0)} -> 11806.789
C61: Marketing & Advertising | G61: {=IFERROR(INDEX('OI & Expense Growth'!$F14:$P14,MATCH('Monthly CFs'!G$5,'OI & Expense Growth'!$F$4:$P$4,0))*G$17/12,0)} -> 0 | H61: {=IFERROR(INDEX('OI & Expense Growth'!$F14:$P14,MATCH('Monthly CFs'!H$5,'OI & Expense Growth'!$F$4:$P$4,0))*H$17/12,0)} -> 0 | I61: {=IFERROR(INDEX('OI & Expense Growth'!$F14:$P14,MATCH('Monthly CFs'!I$5,'OI & Expense Growth'!$F$4:$P$4,0))*I$17/12,0)} -> 0 | J61: {=IFERROR(INDEX('OI & Expense Growth'!$F14:$P14,MATCH('Monthly CFs'!J$5,'OI & Expense Growth'!$F$4:$P$4,0))*J$17/12,0)} -> 0 | K61: {=IFERROR(INDEX('OI & Expense Growth'!$F14:$P14,MATCH('Monthly CFs'!K$5,'OI & Expense Growth'!$F$4:$P$4,0))*K$17/12,0)} -> 0 | L61: {=IFERROR(INDEX('OI & Expense Growth'!$F14:$P14,MATCH('Monthly CFs'!L$5,'OI & Expense Growth'!$F$4:$P$4,0))*L$17/12,0)} -> 0 | M61: {=IFERROR(INDEX('OI & Expense Growth'!$F14:$P14,MATCH('Monthly CFs'!M$5,'OI & Expense Growth'!$F$4:$P$4,0))*M$17/12,0)} -> 0 | N61: {=IFERROR(INDEX('OI & Expense Growth'!$F14:$P14,MATCH('Monthly CFs'!N$5,'OI & Expense Growth'!$F$4:$P$4,0))*N$17/12,0)} -> 0 | ... EI61: {=IFERROR(INDEX('OI & Expense Growth'!$F14:$P14,MATCH('Monthly CFs'!EI$5,'OI & Expense Growth'!$F$4:$P$4,0))*EI$17/12,0)} -> 6641.3189
C62: Repairs & Maintenance | G62: {=IFERROR(INDEX('OI & Expense Growth'!$F15:$P15,MATCH('Monthly CFs'!G$5,'OI & Expense Growth'!$F$4:$P$4,0))*G$17/12,0)} -> 0 | H62: {=IFERROR(INDEX('OI & Expense Growth'!$F15:$P15,MATCH('Monthly CFs'!H$5,'OI & Expense Growth'!$F$4:$P$4,0))*H$17/12,0)} -> 0 | I62: {=IFERROR(INDEX('OI & Expense Growth'!$F15:$P15,MATCH('Monthly CFs'!I$5,'OI & Expense Growth'!$F$4:$P$4,0))*I$17/12,0)} -> 0 | J62: {=IFERROR(INDEX('OI & Expense Growth'!$F15:$P15,MATCH('Monthly CFs'!J$5,'OI & Expense Growth'!$F$4:$P$4,0))*J$17/12,0)} -> 0 | K62: {=IFERROR(INDEX('OI & Expense Growth'!$F15:$P15,MATCH('Monthly CFs'!K$5,'OI & Expense Growth'!$F$4:$P$4,0))*K$17/12,0)} -> 0 | L62: {=IFERROR(INDEX('OI & Expense Growth'!$F15:$P15,MATCH('Monthly CFs'!L$5,'OI & Expense Growth'!$F$4:$P$4,0))*L$17/12,0)} -> 0 | M62: {=IFERROR(INDEX('OI & Expense Growth'!$F15:$P15,MATCH('Monthly CFs'!M$5,'OI & Expense Growth'!$F$4:$P$4,0))*M$17/12,0)} -> 0 | N62: {=IFERROR(INDEX('OI & Expense Growth'!$F15:$P15,MATCH('Monthly CFs'!N$5,'OI & Expense Growth'!$F$4:$P$4,0))*N$17/12,0)} -> 0 | ... EI62: {=IFERROR(INDEX('OI & Expense Growth'!$F15:$P15,MATCH('Monthly CFs'!EI$5,'OI & Expense Growth'!$F$4:$P$4,0))*EI$17/12,0)} -> 6272.3567
C63: Turnover | G63: {=IFERROR(INDEX('OI & Expense Growth'!$F16:$P16,MATCH('Monthly CFs'!G$5,'OI & Expense Growth'!$F$4:$P$4,0))*G$17/12,0)} -> 0 | H63: {=IFERROR(INDEX('OI & Expense Growth'!$F16:$P16,MATCH('Monthly CFs'!H$5,'OI & Expense Growth'!$F$4:$P$4,0))*H$17/12,0)} -> 0 | I63: {=IFERROR(INDEX('OI & Expense Growth'!$F16:$P16,MATCH('Monthly CFs'!I$5,'OI & Expense Growth'!$F$4:$P$4,0))*I$17/12,0)} -> 0 | J63: {=IFERROR(INDEX('OI & Expense Growth'!$F16:$P16,MATCH('Monthly CFs'!J$5,'OI & Expense Growth'!$F$4:$P$4,0))*J$17/12,0)} -> 0 | K63: {=IFERROR(INDEX('OI & Expense Growth'!$F16:$P16,MATCH('Monthly CFs'!K$5,'OI & Expense Growth'!$F$4:$P$4,0))*K$17/12,0)} -> 0 | L63: {=IFERROR(INDEX('OI & Expense Growth'!$F16:$P16,MATCH('Monthly CFs'!L$5,'OI & Expense Growth'!$F$4:$P$4,0))*L$17/12,0)} -> 0 | M63: {=IFERROR(INDEX('OI & Expense Growth'!$F16:$P16,MATCH('Monthly CFs'!M$5,'OI & Expense Growth'!$F$4:$P$4,0))*M$17/12,0)} -> 0 | N63: {=IFERROR(INDEX('OI & Expense Growth'!$F16:$P16,MATCH('Monthly CFs'!N$5,'OI & Expense Growth'!$F$4:$P$4,0))*N$17/12,0)} -> 0 | ... EI63: {=IFERROR(INDEX('OI & Expense Growth'!$F16:$P16,MATCH('Monthly CFs'!EI$5,'OI & Expense Growth'!$F$4:$P$4,0))*EI$17/12,0)} -> 9070.3198
C64: General & Administrative | G64: {=IFERROR(INDEX('OI & Expense Growth'!$F17:$P17,MATCH('Monthly CFs'!G$5,'OI & Expense Growth'!$F$4:$P$4,0))*G$17/12,0)} -> 0 | H64: {=IFERROR(INDEX('OI & Expense Growth'!$F17:$P17,MATCH('Monthly CFs'!H$5,'OI & Expense Growth'!$F$4:$P$4,0))*H$17/12,0)} -> 0 | I64: {=IFERROR(INDEX('OI & Expense Growth'!$F17:$P17,MATCH('Monthly CFs'!I$5,'OI & Expense Growth'!$F$4:$P$4,0))*I$17/12,0)} -> 0 | J64: {=IFERROR(INDEX('OI & Expense Growth'!$F17:$P17,MATCH('Monthly CFs'!J$5,'OI & Expense Growth'!$F$4:$P$4,0))*J$17/12,0)} -> 0 | K64: {=IFERROR(INDEX('OI & Expense Growth'!$F17:$P17,MATCH('Monthly CFs'!K$5,'OI & Expense Growth'!$F$4:$P$4,0))*K$17/12,0)} -> 0 | L64: {=IFERROR(INDEX('OI & Expense Growth'!$F17:$P17,MATCH('Monthly CFs'!L$5,'OI & Expense Growth'!$F$4:$P$4,0))*L$17/12,0)} -> 0 | M64: {=IFERROR(INDEX('OI & Expense Growth'!$F17:$P17,MATCH('Monthly CFs'!M$5,'OI & Expense Growth'!$F$4:$P$4,0))*M$17/12,0)} -> 0 | N64: {=IFERROR(INDEX('OI & Expense Growth'!$F17:$P17,MATCH('Monthly CFs'!N$5,'OI & Expense Growth'!$F$4:$P$4,0))*N$17/12,0)} -> 0 | ... EI64: {=IFERROR(INDEX('OI & Expense Growth'!$F17:$P17,MATCH('Monthly CFs'!EI$5,'OI & Expense Growth'!$F$4:$P$4,0))*EI$17/12,0)} -> 5165.4702
C65: Total Controllable Expenses | G65: =SUM(G60:G64) -> 0 | H65: =SUM(H60:H64) -> 0 | I65: =SUM(I60:I64) -> 0 | J65: =SUM(J60:J64) -> 0 | K65: =SUM(K60:K64) -> 0 | L65: =SUM(L60:L64) -> 0 | M65: =SUM(M60:M64) -> 0 | N65: =SUM(N60:N64) -> 0 | ... EI65: =SUM(EI60:EI64) -> 38956.255
C67: Non-Controllable Expenses
C68: Real Estate Taxes | G68: {=IF(G$5=0,0,IF(G$17=0,'OI & Expense Growth'!$F$20/12/2,IFERROR(INDEX('OI & Expense Growth'!$F20:$P20,MATCH('Monthly CFs'!G$5,'OI & Expense Growth'!$F$4:$P$4,0))/12,0)))} -> 0 | H68: {=IF(H$5=0,0,IF(H$17=0,'Summary & Assumptions'!$L$45/12,IFERROR(INDEX('OI & Expense Growth'!$F20:$P20,MATCH('Monthly CFs'!H$5,'OI & Expense Growth'!$F$4:$P$4,0))/12,0)))} -> 26113.008 | I68: {=IF(I$5=0,0,IF(I$17=0,'Summary & Assumptions'!$L$45/12,IFERROR(INDEX('OI & Expense Growth'!$F20:$P20,MATCH('Monthly CFs'!I$5,'OI & Expense Growth'!$F$4:$P$4,0))/12,0)))} -> 26113.008 | J68: {=IF(J$5=0,0,IF(J$17=0,'Summary & Assumptions'!$L$45/12,IFERROR(INDEX('OI & Expense Growth'!$F20:$P20,MATCH('Monthly CFs'!J$5,'OI & Expense Growth'!$F$4:$P$4,0))/12,0)))} -> 26113.008 | K68: {=IF(K$5=0,0,IF(K$17=0,'Summary & Assumptions'!$L$45/12,IFERROR(INDEX('OI & Expense Growth'!$F20:$P20,MATCH('Monthly CFs'!K$5,'OI & Expense Growth'!$F$4:$P$4,0))/12,0)))} -> 26113.008 | L68: {=IF(L$5=0,0,IF(L$17=0,'Summary & Assumptions'!$L$45/12,IFERROR(INDEX('OI & Expense Growth'!$F20:$P20,MATCH('Monthly CFs'!L$5,'OI & Expense Growth'!$F$4:$P$4,0))/12,0)))} -> 26113.008 | M68: {=IF(M$5=0,0,IF(M$17=0,'Summary & Assumptions'!$L$45/12,IFERROR(INDEX('OI & Expense Growth'!$F20:$P20,MATCH('Monthly CFs'!M$5,'OI & Expense Growth'!$F$4:$P$4,0))/12,0)))} -> 26113.008 | N68: {=IF(N$5=0,0,IF(N$17=0,'Summary & Assumptions'!$L$45/12,IFERROR(INDEX('OI & Expense Growth'!$F20:$P20,MATCH('Monthly CFs'!N$5,'OI & Expense Growth'!$F$4:$P$4,0))/12,0)))} -> 26113.008 | O68: {=IF(O$5=0,0,IF(O$17=0,'Summary & Assumptions'!$L$45/12,IFERROR(INDEX('OI & Expense Growth'!$F20:$P20,MATCH('Monthly CFs'!O$5,'OI & Expense Growth'!$F$4:$P$4,0))/12,0)))} -> 26113.008 | ... EI68: {=IF(EI$5=0,0,IF(EI$17=0,'Summary & Assumptions'!$L$45/12,IFERROR(INDEX('OI & Expense Growth'!$F20:$P20,MATCH('Monthly CFs'!EI$5,'OI & Expense Growth'!$F$4:$P$4,0))/12,0)))} -> 56194.372
C69: Insurance | G69: {=IF(G$5=0,0,IF(G$17=0,'OI & Expense Growth'!$F$21/12/2,IFERROR(INDEX('OI & Expense Growth'!$F21:$P21,MATCH('Monthly CFs'!G$5,'OI & Expense Growth'!$F$4:$P$4,0))/12,0)))} -> 0 | H69: {=IF(H$5=0,0,IF(H$17=0,'OI & Expense Growth'!$F$21/12/2,IFERROR(INDEX('OI & Expense Growth'!$F21:$P21,MATCH('Monthly CFs'!H$5,'OI & Expense Growth'!$F$4:$P$4,0))/12,0)))} -> 3300 | I69: {=IF(I$5=0,0,IF(I$17=0,'OI & Expense Growth'!$F$21/12/2,IFERROR(INDEX('OI & Expense Growth'!$F21:$P21,MATCH('Monthly CFs'!I$5,'OI & Expense Growth'!$F$4:$P$4,0))/12,0)))} -> 3300 | J69: {=IF(J$5=0,0,IF(J$17=0,'OI & Expense Growth'!$F$21/12/2,IFERROR(INDEX('OI & Expense Growth'!$F21:$P21,MATCH('Monthly CFs'!J$5,'OI & Expense Growth'!$F$4:$P$4,0))/12,0)))} -> 3300 | K69: {=IF(K$5=0,0,IF(K$17=0,'OI & Expense Growth'!$F$21/12/2,IFERROR(INDEX('OI & Expense Growth'!$F21:$P21,MATCH('Monthly CFs'!K$5,'OI & Expense Growth'!$F$4:$P$4,0))/12,0)))} -> 3300 | L69: {=IF(L$5=0,0,IF(L$17=0,'OI & Expense Growth'!$F$21/12/2,IFERROR(INDEX('OI & Expense Growth'!$F21:$P21,MATCH('Monthly CFs'!L$5,'OI & Expense Growth'!$F$4:$P$4,0))/12,0)))} -> 3300 | M69: {=IF(M$5=0,0,IF(M$17=0,'OI & Expense Growth'!$F$21/12/2,IFERROR(INDEX('OI & Expense Growth'!$F21:$P21,MATCH('Monthly CFs'!M$5,'OI & Expense Growth'!$F$4:$P$4,0))/12,0)))} -> 3300 | N69: {=IF(N$5=0,0,IF(N$17=0,'OI & Expense Growth'!$F$21/12/2,IFERROR(INDEX('OI & Expense Growth'!$F21:$P21,MATCH('Monthly CFs'!N$5,'OI & Expense Growth'!$F$4:$P$4,0))/12,0)))} -> 3300 | ... EI69: {=IF(EI$5=0,0,IF(EI$17=0,'OI & Expense Growth'!$F$21/12/2,IFERROR(INDEX('OI & Expense Growth'!$F21:$P21,MATCH('Monthly CFs'!EI$5,'OI & Expense Growth'!$F$4:$P$4,0))/12,0)))} -> 8117.1675
C70: Utilities | G70: {=IFERROR(INDEX('OI & Expense Growth'!$F22:$P22,MATCH('Monthly CFs'!G$5,'OI & Expense Growth'!$F$4:$P$4,0))*G$17/12,0)} -> 0 | H70: {=IFERROR(INDEX('OI & Expense Growth'!$F22:$P22,MATCH('Monthly CFs'!H$5,'OI & Expense Growth'!$F$4:$P$4,0))*H$17/12,0)} -> 0 | I70: {=IFERROR(INDEX('OI & Expense Growth'!$F22:$P22,MATCH('Monthly CFs'!I$5,'OI & Expense Growth'!$F$4:$P$4,0))*I$17/12,0)} -> 0 | J70: {=IFERROR(INDEX('OI & Expense Growth'!$F22:$P22,MATCH('Monthly CFs'!J$5,'OI & Expense Growth'!$F$4:$P$4,0))*J$17/12,0)} -> 0 | K70: {=IFERROR(INDEX('OI & Expense Growth'!$F22:$P22,MATCH('Monthly CFs'!K$5,'OI & Expense Growth'!$F$4:$P$4,0))*K$17/12,0)} -> 0 | L70: {=IFERROR(INDEX('OI & Expense Growth'!$F22:$P22,MATCH('Monthly CFs'!L$5,'OI & Expense Growth'!$F$4:$P$4,0))*L$17/12,0)} -> 0 | M70: {=IFERROR(INDEX('OI & Expense Growth'!$F22:$P22,MATCH('Monthly CFs'!M$5,'OI & Expense Growth'!$F$4:$P$4,0))*M$17/12,0)} -> 0 | N70: {=IFERROR(INDEX('OI & Expense Growth'!$F22:$P22,MATCH('Monthly CFs'!N$5,'OI & Expense Growth'!$F$4:$P$4,0))*N$17/12,0)} -> 0 | ... EI70: {=IFERROR(INDEX('OI & Expense Growth'!$F22:$P22,MATCH('Monthly CFs'!EI$5,'OI & Expense Growth'!$F$4:$P$4,0))*EI$17/12,0)} -> 22137.73
C71: Management Fee | G71: {=IFERROR(G57*INDEX('Growth Rates'!$O$10:$O$20,MATCH('Monthly CFs'!G5,'Growth Rates'!$C$10:$C$20,0)),0)} -> 0 | H71: {=IFERROR(H57*INDEX('Growth Rates'!$O$10:$O$20,MATCH('Monthly CFs'!H5,'Growth Rates'!$C$10:$C$20,0)),0)} -> 0 | I71: {=IFERROR(I57*INDEX('Growth Rates'!$O$10:$O$20,MATCH('Monthly CFs'!I5,'Growth Rates'!$C$10:$C$20,0)),0)} -> 0 | J71: {=IFERROR(J57*INDEX('Growth Rates'!$O$10:$O$20,MATCH('Monthly CFs'!J5,'Growth Rates'!$C$10:$C$20,0)),0)} -> 0 | K71: {=IFERROR(K57*INDEX('Growth Rates'!$O$10:$O$20,MATCH('Monthly CFs'!K5,'Growth Rates'!$C$10:$C$20,0)),0)} -> 0 | L71: {=IFERROR(L57*INDEX('Growth Rates'!$O$10:$O$20,MATCH('Monthly CFs'!L5,'Growth Rates'!$C$10:$C$20,0)),0)} -> 0 | M71: {=IFERROR(M57*INDEX('Growth Rates'!$O$10:$O$20,MATCH('Monthly CFs'!M5,'Growth Rates'!$C$10:$C$20,0)),0)} -> 0 | N71: {=IFERROR(N57*INDEX('Growth Rates'!$O$10:$O$20,MATCH('Monthly CFs'!N5,'Growth Rates'!$C$10:$C$20,0)),0)} -> 0 | ... EI71: {=IFERROR(EI57*INDEX('Growth Rates'!$O$10:$O$20,MATCH('Monthly CFs'!EI5,'Growth Rates'!$C$10:$C$20,0)),0)} -> 16254.567
C72: Total Non-Controllable Expenses | G72: =SUM(G68:G71) -> 0 | H72: =SUM(H68:H71) -> 29413.008 | I72: =SUM(I68:I71) -> 29413.008 | J72: =SUM(J68:J71) -> 29413.008 | K72: =SUM(K68:K71) -> 29413.008 | L72: =SUM(L68:L71) -> 29413.008 | M72: =SUM(M68:M71) -> 29413.008 | N72: =SUM(N68:N71) -> 29413.008 | ... EI72: =SUM(EI68:EI71) -> 102703.84
C73: Total Operating Expenses | G73: =G72+G65 -> 0 | H73: =H72+H65 -> 29413.008 | I73: =I72+I65 -> 29413.008 | J73: =J72+J65 -> 29413.008 | K73: =K72+K65 -> 29413.008 | L73: =L72+L65 -> 29413.008 | M73: =M72+M65 -> 29413.008 | N73: =N72+N65 -> 29413.008 | ... EI73: =EI72+EI65 -> 141660.09
C75: Net Operating Income | G75: =G57-G73 -> 0 | H75: =H57-H73 -> -29413.008 | I75: =I57-I73 -> -29413.008 | J75: =J57-J73 -> -29413.008 | K75: =K57-K73 -> -29413.008 | L75: =L57-L73 -> -29413.008 | M75: =M57-M73 -> -29413.008 | N75: =N57-N73 -> -29413.008 | ... EI75: =EI57-EI73 -> 400158.8
C77: Capital Reserves | G77: {=IFERROR('Summary & Assumptions'!$D$34*'Monthly CFs'!G17*INDEX('Growth Rates'!$P$10:$P$20,MATCH('Monthly CFs'!G5,'Growth Rates'!$C$10:$C$20,0)),0)/12} -> 0 | H77: {=IFERROR('Summary & Assumptions'!$D$34*'Monthly CFs'!H17*INDEX('Growth Rates'!$P$10:$P$20,MATCH('Monthly CFs'!H5,'Growth Rates'!$C$10:$C$20,0)),0)/12} -> 0 | I77: {=IFERROR('Summary & Assumptions'!$D$34*'Monthly CFs'!I17*INDEX('Growth Rates'!$P$10:$P$20,MATCH('Monthly CFs'!I5,'Growth Rates'!$C$10:$C$20,0)),0)/12} -> 0 | J77: {=IFERROR('Summary & Assumptions'!$D$34*'Monthly CFs'!J17*INDEX('Growth Rates'!$P$10:$P$20,MATCH('Monthly CFs'!J5,'Growth Rates'!$C$10:$C$20,0)),0)/12} -> 0 | K77: {=IFERROR('Summary & Assumptions'!$D$34*'Monthly CFs'!K17*INDEX('Growth Rates'!$P$10:$P$20,MATCH('Monthly CFs'!K5,'Growth Rates'!$C$10:$C$20,0)),0)/12} -> 0 | L77: {=IFERROR('Summary & Assumptions'!$D$34*'Monthly CFs'!L17*INDEX('Growth Rates'!$P$10:$P$20,MATCH('Monthly CFs'!L5,'Growth Rates'!$C$10:$C$20,0)),0)/12} -> 0 | M77: {=IFERROR('Summary & Assumptions'!$D$34*'Monthly CFs'!M17*INDEX('Growth Rates'!$P$10:$P$20,MATCH('Monthly CFs'!M5,'Growth Rates'!$C$10:$C$20,0)),0)/12} -> 0 | N77: {=IFERROR('Summary & Assumptions'!$D$34*'Monthly CFs'!N17*INDEX('Growth Rates'!$P$10:$P$20,MATCH('Monthly CFs'!N5,'Growth Rates'!$C$10:$C$20,0)),0)/12} -> 0 | ... EI77: {=IFERROR('Summary & Assumptions'!$D$34*'Monthly CFs'!EI17*INDEX('Growth Rates'!$P$10:$P$20,MATCH('Monthly CFs'!EI5,'Growth Rates'!$C$10:$C$20,0)),0)/12} -> 1800
C78: Cash Flows From Operations | G78: =G75-G77 -> 0 | H78: =H75-H77 -> -29413.008 | I78: =I75-I77 -> -29413.008 | J78: =J75-J77 -> -29413.008 | K78: =K75-K77 -> -29413.008 | L78: =L75-L77 -> -29413.008 | M78: =M75-M77 -> -29413.008 | N78: =N75-N77 -> -29413.008 | ... EI78: =EI75-EI77 -> 398358.8

Sheet Budget & Draw Schedule
R3: =IF('Budget & Draw Schedule'!W8>'Summary & Assumptions'!H41,1,0) -> 0 | W3: =IF(W8<='Summary & Assumptions'!$H$51,1,0) -> 1 | X3: =IF(X8<='Summary & Assumptions'!$H$51,1,0) -> 1 | Y3: =IF(Y8<='Summary & Assumptions'!$H$51,1,0) -> 1 | Z3: =IF(Z8<='Summary & Assumptions'!$H$51,1,0) -> 1 | AA3: =IF(AA8<='Summary & Assumptions'!$H$51,1,0) -> 1 | AB3: =IF(AB8<='Summary & Assumptions'!$H$51,1,0) -> 1 | AC3: =IF(AC8<='Summary & Assumptions'!$H$51,1,0) -> 1 | AD3: =IF(AD8<='Summary & Assumptions'!$H$51,1,0) -> 1 | ... EY3: =IF(EY8<='Summary & Assumptions'!$H$51,1,0) -> 0
D5: Budget | N5: Draw Schedule | V5: Year | W5: =YEAR(W8) -> 2022 | X5: =YEAR(X8) -> 2022 | Y5: =YEAR(Y8) -> 2022 | Z5: =YEAR(Z8) -> 2022 | AA5: =YEAR(AA8) -> 2022 | AB5: =YEAR(AB8) -> 2022 | AC5: =YEAR(AC8) -> 2022 | AD5: =YEAR(AD8) -> 2023 | ... EY5: =YEAR(EY8) -> 2033
V6: Year | W6: =ROUNDUP(W7/12,0) -> 0 | X6: =ROUNDUP(X7/12,0) -> 1 | Y6: =ROUNDUP(Y7/12,0) -> 1 | Z6: =ROUNDUP(Z7/12,0) -> 1 | AA6: =ROUNDUP(AA7/12,0) -> 1 | AB6: =ROUNDUP(AB7/12,0) -> 1 | AC6: =ROUNDUP(AC7/12,0) -> 1 | AD6: =ROUNDUP(AD7/12,0) -> 1 | ... EY6: =ROUNDUP(EY7/12,0) -> 11
V7: Month | W7: 0 | X7: =+W7+1 -> 1 | Y7: =+X7+1 -> 2 | Z7: =+Y7+1 -> 3 | AA7: =+Z7+1 -> 4 | AB7: =+AA7+1 -> 5 | AC7: =+AB7+1 -> 6 | AD7: =+AC7+1 -> 7 | AE7: =+AD7+1 -> 8 | ... EY7: =+EX7+1 -> 132
V8: Date | W8: ='Summary & Assumptions'!H38 -> 44713 | X8: =+EOMONTH(W8,1) -> 44773 | Y8: =+EOMONTH(X8,1) -> 44804 | Z8: =+EOMONTH(Y8,1) -> 44834 | AA8: =+EOMONTH(Z8,1) -> 44865 | AB8: =+EOMONTH(AA8,1) -> 44895 | AC8: =+EOMONTH(AB8,1) -> 44926 | AD8: =+EOMONTH(AC8,1) -> 44957 | AE8: =+EOMONTH(AD8,1) -> 44985 | ... EY8: =+EOMONTH(EX8,1) -> 48760
O9: Totals | P9: Check | R9: Start | S9: End | T9: Duration | W9: =IF(W8='Summary & Assumptions'!$H$38,"Loan Close",IF(AND('Budget & Draw Schedule'!W8>'Summary & Assumptions'!$H$38,'Budget & Draw Schedule'!W8<'Summary & Assumptions'!$H$41),"Pre-Dev",IF(AND(W8>'Summary & Assumptions'!$H$41,'Budget & Draw Schedule'!W8<='Summary & Assumptions'!$H$43),"Development","Occupancy"))) -> Loan Close | X9: =IF(X8='Summary & Assumptions'!$H$38,"Loan Close",IF(AND('Budget & Draw Schedule'!X8>'Summary & Assumptions'!$H$38,'Budget & Draw Schedule'!X8<'Summary & Assumptions'!$H$41),"Pre-Dev",IF(AND(X8>'Summary & Assumptions'!$H$41,'Budget & Draw Schedule'!X8<='Summary & Assumptions'!$H$43),"Development","Occupancy"))) -> Pre-Dev | Y9: =IF(Y8='Summary & Assumptions'!$H$38,"Loan Close",IF(AND('Budget & Draw Schedule'!Y8>'Summary & Assumptions'!$H$38,'Budget & Draw Schedule'!Y8<'Summary & Assumptions'!$H$41),"Pre-Dev",IF(AND(Y8>'Summary & Assumptions'!$H$41,'Budget & Draw Schedule'!Y8<='Summary & Assumptions'!$H$43),"Development","Occupancy"))) -> Pre-Dev | Z9: =IF(Z8='Summary & Assumptions'!$H$38,"Loan Close",IF(AND('Budget & Draw Schedule'!Z8>'Summary & Assumptions'!$H$38,'Budget & Draw Schedule'!Z8<'Summary & Assumptions'!$H$41),"Pre-Dev",IF(AND(Z8>'Summary & Assumptions'!$H$41,'Budget & Draw Schedule'!Z8<='Summary & Assumptions'!$H$43),"Development","Occupancy"))) -> Pre-Dev | AA9: =IF(AA8='Summary & Assumptions'!$H$38,"Loan Close",IF(AND('Budget & Draw Schedule'!AA8>'Summary & Assumptions'!$H$38,'Budget & Draw Schedule'!AA8<'Summary & Assumptions'!$H$41),"Pre-Dev",IF(AND(AA8>'Summary & Assumptions'!$H$41,'Budget & Draw Schedule'!AA8<='Summary & Assumptions'!$H$43),"Development","Occupancy"))) -> Pre-Dev | AB9: =IF(AB8='Summary & Assumptions'!$H$38,"Loan Close",IF(AND('Budget & Draw Schedule'!AB8>'Summary & Assumptions'!$H$38,'Budget & Draw Schedule'!AB8<'Summary & Assumptions'!$H$41),"Pre-Dev",IF(AND(AB8>'Summary & Assumptions'!$H$41,'Budget & Draw Schedule'!AB8<='Summary & Assumptions'!$H$43),"Development","Occupancy"))) -> Pre-Dev | AC9: =IF(AC8='Summary & Assumptions'!$H$38,"Loan Close",IF(AND('Budget & Draw Schedule'!AC8>'Summary & Assumptions'!$H$38,'Budget & Draw Schedule'!AC8<'Summary & Assumptions'!$H$41),"Pre-Dev",IF(AND(AC8>'Summary & Assumptions'!$H$41,'Budget & Draw Schedule'!AC8<='Summary & Assumptions'!$H$43),"Development","Occupancy"))) -> Pre-Dev | AD9: =IF(AD8='Summary & Assumptions'!$H$38,"Loan Close",IF(AND('Budget & Draw Schedule'!AD8>'Summary & Assumptions'!$H$38,'Budget & Draw Schedule'!AD8<'Summary & Assumptions'!$H$41),"Pre-Dev",IF(AND(AD8>'Summary & Assumptions'!$H$41,'Budget & Draw Schedule'!AD8<='Summary & Assumptions'!$H$43),"Development","Occupancy"))) -> Pre-Dev | ... EY9: =IF(EY8='Summary & Assumptions'!$H$38,"Loan Close",IF(AND('Budget & Draw Schedule'!EY8>'Summary & Assumptions'!$H$38,'Budget & Draw Schedule'!EY8<'Summary & Assumptions'!$H$41),"Pre-Dev",IF(AND(EY8>'Summary & Assumptions'!$H$41,'Budget & Draw Schedule'!EY8<='Summary & Assumptions'!$H$43),"Development","Occupancy"))) -> Occupancy
D11: Land | G11: Total | H11: $/Unit | I11: $/GSF | J11: $/NSF | K11: % Total | N11: =+D11 -> Land
D12: Land Acquisition Costs | G12: ='Summary & Assumptions'!L22 -> 28800000 | H12: =G12/'Summary & Assumptions'!$D$34 -> 200000 | I12: =G12/'Summary & Assumptions'!$H$11 -> 216.92464 | J12: =G12/'Summary & Assumptions'!$H$16 -> 282.57457 | K12: =G12/$G$52 -> 0.48892388 | N12: =+D12 -> Land Acquisition Costs | P12: =SUM(W12:EY12)-G12 -> 0 | R12: =+'Summary & Assumptions'!$H$40 -> 44713 | S12: =+'Summary & Assumptions'!$H$40 -> 44713 | T12: =DATEDIF(R12,S12,"m")+1 -> 1 | W12: =+IF(AND(W$8>=$R12,W$8<=$S12),$G12/$T12,0) -> 28800000 | X12: =+IF(AND(X$8>=$R12,X$8<=$S12),$G12/$T12,0) -> 0 | Y12: =+IF(AND(Y$8>=$R12,Y$8<=$S12),$G12/$T12,0) -> 0 | Z12: =+IF(AND(Z$8>=$R12,Z$8<=$S12),$G12/$T12,0) -> 0 | AA12: =+IF(AND(AA$8>=$R12,AA$8<=$S12),$G12/$T12,0) -> 0 | AB12: =+IF(AND(AB$8>=$R12,AB$8<=$S12),$G12/$T12,0) -> 0 | AC12: =+IF(AND(AC$8>=$R12,AC$8<=$S12),$G12/$T12,0) -> 0 | AD12: =+IF(AND(AD$8>=$R12,AD$8<=$S12),$G12/$T12,0) -> 0 | ... EY12: =+IF(AND(EY$8>=$R12,EY$8<=$S12),$G12/$T12,0) -> 0
D13: Total Land Costs | G13: =SUM(G12) -> 28800000 | H13: =SUM(H12) -> 200000 | I13: =SUM(I12) -> 216.92464 | J13: =SUM(J12) -> 282.57457 | K13: =SUM(K12) -> 0.48892388 | N13: =+D13 -> Total Land Costs | O13: =SUM(W13:EY13) -> 28800000 | P13: =SUM(P12) -> 0 | W13: =SUM(W12) -> 28800000 | X13: =SUM(X12) -> 0 | Y13: =SUM(Y12) -> 0 | Z13: =SUM(Z12) -> 0 | AA13: =SUM(AA12) -> 0 | AB13: =SUM(AB12) -> 0 | AC13: =SUM(AC12) -> 0 | AD13: =SUM(AD12) -> 0 | ... EY13: =SUM(EY12) -> 0
D15: Hard Costs | N15: =+D15 -> Hard Costs | R15: Per Hard Cost Curve | W15: =SUMIF('Construction Curve'!$G$2:$BN$2,'Budget & Draw Schedule'!W7,'Construction Curve'!$G$3:$BN$3) -> 0 | X15: =SUMIF('Construction Curve'!$G$2:$BN$2,'Budget & Draw Schedule'!X7,'Construction Curve'!$G$3:$BN$3) -> 0 | Y15: =SUMIF('Construction Curve'!$G$2:$BN$2,'Budget & Draw Schedule'!Y7,'Construction Curve'!$G$3:$BN$3) -> 0 | Z15: =SUMIF('Construction Curve'!$G$2:$BN$2,'Budget & Draw Schedule'!Z7,'Construction Curve'!$G$3:$BN$3) -> 0 | AA15: =SUMIF('Construction Curve'!$G$2:$BN$2,'Budget & Draw Schedule'!AA7,'Construction Curve'!$G$3:$BN$3) -> 0 | AB15: =SUMIF('Construction Curve'!$G$2:$BN$2,'Budget & Draw Schedule'!AB7,'Construction Curve'!$G$3:$BN$3) -> 0 | AC15: =SUMIF('Construction Curve'!$G$2:$BN$2,'Budget & Draw Schedule'!AC7,'Construction Curve'!$G$3:$BN$3) -> 0 | AD15: =SUMIF('Construction Curve'!$G$2:$BN$2,'Budget & Draw Schedule'!AD7,'Construction Curve'!$G$3:$BN$3) -> 0 | ... EY15: =SUMIF('Construction Curve'!$G$2:$BN$2,'Budget & Draw Schedule'!EY7,'Construction Curve'!$G$3:$BN$3) -> 0
D16: ='Hard Cost Detail'!C7 -> Direct Construction Costs | G16: ='Hard Cost Detail'!E29 -> 16569750 | H16: =G16/'Summary & Assumptions'!$D$34 -> 115067.71 | I16: =G16/'Summary & Assumptions'!$H$11 -> 124.80511 | J16: =G16/'Summary & Assumptions'!$H$16 -> 162.57604 | K16: =G16/$G$52 -> 0.28129675 | N16: =+D16 -> Direct Construction Costs | P16: =SUM(W16:EY16)-G16 -> 0 | W16: =+$G16*W$15 -> 0 | X16: =+$G16*X$15 -> 0 | Y16: =+$G16*Y$15 -> 0 | Z16: =+$G16*Z$15 -> 0 | AA16: =+$G16*AA$15 -> 0 | AB16: =+$G16*AB$15 -> 0 | AC16: =+$G16*AC$15 -> 0 | AD16: =+$G16*AD$15 -> 0 | ... EY16: =+$G16*EY$15 -> 0
D17: ='Hard Cost Detail'!C32 -> Construction Contingency | G17: ='Hard Cost Detail'!E32 -> 828487.5 | H17: =G17/'Summary & Assumptions'!$D$34 -> 5753.3854 | I17: =G17/'Summary & Assumptions'!$H$11 -> 6.2402553 | J17: =G17/'Summary & Assumptions'!$H$16 -> 8.128802 | K17: =G17/$G$52 -> 0.014064838 | N17: =+D17 -> Construction Contingency | P17: =SUM(W17:EY17)-G17 -> 0 | W17: =+$G17*W$15 -> 0 | X17: =+$G17*X$15 -> 0 | Y17: =+$G17*Y$15 -> 0 | Z17: =+$G17*Z$15 -> 0 | AA17: =+$G17*AA$15 -> 0 | AB17: =+$G17*AB$15 -> 0 | AC17: =+$G17*AC$15 -> 0 | AD17: =+$G17*AD$15 -> 0 | ... EY17: =+$G17*EY$15 -> 0
D18: ='Hard Cost Detail'!C33 -> Building Insurance | G18: ='Hard Cost Detail'!E33 -> 173982.38 | H18: =G18/'Summary & Assumptions'!$D$34 -> 1208.2109 | I18: =G18/'Summary & Assumptions'!$H$11 -> 1.3104536 | J18: =G18/'Summary & Assumptions'!$H$16 -> 1.7070484 | K18: =G18/$G$52 -> 0.0029536159 | N18: =+D18 -> Building Insurance | P18: =SUM(W18:EY18)-G18 -> 0 | W18: =+$G18*W$15 -> 0 | X18: =+$G18*X$15 -> 0 | Y18: =+$G18*Y$15 -> 0 | Z18: =+$G18*Z$15 -> 0 | AA18: =+$G18*AA$15 -> 0 | AB18: =+$G18*AB$15 -> 0 | AC18: =+$G18*AC$15 -> 0 | AD18: =+$G18*AD$15 -> 0 | ... EY18: =+$G18*EY$15 -> 0
D19: ='Hard Cost Detail'!C34 -> Preconstruction Services | G19: ='Hard Cost Detail'!E34 -> 527166.6 | H19: =G19/'Summary & Assumptions'!$D$34 -> 3660.8791 | I19: =G19/'Summary & Assumptions'!$H$11 -> 3.9706745 | J19: =G19/'Summary & Assumptions'!$H$16 -> 5.1723567 | K19: =G19/$G$52 -> 0.0089494561 | N19: =+D19 -> Preconstruction Services | P19: =SUM(W19:EY19)-G19 -> 0 | W19: =+$G19*W$15 -> 0 | X19: =+$G19*X$15 -> 0 | Y19: =+$G19*Y$15 -> 0 | Z19: =+$G19*Z$15 -> 0 | AA19: =+$G19*AA$15 -> 0 | AB19: =+$G19*AB$15 -> 0 | AC19: =+$G19*AC$15 -> 0 | AD19: =+$G19*AD$15 -> 0 | ... EY19: =+$G19*EY$15 -> 0
D20: ='Hard Cost Detail'!C35 -> Contractor's Fee | G20: ='Hard Cost Detail'!E35 -> 904969.32 | H20: =G20/'Summary & Assumptions'!$D$34 -> 6284.5092 | I20: =G20/'Summary & Assumptions'!$H$11 -> 6.8163245 | J20: =G20/'Summary & Assumptions'!$H$16 -> 8.8792124 | K20: =G20/$G$52 -> 0.015363233 | N20: =+D20 -> Contractor's Fee | P20: =SUM(W20:EY20)-G20 -> 0 | W20: =+$G20*W$15 -> 0 | X20: =+$G20*X$15 -> 0 | Y20: =+$G20*Y$15 -> 0 | Z20: =+$G20*Z$15 -> 0 | AA20: =+$G20*AA$15 -> 0 | AB20: =+$G20*AB$15 -> 0 | AC20: =+$G20*AC$15 -> 0 | AD20: =+$G20*AD$15 -> 0 | ... EY20: =+$G20*EY$15 -> 0
D21: ='Hard Cost Detail'!C40 -> Construction Cost Reductions | G21: ='Hard Cost Detail'!E49 -> 0 | H21: =G21/'Summary & Assumptions'!$D$34 -> 0 | I21: =G21/'Summary & Assumptions'!$H$11 -> 0 | J21: =G21/'Summary & Assumptions'!$H$16 -> 0 | K21: =G21/$G$52 -> 0 | N21: =+D21 -> Construction Cost Reductions | P21: =SUM(W21:EY21)-G21 -> 0 | W21: =+$G21*W$15 -> 0 | X21: =+$G21*X$15 -> 0 | Y21: =+$G21*Y$15 -> 0 | Z21: =+$G21*Z$15 -> 0 | AA21: =+$G21*AA$15 -> 0 | AB21: =+$G21*AB$15 -> 0 | AC21: =+$G21*AC$15 -> 0 | AD21: =+$G21*AD$15 -> 0 | ... EY21: =+$G21*EY$15 -> 0
D22: ='Hard Cost Detail'!C51 -> Owner's Contingency | G22: ='Hard Cost Detail'!E51 -> 950217.79 | H22: =G22/'Summary & Assumptions'!$D$34 -> 6598.7347 | I22: =G22/'Summary & Assumptions'!$H$11 -> 7.1571407 | J22: =G22/'Summary & Assumptions'!$H$16 -> 9.323173 | K22: =G22/$G$52 -> 0.016131395 | N22: =+D22 -> Owner's Contingency | P22: =SUM(W22:EY22)-G22 -> 0 | W22: =+$G22*W$15 -> 0 | X22: =+$G22*X$15 -> 0 | Y22: =+$G22*Y$15 -> 0 | Z22: =+$G22*Z$15 -> 0 | AA22: =+$G22*AA$15 -> 0 | AB22: =+$G22*AB$15 -> 0 | AC22: =+$G22*AC$15 -> 0 | AD22: =+$G22*AD$15 -> 0 | ... EY22: =+$G22*EY$15 -> 0
D23: Total Hard Costs | G23: =SUM(G16:G22) -> 19954574 | H23: =SUM(H16:H22) -> 138573.43 | I23: =SUM(I16:I22) -> 150.29996 | J23: =SUM(J16:J22) -> 195.78663 | K23: =SUM(K16:K22) -> 0.33875929 | N23: =+D23 -> Total Hard Costs | O23: =SUM(W23:EY23) -> 19954574 | P23: =SUM(P16:P21) -> 0 | W23: =SUM(W16:W22) -> 0 | X23: =SUM(X16:X22) -> 0 | Y23: =SUM(Y16:Y22) -> 0 | Z23: =SUM(Z16:Z22) -> 0 | AA23: =SUM(AA16:AA22) -> 0 | AB23: =SUM(AB16:AB22) -> 0 | AC23: =SUM(AC16:AC22) -> 0 | AD23: =SUM(AD16:AD22) -> 0 | ... EY23: =SUM(EY16:EY22) -> 0
D25: Soft Costs | N25: =+D25 -> Soft Costs
D26: ='Soft Cost Detail'!C6 -> Architecture | G26: ='Soft Cost Detail'!E14 -> 500000 | H26: =G26/'Summary & Assumptions'!$D$34 -> 3472.2222 | I26: =G26/'Summary & Assumptions'!$H$11 -> 3.7660528 | J26: =G26/'Summary & Assumptions'!$H$16 -> 4.9058085 | K26: =G26/$G$52 -> 0.0084882618 | N26: =+D26 -> Architecture | P26: =SUM(W26:EY26)-G26 -> 0 | R26: ='Summary & Assumptions'!$H$38 -> 44713 | S26: =EOMONTH(R26,T26-1) -> 44895 | T26: 6 | W26: =+IF(AND(W$8>=$R26,W$8<=$S26),$G26/$T26,0) -> 83333.333 | X26: =+IF(AND(X$8>=$R26,X$8<=$S26),$G26/$T26,0) -> 83333.333 | Y26: =+IF(AND(Y$8>=$R26,Y$8<=$S26),$G26/$T26,0) -> 83333.333 | Z26: =+IF(AND(Z$8>=$R26,Z$8<=$S26),$G26/$T26,0) -> 83333.333 | AA26: =+IF(AND(AA$8>=$R26,AA$8<=$S26),$G26/$T26,0) -> 83333.333 | AB26: =+IF(AND(AB$8>=$R26,AB$8<=$S26),$G26/$T26,0) -> 83333.333 | AC26: =+IF(AND(AC$8>=$R26,AC$8<=$S26),$G26/$T26,0) -> 0 | AD26: =+IF(AND(AD$8>=$R26,AD$8<=$S26),$G26/$T26,0) -> 0 | ... EY26: =+IF(AND(EY$8>=$R26,EY$8<=$S26),$G26/$T26,0) -> 0
D27: ='Soft Cost Detail'!C16 -> Consultants and Engineering | G27: ='Soft Cost Detail'!E32 -> 450000 | H27: =G27/'Summary & Assumptions'!$D$34 -> 3125 | I27: =G27/'Summary & Assumptions'!$H$11 -> 3.3894475 | J27: =G27/'Summary & Assumptions'!$H$16 -> 4.4152276 | K27: =G27/$G$52 -> 0.0076394356 | N27: =+D27 -> Consultants and Engineering | P27: =SUM(W27:EY27)-G27 -> 0 | R27: ='Summary & Assumptions'!$H$38 -> 44713 | S27: =EOMONTH(R27,T27-1) -> 44895 | T27: 6 | W27: =+IF(AND(W$8>=$R27,W$8<=$S27),$G27/$T27,0) -> 75000 | X27: =+IF(AND(X$8>=$R27,X$8<=$S27),$G27/$T27,0) -> 75000 | Y27: =+IF(AND(Y$8>=$R27,Y$8<=$S27),$G27/$T27,0) -> 75000 | Z27: =+IF(AND(Z$8>=$R27,Z$8<=$S27),$G27/$T27,0) -> 75000 | AA27: =+IF(AND(AA$8>=$R27,AA$8<=$S27),$G27/$T27,0) -> 75000 | AB27: =+IF(AND(AB$8>=$R27,AB$8<=$S27),$G27/$T27,0) -> 75000 | AC27: =+IF(AND(AC$8>=$R27,AC$8<=$S27),$G27/$T27,0) -> 0 | AD27: =+IF(AND(AD$8>=$R27,AD$8<=$S27),$G27/$T27,0) -> 0 | ... EY27: =+IF(AND(EY$8>=$R27,EY$8<=$S27),$G27/$T27,0) -> 0
D28: ='Soft Cost Detail'!C34 -> Legal | G28: ='Soft Cost Detail'!E40 -> 490000 | H28: =G28/'Summary & Assumptions'!$D$34 -> 3402.7778 | I28: =G28/'Summary & Assumptions'!$H$11 -> 3.6907317 | J28: =G28/'Summary & Assumptions'!$H$16 -> 4.8076923 | K28: =G28/$G$52 -> 0.0083184965 | N28: =+D28 -> Legal | P28: =SUM(W28:EY28)-G28 -> 0 | R28: ='Summary & Assumptions'!$H$38 -> 44713 | S28: =EOMONTH(R28,T28-1) -> 44895 | T28: 6 | W28: =+IF(AND(W$8>=$R28,W$8<=$S28),$G28/$T28,0) -> 81666.667 | X28: =+IF(AND(X$8>=$R28,X$8<=$S28),$G28/$T28,0) -> 81666.667 | Y28: =+IF(AND(Y$8>=$R28,Y$8<=$S28),$G28/$T28,0) -> 81666.667 | Z28: =+IF(AND(Z$8>=$R28,Z$8<=$S28),$G28/$T28,0) -> 81666.667 | AA28: =+IF(AND(AA$8>=$R28,AA$8<=$S28),$G28/$T28,0) -> 81666.667 | AB28: =+IF(AND(AB$8>=$R28,AB$8<=$S28),$G28/$T28,0) -> 81666.667 | AC28: =+IF(AND(AC$8>=$R28,AC$8<=$S28),$G28/$T28,0) -> 0 | AD28: =+IF(AND(AD$8>=$R28,AD$8<=$S28),$G28/$T28,0) -> 0 | ... EY28: =+IF(AND(EY$8>=$R28,EY$8<=$S28),$G28/$T28,0) -> 0
D29: ='Soft Cost Detail'!C42 -> Insurance | G29: ='Soft Cost Detail'!E49 -> 250000 | H29: =G29/'Summary & Assumptions'!$D$34 -> 1736.1111 | I29: =G29/'Summary & Assumptions'!$H$11 -> 1.8830264 | J29: =G29/'Summary & Assumptions'!$H$16 -> 2.4529042 | K29: =G29/$G$52 -> 0.0042441309 | N29: =+D29 -> Insurance | P29: =SUM(W29:EY29)-G29 -> 0 | R29: ='Summary & Assumptions'!$H$41 -> 45474 | S29: =EOMONTH(R29,T29-1) -> 46022 | T29: ='Construction Curve'!$B$4 -> 18 | W29: =+IF(AND(W$8>=$R29,W$8<=$S29),$G29/$T29,0) -> 0 | X29: =+IF(AND(X$8>=$R29,X$8<=$S29),$G29/$T29,0) -> 0 | Y29: =+IF(AND(Y$8>=$R29,Y$8<=$S29),$G29/$T29,0) -> 0 | Z29: =+IF(AND(Z$8>=$R29,Z$8<=$S29),$G29/$T29,0) -> 0 | AA29: =+IF(AND(AA$8>=$R29,AA$8<=$S29),$G29/$T29,0) -> 0 | AB29: =+IF(AND(AB$8>=$R29,AB$8<=$S29),$G29/$T29,0) -> 0 | AC29: =+IF(AND(AC$8>=$R29,AC$8<=$S29),$G29/$T29,0) -> 0 | AD29: =+IF(AND(AD$8>=$R29,AD$8<=$S29),$G29/$T29,0) -> 0 | ... EY29: =+IF(AND(EY$8>=$R29,EY$8<=$S29),$G29/$T29,0) -> 0
D30: ='Soft Cost Detail'!C51 -> G&A | G30: ='Soft Cost Detail'!E73 -> 0 | H30: =G30/'Summary & Assumptions'!$D$34 -> 0 | I30: =G30/'Summary & Assumptions'!$H$11 -> 0 | J30: =G30/'Summary & Assumptions'!$H$16 -> 0 | K30: =G30/$G$52 -> 0 | N30: =+D30 -> G&A | P30: =SUM(W30:EY30)-G30 -> 0 | R30: ='Summary & Assumptions'!$H$41 -> 45474 | S30: =EOMONTH(R30,T30-1) -> 46022 | T30: ='Construction Curve'!$B$4 -> 18 | W30: =+IF(AND(W$8>=$R30,W$8<=$S30),$G30/$T30,0) -> 0 | X30: =+IF(AND(X$8>=$R30,X$8<=$S30),$G30/$T30,0) -> 0 | Y30: =+IF(AND(Y$8>=$R30,Y$8<=$S30),$G30/$T30,0) -> 0 | Z30: =+IF(AND(Z$8>=$R30,Z$8<=$S30),$G30/$T30,0) -> 0 | AA30: =+IF(AND(AA$8>=$R30,AA$8<=$S30),$G30/$T30,0) -> 0 | AB30: =+IF(AND(AB$8>=$R30,AB$8<=$S30),$G30/$T30,0) -> 0 | AC30: =+IF(AND(AC$8>=$R30,AC$8<=$S30),$G30/$T30,0) -> 0 | AD30: =+IF(AND(AD$8>=$R30,AD$8<=$S30),$G30/$T30,0) -> 0 | ... EY30: =+IF(AND(EY$8>=$R30,EY$8<=$S30),$G30/$T30,0) -> 0
D31: ='Soft Cost Detail'!C75 -> Municipal Fees | G31: ='Soft Cost Detail'!E79 -> 250000 | H31: =G31/'Summary & Assumptions'!$D$34 -> 1736.1111 | I31: =G31/'Summary & Assumptions'!$H$11 -> 1.8830264 | J31: =G31/'Summary & Assumptions'!$H$16 -> 2.4529042 | K31: =G31/$G$52 -> 0.0042441309 | N31: =+D31 -> Municipal Fees | P31: =SUM(W31:EY31)-G31 -> 0 | R31: ='Summary & Assumptions'!$H$38 -> 44713 | S31: =EOMONTH(R31,T31-1) -> 44895 | T31: 6 | W31: =+IF(AND(W$8>=$R31,W$8<=$S31),$G31/$T31,0) -> 41666.667 | X31: =+IF(AND(X$8>=$R31,X$8<=$S31),$G31/$T31,0) -> 41666.667 | Y31: =+IF(AND(Y$8>=$R31,Y$8<=$S31),$G31/$T31,0) -> 41666.667 | Z31: =+IF(AND(Z$8>=$R31,Z$8<=$S31),$G31/$T31,0) -> 41666.667 | AA31: =+IF(AND(AA$8>=$R31,AA$8<=$S31),$G31/$T31,0) -> 41666.667 | AB31: =+IF(AND(AB$8>=$R31,AB$8<=$S31),$G31/$T31,0) -> 41666.667 | AC31: =+IF(AND(AC$8>=$R31,AC$8<=$S31),$G31/$T31,0) -> 0 | AD31: =+IF(AND(AD$8>=$R31,AD$8<=$S31),$G31/$T31,0) -> 0 | ... EY31: =+IF(AND(EY$8>=$R31,EY$8<=$S31),$G31/$T31,0) -> 0
D32: ='Soft Cost Detail'!C81 -> Developer Fee | G32: ='Soft Cost Detail'!E81 -> 497092.5 | H32: =G32/'Summary & Assumptions'!$D$34 -> 3452.0312 | I32: =G32/'Summary & Assumptions'!$H$11 -> 3.7441532 | J32: =G32/'Summary & Assumptions'!$H$16 -> 4.8772812 | K32: =G32/$G$52 -> 0.0084389025 | N32: =+D32 -> Developer Fee | P32: =SUM(W32:EY32)-G32 -> 0 | R32: ='Summary & Assumptions'!$H$41 -> 45474 | S32: =EOMONTH(R32,T32-1) -> 46022 | T32: ='Construction Curve'!$B$4 -> 18 | W32: =+IF(AND(W$8>=$R32,W$8<=$S32),$G32/$T32,0) -> 0 | X32: =+IF(AND(X$8>=$R32,X$8<=$S32),$G32/$T32,0) -> 0 | Y32: =+IF(AND(Y$8>=$R32,Y$8<=$S32),$G32/$T32,0) -> 0 | Z32: =+IF(AND(Z$8>=$R32,Z$8<=$S32),$G32/$T32,0) -> 0 | AA32: =+IF(AND(AA$8>=$R32,AA$8<=$S32),$G32/$T32,0) -> 0 | AB32: =+IF(AND(AB$8>=$R32,AB$8<=$S32),$G32/$T32,0) -> 0 | AC32: =+IF(AND(AC$8>=$R32,AC$8<=$S32),$G32/$T32,0) -> 0 | AD32: =+IF(AND(AD$8>=$R32,AD$8<=$S32),$G32/$T32,0) -> 0 | ... EY32: =+IF(AND(EY$8>=$R32,EY$8<=$S32),$G32/$T32,0) -> 0
D33: ='Soft Cost Detail'!C82 -> Marketing | G33: ='Soft Cost Detail'!E82 -> 392680 | H33: =G33/'Summary & Assumptions'!$D$34 -> 2726.9444 | I33: =G33/'Summary & Assumptions'!$H$11 -> 2.9577072 | J33: =G33/'Summary & Assumptions'!$H$16 -> 3.8528257 | K33: =G33/$G$52 -> 0.0066663413 | N33: =+D33 -> Marketing | P33: =SUM(W33:EY33)-G33 -> 0 | R33: =EOMONTH(S33,-12)+1 -> 45658 | S33: ='Summary & Assumptions'!H44-1 -> 46022 | T33: =DATEDIF(R33,S33+1,"m") -> 12 | W33: =+IF(AND(W$8>=$R33,W$8<=$S33),$G33/$T33,0) -> 0 | X33: =+IF(AND(X$8>=$R33,X$8<=$S33),$G33/$T33,0) -> 0 | Y33: =+IF(AND(Y$8>=$R33,Y$8<=$S33),$G33/$T33,0) -> 0 | Z33: =+IF(AND(Z$8>=$R33,Z$8<=$S33),$G33/$T33,0) -> 0 | AA33: =+IF(AND(AA$8>=$R33,AA$8<=$S33),$G33/$T33,0) -> 0 | AB33: =+IF(AND(AB$8>=$R33,AB$8<=$S33),$G33/$T33,0) -> 0 | AC33: =+IF(AND(AC$8>=$R33,AC$8<=$S33),$G33/$T33,0) -> 0 | AD33: =+IF(AND(AD$8>=$R33,AD$8<=$S33),$G33/$T33,0) -> 0 | ... EY33: =+IF(AND(EY$8>=$R33,EY$8<=$S33),$G33/$T33,0) -> 0
D34: ='Soft Cost Detail'!C83 -> Leasing Commissions | G34: ='Soft Cost Detail'!E83 -> 0 | H34: =G34/'Summary & Assumptions'!$D$34 -> 0 | I34: =G34/'Summary & Assumptions'!$H$11 -> 0 | J34: =G34/'Summary & Assumptions'!$H$16 -> 0 | K34: =G34/$G$52 -> 0 | N34: =+D34 -> Leasing Commissions | P34: =SUM(W34:EY34)-G34 -> 0 | R34: ='Summary & Assumptions'!$H$38 -> 44713 | S34: =EOMONTH(R34,T34-1) -> 44895 | T34: 6 | W34: =+IF(AND(W$8>=$R34,W$8<=$S34),$G34/$T34,0) -> 0 | X34: =+IF(AND(X$8>=$R34,X$8<=$S34),$G34/$T34,0) -> 0 | Y34: =+IF(AND(Y$8>=$R34,Y$8<=$S34),$G34/$T34,0) -> 0 | Z34: =+IF(AND(Z$8>=$R34,Z$8<=$S34),$G34/$T34,0) -> 0 | AA34: =+IF(AND(AA$8>=$R34,AA$8<=$S34),$G34/$T34,0) -> 0 | AB34: =+IF(AND(AB$8>=$R34,AB$8<=$S34),$G34/$T34,0) -> 0 | AC34: =+IF(AND(AC$8>=$R34,AC$8<=$S34),$G34/$T34,0) -> 0 | AD34: =+IF(AND(AD$8>=$R34,AD$8<=$S34),$G34/$T34,0) -> 0 | ... EY34: =+IF(AND(EY$8>=$R34,EY$8<=$S34),$G34/$T34,0) -> 0
D35: ='Soft Cost Detail'!C84 -> Tenant Buyout Cost | G35: ='Soft Cost Detail'!E84 -> 1000000 | H35: =G35/'Summary & Assumptions'!$D$34 -> 6944.4444 | I35: =G35/'Summary & Assumptions'!$H$11 -> 7.5321056 | J35: =G35/'Summary & Assumptions'!$H$16 -> 9.811617 | K35: =G35/$G$52 -> 0.016976524 | N35: =+D35 -> Tenant Buyout Cost | P35: =SUM(W35:EY35)-G35 -> 0 | R35: ='Summary & Assumptions'!$H$38 -> 44713 | S35: =EOMONTH(R35,T35-1) -> 44895 | T35: 6 | W35: =+IF(AND(W$8>=$R35,W$8<=$S35),$G35/$T35,0) -> 166666.67 | X35: =+IF(AND(X$8>=$R35,X$8<=$S35),$G35/$T35,0) -> 166666.67 | Y35: =+IF(AND(Y$8>=$R35,Y$8<=$S35),$G35/$T35,0) -> 166666.67 | Z35: =+IF(AND(Z$8>=$R35,Z$8<=$S35),$G35/$T35,0) -> 166666.67 | AA35: =+IF(AND(AA$8>=$R35,AA$8<=$S35),$G35/$T35,0) -> 166666.67 | AB35: =+IF(AND(AB$8>=$R35,AB$8<=$S35),$G35/$T35,0) -> 166666.67 | AC35: =+IF(AND(AC$8>=$R35,AC$8<=$S35),$G35/$T35,0) -> 0 | AD35: =+IF(AND(AD$8>=$R35,AD$8<=$S35),$G35/$T35,0) -> 0 | ... EY35: =+IF(AND(EY$8>=$R35,EY$8<=$S35),$G35/$T35,0) -> 0
D36: ='Soft Cost Detail'!C85 -> Tenant Improvements (Retail) | G36: ='Soft Cost Detail'!E85 -> 0 | H36: =G36/'Summary & Assumptions'!$D$34 -> 0 | I36: =G36/'Summary & Assumptions'!$H$11 -> 0 | J36: =G36/'Summary & Assumptions'!$H$16 -> 0 | K36: =G36/$G$52 -> 0 | N36: =+D36 -> Tenant Improvements (Retail) | P36: =SUM(W36:EY36)-G36 -> 0 | R36: ='Summary & Assumptions'!$H$38 -> 44713 | S36: =EOMONTH(R36,T36-1) -> 44895 | T36: 6 | W36: =+IF(AND(W$8>=$R36,W$8<=$S36),$G36/$T36,0) -> 0 | X36: =+IF(AND(X$8>=$R36,X$8<=$S36),$G36/$T36,0) -> 0 | Y36: =+IF(AND(Y$8>=$R36,Y$8<=$S36),$G36/$T36,0) -> 0 | Z36: =+IF(AND(Z$8>=$R36,Z$8<=$S36),$G36/$T36,0) -> 0 | AA36: =+IF(AND(AA$8>=$R36,AA$8<=$S36),$G36/$T36,0) -> 0 | AB36: =+IF(AND(AB$8>=$R36,AB$8<=$S36),$G36/$T36,0) -> 0 | AC36: =+IF(AND(AC$8>=$R36,AC$8<=$S36),$G36/$T36,0) -> 0 | AD36: =+IF(AND(AD$8>=$R36,AD$8<=$S36),$G36/$T36,0) -> 0 | ... EY36: =+IF(AND(EY$8>=$R36,EY$8<=$S36),$G36/$T36,0) -> 0
D37: ='Soft Cost Detail'!C86 -> Operating Reserve | G37: =P88 -> 1235346.3 | H37: =G37/'Summary & Assumptions'!$D$34 -> 8578.794 | I37: =G37/'Summary & Assumptions'!$H$11 -> 9.3047591 | J37: =G37/'Summary & Assumptions'!$H$16 -> 12.120745 | K37: =G37/$G$52 -> 0.020971886 | N37: =+D37 -> Operating Reserve | P37: =SUM(W37:EY37)-G37 -> 0 | W37: =W88 -> 0 | X37: =X88 -> 29413.008 | Y37: =Y88 -> 29413.008 | Z37: =Z88 -> 29413.008 | AA37: =AA88 -> 29413.008 | AB37: =AB88 -> 29413.008 | AC37: =AC88 -> 29413.008 | AD37: =AD88 -> 29413.008 | ... EY37: =EY88 -> 0
D38: ='Soft Cost Detail'!C87 -> Soft Cost Contingency | G38: ='Soft Cost Detail'!E87 -> 296903.73 | H38: =G38/'Summary & Assumptions'!$D$34 -> 2061.8315 | I38: =G38/'Summary & Assumptions'!$H$11 -> 2.2363103 | J38: =G38/'Summary & Assumptions'!$H$16 -> 2.9131057 | K38: =G38/$G$52 -> 0.0050403932 | N38: =+D38 -> Soft Cost Contingency | P38: =SUM(W38:EY38)-G38 -> 0 | R38: ='Summary & Assumptions'!$H$38 -> 44713 | S38: =EOMONTH(R38,T38-1) -> 44895 | T38: 6 | W38: =+IF(AND(W$8>=$R38,W$8<=$S38),$G38/$T38,0) -> 49483.956 | X38: =+IF(AND(X$8>=$R38,X$8<=$S38),$G38/$T38,0) -> 49483.956 | Y38: =+IF(AND(Y$8>=$R38,Y$8<=$S38),$G38/$T38,0) -> 49483.956 | Z38: =+IF(AND(Z$8>=$R38,Z$8<=$S38),$G38/$T38,0) -> 49483.956 | AA38: =+IF(AND(AA$8>=$R38,AA$8<=$S38),$G38/$T38,0) -> 49483.956 | AB38: =+IF(AND(AB$8>=$R38,AB$8<=$S38),$G38/$T38,0) -> 49483.956 | AC38: =+IF(AND(AC$8>=$R38,AC$8<=$S38),$G38/$T38,0) -> 0 | AD38: =+IF(AND(AD$8>=$R38,AD$8<=$S38),$G38/$T38,0) -> 0 | ... EY38: =+IF(AND(EY$8>=$R38,EY$8<=$S38),$G38/$T38,0) -> 0
D39: Total Soft Costs | G39: =SUM(G26:G38) -> 5362022.6 | H39: =SUM(H26:H38) -> 37236.268 | I39: =SUM(I26:I38) -> 40.38732 | J39: =SUM(J26:J38) -> 52.610112 | K39: =SUM(K26:K38) -> 0.091028503 | N39: =+D39 -> Total Soft Costs | O39: =SUM(W39:EY39) -> 5362022.6 | P39: =SUM(P26:P38) -> 0 | W39: =SUM(W26:W38) -> 497817.29 | X39: =SUM(X26:X38) -> 527230.3 | Y39: =SUM(Y26:Y38) -> 527230.3 | Z39: =SUM(Z26:Z38) -> 527230.3 | AA39: =SUM(AA26:AA38) -> 527230.3 | AB39: =SUM(AB26:AB38) -> 527230.3 | AC39: =SUM(AC26:AC38) -> 29413.008 | AD39: =SUM(AD26:AD38) -> 29413.008 | ... EY39: =SUM(EY26:EY38) -> 0
D41: Total Unlevered Costs | G41: =G39+G23+G13 -> 54116596 | H41: =+H39+H23+H13 -> 375809.7 | I41: =+I39+I23+I13 -> 407.61192 | J41: =+J39+J23+J13 -> 530.97131 | K41: =+K39+K23+K13 -> 0.91871167 | N41: =+D41 -> Total Unlevered Costs | O41: =SUM(W41:EY41) -> 54116596 | P41: =+P39+P23+P13 -> 0 | W41: =+W39+W23+W13 -> 29297817 | X41: =+X39+X23+X13 -> 527230.3 | Y41: =+Y39+Y23+Y13 -> 527230.3 | Z41: =+Z39+Z23+Z13 -> 527230.3 | AA41: =+AA39+AA23+AA13 -> 527230.3 | AB41: =+AB39+AB23+AB13 -> 527230.3 | AC41: =+AC39+AC23+AC13 -> 29413.008 | AD41: =+AD39+AD23+AD13 -> 29413.008 | ... EY41: =+EY39+EY23+EY13 -> 0
D43: Financing Costs | N43: =+D43 -> Financing Costs
D44: Bridge Loan Lender Origination Fee | E44: 0.005 | G44: ='Summary & Assumptions'!$L$24*'Budget & Draw Schedule'!E44 -> 79200 | H44: =G44/'Summary & Assumptions'!$D$34 -> 550 | I44: =G44/'Summary & Assumptions'!$H$11 -> 0.59654276 | J44: =G44/'Summary & Assumptions'!$H$16 -> 0.77708006 | K44: =G44/$G$52 -> 0.0013445407 | N44: =D44 -> Bridge Loan Lender Origination Fee | P44: =SUM(W44:EY44)-G44 -> 0 | R44: ='Summary & Assumptions'!$H$38 -> 44713 | S44: ='Summary & Assumptions'!$H$38 -> 44713 | T44: 1 | W44: =+IF(AND(W$8>=$R44,W$8<=$S44),$G$44/$T44,0) -> 79200 | X44: =+IF(AND(X$8>=$R44,X$8<=$S44),$G$44/$T44,0) -> 0 | Y44: =+IF(AND(Y$8>=$R44,Y$8<=$S44),$G$44/$T44,0) -> 0 | Z44: =+IF(AND(Z$8>=$R44,Z$8<=$S44),$G$44/$T44,0) -> 0 | AA44: =+IF(AND(AA$8>=$R44,AA$8<=$S44),$G$44/$T44,0) -> 0 | AB44: =+IF(AND(AB$8>=$R44,AB$8<=$S44),$G$44/$T44,0) -> 0 | AC44: =+IF(AND(AC$8>=$R44,AC$8<=$S44),$G$44/$T44,0) -> 0 | AD44: =+IF(AND(AD$8>=$R44,AD$8<=$S44),$G$44/$T44,0) -> 0 | ... EY44: =+IF(AND(EY$8>=$R44,EY$8<=$S44),$G$44/$T44,0) -> 0
D45: Bridge Loan Broker Fee | E45: 0.0075 | G45: ='Summary & Assumptions'!$L$24*'Budget & Draw Schedule'!E45 -> 118800 | H45: =G45/'Summary & Assumptions'!$D$34 -> 825 | I45: =G45/'Summary & Assumptions'!$H$11 -> 0.89481415 | J45: =G45/'Summary & Assumptions'!$H$16 -> 1.1656201 | K45: =G45/$G$52 -> 0.002016811 | N45: =D45 -> Bridge Loan Broker Fee | P45: =SUM(W45:EY45)-G45 -> 0 | R45: ='Summary & Assumptions'!$H$38 -> 44713 | S45: ='Summary & Assumptions'!$H$38 -> 44713 | T45: 1 | W45: =+IF(AND(W$8>=$R45,W$8<=$S45),$G$45/$T45,0) -> 118800 | X45: =+IF(AND(X$8>=$R45,X$8<=$S45),#REF!/$T45,0) -> 0 | Y45: =+IF(AND(Y$8>=$R45,Y$8<=$S45),#REF!/$T45,0) -> 0 | Z45: =+IF(AND(Z$8>=$R45,Z$8<=$S45),#REF!/$T45,0) -> 0 | AA45: =+IF(AND(AA$8>=$R45,AA$8<=$S45),#REF!/$T45,0) -> 0 | AB45: =+IF(AND(AB$8>=$R45,AB$8<=$S45),#REF!/$T45,0) -> 0 | AC45: =+IF(AND(AC$8>=$R45,AC$8<=$S45),#REF!/$T45,0) -> 0 | AD45: =+IF(AND(AD$8>=$R45,AD$8<=$S45),#REF!/$T45,0) -> 0 | AE45: =+IF(AND(AE$8>=$R45,AE$8<=$S45),#REF!/$T45,0) -> 0 | ... EY45: =+IF(AND(EY$8>=$R45,EY$8<=$S45),#REF!/$T45,0) -> 0
D46: Senior Construction Lender Origination Fee | E46: 0.01 | G46: ='Summary & Assumptions'!M14*'Summary & Assumptions'!L28*'Budget & Draw Schedule'!E46 -> 324699.58 | H46: =G46/'Summary & Assumptions'!$D$34 -> 2254.8582 | I46: =G46/'Summary & Assumptions'!$H$11 -> 2.4456715 | J46: =G46/'Summary & Assumptions'!$H$16 -> 3.1858279 | K46: =G46/$G$52 -> 0.00551227 | N46: =+D46 -> Senior Construction Lender Origination Fee | P46: =SUM(W46:EY46)-G46 -> 0 | R46: 45473 | S46: =R46 -> 45473 | T46: 1 | W46: =+IF(AND(W$8>=$R46,W$8<=$S46),$G46/$T46,0) -> 0 | X46: =+IF(AND(X$8>=$R46,X$8<=$S46),$G46/$T46,0) -> 0 | Y46: =+IF(AND(Y$8>=$R46,Y$8<=$S46),$G46/$T46,0) -> 0 | Z46: =+IF(AND(Z$8>=$R46,Z$8<=$S46),$G46/$T46,0) -> 0 | AA46: =+IF(AND(AA$8>=$R46,AA$8<=$S46),$G46/$T46,0) -> 0 | AB46: =+IF(AND(AB$8>=$R46,AB$8<=$S46),$G46/$T46,0) -> 0 | AC46: =+IF(AND(AC$8>=$R46,AC$8<=$S46),$G46/$T46,0) -> 0 | AD46: =+IF(AND(AD$8>=$R46,AD$8<=$S46),$G46/$T46,0) -> 0 | ... EY46: =+IF(AND(EY$8>=$R46,EY$8<=$S46),$G46/$T46,0) -> 0
D47: Other Financing and Closing Costs | G47: 250000 | H47: =G47/'Summary & Assumptions'!$D$34 -> 1736.1111 | I47: =G47/'Summary & Assumptions'!$H$11 -> 1.8830264 | J47: =G47/'Summary & Assumptions'!$H$16 -> 2.4529042 | K47: =G47/$G$52 -> 0.0042441309 | N47: =+D47 -> Other Financing and Closing Costs | P47: =SUM(W47:EY47)-G47 -> 0 | R47: ='Summary & Assumptions'!$H$38 -> 44713 | S47: ='Summary & Assumptions'!$H$38 -> 44713 | T47: 1 | W47: =+IF(AND(W$8>=$R47,W$8<=$S47),$G47/$T47,0) -> 250000 | X47: =+IF(AND(X$8>=$R47,X$8<=$S47),$G47/$T47,0) -> 0 | Y47: =+IF(AND(Y$8>=$R47,Y$8<=$S47),$G47/$T47,0) -> 0 | Z47: =+IF(AND(Z$8>=$R47,Z$8<=$S47),$G47/$T47,0) -> 0 | AA47: =+IF(AND(AA$8>=$R47,AA$8<=$S47),$G47/$T47,0) -> 0 | AB47: =+IF(AND(AB$8>=$R47,AB$8<=$S47),$G47/$T47,0) -> 0 | AC47: =+IF(AND(AC$8>=$R47,AC$8<=$S47),$G47/$T47,0) -> 0 | AD47: =+IF(AND(AD$8>=$R47,AD$8<=$S47),$G47/$T47,0) -> 0 | ... EY47: =+IF(AND(EY$8>=$R47,EY$8<=$S47),$G47/$T47,0) -> 0
D48: Senior Debt Total Interest | G48: =P85 -> 6505033.1 | H48: =G48/'Summary & Assumptions'!$D$34 -> 45173.841 | I48: =G48/'Summary & Assumptions'!$H$11 -> 48.996597 | J48: =G48/'Summary & Assumptions'!$H$16 -> 63.824893 | K48: =G48/$G$52 -> 0.11043285 | N48: =+D48 -> Senior Debt Total Interest | P48: =SUM(W48:EY48)-G48 -> 0 | R48: Per Schedule | W48: =W85 -> 0 | X48: =X85 -> 75900 | Y48: =Y85 -> 75900 | Z48: =Z85 -> 75900 | AA48: =AA85 -> 75900 | AB48: =AB85 -> 75900 | AC48: =AC85 -> 75900 | AD48: =AD85 -> 75900 | ... EY48: =EY85 -> 0
D49: NOI Offset to Interest | G49: =-P89 -> -2489453.8 | H49: =G49/'Summary & Assumptions'!$D$34 -> -17287.874 | I49: =G49/'Summary & Assumptions'!$H$11 -> -18.750829 | J49: =G49/'Summary & Assumptions'!$H$16 -> -24.425567 | K49: =G49/$G$52 -> -0.042262271 | N49: =+D49 -> NOI Offset to Interest | P49: =SUM(W49:EY49)-G49 -> 0 | R49: Per Schedule | W49: =-W89 -> 0 | X49: =-X89 -> 0 | Y49: =-Y89 -> 0 | Z49: =-Z89 -> 0 | AA49: =-AA89 -> 0 | AB49: =-AB89 -> 0 | AC49: =-AC89 -> 0 | AD49: =-AD89 -> 0 | ... EY49: =-EY89 -> 0
D50: Total Financing Costs | G50: =SUM(G44:G49) -> 4788278.9 | H50: =SUM(H44:H49) -> 33251.937 | I50: =SUM(I44:I49) -> 36.065823 | J50: =SUM(J44:J49) -> 46.980759 | K50: =SUM(K44:K49) -> 0.08128833 | N50: =+D50 -> Total Financing Costs | O50: =SUM(W50:EY50) -> 4788278.9 | P50: =SUM(P44:P49) -> 0 | W50: =SUM(W44:W49) -> 448000 | X50: =SUM(X44:X49) -> 75900 | Y50: =SUM(Y44:Y49) -> 75900 | Z50: =SUM(Z44:Z49) -> 75900 | AA50: =SUM(AA44:AA49) -> 75900 | AB50: =SUM(AB44:AB49) -> 75900 | AC50: =SUM(AC44:AC49) -> 75900 | AD50: =SUM(AD44:AD49) -> 75900 | ... EY50: =SUM(EY44:EY49) -> 0
D52: Total Project Budget | G52: =+G50+G41 -> 58904875 | H52: =+H50+H41 -> 409061.63 | I52: =+I50+I41 -> 443.67774 | J52: =+J50+J41 -> 577.95207 | K52: =+K50+K41 -> 1 | N52: =+D52 -> Total Project Budget | O52: =SUM(W52:EY52) -> 58904875 | P52: =+P50+P41 -> 0 | W52: =+W50+W41 -> 29745817 | X52: =+X50+X41 -> 603130.3 | Y52: =+Y50+Y41 -> 603130.3 | Z52: =+Z50+Z41 -> 603130.3 | AA52: =+AA50+AA41 -> 603130.3 | AB52: =+AB50+AB41 -> 603130.3 | AC52: =+AC50+AC41 -> 105313.01 | AD52: =+AD50+AD41 -> 105313.01 | ... EY52: =+EY50+EY41 -> 0
D54: Total Land Costs | G54: =+G13 -> 28800000 | N54: =+D54 -> Total Land Costs | P54: =SUM(W54:EY54)-G54 -> 0 | W54: =+W13 -> 28800000 | X54: =+X13 -> 0 | Y54: =+Y13 -> 0 | Z54: =+Z13 -> 0 | AA54: =+AA13 -> 0 | AB54: =+AB13 -> 0 | AC54: =+AC13 -> 0 | AD54: =+AD13 -> 0 | ... EY54: =+EY13 -> 0
D55: Total Hard Costs | G55: =+G23 -> 19954574 | N55: =+D55 -> Total Hard Costs | P55: =SUM(W55:EY55)-G55 -> 0 | W55: =+W23 -> 0 | X55: =+X23 -> 0 | Y55: =+Y23 -> 0 | Z55: =+Z23 -> 0 | AA55: =+AA23 -> 0 | AB55: =+AB23 -> 0 | AC55: =+AC23 -> 0 | AD55: =+AD23 -> 0 | ... EY55: =+EY23 -> 0
D56: Total Soft Costs | G56: =+G39 -> 5362022.6 | N56: =+D56 -> Total Soft Costs | P56: =SUM(W56:EY56)-G56 -> 0 | W56: =+W39 -> 497817.29 | X56: =+X39 -> 527230.3 | Y56: =+Y39 -> 527230.3 | Z56: =+Z39 -> 527230.3 | AA56: =+AA39 -> 527230.3 | AB56: =+AB39 -> 527230.3 | AC56: =+AC39 -> 29413.008 | AD56: =+AD39 -> 29413.008 | ... EY56: =+EY39 -> 0
D57: Financing Costs | G57: =+G50 -> 4788278.9 | N57: =+D57 -> Financing Costs | P57: =SUM(W57:EY57)-G57 -> 0 | W57: =+W50 -> 448000 | X57: =+X50 -> 75900 | Y57: =+Y50 -> 75900 | Z57: =+Z50 -> 75900 | AA57: =+AA50 -> 75900 | AB57: =+AB50 -> 75900 | AC57: =+AC50 -> 75900 | AD57: =+AD50 -> 75900 | ... EY57: =+EY50 -> 0
D58: Total | G58: =SUM(G54:G57) -> 58904875 | N58: =+D58 -> Total | P58: =SUM(P54:P57) -> 0 | R58: =+IF(ROUND(P58,0)=0,"True","False") -> True | W58: =SUM(W54:W57) -> 29745817 | X58: =SUM(X54:X57) -> 603130.3 | Y58: =SUM(Y54:Y57) -> 603130.3 | Z58: =SUM(Z54:Z57) -> 603130.3 | AA58: =SUM(AA54:AA57) -> 603130.3 | AB58: =SUM(AB54:AB57) -> 603130.3 | AC58: =SUM(AC54:AC57) -> 105313.01 | AD58: =SUM(AD54:AD57) -> 105313.01 | ... EY58: =SUM(EY54:EY57) -> 0
N60: Total Equity Funded in Period | P60: =+SUM(W60:EY60) -> 26434917 | R60: =IF(ROUND('Summary & Assumptions'!M8,0)=ROUND('Budget & Draw Schedule'!P60,0),"True","False") -> True | W60: =+W67 -> 13905817 | X60: =+X67 -> 603130.3 | Y60: =+Y67 -> 603130.3 | Z60: =+Z67 -> 603130.3 | AA60: =+AA67 -> 603130.3 | AB60: =+AB67 -> 603130.3 | AC60: =+AC67 -> 105313.01 | AD60: =+AD67 -> 105313.01 | ... EY60: =+EY67 -> 0
N61: Total Construction Debt Funded in Period | P61: =+SUM(W61:EY61) -> 32469958 | R61: =IF(ROUND('Summary & Assumptions'!M7,0)=ROUND('Budget & Draw Schedule'!P61,0),"True","False") -> True | W61: =+W73 -> 15840000 | X61: =+X73 -> 0 | Y61: =+Y73 -> 0 | Z61: =+Z73 -> 0 | AA61: =+AA73 -> 0 | AB61: =+AB73 -> 0 | AC61: =+AC73 -> 0 | AD61: =+AD73 -> 0 | ... EY61: =+EY73 -> 0
N62: Total $ Funded in Development Period | P62: =SUM(P60:P61) -> 58904875 | W62: =SUM(W60:W61) -> 29745817 | X62: =SUM(X60:X61) -> 603130.3 | Y62: =SUM(Y60:Y61) -> 603130.3 | Z62: =SUM(Z60:Z61) -> 603130.3 | AA62: =SUM(AA60:AA61) -> 603130.3 | AB62: =SUM(AB60:AB61) -> 603130.3 | AC62: =SUM(AC60:AC61) -> 105313.01 | AD62: =SUM(AD60:AD61) -> 105313.01 | ... EY62: =SUM(EY60:EY61) -> 0
N63: CHECK | P63: =+SUM(W63:EY63) -> 0 | W63: =+W52-W62 -> 0 | X63: =+X52-X62 -> 0 | Y63: =+Y52-Y62 -> 0 | Z63: =+Z52-Z62 -> 0 | AA63: =+AA52-AA62 -> 0 | AB63: =+AB52-AB62 -> 0 | AC63: =+AC52-AC62 -> 0 | AD63: =+AD52-AD62 -> 0 | ... EY63: =+EY52-EY62 -> 0
N65: Equity Funding
N66: Available Equity Balance | W66: ='Summary & Assumptions'!$M$8 -> 26434917 | X66: =+W68 -> 12529100 | Y66: =+X68 -> 11925970 | Z66: =+Y68 -> 11322840 | AA66: =+Z68 -> 10719709 | AB66: =+AA68 -> 10116579 | AC66: =+AB68 -> 9513448.6 | AD66: =+AC68 -> 9408135.6 | AE66: =+AD68 -> 9302822.6 | ... EY66: =+EX68 -> 0
N67: Equity Funded in Period | P67: =+SUM(W67:EY67) -> 26434917 | R67: =+IF(ROUND(P67,0)=ROUND(W66,0),"True","False") -> True | W67: =MIN('Summary & Assumptions'!K8,W52) -> 13905817 | X67: =MIN(X66,X52) -> 603130.3 | Y67: =MIN(Y66,Y52) -> 603130.3 | Z67: =MIN(Z66,Z52) -> 603130.3 | AA67: =MIN(AA66,AA52) -> 603130.3 | AB67: =MIN(AB66,AB52) -> 603130.3 | AC67: =MIN(AC66,AC52) -> 105313.01 | AD67: =MIN(AD66,AD52) -> 105313.01 | AE67: =MIN(AE66,AE52) -> 105313.01 | ... EY67: =MIN(EY66,EY52) -> 0
N68: Ending Available Equity Balance | W68: =+W66-W67 -> 12529100 | X68: =+X66-X67 -> 11925970 | Y68: =+Y66-Y67 -> 11322840 | Z68: =+Z66-Z67 -> 10719709 | AA68: =+AA66-AA67 -> 10116579 | AB68: =+AB66-AB67 -> 9513448.6 | AC68: =+AC66-AC67 -> 9408135.6 | AD68: =+AD66-AD67 -> 9302822.6 | ... EY68: =+EY66-EY67 -> 0
N69: Cumulative Balance | P69: =MAX(W69:EY69) -> 26434917 | W69: =SUM($W$67:W67) -> 13905817 | X69: =SUM($W$67:X67) -> 14508948 | Y69: =SUM($W$67:Y67) -> 15112078 | Z69: =SUM($W$67:Z67) -> 15715208 | AA69: =SUM($W$67:AA67) -> 16318338 | AB69: =SUM($W$67:AB67) -> 16921469 | AC69: =SUM($W$67:AC67) -> 17026782 | AD69: =SUM($W$67:AD67) -> 17132095 | ... EY69: =SUM($W$67:EY67) -> 26434917
N71: Senior Debt Funding
N72: Senior Debt Available to Fund | W72: ='Summary & Assumptions'!K6 -> 15840000 | X72: =+W76 -> 0 | Y72: =+X76 -> 0 | Z72: =+Y76 -> 0 | AA72: =+Z76 -> 0 | AB72: =+AA76 -> 0 | AC72: =+AB76 -> 0 | AD72: =+AC76 -> 0 | AE72: =+AD76 -> 0 | ... EY72: =+EX76 -> 1.7462298e-09
N73: Senior Debt Funded in Period | P73: =+SUM(W73:EY73) -> 32469958 | W73: =+MIN(W72,W52-W67) -> 15840000 | X73: =+MIN(X72,X52-X67) -> 0 | Y73: =+MIN(Y72,Y52-Y67) -> 0 | Z73: =+MIN(Z72,Z52-Z67) -> 0 | AA73: =+MIN(AA72,AA52-AA67) -> 0 | AB73: =+MIN(AB72,AB52-AB67) -> 0 | AC73: =+MIN(AC72,AC52-AC67) -> 0 | AD73: =+MIN(AD72,AD52-AD67) -> 0 | ... EY73: =+MIN(EY72,EY52-EY67) -> 0
N74: Construction Loan Funding | P74: =+SUM(W74:EY74) -> 32469958 | W74: =IF(W$7='Summary & Assumptions'!$H$39,'Summary & Assumptions'!$L$29,0) -> 0 | X74: =IF(X$7='Summary & Assumptions'!$H$39,'Summary & Assumptions'!$L$29,0) -> 0 | Y74: =IF(Y$7='Summary & Assumptions'!$H$39,'Summary & Assumptions'!$L$29,0) -> 0 | Z74: =IF(Z$7='Summary & Assumptions'!$H$39,'Summary & Assumptions'!$L$29,0) -> 0 | AA74: =IF(AA$7='Summary & Assumptions'!$H$39,'Summary & Assumptions'!$L$29,0) -> 0 | AB74: =IF(AB$7='Summary & Assumptions'!$H$39,'Summary & Assumptions'!$L$29,0) -> 0 | AC74: =IF(AC$7='Summary & Assumptions'!$H$39,'Summary & Assumptions'!$L$29,0) -> 0 | AD74: =IF(AD$7='Summary & Assumptions'!$H$39,'Summary & Assumptions'!$L$29,0) -> 0 | ... EY74: =IF(EY$7='Summary & Assumptions'!$H$39,'Summary & Assumptions'!$L$29,0) -> 0
N75: Repayment of Bridge Loan | P75: =+SUM(W75:EY75) -> -15840000 | W75: =IF(W$7='Summary & Assumptions'!$H$39,-('Budget & Draw Schedule'!$W$73),0) -> 0 | X75: =IF(X$7='Summary & Assumptions'!$H$39,-('Budget & Draw Schedule'!$W$73),0) -> 0 | Y75: =IF(Y$7='Summary & Assumptions'!$H$39,-('Budget & Draw Schedule'!$W$73),0) -> 0 | Z75: =IF(Z$7='Summary & Assumptions'!$H$39,-('Budget & Draw Schedule'!$W$73),0) -> 0 | AA75: =IF(AA$7='Summary & Assumptions'!$H$39,-('Budget & Draw Schedule'!$W$73),0) -> 0 | AB75: =IF(AB$7='Summary & Assumptions'!$H$39,-('Budget & Draw Schedule'!$W$73),0) -> 0 | AC75: =IF(AC$7='Summary & Assumptions'!$H$39,-('Budget & Draw Schedule'!$W$73),0) -> 0 | AD75: =IF(AD$7='Summary & Assumptions'!$H$39,-('Budget & Draw Schedule'!$W$73),0) -> 0 | ... EY75: =IF(EY$7='Summary & Assumptions'!$H$39,-('Budget & Draw Schedule'!$W$73),0) -> 0
N76: Senior Debt Remaining to be Funded | P76: =MIN(AT76:EY76) -> 0 | W76: =+W72-W73+W74+W75 -> 0 | X76: =+X72-X73+X74+X75 -> 0 | Y76: =+Y72-Y73+Y74+Y75 -> 0 | Z76: =+Z72-Z73+Z74+Z75 -> 0 | AA76: =+AA72-AA73+AA74+AA75 -> 0 | AB76: =+AB72-AB73+AB74+AB75 -> 0 | AC76: =+AC72-AC73+AC74+AC75 -> 0 | AD76: =+AD72-AD73+AD74+AD75 -> 0 | ... EY76: =+EY72-EY73+EY74+EY75 -> 1.7462298e-09
N77: Cumulative Debt Funded | P77: =MAX(W77:EY77) -> 32469958 | W77: =IF(W$7<'Summary & Assumptions'!$H$39,'Summary & Assumptions'!$L$24,'Summary & Assumptions'!$L$29) -> 15840000 | X77: =IF(X$7<'Summary & Assumptions'!$H$39,'Summary & Assumptions'!$L$24,'Summary & Assumptions'!$L$29) -> 15840000 | Y77: =IF(Y$7<'Summary & Assumptions'!$H$39,'Summary & Assumptions'!$L$24,'Summary & Assumptions'!$L$29) -> 15840000 | Z77: =IF(Z$7<'Summary & Assumptions'!$H$39,'Summary & Assumptions'!$L$24,'Summary & Assumptions'!$L$29) -> 15840000 | AA77: =IF(AA$7<'Summary & Assumptions'!$H$39,'Summary & Assumptions'!$L$24,'Summary & Assumptions'!$L$29) -> 15840000 | AB77: =IF(AB$7<'Summary & Assumptions'!$H$39,'Summary & Assumptions'!$L$24,'Summary & Assumptions'!$L$29) -> 15840000 | AC77: =IF(AC$7<'Summary & Assumptions'!$H$39,'Summary & Assumptions'!$L$24,'Summary & Assumptions'!$L$29) -> 15840000 | AD77: =IF(AD$7<'Summary & Assumptions'!$H$39,'Summary & Assumptions'!$L$24,'Summary & Assumptions'!$L$29) -> 15840000 | ... EY77: =IF(EY$7<'Summary & Assumptions'!$H$39,'Summary & Assumptions'!$L$24,'Summary & Assumptions'!$L$29) -> 32469958
N79: Construction Interest
N80: Libor Forward Curve (04/01/21) | W80: =IFERROR(SUMIF(LIBOR!$C$4:$DS$4,EOMONTH('Budget & Draw Schedule'!W8,0),LIBOR!$C$5:$DS$5),0) -> 0.0010088 | X80: =IFERROR(SUMIF(LIBOR!$C$4:$DS$4,'Budget & Draw Schedule'!X8,LIBOR!$C$5:$DS$5),0) -> 0.0010073 | Y80: =IFERROR(SUMIF(LIBOR!$C$4:$DS$4,'Budget & Draw Schedule'!Y8,LIBOR!$C$5:$DS$5),0) -> 0.0010217 | Z80: =IFERROR(SUMIF(LIBOR!$C$4:$DS$4,'Budget & Draw Schedule'!Z8,LIBOR!$C$5:$DS$5),0) -> 0.0010801 | AA80: =IFERROR(SUMIF(LIBOR!$C$4:$DS$4,'Budget & Draw Schedule'!AA8,LIBOR!$C$5:$DS$5),0) -> 0.0011545 | AB80: =IFERROR(SUMIF(LIBOR!$C$4:$DS$4,'Budget & Draw Schedule'!AB8,LIBOR!$C$5:$DS$5),0) -> 0.0012321 | AC80: =IFERROR(SUMIF(LIBOR!$C$4:$DS$4,'Budget & Draw Schedule'!AC8,LIBOR!$C$5:$DS$5),0) -> 0.0013311 | AD80: =IFERROR(SUMIF(LIBOR!$C$4:$DS$4,'Budget & Draw Schedule'!AD8,LIBOR!$C$5:$DS$5),0) -> 0.001428 | AE80: =IFERROR(SUMIF(LIBOR!$C$4:$DS$4,'Budget & Draw Schedule'!AE8,LIBOR!$C$5:$DS$5),0) -> 0.0015208 | ... EY80: =IFERROR(SUMIF(LIBOR!$C$4:$DS$4,'Budget & Draw Schedule'!EY8,LIBOR!$C$5:$DS$5),0) -> 0
N81: Libor Cap | W81: ='Summary & Assumptions'!$L$31 -> 0.03 | X81: ='Summary & Assumptions'!$L$31 -> 0.03 | Y81: ='Summary & Assumptions'!$L$31 -> 0.03 | Z81: ='Summary & Assumptions'!$L$31 -> 0.03 | AA81: ='Summary & Assumptions'!$L$31 -> 0.03 | AB81: ='Summary & Assumptions'!$L$31 -> 0.03 | AC81: ='Summary & Assumptions'!$L$31 -> 0.03 | AD81: ='Summary & Assumptions'!$L$31 -> 0.03 | ... EY81: ='Summary & Assumptions'!$L$31 -> 0.03
N82: Floor | W82: ='Summary & Assumptions'!$L$32 -> 0.0025 | X82: ='Summary & Assumptions'!$L$32 -> 0.0025 | Y82: ='Summary & Assumptions'!$L$32 -> 0.0025 | Z82: ='Summary & Assumptions'!$L$32 -> 0.0025 | AA82: ='Summary & Assumptions'!$L$32 -> 0.0025 | AB82: ='Summary & Assumptions'!$L$32 -> 0.0025 | AC82: ='Summary & Assumptions'!$L$32 -> 0.0025 | AD82: ='Summary & Assumptions'!$L$32 -> 0.0025 | ... EY82: ='Summary & Assumptions'!$L$32 -> 0.0025
N83: Spread | W83: ='Summary & Assumptions'!$L$34 -> 0.04 | X83: ='Summary & Assumptions'!$L$34 -> 0.04 | Y83: ='Summary & Assumptions'!$L$34 -> 0.04 | Z83: ='Summary & Assumptions'!$L$34 -> 0.04 | AA83: ='Summary & Assumptions'!$L$34 -> 0.04 | AB83: ='Summary & Assumptions'!$L$34 -> 0.04 | AC83: ='Summary & Assumptions'!$L$34 -> 0.04 | AD83: ='Summary & Assumptions'!$L$34 -> 0.04 | ... EY83: ='Summary & Assumptions'!$L$34 -> 0.04
N84: Rate | W84: =IF(W7<='Summary & Assumptions'!$H$39,'Summary & Assumptions'!$L$25,MIN(MAX(W83+W80,W82+W83),W81+W83)) -> 0.0575 | X84: =IF(X7<='Summary & Assumptions'!$H$39,'Summary & Assumptions'!$L$25,MIN(MAX(X83+X80,X82+X83),X81+X83)) -> 0.0575 | Y84: =IF(Y7<='Summary & Assumptions'!$H$39,'Summary & Assumptions'!$L$25,MIN(MAX(Y83+Y80,Y82+Y83),Y81+Y83)) -> 0.0575 | Z84: =IF(Z7<='Summary & Assumptions'!$H$39,'Summary & Assumptions'!$L$25,MIN(MAX(Z83+Z80,Z82+Z83),Z81+Z83)) -> 0.0575 | AA84: =IF(AA7<='Summary & Assumptions'!$H$39,'Summary & Assumptions'!$L$25,MIN(MAX(AA83+AA80,AA82+AA83),AA81+AA83)) -> 0.0575 | AB84: =IF(AB7<='Summary & Assumptions'!$H$39,'Summary & Assumptions'!$L$25,MIN(MAX(AB83+AB80,AB82+AB83),AB81+AB83)) -> 0.0575 | AC84: =IF(AC7<='Summary & Assumptions'!$H$39,'Summary & Assumptions'!$L$25,MIN(MAX(AC83+AC80,AC82+AC83),AC81+AC83)) -> 0.0575 | AD84: =IF(AD7<='Summary & Assumptions'!$H$39,'Summary & Assumptions'!$L$25,MIN(MAX(AD83+AD80,AD82+AD83),AD81+AD83)) -> 0.0575 | ... EY84: =IF(EY7<='Summary & Assumptions'!$H$39,'Summary & Assumptions'!$L$25,MIN(MAX(EY83+EY80,EY82+EY83),EY81+EY83)) -> 0.0425
N85: Interest Expense in Period | P85: =+SUM(W85:EY85) -> 6505033.1 | W85: =IF(W8>'Summary & Assumptions'!$H$51,0,'Budget & Draw Schedule'!V77*'Budget & Draw Schedule'!W84/12) -> 0 | X85: =IF(X8>'Summary & Assumptions'!$H$51,0,'Budget & Draw Schedule'!W77*'Budget & Draw Schedule'!X84/12) -> 75900 | Y85: =IF(Y8>'Summary & Assumptions'!$H$51,0,'Budget & Draw Schedule'!X77*'Budget & Draw Schedule'!Y84/12) -> 75900 | Z85: =IF(Z8>'Summary & Assumptions'!$H$51,0,'Budget & Draw Schedule'!Y77*'Budget & Draw Schedule'!Z84/12) -> 75900 | AA85: =IF(AA8>'Summary & Assumptions'!$H$51,0,'Budget & Draw Schedule'!Z77*'Budget & Draw Schedule'!AA84/12) -> 75900 | AB85: =IF(AB8>'Summary & Assumptions'!$H$51,0,'Budget & Draw Schedule'!AA77*'Budget & Draw Schedule'!AB84/12) -> 75900 | AC85: =IF(AC8>'Summary & Assumptions'!$H$51,0,'Budget & Draw Schedule'!AB77*'Budget & Draw Schedule'!AC84/12) -> 75900 | AD85: =IF(AD8>'Summary & Assumptions'!$H$51,0,'Budget & Draw Schedule'!AC77*'Budget & Draw Schedule'!AD84/12) -> 75900 | ... EY85: =IF(EY8>'Summary & Assumptions'!$H$51,0,'Budget & Draw Schedule'!EX77*'Budget & Draw Schedule'!EY84/12) -> 0
N87: Total NOI | P87: =+SUM(W87:EY87) -> 30993521 | W87: {=INDEX('Monthly CFs'!$G$78:$EI$78,MATCH('Budget & Draw Schedule'!W7,'Monthly CFs'!$G$6:$EI$6,0))} -> 0 | X87: {=INDEX('Monthly CFs'!$G$78:$EI$78,MATCH('Budget & Draw Schedule'!X7,'Monthly CFs'!$G$6:$EI$6,0))} -> -29413.008 | Y87: {=INDEX('Monthly CFs'!$G$78:$EI$78,MATCH('Budget & Draw Schedule'!Y7,'Monthly CFs'!$G$6:$EI$6,0))} -> -29413.008 | Z87: {=INDEX('Monthly CFs'!$G$78:$EI$78,MATCH('Budget & Draw Schedule'!Z7,'Monthly CFs'!$G$6:$EI$6,0))} -> -29413.008 | AA87: {=INDEX('Monthly CFs'!$G$78:$EI$78,MATCH('Budget & Draw Schedule'!AA7,'Monthly CFs'!$G$6:$EI$6,0))} -> -29413.008 | AB87: {=INDEX('Monthly CFs'!$G$78:$EI$78,MATCH('Budget & Draw Schedule'!AB7,'Monthly CFs'!$G$6:$EI$6,0))} -> -29413.008 | AC87: {=INDEX('Monthly CFs'!$G$78:$EI$78,MATCH('Budget & Draw Schedule'!AC7,'Monthly CFs'!$G$6:$EI$6,0))} -> -29413.008 | AD87: {=INDEX('Monthly CFs'!$G$78:$EI$78,MATCH('Budget & Draw Schedule'!AD7,'Monthly CFs'!$G$6:$EI$6,0))} -> -29413.008 | ... EY87: {=INDEX('Monthly CFs'!$G$78:$EI$78,MATCH('Budget & Draw Schedule'!EY7,'Monthly CFs'!$G$6:$EI$6,0))} -> 398358.8
N88: Operating Reserve | P88: =+SUM(W88:EY88) -> 1235346.3 | W88: =-IF(W87<0,W87,0) -> 0 | X88: =-IF(X87<0,X87,0) -> 29413.008 | Y88: =-IF(Y87<0,Y87,0) -> 29413.008 | Z88: =-IF(Z87<0,Z87,0) -> 29413.008 | AA88: =-IF(AA87<0,AA87,0) -> 29413.008 | AB88: =-IF(AB87<0,AB87,0) -> 29413.008 | AC88: =-IF(AC87<0,AC87,0) -> 29413.008 | AD88: =-IF(AD87<0,AD87,0) -> 29413.008 | ... EY88: =-IF(EY87<0,EY87,0) -> 0
N89: NOI to Offset Interest Reserve | P89: =+SUM(W89:EY89) -> 2489453.8 | W89: =MIN(SUM(W87:W88),W85) -> 0 | X89: =MIN(SUM(X87:X88),X85) -> 0 | Y89: =MIN(SUM(Y87:Y88),Y85) -> 0 | Z89: =MIN(SUM(Z87:Z88),Z85) -> 0 | AA89: =MIN(SUM(AA87:AA88),AA85) -> 0 | AB89: =MIN(SUM(AB87:AB88),AB85) -> 0 | AC89: =MIN(SUM(AC87:AC88),AC85) -> 0 | AD89: =MIN(SUM(AD87:AD88),AD85) -> 0 | ... EY89: =MIN(SUM(EY87:EY88),EY85) -> 0
N90: Net Interest Reserve | P90: =+SUM(W90:EY90) -> 4015579.3 | W90: =W85-W89 -> 0 | X90: =X85-X89 -> 75900 | Y90: =Y85-Y89 -> 75900 | Z90: =Z85-Z89 -> 75900 | AA90: =AA85-AA89 -> 75900 | AB90: =AB85-AB89 -> 75900 | AC90: =AC85-AC89 -> 75900 | AD90: =AD85-AD89 -> 75900 | ... EY90: =EY85-EY89 -> 0
N91: Net Cash Flow After Debt Service | P91: =SUMIF($W$3:$EY$3,1,W91:EY91) -> 3419167.3 | W91: =MAX(0,W87-W85) -> 0 | X91: =MAX(0,X87-X85) -> 0 | Y91: =MAX(0,Y87-Y85) -> 0 | Z91: =MAX(0,Z87-Z85) -> 0 | AA91: =MAX(0,AA87-AA85) -> 0 | AB91: =MAX(0,AB87-AB85) -> 0 | AC91: =MAX(0,AC87-AC85) -> 0 | AD91: =MAX(0,AD87-AD85) -> 0 | ... EY91: =MAX(0,EY87-EY85) -> 398358.8
N94: ='Summary & Assumptions'!P25 -> 0.0475 | P94: =SUM(W94:EY94) -> 89819599 | W94: =IF(W8='Summary & Assumptions'!$H$51,'Summary & Assumptions'!$P$29,0) -> 0 | X94: =IF(X8='Summary & Assumptions'!$H$51,'Summary & Assumptions'!$P$29,0) -> 0 | Y94: =IF(Y8='Summary & Assumptions'!$H$51,'Summary & Assumptions'!$P$29,0) -> 0 | Z94: =IF(Z8='Summary & Assumptions'!$H$51,'Summary & Assumptions'!$P$29,0) -> 0 | AA94: =IF(AA8='Summary & Assumptions'!$H$51,'Summary & Assumptions'!$P$29,0) -> 0 | AB94: =IF(AB8='Summary & Assumptions'!$H$51,'Summary & Assumptions'!$P$29,0) -> 0 | AC94: =IF(AC8='Summary & Assumptions'!$H$51,'Summary & Assumptions'!$P$29,0) -> 0 | AD94: =IF(AD8='Summary & Assumptions'!$H$51,'Summary & Assumptions'!$P$29,0) -> 0 | ... EY94: =IF(EY8='Summary & Assumptions'!$H$51,'Summary & Assumptions'!$P$29,0) -> 0
N95: ='Summary & Assumptions'!P26 -> 0.01 | P95: =SUM(W95:EY95) -> -898195.99 | W95: =+IF(W94>0,-$N$95*W94,0) -> 0 | X95: =+IF(X94>0,-$N$95*X94,0) -> 0 | Y95: =+IF(Y94>0,-$N$95*Y94,0) -> 0 | Z95: =+IF(Z94>0,-$N$95*Z94,0) -> 0 | AA95: =+IF(AA94>0,-$N$95*AA94,0) -> 0 | AB95: =+IF(AB94>0,-$N$95*AB94,0) -> 0 | AC95: =+IF(AC94>0,-$N$95*AC94,0) -> 0 | AD95: =+IF(AD94>0,-$N$95*AD94,0) -> 0 | ... EY95: =+IF(EY94>0,-$N$95*EY94,0) -> 0
N96: Repayment of Existing Senior Debt | P96: =SUM(W96:EY96) -> -32469958 | W96: =IF(W8='Summary & Assumptions'!$H$51,-'Summary & Assumptions'!$M$7,0) -> 0 | X96: =IF(X8='Summary & Assumptions'!$H$51,-'Summary & Assumptions'!$M$7,0) -> 0 | Y96: =IF(Y8='Summary & Assumptions'!$H$51,-'Summary & Assumptions'!$M$7,0) -> 0 | Z96: =IF(Z8='Summary & Assumptions'!$H$51,-'Summary & Assumptions'!$M$7,0) -> 0 | AA96: =IF(AA8='Summary & Assumptions'!$H$51,-'Summary & Assumptions'!$M$7,0) -> 0 | AB96: =IF(AB8='Summary & Assumptions'!$H$51,-'Summary & Assumptions'!$M$7,0) -> 0 | AC96: =IF(AC8='Summary & Assumptions'!$H$51,-'Summary & Assumptions'!$M$7,0) -> 0 | AD96: =IF(AD8='Summary & Assumptions'!$H$51,-'Summary & Assumptions'!$M$7,0) -> 0 | ... EY96: =IF(EY8='Summary & Assumptions'!$H$51,-'Summary & Assumptions'!$M$7,0) -> 0
N97: Residual Sale Proceeds | P97: =SUM(P94:P96) -> 56451445 | W97: =SUM(W94:W96) -> 0 | X97: =SUM(X94:X96) -> 0 | Y97: =SUM(Y94:Y96) -> 0 | Z97: =SUM(Z94:Z96) -> 0 | AA97: =SUM(AA94:AA96) -> 0 | AB97: =SUM(AB94:AB96) -> 0 | AC97: =SUM(AC94:AC96) -> 0 | AD97: =SUM(AD94:AD96) -> 0 | ... EY97: =SUM(EY94:EY96) -> 0
N100: Levered Cash Flows
N101: Contributions | P101: =-SUMIF($W$111:$EY$111,"<0") -> 26434917
N102: Distributions (Sale Proceeds + NOI) | P102: =SUMIF($W$111:$EY$111,">0") -> 59870612
N103: Profit | P103: =+P102-P101 -> 33435695
N104: IRR | P104: =XIRR($W$111:$EY$111,$W$8:$EY$8) -> 0.2045109
N105: Equity Multiple | P105: =P102/P101-1 -> 1.2648307
N107: Net Cash Flow After Debt Service | W107: =IF(W8<='Summary & Assumptions'!$H$51,'Budget & Draw Schedule'!W91,0) -> 0 | X107: =IF(X8<='Summary & Assumptions'!$H$51,'Budget & Draw Schedule'!X91,0) -> 0 | Y107: =IF(Y8<='Summary & Assumptions'!$H$51,'Budget & Draw Schedule'!Y91,0) -> 0 | Z107: =IF(Z8<='Summary & Assumptions'!$H$51,'Budget & Draw Schedule'!Z91,0) -> 0 | AA107: =IF(AA8<='Summary & Assumptions'!$H$51,'Budget & Draw Schedule'!AA91,0) -> 0 | AB107: =IF(AB8<='Summary & Assumptions'!$H$51,'Budget & Draw Schedule'!AB91,0) -> 0 | AC107: =IF(AC8<='Summary & Assumptions'!$H$51,'Budget & Draw Schedule'!AC91,0) -> 0 | AD107: =IF(AD8<='Summary & Assumptions'!$H$51,'Budget & Draw Schedule'!AD91,0) -> 0 | ... EY107: =IF(EY8<='Summary & Assumptions'!$H$51,'Budget & Draw Schedule'!EY91,0) -> 0
N108: Residual Proceeds | W108: =W97 -> 0 | X108: =X97 -> 0 | Y108: =Y97 -> 0 | Z108: =Z97 -> 0 | AA108: =AA97 -> 0 | AB108: =AB97 -> 0 | AC108: =AC97 -> 0 | AD108: =AD97 -> 0 | ... EY108: =EY97 -> 0
N109: Total Net Cash Flow | W109: =SUM(W107:W108) -> 0 | X109: =SUM(X107:X108) -> 0 | Y109: =SUM(Y107:Y108) -> 0 | Z109: =SUM(Z107:Z108) -> 0 | AA109: =SUM(AA107:AA108) -> 0 | AB109: =SUM(AB107:AB108) -> 0 | AC109: =SUM(AC107:AC108) -> 0 | AD109: =SUM(AD107:AD108) -> 0 | ... EY109: =SUM(EY107:EY108) -> 0
N110: Total Equity Funded in Period | W110: =-W60 -> -13905817 | X110: =-X60 -> -603130.3 | Y110: =-Y60 -> -603130.3 | Z110: =-Z60 -> -603130.3 | AA110: =-AA60 -> -603130.3 | AB110: =-AB60 -> -603130.3 | AC110: =-AC60 -> -105313.01 | AD110: =-AD60 -> -105313.01 | ... EY110: =-EY60 -> 0
N111: LEVERED PROJECT LEVEL CASH FLOW | W111: =+W110+W109 -> -13905817 | X111: =+X110+X109 -> -603130.3 | Y111: =+Y110+Y109 -> -603130.3 | Z111: =+Z110+Z109 -> -603130.3 | AA111: =+AA110+AA109 -> -603130.3 | AB111: =+AB110+AB109 -> -603130.3 | AC111: =+AC110+AC109 -> -105313.01 | AD111: =+AD110+AD109 -> -105313.01 | ... EY111: =+EY110+EY109 -> 0

Sheet Unit Mix
C2: =TODAY() -> 46212
C4: Unit Mix | Q4: Affordable Unit Rents by Unit Type*
C5: Unit | D5: # of | E5: # of Beds | F5: Bedroom | G5: Avg. | H5: Total | I5: Avg. Rent | J5: Avg. Rent | K5: Avg. Rent | L5: Total Mo. | M5: Total Annual | N5: Note | Q5: Studio | R5: 1bd | S5: 2bd | T5: 3bd
C6: Description | D6: Units | E6: Per Unit | F6: Count | G6: SF/Unit | H6: NSF | I6: Per Unit | J6: Per Bed | K6: Per SF | L6: Rent | M6: Rent | Q6: 1400 | R6: 1650 | S6: 2150 | T6: 2800
C7: Studio A | D7: 8 | E7: 1 | F7: =E7*D7 -> 8 | G7: 560 | H7: =G7*D7 -> 4480 | I7: 2500 | J7: =I7/E7 -> 2500 | K7: =I7/G7 -> 4.4642857 | L7: =I7*D7 -> 20000 | M7: =L7*12 -> 240000
C8: Studio A - Affordable | D8: 12 | E8: 1 | F8: =E8*D8 -> 12 | G8: =G7 -> 560 | H8: =G8*D8 -> 6720 | I8: =Q6 -> 1400 | J8: =I8/E8 -> 1400 | K8: =I8/G8 -> 2.5 | L8: =I8*D8 -> 16800 | M8: =L8*12 -> 201600
C9: Studio B | D9: 30 | E9: 1 | F9: =E9*D9 -> 30 | G9: 560 | H9: =G9*D9 -> 16800 | I9: 2600 | J9: =I9/E9 -> 2600 | K9: =I9/G9 -> 4.6428571 | L9: =I9*D9 -> 78000 | M9: =L9*12 -> 936000
C10: Studio B - Affordable | D10: 10 | E10: =E9 -> 1 | F10: =E10*D10 -> 10 | G10: =G9 -> 560 | H10: =G10*D10 -> 5600 | I10: =Q6 -> 1400 | J10: =I10/E10 -> 1400 | K10: =I10/G10 -> 2.5 | L10: =I10*D10 -> 14000 | M10: =L10*12 -> 168000
C11: Studio C | D11: 30 | E11: 1 | F11: =E11*D11 -> 30 | G11: 600 | H11: =G11*D11 -> 18000 | I11: 2700 | J11: =I11/E11 -> 2700 | K11: =I11/G11 -> 4.5 | L11: =I11*D11 -> 81000 | M11: =L11*12 -> 972000
C12: 1 Bed / 1 Bath | D12: 6 | E12: 1 | F12: =E12*D12 -> 6 | G12: 785 | H12: =G12*D12 -> 4710 | I12: 2800 | J12: =I12/E12 -> 2800 | K12: =I12/G12 -> 3.566879 | L12: =I12*D12 -> 16800 | M12: =L12*12 -> 201600
C13: 1 Bed / 1 Bath - A (Corner unit) | D13: 13 | E13: 1 | F13: =E13*D13 -> 13 | G13: =(1000+940)/2 -> 970 | H13: =G13*D13 -> 12610 | I13: 3000 | J13: =I13/E13 -> 3000 | K13: =I13/G13 -> 3.0927835 | L13: =I13*D13 -> 39000 | M13: =L13*12 -> 468000
A14: =144*0.15 -> 21.6 | C14: 1 Bed / 1 Bath - B (Regular Unit) | D14: =4*4 -> 16 | E14: 1 | F14: =E14*D14 -> 16 | G14: =(775+960+860+1000)/4 -> 898.75 | H14: =G14*D14 -> 14380 | I14: 2900 | J14: =I14/E14 -> 2900 | K14: =I14/G14 -> 3.2267038 | L14: =I14*D14 -> 46400 | M14: =L14*12 -> 556800
C15: 2 Bed / 2 Bath | D15: 8 | E15: 2 | F15: =E15*D15 -> 16 | G15: 1100 | H15: =G15*D15 -> 8800 | I15: 3800 | J15: =I15/E15 -> 1900 | K15: =I15/G15 -> 3.4545455 | L15: =I15*D15 -> 30400 | M15: =L15*12 -> 364800
C16: Live Work Loft - A | D16: 3 | E16: 1 | F16: =E16*D16 -> 3 | G16: 1100 | H16: =G16*D16 -> 3300 | I16: 3850 | J16: =I16/E16 -> 3850 | K16: =I16/G16 -> 3.5 | L16: =I16*D16 -> 11550 | M16: =L16*12 -> 138600 | N16: Assuming 400 SF of mezz level
C17: Live Work Loft - B | D17: 7 | E17: 1 | F17: =E17*D17 -> 7 | G17: =(((510*4)+(515*2)+600)/7)+250 -> 774.28571 | H17: =G17*D17 -> 5420 | I17: 3000 | J17: =I17/E17 -> 3000 | K17: =I17/G17 -> 3.8745387 | L17: =I17*D17 -> 21000 | M17: =L17*12 -> 252000 | N17: Assuming 250 SF of mezz level
C18: Live Work Loft - C | D18: 1 | E18: 2 | F18: =E18*D18 -> 2 | G18: 1100 | H18: =G18*D18 -> 1100 | I18: 4000 | J18: =I18/E18 -> 2000 | K18: =I18/G18 -> 3.6363636 | L18: =I18*D18 -> 4000 | M18: =L18*12 -> 48000
C19: Total / Wtd. Avg. | D19: =SUM(D7:D18) -> 144 | E19: =SUMPRODUCT(E7:E18,$D$7:$D$18)/$D$19 -> 1.0625 | F19: =SUM(F7:F18) -> 153 | G19: =SUMPRODUCT(G7:G18,$D$7:$D$18)/$D$19 -> 707.77778 | H19: =SUM(H7:H18) -> 101920 | I19: =SUMPRODUCT(I7:I18,$D$7:$D$18)/$D$19 -> 2631.5972 | J19: =I19/E19 -> 2476.7974 | K19: =I19/G19 -> 3.7181122 | L19: =SUM(L7:L18) -> 378950 | M19: =SUM(M7:M18) -> 4547400
K20: =+'Summary & Assumptions'!H35 -> 3.7181122 | M20: =M19+'Annual CFs'!G53 -> 4560757 | N20: Rough goal
M22: =M20/2600/12 -> 146.17811

Sheet Hard Cost Detail
C4: Hard Cost Detail
C5: Description | E5: $ Total | F5: $/GSF | G5: $/Unit
C6: Unit RSF | E6: ='Summary & Assumptions'!H12 -> 110465
C7: Direct Construction Costs
C8: PSF Cost | F8: 150
C9: Foundations | F9: =E9/'Summary & Assumptions'!$H$11 -> 0 | G9: =E9/'Summary & Assumptions'!$D$34 -> 0
C10: Superstructure | F10: =E10/'Summary & Assumptions'!$H$11 -> 0 | G10: =E10/'Summary & Assumptions'!$D$34 -> 0
C11: Exterior Enclosure | F11: =E11/'Summary & Assumptions'!$H$11 -> 0 | G11: =E11/'Summary & Assumptions'!$D$34 -> 0
C12: Roofing | F12: =E12/'Summary & Assumptions'!$H$11 -> 0 | G12: =E12/'Summary & Assumptions'!$D$34 -> 0
C13: Interior Construction | F13: =E13/'Summary & Assumptions'!$H$11 -> 0 | G13: =E13/'Summary & Assumptions'!$D$34 -> 0
C14: Stairs | F14: =E14/'Summary & Assumptions'!$H$11 -> 0 | G14: =E14/'Summary & Assumptions'!$D$34 -> 0
C15: Interior Finishes | F15: =E15/'Summary & Assumptions'!$H$11 -> 0 | G15: =E15/'Summary & Assumptions'!$D$34 -> 0
C16: Conveying | F16: =E16/'Summary & Assumptions'!$H$11 -> 0 | G16: =E16/'Summary & Assumptions'!$D$34 -> 0
C17: Plumbing | F17: =E17/'Summary & Assumptions'!$H$11 -> 0 | G17: =E17/'Summary & Assumptions'!$D$34 -> 0
C18: HVAC | F18: =E18/'Summary & Assumptions'!$H$11 -> 0 | G18: =E18/'Summary & Assumptions'!$D$34 -> 0
C19: Fire Protection | F19: =E19/'Summary & Assumptions'!$H$11 -> 0 | G19: =E19/'Summary & Assumptions'!$D$34 -> 0
C20: Electrical | F20: =E20/'Summary & Assumptions'!$H$11 -> 0 | G20: =E20/'Summary & Assumptions'!$D$34 -> 0
... C28: Contractor General Conditions | F28: =E28/'Summary & Assumptions'!$H$11 -> 0 | G28: =E28/'Summary & Assumptions'!$D$34 -> 0
C29: Total Direct Construction Costs | E29: =E6*F8 -> 16569750 | F29: =SUM(F9:F28) -> 0 | G29: =SUM(G9:G28) -> 0
C31: Total Contingency, Insurance, & Fees
C32: Construction Contingency | D32: 0.05 | E32: =D32*$E$29 -> 828487.5 | F32: =E32/'Summary & Assumptions'!$H$11 -> 6.2402553 | G32: =E32/'Summary & Assumptions'!$D$34 -> 5753.3854
C33: Building Insurance | D33: 0.01 | E33: =D33*($E$29+E32) -> 173982.38 | F33: =E33/'Summary & Assumptions'!$H$11 -> 1.3104536 | G33: =E33/'Summary & Assumptions'!$D$34 -> 1208.2109
C34: Preconstruction Services | D34: 0.03 | E34: =D34*SUM($E$29,E32,E33) -> 527166.6 | F34: =E34/'Summary & Assumptions'!$H$11 -> 3.9706745 | G34: =E34/'Summary & Assumptions'!$D$34 -> 3660.8791
C35: Contractor's Fee | D35: 0.05 | E35: =D35*SUM($E$29,E32,E33,E34) -> 904969.32 | F35: =E35/'Summary & Assumptions'!$H$11 -> 6.8163245 | G35: =E35/'Summary & Assumptions'!$D$34 -> 6284.5092
C36: Total Contingency, Insurance, & Fees | E36: =SUM(E32:E35) -> 2434605.8 | F36: =SUM(F32:F35) -> 18.337708 | G36: =SUM(G32:G35) -> 16906.985
C38: Total GMP | E38: =E29+E36 -> 19004356 | F38: =F29+F36 -> 18.337708 | G38: =G29+G36 -> 16906.985
C40: Construction Cost Reductions
C41: Reduce Enclosure Articulations | G41: =E41/'Summary & Assumptions'!$D$34 -> 0
C42: Unit Millwork | G42: =E42/'Summary & Assumptions'!$D$34 -> 0
C43: Electrical | G43: =E43/'Summary & Assumptions'!$D$34 -> 0
C44: Reduce Finish Costs - Tower | G44: =E44/'Summary & Assumptions'!$D$34 -> 0
C45: Load Bearing Stud Alternate | G45: =E45/'Summary & Assumptions'!$D$34 -> 0
C46: Exposed Concrete Deck Ceilings | G46: =E46/'Summary & Assumptions'!$D$34 -> 0
C47: Reduce SF of Glass | G47: =E47/'Summary & Assumptions'!$D$34 -> 0
C48: Appliances | G48: =E48/'Summary & Assumptions'!$D$34 -> 0
C49: Total Construction Cost Reductions | E49: =SUM(E41:E48) -> 0 | F49: =SUM(F41:F48) -> 0 | G49: =SUM(G41:G48) -> 0
C51: Owner's Contingency | D51: 0.05 | E51: =D51*(E38+E49) -> 950217.79 | F51: =E51/'Summary & Assumptions'!$H$11 -> 7.1571407 | G51: =E51/'Summary & Assumptions'!$D$34 -> 6598.7347
C53: Total Hard Costs | E53: =E38+E49+E51 -> 19954574 | F53: =F38+F49+F51 -> 25.494849 | G53: =G38+G49+G51 -> 23505.719

Sheet Soft Cost Detail
C4: Soft Cost Detail
C5: Description | E5: $ Total | F5: $/GSF | G5: $/Unit
C6: Architecture
C7: Feasibility and Concept | F7: =E7/'Summary & Assumptions'!$H$11 -> 0 | G7: =E7/'Summary & Assumptions'!$D$34 -> 0
C8: Schematic Design | F8: =E8/'Summary & Assumptions'!$H$11 -> 0 | G8: =E8/'Summary & Assumptions'!$D$34 -> 0
C9: Design Development | F9: =E9/'Summary & Assumptions'!$H$11 -> 0 | G9: =E9/'Summary & Assumptions'!$D$34 -> 0
C10: Construction Documents | F10: =E10/'Summary & Assumptions'!$H$11 -> 0 | G10: =E10/'Summary & Assumptions'!$D$34 -> 0
C11: Permit | F11: =E11/'Summary & Assumptions'!$H$11 -> 0 | G11: =E11/'Summary & Assumptions'!$D$34 -> 0
C12: Bidding & Construction Administration | F12: =E12/'Summary & Assumptions'!$H$11 -> 0 | G12: =E12/'Summary & Assumptions'!$D$34 -> 0
C13: Architectural Team | F13: =E13/'Summary & Assumptions'!$H$11 -> 0 | G13: =E13/'Summary & Assumptions'!$D$34 -> 0
C14: Total Architecture | E14: 500000 | F14: =SUM(F7:F13) -> 0 | G14: =SUM(G7:G13) -> 0
C16: Consultants and Engineering
C17: Structural Engineer | F17: =E17/'Summary & Assumptions'!$H$11 -> 0 | G17: =E17/'Summary & Assumptions'!$D$34 -> 0
C18: Landscaping Architect | F18: =E18/'Summary & Assumptions'!$H$11 -> 0 | G18: =E18/'Summary & Assumptions'!$D$34 -> 0
C19: Landscaping Irrigation Design | F19: =E19/'Summary & Assumptions'!$H$11 -> 0 | G19: =E19/'Summary & Assumptions'!$D$34 -> 0
C20: Civil Engineer | F20: =E20/'Summary & Assumptions'!$H$11 -> 0 | G20: =E20/'Summary & Assumptions'!$D$34 -> 0
C21: Mechanical & Plumbing | F21: =E21/'Summary & Assumptions'!$H$11 -> 0 | G21: =E21/'Summary & Assumptions'!$D$34 -> 0
C22: Electrical Engineer | F22: =E22/'Summary & Assumptions'!$H$11 -> 0 | G22: =E22/'Summary & Assumptions'!$D$34 -> 0
C23: Interior Design | F23: =E23/'Summary & Assumptions'!$H$11 -> 0 | G23: =E23/'Summary & Assumptions'!$D$34 -> 0
C24: ADA / Accessibility | F24: =E24/'Summary & Assumptions'!$H$11 -> 0 | G24: =E24/'Summary & Assumptions'!$D$34 -> 0
C25: Sustainability/LEED | F25: =E25/'Summary & Assumptions'!$H$11 -> 0 | G25: =E25/'Summary & Assumptions'!$D$34 -> 0
C26: Utilities Consultant | F26: =E26/'Summary & Assumptions'!$H$11 -> 0 | G26: =E26/'Summary & Assumptions'!$D$34 -> 0
C27: Skin | F27: =E27/'Summary & Assumptions'!$H$11 -> 0 | G27: =E27/'Summary & Assumptions'!$D$34 -> 0
C28: Sound | F28: =E28/'Summary & Assumptions'!$H$11 -> 0 | G28: =E28/'Summary & Assumptions'!$D$34 -> 0
... C31: Permit Expeditor | F31: =E31/'Summary & Assumptions'!$H$11 -> 0 | G31: =E31/'Summary & Assumptions'!$D$34 -> 0
C32: Total Consultants and Engineering | E32: 450000 | F32: =SUM(F17:F31) -> 0 | G32: =SUM(G17:G31) -> 0
C34: Legal
C35: JV Documents | E35: 50000 | F35: =E35/'Summary & Assumptions'!$H$11 -> 0.37660528 | G35: =E35/'Summary & Assumptions'!$D$34 -> 347.22222
C36: Land Use | E36: 50000 | F36: =E36/'Summary & Assumptions'!$H$11 -> 0.37660528 | G36: =E36/'Summary & Assumptions'!$D$34 -> 347.22222
C37: Construction Loan/Transaction Cost | E37: 175000 | F37: =E37/'Summary & Assumptions'!$H$11 -> 1.3181185 | G37: =E37/'Summary & Assumptions'!$D$34 -> 1215.2778
C38: Development-GC/Vendor/Consultant Contracts/Contingency | E38: 100000 | F38: =E38/'Summary & Assumptions'!$H$11 -> 0.75321056 | G38: =E38/'Summary & Assumptions'!$D$34 -> 694.44444
C39: Project Legal Counsel | E39: 115000 | F39: =E39/'Summary & Assumptions'!$H$11 -> 0.86619214 | G39: =E39/'Summary & Assumptions'!$D$34 -> 798.61111
C40: Total Legal | E40: =SUM(E35:E39) -> 490000 | F40: =SUM(F35:F39) -> 3.6907317 | G40: =SUM(G35:G39) -> 3402.7778
C42: Insurance
C43: OCIP | F43: =E43/'Summary & Assumptions'!$H$11 -> 0 | G43: =E43/'Summary & Assumptions'!$D$34 -> 0
C44: General Liability and Property | F44: =E44/'Summary & Assumptions'!$H$11 -> 0 | G44: =E44/'Summary & Assumptions'!$D$34 -> 0
C45: Builders Risk | F45: =E45/'Summary & Assumptions'!$H$11 -> 0 | G45: =E45/'Summary & Assumptions'!$D$34 -> 0
C46: E&O Insurance | F46: =E46/'Summary & Assumptions'!$H$11 -> 0 | G46: =E46/'Summary & Assumptions'!$D$34 -> 0
C47: Pollution Liability | F47: =E47/'Summary & Assumptions'!$H$11 -> 0 | G47: =E47/'Summary & Assumptions'!$D$34 -> 0
C48: Risk Management Services | F48: =E48/'Summary & Assumptions'!$H$11 -> 0 | G48: =E48/'Summary & Assumptions'!$D$34 -> 0
C49: Total Insurance | E49: 250000 | F49: =SUM(F43:F48) -> 0 | G49: =SUM(G43:G48) -> 0
C51: G&A
C52: Printing | E52: 0 | F52: =E52/'Summary & Assumptions'!$H$11 -> 0 | G52: =E52/'Summary & Assumptions'!$D$34 -> 0
C53: Miscellaneous | E53: 0 | F53: =E53/'Summary & Assumptions'!$H$11 -> 0 | G53: =E53/'Summary & Assumptions'!$D$34 -> 0
C54: Rent | E54: 0 | F54: =E54/'Summary & Assumptions'!$H$11 -> 0 | G54: =E54/'Summary & Assumptions'!$D$34 -> 0
C55: Phones / Internet | E55: 0 | F55: =E55/'Summary & Assumptions'!$H$11 -> 0 | G55: =E55/'Summary & Assumptions'!$D$34 -> 0
C56: Office Supplies | E56: 0 | F56: =E56/'Summary & Assumptions'!$H$11 -> 0 | G56: =E56/'Summary & Assumptions'!$D$34 -> 0
C57: Courier / Overnight Expense | E57: 0 | F57: =E57/'Summary & Assumptions'!$H$11 -> 0 | G57: =E57/'Summary & Assumptions'!$D$34 -> 0
C58: Mobile Phone | E58: 0 | F58: =E58/'Summary & Assumptions'!$H$11 -> 0 | G58: =E58/'Summary & Assumptions'!$D$34 -> 0
C59: Copier | E59: 0 | F59: =E59/'Summary & Assumptions'!$H$11 -> 0 | G59: =E59/'Summary & Assumptions'!$D$34 -> 0
C60: Software Expense | E60: 0 | F60: =E60/'Summary & Assumptions'!$H$11 -> 0 | G60: =E60/'Summary & Assumptions'!$D$34 -> 0
C61: IT Services | E61: 0 | F61: =E61/'Summary & Assumptions'!$H$11 -> 0 | G61: =E61/'Summary & Assumptions'!$D$34 -> 0
C62: Developer Meetings | E62: 0 | F62: =E62/'Summary & Assumptions'!$H$11 -> 0 | G62: =E62/'Summary & Assumptions'!$D$34 -> 0
C63: Janitorial / Housekeeping | E63: 0 | F63: =E63/'Summary & Assumptions'!$H$11 -> 0 | G63: =E63/'Summary & Assumptions'!$D$34 -> 0
... C72: Audit Fees | E72: 0 | F72: =E72/'Summary & Assumptions'!$H$11 -> 0 | G72: =E72/'Summary & Assumptions'!$D$34 -> 0
C73: Total G&A | E73: =SUM(E52:E72) -> 0 | F73: =SUM(F52:F72) -> 0 | G73: =SUM(G52:G72) -> 0
C75: Municipal Fees
C76: Utility Connection | E76: 0 | F76: =E76/'Summary & Assumptions'!$H$11 -> 0 | G76: =E76/'Summary & Assumptions'!$D$34 -> 0
C77: Affordable Buyout | E77: 0 | F77: =E77/'Summary & Assumptions'!$H$11 -> 0 | G77: =E77/'Summary & Assumptions'!$D$34 -> 0
C78: Building Permit | E78: 250000 | F78: =E78/'Summary & Assumptions'!$H$11 -> 1.8830264 | G78: =E78/'Summary & Assumptions'!$D$34 -> 1736.1111
C79: Total Municipal Fees | E79: =SUM(E76:E78) -> 250000 | F79: =SUM(F76:F78) -> 1.8830264 | G79: =SUM(G76:G78) -> 1736.1111
C81: Developer Fee | D81: 0.03 | E81: ='Hard Cost Detail'!E29*'Soft Cost Detail'!D81 -> 497092.5 | F81: =E81/'Summary & Assumptions'!$H$11 -> 3.7441532 | G81: =E81/'Summary & Assumptions'!$D$34 -> 3452.0312
C82: Marketing | E82: 392680 | F82: =E82/'Summary & Assumptions'!$H$11 -> 2.9577072 | G82: =E82/'Summary & Assumptions'!$D$34 -> 2726.9444
C83: Leasing Commissions | E83: 0 | F83: =E83/'Summary & Assumptions'!$H$11 -> 0 | G83: =E83/'Summary & Assumptions'!$D$34 -> 0
C84: Tenant Buyout Cost | E84: 1000000 | F84: =E84/'Summary & Assumptions'!$H$11 -> 7.5321056 | G84: =E84/'Summary & Assumptions'!$D$34 -> 6944.4444
C85: Tenant Improvements (Retail) | E85: 0 | F85: 0 | G85: =E85/'Summary & Assumptions'!$D$34 -> 0
C86: Operating Reserve | E86: ='Budget & Draw Schedule'!G37 -> 1235346.3 | F86: =E86/'Summary & Assumptions'!$H$11 -> 9.3047591 | G86: =E86/'Summary & Assumptions'!$D$34 -> 8578.794
C87: Soft Cost Contingency | E87: 296903.73 | F87: =E87/'Summary & Assumptions'!$H$11 -> 2.2363103 | G87: =E87/'Summary & Assumptions'!$D$34 -> 2061.8315
C88: Total Soft Costs | E88: =E14+E32+E40+E49+E73+E79+SUM(E81:E87) -> 5362022.6 | F88: =F14+F32+F40+F49+F73+F79+SUM(F81:F87) -> 31.348794 | G88: =G14+G32+G40+G49+G73+G79+SUM(G81:G87) -> 28902.935

Sheet OI & Expense Growth
C4: Year | F4: 1 | G4: =+F4+1 -> 2 | H4: =+G4+1 -> 3 | I4: =+H4+1 -> 4 | J4: =+I4+1 -> 5 | K4: =+J4+1 -> 6 | L4: =+K4+1 -> 7 | M4: =+L4+1 -> 8 | N4: =+M4+1 -> 9 | ... P4: =+O4+1 -> 11
C6: Other Income
C7: Parking Permit Fees | D7: 100 | F7: =D7*12*'Summary & Assumptions'!H17 -> 438000 | G7: {=F7*(1+INDEX('Growth Rates'!$L$10:$L$20,MATCH('OI & Expense Growth'!G$4,'Growth Rates'!$C$10:$C$20,0)))} -> 438000 | H7: {=G7*(1+INDEX('Growth Rates'!$L$10:$L$20,MATCH('OI & Expense Growth'!H$4,'Growth Rates'!$C$10:$C$20,0)))} -> 438000 | I7: {=H7*(1+INDEX('Growth Rates'!$L$10:$L$20,MATCH('OI & Expense Growth'!I$4,'Growth Rates'!$C$10:$C$20,0)))} -> 438000 | J7: {=I7*(1+INDEX('Growth Rates'!$L$10:$L$20,MATCH('OI & Expense Growth'!J$4,'Growth Rates'!$C$10:$C$20,0)))} -> 451140 | K7: {=J7*(1+INDEX('Growth Rates'!$L$10:$L$20,MATCH('OI & Expense Growth'!K$4,'Growth Rates'!$C$10:$C$20,0)))} -> 464674.2 | L7: {=K7*(1+INDEX('Growth Rates'!$L$10:$L$20,MATCH('OI & Expense Growth'!L$4,'Growth Rates'!$C$10:$C$20,0)))} -> 478614.43 | M7: {=L7*(1+INDEX('Growth Rates'!$L$10:$L$20,MATCH('OI & Expense Growth'!M$4,'Growth Rates'!$C$10:$C$20,0)))} -> 492972.86 | N7: {=M7*(1+INDEX('Growth Rates'!$L$10:$L$20,MATCH('OI & Expense Growth'!N$4,'Growth Rates'!$C$10:$C$20,0)))} -> 507762.04 | ... P7: {=O7*(1+INDEX('Growth Rates'!$L$10:$L$20,MATCH('OI & Expense Growth'!P$4,'Growth Rates'!$C$10:$C$20,0)))} -> 538684.75
C8: Utility Charge | D8: 75 | F8: =D8*12*'Summary & Assumptions'!$D$34 -> 129600 | G8: {=F8*(1+INDEX('Growth Rates'!$L$10:$L$20,MATCH('OI & Expense Growth'!G$4,'Growth Rates'!$C$10:$C$20,0)))} -> 129600 | H8: {=G8*(1+INDEX('Growth Rates'!$L$10:$L$20,MATCH('OI & Expense Growth'!H$4,'Growth Rates'!$C$10:$C$20,0)))} -> 129600 | I8: {=H8*(1+INDEX('Growth Rates'!$L$10:$L$20,MATCH('OI & Expense Growth'!I$4,'Growth Rates'!$C$10:$C$20,0)))} -> 129600 | J8: {=I8*(1+INDEX('Growth Rates'!$L$10:$L$20,MATCH('OI & Expense Growth'!J$4,'Growth Rates'!$C$10:$C$20,0)))} -> 133488 | K8: {=J8*(1+INDEX('Growth Rates'!$L$10:$L$20,MATCH('OI & Expense Growth'!K$4,'Growth Rates'!$C$10:$C$20,0)))} -> 137492.64 | L8: {=K8*(1+INDEX('Growth Rates'!$L$10:$L$20,MATCH('OI & Expense Growth'!L$4,'Growth Rates'!$C$10:$C$20,0)))} -> 141617.42 | M8: {=L8*(1+INDEX('Growth Rates'!$L$10:$L$20,MATCH('OI & Expense Growth'!M$4,'Growth Rates'!$C$10:$C$20,0)))} -> 145865.94 | N8: {=M8*(1+INDEX('Growth Rates'!$L$10:$L$20,MATCH('OI & Expense Growth'!N$4,'Growth Rates'!$C$10:$C$20,0)))} -> 150241.92 | ... P8: {=O8*(1+INDEX('Growth Rates'!$L$10:$L$20,MATCH('OI & Expense Growth'!P$4,'Growth Rates'!$C$10:$C$20,0)))} -> 159391.65
C9: Utility Billing Income | D9: 35 | F9: =D9*12*'Summary & Assumptions'!$D$34 -> 60480 | G9: {=F9*(1+INDEX('Growth Rates'!$L$10:$L$20,MATCH('OI & Expense Growth'!G$4,'Growth Rates'!$C$10:$C$20,0)))} -> 60480 | H9: {=G9*(1+INDEX('Growth Rates'!$L$10:$L$20,MATCH('OI & Expense Growth'!H$4,'Growth Rates'!$C$10:$C$20,0)))} -> 60480 | I9: {=H9*(1+INDEX('Growth Rates'!$L$10:$L$20,MATCH('OI & Expense Growth'!I$4,'Growth Rates'!$C$10:$C$20,0)))} -> 60480 | J9: {=I9*(1+INDEX('Growth Rates'!$L$10:$L$20,MATCH('OI & Expense Growth'!J$4,'Growth Rates'!$C$10:$C$20,0)))} -> 62294.4 | K9: {=J9*(1+INDEX('Growth Rates'!$L$10:$L$20,MATCH('OI & Expense Growth'!K$4,'Growth Rates'!$C$10:$C$20,0)))} -> 64163.232 | L9: {=K9*(1+INDEX('Growth Rates'!$L$10:$L$20,MATCH('OI & Expense Growth'!L$4,'Growth Rates'!$C$10:$C$20,0)))} -> 66088.129 | M9: {=L9*(1+INDEX('Growth Rates'!$L$10:$L$20,MATCH('OI & Expense Growth'!M$4,'Growth Rates'!$C$10:$C$20,0)))} -> 68070.773 | N9: {=M9*(1+INDEX('Growth Rates'!$L$10:$L$20,MATCH('OI & Expense Growth'!N$4,'Growth Rates'!$C$10:$C$20,0)))} -> 70112.896 | ... P9: {=O9*(1+INDEX('Growth Rates'!$L$10:$L$20,MATCH('OI & Expense Growth'!P$4,'Growth Rates'!$C$10:$C$20,0)))} -> 74382.771
C10: Retail Income (NNN) | D10: 2.5 | F10: =D10*'Summary & Assumptions'!$H$15 -> 0 | G10: {=F10*(1+INDEX('Growth Rates'!$L$10:$L$20,MATCH('OI & Expense Growth'!G$4,'Growth Rates'!$C$10:$C$20,0)))} -> 0 | H10: {=G10*(1+INDEX('Growth Rates'!$L$10:$L$20,MATCH('OI & Expense Growth'!H$4,'Growth Rates'!$C$10:$C$20,0)))} -> 0 | I10: {=H10*(1+INDEX('Growth Rates'!$L$10:$L$20,MATCH('OI & Expense Growth'!I$4,'Growth Rates'!$C$10:$C$20,0)))} -> 0 | J10: {=I10*(1+INDEX('Growth Rates'!$L$10:$L$20,MATCH('OI & Expense Growth'!J$4,'Growth Rates'!$C$10:$C$20,0)))} -> 0 | K10: {=J10*(1+INDEX('Growth Rates'!$L$10:$L$20,MATCH('OI & Expense Growth'!K$4,'Growth Rates'!$C$10:$C$20,0)))} -> 0 | L10: {=K10*(1+INDEX('Growth Rates'!$L$10:$L$20,MATCH('OI & Expense Growth'!L$4,'Growth Rates'!$C$10:$C$20,0)))} -> 0 | M10: {=L10*(1+INDEX('Growth Rates'!$L$10:$L$20,MATCH('OI & Expense Growth'!M$4,'Growth Rates'!$C$10:$C$20,0)))} -> 0 | N10: {=M10*(1+INDEX('Growth Rates'!$L$10:$L$20,MATCH('OI & Expense Growth'!N$4,'Growth Rates'!$C$10:$C$20,0)))} -> 0 | ... P10: {=O10*(1+INDEX('Growth Rates'!$L$10:$L$20,MATCH('OI & Expense Growth'!P$4,'Growth Rates'!$C$10:$C$20,0)))} -> 0
C12: Controllable Expenses | D12: Per Unit
C13: Payroll | D13: 800 | F13: =D13*'Summary & Assumptions'!$D$34 -> 115200 | G13: {=F13*(1+INDEX('Growth Rates'!$M$10:$M$20,MATCH('OI & Expense Growth'!G$4,'Growth Rates'!$C$10:$C$20,0)))} -> 115200 | H13: {=G13*(1+INDEX('Growth Rates'!$M$10:$M$20,MATCH('OI & Expense Growth'!H$4,'Growth Rates'!$C$10:$C$20,0)))} -> 115200 | I13: {=H13*(1+INDEX('Growth Rates'!$M$10:$M$20,MATCH('OI & Expense Growth'!I$4,'Growth Rates'!$C$10:$C$20,0)))} -> 115200 | J13: {=I13*(1+INDEX('Growth Rates'!$M$10:$M$20,MATCH('OI & Expense Growth'!J$4,'Growth Rates'!$C$10:$C$20,0)))} -> 118656 | K13: {=J13*(1+INDEX('Growth Rates'!$M$10:$M$20,MATCH('OI & Expense Growth'!K$4,'Growth Rates'!$C$10:$C$20,0)))} -> 122215.68 | L13: {=K13*(1+INDEX('Growth Rates'!$M$10:$M$20,MATCH('OI & Expense Growth'!L$4,'Growth Rates'!$C$10:$C$20,0)))} -> 125882.15 | M13: {=L13*(1+INDEX('Growth Rates'!$M$10:$M$20,MATCH('OI & Expense Growth'!M$4,'Growth Rates'!$C$10:$C$20,0)))} -> 129658.61 | N13: {=M13*(1+INDEX('Growth Rates'!$M$10:$M$20,MATCH('OI & Expense Growth'!N$4,'Growth Rates'!$C$10:$C$20,0)))} -> 133548.37 | ... P13: {=O13*(1+INDEX('Growth Rates'!$M$10:$M$20,MATCH('OI & Expense Growth'!P$4,'Growth Rates'!$C$10:$C$20,0)))} -> 141681.47
C14: Marketing & Advertising | D14: 450 | F14: =D14*'Summary & Assumptions'!$D$34 -> 64800 | G14: {=F14*(1+INDEX('Growth Rates'!$M$10:$M$20,MATCH('OI & Expense Growth'!G$4,'Growth Rates'!$C$10:$C$20,0)))} -> 64800 | H14: {=G14*(1+INDEX('Growth Rates'!$M$10:$M$20,MATCH('OI & Expense Growth'!H$4,'Growth Rates'!$C$10:$C$20,0)))} -> 64800 | I14: {=H14*(1+INDEX('Growth Rates'!$M$10:$M$20,MATCH('OI & Expense Growth'!I$4,'Growth Rates'!$C$10:$C$20,0)))} -> 64800 | J14: {=I14*(1+INDEX('Growth Rates'!$M$10:$M$20,MATCH('OI & Expense Growth'!J$4,'Growth Rates'!$C$10:$C$20,0)))} -> 66744 | K14: {=J14*(1+INDEX('Growth Rates'!$M$10:$M$20,MATCH('OI & Expense Growth'!K$4,'Growth Rates'!$C$10:$C$20,0)))} -> 68746.32 | L14: {=K14*(1+INDEX('Growth Rates'!$M$10:$M$20,MATCH('OI & Expense Growth'!L$4,'Growth Rates'!$C$10:$C$20,0)))} -> 70808.71 | M14: {=L14*(1+INDEX('Growth Rates'!$M$10:$M$20,MATCH('OI & Expense Growth'!M$4,'Growth Rates'!$C$10:$C$20,0)))} -> 72932.971 | N14: {=M14*(1+INDEX('Growth Rates'!$M$10:$M$20,MATCH('OI & Expense Growth'!N$4,'Growth Rates'!$C$10:$C$20,0)))} -> 75120.96 | ... P14: {=O14*(1+INDEX('Growth Rates'!$M$10:$M$20,MATCH('OI & Expense Growth'!P$4,'Growth Rates'!$C$10:$C$20,0)))} -> 79695.826
C15: Repairs & Maintenance | D15: 425 | F15: =D15*'Summary & Assumptions'!$D$34 -> 61200 | G15: {=F15*(1+INDEX('Growth Rates'!$M$10:$M$20,MATCH('OI & Expense Growth'!G$4,'Growth Rates'!$C$10:$C$20,0)))} -> 61200 | H15: {=G15*(1+INDEX('Growth Rates'!$M$10:$M$20,MATCH('OI & Expense Growth'!H$4,'Growth Rates'!$C$10:$C$20,0)))} -> 61200 | I15: {=H15*(1+INDEX('Growth Rates'!$M$10:$M$20,MATCH('OI & Expense Growth'!I$4,'Growth Rates'!$C$10:$C$20,0)))} -> 61200 | J15: {=I15*(1+INDEX('Growth Rates'!$M$10:$M$20,MATCH('OI & Expense Growth'!J$4,'Growth Rates'!$C$10:$C$20,0)))} -> 63036 | K15: {=J15*(1+INDEX('Growth Rates'!$M$10:$M$20,MATCH('OI & Expense Growth'!K$4,'Growth Rates'!$C$10:$C$20,0)))} -> 64927.08 | L15: {=K15*(1+INDEX('Growth Rates'!$M$10:$M$20,MATCH('OI & Expense Growth'!L$4,'Growth Rates'!$C$10:$C$20,0)))} -> 66874.892 | M15: {=L15*(1+INDEX('Growth Rates'!$M$10:$M$20,MATCH('OI & Expense Growth'!M$4,'Growth Rates'!$C$10:$C$20,0)))} -> 68881.139 | N15: {=M15*(1+INDEX('Growth Rates'!$M$10:$M$20,MATCH('OI & Expense Growth'!N$4,'Growth Rates'!$C$10:$C$20,0)))} -> 70947.573 | ... P15: {=O15*(1+INDEX('Growth Rates'!$M$10:$M$20,MATCH('OI & Expense Growth'!P$4,'Growth Rates'!$C$10:$C$20,0)))} -> 75268.281
C16: Turnover | D16: 614.58333 | F16: =D16*'Summary & Assumptions'!$D$34 -> 88500 | G16: {=F16*(1+INDEX('Growth Rates'!$M$10:$M$20,MATCH('OI & Expense Growth'!G$4,'Growth Rates'!$C$10:$C$20,0)))} -> 88500 | H16: {=G16*(1+INDEX('Growth Rates'!$M$10:$M$20,MATCH('OI & Expense Growth'!H$4,'Growth Rates'!$C$10:$C$20,0)))} -> 88500 | I16: {=H16*(1+INDEX('Growth Rates'!$M$10:$M$20,MATCH('OI & Expense Growth'!I$4,'Growth Rates'!$C$10:$C$20,0)))} -> 88500 | J16: {=I16*(1+INDEX('Growth Rates'!$M$10:$M$20,MATCH('OI & Expense Growth'!J$4,'Growth Rates'!$C$10:$C$20,0)))} -> 91155 | K16: {=J16*(1+INDEX('Growth Rates'!$M$10:$M$20,MATCH('OI & Expense Growth'!K$4,'Growth Rates'!$C$10:$C$20,0)))} -> 93889.65 | L16: {=K16*(1+INDEX('Growth Rates'!$M$10:$M$20,MATCH('OI & Expense Growth'!L$4,'Growth Rates'!$C$10:$C$20,0)))} -> 96706.34 | M16: {=L16*(1+INDEX('Growth Rates'!$M$10:$M$20,MATCH('OI & Expense Growth'!M$4,'Growth Rates'!$C$10:$C$20,0)))} -> 99607.53 | N16: {=M16*(1+INDEX('Growth Rates'!$M$10:$M$20,MATCH('OI & Expense Growth'!N$4,'Growth Rates'!$C$10:$C$20,0)))} -> 102595.76 | ... P16: {=O16*(1+INDEX('Growth Rates'!$M$10:$M$20,MATCH('OI & Expense Growth'!P$4,'Growth Rates'!$C$10:$C$20,0)))} -> 108843.84
C17: General & Administrative | D17: 350 | F17: =D17*'Summary & Assumptions'!$D$34 -> 50400 | G17: {=F17*(1+INDEX('Growth Rates'!$M$10:$M$20,MATCH('OI & Expense Growth'!G$4,'Growth Rates'!$C$10:$C$20,0)))} -> 50400 | H17: {=G17*(1+INDEX('Growth Rates'!$M$10:$M$20,MATCH('OI & Expense Growth'!H$4,'Growth Rates'!$C$10:$C$20,0)))} -> 50400 | I17: {=H17*(1+INDEX('Growth Rates'!$M$10:$M$20,MATCH('OI & Expense Growth'!I$4,'Growth Rates'!$C$10:$C$20,0)))} -> 50400 | J17: {=I17*(1+INDEX('Growth Rates'!$M$10:$M$20,MATCH('OI & Expense Growth'!J$4,'Growth Rates'!$C$10:$C$20,0)))} -> 51912 | K17: {=J17*(1+INDEX('Growth Rates'!$M$10:$M$20,MATCH('OI & Expense Growth'!K$4,'Growth Rates'!$C$10:$C$20,0)))} -> 53469.36 | L17: {=K17*(1+INDEX('Growth Rates'!$M$10:$M$20,MATCH('OI & Expense Growth'!L$4,'Growth Rates'!$C$10:$C$20,0)))} -> 55073.441 | M17: {=L17*(1+INDEX('Growth Rates'!$M$10:$M$20,MATCH('OI & Expense Growth'!M$4,'Growth Rates'!$C$10:$C$20,0)))} -> 56725.644 | N17: {=M17*(1+INDEX('Growth Rates'!$M$10:$M$20,MATCH('OI & Expense Growth'!N$4,'Growth Rates'!$C$10:$C$20,0)))} -> 58427.413 | ... P17: {=O17*(1+INDEX('Growth Rates'!$M$10:$M$20,MATCH('OI & Expense Growth'!P$4,'Growth Rates'!$C$10:$C$20,0)))} -> 61985.643
C19: Non-Controllable Expenses
C20: Real Estate Taxes | D20: =F20/'Summary & Assumptions'!$D$34 -> 3807.5972 | F20: ='Summary & Assumptions'!L46 -> 548294 | G20: {=F20*(1+INDEX('Growth Rates'!$N$10:$N$20,MATCH('OI & Expense Growth'!G$4,'Growth Rates'!$C$10:$C$20,0)))} -> 548294 | H20: {=G20*(1+INDEX('Growth Rates'!$N$10:$N$20,MATCH('OI & Expense Growth'!H$4,'Growth Rates'!$C$10:$C$20,0)))} -> 548294 | I20: {=H20*(1+INDEX('Growth Rates'!$N$10:$N$20,MATCH('OI & Expense Growth'!I$4,'Growth Rates'!$C$10:$C$20,0)))} -> 548294 | J20: {=I20*(1+INDEX('Growth Rates'!$N$10:$N$20,MATCH('OI & Expense Growth'!J$4,'Growth Rates'!$C$10:$C$20,0)))} -> 564742.82 | K20: {=J20*(1+INDEX('Growth Rates'!$N$10:$N$20,MATCH('OI & Expense Growth'!K$4,'Growth Rates'!$C$10:$C$20,0)))} -> 581685.1 | L20: {=K20*(1+INDEX('Growth Rates'!$N$10:$N$20,MATCH('OI & Expense Growth'!L$4,'Growth Rates'!$C$10:$C$20,0)))} -> 599135.66 | M20: {=L20*(1+INDEX('Growth Rates'!$N$10:$N$20,MATCH('OI & Expense Growth'!M$4,'Growth Rates'!$C$10:$C$20,0)))} -> 617109.73 | N20: {=M20*(1+INDEX('Growth Rates'!$N$10:$N$20,MATCH('OI & Expense Growth'!N$4,'Growth Rates'!$C$10:$C$20,0)))} -> 635623.02 | ... P20: {=O20*(1+INDEX('Growth Rates'!$N$10:$N$20,MATCH('OI & Expense Growth'!P$4,'Growth Rates'!$C$10:$C$20,0)))} -> 674332.46
C21: Insurance | D21: 550 | F21: =D21*'Summary & Assumptions'!$D$34 -> 79200 | G21: {=F21*(1+INDEX('Growth Rates'!$N$10:$N$20,MATCH('OI & Expense Growth'!G$4,'Growth Rates'!$C$10:$C$20,0)))} -> 79200 | H21: {=G21*(1+INDEX('Growth Rates'!$N$10:$N$20,MATCH('OI & Expense Growth'!H$4,'Growth Rates'!$C$10:$C$20,0)))} -> 79200 | I21: {=H21*(1+INDEX('Growth Rates'!$N$10:$N$20,MATCH('OI & Expense Growth'!I$4,'Growth Rates'!$C$10:$C$20,0)))} -> 79200 | J21: {=I21*(1+INDEX('Growth Rates'!$N$10:$N$20,MATCH('OI & Expense Growth'!J$4,'Growth Rates'!$C$10:$C$20,0)))} -> 81576 | K21: {=J21*(1+INDEX('Growth Rates'!$N$10:$N$20,MATCH('OI & Expense Growth'!K$4,'Growth Rates'!$C$10:$C$20,0)))} -> 84023.28 | L21: {=K21*(1+INDEX('Growth Rates'!$N$10:$N$20,MATCH('OI & Expense Growth'!L$4,'Growth Rates'!$C$10:$C$20,0)))} -> 86543.978 | M21: {=L21*(1+INDEX('Growth Rates'!$N$10:$N$20,MATCH('OI & Expense Growth'!M$4,'Growth Rates'!$C$10:$C$20,0)))} -> 89140.298 | N21: {=M21*(1+INDEX('Growth Rates'!$N$10:$N$20,MATCH('OI & Expense Growth'!N$4,'Growth Rates'!$C$10:$C$20,0)))} -> 91814.507 | ... P21: {=O21*(1+INDEX('Growth Rates'!$N$10:$N$20,MATCH('OI & Expense Growth'!P$4,'Growth Rates'!$C$10:$C$20,0)))} -> 97406.01
C22: Utilities | D22: 1500 | F22: =D22*'Summary & Assumptions'!$D$34 -> 216000 | G22: {=F22*(1+INDEX('Growth Rates'!$N$10:$N$20,MATCH('OI & Expense Growth'!G$4,'Growth Rates'!$C$10:$C$20,0)))} -> 216000 | H22: {=G22*(1+INDEX('Growth Rates'!$N$10:$N$20,MATCH('OI & Expense Growth'!H$4,'Growth Rates'!$C$10:$C$20,0)))} -> 216000 | I22: {=H22*(1+INDEX('Growth Rates'!$N$10:$N$20,MATCH('OI & Expense Growth'!I$4,'Growth Rates'!$C$10:$C$20,0)))} -> 216000 | J22: {=I22*(1+INDEX('Growth Rates'!$N$10:$N$20,MATCH('OI & Expense Growth'!J$4,'Growth Rates'!$C$10:$C$20,0)))} -> 222480 | K22: {=J22*(1+INDEX('Growth Rates'!$N$10:$N$20,MATCH('OI & Expense Growth'!K$4,'Growth Rates'!$C$10:$C$20,0)))} -> 229154.4 | L22: {=K22*(1+INDEX('Growth Rates'!$N$10:$N$20,MATCH('OI & Expense Growth'!L$4,'Growth Rates'!$C$10:$C$20,0)))} -> 236029.03 | M22: {=L22*(1+INDEX('Growth Rates'!$N$10:$N$20,MATCH('OI & Expense Growth'!M$4,'Growth Rates'!$C$10:$C$20,0)))} -> 243109.9 | N22: {=M22*(1+INDEX('Growth Rates'!$N$10:$N$20,MATCH('OI & Expense Growth'!N$4,'Growth Rates'!$C$10:$C$20,0)))} -> 250403.2 | ... P22: {=O22*(1+INDEX('Growth Rates'!$N$10:$N$20,MATCH('OI & Expense Growth'!P$4,'Growth Rates'!$C$10:$C$20,0)))} -> 265652.75
C25: All-in OpEx (AMC estimate) | D25: 8800
C26: back out: non-controllable | D26: =-SUM(D20:D22) -> -5857.5972
C27: Pro Forma Controllable OpEx | D27: =SUM(D25:D26) -> 2942.4028
D29: =SUM(D13:D17) -> 2639.5833

Sheet Growth Rates
C3: ='Summary & Assumptions'!C1 -> 425 Colorado Street - Glendale, CA
C4: Growth Rates
C6: Revenue/Expense Growth Rates
E7: Ann. Incr. % | G7: % of Gross Potential Rent | L7: Other Income | M7: Expenses
E8: Rent | F8: Market | G8: Market | H8: Retail | I8: Non-Rev. | L8: Other | M8: Controllable | N8: Non-Controllable | O8: Mgmt | P8: Capital
C9: Model Year | D9: Fiscal Year | E9: Growth | F9: Rent | G9: Vacancy | H9: Vacancy | I9: Beds | J9: Bad Debt | K9: Concessions | L9: Income | M9: Expenses | N9: Expenses | O9: Fees | P9: Reserves
C10: 1 | D10: =TEXT('Summary & Assumptions'!$H$38+(366*(C10-1)),"yyyy")&"-"&TEXT('Summary & Assumptions'!$H$38+366*(C10),"yy") -> 2022-23 | E10: 0.03 | F10: =+'Unit Mix'!K20 -> 3.7181122 | G10: 0.05 | H10: 0.1 | I10: 0.0025 | J10: 0.0075 | K10: 0.01 | L10: 0 | M10: 0 | N10: 0 | O10: 0.03 | P10: 150
C11: 2 | D11: =TEXT('Summary & Assumptions'!$H$38+(366*(C11-1)),"yyyy")&"-"&TEXT('Summary & Assumptions'!$H$38+366*(C11),"yy") -> 2023-24 | E11: 0.03 | F11: =F10*(1+E11) -> 3.8296556 | G11: 0.05 | H11: 0.1 | I11: 0.0025 | J11: 0.0075 | K11: 0.01 | L11: 0 | M11: 0 | N11: 0 | O11: 0.03 | P11: 150
C12: 3 | D12: =TEXT('Summary & Assumptions'!$H$38+(366*(C12-1)),"yyyy")&"-"&TEXT('Summary & Assumptions'!$H$38+366*(C12),"yy") -> 2024-25 | E12: 0.03 | F12: =F11*(1+E12) -> 3.9445453 | G12: 0.05 | H12: 0.1 | I12: 0.0025 | J12: 0.0075 | K12: 0.01 | L12: 0 | M12: 0 | N12: 0 | O12: 0.03 | P12: 150
C13: 4 | D13: =TEXT('Summary & Assumptions'!$H$38+(366*(C13-1)),"yyyy")&"-"&TEXT('Summary & Assumptions'!$H$38+366*(C13),"yy") -> 2025-26 | E13: 0.03 | F13: =F12*(1+E13) -> 4.0628816 | G13: 0.05 | H13: 0.1 | I13: 0.0025 | J13: 0.0075 | K13: 0.01 | L13: 0 | M13: 0 | N13: 0 | O13: 0.03 | P13: 150
C14: 5 | D14: =TEXT('Summary & Assumptions'!$H$38+(366*(C14-1)),"yyyy")&"-"&TEXT('Summary & Assumptions'!$H$38+366*(C14),"yy") -> 2026-27 | E14: 0.03 | F14: =F13*(1+E14) -> 4.1847681 | G14: 0.05 | H14: 0.1 | I14: 0.0025 | J14: 0.0075 | K14: 0.0025 | L14: 0.03 | M14: 0.03 | N14: 0.03 | O14: 0.03 | P14: 150
C15: 6 | D15: =TEXT('Summary & Assumptions'!$H$38+(366*(C15-1)),"yyyy")&"-"&TEXT('Summary & Assumptions'!$H$38+366*(C15),"yy") -> 2027-28 | E15: 0.03 | F15: =F14*(1+E15) -> 4.3103111 | G15: 0.05 | H15: 0.1 | I15: 0.0025 | J15: 0.0075 | K15: 0.0025 | L15: 0.03 | M15: 0.03 | N15: 0.03 | O15: 0.03 | P15: 150
C16: 7 | D16: =TEXT('Summary & Assumptions'!$H$38+(366*(C16-1)),"yyyy")&"-"&TEXT('Summary & Assumptions'!$H$38+366*(C16),"yy") -> 2028-29 | E16: 0.03 | F16: =F15*(1+E16) -> 4.4396205 | G16: 0.05 | H16: 0.1 | I16: 0.0025 | J16: 0.0075 | K16: 0.0025 | L16: 0.03 | M16: 0.03 | N16: 0.03 | O16: 0.03 | P16: 150
C17: 8 | D17: =TEXT('Summary & Assumptions'!$H$38+(366*(C17-1)),"yyyy")&"-"&TEXT('Summary & Assumptions'!$H$38+366*(C17),"yy") -> 2029-30 | E17: 0.03 | F17: =F16*(1+E17) -> 4.5728091 | G17: 0.05 | H17: 0.1 | I17: 0.0025 | J17: 0.0075 | K17: 0.0025 | L17: 0.03 | M17: 0.03 | N17: 0.03 | O17: 0.03 | P17: 150
C18: 9 | D18: =TEXT('Summary & Assumptions'!$H$38+(366*(C18-1)),"yyyy")&"-"&TEXT('Summary & Assumptions'!$H$38+366*(C18),"yy") -> 2030-31 | E18: 0.03 | F18: =F17*(1+E18) -> 4.7099934 | G18: 0.05 | H18: 0.1 | I18: 0.0025 | J18: 0.0075 | K18: 0.0025 | L18: 0.03 | M18: 0.03 | N18: 0.03 | O18: 0.03 | P18: 150
C19: 10 | D19: =TEXT('Summary & Assumptions'!$H$38+(366*(C19-1)),"yyyy")&"-"&TEXT('Summary & Assumptions'!$H$38+366*(C19),"yy") -> 2031-32 | E19: 0.03 | F19: =F18*(1+E19) -> 4.8512932 | G19: 0.05 | H19: 0.1 | I19: 0.0025 | J19: 0.0075 | K19: 0.0025 | L19: 0.03 | M19: 0.03 | N19: 0.03 | O19: 0.03 | P19: 150
C20: 11 | D20: =TEXT('Summary & Assumptions'!$H$38+(366*(C20-1)),"yyyy")&"-"&TEXT('Summary & Assumptions'!$H$38+366*(C20),"yy") -> 2032-33 | E20: 0.03 | F20: =F19*(1+E20) -> 4.9968319 | G20: 0.05 | H20: 0.1 | I20: 0.0025 | J20: 0.0075 | K20: 0.0025 | L20: 0.03 | M20: 0.03 | N20: 0.03 | O20: 0.03 | P20: 150

Sheet Sales Comps
B2: 425 Colorado St
B3: Comparables
B6: Glendale Multi-Family Sale Comparables
B7: # | C7: Property Name | D7: Property Address | E7: Submarket | F7: Built/Reno | G7: Sale Date | H7: Units | I7: NRSF | J7: Sale Price | L7: $/Unit | M7: $ / NRSF | N7: Cap Rate | O7: Buyer | P7: Seller | Q7: Comments
B8: 1 | C8: Altana Apartments | D8: 633 N Central Ave | E8: Downtown Glendale | F8: 2017 | G8: 44308 | H8: 507 | I8: 550872 | J8: 300000000 | L8: =+J8/H8 -> 591715.98 | M8: =+J8/I8 -> 544.59112 | N8: 0.0335 | O8: Waterford Property Company | P8: Brookfield Property Group
B9: =+B8+1 -> 2 | C9: Next on Lex | D9: 275 W Lexington Dr | E9: Downtown Glendale | F9: 2019 | G9: 44286 | H9: 494 | I9: 458600 | J9: 290000000 | L9: =+J9/H9 -> 587044.53 | M9: =+J9/I9 -> 632.35935 | N9: 0.0327 | O9: California Community Housing Agency ("CalCHA") | P9: Cypress Equity Investments LLC
B10: =+B9+1 -> 3 | C10: Brio Apartments | D10: 546 W Colorado St | E10: Pacific-Edison | F10: 2013 | G10: 44286 | H10: 205 | I10: 237267 | J10: 110000000 | L10: =+J10/H10 -> 536585.37 | M10: =+J10/I10 -> 463.61272 | N10: 0.035 | O10: California Community Housing Agency ("CalCHA") | P10: Sequoia Equities, Inc
B11: =+B10+1 -> 4 | C11: The Harrison Glendale | D11: 318 W Wilson Ave | E11: Vineyard | F11: 2018 | G11: 44270 | H11: 164 | I11: 128790 | J11: 90700000 | L11: =+J11/H11 -> 553048.78 | M11: =+J11/I11 -> 704.24722 | N11: 0.039 | O11: JRK Property Holdings | P11: Molasky Ventures LLC
B12: =+B11+1 -> 5 | C12: 416 on Broadway | D12: 416 E Broadway | E12: Downtown Glendale | F12: 2009 | G12: 44132 | H12: 115 | I12: 126782 | J12: 60000000 | L12: =+J12/H12 -> 521739.13 | M12: =+J12/I12 -> 473.2533 | N12: 0.04 | O12: Fairmont Management Company | P12: Essex Property Trust, Inc.
B13: =+B12+1 -> 6 | C13: The Griffith | D13: 435 W Los Feliz Rd | E13: Tropico | F13: 2018 | G13: 43783 | H13: 220 | I13: 193953 | J13: 118500000 | L13: =+J13/H13 -> 538636.36 | M13: =+J13/I13 -> 610.97276 | N13: 0.04 | O13: Greystar Real Estate Partners | P13: PNC Realty Advisors
B14: =+B13+1 -> 7 | C14: ONYX Glendale | D14: 313 W California Ave | E14: Vineyard | F14: 2017 | G14: 43313 | H14: 183 | I14: 212943 | J14: 86200000 | L14: =+J14/H14 -> 471038.25 | M14: =+J14/I14 -> 404.80316 | N14: 0.043 | O14: MetLife, Inc. | P14: The Carlyle Group
B15: =+B14+1 -> 8 | C15: Altana Apartments | D15: 633 N Central Ave (Part of Portfolio) | E15: Downtown Glendale | F15: 2017 | G15: 43239 | H15: 507 | I15: 550872 | J15: 256000000 | L15: =+J15/H15 -> 504930.97 | M15: =+J15/I15 -> 464.71776 | N15: 0.04 | O15: Brookfield Property Group | P15: Carmel Partners
C16: Average | H16: =AVERAGE(H8:H15) -> 299.375 | I16: =AVERAGE(I8:I15) -> 307509.88 | J16: =SUMPRODUCT(J8:J15, $H8:$H15)/SUM($H8:$H15) -> 2.1349537e+08 | L16: =SUMPRODUCT(L8:L15, $H8:$H15)/SUM($H8:$H15) -> 547557.41 | M16: =SUMPRODUCT(M8:M15,$I8:$I15)/SUM($I8:$I15) -> 533.07231 | N16: =AVERAGE(N8:N15) -> 0.0379
C17: =TEXT(B2, 0) & " Acquisition Price" -> 425 Colorado St Acquisition Price | H17: ='Unit Mix'!$D$19 -> 144 | I17: ='Summary & Assumptions'!H16 -> 101920 | J17: ='Summary & Assumptions'!L22 -> 28800000 | L17: =+J17/H17 -> 200000 | M17: =+J17/I17 -> 282.57457 | N17: N/A*
C18: Premium/(Discount) to Comps | L18: =IFERROR(L17/L$16-1,"N/A") -> -0.6347415 | M18: =M17/M$16-1 -> -0.46991325 | N18: =IFERROR(N17/N$16-1,"N/A") -> N/A
C19: =TEXT(B2, 0) & " Stabilized Cost" -> 425 Colorado St Stabilized Cost | H19: =H17 -> 144 | I19: =I17 -> 101920 | J19: ='Summary & Assumptions'!M14 -> 54116596 | L19: =+J19/H19 -> 375809.7 | M19: =+J19/I19 -> 530.97131 | N19: ='Summary & Assumptions'!K41 -> 0.059773244
C20: Premium/(Discount) to Comps | L20: =IFERROR(L19/L$16-1,"N/A") -> -0.31366157 | M20: =M19/M$16-1 -> -0.0039413031 | N20: =IFERROR(N19/N$16-1,"N/A") -> 0.57713045
B21: Source: CoStar
B22: *Per January 2022 rent roll, existing office space is only 24% leased

Sheet LIBOR
C3: 44077 | D3: 44109 | E3: 44138 | F3: 44168 | G3: 44200 | H3: 44230 | I3: 44258 | J3: 44291 | K3: 44319 | L3: 44350 | M3: 44382 | N3: 44411 | O3: 44442 | P3: 44473 | Q3: 44503 | R3: 44533 | S3: 44564 | T3: 44595 | U3: 44623 | V3: 44655 | W3: 44684 | X3: 44715 | Y3: 44746 | Z3: 44776 | AA3: 44809 | AB3: 44837 | AC3: 44868 | AD3: 44900 | AE3: 44929 | AF3: 44960 | AG3: 44988 | AH3: 45019 | AI3: 45049 | AJ3: 45082 | AK3: 45110 | AL3: 45141 | AM3: 45173 | AN3: 45202 | AO3: 45233 | AP3: 45264 | AQ3: 45294 | AR3: 45327 | AS3: 45355 | AT3: 45385 | AU3: 45415 | AV3: 45446 | AW3: 45476 | AX3: 45509 | AY3: 45538 | AZ3: 45568 | BA3: 45600 | BB3: 45629 | BC3: 45660 | BD3: 45691 | BE3: 45719 | BF3: 45750 | BG3: 45782 | BH3: 45811 | BI3: 45841 | BJ3: 45873 | BK3: 45903 | BL3: 45933 | BM3: 45964 | BN3: 45994 | BO3: 46027 | BP3: 46056 | BQ3: 46084 | BR3: 46115 | BS3: 46146 | BT3: 46176 | BU3: 46206 | BV3: 46237 | BW3: 46268 | BX3: 46300 | BY3: 46329 | BZ3: 46359 | CA3: 46391 | CB3: 46421 | CC3: 46449 | CD3: 46482 | CE3: 46510 | CF3: 46541 | CG3: 46573 | CH3: 46602 | CI3: 46633 | CJ3: 46664 | CK3: 46694 | CL3: 46724 | CM3: 46755 | CN3: 46786 | CO3: 46815 | CP3: 46846 | CQ3: 46876 | CR3: 46909 | CS3: 46937 | CT3: 46968 | CU3: 47000 | CV3: 47029 | CW3: 47060 | CX3: 47091 | CY3: 47121 | CZ3: 47154 | DA3: 47182 | DB3: 47211 | DC3: 47241 | DD3: 47273 | DE3: 47302 | DF3: 47333 | DG3: 47364 | DH3: 47394 | DI3: 47427 | DJ3: 47455 | DK3: 47486 | DL3: 47518 | DM3: 47546 | DN3: 47576 | DO3: 47606 | DP3: 47637 | DQ3: 47667 | DR3: 47700 | DS3: 47729
C4: =EOMONTH(C3,0) -> 44104 | D4: =EOMONTH(D3,0) -> 44135 | E4: =EOMONTH(E3,0) -> 44165 | F4: =EOMONTH(F3,0) -> 44196 | G4: =EOMONTH(G3,0) -> 44227 | H4: =EOMONTH(H3,0) -> 44255 | I4: =EOMONTH(I3,0) -> 44286 | J4: =EOMONTH(J3,0) -> 44316 | ... DS4: =EOMONTH(DS3,0) -> 47756
C5: 0.0015653 | D5: 0.001515 | E5: 0.0016573 | F5: 0.0019812 | G5: 0.0021553 | H5: 0.0020255 | I5: 0.0016903 | J5: 0.0013855 | K5: 0.0011693 | L5: 0.001111 | M5: 0.0011638 | N5: 0.0012339 | O5: 0.0013231 | P5: 0.0014038 | Q5: 0.0014481 | R5: 0.001457 | S5: 0.0014293 | T5: 0.0013381 | U5: 0.0012346 | V5: 0.0011446 | W5: 0.001056 | X5: 0.0010088 | Y5: 0.0010073 | Z5: 0.0010217 | AA5: 0.0010801 | AB5: 0.0011545 | AC5: 0.0012321 | AD5: 0.0013311 | AE5: 0.001428 | AF5: 0.0015208 | AG5: 0.0016196 | AH5: 0.0017258 | AI5: 0.0018206 | AJ5: 0.0019315 | AK5: 0.0020359 | AL5: 0.002139 | AM5: 0.0022493 | AN5: 0.0023796 | AO5: 0.0024914 | AP5: 0.0026133 | AQ5: 0.0027561 | AR5: 0.0028876 | AS5: 0.0030094 | AT5: 0.0031598 | AU5: 0.0032882 | AV5: 0.0034247 | AW5: 0.0035819 | AX5: 0.0037284 | AY5: 0.00387 | AZ5: 0.004035 | BA5: 0.0041828 | BB5: 0.0043561 | BC5: 0.0045384 | BD5: 0.0047019 | BE5: 0.0048843 | BF5: 0.005087 | BG5: 0.0052815 | BH5: 0.0054663 | BI5: 0.0056768 | BJ5: 0.0058676 | BK5: 0.0060834 | BL5: 0.0063004 | BM5: 0.0064912 | BN5: 0.0067012 | BO5: 0.0069217 | BP5: 0.0070957 | BQ5: 0.0072845 | BR5: 0.0074783 | BS5: 0.0076397 | BT5: 0.0078274 | BU5: 0.0080079 | BV5: 0.0081616 | BW5: 0.0083316 | BX5: 0.00851 | BY5: 0.0086473 | BZ5: 0.0087987 | CA5: 0.0089511 | CB5: 0.0090868 | CC5: 0.0092189 | CD5: 0.0093594 | CE5: 0.009454 | CF5: 0.009571 | CG5: 0.0096878 | CH5: 0.0097687 | CI5: 0.009862 | CJ5: 0.0099618 | CK5: 0.0100474 | CL5: 0.0101418 | CM5: 0.0102421 | CN5: 0.0103342 | CO5: 0.0104295 | CP5: 0.010532 | CQ5: 0.0106182 | CR5: 0.0107187 | CS5: 0.0108125 | CT5: 0.0108975 | CU5: 0.0109876 | CV5: 0.0110921 | CW5: 0.011172 | CX5: 0.0112585 | CY5: 0.0113585 | CZ5: 0.0114391 | DA5: 0.0115204 | DB5: 0.0116023 | DC5: 0.0116722 | DD5: 0.0117472 | DE5: 0.0118345 | DF5: 0.0118975 | DG5: 0.0119672 | DH5: 0.0120487 | DI5: 0.0121092 | DJ5: 0.012167 | DK5: 0.0122401 | DL5: 0.0122865 | DM5: 0.0123394 | DN5: 0.0123987 | DO5: 0.0124325 | DP5: 0.0124732 | DQ5: 0.0125244 | DR5: 0.0125562 | DS5: 0.0125924
C9: DATE | D9: Begging of Mo | E9: End of Mo | F9: LIBOR
C10: 44077 | D10: =EOMONTH(C10,-1)+1 -> 44075 | E10: =EOMONTH(C10,0) -> 44104 | F10: 0.0015653
C11: 44109 | D11: =EOMONTH(C11,-1)+1 -> 44105 | E11: =EOMONTH(C11,0) -> 44135 | F11: 0.001515
C12: 44138 | D12: =EOMONTH(C12,-1)+1 -> 44136 | E12: =EOMONTH(C12,0) -> 44165 | F12: 0.0016573
C13: 44168 | D13: =EOMONTH(C13,-1)+1 -> 44166 | E13: =EOMONTH(C13,0) -> 44196 | F13: 0.0019812
C14: 44200 | D14: =EOMONTH(C14,-1)+1 -> 44197 | E14: =EOMONTH(C14,0) -> 44227 | F14: 0.0021553
C15: 44230 | D15: =EOMONTH(C15,-1)+1 -> 44228 | E15: =EOMONTH(C15,0) -> 44255 | F15: 0.0020255
C16: 44258 | D16: =EOMONTH(C16,-1)+1 -> 44256 | E16: =EOMONTH(C16,0) -> 44286 | F16: 0.0016903
C17: 44291 | D17: =EOMONTH(C17,-1)+1 -> 44287 | E17: =EOMONTH(C17,0) -> 44316 | F17: 0.0013855
C18: 44319 | D18: =EOMONTH(C18,-1)+1 -> 44317 | E18: =EOMONTH(C18,0) -> 44347 | F18: 0.0011693
C19: 44350 | D19: =EOMONTH(C19,-1)+1 -> 44348 | E19: =EOMONTH(C19,0) -> 44377 | F19: 0.001111
C20: 44382 | D20: =EOMONTH(C20,-1)+1 -> 44378 | E20: =EOMONTH(C20,0) -> 44408 | F20: 0.0011638
C21: 44411 | D21: =EOMONTH(C21,-1)+1 -> 44409 | E21: =EOMONTH(C21,0) -> 44439 | F21: 0.0012339
... C130: 47729 | D130: =EOMONTH(C130,-1)+1 -> 47727 | E130: =EOMONTH(C130,0) -> 47756 | F130: 0.0125924

Sheet Construction Curve
A1: Percentage Allocation | B1: 1
A2: Standard Deviation | B2: 2 | E2: Construction Start Month --> | G2: =B3 -> 25 | H2: =G2+1 -> 26 | I2: =H2+1 -> 27 | J2: =I2+1 -> 28 | K2: =J2+1 -> 29 | L2: =K2+1 -> 30 | M2: =L2+1 -> 31 | N2: =M2+1 -> 32 | O2: =N2+1 -> 33 | ... BN2: =BM2+1 -> 84
A3: Construction Start | B3: =DATEDIF('Summary & Assumptions'!H38,'Summary & Assumptions'!H41,"m") -> 25 | E3: =SUM(G3:BN3) -> 1 | G3: =SUMIFS(G7:G66,$E$7:$E$66,$B$4) -> 0.015683658 | H3: =SUMIFS(H7:H66,$E$7:$E$66,$B$4) -> 0.023244351 | I3: =SUMIFS(I7:I66,$E$7:$E$66,$B$4) -> 0.032796565 | J3: =SUMIFS(J7:J66,$E$7:$E$66,$B$4) -> 0.044053489 | K3: =SUMIFS(K7:K66,$E$7:$E$66,$B$4) -> 0.056334364 | L3: =SUMIFS(L7:L66,$E$7:$E$66,$B$4) -> 0.068581621 | M3: =SUMIFS(M7:M66,$E$7:$E$66,$B$4) -> 0.07948468 | N3: =SUMIFS(N7:N66,$E$7:$E$66,$B$4) -> 0.087700186 | ... BN3: =SUMIFS(BN7:BN66,$E$7:$E$66,$B$4) -> 0
A4: Construction Length | B4: ='Summary & Assumptions'!H42 -> 18
G5: Monthly Distributional Allocation
F6: 0 | G6: 1 | H6: =G6+1 -> 2 | I6: =H6+1 -> 3 | J6: =I6+1 -> 4 | K6: =J6+1 -> 5 | L6: =K6+1 -> 6 | M6: =L6+1 -> 7 | N6: =M6+1 -> 8 | O6: =N6+1 -> 9 | ... BN6: =BM6+1 -> 60
D7: =SUM(G7:BN7) -> 1 | E7: 1 | G7: =IF(G$6>$E7,0,(NORMSDIST(G70)-NORMSDIST(F70))*$B$1/(1-2*NORMSDIST($F70))) -> 1 | H7: =IF(H$6>$E7,0,(NORMSDIST(H70)-NORMSDIST(G70))*$B$1/(1-2*NORMSDIST($F70))) -> 0 | I7: =IF(I$6>$E7,0,(NORMSDIST(I70)-NORMSDIST(H70))*$B$1/(1-2*NORMSDIST($F70))) -> 0 | J7: =IF(J$6>$E7,0,(NORMSDIST(J70)-NORMSDIST(I70))*$B$1/(1-2*NORMSDIST($F70))) -> 0 | K7: =IF(K$6>$E7,0,(NORMSDIST(K70)-NORMSDIST(J70))*$B$1/(1-2*NORMSDIST($F70))) -> 0 | L7: =IF(L$6>$E7,0,(NORMSDIST(L70)-NORMSDIST(K70))*$B$1/(1-2*NORMSDIST($F70))) -> 0 | M7: =IF(M$6>$E7,0,(NORMSDIST(M70)-NORMSDIST(L70))*$B$1/(1-2*NORMSDIST($F70))) -> 0 | N7: =IF(N$6>$E7,0,(NORMSDIST(N70)-NORMSDIST(M70))*$B$1/(1-2*NORMSDIST($F70))) -> 0 | ... BN7: =IF(BN$6>$E7,0,(NORMSDIST(BN70)-NORMSDIST(BM70))*$B$1/(1-2*NORMSDIST($F70))) -> 0
D8: =SUM(G8:BN8) -> 1 | E8: =E7+1 -> 2 | G8: =IF(G$6>$E8,0,(NORMSDIST(G71)-NORMSDIST(F71))*$B$1/(1-2*NORMSDIST($F71))) -> 0.5 | H8: =IF(H$6>$E8,0,(NORMSDIST(H71)-NORMSDIST(G71))*$B$1/(1-2*NORMSDIST($F71))) -> 0.5 | I8: =IF(I$6>$E8,0,(NORMSDIST(I71)-NORMSDIST(H71))*$B$1/(1-2*NORMSDIST($F71))) -> 0 | J8: =IF(J$6>$E8,0,(NORMSDIST(J71)-NORMSDIST(I71))*$B$1/(1-2*NORMSDIST($F71))) -> 0 | K8: =IF(K$6>$E8,0,(NORMSDIST(K71)-NORMSDIST(J71))*$B$1/(1-2*NORMSDIST($F71))) -> 0 | L8: =IF(L$6>$E8,0,(NORMSDIST(L71)-NORMSDIST(K71))*$B$1/(1-2*NORMSDIST($F71))) -> 0 | M8: =IF(M$6>$E8,0,(NORMSDIST(M71)-NORMSDIST(L71))*$B$1/(1-2*NORMSDIST($F71))) -> 0 | N8: =IF(N$6>$E8,0,(NORMSDIST(N71)-NORMSDIST(M71))*$B$1/(1-2*NORMSDIST($F71))) -> 0 | ... BN8: =IF(BN$6>$E8,0,(NORMSDIST(BN71)-NORMSDIST(BM71))*$B$1/(1-2*NORMSDIST($F71))) -> 0
D9: =SUM(G9:BN9) -> 1 | E9: =E8+1 -> 3 | G9: =IF(G$6>$E9,0,(NORMSDIST(G72)-NORMSDIST(F72))*$B$1/(1-2*NORMSDIST($F72))) -> 0.24069405 | H9: =IF(H$6>$E9,0,(NORMSDIST(H72)-NORMSDIST(G72))*$B$1/(1-2*NORMSDIST($F72))) -> 0.5186119 | I9: =IF(I$6>$E9,0,(NORMSDIST(I72)-NORMSDIST(H72))*$B$1/(1-2*NORMSDIST($F72))) -> 0.24069405 | J9: =IF(J$6>$E9,0,(NORMSDIST(J72)-NORMSDIST(I72))*$B$1/(1-2*NORMSDIST($F72))) -> 0 | K9: =IF(K$6>$E9,0,(NORMSDIST(K72)-NORMSDIST(J72))*$B$1/(1-2*NORMSDIST($F72))) -> 0 | L9: =IF(L$6>$E9,0,(NORMSDIST(L72)-NORMSDIST(K72))*$B$1/(1-2*NORMSDIST($F72))) -> 0 | M9: =IF(M$6>$E9,0,(NORMSDIST(M72)-NORMSDIST(L72))*$B$1/(1-2*NORMSDIST($F72))) -> 0 | N9: =IF(N$6>$E9,0,(NORMSDIST(N72)-NORMSDIST(M72))*$B$1/(1-2*NORMSDIST($F72))) -> 0 | ... BN9: =IF(BN$6>$E9,0,(NORMSDIST(BN72)-NORMSDIST(BM72))*$B$1/(1-2*NORMSDIST($F72))) -> 0
D10: =SUM(G10:BN10) -> 1 | E10: =E9+1 -> 4 | G10: =IF(G$6>$E10,0,(NORMSDIST(G73)-NORMSDIST(F73))*$B$1/(1-2*NORMSDIST($F73))) -> 0.14238361 | H10: =IF(H$6>$E10,0,(NORMSDIST(H73)-NORMSDIST(G73))*$B$1/(1-2*NORMSDIST($F73))) -> 0.35761639 | I10: =IF(I$6>$E10,0,(NORMSDIST(I73)-NORMSDIST(H73))*$B$1/(1-2*NORMSDIST($F73))) -> 0.35761639 | J10: =IF(J$6>$E10,0,(NORMSDIST(J73)-NORMSDIST(I73))*$B$1/(1-2*NORMSDIST($F73))) -> 0.14238361 | K10: =IF(K$6>$E10,0,(NORMSDIST(K73)-NORMSDIST(J73))*$B$1/(1-2*NORMSDIST($F73))) -> 0 | L10: =IF(L$6>$E10,0,(NORMSDIST(L73)-NORMSDIST(K73))*$B$1/(1-2*NORMSDIST($F73))) -> 0 | M10: =IF(M$6>$E10,0,(NORMSDIST(M73)-NORMSDIST(L73))*$B$1/(1-2*NORMSDIST($F73))) -> 0 | N10: =IF(N$6>$E10,0,(NORMSDIST(N73)-NORMSDIST(M73))*$B$1/(1-2*NORMSDIST($F73))) -> 0 | ... BN10: =IF(BN$6>$E10,0,(NORMSDIST(BN73)-NORMSDIST(BM73))*$B$1/(1-2*NORMSDIST($F73))) -> 0
D11: =SUM(G11:BN11) -> 1 | E11: =E10+1 -> 5 | G11: =IF(G$6>$E11,0,(NORMSDIST(G74)-NORMSDIST(F74))*$B$1/(1-2*NORMSDIST($F74))) -> 0.096720339 | H11: =IF(H$6>$E11,0,(NORMSDIST(H74)-NORMSDIST(G74))*$B$1/(1-2*NORMSDIST($F74))) -> 0.24044908 | I11: =IF(I$6>$E11,0,(NORMSDIST(I74)-NORMSDIST(H74))*$B$1/(1-2*NORMSDIST($F74))) -> 0.32566115 | J11: =IF(J$6>$E11,0,(NORMSDIST(J74)-NORMSDIST(I74))*$B$1/(1-2*NORMSDIST($F74))) -> 0.24044908 | K11: =IF(K$6>$E11,0,(NORMSDIST(K74)-NORMSDIST(J74))*$B$1/(1-2*NORMSDIST($F74))) -> 0.096720339 | L11: =IF(L$6>$E11,0,(NORMSDIST(L74)-NORMSDIST(K74))*$B$1/(1-2*NORMSDIST($F74))) -> 0 | M11: =IF(M$6>$E11,0,(NORMSDIST(M74)-NORMSDIST(L74))*$B$1/(1-2*NORMSDIST($F74))) -> 0 | N11: =IF(N$6>$E11,0,(NORMSDIST(N74)-NORMSDIST(M74))*$B$1/(1-2*NORMSDIST($F74))) -> 0 | ... BN11: =IF(BN$6>$E11,0,(NORMSDIST(BN74)-NORMSDIST(BM74))*$B$1/(1-2*NORMSDIST($F74))) -> 0
D12: =SUM(G12:BN12) -> 1 | E12: =E11+1 -> 6 | G12: =IF(G$6>$E12,0,(NORMSDIST(G75)-NORMSDIST(F75))*$B$1/(1-2*NORMSDIST($F75))) -> 0.071724575 | H12: =IF(H$6>$E12,0,(NORMSDIST(H75)-NORMSDIST(G75))*$B$1/(1-2*NORMSDIST($F75))) -> 0.16896947 | I12: =IF(I$6>$E12,0,(NORMSDIST(I75)-NORMSDIST(H75))*$B$1/(1-2*NORMSDIST($F75))) -> 0.25930595 | J12: =IF(J$6>$E12,0,(NORMSDIST(J75)-NORMSDIST(I75))*$B$1/(1-2*NORMSDIST($F75))) -> 0.25930595 | K12: =IF(K$6>$E12,0,(NORMSDIST(K75)-NORMSDIST(J75))*$B$1/(1-2*NORMSDIST($F75))) -> 0.16896947 | L12: =IF(L$6>$E12,0,(NORMSDIST(L75)-NORMSDIST(K75))*$B$1/(1-2*NORMSDIST($F75))) -> 0.071724575 | M12: =IF(M$6>$E12,0,(NORMSDIST(M75)-NORMSDIST(L75))*$B$1/(1-2*NORMSDIST($F75))) -> 0 | N12: =IF(N$6>$E12,0,(NORMSDIST(N75)-NORMSDIST(M75))*$B$1/(1-2*NORMSDIST($F75))) -> 0 | ... BN12: =IF(BN$6>$E12,0,(NORMSDIST(BN75)-NORMSDIST(BM75))*$B$1/(1-2*NORMSDIST($F75))) -> 0
D13: =SUM(G13:BN13) -> 1 | E13: =E12+1 -> 7 | G13: =IF(G$6>$E13,0,(NORMSDIST(G76)-NORMSDIST(F76))*$B$1/(1-2*NORMSDIST($F76))) -> 0.056378846 | H13: =IF(H$6>$E13,0,(NORMSDIST(H76)-NORMSDIST(G76))*$B$1/(1-2*NORMSDIST($F76))) -> 0.12479757 | I13: =IF(I$6>$E13,0,(NORMSDIST(I76)-NORMSDIST(H76))*$B$1/(1-2*NORMSDIST($F76))) -> 0.20101159 | J13: =IF(J$6>$E13,0,(NORMSDIST(J76)-NORMSDIST(I76))*$B$1/(1-2*NORMSDIST($F76))) -> 0.23562399 | K13: =IF(K$6>$E13,0,(NORMSDIST(K76)-NORMSDIST(J76))*$B$1/(1-2*NORMSDIST($F76))) -> 0.20101159 | L13: =IF(L$6>$E13,0,(NORMSDIST(L76)-NORMSDIST(K76))*$B$1/(1-2*NORMSDIST($F76))) -> 0.12479757 | M13: =IF(M$6>$E13,0,(NORMSDIST(M76)-NORMSDIST(L76))*$B$1/(1-2*NORMSDIST($F76))) -> 0.056378846 | N13: =IF(N$6>$E13,0,(NORMSDIST(N76)-NORMSDIST(M76))*$B$1/(1-2*NORMSDIST($F76))) -> 0 | ... BN13: =IF(BN$6>$E13,0,(NORMSDIST(BN76)-NORMSDIST(BM76))*$B$1/(1-2*NORMSDIST($F76))) -> 0
D14: =SUM(G14:BN14) -> 1 | E14: =E13+1 -> 8 | G14: =IF(G$6>$E14,0,(NORMSDIST(G77)-NORMSDIST(F77))*$B$1/(1-2*NORMSDIST($F77))) -> 0.046157236 | H14: =IF(H$6>$E14,0,(NORMSDIST(H77)-NORMSDIST(G77))*$B$1/(1-2*NORMSDIST($F77))) -> 0.096226378 | I14: =IF(I$6>$E14,0,(NORMSDIST(I77)-NORMSDIST(H77))*$B$1/(1-2*NORMSDIST($F77))) -> 0.15702706 | J14: =IF(J$6>$E14,0,(NORMSDIST(J77)-NORMSDIST(I77))*$B$1/(1-2*NORMSDIST($F77))) -> 0.20058933 | K14: =IF(K$6>$E14,0,(NORMSDIST(K77)-NORMSDIST(J77))*$B$1/(1-2*NORMSDIST($F77))) -> 0.20058933 | L14: =IF(L$6>$E14,0,(NORMSDIST(L77)-NORMSDIST(K77))*$B$1/(1-2*NORMSDIST($F77))) -> 0.15702706 | M14: =IF(M$6>$E14,0,(NORMSDIST(M77)-NORMSDIST(L77))*$B$1/(1-2*NORMSDIST($F77))) -> 0.096226378 | N14: =IF(N$6>$E14,0,(NORMSDIST(N77)-NORMSDIST(M77))*$B$1/(1-2*NORMSDIST($F77))) -> 0.046157236 | ... BN14: =IF(BN$6>$E14,0,(NORMSDIST(BN77)-NORMSDIST(BM77))*$B$1/(1-2*NORMSDIST($F77))) -> 0
D15: =SUM(G15:BN15) -> 1 | E15: =E14+1 -> 9 | G15: =IF(G$6>$E15,0,(NORMSDIST(G78)-NORMSDIST(F78))*$B$1/(1-2*NORMSDIST($F78))) -> 0.03892801 | H15: =IF(H$6>$E15,0,(NORMSDIST(H78)-NORMSDIST(G78))*$B$1/(1-2*NORMSDIST($F78))) -> 0.076850054 | I15: =IF(I$6>$E15,0,(NORMSDIST(I78)-NORMSDIST(H78))*$B$1/(1-2*NORMSDIST($F78))) -> 0.12491598 | J15: =IF(J$6>$E15,0,(NORMSDIST(J78)-NORMSDIST(I78))*$B$1/(1-2*NORMSDIST($F78))) -> 0.16718487 | K15: =IF(K$6>$E15,0,(NORMSDIST(K78)-NORMSDIST(J78))*$B$1/(1-2*NORMSDIST($F78))) -> 0.18424217 | L15: =IF(L$6>$E15,0,(NORMSDIST(L78)-NORMSDIST(K78))*$B$1/(1-2*NORMSDIST($F78))) -> 0.16718487 | M15: =IF(M$6>$E15,0,(NORMSDIST(M78)-NORMSDIST(L78))*$B$1/(1-2*NORMSDIST($F78))) -> 0.12491598 | N15: =IF(N$6>$E15,0,(NORMSDIST(N78)-NORMSDIST(M78))*$B$1/(1-2*NORMSDIST($F78))) -> 0.076850054 | ... BN15: =IF(BN$6>$E15,0,(NORMSDIST(BN78)-NORMSDIST(BM78))*$B$1/(1-2*NORMSDIST($F78))) -> 0
D16: =SUM(G16:BN16) -> 1 | E16: =E15+1 -> 10 | G16: =IF(G$6>$E16,0,(NORMSDIST(G79)-NORMSDIST(F79))*$B$1/(1-2*NORMSDIST($F79))) -> 0.033576918 | H16: =IF(H$6>$E16,0,(NORMSDIST(H79)-NORMSDIST(G79))*$B$1/(1-2*NORMSDIST($F79))) -> 0.063143421 | I16: =IF(I$6>$E16,0,(NORMSDIST(I79)-NORMSDIST(H79))*$B$1/(1-2*NORMSDIST($F79))) -> 0.10139943 | J16: =IF(J$6>$E16,0,(NORMSDIST(J79)-NORMSDIST(I79))*$B$1/(1-2*NORMSDIST($F79))) -> 0.13904966 | K16: =IF(K$6>$E16,0,(NORMSDIST(K79)-NORMSDIST(J79))*$B$1/(1-2*NORMSDIST($F79))) -> 0.16283058 | L16: =IF(L$6>$E16,0,(NORMSDIST(L79)-NORMSDIST(K79))*$B$1/(1-2*NORMSDIST($F79))) -> 0.16283058 | M16: =IF(M$6>$E16,0,(NORMSDIST(M79)-NORMSDIST(L79))*$B$1/(1-2*NORMSDIST($F79))) -> 0.13904966 | N16: =IF(N$6>$E16,0,(NORMSDIST(N79)-NORMSDIST(M79))*$B$1/(1-2*NORMSDIST($F79))) -> 0.10139943 | ... BN16: =IF(BN$6>$E16,0,(NORMSDIST(BN79)-NORMSDIST(BM79))*$B$1/(1-2*NORMSDIST($F79))) -> 0
D17: =SUM(G17:BN17) -> 1 | E17: =E16+1 -> 11 | G17: =IF(G$6>$E17,0,(NORMSDIST(G80)-NORMSDIST(F80))*$B$1/(1-2*NORMSDIST($F80))) -> 0.029472633 | H17: =IF(H$6>$E17,0,(NORMSDIST(H80)-NORMSDIST(G80))*$B$1/(1-2*NORMSDIST($F80))) -> 0.053091335 | I17: =IF(I$6>$E17,0,(NORMSDIST(I80)-NORMSDIST(H80))*$B$1/(1-2*NORMSDIST($F80))) -> 0.083911655 | J17: =IF(J$6>$E17,0,(NORMSDIST(J80)-NORMSDIST(I80))*$B$1/(1-2*NORMSDIST($F80))) -> 0.11636399 | K17: =IF(K$6>$E17,0,(NORMSDIST(K80)-NORMSDIST(J80))*$B$1/(1-2*NORMSDIST($F80))) -> 0.14158437 | L17: =IF(L$6>$E17,0,(NORMSDIST(L80)-NORMSDIST(K80))*$B$1/(1-2*NORMSDIST($F80))) -> 0.15115204 | M17: =IF(M$6>$E17,0,(NORMSDIST(M80)-NORMSDIST(L80))*$B$1/(1-2*NORMSDIST($F80))) -> 0.14158437 | N17: =IF(N$6>$E17,0,(NORMSDIST(N80)-NORMSDIST(M80))*$B$1/(1-2*NORMSDIST($F80))) -> 0.11636399 | ... BN17: =IF(BN$6>$E17,0,(NORMSDIST(BN80)-NORMSDIST(BM80))*$B$1/(1-2*NORMSDIST($F80))) -> 0
D18: =SUM(G18:BN18) -> 1 | E18: =E17+1 -> 12 | G18: =IF(G$6>$E18,0,(NORMSDIST(G81)-NORMSDIST(F81))*$B$1/(1-2*NORMSDIST($F81))) -> 0.026233868 | H18: =IF(H$6>$E18,0,(NORMSDIST(H81)-NORMSDIST(G81))*$B$1/(1-2*NORMSDIST($F81))) -> 0.045490707 | I18: =IF(I$6>$E18,0,(NORMSDIST(I81)-NORMSDIST(H81))*$B$1/(1-2*NORMSDIST($F81))) -> 0.070659039 | J18: =IF(J$6>$E18,0,(NORMSDIST(J81)-NORMSDIST(I81))*$B$1/(1-2*NORMSDIST($F81))) -> 0.098310434 | K18: =IF(K$6>$E18,0,(NORMSDIST(K81)-NORMSDIST(J81))*$B$1/(1-2*NORMSDIST($F81))) -> 0.12252366 | L18: =IF(L$6>$E18,0,(NORMSDIST(L81)-NORMSDIST(K81))*$B$1/(1-2*NORMSDIST($F81))) -> 0.13678229 | M18: =IF(M$6>$E18,0,(NORMSDIST(M81)-NORMSDIST(L81))*$B$1/(1-2*NORMSDIST($F81))) -> 0.13678229 | N18: =IF(N$6>$E18,0,(NORMSDIST(N81)-NORMSDIST(M81))*$B$1/(1-2*NORMSDIST($F81))) -> 0.12252366 | ... BN18: =IF(BN$6>$E18,0,(NORMSDIST(BN81)-NORMSDIST(BM81))*$B$1/(1-2*NORMSDIST($F81))) -> 0
D19: =SUM(G19:BN19) -> 1 | E19: =E18+1 -> 13 | G19: =IF(G$6>$E19,0,(NORMSDIST(G82)-NORMSDIST(F82))*$B$1/(1-2*NORMSDIST($F82))) -> 0.023618162 | H19: =IF(H$6>$E19,0,(NORMSDIST(H82)-NORMSDIST(G82))*$B$1/(1-2*NORMSDIST($F82))) -> 0.039592878 | I19: =IF(I$6>$E19,0,(NORMSDIST(I82)-NORMSDIST(H82))*$B$1/(1-2*NORMSDIST($F82))) -> 0.060421456 | J19: =IF(J$6>$E19,0,(NORMSDIST(J82)-NORMSDIST(I82))*$B$1/(1-2*NORMSDIST($F82))) -> 0.083940146 | K19: =IF(K$6>$E19,0,(NORMSDIST(K82)-NORMSDIST(J82))*$B$1/(1-2*NORMSDIST($F82))) -> 0.10615823 | L19: =IF(L$6>$E19,0,(NORMSDIST(L82)-NORMSDIST(K82))*$B$1/(1-2*NORMSDIST($F82))) -> 0.12222042 | M19: =IF(M$6>$E19,0,(NORMSDIST(M82)-NORMSDIST(L82))*$B$1/(1-2*NORMSDIST($F82))) -> 0.12809743 | N19: =IF(N$6>$E19,0,(NORMSDIST(N82)-NORMSDIST(M82))*$B$1/(1-2*NORMSDIST($F82))) -> 0.12222042 | ... BN19: =IF(BN$6>$E19,0,(NORMSDIST(BN82)-NORMSDIST(BM82))*$B$1/(1-2*NORMSDIST($F82))) -> 0
... D66: =SUM(G66:BN66) -> 1 | E66: =E65+1 -> 60 | G66: =IF(G$6>$E66,0,(NORMSDIST(G129)-NORMSDIST(F129))*$B$1/(1-2*NORMSDIST($F129))) -> 0.0040308467 | H66: =IF(H$6>$E66,0,(NORMSDIST(H129)-NORMSDIST(G129))*$B$1/(1-2*NORMSDIST($F129))) -> 0.0045851261 | I66: =IF(I$6>$E66,0,(NORMSDIST(I129)-NORMSDIST(H129))*$B$1/(1-2*NORMSDIST($F129))) -> 0.0051925037 | J66: =IF(J$6>$E66,0,(NORMSDIST(J129)-NORMSDIST(I129))*$B$1/(1-2*NORMSDIST($F129))) -> 0.0058542715 | K66: =IF(K$6>$E66,0,(NORMSDIST(K129)-NORMSDIST(J129))*$B$1/(1-2*NORMSDIST($F129))) -> 0.0065711203 | L66: =IF(L$6>$E66,0,(NORMSDIST(L129)-NORMSDIST(K129))*$B$1/(1-2*NORMSDIST($F129))) -> 0.0073430501 | M66: =IF(M$6>$E66,0,(NORMSDIST(M129)-NORMSDIST(L129))*$B$1/(1-2*NORMSDIST($F129))) -> 0.0081692857 | N66: =IF(N$6>$E66,0,(NORMSDIST(N129)-NORMSDIST(M129))*$B$1/(1-2*NORMSDIST($F129))) -> 0.0090482001 | ... BN66: =IF(BN$6>$E66,0,(NORMSDIST(BN129)-NORMSDIST(BM129))*$B$1/(1-2*NORMSDIST($F129))) -> 0.0040308467
F69: 0 | G69: 1 | H69: =G69+1 -> 2 | I69: =H69+1 -> 3 | J69: =I69+1 -> 4 | K69: =J69+1 -> 5 | L69: =K69+1 -> 6 | M69: =L69+1 -> 7 | N69: =M69+1 -> 8 | O69: =N69+1 -> 9 | ... BN69: =BM69+1 -> 60
E70: 1 | F70: =-$B$2 -> -2 | G70: =IF(G$69>$E70,0,(F70-((2*$F$70)/$E70))) -> 2 | H70: =IF(H$69>$E70,0,(G70-((2*$F$70)/$E70))) -> 0 | I70: =IF(I$69>$E70,0,(H70-((2*$F$70)/$E70))) -> 0 | J70: =IF(J$69>$E70,0,(I70-((2*$F$70)/$E70))) -> 0 | K70: =IF(K$69>$E70,0,(J70-((2*$F$70)/$E70))) -> 0 | L70: =IF(L$69>$E70,0,(K70-((2*$F$70)/$E70))) -> 0 | M70: =IF(M$69>$E70,0,(L70-((2*$F$70)/$E70))) -> 0 | N70: =IF(N$69>$E70,0,(M70-((2*$F$70)/$E70))) -> 0 | ... BN70: =IF(BN$69>$E70,0,(BM70-((2*$F$70)/$E70))) -> 0
E71: =E70+1 -> 2 | F71: =-$B$2 -> -2 | G71: =IF(G$69>$E71,0,(F71-((2*$F$70)/$E71))) -> 0 | H71: =IF(H$69>$E71,0,(G71-((2*$F$70)/$E71))) -> 2 | I71: =IF(I$69>$E71,0,(H71-((2*$F$70)/$E71))) -> 0 | J71: =IF(J$69>$E71,0,(I71-((2*$F$70)/$E71))) -> 0 | K71: =IF(K$69>$E71,0,(J71-((2*$F$70)/$E71))) -> 0 | L71: =IF(L$69>$E71,0,(K71-((2*$F$70)/$E71))) -> 0 | M71: =IF(M$69>$E71,0,(L71-((2*$F$70)/$E71))) -> 0 | N71: =IF(N$69>$E71,0,(M71-((2*$F$70)/$E71))) -> 0 | ... BN71: =IF(BN$69>$E71,0,(BM71-((2*$F$70)/$E71))) -> 0
E72: =E71+1 -> 3 | F72: =-$B$2 -> -2 | G72: =IF(G$69>$E72,0,(F72-((2*$F$70)/$E72))) -> -0.66666667 | H72: =IF(H$69>$E72,0,(G72-((2*$F$70)/$E72))) -> 0.66666667 | I72: =IF(I$69>$E72,0,(H72-((2*$F$70)/$E72))) -> 2 | J72: =IF(J$69>$E72,0,(I72-((2*$F$70)/$E72))) -> 0 | K72: =IF(K$69>$E72,0,(J72-((2*$F$70)/$E72))) -> 0 | L72: =IF(L$69>$E72,0,(K72-((2*$F$70)/$E72))) -> 0 | M72: =IF(M$69>$E72,0,(L72-((2*$F$70)/$E72))) -> 0 | N72: =IF(N$69>$E72,0,(M72-((2*$F$70)/$E72))) -> 0 | ... BN72: =IF(BN$69>$E72,0,(BM72-((2*$F$70)/$E72))) -> 0
E73: =E72+1 -> 4 | F73: =-$B$2 -> -2 | G73: =IF(G$69>$E73,0,(F73-((2*$F$70)/$E73))) -> -1 | H73: =IF(H$69>$E73,0,(G73-((2*$F$70)/$E73))) -> 0 | I73: =IF(I$69>$E73,0,(H73-((2*$F$70)/$E73))) -> 1 | J73: =IF(J$69>$E73,0,(I73-((2*$F$70)/$E73))) -> 2 | K73: =IF(K$69>$E73,0,(J73-((2*$F$70)/$E73))) -> 0 | L73: =IF(L$69>$E73,0,(K73-((2*$F$70)/$E73))) -> 0 | M73: =IF(M$69>$E73,0,(L73-((2*$F$70)/$E73))) -> 0 | N73: =IF(N$69>$E73,0,(M73-((2*$F$70)/$E73))) -> 0 | ... BN73: =IF(BN$69>$E73,0,(BM73-((2*$F$70)/$E73))) -> 0
E74: =E73+1 -> 5 | F74: =-$B$2 -> -2 | G74: =IF(G$69>$E74,0,(F74-((2*$F$70)/$E74))) -> -1.2 | H74: =IF(H$69>$E74,0,(G74-((2*$F$70)/$E74))) -> -0.4 | I74: =IF(I$69>$E74,0,(H74-((2*$F$70)/$E74))) -> 0.4 | J74: =IF(J$69>$E74,0,(I74-((2*$F$70)/$E74))) -> 1.2 | K74: =IF(K$69>$E74,0,(J74-((2*$F$70)/$E74))) -> 2 | L74: =IF(L$69>$E74,0,(K74-((2*$F$70)/$E74))) -> 0 | M74: =IF(M$69>$E74,0,(L74-((2*$F$70)/$E74))) -> 0 | N74: =IF(N$69>$E74,0,(M74-((2*$F$70)/$E74))) -> 0 | ... BN74: =IF(BN$69>$E74,0,(BM74-((2*$F$70)/$E74))) -> 0
E75: =E74+1 -> 6 | F75: =-$B$2 -> -2 | G75: =IF(G$69>$E75,0,(F75-((2*$F$70)/$E75))) -> -1.3333333 | H75: =IF(H$69>$E75,0,(G75-((2*$F$70)/$E75))) -> -0.66666667 | I75: =IF(I$69>$E75,0,(H75-((2*$F$70)/$E75))) -> -2.220446e-16 | J75: =IF(J$69>$E75,0,(I75-((2*$F$70)/$E75))) -> 0.66666667 | K75: =IF(K$69>$E75,0,(J75-((2*$F$70)/$E75))) -> 1.3333333 | L75: =IF(L$69>$E75,0,(K75-((2*$F$70)/$E75))) -> 2 | M75: =IF(M$69>$E75,0,(L75-((2*$F$70)/$E75))) -> 0 | N75: =IF(N$69>$E75,0,(M75-((2*$F$70)/$E75))) -> 0 | ... BN75: =IF(BN$69>$E75,0,(BM75-((2*$F$70)/$E75))) -> 0
E76: =E75+1 -> 7 | F76: =-$B$2 -> -2 | G76: =IF(G$69>$E76,0,(F76-((2*$F$70)/$E76))) -> -1.4285714 | H76: =IF(H$69>$E76,0,(G76-((2*$F$70)/$E76))) -> -0.85714286 | I76: =IF(I$69>$E76,0,(H76-((2*$F$70)/$E76))) -> -0.28571429 | J76: =IF(J$69>$E76,0,(I76-((2*$F$70)/$E76))) -> 0.28571429 | K76: =IF(K$69>$E76,0,(J76-((2*$F$70)/$E76))) -> 0.85714286 | L76: =IF(L$69>$E76,0,(K76-((2*$F$70)/$E76))) -> 1.4285714 | M76: =IF(M$69>$E76,0,(L76-((2*$F$70)/$E76))) -> 2 | N76: =IF(N$69>$E76,0,(M76-((2*$F$70)/$E76))) -> 0 | ... BN76: =IF(BN$69>$E76,0,(BM76-((2*$F$70)/$E76))) -> 0
E77: =E76+1 -> 8 | F77: =-$B$2 -> -2 | G77: =IF(G$69>$E77,0,(F77-((2*$F$70)/$E77))) -> -1.5 | H77: =IF(H$69>$E77,0,(G77-((2*$F$70)/$E77))) -> -1 | I77: =IF(I$69>$E77,0,(H77-((2*$F$70)/$E77))) -> -0.5 | J77: =IF(J$69>$E77,0,(I77-((2*$F$70)/$E77))) -> 0 | K77: =IF(K$69>$E77,0,(J77-((2*$F$70)/$E77))) -> 0.5 | L77: =IF(L$69>$E77,0,(K77-((2*$F$70)/$E77))) -> 1 | M77: =IF(M$69>$E77,0,(L77-((2*$F$70)/$E77))) -> 1.5 | N77: =IF(N$69>$E77,0,(M77-((2*$F$70)/$E77))) -> 2 | ... BN77: =IF(BN$69>$E77,0,(BM77-((2*$F$70)/$E77))) -> 0
E78: =E77+1 -> 9 | F78: =-$B$2 -> -2 | G78: =IF(G$69>$E78,0,(F78-((2*$F$70)/$E78))) -> -1.5555556 | H78: =IF(H$69>$E78,0,(G78-((2*$F$70)/$E78))) -> -1.1111111 | I78: =IF(I$69>$E78,0,(H78-((2*$F$70)/$E78))) -> -0.66666667 | J78: =IF(J$69>$E78,0,(I78-((2*$F$70)/$E78))) -> -0.22222222 | K78: =IF(K$69>$E78,0,(J78-((2*$F$70)/$E78))) -> 0.22222222 | L78: =IF(L$69>$E78,0,(K78-((2*$F$70)/$E78))) -> 0.66666667 | M78: =IF(M$69>$E78,0,(L78-((2*$F$70)/$E78))) -> 1.1111111 | N78: =IF(N$69>$E78,0,(M78-((2*$F$70)/$E78))) -> 1.5555556 | ... BN78: =IF(BN$69>$E78,0,(BM78-((2*$F$70)/$E78))) -> 0
E79: =E78+1 -> 10 | F79: =-$B$2 -> -2 | G79: =IF(G$69>$E79,0,(F79-((2*$F$70)/$E79))) -> -1.6 | H79: =IF(H$69>$E79,0,(G79-((2*$F$70)/$E79))) -> -1.2 | I79: =IF(I$69>$E79,0,(H79-((2*$F$70)/$E79))) -> -0.8 | J79: =IF(J$69>$E79,0,(I79-((2*$F$70)/$E79))) -> -0.4 | K79: =IF(K$69>$E79,0,(J79-((2*$F$70)/$E79))) -> -1.110223e-16 | L79: =IF(L$69>$E79,0,(K79-((2*$F$70)/$E79))) -> 0.4 | M79: =IF(M$69>$E79,0,(L79-((2*$F$70)/$E79))) -> 0.8 | N79: =IF(N$69>$E79,0,(M79-((2*$F$70)/$E79))) -> 1.2 | ... BN79: =IF(BN$69>$E79,0,(BM79-((2*$F$70)/$E79))) -> 0
E80: =E79+1 -> 11 | F80: =-$B$2 -> -2 | G80: =IF(G$69>$E80,0,(F80-((2*$F$70)/$E80))) -> -1.6363636 | H80: =IF(H$69>$E80,0,(G80-((2*$F$70)/$E80))) -> -1.2727273 | I80: =IF(I$69>$E80,0,(H80-((2*$F$70)/$E80))) -> -0.90909091 | J80: =IF(J$69>$E80,0,(I80-((2*$F$70)/$E80))) -> -0.54545455 | K80: =IF(K$69>$E80,0,(J80-((2*$F$70)/$E80))) -> -0.18181818 | L80: =IF(L$69>$E80,0,(K80-((2*$F$70)/$E80))) -> 0.18181818 | M80: =IF(M$69>$E80,0,(L80-((2*$F$70)/$E80))) -> 0.54545455 | N80: =IF(N$69>$E80,0,(M80-((2*$F$70)/$E80))) -> 0.90909091 | ... BN80: =IF(BN$69>$E80,0,(BM80-((2*$F$70)/$E80))) -> 0
E81: =E80+1 -> 12 | F81: =-$B$2 -> -2 | G81: =IF(G$69>$E81,0,(F81-((2*$F$70)/$E81))) -> -1.6666667 | H81: =IF(H$69>$E81,0,(G81-((2*$F$70)/$E81))) -> -1.3333333 | I81: =IF(I$69>$E81,0,(H81-((2*$F$70)/$E81))) -> -1 | J81: =IF(J$69>$E81,0,(I81-((2*$F$70)/$E81))) -> -0.66666667 | K81: =IF(K$69>$E81,0,(J81-((2*$F$70)/$E81))) -> -0.33333333 | L81: =IF(L$69>$E81,0,(K81-((2*$F$70)/$E81))) -> -3.3306691e-16 | M81: =IF(M$69>$E81,0,(L81-((2*$F$70)/$E81))) -> 0.33333333 | N81: =IF(N$69>$E81,0,(M81-((2*$F$70)/$E81))) -> 0.66666667 | ... BN81: =IF(BN$69>$E81,0,(BM81-((2*$F$70)/$E81))) -> 0
E82: =E81+1 -> 13 | F82: =-$B$2 -> -2 | G82: =IF(G$69>$E82,0,(F82-((2*$F$70)/$E82))) -> -1.6923077 | H82: =IF(H$69>$E82,0,(G82-((2*$F$70)/$E82))) -> -1.3846154 | I82: =IF(I$69>$E82,0,(H82-((2*$F$70)/$E82))) -> -1.0769231 | J82: =IF(J$69>$E82,0,(I82-((2*$F$70)/$E82))) -> -0.76923077 | K82: =IF(K$69>$E82,0,(J82-((2*$F$70)/$E82))) -> -0.46153846 | L82: =IF(L$69>$E82,0,(K82-((2*$F$70)/$E82))) -> -0.15384615 | M82: =IF(M$69>$E82,0,(L82-((2*$F$70)/$E82))) -> 0.15384615 | N82: =IF(N$69>$E82,0,(M82-((2*$F$70)/$E82))) -> 0.46153846 | ... BN82: =IF(BN$69>$E82,0,(BM82-((2*$F$70)/$E82))) -> 0
... E129: =E128+1 -> 60 | F129: =-$B$2 -> -2 | G129: =IF(G$69>$E129,0,(F129-((2*$F$70)/$E129))) -> -1.9333333 | H129: =IF(H$69>$E129,0,(G129-((2*$F$70)/$E129))) -> -1.8666667 | I129: =IF(I$69>$E129,0,(H129-((2*$F$70)/$E129))) -> -1.8 | J129: =IF(J$69>$E129,0,(I129-((2*$F$70)/$E129))) -> -1.7333333 | K129: =IF(K$69>$E129,0,(J129-((2*$F$70)/$E129))) -> -1.6666667 | L129: =IF(L$69>$E129,0,(K129-((2*$F$70)/$E129))) -> -1.6 | M129: =IF(M$69>$E129,0,(L129-((2*$F$70)/$E129))) -> -1.5333333 | N129: =IF(N$69>$E129,0,(M129-((2*$F$70)/$E129))) -> -1.4666667 | ... BN129: =IF(BN$69>$E129,0,(BM129-((2*$F$70)/$E129))) -> 2
