Workbook
Name ________EXP1: #REF!
Name ________EXP1: #REF!
Name ________LTL1: #REF!
Name ________LTL2: #REF!
Name ________LTL3: #REF!
Name ________LTL4: #REF!
Name ________LTL5: #REF!
Name ________LTL6: #REF!
Name _______EXP1: #REF!
Name _______EXP1: #REF!
Name _______LTL1: #REF!
Name _______LTL2: #REF!
Name _______LTL3: #REF!
Name _______LTL4: #REF!
Name _______LTL5: #REF!
Name _______LTL6: #REF!
Name ______EXP1: #REF!
Name ______EXP1: #REF!
Name ____GPR1: #REF!
Name ____GPR2: #REF!
Name ____GPR3: #REF!
Name ____GPR4: #REF!
Name ____GPR5: #REF!
Name ____GPR6: #REF!
Name ____LA1: #REF!
Name ____REF1: #N/A
Name ____REF2: #N/A
Name ___ASS1: #N/A
Name ___ASS2: #N/A
Name ___ass3: #N/A
Name ___AVI1: #N/A
Name ___CAM96: #REF!
Name ___CAM96: #REF!
Name ___CAM97: #REF!
Name ___CAM9710: #REF!
Name ___CAM9710: #REF!
Name ___GPR1: #REF!
Name ___GPR2: #REF!
Name ___GPR3: #REF!
Name ___GPR4: #REF!
Name ___GPR5: #REF!
Name ___GPR6: #REF!
Name ___GSF2: #N/A
Name ___INF1: #N/A
Name ___INF2: #N/A
Name ___INS97: #REF!
Name ___LA1: #REF!
Name ___LC1: #N/A
Name ___LC2: #N/A
Name ___LC3: #N/A
Name ___LTL1: #REF!
Name ___LTL2: #REF!
Name ___LTL3: #REF!
Name ___LTL4: #REF!
Name ___LTL5: #REF!
Name ___LTL6: #REF!
Name ___MGT2: #N/A
Name ___MGT3: #N/A
Name ___PER1: #REF!
Name ___PER1: #REF!

Sheet Disclaimer
B3: =+Assumptions!B2 -> Westview Austin
B4: =TODAY() -> 46199
B6: DISCLAIMER
B7: This confidential summary contains forward-looking statements that are not historical facts. These forward-looking statements include statements, express or implied, regarding the current expectations, estimates, projections, opinions and beliefs of the Arc Capital Partners LLC ("Company"), as well as certain assumptions on which those statements are based. Such forward-looking statements are subject to risks, uncertainties and other factors that may cause actual events to differ materially from any anticipated development and no assurance can be given that the Company, or any investment vehicle that may be formed or managed by the Company in the future, will achieve the projected returns. The pro forma information set forth in this confidential summary is shown for illustration purposes only and should not be relied upon. No representation or assurance is made that any potential investor will or is likely to achieve results comparable to those shown or will make any profit or will be able to avoid incurring substantial losses. The information contained herein is confidential and intended solely for use by the Company and persons to whom the Company has delivered this document. This confidential summary is not to be reproduced or distributed to any third party. The recipient, by accepting this document, agrees to this restriction and to return the document to the Company upon request. The pro forma information reflects the Company’s judgment, based on current circumstances, of the most likely set of conditions and its most likely course of action. The assumptions disclosed herein are those that the Company believes are significant to the pro forma information or are key factors upon which the financial results of the Company and any potential real estate investment opportunity depend. Some assumptions inevitably will not materialize and unanticipated events and circumstances may occur subsequent to the date of this information. Therefore, the actual results achieved during the forecast period will vary from the forecast, and the variations may be material. None of the Company, its managers, officers, directors, employees or affiliates assume any responsibility to notify recipients of any updates to this pro forma information if there are changes to the assumptions or results. Recipients are encouraged to consult with their own professional advisors concerning this pro forma information, including the assumptions used. The Company will make available additional information upon request concerning the pro forma information to the extent it is readily available to the Company at no additional cost and the Company is not otherwise restricted from providing such information.

Sheet Lease Audit Report
A1: Lease Audit Report
A2: Ten-O-Five St. Elmo - Arc Model 9.28.2021 (Amounts in USD, Measures in SF)
A3: Oct, 2021 through Sep, 2032
A4: 10/2/2021 2:33:18 PM
D5: 1 | E5: 1 | F5: 1 | G5: 1 | H5: 1 | I5: 1 | J5: 1 | K5: 1 | L5: 1 | M5: 1 | N5: 1 | O5: 1 | P5: =D5+1 -> 2 | Q5: =E5+1 -> 2 | R5: =F5+1 -> 2 | S5: =G5+1 -> 2 | T5: =H5+1 -> 2 | U5: =I5+1 -> 2 | V5: =J5+1 -> 2 | W5: =K5+1 -> 2 | ... ED5: =DR5+1 -> 11
C6: Month 1 | D6: Month 2 | E6: Month 3 | F6: Month 4 | G6: Month 5 | H6: Month 6 | I6: Month 7 | J6: Month 8 | K6: Month 9 | L6: Month 10 | M6: Month 11 | N6: Month 12 | O6: Month 13 | P6: Month 14 | Q6: Month 15 | R6: Month 16 | S6: Month 17 | T6: Month 18 | U6: Month 19 | V6: Month 20 | W6: Month 21 | X6: Month 22 | Y6: Month 23 | Z6: Month 24 | AA6: Month 25 | AB6: Month 26 | AC6: Month 27 | AD6: Month 28 | AE6: Month 29 | AF6: Month 30 | AG6: Month 31 | AH6: Month 32 | AI6: Month 33 | AJ6: Month 34 | AK6: Month 35 | AL6: Month 36 | AM6: Month 37 | AN6: Month 38 | AO6: Month 39 | AP6: Month 40 | AQ6: Month 41 | AR6: Month 42 | AS6: Month 43 | AT6: Month 44 | AU6: Month 45 | AV6: Month 46 | AW6: Month 47 | AX6: Month 48 | AY6: Month 49 | AZ6: Month 50 | BA6: Month 51 | BB6: Month 52 | BC6: Month 53 | BD6: Month 54 | BE6: Month 55 | BF6: Month 56 | BG6: Month 57 | BH6: Month 58 | BI6: Month 59 | BJ6: Month 60 | BK6: Month 61 | BL6: Month 62 | BM6: Month 63 | BN6: Month 64 | BO6: Month 65 | BP6: Month 66 | BQ6: Month 67 | BR6: Month 68 | BS6: Month 69 | BT6: Month 70 | BU6: Month 71 | BV6: Month 72 | BW6: Month 73 | BX6: Month 74 | BY6: Month 75 | BZ6: Month 76 | CA6: Month 77 | CB6: Month 78 | CC6: Month 79 | CD6: Month 80 | CE6: Month 81 | CF6: Month 82 | CG6: Month 83 | CH6: Month 84 | CI6: Month 85 | CJ6: Month 86 | CK6: Month 87 | CL6: Month 88 | CM6: Month 89 | CN6: Month 90 | CO6: Month 91 | CP6: Month 92 | CQ6: Month 93 | CR6: Month 94 | CS6: Month 95 | CT6: Month 96 | CU6: Month 97 | CV6: Month 98 | CW6: Month 99 | CX6: Month 100 | CY6: Month 101 | CZ6: Month 102 | DA6: Month 103 | DB6: Month 104 | DC6: Month 105 | DD6: Month 106 | DE6: Month 107 | DF6: Month 108 | DG6: Month 109 | DH6: Month 110 | DI6: Month 111 | DJ6: Month 112 | DK6: Month 113 | DL6: Month 114 | DM6: Month 115 | DN6: Month 116 | DO6: Month 117 | DP6: Month 118 | DQ6: Month 119 | DR6: Month 120 | DS6: Month 121 | DT6: Month 122 | DU6: Month 123 | DV6: Month 124 | DW6: Month 125 | DX6: Month 126 | DY6: Month 127 | DZ6: Month 128 | EA6: Month 129 | EB6: Month 130 | EC6: Month 131 | ED6: Month 132
A7: For the Months | B7: Suite | C7: Oct-2021 | D7: Nov-2021 | E7: Dec-2021 | F7: Jan-2022 | G7: Feb-2022 | H7: Mar-2022 | I7: Apr-2022 | J7: May-2022 | K7: Jun-2022 | L7: Jul-2022 | M7: Aug-2022 | N7: Sep-2022 | O7: Oct-2022 | P7: Nov-2022 | Q7: Dec-2022 | R7: Jan-2023 | S7: Feb-2023 | T7: Mar-2023 | U7: Apr-2023 | V7: May-2023 | W7: Jun-2023 | X7: Jul-2023 | Y7: Aug-2023 | Z7: Sep-2023 | AA7: Oct-2023 | AB7: Nov-2023 | AC7: Dec-2023 | AD7: Jan-2024 | AE7: Feb-2024 | AF7: Mar-2024 | AG7: Apr-2024 | AH7: May-2024 | AI7: Jun-2024 | AJ7: Jul-2024 | AK7: Aug-2024 | AL7: Sep-2024 | AM7: Oct-2024 | AN7: Nov-2024 | AO7: Dec-2024 | AP7: Jan-2025 | AQ7: Feb-2025 | AR7: Mar-2025 | AS7: Apr-2025 | AT7: May-2025 | AU7: Jun-2025 | AV7: Jul-2025 | AW7: Aug-2025 | AX7: Sep-2025 | AY7: Oct-2025 | AZ7: Nov-2025 | BA7: Dec-2025 | BB7: Jan-2026 | BC7: Feb-2026 | BD7: Mar-2026 | BE7: Apr-2026 | BF7: May-2026 | BG7: Jun-2026 | BH7: Jul-2026 | BI7: Aug-2026 | BJ7: Sep-2026 | BK7: Oct-2026 | BL7: Nov-2026 | BM7: Dec-2026 | BN7: Jan-2027 | BO7: Feb-2027 | BP7: Mar-2027 | BQ7: Apr-2027 | BR7: May-2027 | BS7: Jun-2027 | BT7: Jul-2027 | BU7: Aug-2027 | BV7: Sep-2027 | BW7: Oct-2027 | BX7: Nov-2027 | BY7: Dec-2027 | BZ7: Jan-2028 | CA7: Feb-2028 | CB7: Mar-2028 | CC7: Apr-2028 | CD7: May-2028 | CE7: Jun-2028 | CF7: Jul-2028 | CG7: Aug-2028 | CH7: Sep-2028 | CI7: Oct-2028 | CJ7: Nov-2028 | CK7: Dec-2028 | CL7: Jan-2029 | CM7: Feb-2029 | CN7: Mar-2029 | CO7: Apr-2029 | CP7: May-2029 | CQ7: Jun-2029 | CR7: Jul-2029 | CS7: Aug-2029 | CT7: Sep-2029 | CU7: Oct-2029 | CV7: Nov-2029 | CW7: Dec-2029 | CX7: Jan-2030 | CY7: Feb-2030 | CZ7: Mar-2030 | DA7: Apr-2030 | DB7: May-2030 | DC7: Jun-2030 | DD7: Jul-2030 | DE7: Aug-2030 | DF7: Sep-2030 | DG7: Oct-2030 | DH7: Nov-2030 | DI7: Dec-2030 | DJ7: Jan-2031 | DK7: Feb-2031 | DL7: Mar-2031 | DM7: Apr-2031 | DN7: May-2031 | DO7: Jun-2031 | DP7: Jul-2031 | DQ7: Aug-2031 | DR7: Sep-2031 | DS7: Oct-2031 | DT7: Nov-2031 | DU7: Dec-2031 | DV7: Jan-2032 | DW7: Feb-2032 | DX7: Mar-2032 | DY7: Apr-2032 | DZ7: May-2032 | EA7: Jun-2032 | EB7: Jul-2032 | EC7: Aug-2032 | ED7: Sep-2032 | EE7: Total
A8: Area
A9: 1. Kitu Life, Inc. | B9: 1 | C9: 8085 | D9: 8085 | E9: 8085 | F9: 8085 | G9: 8085 | H9: 8085 | I9: 8085 | J9: 8085 | K9: 8085 | L9: 8085 | M9: 8085 | N9: 8085 | O9: 8085 | P9: 8085 | Q9: 8085 | R9: 8085 | S9: 8085 | T9: 8085 | U9: 8085 | V9: 8085 | W9: 8085 | X9: 8085 | Y9: 8085 | Z9: 8085 | AA9: 8085 | AB9: 8085 | AC9: 8085 | AD9: 8085 | AE9: 8085 | AF9: 8085 | AG9: 8085 | AH9: 8085 | AI9: 8085 | AJ9: 8085 | AK9: 8085 | AL9: 8085 | AM9: 8085 | AN9: 8085 | AO9: 8085 | AP9: 8085 | AQ9: 8085 | AR9: 8085 | AS9: 8085 | AT9: 8085 | AU9: 8085 | AV9: 8085 | AW9: 8085 | AX9: 8085 | AY9: 8085 | AZ9: 8085 | BA9: 8085 | BB9: 8085 | BC9: 8085 | BD9: 8085 | BE9: 8085 | BF9: 8085 | BG9: 8085 | BH9: 8085 | BI9: 8085 | BJ9: 8085 | BK9: 0 | BL9: 0 | BM9: 8085 | BN9: 8085 | BO9: 8085 | BP9: 8085 | BQ9: 8085 | BR9: 8085 | BS9: 8085 | BT9: 8085 | BU9: 8085 | BV9: 8085 | BW9: 8085 | BX9: 8085 | BY9: 8085 | BZ9: 8085 | CA9: 8085 | CB9: 8085 | CC9: 8085 | CD9: 8085 | CE9: 8085 | CF9: 8085 | CG9: 8085 | CH9: 8085 | CI9: 8085 | CJ9: 8085 | CK9: 8085 | CL9: 8085 | CM9: 8085 | CN9: 8085 | CO9: 8085 | CP9: 8085 | CQ9: 8085 | CR9: 8085 | CS9: 8085 | CT9: 8085 | CU9: 8085 | CV9: 8085 | CW9: 8085 | CX9: 8085 | CY9: 8085 | CZ9: 8085 | DA9: 8085 | DB9: 8085 | DC9: 8085 | DD9: 8085 | DE9: 8085 | DF9: 8085 | DG9: 8085 | DH9: 8085 | DI9: 8085 | DJ9: 8085 | DK9: 8085 | DL9: 8085 | DM9: 8085 | DN9: 8085 | DO9: 8085 | DP9: 8085 | DQ9: 8085 | DR9: 8085 | DS9: 8085 | DT9: 8085 | DU9: 8085 | DV9: 8085 | DW9: 8085 | DX9: 0 | DY9: 0 | DZ9: 8085 | EA9: 8085 | EB9: 8085 | EC9: 8085 | ED9: 8085
A10: 2. VACANT | B10: 2 | C10: 0 | D10: 0 | E10: 0 | F10: 0 | G10: 0 | H10: 0 | I10: 0 | J10: 8956 | K10: 8956 | L10: 8956 | M10: 8956 | N10: 8956 | O10: 8956 | P10: 8956 | Q10: 8956 | R10: 8956 | S10: 8956 | T10: 8956 | U10: 8956 | V10: 8956 | W10: 8956 | X10: 8956 | Y10: 8956 | Z10: 8956 | AA10: 8956 | AB10: 8956 | AC10: 8956 | AD10: 8956 | AE10: 8956 | AF10: 8956 | AG10: 8956 | AH10: 8956 | AI10: 8956 | AJ10: 8956 | AK10: 8956 | AL10: 8956 | AM10: 8956 | AN10: 8956 | AO10: 8956 | AP10: 8956 | AQ10: 8956 | AR10: 8956 | AS10: 8956 | AT10: 8956 | AU10: 8956 | AV10: 8956 | AW10: 8956 | AX10: 8956 | AY10: 8956 | AZ10: 8956 | BA10: 8956 | BB10: 8956 | BC10: 8956 | BD10: 8956 | BE10: 8956 | BF10: 8956 | BG10: 8956 | BH10: 8956 | BI10: 8956 | BJ10: 8956 | BK10: 8956 | BL10: 8956 | BM10: 8956 | BN10: 8956 | BO10: 8956 | BP10: 8956 | BQ10: 8956 | BR10: 8956 | BS10: 8956 | BT10: 8956 | BU10: 0 | BV10: 0 | BW10: 8956 | BX10: 8956 | BY10: 8956 | BZ10: 8956 | CA10: 8956 | CB10: 8956 | CC10: 8956 | CD10: 8956 | CE10: 8956 | CF10: 8956 | CG10: 8956 | CH10: 8956 | CI10: 8956 | CJ10: 8956 | CK10: 8956 | CL10: 8956 | CM10: 8956 | CN10: 8956 | CO10: 8956 | CP10: 8956 | CQ10: 8956 | CR10: 8956 | CS10: 8956 | CT10: 8956 | CU10: 8956 | CV10: 8956 | CW10: 8956 | CX10: 8956 | CY10: 8956 | CZ10: 8956 | DA10: 8956 | DB10: 8956 | DC10: 8956 | DD10: 8956 | DE10: 8956 | DF10: 8956 | DG10: 8956 | DH10: 8956 | DI10: 8956 | DJ10: 8956 | DK10: 8956 | DL10: 8956 | DM10: 8956 | DN10: 8956 | DO10: 8956 | DP10: 8956 | DQ10: 8956 | DR10: 8956 | DS10: 8956 | DT10: 8956 | DU10: 8956 | DV10: 8956 | DW10: 8956 | DX10: 8956 | DY10: 8956 | DZ10: 8956 | EA10: 8956 | EB10: 8956 | EC10: 8956 | ED10: 8956
A11: 3. Saatva | B11: 3 | C11: 6000 | D11: 6000 | E11: 6000 | F11: 6000 | G11: 6000 | H11: 6000 | I11: 6000 | J11: 6000 | K11: 6000 | L11: 6000 | M11: 6000 | N11: 6000 | O11: 6000 | P11: 6000 | Q11: 6000 | R11: 6000 | S11: 6000 | T11: 6000 | U11: 6000 | V11: 6000 | W11: 6000 | X11: 6000 | Y11: 6000 | Z11: 6000 | AA11: 6000 | AB11: 6000 | AC11: 6000 | AD11: 0 | AE11: 0 | AF11: 6009 | AG11: 6009 | AH11: 6009 | AI11: 6009 | AJ11: 6009 | AK11: 6009 | AL11: 6009 | AM11: 6009 | AN11: 6009 | AO11: 6009 | AP11: 6009 | AQ11: 6009 | AR11: 6009 | AS11: 6009 | AT11: 6009 | AU11: 6009 | AV11: 6009 | AW11: 6009 | AX11: 6009 | AY11: 6009 | AZ11: 6009 | BA11: 6009 | BB11: 6009 | BC11: 6009 | BD11: 6009 | BE11: 6009 | BF11: 6009 | BG11: 6009 | BH11: 6009 | BI11: 6009 | BJ11: 6009 | BK11: 6009 | BL11: 6009 | BM11: 6009 | BN11: 6009 | BO11: 6009 | BP11: 6009 | BQ11: 6009 | BR11: 6009 | BS11: 6009 | BT11: 6009 | BU11: 6009 | BV11: 6009 | BW11: 6009 | BX11: 6009 | BY11: 6009 | BZ11: 6009 | CA11: 6009 | CB11: 6009 | CC11: 6009 | CD11: 6009 | CE11: 6009 | CF11: 6009 | CG11: 6009 | CH11: 6009 | CI11: 6009 | CJ11: 6009 | CK11: 6009 | CL11: 6009 | CM11: 6009 | CN11: 6009 | CO11: 6009 | CP11: 6009 | CQ11: 0 | CR11: 0 | CS11: 6009 | CT11: 6009 | CU11: 6009 | CV11: 6009 | CW11: 6009 | CX11: 6009 | CY11: 6009 | CZ11: 6009 | DA11: 6009 | DB11: 6009 | DC11: 6009 | DD11: 6009 | DE11: 6009 | DF11: 6009 | DG11: 6009 | DH11: 6009 | DI11: 6009 | DJ11: 6009 | DK11: 6009 | DL11: 6009 | DM11: 6009 | DN11: 6009 | DO11: 6009 | DP11: 6009 | DQ11: 6009 | DR11: 6009 | DS11: 6009 | DT11: 6009 | DU11: 6009 | DV11: 6009 | DW11: 6009 | DX11: 6009 | DY11: 6009 | DZ11: 6009 | EA11: 6009 | EB11: 6009 | EC11: 6009 | ED11: 6009
A12: 4. Fuse Architecture Studio | B12: 4 | C12: 3000 | D12: 3000 | E12: 3000 | F12: 3000 | G12: 3000 | H12: 3000 | I12: 3000 | J12: 3000 | K12: 3000 | L12: 3000 | M12: 3000 | N12: 3000 | O12: 3000 | P12: 3000 | Q12: 3000 | R12: 3000 | S12: 3000 | T12: 3000 | U12: 3000 | V12: 0 | W12: 0 | X12: 3143 | Y12: 3143 | Z12: 3143 | AA12: 3143 | AB12: 3143 | AC12: 3143 | AD12: 3143 | AE12: 3143 | AF12: 3143 | AG12: 3143 | AH12: 3143 | AI12: 3143 | AJ12: 3143 | AK12: 3143 | AL12: 3143 | AM12: 3143 | AN12: 3143 | AO12: 3143 | AP12: 3143 | AQ12: 3143 | AR12: 3143 | AS12: 3143 | AT12: 3143 | AU12: 3143 | AV12: 3143 | AW12: 3143 | AX12: 3143 | AY12: 3143 | AZ12: 3143 | BA12: 3143 | BB12: 3143 | BC12: 3143 | BD12: 3143 | BE12: 3143 | BF12: 3143 | BG12: 3143 | BH12: 3143 | BI12: 3143 | BJ12: 3143 | BK12: 3143 | BL12: 3143 | BM12: 3143 | BN12: 3143 | BO12: 3143 | BP12: 3143 | BQ12: 3143 | BR12: 3143 | BS12: 3143 | BT12: 3143 | BU12: 3143 | BV12: 3143 | BW12: 3143 | BX12: 3143 | BY12: 3143 | BZ12: 3143 | CA12: 3143 | CB12: 3143 | CC12: 3143 | CD12: 3143 | CE12: 3143 | CF12: 3143 | CG12: 3143 | CH12: 3143 | CI12: 0 | CJ12: 0 | CK12: 3143 | CL12: 3143 | CM12: 3143 | CN12: 3143 | CO12: 3143 | CP12: 3143 | CQ12: 3143 | CR12: 3143 | CS12: 3143 | CT12: 3143 | CU12: 3143 | CV12: 3143 | CW12: 3143 | CX12: 3143 | CY12: 3143 | CZ12: 3143 | DA12: 3143 | DB12: 3143 | DC12: 3143 | DD12: 3143 | DE12: 3143 | DF12: 3143 | DG12: 3143 | DH12: 3143 | DI12: 3143 | DJ12: 3143 | DK12: 3143 | DL12: 3143 | DM12: 3143 | DN12: 3143 | DO12: 3143 | DP12: 3143 | DQ12: 3143 | DR12: 3143 | DS12: 3143 | DT12: 3143 | DU12: 3143 | DV12: 3143 | DW12: 3143 | DX12: 3143 | DY12: 3143 | DZ12: 3143 | EA12: 3143 | EB12: 3143 | EC12: 3143 | ED12: 3143
A13: 5. Made In (sublessee to Geek Powered Studios) | B13: 5 | C13: 6000 | D13: 6000 | E13: 6000 | F13: 6000 | G13: 6000 | H13: 6000 | I13: 6000 | J13: 0 | K13: 0 | L13: 0 | M13: 0 | N13: 0 | O13: 0 | P13: 6057 | Q13: 6057 | R13: 6057 | S13: 6057 | T13: 6057 | U13: 6057 | V13: 6057 | W13: 6057 | X13: 6057 | Y13: 6057 | Z13: 6057 | AA13: 6057 | AB13: 6057 | AC13: 6057 | AD13: 6057 | AE13: 6057 | AF13: 6057 | AG13: 6057 | AH13: 6057 | AI13: 6057 | AJ13: 6057 | AK13: 6057 | AL13: 6057 | AM13: 6057 | AN13: 6057 | AO13: 6057 | AP13: 6057 | AQ13: 6057 | AR13: 6057 | AS13: 6057 | AT13: 6057 | AU13: 6057 | AV13: 6057 | AW13: 6057 | AX13: 6057 | AY13: 6057 | AZ13: 6057 | BA13: 6057 | BB13: 6057 | BC13: 6057 | BD13: 6057 | BE13: 6057 | BF13: 6057 | BG13: 6057 | BH13: 6057 | BI13: 6057 | BJ13: 6057 | BK13: 6057 | BL13: 6057 | BM13: 6057 | BN13: 6057 | BO13: 6057 | BP13: 6057 | BQ13: 6057 | BR13: 6057 | BS13: 6057 | BT13: 6057 | BU13: 6057 | BV13: 6057 | BW13: 6057 | BX13: 6057 | BY13: 6057 | BZ13: 6057 | CA13: 0 | CB13: 0 | CC13: 6057 | CD13: 6057 | CE13: 6057 | CF13: 6057 | CG13: 6057 | CH13: 6057 | CI13: 6057 | CJ13: 6057 | CK13: 6057 | CL13: 6057 | CM13: 6057 | CN13: 6057 | CO13: 6057 | CP13: 6057 | CQ13: 6057 | CR13: 6057 | CS13: 6057 | CT13: 6057 | CU13: 6057 | CV13: 6057 | CW13: 6057 | CX13: 6057 | CY13: 6057 | CZ13: 6057 | DA13: 6057 | DB13: 6057 | DC13: 6057 | DD13: 6057 | DE13: 6057 | DF13: 6057 | DG13: 6057 | DH13: 6057 | DI13: 6057 | DJ13: 6057 | DK13: 6057 | DL13: 6057 | DM13: 6057 | DN13: 6057 | DO13: 6057 | DP13: 6057 | DQ13: 6057 | DR13: 6057 | DS13: 6057 | DT13: 6057 | DU13: 6057 | DV13: 6057 | DW13: 6057 | DX13: 6057 | DY13: 6057 | DZ13: 6057 | EA13: 6057 | EB13: 6057 | EC13: 6057 | ED13: 6057
A14: 6. Elmo 35, LLC | B14: 6 | C14: 6569 | D14: 6569 | E14: 6569 | F14: 6569 | G14: 6569 | H14: 6569 | I14: 6569 | J14: 6569 | K14: 6569 | L14: 6569 | M14: 6569 | N14: 6569 | O14: 6569 | P14: 6569 | Q14: 6569 | R14: 6569 | S14: 6569 | T14: 6569 | U14: 6569 | V14: 6569 | W14: 6569 | X14: 6569 | Y14: 6569 | Z14: 6569 | AA14: 6569 | AB14: 6569 | AC14: 6569 | AD14: 6569 | AE14: 6569 | AF14: 6569 | AG14: 6569 | AH14: 6569 | AI14: 6569 | AJ14: 6569 | AK14: 6569 | AL14: 6569 | AM14: 6569 | AN14: 6569 | AO14: 6569 | AP14: 6569 | AQ14: 6569 | AR14: 6569 | AS14: 6569 | AT14: 6569 | AU14: 6569 | AV14: 6569 | AW14: 6569 | AX14: 6569 | AY14: 6569 | AZ14: 6569 | BA14: 6569 | BB14: 6569 | BC14: 6569 | BD14: 6569 | BE14: 6569 | BF14: 6569 | BG14: 6569 | BH14: 6569 | BI14: 6569 | BJ14: 6569 | BK14: 6569 | BL14: 6569 | BM14: 6569 | BN14: 6569 | BO14: 6569 | BP14: 6569 | BQ14: 6569 | BR14: 6569 | BS14: 6569 | BT14: 6569 | BU14: 6569 | BV14: 6569 | BW14: 6569 | BX14: 6569 | BY14: 6569 | BZ14: 6569 | CA14: 6569 | CB14: 6569 | CC14: 6569 | CD14: 6569 | CE14: 6569 | CF14: 6569 | CG14: 6569 | CH14: 6569 | CI14: 0 | CJ14: 0 | CK14: 6569 | CL14: 6569 | CM14: 6569 | CN14: 6569 | CO14: 6569 | CP14: 6569 | CQ14: 6569 | CR14: 6569 | CS14: 6569 | CT14: 6569 | CU14: 6569 | CV14: 6569 | CW14: 6569 | CX14: 6569 | CY14: 6569 | CZ14: 6569 | DA14: 6569 | DB14: 6569 | DC14: 6569 | DD14: 6569 | DE14: 6569 | DF14: 6569 | DG14: 6569 | DH14: 6569 | DI14: 6569 | DJ14: 6569 | DK14: 6569 | DL14: 6569 | DM14: 6569 | DN14: 6569 | DO14: 6569 | DP14: 6569 | DQ14: 6569 | DR14: 6569 | DS14: 6569 | DT14: 6569 | DU14: 6569 | DV14: 6569 | DW14: 6569 | DX14: 6569 | DY14: 6569 | DZ14: 6569 | EA14: 6569 | EB14: 6569 | EC14: 6569 | ED14: 6569
A15: 7. Trihydro Corporation | B15: 7 | C15: 3000 | D15: 3000 | E15: 3000 | F15: 3000 | G15: 3000 | H15: 3000 | I15: 3000 | J15: 3000 | K15: 3000 | L15: 3000 | M15: 3000 | N15: 3000 | O15: 3000 | P15: 3000 | Q15: 3000 | R15: 3000 | S15: 3000 | T15: 3000 | U15: 0 | V15: 0 | W15: 0 | X15: 0 | Y15: 0 | Z15: 0 | AA15: 3019 | AB15: 3019 | AC15: 3019 | AD15: 3019 | AE15: 3019 | AF15: 3019 | AG15: 3019 | AH15: 3019 | AI15: 3019 | AJ15: 3019 | AK15: 3019 | AL15: 3019 | AM15: 3019 | AN15: 3019 | AO15: 3019 | AP15: 3019 | AQ15: 3019 | AR15: 3019 | AS15: 3019 | AT15: 3019 | AU15: 3019 | AV15: 3019 | AW15: 3019 | AX15: 3019 | AY15: 3019 | AZ15: 3019 | BA15: 3019 | BB15: 3019 | BC15: 3019 | BD15: 3019 | BE15: 3019 | BF15: 3019 | BG15: 3019 | BH15: 3019 | BI15: 3019 | BJ15: 3019 | BK15: 3019 | BL15: 3019 | BM15: 3019 | BN15: 3019 | BO15: 3019 | BP15: 3019 | BQ15: 3019 | BR15: 3019 | BS15: 3019 | BT15: 3019 | BU15: 3019 | BV15: 3019 | BW15: 3019 | BX15: 3019 | BY15: 3019 | BZ15: 3019 | CA15: 3019 | CB15: 3019 | CC15: 3019 | CD15: 3019 | CE15: 3019 | CF15: 3019 | CG15: 3019 | CH15: 3019 | CI15: 3019 | CJ15: 3019 | CK15: 3019 | CL15: 0 | CM15: 0 | CN15: 3019 | CO15: 3019 | CP15: 3019 | CQ15: 3019 | CR15: 3019 | CS15: 3019 | CT15: 3019 | CU15: 3019 | CV15: 3019 | CW15: 3019 | CX15: 3019 | CY15: 3019 | CZ15: 3019 | DA15: 3019 | DB15: 3019 | DC15: 3019 | DD15: 3019 | DE15: 3019 | DF15: 3019 | DG15: 3019 | DH15: 3019 | DI15: 3019 | DJ15: 3019 | DK15: 3019 | DL15: 3019 | DM15: 3019 | DN15: 3019 | DO15: 3019 | DP15: 3019 | DQ15: 3019 | DR15: 3019 | DS15: 3019 | DT15: 3019 | DU15: 3019 | DV15: 3019 | DW15: 3019 | DX15: 3019 | DY15: 3019 | DZ15: 3019 | EA15: 3019 | EB15: 3019 | EC15: 3019 | ED15: 3019
A16: 8. Urban ATX | B16: 07A | C16: 1500 | D16: 1500 | E16: 1500 | F16: 1500 | G16: 1500 | H16: 1500 | I16: 1500 | J16: 1500 | K16: 1500 | L16: 1500 | M16: 1500 | N16: 1500 | O16: 1500 | P16: 1500 | Q16: 1500 | R16: 1500 | S16: 1500 | T16: 1500 | U16: 1500 | V16: 1500 | W16: 1500 | X16: 1500 | Y16: 1500 | Z16: 1500 | AA16: 1500 | AB16: 1500 | AC16: 1500 | AD16: 1500 | AE16: 1500 | AF16: 1500 | AG16: 1500 | AH16: 1500 | AI16: 1500 | AJ16: 1500 | AK16: 1500 | AL16: 1500 | AM16: 1500 | AN16: 1500 | AO16: 1500 | AP16: 1500 | AQ16: 1500 | AR16: 1500 | AS16: 1500 | AT16: 1500 | AU16: 1500 | AV16: 1500 | AW16: 1500 | AX16: 1500 | AY16: 1500 | AZ16: 1500 | BA16: 1500 | BB16: 1500 | BC16: 1500 | BD16: 1500 | BE16: 1500 | BF16: 1500 | BG16: 1500 | BH16: 0 | BI16: 0 | BJ16: 1514 | BK16: 1514 | BL16: 1514 | BM16: 1514 | BN16: 1514 | BO16: 1514 | BP16: 1514 | BQ16: 1514 | BR16: 1514 | BS16: 1514 | BT16: 1514 | BU16: 1514 | BV16: 1514 | BW16: 1514 | BX16: 1514 | BY16: 1514 | BZ16: 1514 | CA16: 1514 | CB16: 1514 | CC16: 1514 | CD16: 1514 | CE16: 1514 | CF16: 1514 | CG16: 1514 | CH16: 1514 | CI16: 1514 | CJ16: 1514 | CK16: 1514 | CL16: 1514 | CM16: 1514 | CN16: 1514 | CO16: 1514 | CP16: 1514 | CQ16: 1514 | CR16: 1514 | CS16: 1514 | CT16: 1514 | CU16: 1514 | CV16: 1514 | CW16: 1514 | CX16: 1514 | CY16: 1514 | CZ16: 1514 | DA16: 1514 | DB16: 1514 | DC16: 1514 | DD16: 1514 | DE16: 1514 | DF16: 1514 | DG16: 1514 | DH16: 1514 | DI16: 1514 | DJ16: 1514 | DK16: 1514 | DL16: 1514 | DM16: 1514 | DN16: 1514 | DO16: 1514 | DP16: 1514 | DQ16: 1514 | DR16: 1514 | DS16: 1514 | DT16: 1514 | DU16: 0 | DV16: 0 | DW16: 1514 | DX16: 1514 | DY16: 1514 | DZ16: 1514 | EA16: 1514 | EB16: 1514 | EC16: 1514 | ED16: 1514
A17: 9. Brinkley Sargent Winginton Architects | B17: 8 | C17: 3000 | D17: 3000 | E17: 3000 | F17: 3000 | G17: 3000 | H17: 3000 | I17: 3000 | J17: 3000 | K17: 3000 | L17: 3000 | M17: 3000 | N17: 3000 | O17: 3000 | P17: 3029 | Q17: 3029 | R17: 3029 | S17: 3029 | T17: 3029 | U17: 3029 | V17: 3029 | W17: 3029 | X17: 3029 | Y17: 3029 | Z17: 3029 | AA17: 3029 | AB17: 3029 | AC17: 3029 | AD17: 3029 | AE17: 3029 | AF17: 3029 | AG17: 3029 | AH17: 3029 | AI17: 3029 | AJ17: 3029 | AK17: 3029 | AL17: 3029 | AM17: 3029 | AN17: 3029 | AO17: 3029 | AP17: 3029 | AQ17: 3029 | AR17: 3029 | AS17: 3029 | AT17: 3029 | AU17: 3029 | AV17: 3029 | AW17: 3029 | AX17: 3029 | AY17: 3029 | AZ17: 3029 | BA17: 3029 | BB17: 3029 | BC17: 3029 | BD17: 3029 | BE17: 3029 | BF17: 3029 | BG17: 3029 | BH17: 3029 | BI17: 3029 | BJ17: 3029 | BK17: 3029 | BL17: 3029 | BM17: 3029 | BN17: 3029 | BO17: 3029 | BP17: 3029 | BQ17: 3029 | BR17: 3029 | BS17: 3029 | BT17: 3029 | BU17: 3029 | BV17: 3029 | BW17: 3029 | BX17: 3029 | BY17: 3029 | BZ17: 3029 | CA17: 3029 | CB17: 3029 | CC17: 3029 | CD17: 3029 | CE17: 3029 | CF17: 3029 | CG17: 3029 | CH17: 3029 | CI17: 3029 | CJ17: 3029 | CK17: 3029 | CL17: 3029 | CM17: 3029 | CN17: 3029 | CO17: 3029 | CP17: 3029 | CQ17: 3029 | CR17: 3029 | CS17: 3029 | CT17: 3029 | CU17: 3029 | CV17: 3029 | CW17: 3029 | CX17: 3029 | CY17: 3029 | CZ17: 3029 | DA17: 3029 | DB17: 3029 | DC17: 3029 | DD17: 3029 | DE17: 3029 | DF17: 3029 | DG17: 3029 | DH17: 3029 | DI17: 3029 | DJ17: 3029 | DK17: 3029 | DL17: 3029 | DM17: 3029 | DN17: 3029 | DO17: 3029 | DP17: 3029 | DQ17: 3029 | DR17: 3029 | DS17: 3029 | DT17: 3029 | DU17: 3029 | DV17: 3029 | DW17: 3029 | DX17: 3029 | DY17: 3029 | DZ17: 3029 | EA17: 3029 | EB17: 3029 | EC17: 3029 | ED17: 3029
A18: 10. Austin Prosthetics Center | B18: 9 | C18: 4000 | D18: 4000 | E18: 4000 | F18: 4000 | G18: 4000 | H18: 4000 | I18: 4000 | J18: 4000 | K18: 4000 | L18: 4000 | M18: 4000 | N18: 4000 | O18: 4000 | P18: 4000 | Q18: 4000 | R18: 4000 | S18: 4000 | T18: 4000 | U18: 4000 | V18: 4000 | W18: 4000 | X18: 4000 | Y18: 4000 | Z18: 4000 | AA18: 4000 | AB18: 4000 | AC18: 4000 | AD18: 4000 | AE18: 4000 | AF18: 4000 | AG18: 4000 | AH18: 4000 | AI18: 4000 | AJ18: 4000 | AK18: 4000 | AL18: 4000 | AM18: 4000 | AN18: 4000 | AO18: 4000 | AP18: 4000 | AQ18: 4000 | AR18: 4000 | AS18: 4000 | AT18: 4000 | AU18: 4000 | AV18: 4000 | AW18: 4000 | AX18: 4000 | AY18: 4000 | AZ18: 4000 | BA18: 4000 | BB18: 4000 | BC18: 4000 | BD18: 4000 | BE18: 4000 | BF18: 4000 | BG18: 4000 | BH18: 4000 | BI18: 4000 | BJ18: 4000 | BK18: 4000 | BL18: 4000 | BM18: 4000 | BN18: 4000 | BO18: 4000 | BP18: 4000 | BQ18: 4000 | BR18: 4000 | BS18: 0 | BT18: 0 | BU18: 4205 | BV18: 4205 | BW18: 4205 | BX18: 4205 | BY18: 4205 | BZ18: 4205 | CA18: 4205 | CB18: 4205 | CC18: 4205 | CD18: 4205 | CE18: 4205 | CF18: 4205 | CG18: 4205 | CH18: 4205 | CI18: 4205 | CJ18: 4205 | CK18: 4205 | CL18: 4205 | CM18: 4205 | CN18: 4205 | CO18: 4205 | CP18: 4205 | CQ18: 4205 | CR18: 4205 | CS18: 4205 | CT18: 4205 | CU18: 4205 | CV18: 4205 | CW18: 4205 | CX18: 4205 | CY18: 4205 | CZ18: 4205 | DA18: 4205 | DB18: 4205 | DC18: 4205 | DD18: 4205 | DE18: 4205 | DF18: 4205 | DG18: 4205 | DH18: 4205 | DI18: 4205 | DJ18: 4205 | DK18: 4205 | DL18: 4205 | DM18: 4205 | DN18: 4205 | DO18: 4205 | DP18: 4205 | DQ18: 4205 | DR18: 4205 | DS18: 4205 | DT18: 4205 | DU18: 4205 | DV18: 4205 | DW18: 4205 | DX18: 4205 | DY18: 4205 | DZ18: 4205 | EA18: 4205 | EB18: 4205 | EC18: 4205 | ED18: 4205
A19: 11. Ignite Fitnez | B19: 10 | C19: 11815 | D19: 11815 | E19: 11815 | F19: 0 | G19: 0 | H19: 0 | I19: 0 | J19: 0 | K19: 0 | L19: 0 | M19: 0 | N19: 0 | O19: 0 | P19: 0 | Q19: 0 | R19: 11815 | S19: 11815 | T19: 11815 | U19: 11815 | V19: 11815 | W19: 11815 | X19: 11815 | Y19: 11815 | Z19: 11815 | AA19: 11815 | AB19: 11815 | AC19: 11815 | AD19: 11815 | AE19: 11815 | AF19: 11815 | AG19: 11815 | AH19: 11815 | AI19: 11815 | AJ19: 11815 | AK19: 11815 | AL19: 11815 | AM19: 11815 | AN19: 11815 | AO19: 11815 | AP19: 11815 | AQ19: 11815 | AR19: 11815 | AS19: 11815 | AT19: 11815 | AU19: 11815 | AV19: 11815 | AW19: 11815 | AX19: 11815 | AY19: 11815 | AZ19: 11815 | BA19: 11815 | BB19: 11815 | BC19: 11815 | BD19: 11815 | BE19: 11815 | BF19: 11815 | BG19: 11815 | BH19: 11815 | BI19: 11815 | BJ19: 11815 | BK19: 11815 | BL19: 11815 | BM19: 11815 | BN19: 11815 | BO19: 11815 | BP19: 11815 | BQ19: 11815 | BR19: 11815 | BS19: 11815 | BT19: 11815 | BU19: 11815 | BV19: 11815 | BW19: 11815 | BX19: 11815 | BY19: 11815 | BZ19: 11815 | CA19: 11815 | CB19: 11815 | CC19: 11815 | CD19: 11815 | CE19: 11815 | CF19: 11815 | CG19: 11815 | CH19: 11815 | CI19: 11815 | CJ19: 11815 | CK19: 11815 | CL19: 11815 | CM19: 11815 | CN19: 11815 | CO19: 11815 | CP19: 11815 | CQ19: 11815 | CR19: 11815 | CS19: 11815 | CT19: 11815 | CU19: 11815 | CV19: 11815 | CW19: 11815 | CX19: 11815 | CY19: 11815 | CZ19: 11815 | DA19: 11815 | DB19: 11815 | DC19: 0 | DD19: 0 | DE19: 0 | DF19: 0 | DG19: 11815 | DH19: 11815 | DI19: 11815 | DJ19: 11815 | DK19: 11815 | DL19: 11815 | DM19: 11815 | DN19: 11815 | DO19: 11815 | DP19: 11815 | DQ19: 11815 | DR19: 11815 | DS19: 11815 | DT19: 11815 | DU19: 11815 | DV19: 11815 | DW19: 11815 | DX19: 11815 | DY19: 11815 | DZ19: 11815 | EA19: 11815 | EB19: 11815 | EC19: 11815 | ED19: 11815
A20: Total Area | C20: 52969 | D20: 52969 | E20: 52969 | F20: 41154 | G20: 41154 | H20: 41154 | I20: 41154 | J20: 44110 | K20: 44110 | L20: 44110 | M20: 44110 | N20: 44110 | O20: 44110 | P20: 50196 | Q20: 50196 | R20: 62011 | S20: 62011 | T20: 62011 | U20: 59011 | V20: 56011 | W20: 56011 | X20: 59154 | Y20: 59154 | Z20: 59154 | AA20: 62173 | AB20: 62173 | AC20: 62173 | AD20: 56173 | AE20: 56173 | AF20: 62182 | AG20: 62182 | AH20: 62182 | AI20: 62182 | AJ20: 62182 | AK20: 62182 | AL20: 62182 | AM20: 62182 | AN20: 62182 | AO20: 62182 | AP20: 62182 | AQ20: 62182 | AR20: 62182 | AS20: 62182 | AT20: 62182 | AU20: 62182 | AV20: 62182 | AW20: 62182 | AX20: 62182 | AY20: 62182 | AZ20: 62182 | BA20: 62182 | BB20: 62182 | BC20: 62182 | BD20: 62182 | BE20: 62182 | BF20: 62182 | BG20: 62182 | BH20: 60682 | BI20: 60682 | BJ20: 62196 | BK20: 54111 | BL20: 54111 | BM20: 62196 | BN20: 62196 | BO20: 62196 | BP20: 62196 | BQ20: 62196 | BR20: 62196 | BS20: 58196 | BT20: 58196 | BU20: 53445 | BV20: 53445 | BW20: 62401 | BX20: 62401 | BY20: 62401 | BZ20: 62401 | CA20: 56344 | CB20: 56344 | CC20: 62401 | CD20: 62401 | CE20: 62401 | CF20: 62401 | CG20: 62401 | CH20: 62401 | CI20: 52689 | CJ20: 52689 | CK20: 62401 | CL20: 59382 | CM20: 59382 | CN20: 62401 | CO20: 62401 | CP20: 62401 | CQ20: 56392 | CR20: 56392 | CS20: 62401 | CT20: 62401 | CU20: 62401 | CV20: 62401 | CW20: 62401 | CX20: 62401 | CY20: 62401 | CZ20: 62401 | DA20: 62401 | DB20: 62401 | DC20: 50586 | DD20: 50586 | DE20: 50586 | DF20: 50586 | DG20: 62401 | DH20: 62401 | DI20: 62401 | DJ20: 62401 | DK20: 62401 | DL20: 62401 | DM20: 62401 | DN20: 62401 | DO20: 62401 | DP20: 62401 | DQ20: 62401 | DR20: 62401 | DS20: 62401 | DT20: 62401 | DU20: 60887 | DV20: 60887 | DW20: 62401 | DX20: 54316 | DY20: 54316 | DZ20: 62401 | EA20: 62401 | EB20: 62401 | EC20: 62401 | ED20: 62401
A22: Total Occupancy % | C22: 0.85537344 | D22: 0.85537344 | E22: 0.85537344 | F22: 0.66457812 | G22: 0.66457812 | H22: 0.66457812 | I22: 0.66457812 | J22: 0.71165822 | K22: 0.71165822 | L22: 0.71165822 | M22: 0.71165822 | N22: 0.71165822 | O22: 0.71165822 | P22: 0.80946929 | Q22: 0.80946929 | R22: 1 | S22: 1 | T22: 1 | U22: 0.95133 | V22: 0.90088945 | W22: 0.90088945 | X22: 0.95144194 | Y22: 0.95144194 | Z22: 0.95144194 | AA22: 1 | AB22: 1 | AC22: 1 | AD22: 0.90336432 | AE22: 0.90336432 | AF22: 1 | AG22: 1 | AH22: 1 | AI22: 1 | AJ22: 1 | AK22: 1 | AL22: 1 | AM22: 1 | AN22: 1 | AO22: 1 | AP22: 1 | AQ22: 1 | AR22: 1 | AS22: 1 | AT22: 1 | AU22: 1 | AV22: 1 | AW22: 1 | AX22: 1 | AY22: 1 | AZ22: 1 | BA22: 1 | BB22: 1 | BC22: 1 | BD22: 1 | BE22: 1 | BF22: 1 | BG22: 1 | BH22: 0.9756576 | BI22: 0.9756576 | BJ22: 1 | BK22: 0.87000772 | BL22: 0.87000772 | BM22: 1 | BN22: 1 | BO22: 1 | BP22: 1 | BQ22: 1 | BR22: 1 | BS22: 0.93261326 | BT22: 0.93261326 | BU22: 0.85647666 | BV22: 0.85647666 | BW22: 1 | BX22: 1 | BY22: 1 | BZ22: 1 | CA22: 0.90293425 | CB22: 0.90293425 | CC22: 1 | CD22: 1 | CE22: 1 | CF22: 1 | CG22: 1 | CH22: 1 | CI22: 0.84436147 | CJ22: 0.84436147 | CK22: 1 | CL22: 0.95161937 | CM22: 0.95161937 | CN22: 1 | CO22: 1 | CP22: 1 | CQ22: 0.90370347 | CR22: 0.90370347 | CS22: 1 | CT22: 1 | CU22: 1 | CV22: 1 | CW22: 1 | CX22: 1 | CY22: 1 | CZ22: 1 | DA22: 1 | DB22: 1 | DC22: 0.81066009 | DD22: 0.81066009 | DE22: 0.81066009 | DF22: 0.81066009 | DG22: 1 | DH22: 1 | DI22: 1 | DJ22: 1 | DK22: 1 | DL22: 1 | DM22: 1 | DN22: 1 | DO22: 1 | DP22: 1 | DQ22: 1 | DR22: 1 | DS22: 1 | DT22: 1 | DU22: 0.97573757 | DV22: 0.97573757 | DW22: 1 | DX22: 0.87043477 | DY22: 0.87043477 | DZ22: 1 | EA22: 1 | EB22: 1 | EC22: 1 | ED22: 1
A24: Potential Base Rent
A25: 1. Kitu Life, Inc. | B25: 1 | C25: 18191 | D25: 18191 | E25: 18191 | F25: 18191 | G25: 18191 | H25: 18191 | I25: 18191 | J25: 18191 | K25: 18692 | L25: 18692 | M25: 18692 | N25: 18692 | O25: 18692 | P25: 18692 | Q25: 18692 | R25: 18692 | S25: 18692 | T25: 18692 | U25: 18692 | V25: 18692 | W25: 19206 | X25: 19206 | Y25: 19206 | Z25: 19206 | AA25: 19206 | AB25: 19206 | AC25: 19206 | AD25: 19206 | AE25: 19206 | AF25: 19206 | AG25: 19206 | AH25: 19206 | AI25: 19734 | AJ25: 19734 | AK25: 19734 | AL25: 19734 | AM25: 19734 | AN25: 19734 | AO25: 19734 | AP25: 19734 | AQ25: 19734 | AR25: 19734 | AS25: 19734 | AT25: 19734 | AU25: 20276 | AV25: 20276 | AW25: 20276 | AX25: 20276 | AY25: 20276 | AZ25: 20276 | BA25: 20276 | BB25: 20276 | BC25: 20276 | BD25: 20276 | BE25: 20276 | BF25: 20276 | BG25: 20834 | BH25: 20834 | BI25: 20834 | BJ25: 20834 | BK25: 22651 | BL25: 22651 | BM25: 22651 | BN25: 22651 | BO25: 22651 | BP25: 22651 | BQ25: 22651 | BR25: 22651 | BS25: 22651 | BT25: 22651 | BU25: 22651 | BV25: 22651 | BW25: 22651 | BX25: 22651 | BY25: 23330 | BZ25: 23330 | CA25: 23330 | CB25: 23330 | CC25: 23330 | CD25: 23330 | CE25: 23330 | CF25: 23330 | CG25: 23330 | CH25: 23330 | CI25: 23330 | CJ25: 23330 | CK25: 24030 | CL25: 24030 | CM25: 24030 | CN25: 24030 | CO25: 24030 | CP25: 24030 | CQ25: 24030 | CR25: 24030 | CS25: 24030 | CT25: 24030 | CU25: 24030 | CV25: 24030 | CW25: 24751 | CX25: 24751 | CY25: 24751 | CZ25: 24751 | DA25: 24751 | DB25: 24751 | DC25: 24751 | DD25: 24751 | DE25: 24751 | DF25: 24751 | DG25: 24751 | DH25: 24751 | DI25: 25494 | DJ25: 25494 | DK25: 25494 | DL25: 25494 | DM25: 25494 | DN25: 25494 | DO25: 25494 | DP25: 25494 | DQ25: 25494 | DR25: 25494 | DS25: 25494 | DT25: 25494 | DU25: 26258 | DV25: 26258 | DW25: 26258 | DX25: 26258 | DY25: 26258 | DZ25: 26258 | EA25: 26258 | EB25: 26258 | EC25: 26258 | ED25: 26258 | EE25: 2914709
A26: 2. VACANT | B26: 2 | C26: 21644 | D26: 21644 | E26: 21644 | F26: 21644 | G26: 21644 | H26: 21644 | I26: 21644 | J26: 21644 | K26: 21644 | L26: 21644 | M26: 21644 | N26: 21644 | O26: 21644 | P26: 21644 | Q26: 21644 | R26: 21644 | S26: 21644 | T26: 21644 | U26: 21644 | V26: 22293 | W26: 22293 | X26: 22293 | Y26: 22293 | Z26: 22293 | AA26: 22293 | AB26: 22293 | AC26: 22293 | AD26: 22293 | AE26: 22293 | AF26: 22293 | AG26: 22293 | AH26: 22962 | AI26: 22962 | AJ26: 22962 | AK26: 22962 | AL26: 22962 | AM26: 22962 | AN26: 22962 | AO26: 22962 | AP26: 22962 | AQ26: 22962 | AR26: 22962 | AS26: 22962 | AT26: 23651 | AU26: 23651 | AV26: 23651 | AW26: 23651 | AX26: 23651 | AY26: 23651 | AZ26: 23651 | BA26: 23651 | BB26: 23651 | BC26: 23651 | BD26: 23651 | BE26: 23651 | BF26: 24360 | BG26: 24360 | BH26: 24360 | BI26: 24360 | BJ26: 24360 | BK26: 24360 | BL26: 24360 | BM26: 24360 | BN26: 24360 | BO26: 24360 | BP26: 24360 | BQ26: 24360 | BR26: 25091 | BS26: 25091 | BT26: 25091 | BU26: 25091 | BV26: 25091 | BW26: 25844 | BX26: 25844 | BY26: 25844 | BZ26: 25844 | CA26: 25844 | CB26: 25844 | CC26: 25844 | CD26: 25844 | CE26: 25844 | CF26: 25844 | CG26: 25844 | CH26: 25844 | CI26: 26619 | CJ26: 26619 | CK26: 26619 | CL26: 26619 | CM26: 26619 | CN26: 26619 | CO26: 26619 | CP26: 26619 | CQ26: 26619 | CR26: 26619 | CS26: 26619 | CT26: 26619 | CU26: 27418 | CV26: 27418 | CW26: 27418 | CX26: 27418 | CY26: 27418 | CZ26: 27418 | DA26: 27418 | DB26: 27418 | DC26: 27418 | DD26: 27418 | DE26: 27418 | DF26: 27418 | DG26: 28240 | DH26: 28240 | DI26: 28240 | DJ26: 28240 | DK26: 28240 | DL26: 28240 | DM26: 28240 | DN26: 28240 | DO26: 28240 | DP26: 28240 | DQ26: 28240 | DR26: 28240 | DS26: 29087 | DT26: 29087 | DU26: 29087 | DV26: 29087 | DW26: 29087 | DX26: 29087 | DY26: 29087 | DZ26: 29087 | EA26: 29087 | EB26: 29087 | EC26: 29087 | ED26: 29087 | EE26: 3302361
A27: 3. Saatva | B27: 3 | C27: 12208 | D27: 12208 | E27: 12208 | F27: 10750 | G27: 10750 | H27: 10750 | I27: 10750 | J27: 10750 | K27: 10750 | L27: 10750 | M27: 10750 | N27: 10750 | O27: 10750 | P27: 10750 | Q27: 10750 | R27: 13500 | S27: 13500 | T27: 13500 | U27: 13500 | V27: 13500 | W27: 13500 | X27: 13500 | Y27: 13500 | Z27: 13500 | AA27: 13500 | AB27: 13500 | AC27: 13500 | AD27: 15406 | AE27: 15406 | AF27: 15406 | AG27: 15406 | AH27: 15406 | AI27: 15406 | AJ27: 15406 | AK27: 15406 | AL27: 15406 | AM27: 15406 | AN27: 15406 | AO27: 15406 | AP27: 15406 | AQ27: 15406 | AR27: 15868 | AS27: 15868 | AT27: 15868 | AU27: 15868 | AV27: 15868 | AW27: 15868 | AX27: 15868 | AY27: 15868 | AZ27: 15868 | BA27: 15868 | BB27: 15868 | BC27: 15868 | BD27: 16344 | BE27: 16344 | BF27: 16344 | BG27: 16344 | BH27: 16344 | BI27: 16344 | BJ27: 16344 | BK27: 16344 | BL27: 16344 | BM27: 16344 | BN27: 16344 | BO27: 16344 | BP27: 16835 | BQ27: 16835 | BR27: 16835 | BS27: 16835 | BT27: 16835 | BU27: 16835 | BV27: 16835 | BW27: 16835 | BX27: 16835 | BY27: 16835 | BZ27: 16835 | CA27: 16835 | CB27: 17340 | CC27: 17340 | CD27: 17340 | CE27: 17340 | CF27: 17340 | CG27: 17340 | CH27: 17340 | CI27: 17340 | CJ27: 17340 | CK27: 17340 | CL27: 17340 | CM27: 17340 | CN27: 17860 | CO27: 17860 | CP27: 17860 | CQ27: 17860 | CR27: 17860 | CS27: 17860 | CT27: 17860 | CU27: 17860 | CV27: 17860 | CW27: 17860 | CX27: 17860 | CY27: 17860 | CZ27: 17860 | DA27: 17860 | DB27: 17860 | DC27: 17860 | DD27: 17860 | DE27: 18396 | DF27: 18396 | DG27: 18396 | DH27: 18396 | DI27: 18396 | DJ27: 18396 | DK27: 18396 | DL27: 18396 | DM27: 18396 | DN27: 18396 | DO27: 18396 | DP27: 18396 | DQ27: 18948 | DR27: 18948 | DS27: 18948 | DT27: 18948 | DU27: 18948 | DV27: 18948 | DW27: 18948 | DX27: 18948 | DY27: 18948 | DZ27: 18948 | EA27: 18948 | EB27: 18948 | EC27: 19516 | ED27: 19516 | EE27: 2130726
A28: 4. Fuse Architecture Studio | B28: 4 | C28: 6010 | D28: 6010 | E28: 6010 | F28: 6010 | G28: 6010 | H28: 6010 | I28: 6010 | J28: 6190 | K28: 6190 | L28: 6190 | M28: 6190 | N28: 6190 | O28: 6190 | P28: 6190 | Q28: 6190 | R28: 6190 | S28: 6190 | T28: 6190 | U28: 6190 | V28: 7823 | W28: 7823 | X28: 7823 | Y28: 7823 | Z28: 7823 | AA28: 7823 | AB28: 7823 | AC28: 7823 | AD28: 7823 | AE28: 7823 | AF28: 7823 | AG28: 7823 | AH28: 7823 | AI28: 7823 | AJ28: 8058 | AK28: 8058 | AL28: 8058 | AM28: 8058 | AN28: 8058 | AO28: 8058 | AP28: 8058 | AQ28: 8058 | AR28: 8058 | AS28: 8058 | AT28: 8058 | AU28: 8058 | AV28: 8300 | AW28: 8300 | AX28: 8300 | AY28: 8300 | AZ28: 8300 | BA28: 8300 | BB28: 8300 | BC28: 8300 | BD28: 8300 | BE28: 8300 | BF28: 8300 | BG28: 8300 | BH28: 8549 | BI28: 8549 | BJ28: 8549 | BK28: 8549 | BL28: 8549 | BM28: 8549 | BN28: 8549 | BO28: 8549 | BP28: 8549 | BQ28: 8549 | BR28: 8549 | BS28: 8549 | BT28: 8805 | BU28: 8805 | BV28: 8805 | BW28: 8805 | BX28: 8805 | BY28: 8805 | BZ28: 8805 | CA28: 8805 | CB28: 8805 | CC28: 8805 | CD28: 8805 | CE28: 8805 | CF28: 9070 | CG28: 9070 | CH28: 9070 | CI28: 9342 | CJ28: 9342 | CK28: 9342 | CL28: 9342 | CM28: 9342 | CN28: 9342 | CO28: 9342 | CP28: 9342 | CQ28: 9342 | CR28: 9342 | CS28: 9342 | CT28: 9342 | CU28: 9342 | CV28: 9342 | CW28: 9622 | CX28: 9622 | CY28: 9622 | CZ28: 9622 | DA28: 9622 | DB28: 9622 | DC28: 9622 | DD28: 9622 | DE28: 9622 | DF28: 9622 | DG28: 9622 | DH28: 9622 | DI28: 9911 | DJ28: 9911 | DK28: 9911 | DL28: 9911 | DM28: 9911 | DN28: 9911 | DO28: 9911 | DP28: 9911 | DQ28: 9911 | DR28: 9911 | DS28: 9911 | DT28: 9911 | DU28: 10208 | DV28: 10208 | DW28: 10208 | DX28: 10208 | DY28: 10208 | DZ28: 10208 | EA28: 10208 | EB28: 10208 | EC28: 10208 | ED28: 10208 | EE28: 1124884
A29: 5. Made In (sublessee to Geek Powered Studios) | B29: 5 | C29: 9850 | D29: 9850 | E29: 9850 | F29: 9850 | G29: 9850 | H29: 9850 | I29: 9850 | J29: 14638 | K29: 14638 | L29: 14638 | M29: 14638 | N29: 14638 | O29: 15077 | P29: 15077 | Q29: 15077 | R29: 15077 | S29: 15077 | T29: 15077 | U29: 15077 | V29: 15077 | W29: 15077 | X29: 15077 | Y29: 15077 | Z29: 15077 | AA29: 15077 | AB29: 15529 | AC29: 15529 | AD29: 15529 | AE29: 15529 | AF29: 15529 | AG29: 15529 | AH29: 15529 | AI29: 15529 | AJ29: 15529 | AK29: 15529 | AL29: 15529 | AM29: 15529 | AN29: 15995 | AO29: 15995 | AP29: 15995 | AQ29: 15995 | AR29: 15995 | AS29: 15995 | AT29: 15995 | AU29: 15995 | AV29: 15995 | AW29: 15995 | AX29: 15995 | AY29: 15995 | AZ29: 16475 | BA29: 16475 | BB29: 16475 | BC29: 16475 | BD29: 16475 | BE29: 16475 | BF29: 16475 | BG29: 16475 | BH29: 16475 | BI29: 16475 | BJ29: 16475 | BK29: 16475 | BL29: 16969 | BM29: 16969 | BN29: 16969 | BO29: 16969 | BP29: 16969 | BQ29: 16969 | BR29: 16969 | BS29: 16969 | BT29: 16969 | BU29: 16969 | BV29: 16969 | BW29: 16969 | BX29: 17478 | BY29: 17478 | BZ29: 17478 | CA29: 17478 | CB29: 17478 | CC29: 17478 | CD29: 17478 | CE29: 17478 | CF29: 17478 | CG29: 17478 | CH29: 17478 | CI29: 17478 | CJ29: 17478 | CK29: 17478 | CL29: 17478 | CM29: 17478 | CN29: 17478 | CO29: 18003 | CP29: 18003 | CQ29: 18003 | CR29: 18003 | CS29: 18003 | CT29: 18003 | CU29: 18003 | CV29: 18003 | CW29: 18003 | CX29: 18003 | CY29: 18003 | CZ29: 18003 | DA29: 18543 | DB29: 18543 | DC29: 18543 | DD29: 18543 | DE29: 18543 | DF29: 18543 | DG29: 18543 | DH29: 18543 | DI29: 18543 | DJ29: 18543 | DK29: 18543 | DL29: 18543 | DM29: 19099 | DN29: 19099 | DO29: 19099 | DP29: 19099 | DQ29: 19099 | DR29: 19099 | DS29: 19099 | DT29: 19099 | DU29: 19099 | DV29: 19099 | DW29: 19099 | DX29: 19099 | DY29: 19672 | DZ29: 19672 | EA29: 19672 | EB29: 19672 | EC29: 19672 | ED29: 19672 | EE29: 2200650
A30: 6. Elmo 35, LLC | B30: 6 | C30: 15875 | D30: 15875 | E30: 15875 | F30: 15875 | G30: 15875 | H30: 15875 | I30: 15875 | J30: 15875 | K30: 15875 | L30: 15875 | M30: 15875 | N30: 15875 | O30: 16351 | P30: 16351 | Q30: 16351 | R30: 16351 | S30: 16351 | T30: 16351 | U30: 16351 | V30: 16351 | W30: 16351 | X30: 16351 | Y30: 16351 | Z30: 16351 | AA30: 16842 | AB30: 16842 | AC30: 16842 | AD30: 16842 | AE30: 16842 | AF30: 16842 | AG30: 16842 | AH30: 16842 | AI30: 16842 | AJ30: 16842 | AK30: 16842 | AL30: 16842 | AM30: 17347 | AN30: 17347 | AO30: 17347 | AP30: 17347 | AQ30: 17347 | AR30: 17347 | AS30: 17347 | AT30: 17347 | AU30: 17347 | AV30: 17347 | AW30: 17347 | AX30: 17347 | AY30: 17868 | AZ30: 17868 | BA30: 17868 | BB30: 17868 | BC30: 17868 | BD30: 17868 | BE30: 17868 | BF30: 17868 | BG30: 17868 | BH30: 17868 | BI30: 17868 | BJ30: 17868 | BK30: 18404 | BL30: 18404 | BM30: 18404 | BN30: 18404 | BO30: 18404 | BP30: 18404 | BQ30: 18404 | BR30: 18404 | BS30: 18404 | BT30: 18404 | BU30: 18404 | BV30: 18404 | BW30: 18956 | BX30: 18956 | BY30: 18956 | BZ30: 18956 | CA30: 18956 | CB30: 18956 | CC30: 18956 | CD30: 18956 | CE30: 18956 | CF30: 18956 | CG30: 18956 | CH30: 18956 | CI30: 19524 | CJ30: 19524 | CK30: 19524 | CL30: 19524 | CM30: 19524 | CN30: 19524 | CO30: 19524 | CP30: 19524 | CQ30: 19524 | CR30: 19524 | CS30: 19524 | CT30: 19524 | CU30: 19524 | CV30: 19524 | CW30: 20110 | CX30: 20110 | CY30: 20110 | CZ30: 20110 | DA30: 20110 | DB30: 20110 | DC30: 20110 | DD30: 20110 | DE30: 20110 | DF30: 20110 | DG30: 20110 | DH30: 20110 | DI30: 20713 | DJ30: 20713 | DK30: 20713 | DL30: 20713 | DM30: 20713 | DN30: 20713 | DO30: 20713 | DP30: 20713 | DQ30: 20713 | DR30: 20713 | DS30: 20713 | DT30: 20713 | DU30: 21335 | DV30: 21335 | DW30: 21335 | DX30: 21335 | DY30: 21335 | DZ30: 21335 | EA30: 21335 | EB30: 21335 | EC30: 21335 | ED30: 21335 | EE30: 2436277
A31: 7. Trihydro Corporation | B31: 7 | C31: 6010 | D31: 6010 | E31: 6010 | F31: 6010 | G31: 6010 | H31: 6010 | I31: 6190 | J31: 6190 | K31: 6190 | L31: 6190 | M31: 6190 | N31: 6190 | O31: 6190 | P31: 6190 | Q31: 6190 | R31: 6190 | S31: 6190 | T31: 6190 | U31: 7515 | V31: 7515 | W31: 7515 | X31: 7515 | Y31: 7515 | Z31: 7515 | AA31: 7740 | AB31: 7740 | AC31: 7740 | AD31: 7740 | AE31: 7740 | AF31: 7740 | AG31: 7740 | AH31: 7740 | AI31: 7740 | AJ31: 7740 | AK31: 7740 | AL31: 7740 | AM31: 7972 | AN31: 7972 | AO31: 7972 | AP31: 7972 | AQ31: 7972 | AR31: 7972 | AS31: 7972 | AT31: 7972 | AU31: 7972 | AV31: 7972 | AW31: 7972 | AX31: 7972 | AY31: 8212 | AZ31: 8212 | BA31: 8212 | BB31: 8212 | BC31: 8212 | BD31: 8212 | BE31: 8212 | BF31: 8212 | BG31: 8212 | BH31: 8212 | BI31: 8212 | BJ31: 8212 | BK31: 8458 | BL31: 8458 | BM31: 8458 | BN31: 8458 | BO31: 8458 | BP31: 8458 | BQ31: 8458 | BR31: 8458 | BS31: 8458 | BT31: 8458 | BU31: 8458 | BV31: 8458 | BW31: 8712 | BX31: 8712 | BY31: 8712 | BZ31: 8712 | CA31: 8712 | CB31: 8712 | CC31: 8712 | CD31: 8712 | CE31: 8712 | CF31: 8712 | CG31: 8712 | CH31: 8712 | CI31: 8973 | CJ31: 8973 | CK31: 8973 | CL31: 8973 | CM31: 8973 | CN31: 8973 | CO31: 8973 | CP31: 8973 | CQ31: 8973 | CR31: 8973 | CS31: 8973 | CT31: 8973 | CU31: 8973 | CV31: 8973 | CW31: 8973 | CX31: 8973 | CY31: 8973 | CZ31: 9242 | DA31: 9242 | DB31: 9242 | DC31: 9242 | DD31: 9242 | DE31: 9242 | DF31: 9242 | DG31: 9242 | DH31: 9242 | DI31: 9242 | DJ31: 9242 | DK31: 9242 | DL31: 9520 | DM31: 9520 | DN31: 9520 | DO31: 9520 | DP31: 9520 | DQ31: 9520 | DR31: 9520 | DS31: 9520 | DT31: 9520 | DU31: 9520 | DV31: 9520 | DW31: 9520 | DX31: 9805 | DY31: 9805 | DZ31: 9805 | EA31: 9805 | EB31: 9805 | EC31: 9805 | ED31: 9805 | EE31: 1094879
A32: 8. Urban ATX | B32: 07A | C32: 3252 | D32: 3252 | E32: 3252 | F32: 3252 | G32: 3252 | H32: 3252 | I32: 3252 | J32: 3350 | K32: 3350 | L32: 3350 | M32: 3350 | N32: 3350 | O32: 3350 | P32: 3350 | Q32: 3350 | R32: 3350 | S32: 3350 | T32: 3350 | U32: 3350 | V32: 3450 | W32: 3450 | X32: 3450 | Y32: 3450 | Z32: 3450 | AA32: 3450 | AB32: 3450 | AC32: 3450 | AD32: 3450 | AE32: 3450 | AF32: 3450 | AG32: 3450 | AH32: 3554 | AI32: 3554 | AJ32: 3554 | AK32: 3554 | AL32: 3554 | AM32: 3554 | AN32: 3554 | AO32: 3554 | AP32: 3554 | AQ32: 3554 | AR32: 3554 | AS32: 3554 | AT32: 3660 | AU32: 3660 | AV32: 3660 | AW32: 3660 | AX32: 3660 | AY32: 3660 | AZ32: 3660 | BA32: 3660 | BB32: 3660 | BC32: 3660 | BD32: 3660 | BE32: 3660 | BF32: 3660 | BG32: 3660 | BH32: 4118 | BI32: 4118 | BJ32: 4118 | BK32: 4118 | BL32: 4118 | BM32: 4118 | BN32: 4118 | BO32: 4118 | BP32: 4118 | BQ32: 4118 | BR32: 4118 | BS32: 4118 | BT32: 4118 | BU32: 4118 | BV32: 4242 | BW32: 4242 | BX32: 4242 | BY32: 4242 | BZ32: 4242 | CA32: 4242 | CB32: 4242 | CC32: 4242 | CD32: 4242 | CE32: 4242 | CF32: 4242 | CG32: 4242 | CH32: 4369 | CI32: 4369 | CJ32: 4369 | CK32: 4369 | CL32: 4369 | CM32: 4369 | CN32: 4369 | CO32: 4369 | CP32: 4369 | CQ32: 4369 | CR32: 4369 | CS32: 4369 | CT32: 4500 | CU32: 4500 | CV32: 4500 | CW32: 4500 | CX32: 4500 | CY32: 4500 | CZ32: 4500 | DA32: 4500 | DB32: 4500 | DC32: 4500 | DD32: 4500 | DE32: 4500 | DF32: 4635 | DG32: 4635 | DH32: 4635 | DI32: 4635 | DJ32: 4635 | DK32: 4635 | DL32: 4635 | DM32: 4635 | DN32: 4635 | DO32: 4635 | DP32: 4635 | DQ32: 4635 | DR32: 4774 | DS32: 4774 | DT32: 4774 | DU32: 4917 | DV32: 4917 | DW32: 4917 | DX32: 4917 | DY32: 4917 | DZ32: 4917 | EA32: 4917 | EB32: 4917 | EC32: 4917 | ED32: 4917 | EE32: 532343
A33: 9. Brinkley Sargent Winginton Architects | B33: 8 | C33: 5375 | D33: 5500 | E33: 5500 | F33: 5500 | G33: 5500 | H33: 5500 | I33: 5500 | J33: 5500 | K33: 5500 | L33: 5500 | M33: 5500 | N33: 5500 | O33: 5500 | P33: 6563 | Q33: 6563 | R33: 6563 | S33: 6563 | T33: 6563 | U33: 6563 | V33: 6563 | W33: 6563 | X33: 6563 | Y33: 6563 | Z33: 6563 | AA33: 6563 | AB33: 6760 | AC33: 6760 | AD33: 6760 | AE33: 6760 | AF33: 6760 | AG33: 6760 | AH33: 6760 | AI33: 6760 | AJ33: 6760 | AK33: 6760 | AL33: 6760 | AM33: 6760 | AN33: 6963 | AO33: 6963 | AP33: 6963 | AQ33: 6963 | AR33: 6963 | AS33: 6963 | AT33: 6963 | AU33: 6963 | AV33: 6963 | AW33: 6963 | AX33: 6963 | AY33: 6963 | AZ33: 7171 | BA33: 7171 | BB33: 7171 | BC33: 7171 | BD33: 7171 | BE33: 7171 | BF33: 7171 | BG33: 7171 | BH33: 7171 | BI33: 7171 | BJ33: 7171 | BK33: 7171 | BL33: 7387 | BM33: 7387 | BN33: 7387 | BO33: 7387 | BP33: 7387 | BQ33: 7387 | BR33: 7387 | BS33: 7387 | BT33: 7387 | BU33: 7387 | BV33: 7387 | BW33: 7387 | BX33: 7608 | BY33: 7608 | BZ33: 7608 | CA33: 7608 | CB33: 7608 | CC33: 7608 | CD33: 7608 | CE33: 7608 | CF33: 7608 | CG33: 7608 | CH33: 7608 | CI33: 7608 | CJ33: 7836 | CK33: 7836 | CL33: 7836 | CM33: 7836 | CN33: 7836 | CO33: 7836 | CP33: 7836 | CQ33: 7836 | CR33: 7836 | CS33: 7836 | CT33: 7836 | CU33: 7836 | CV33: 8071 | CW33: 8071 | CX33: 8071 | CY33: 8071 | CZ33: 8071 | DA33: 8071 | DB33: 8071 | DC33: 8071 | DD33: 8071 | DE33: 8071 | DF33: 8071 | DG33: 8071 | DH33: 8314 | DI33: 8314 | DJ33: 8314 | DK33: 8314 | DL33: 8314 | DM33: 8314 | DN33: 8314 | DO33: 8314 | DP33: 8314 | DQ33: 8314 | DR33: 8314 | DS33: 8314 | DT33: 8563 | DU33: 8563 | DV33: 8563 | DW33: 8563 | DX33: 8563 | DY33: 8563 | DZ33: 8563 | EA33: 8563 | EB33: 8563 | EC33: 8563 | ED33: 8563 | EE33: 965638
A34: 10. Austin Prosthetics Center | B34: 9 | C34: 7167 | D34: 7167 | E34: 7167 | F34: 7167 | G34: 7167 | H34: 7167 | I34: 7167 | J34: 7167 | K34: 7333 | L34: 7333 | M34: 7333 | N34: 7333 | O34: 7333 | P34: 7333 | Q34: 7333 | R34: 7333 | S34: 7333 | T34: 7333 | U34: 7333 | V34: 7333 | W34: 7500 | X34: 7500 | Y34: 7500 | Z34: 7500 | AA34: 7500 | AB34: 7500 | AC34: 7500 | AD34: 7500 | AE34: 7500 | AF34: 7500 | AG34: 7500 | AH34: 7500 | AI34: 7667 | AJ34: 7667 | AK34: 7667 | AL34: 7667 | AM34: 7667 | AN34: 7667 | AO34: 7667 | AP34: 7667 | AQ34: 7667 | AR34: 7667 | AS34: 7667 | AT34: 7667 | AU34: 7833 | AV34: 7833 | AW34: 7833 | AX34: 7833 | AY34: 7833 | AZ34: 7833 | BA34: 7833 | BB34: 7833 | BC34: 7833 | BD34: 7833 | BE34: 7833 | BF34: 7833 | BG34: 8000 | BH34: 8000 | BI34: 8000 | BJ34: 8000 | BK34: 8000 | BL34: 8000 | BM34: 8000 | BN34: 8000 | BO34: 8000 | BP34: 8000 | BQ34: 8000 | BR34: 8000 | BS34: 11781 | BT34: 11781 | BU34: 11781 | BV34: 11781 | BW34: 11781 | BX34: 11781 | BY34: 11781 | BZ34: 11781 | CA34: 11781 | CB34: 11781 | CC34: 11781 | CD34: 11781 | CE34: 11781 | CF34: 11781 | CG34: 12134 | CH34: 12134 | CI34: 12134 | CJ34: 12134 | CK34: 12134 | CL34: 12134 | CM34: 12134 | CN34: 12134 | CO34: 12134 | CP34: 12134 | CQ34: 12134 | CR34: 12134 | CS34: 12498 | CT34: 12498 | CU34: 12498 | CV34: 12498 | CW34: 12498 | CX34: 12498 | CY34: 12498 | CZ34: 12498 | DA34: 12498 | DB34: 12498 | DC34: 12498 | DD34: 12498 | DE34: 12873 | DF34: 12873 | DG34: 12873 | DH34: 12873 | DI34: 12873 | DJ34: 12873 | DK34: 12873 | DL34: 12873 | DM34: 12873 | DN34: 12873 | DO34: 12873 | DP34: 12873 | DQ34: 13259 | DR34: 13259 | DS34: 13259 | DT34: 13259 | DU34: 13259 | DV34: 13259 | DW34: 13259 | DX34: 13259 | DY34: 13259 | DZ34: 13259 | EA34: 13259 | EB34: 13259 | EC34: 13657 | ED34: 13657 | EE34: 1318749
A35: 11. Ignite Fitnez | B35: 10 | C35: 0 | D35: 0 | E35: 0 | F35: 28553 | G35: 28553 | H35: 28553 | I35: 28553 | J35: 28553 | K35: 28553 | L35: 28553 | M35: 28553 | N35: 28553 | O35: 29410 | P35: 29410 | Q35: 29410 | R35: 29410 | S35: 29410 | T35: 29410 | U35: 29410 | V35: 29410 | W35: 29410 | X35: 29410 | Y35: 29410 | Z35: 29410 | AA35: 29410 | AB35: 29410 | AC35: 29410 | AD35: 30292 | AE35: 30292 | AF35: 30292 | AG35: 30292 | AH35: 30292 | AI35: 30292 | AJ35: 30292 | AK35: 30292 | AL35: 30292 | AM35: 30292 | AN35: 30292 | AO35: 30292 | AP35: 31201 | AQ35: 31201 | AR35: 31201 | AS35: 31201 | AT35: 31201 | AU35: 31201 | AV35: 31201 | AW35: 31201 | AX35: 31201 | AY35: 31201 | AZ35: 31201 | BA35: 31201 | BB35: 32137 | BC35: 32137 | BD35: 32137 | BE35: 32137 | BF35: 32137 | BG35: 32137 | BH35: 32137 | BI35: 32137 | BJ35: 32137 | BK35: 32137 | BL35: 32137 | BM35: 32137 | BN35: 33101 | BO35: 33101 | BP35: 33101 | BQ35: 33101 | BR35: 33101 | BS35: 33101 | BT35: 33101 | BU35: 33101 | BV35: 33101 | BW35: 33101 | BX35: 33101 | BY35: 33101 | BZ35: 34094 | CA35: 34094 | CB35: 34094 | CC35: 34094 | CD35: 34094 | CE35: 34094 | CF35: 34094 | CG35: 34094 | CH35: 34094 | CI35: 34094 | CJ35: 34094 | CK35: 34094 | CL35: 35116 | CM35: 35116 | CN35: 35116 | CO35: 35116 | CP35: 35116 | CQ35: 35116 | CR35: 35116 | CS35: 35116 | CT35: 35116 | CU35: 35116 | CV35: 35116 | CW35: 35116 | CX35: 36170 | CY35: 36170 | CZ35: 36170 | DA35: 36170 | DB35: 36170 | DC35: 36170 | DD35: 36170 | DE35: 36170 | DF35: 36170 | DG35: 37255 | DH35: 37255 | DI35: 37255 | DJ35: 37255 | DK35: 37255 | DL35: 37255 | DM35: 37255 | DN35: 37255 | DO35: 37255 | DP35: 37255 | DQ35: 37255 | DR35: 37255 | DS35: 38373 | DT35: 38373 | DU35: 38373 | DV35: 38373 | DW35: 38373 | DX35: 38373 | DY35: 38373 | DZ35: 38373 | EA35: 38373 | EB35: 38373 | EC35: 38373 | ED35: 38373 | EE35: 4282459
A36: Total Potential Base Rent | C36: 105582 | D36: 105707 | E36: 105707 | F36: 132802 | G36: 132802 | H36: 132802 | I36: 132982 | J36: 138047 | K36: 138714 | L36: 138714 | M36: 138714 | N36: 138714 | O36: 140486 | P36: 141549 | Q36: 141549 | R36: 144299 | S36: 144299 | T36: 144299 | U36: 145624 | V36: 148007 | W36: 148688 | X36: 148688 | Y36: 148688 | Z36: 148688 | AA36: 149404 | AB36: 150053 | AC36: 150053 | AD36: 152841 | AE36: 152841 | AF36: 152841 | AG36: 152841 | AH36: 153613 | AI36: 154308 | AJ36: 154543 | AK36: 154543 | AL36: 154543 | AM36: 155280 | AN36: 155949 | AO36: 155949 | AP36: 156858 | AQ36: 156858 | AR36: 157320 | AS36: 157320 | AT36: 158115 | AU36: 158825 | AV36: 159067 | AW36: 159067 | AX36: 159067 | AY36: 159826 | AZ36: 160515 | BA36: 160515 | BB36: 161451 | BC36: 161451 | BD36: 161927 | BE36: 161927 | BF36: 162636 | BG36: 163361 | BH36: 164067 | BI36: 164067 | BJ36: 164067 | BK36: 166667 | BL36: 167376 | BM36: 167376 | BN36: 168340 | BO36: 168340 | BP36: 168830 | BQ36: 168830 | BR36: 169561 | BS36: 173342 | BT36: 173598 | BU36: 173598 | BV36: 173722 | BW36: 175280 | BX36: 176011 | BY36: 176691 | BZ36: 177684 | CA36: 177684 | CB36: 178189 | CC36: 178189 | CD36: 178189 | CE36: 178189 | CF36: 178453 | CG36: 178806 | CH36: 178934 | CI36: 180811 | CJ36: 181039 | CK36: 181739 | CL36: 182762 | CM36: 182762 | CN36: 183282 | CO36: 183806 | CP36: 183806 | CQ36: 183806 | CR36: 183806 | CS36: 184170 | CT36: 184302 | CU36: 185100 | CV36: 185335 | CW36: 186922 | CX36: 187976 | CY36: 187976 | CZ36: 188245 | DA36: 188785 | DB36: 188785 | DC36: 188785 | DD36: 188785 | DE36: 189696 | DF36: 189831 | DG36: 191738 | DH36: 191980 | DI36: 193615 | DJ36: 193615 | DK36: 193615 | DL36: 193892 | DM36: 194448 | DN36: 194448 | DO36: 194448 | DP36: 194448 | DQ36: 195386 | DR36: 195526 | DS36: 197490 | DT36: 197740 | DU36: 199567 | DV36: 199567 | DW36: 199567 | DX36: 199852 | DY36: 200425 | DZ36: 200425 | EA36: 200425 | EB36: 200425 | EC36: 201391 | ED36: 201391 | EE36: 22303675
A38: Lost Absorption / Turnover Rent
A39: 1. Kitu Life, Inc. | B39: 1 | C39: 0 | D39: 0 | E39: 0 | F39: 0 | G39: 0 | H39: 0 | I39: 0 | J39: 0 | K39: 0 | L39: 0 | M39: 0 | N39: 0 | O39: 0 | P39: 0 | Q39: 0 | R39: 0 | S39: 0 | T39: 0 | U39: 0 | V39: 0 | W39: 0 | X39: 0 | Y39: 0 | Z39: 0 | AA39: 0 | AB39: 0 | AC39: 0 | AD39: 0 | AE39: 0 | AF39: 0 | AG39: 0 | AH39: 0 | AI39: 0 | AJ39: 0 | AK39: 0 | AL39: 0 | AM39: 0 | AN39: 0 | AO39: 0 | AP39: 0 | AQ39: 0 | AR39: 0 | AS39: 0 | AT39: 0 | AU39: 0 | AV39: 0 | AW39: 0 | AX39: 0 | AY39: 0 | AZ39: 0 | BA39: 0 | BB39: 0 | BC39: 0 | BD39: 0 | BE39: 0 | BF39: 0 | BG39: 0 | BH39: 0 | BI39: 0 | BJ39: 0 | BK39: -22651 | BL39: -22651 | BM39: 0 | BN39: 0 | BO39: 0 | BP39: 0 | BQ39: 0 | BR39: 0 | BS39: 0 | BT39: 0 | BU39: 0 | BV39: 0 | BW39: 0 | BX39: 0 | BY39: 0 | BZ39: 0 | CA39: 0 | CB39: 0 | CC39: 0 | CD39: 0 | CE39: 0 | CF39: 0 | CG39: 0 | CH39: 0 | CI39: 0 | CJ39: 0 | CK39: 0 | CL39: 0 | CM39: 0 | CN39: 0 | CO39: 0 | CP39: 0 | CQ39: 0 | CR39: 0 | CS39: 0 | CT39: 0 | CU39: 0 | CV39: 0 | CW39: 0 | CX39: 0 | CY39: 0 | CZ39: 0 | DA39: 0 | DB39: 0 | DC39: 0 | DD39: 0 | DE39: 0 | DF39: 0 | DG39: 0 | DH39: 0 | DI39: 0 | DJ39: 0 | DK39: 0 | DL39: 0 | DM39: 0 | DN39: 0 | DO39: 0 | DP39: 0 | DQ39: 0 | DR39: 0 | DS39: 0 | DT39: 0 | DU39: 0 | DV39: 0 | DW39: 0 | DX39: -26258 | DY39: -26258 | DZ39: 0 | EA39: 0 | EB39: 0 | EC39: 0 | ED39: 0 | EE39: -97818
A40: 2. VACANT | B40: 2 | C40: -21644 | D40: -21644 | E40: -21644 | F40: -21644 | G40: -21644 | H40: -21644 | I40: -21644 | J40: 0 | K40: 0 | L40: 0 | M40: 0 | N40: 0 | O40: 0 | P40: 0 | Q40: 0 | R40: 0 | S40: 0 | T40: 0 | U40: 0 | V40: 0 | W40: 0 | X40: 0 | Y40: 0 | Z40: 0 | AA40: 0 | AB40: 0 | AC40: 0 | AD40: 0 | AE40: 0 | AF40: 0 | AG40: 0 | AH40: 0 | AI40: 0 | AJ40: 0 | AK40: 0 | AL40: 0 | AM40: 0 | AN40: 0 | AO40: 0 | AP40: 0 | AQ40: 0 | AR40: 0 | AS40: 0 | AT40: 0 | AU40: 0 | AV40: 0 | AW40: 0 | AX40: 0 | AY40: 0 | AZ40: 0 | BA40: 0 | BB40: 0 | BC40: 0 | BD40: 0 | BE40: 0 | BF40: 0 | BG40: 0 | BH40: 0 | BI40: 0 | BJ40: 0 | BK40: 0 | BL40: 0 | BM40: 0 | BN40: 0 | BO40: 0 | BP40: 0 | BQ40: 0 | BR40: 0 | BS40: 0 | BT40: 0 | BU40: -25091 | BV40: -25091 | BW40: 0 | BX40: 0 | BY40: 0 | BZ40: 0 | CA40: 0 | CB40: 0 | CC40: 0 | CD40: 0 | CE40: 0 | CF40: 0 | CG40: 0 | CH40: 0 | CI40: 0 | CJ40: 0 | CK40: 0 | CL40: 0 | CM40: 0 | CN40: 0 | CO40: 0 | CP40: 0 | CQ40: 0 | CR40: 0 | CS40: 0 | CT40: 0 | CU40: 0 | CV40: 0 | CW40: 0 | CX40: 0 | CY40: 0 | CZ40: 0 | DA40: 0 | DB40: 0 | DC40: 0 | DD40: 0 | DE40: 0 | DF40: 0 | DG40: 0 | DH40: 0 | DI40: 0 | DJ40: 0 | DK40: 0 | DL40: 0 | DM40: 0 | DN40: 0 | DO40: 0 | DP40: 0 | DQ40: 0 | DR40: 0 | DS40: 0 | DT40: 0 | DU40: 0 | DV40: 0 | DW40: 0 | DX40: 0 | DY40: 0 | DZ40: 0 | EA40: 0 | EB40: 0 | EC40: 0 | ED40: 0 | EE40: -201688
A41: 3. Saatva | B41: 3 | C41: 0 | D41: 0 | E41: 0 | F41: 0 | G41: 0 | H41: 0 | I41: 0 | J41: 0 | K41: 0 | L41: 0 | M41: 0 | N41: 0 | O41: 0 | P41: 0 | Q41: 0 | R41: 0 | S41: 0 | T41: 0 | U41: 0 | V41: 0 | W41: 0 | X41: 0 | Y41: 0 | Z41: 0 | AA41: 0 | AB41: 0 | AC41: 0 | AD41: -15406 | AE41: -15406 | AF41: 0 | AG41: 0 | AH41: 0 | AI41: 0 | AJ41: 0 | AK41: 0 | AL41: 0 | AM41: 0 | AN41: 0 | AO41: 0 | AP41: 0 | AQ41: 0 | AR41: 0 | AS41: 0 | AT41: 0 | AU41: 0 | AV41: 0 | AW41: 0 | AX41: 0 | AY41: 0 | AZ41: 0 | BA41: 0 | BB41: 0 | BC41: 0 | BD41: 0 | BE41: 0 | BF41: 0 | BG41: 0 | BH41: 0 | BI41: 0 | BJ41: 0 | BK41: 0 | BL41: 0 | BM41: 0 | BN41: 0 | BO41: 0 | BP41: 0 | BQ41: 0 | BR41: 0 | BS41: 0 | BT41: 0 | BU41: 0 | BV41: 0 | BW41: 0 | BX41: 0 | BY41: 0 | BZ41: 0 | CA41: 0 | CB41: 0 | CC41: 0 | CD41: 0 | CE41: 0 | CF41: 0 | CG41: 0 | CH41: 0 | CI41: 0 | CJ41: 0 | CK41: 0 | CL41: 0 | CM41: 0 | CN41: 0 | CO41: 0 | CP41: 0 | CQ41: -17860 | CR41: -17860 | CS41: 0 | CT41: 0 | CU41: 0 | CV41: 0 | CW41: 0 | CX41: 0 | CY41: 0 | CZ41: 0 | DA41: 0 | DB41: 0 | DC41: 0 | DD41: 0 | DE41: 0 | DF41: 0 | DG41: 0 | DH41: 0 | DI41: 0 | DJ41: 0 | DK41: 0 | DL41: 0 | DM41: 0 | DN41: 0 | DO41: 0 | DP41: 0 | DQ41: 0 | DR41: 0 | DS41: 0 | DT41: 0 | DU41: 0 | DV41: 0 | DW41: 0 | DX41: 0 | DY41: 0 | DZ41: 0 | EA41: 0 | EB41: 0 | EC41: 0 | ED41: 0 | EE41: -66532
A42: 4. Fuse Architecture Studio | B42: 4 | C42: 0 | D42: 0 | E42: 0 | F42: 0 | G42: 0 | H42: 0 | I42: 0 | J42: 0 | K42: 0 | L42: 0 | M42: 0 | N42: 0 | O42: 0 | P42: 0 | Q42: 0 | R42: 0 | S42: 0 | T42: 0 | U42: 0 | V42: -7823 | W42: -7823 | X42: 0 | Y42: 0 | Z42: 0 | AA42: 0 | AB42: 0 | AC42: 0 | AD42: 0 | AE42: 0 | AF42: 0 | AG42: 0 | AH42: 0 | AI42: 0 | AJ42: 0 | AK42: 0 | AL42: 0 | AM42: 0 | AN42: 0 | AO42: 0 | AP42: 0 | AQ42: 0 | AR42: 0 | AS42: 0 | AT42: 0 | AU42: 0 | AV42: 0 | AW42: 0 | AX42: 0 | AY42: 0 | AZ42: 0 | BA42: 0 | BB42: 0 | BC42: 0 | BD42: 0 | BE42: 0 | BF42: 0 | BG42: 0 | BH42: 0 | BI42: 0 | BJ42: 0 | BK42: 0 | BL42: 0 | BM42: 0 | BN42: 0 | BO42: 0 | BP42: 0 | BQ42: 0 | BR42: 0 | BS42: 0 | BT42: 0 | BU42: 0 | BV42: 0 | BW42: 0 | BX42: 0 | BY42: 0 | BZ42: 0 | CA42: 0 | CB42: 0 | CC42: 0 | CD42: 0 | CE42: 0 | CF42: 0 | CG42: 0 | CH42: 0 | CI42: -9342 | CJ42: -9342 | CK42: 0 | CL42: 0 | CM42: 0 | CN42: 0 | CO42: 0 | CP42: 0 | CQ42: 0 | CR42: 0 | CS42: 0 | CT42: 0 | CU42: 0 | CV42: 0 | CW42: 0 | CX42: 0 | CY42: 0 | CZ42: 0 | DA42: 0 | DB42: 0 | DC42: 0 | DD42: 0 | DE42: 0 | DF42: 0 | DG42: 0 | DH42: 0 | DI42: 0 | DJ42: 0 | DK42: 0 | DL42: 0 | DM42: 0 | DN42: 0 | DO42: 0 | DP42: 0 | DQ42: 0 | DR42: 0 | DS42: 0 | DT42: 0 | DU42: 0 | DV42: 0 | DW42: 0 | DX42: 0 | DY42: 0 | DZ42: 0 | EA42: 0 | EB42: 0 | EC42: 0 | ED42: 0 | EE42: -34330
A43: 5. Made In (sublessee to Geek Powered Studios) | B43: 5 | C43: 0 | D43: 0 | E43: 0 | F43: 0 | G43: 0 | H43: 0 | I43: 0 | J43: -14638 | K43: -14638 | L43: -14638 | M43: -14638 | N43: -14638 | O43: -15077 | P43: 0 | Q43: 0 | R43: 0 | S43: 0 | T43: 0 | U43: 0 | V43: 0 | W43: 0 | X43: 0 | Y43: 0 | Z43: 0 | AA43: 0 | AB43: 0 | AC43: 0 | AD43: 0 | AE43: 0 | AF43: 0 | AG43: 0 | AH43: 0 | AI43: 0 | AJ43: 0 | AK43: 0 | AL43: 0 | AM43: 0 | AN43: 0 | AO43: 0 | AP43: 0 | AQ43: 0 | AR43: 0 | AS43: 0 | AT43: 0 | AU43: 0 | AV43: 0 | AW43: 0 | AX43: 0 | AY43: 0 | AZ43: 0 | BA43: 0 | BB43: 0 | BC43: 0 | BD43: 0 | BE43: 0 | BF43: 0 | BG43: 0 | BH43: 0 | BI43: 0 | BJ43: 0 | BK43: 0 | BL43: 0 | BM43: 0 | BN43: 0 | BO43: 0 | BP43: 0 | BQ43: 0 | BR43: 0 | BS43: 0 | BT43: 0 | BU43: 0 | BV43: 0 | BW43: 0 | BX43: 0 | BY43: 0 | BZ43: 0 | CA43: -17478 | CB43: -17478 | CC43: 0 | CD43: 0 | CE43: 0 | CF43: 0 | CG43: 0 | CH43: 0 | CI43: 0 | CJ43: 0 | CK43: 0 | CL43: 0 | CM43: 0 | CN43: 0 | CO43: 0 | CP43: 0 | CQ43: 0 | CR43: 0 | CS43: 0 | CT43: 0 | CU43: 0 | CV43: 0 | CW43: 0 | CX43: 0 | CY43: 0 | CZ43: 0 | DA43: 0 | DB43: 0 | DC43: 0 | DD43: 0 | DE43: 0 | DF43: 0 | DG43: 0 | DH43: 0 | DI43: 0 | DJ43: 0 | DK43: 0 | DL43: 0 | DM43: 0 | DN43: 0 | DO43: 0 | DP43: 0 | DQ43: 0 | DR43: 0 | DS43: 0 | DT43: 0 | DU43: 0 | DV43: 0 | DW43: 0 | DX43: 0 | DY43: 0 | DZ43: 0 | EA43: 0 | EB43: 0 | EC43: 0 | ED43: 0 | EE43: -123222
A44: 6. Elmo 35, LLC | B44: 6 | C44: 0 | D44: 0 | E44: 0 | F44: 0 | G44: 0 | H44: 0 | I44: 0 | J44: 0 | K44: 0 | L44: 0 | M44: 0 | N44: 0 | O44: 0 | P44: 0 | Q44: 0 | R44: 0 | S44: 0 | T44: 0 | U44: 0 | V44: 0 | W44: 0 | X44: 0 | Y44: 0 | Z44: 0 | AA44: 0 | AB44: 0 | AC44: 0 | AD44: 0 | AE44: 0 | AF44: 0 | AG44: 0 | AH44: 0 | AI44: 0 | AJ44: 0 | AK44: 0 | AL44: 0 | AM44: 0 | AN44: 0 | AO44: 0 | AP44: 0 | AQ44: 0 | AR44: 0 | AS44: 0 | AT44: 0 | AU44: 0 | AV44: 0 | AW44: 0 | AX44: 0 | AY44: 0 | AZ44: 0 | BA44: 0 | BB44: 0 | BC44: 0 | BD44: 0 | BE44: 0 | BF44: 0 | BG44: 0 | BH44: 0 | BI44: 0 | BJ44: 0 | BK44: 0 | BL44: 0 | BM44: 0 | BN44: 0 | BO44: 0 | BP44: 0 | BQ44: 0 | BR44: 0 | BS44: 0 | BT44: 0 | BU44: 0 | BV44: 0 | BW44: 0 | BX44: 0 | BY44: 0 | BZ44: 0 | CA44: 0 | CB44: 0 | CC44: 0 | CD44: 0 | CE44: 0 | CF44: 0 | CG44: 0 | CH44: 0 | CI44: -19524 | CJ44: -19524 | CK44: 0 | CL44: 0 | CM44: 0 | CN44: 0 | CO44: 0 | CP44: 0 | CQ44: 0 | CR44: 0 | CS44: 0 | CT44: 0 | CU44: 0 | CV44: 0 | CW44: 0 | CX44: 0 | CY44: 0 | CZ44: 0 | DA44: 0 | DB44: 0 | DC44: 0 | DD44: 0 | DE44: 0 | DF44: 0 | DG44: 0 | DH44: 0 | DI44: 0 | DJ44: 0 | DK44: 0 | DL44: 0 | DM44: 0 | DN44: 0 | DO44: 0 | DP44: 0 | DQ44: 0 | DR44: 0 | DS44: 0 | DT44: 0 | DU44: 0 | DV44: 0 | DW44: 0 | DX44: 0 | DY44: 0 | DZ44: 0 | EA44: 0 | EB44: 0 | EC44: 0 | ED44: 0 | EE44: -39049
A45: 7. Trihydro Corporation | B45: 7 | C45: 0 | D45: 0 | E45: 0 | F45: 0 | G45: 0 | H45: 0 | I45: 0 | J45: 0 | K45: 0 | L45: 0 | M45: 0 | N45: 0 | O45: 0 | P45: 0 | Q45: 0 | R45: 0 | S45: 0 | T45: 0 | U45: -7515 | V45: -7515 | W45: -7515 | X45: -7515 | Y45: -7515 | Z45: -7515 | AA45: 0 | AB45: 0 | AC45: 0 | AD45: 0 | AE45: 0 | AF45: 0 | AG45: 0 | AH45: 0 | AI45: 0 | AJ45: 0 | AK45: 0 | AL45: 0 | AM45: 0 | AN45: 0 | AO45: 0 | AP45: 0 | AQ45: 0 | AR45: 0 | AS45: 0 | AT45: 0 | AU45: 0 | AV45: 0 | AW45: 0 | AX45: 0 | AY45: 0 | AZ45: 0 | BA45: 0 | BB45: 0 | BC45: 0 | BD45: 0 | BE45: 0 | BF45: 0 | BG45: 0 | BH45: 0 | BI45: 0 | BJ45: 0 | BK45: 0 | BL45: 0 | BM45: 0 | BN45: 0 | BO45: 0 | BP45: 0 | BQ45: 0 | BR45: 0 | BS45: 0 | BT45: 0 | BU45: 0 | BV45: 0 | BW45: 0 | BX45: 0 | BY45: 0 | BZ45: 0 | CA45: 0 | CB45: 0 | CC45: 0 | CD45: 0 | CE45: 0 | CF45: 0 | CG45: 0 | CH45: 0 | CI45: 0 | CJ45: 0 | CK45: 0 | CL45: -8973 | CM45: -8973 | CN45: 0 | CO45: 0 | CP45: 0 | CQ45: 0 | CR45: 0 | CS45: 0 | CT45: 0 | CU45: 0 | CV45: 0 | CW45: 0 | CX45: 0 | CY45: 0 | CZ45: 0 | DA45: 0 | DB45: 0 | DC45: 0 | DD45: 0 | DE45: 0 | DF45: 0 | DG45: 0 | DH45: 0 | DI45: 0 | DJ45: 0 | DK45: 0 | DL45: 0 | DM45: 0 | DN45: 0 | DO45: 0 | DP45: 0 | DQ45: 0 | DR45: 0 | DS45: 0 | DT45: 0 | DU45: 0 | DV45: 0 | DW45: 0 | DX45: 0 | DY45: 0 | DZ45: 0 | EA45: 0 | EB45: 0 | EC45: 0 | ED45: 0 | EE45: -63035
A46: 8. Urban ATX | B46: 07A | C46: 0 | D46: 0 | E46: 0 | F46: 0 | G46: 0 | H46: 0 | I46: 0 | J46: 0 | K46: 0 | L46: 0 | M46: 0 | N46: 0 | O46: 0 | P46: 0 | Q46: 0 | R46: 0 | S46: 0 | T46: 0 | U46: 0 | V46: 0 | W46: 0 | X46: 0 | Y46: 0 | Z46: 0 | AA46: 0 | AB46: 0 | AC46: 0 | AD46: 0 | AE46: 0 | AF46: 0 | AG46: 0 | AH46: 0 | AI46: 0 | AJ46: 0 | AK46: 0 | AL46: 0 | AM46: 0 | AN46: 0 | AO46: 0 | AP46: 0 | AQ46: 0 | AR46: 0 | AS46: 0 | AT46: 0 | AU46: 0 | AV46: 0 | AW46: 0 | AX46: 0 | AY46: 0 | AZ46: 0 | BA46: 0 | BB46: 0 | BC46: 0 | BD46: 0 | BE46: 0 | BF46: 0 | BG46: 0 | BH46: -4118 | BI46: -4118 | BJ46: 0 | BK46: 0 | BL46: 0 | BM46: 0 | BN46: 0 | BO46: 0 | BP46: 0 | BQ46: 0 | BR46: 0 | BS46: 0 | BT46: 0 | BU46: 0 | BV46: 0 | BW46: 0 | BX46: 0 | BY46: 0 | BZ46: 0 | CA46: 0 | CB46: 0 | CC46: 0 | CD46: 0 | CE46: 0 | CF46: 0 | CG46: 0 | CH46: 0 | CI46: 0 | CJ46: 0 | CK46: 0 | CL46: 0 | CM46: 0 | CN46: 0 | CO46: 0 | CP46: 0 | CQ46: 0 | CR46: 0 | CS46: 0 | CT46: 0 | CU46: 0 | CV46: 0 | CW46: 0 | CX46: 0 | CY46: 0 | CZ46: 0 | DA46: 0 | DB46: 0 | DC46: 0 | DD46: 0 | DE46: 0 | DF46: 0 | DG46: 0 | DH46: 0 | DI46: 0 | DJ46: 0 | DK46: 0 | DL46: 0 | DM46: 0 | DN46: 0 | DO46: 0 | DP46: 0 | DQ46: 0 | DR46: 0 | DS46: 0 | DT46: 0 | DU46: -4917 | DV46: -4917 | DW46: 0 | DX46: 0 | DY46: 0 | DZ46: 0 | EA46: 0 | EB46: 0 | EC46: 0 | ED46: 0 | EE46: -18070
A47: 10. Austin Prosthetics Center | B47: 9 | C47: 0 | D47: 0 | E47: 0 | F47: 0 | G47: 0 | H47: 0 | I47: 0 | J47: 0 | K47: 0 | L47: 0 | M47: 0 | N47: 0 | O47: 0 | P47: 0 | Q47: 0 | R47: 0 | S47: 0 | T47: 0 | U47: 0 | V47: 0 | W47: 0 | X47: 0 | Y47: 0 | Z47: 0 | AA47: 0 | AB47: 0 | AC47: 0 | AD47: 0 | AE47: 0 | AF47: 0 | AG47: 0 | AH47: 0 | AI47: 0 | AJ47: 0 | AK47: 0 | AL47: 0 | AM47: 0 | AN47: 0 | AO47: 0 | AP47: 0 | AQ47: 0 | AR47: 0 | AS47: 0 | AT47: 0 | AU47: 0 | AV47: 0 | AW47: 0 | AX47: 0 | AY47: 0 | AZ47: 0 | BA47: 0 | BB47: 0 | BC47: 0 | BD47: 0 | BE47: 0 | BF47: 0 | BG47: 0 | BH47: 0 | BI47: 0 | BJ47: 0 | BK47: 0 | BL47: 0 | BM47: 0 | BN47: 0 | BO47: 0 | BP47: 0 | BQ47: 0 | BR47: 0 | BS47: -11781 | BT47: -11781 | BU47: 0 | BV47: 0 | BW47: 0 | BX47: 0 | BY47: 0 | BZ47: 0 | CA47: 0 | CB47: 0 | CC47: 0 | CD47: 0 | CE47: 0 | CF47: 0 | CG47: 0 | CH47: 0 | CI47: 0 | CJ47: 0 | CK47: 0 | CL47: 0 | CM47: 0 | CN47: 0 | CO47: 0 | CP47: 0 | CQ47: 0 | CR47: 0 | CS47: 0 | CT47: 0 | CU47: 0 | CV47: 0 | CW47: 0 | CX47: 0 | CY47: 0 | CZ47: 0 | DA47: 0 | DB47: 0 | DC47: 0 | DD47: 0 | DE47: 0 | DF47: 0 | DG47: 0 | DH47: 0 | DI47: 0 | DJ47: 0 | DK47: 0 | DL47: 0 | DM47: 0 | DN47: 0 | DO47: 0 | DP47: 0 | DQ47: 0 | DR47: 0 | DS47: 0 | DT47: 0 | DU47: 0 | DV47: 0 | DW47: 0 | DX47: 0 | DY47: 0 | DZ47: 0 | EA47: 0 | EB47: 0 | EC47: 0 | ED47: 0 | EE47: -23561
A48: 11. Ignite Fitnez | B48: 10 | C48: 0 | D48: 0 | E48: 0 | F48: -28553 | G48: -28553 | H48: -28553 | I48: -28553 | J48: -28553 | K48: -28553 | L48: -28553 | M48: -28553 | N48: -28553 | O48: -29410 | P48: -29410 | Q48: -29410 | R48: 0 | S48: 0 | T48: 0 | U48: 0 | V48: 0 | W48: 0 | X48: 0 | Y48: 0 | Z48: 0 | AA48: 0 | AB48: 0 | AC48: 0 | AD48: 0 | AE48: 0 | AF48: 0 | AG48: 0 | AH48: 0 | AI48: 0 | AJ48: 0 | AK48: 0 | AL48: 0 | AM48: 0 | AN48: 0 | AO48: 0 | AP48: 0 | AQ48: 0 | AR48: 0 | AS48: 0 | AT48: 0 | AU48: 0 | AV48: 0 | AW48: 0 | AX48: 0 | AY48: 0 | AZ48: 0 | BA48: 0 | BB48: 0 | BC48: 0 | BD48: 0 | BE48: 0 | BF48: 0 | BG48: 0 | BH48: 0 | BI48: 0 | BJ48: 0 | BK48: 0 | BL48: 0 | BM48: 0 | BN48: 0 | BO48: 0 | BP48: 0 | BQ48: 0 | BR48: 0 | BS48: 0 | BT48: 0 | BU48: 0 | BV48: 0 | BW48: 0 | BX48: 0 | BY48: 0 | BZ48: 0 | CA48: 0 | CB48: 0 | CC48: 0 | CD48: 0 | CE48: 0 | CF48: 0 | CG48: 0 | CH48: 0 | CI48: 0 | CJ48: 0 | CK48: 0 | CL48: 0 | CM48: 0 | CN48: 0 | CO48: 0 | CP48: 0 | CQ48: 0 | CR48: 0 | CS48: 0 | CT48: 0 | CU48: 0 | CV48: 0 | CW48: 0 | CX48: 0 | CY48: 0 | CZ48: 0 | DA48: 0 | DB48: 0 | DC48: -36170 | DD48: -36170 | DE48: -36170 | DF48: -36170 | DG48: 0 | DH48: 0 | DI48: 0 | DJ48: 0 | DK48: 0 | DL48: 0 | DM48: 0 | DN48: 0 | DO48: 0 | DP48: 0 | DQ48: 0 | DR48: 0 | DS48: 0 | DT48: 0 | DU48: 0 | DV48: 0 | DW48: 0 | DX48: 0 | DY48: 0 | DZ48: 0 | EA48: 0 | EB48: 0 | EC48: 0 | ED48: 0 | EE48: -489885
A49: Total Lost Absorption / Turnover Rent | C49: -21644 | D49: -21644 | E49: -21644 | F49: -50197 | G49: -50197 | H49: -50197 | I49: -50197 | J49: -43191 | K49: -43191 | L49: -43191 | M49: -43191 | N49: -43191 | O49: -44486 | P49: -29410 | Q49: -29410 | R49: 0 | S49: 0 | T49: 0 | U49: -7515 | V49: -15338 | W49: -15338 | X49: -7515 | Y49: -7515 | Z49: -7515 | AA49: 0 | AB49: 0 | AC49: 0 | AD49: -15406 | AE49: -15406 | AF49: 0 | AG49: 0 | AH49: 0 | AI49: 0 | AJ49: 0 | AK49: 0 | AL49: 0 | AM49: 0 | AN49: 0 | AO49: 0 | AP49: 0 | AQ49: 0 | AR49: 0 | AS49: 0 | AT49: 0 | AU49: 0 | AV49: 0 | AW49: 0 | AX49: 0 | AY49: 0 | AZ49: 0 | BA49: 0 | BB49: 0 | BC49: 0 | BD49: 0 | BE49: 0 | BF49: 0 | BG49: 0 | BH49: -4118 | BI49: -4118 | BJ49: 0 | BK49: -22651 | BL49: -22651 | BM49: 0 | BN49: 0 | BO49: 0 | BP49: 0 | BQ49: 0 | BR49: 0 | BS49: -11781 | BT49: -11781 | BU49: -25091 | BV49: -25091 | BW49: 0 | BX49: 0 | BY49: 0 | BZ49: 0 | CA49: -17478 | CB49: -17478 | CC49: 0 | CD49: 0 | CE49: 0 | CF49: 0 | CG49: 0 | CH49: 0 | CI49: -28866 | CJ49: -28866 | CK49: 0 | CL49: -8973 | CM49: -8973 | CN49: 0 | CO49: 0 | CP49: 0 | CQ49: -17860 | CR49: -17860 | CS49: 0 | CT49: 0 | CU49: 0 | CV49: 0 | CW49: 0 | CX49: 0 | CY49: 0 | CZ49: 0 | DA49: 0 | DB49: 0 | DC49: -36170 | DD49: -36170 | DE49: -36170 | DF49: -36170 | DG49: 0 | DH49: 0 | DI49: 0 | DJ49: 0 | DK49: 0 | DL49: 0 | DM49: 0 | DN49: 0 | DO49: 0 | DP49: 0 | DQ49: 0 | DR49: 0 | DS49: 0 | DT49: 0 | DU49: -4917 | DV49: -4917 | DW49: 0 | DX49: -26258 | DY49: -26258 | DZ49: 0 | EA49: 0 | EB49: 0 | EC49: 0 | ED49: 0 | EE49: -1157190
A51: Free Rent
A52: 1. Kitu Life, Inc. | B52: 1 | C52: 0 | D52: 0 | E52: 0 | F52: 0 | G52: 0 | H52: 0 | I52: 0 | J52: 0 | K52: 0 | L52: 0 | M52: 0 | N52: 0 | O52: 0 | P52: 0 | Q52: 0 | R52: 0 | S52: 0 | T52: 0 | U52: 0 | V52: 0 | W52: 0 | X52: 0 | Y52: 0 | Z52: 0 | AA52: 0 | AB52: 0 | AC52: 0 | AD52: 0 | AE52: 0 | AF52: 0 | AG52: 0 | AH52: 0 | AI52: 0 | AJ52: 0 | AK52: 0 | AL52: 0 | AM52: 0 | AN52: 0 | AO52: 0 | AP52: 0 | AQ52: 0 | AR52: 0 | AS52: 0 | AT52: 0 | AU52: 0 | AV52: 0 | AW52: 0 | AX52: 0 | AY52: 0 | AZ52: 0 | BA52: 0 | BB52: 0 | BC52: 0 | BD52: 0 | BE52: 0 | BF52: 0 | BG52: 0 | BH52: 0 | BI52: 0 | BJ52: 0 | BK52: 0 | BL52: 0 | BM52: -20386 | BN52: 0 | BO52: 0 | BP52: 0 | BQ52: 0 | BR52: 0 | BS52: 0 | BT52: 0 | BU52: 0 | BV52: 0 | BW52: 0 | BX52: 0 | BY52: 0 | BZ52: 0 | CA52: 0 | CB52: 0 | CC52: 0 | CD52: 0 | CE52: 0 | CF52: 0 | CG52: 0 | CH52: 0 | CI52: 0 | CJ52: 0 | CK52: 0 | CL52: 0 | CM52: 0 | CN52: 0 | CO52: 0 | CP52: 0 | CQ52: 0 | CR52: 0 | CS52: 0 | CT52: 0 | CU52: 0 | CV52: 0 | CW52: 0 | CX52: 0 | CY52: 0 | CZ52: 0 | DA52: 0 | DB52: 0 | DC52: 0 | DD52: 0 | DE52: 0 | DF52: 0 | DG52: 0 | DH52: 0 | DI52: 0 | DJ52: 0 | DK52: 0 | DL52: 0 | DM52: 0 | DN52: 0 | DO52: 0 | DP52: 0 | DQ52: 0 | DR52: 0 | DS52: 0 | DT52: 0 | DU52: 0 | DV52: 0 | DW52: 0 | DX52: 0 | DY52: 0 | DZ52: -23633 | EA52: 0 | EB52: 0 | EC52: 0 | ED52: 0 | EE52: -44018
A53: 2. VACANT | B53: 2 | C53: 0 | D53: 0 | E53: 0 | F53: 0 | G53: 0 | H53: 0 | I53: 0 | J53: -21644 | K53: -21644 | L53: -21644 | M53: 0 | N53: 0 | O53: 0 | P53: 0 | Q53: 0 | R53: 0 | S53: 0 | T53: 0 | U53: 0 | V53: 0 | W53: 0 | X53: 0 | Y53: 0 | Z53: 0 | AA53: 0 | AB53: 0 | AC53: 0 | AD53: 0 | AE53: 0 | AF53: 0 | AG53: 0 | AH53: 0 | AI53: 0 | AJ53: 0 | AK53: 0 | AL53: 0 | AM53: 0 | AN53: 0 | AO53: 0 | AP53: 0 | AQ53: 0 | AR53: 0 | AS53: 0 | AT53: 0 | AU53: 0 | AV53: 0 | AW53: 0 | AX53: 0 | AY53: 0 | AZ53: 0 | BA53: 0 | BB53: 0 | BC53: 0 | BD53: 0 | BE53: 0 | BF53: 0 | BG53: 0 | BH53: 0 | BI53: 0 | BJ53: 0 | BK53: 0 | BL53: 0 | BM53: 0 | BN53: 0 | BO53: 0 | BP53: 0 | BQ53: 0 | BR53: 0 | BS53: 0 | BT53: 0 | BU53: 0 | BV53: 0 | BW53: -23259 | BX53: 0 | BY53: 0 | BZ53: 0 | CA53: 0 | CB53: 0 | CC53: 0 | CD53: 0 | CE53: 0 | CF53: 0 | CG53: 0 | CH53: 0 | CI53: 0 | CJ53: 0 | CK53: 0 | CL53: 0 | CM53: 0 | CN53: 0 | CO53: 0 | CP53: 0 | CQ53: 0 | CR53: 0 | CS53: 0 | CT53: 0 | CU53: 0 | CV53: 0 | CW53: 0 | CX53: 0 | CY53: 0 | CZ53: 0 | DA53: 0 | DB53: 0 | DC53: 0 | DD53: 0 | DE53: 0 | DF53: 0 | DG53: 0 | DH53: 0 | DI53: 0 | DJ53: 0 | DK53: 0 | DL53: 0 | DM53: 0 | DN53: 0 | DO53: 0 | DP53: 0 | DQ53: 0 | DR53: 0 | DS53: 0 | DT53: 0 | DU53: 0 | DV53: 0 | DW53: 0 | DX53: 0 | DY53: 0 | DZ53: 0 | EA53: 0 | EB53: 0 | EC53: 0 | ED53: 0 | EE53: -88190
A54: 3. Saatva | B54: 3 | C54: 0 | D54: 0 | E54: 0 | F54: 0 | G54: 0 | H54: 0 | I54: 0 | J54: 0 | K54: 0 | L54: 0 | M54: 0 | N54: 0 | O54: 0 | P54: 0 | Q54: 0 | R54: 0 | S54: 0 | T54: 0 | U54: 0 | V54: 0 | W54: 0 | X54: 0 | Y54: 0 | Z54: 0 | AA54: 0 | AB54: 0 | AC54: 0 | AD54: 0 | AE54: 0 | AF54: -13866 | AG54: 0 | AH54: 0 | AI54: 0 | AJ54: 0 | AK54: 0 | AL54: 0 | AM54: 0 | AN54: 0 | AO54: 0 | AP54: 0 | AQ54: 0 | AR54: 0 | AS54: 0 | AT54: 0 | AU54: 0 | AV54: 0 | AW54: 0 | AX54: 0 | AY54: 0 | AZ54: 0 | BA54: 0 | BB54: 0 | BC54: 0 | BD54: 0 | BE54: 0 | BF54: 0 | BG54: 0 | BH54: 0 | BI54: 0 | BJ54: 0 | BK54: 0 | BL54: 0 | BM54: 0 | BN54: 0 | BO54: 0 | BP54: 0 | BQ54: 0 | BR54: 0 | BS54: 0 | BT54: 0 | BU54: 0 | BV54: 0 | BW54: 0 | BX54: 0 | BY54: 0 | BZ54: 0 | CA54: 0 | CB54: 0 | CC54: 0 | CD54: 0 | CE54: 0 | CF54: 0 | CG54: 0 | CH54: 0 | CI54: 0 | CJ54: 0 | CK54: 0 | CL54: 0 | CM54: 0 | CN54: 0 | CO54: 0 | CP54: 0 | CQ54: 0 | CR54: 0 | CS54: -16074 | CT54: 0 | CU54: 0 | CV54: 0 | CW54: 0 | CX54: 0 | CY54: 0 | CZ54: 0 | DA54: 0 | DB54: 0 | DC54: 0 | DD54: 0 | DE54: 0 | DF54: 0 | DG54: 0 | DH54: 0 | DI54: 0 | DJ54: 0 | DK54: 0 | DL54: 0 | DM54: 0 | DN54: 0 | DO54: 0 | DP54: 0 | DQ54: 0 | DR54: 0 | DS54: 0 | DT54: 0 | DU54: 0 | DV54: 0 | DW54: 0 | DX54: 0 | DY54: 0 | DZ54: 0 | EA54: 0 | EB54: 0 | EC54: 0 | ED54: 0 | EE54: -29939
A55: 4. Fuse Architecture Studio | B55: 4 | C55: 0 | D55: 0 | E55: 0 | F55: 0 | G55: 0 | H55: 0 | I55: 0 | J55: 0 | K55: 0 | L55: 0 | M55: 0 | N55: 0 | O55: 0 | P55: 0 | Q55: 0 | R55: 0 | S55: 0 | T55: 0 | U55: 0 | V55: 0 | W55: 0 | X55: -7041 | Y55: 0 | Z55: 0 | AA55: 0 | AB55: 0 | AC55: 0 | AD55: 0 | AE55: 0 | AF55: 0 | AG55: 0 | AH55: 0 | AI55: 0 | AJ55: 0 | AK55: 0 | AL55: 0 | AM55: 0 | AN55: 0 | AO55: 0 | AP55: 0 | AQ55: 0 | AR55: 0 | AS55: 0 | AT55: 0 | AU55: 0 | AV55: 0 | AW55: 0 | AX55: 0 | AY55: 0 | AZ55: 0 | BA55: 0 | BB55: 0 | BC55: 0 | BD55: 0 | BE55: 0 | BF55: 0 | BG55: 0 | BH55: 0 | BI55: 0 | BJ55: 0 | BK55: 0 | BL55: 0 | BM55: 0 | BN55: 0 | BO55: 0 | BP55: 0 | BQ55: 0 | BR55: 0 | BS55: 0 | BT55: 0 | BU55: 0 | BV55: 0 | BW55: 0 | BX55: 0 | BY55: 0 | BZ55: 0 | CA55: 0 | CB55: 0 | CC55: 0 | CD55: 0 | CE55: 0 | CF55: 0 | CG55: 0 | CH55: 0 | CI55: 0 | CJ55: 0 | CK55: -8407 | CL55: 0 | CM55: 0 | CN55: 0 | CO55: 0 | CP55: 0 | CQ55: 0 | CR55: 0 | CS55: 0 | CT55: 0 | CU55: 0 | CV55: 0 | CW55: 0 | CX55: 0 | CY55: 0 | CZ55: 0 | DA55: 0 | DB55: 0 | DC55: 0 | DD55: 0 | DE55: 0 | DF55: 0 | DG55: 0 | DH55: 0 | DI55: 0 | DJ55: 0 | DK55: 0 | DL55: 0 | DM55: 0 | DN55: 0 | DO55: 0 | DP55: 0 | DQ55: 0 | DR55: 0 | DS55: 0 | DT55: 0 | DU55: 0 | DV55: 0 | DW55: 0 | DX55: 0 | DY55: 0 | DZ55: 0 | EA55: 0 | EB55: 0 | EC55: 0 | ED55: 0 | EE55: -15449
A56: 5. Made In (sublessee to Geek Powered Studios) | B56: 5 | C56: 0 | D56: 0 | E56: 0 | F56: 0 | G56: 0 | H56: 0 | I56: 0 | J56: 0 | K56: 0 | L56: 0 | M56: 0 | N56: 0 | O56: 0 | P56: -15077 | Q56: -15077 | R56: -15077 | S56: 0 | T56: 0 | U56: 0 | V56: 0 | W56: 0 | X56: 0 | Y56: 0 | Z56: 0 | AA56: 0 | AB56: 0 | AC56: 0 | AD56: 0 | AE56: 0 | AF56: 0 | AG56: 0 | AH56: 0 | AI56: 0 | AJ56: 0 | AK56: 0 | AL56: 0 | AM56: 0 | AN56: 0 | AO56: 0 | AP56: 0 | AQ56: 0 | AR56: 0 | AS56: 0 | AT56: 0 | AU56: 0 | AV56: 0 | AW56: 0 | AX56: 0 | AY56: 0 | AZ56: 0 | BA56: 0 | BB56: 0 | BC56: 0 | BD56: 0 | BE56: 0 | BF56: 0 | BG56: 0 | BH56: 0 | BI56: 0 | BJ56: 0 | BK56: 0 | BL56: 0 | BM56: 0 | BN56: 0 | BO56: 0 | BP56: 0 | BQ56: 0 | BR56: 0 | BS56: 0 | BT56: 0 | BU56: 0 | BV56: 0 | BW56: 0 | BX56: 0 | BY56: 0 | BZ56: 0 | CA56: 0 | CB56: 0 | CC56: -15730 | CD56: 0 | CE56: 0 | CF56: 0 | CG56: 0 | CH56: 0 | CI56: 0 | CJ56: 0 | CK56: 0 | CL56: 0 | CM56: 0 | CN56: 0 | CO56: 0 | CP56: 0 | CQ56: 0 | CR56: 0 | CS56: 0 | CT56: 0 | CU56: 0 | CV56: 0 | CW56: 0 | CX56: 0 | CY56: 0 | CZ56: 0 | DA56: 0 | DB56: 0 | DC56: 0 | DD56: 0 | DE56: 0 | DF56: 0 | DG56: 0 | DH56: 0 | DI56: 0 | DJ56: 0 | DK56: 0 | DL56: 0 | DM56: 0 | DN56: 0 | DO56: 0 | DP56: 0 | DQ56: 0 | DR56: 0 | DS56: 0 | DT56: 0 | DU56: 0 | DV56: 0 | DW56: 0 | DX56: 0 | DY56: 0 | DZ56: 0 | EA56: 0 | EB56: 0 | EC56: 0 | ED56: 0 | EE56: -60961
A57: 6. Elmo 35, LLC | B57: 6 | C57: 0 | D57: 0 | E57: 0 | F57: 0 | G57: 0 | H57: 0 | I57: 0 | J57: 0 | K57: 0 | L57: 0 | M57: 0 | N57: 0 | O57: 0 | P57: 0 | Q57: 0 | R57: 0 | S57: 0 | T57: 0 | U57: 0 | V57: 0 | W57: 0 | X57: 0 | Y57: 0 | Z57: 0 | AA57: 0 | AB57: 0 | AC57: 0 | AD57: 0 | AE57: 0 | AF57: 0 | AG57: 0 | AH57: 0 | AI57: 0 | AJ57: 0 | AK57: 0 | AL57: 0 | AM57: 0 | AN57: 0 | AO57: 0 | AP57: 0 | AQ57: 0 | AR57: 0 | AS57: 0 | AT57: 0 | AU57: 0 | AV57: 0 | AW57: 0 | AX57: 0 | AY57: 0 | AZ57: 0 | BA57: 0 | BB57: 0 | BC57: 0 | BD57: 0 | BE57: 0 | BF57: 0 | BG57: 0 | BH57: 0 | BI57: 0 | BJ57: 0 | BK57: 0 | BL57: 0 | BM57: 0 | BN57: 0 | BO57: 0 | BP57: 0 | BQ57: 0 | BR57: 0 | BS57: 0 | BT57: 0 | BU57: 0 | BV57: 0 | BW57: 0 | BX57: 0 | BY57: 0 | BZ57: 0 | CA57: 0 | CB57: 0 | CC57: 0 | CD57: 0 | CE57: 0 | CF57: 0 | CG57: 0 | CH57: 0 | CI57: 0 | CJ57: 0 | CK57: -17572 | CL57: 0 | CM57: 0 | CN57: 0 | CO57: 0 | CP57: 0 | CQ57: 0 | CR57: 0 | CS57: 0 | CT57: 0 | CU57: 0 | CV57: 0 | CW57: 0 | CX57: 0 | CY57: 0 | CZ57: 0 | DA57: 0 | DB57: 0 | DC57: 0 | DD57: 0 | DE57: 0 | DF57: 0 | DG57: 0 | DH57: 0 | DI57: 0 | DJ57: 0 | DK57: 0 | DL57: 0 | DM57: 0 | DN57: 0 | DO57: 0 | DP57: 0 | DQ57: 0 | DR57: 0 | DS57: 0 | DT57: 0 | DU57: 0 | DV57: 0 | DW57: 0 | DX57: 0 | DY57: 0 | DZ57: 0 | EA57: 0 | EB57: 0 | EC57: 0 | ED57: 0 | EE57: -17572
A58: 7. Trihydro Corporation | B58: 7 | C58: 0 | D58: 0 | E58: 0 | F58: 0 | G58: 0 | H58: 0 | I58: 0 | J58: 0 | K58: 0 | L58: 0 | M58: 0 | N58: 0 | O58: 0 | P58: 0 | Q58: 0 | R58: 0 | S58: 0 | T58: 0 | U58: 0 | V58: 0 | W58: 0 | X58: 0 | Y58: 0 | Z58: 0 | AA58: -7740 | AB58: -7740 | AC58: -7740 | AD58: 0 | AE58: 0 | AF58: 0 | AG58: 0 | AH58: 0 | AI58: 0 | AJ58: 0 | AK58: 0 | AL58: 0 | AM58: 0 | AN58: 0 | AO58: 0 | AP58: 0 | AQ58: 0 | AR58: 0 | AS58: 0 | AT58: 0 | AU58: 0 | AV58: 0 | AW58: 0 | AX58: 0 | AY58: 0 | AZ58: 0 | BA58: 0 | BB58: 0 | BC58: 0 | BD58: 0 | BE58: 0 | BF58: 0 | BG58: 0 | BH58: 0 | BI58: 0 | BJ58: 0 | BK58: 0 | BL58: 0 | BM58: 0 | BN58: 0 | BO58: 0 | BP58: 0 | BQ58: 0 | BR58: 0 | BS58: 0 | BT58: 0 | BU58: 0 | BV58: 0 | BW58: 0 | BX58: 0 | BY58: 0 | BZ58: 0 | CA58: 0 | CB58: 0 | CC58: 0 | CD58: 0 | CE58: 0 | CF58: 0 | CG58: 0 | CH58: 0 | CI58: 0 | CJ58: 0 | CK58: 0 | CL58: 0 | CM58: 0 | CN58: -8076 | CO58: 0 | CP58: 0 | CQ58: 0 | CR58: 0 | CS58: 0 | CT58: 0 | CU58: 0 | CV58: 0 | CW58: 0 | CX58: 0 | CY58: 0 | CZ58: 0 | DA58: 0 | DB58: 0 | DC58: 0 | DD58: 0 | DE58: 0 | DF58: 0 | DG58: 0 | DH58: 0 | DI58: 0 | DJ58: 0 | DK58: 0 | DL58: 0 | DM58: 0 | DN58: 0 | DO58: 0 | DP58: 0 | DQ58: 0 | DR58: 0 | DS58: 0 | DT58: 0 | DU58: 0 | DV58: 0 | DW58: 0 | DX58: 0 | DY58: 0 | DZ58: 0 | EA58: 0 | EB58: 0 | EC58: 0 | ED58: 0 | EE58: -31296
A59: 8. Urban ATX | B59: 07A | C59: 0 | D59: 0 | E59: 0 | F59: 0 | G59: 0 | H59: 0 | I59: 0 | J59: 0 | K59: 0 | L59: 0 | M59: 0 | N59: 0 | O59: 0 | P59: 0 | Q59: 0 | R59: 0 | S59: 0 | T59: 0 | U59: 0 | V59: 0 | W59: 0 | X59: 0 | Y59: 0 | Z59: 0 | AA59: 0 | AB59: 0 | AC59: 0 | AD59: 0 | AE59: 0 | AF59: 0 | AG59: 0 | AH59: 0 | AI59: 0 | AJ59: 0 | AK59: 0 | AL59: 0 | AM59: 0 | AN59: 0 | AO59: 0 | AP59: 0 | AQ59: 0 | AR59: 0 | AS59: 0 | AT59: 0 | AU59: 0 | AV59: 0 | AW59: 0 | AX59: 0 | AY59: 0 | AZ59: 0 | BA59: 0 | BB59: 0 | BC59: 0 | BD59: 0 | BE59: 0 | BF59: 0 | BG59: 0 | BH59: 0 | BI59: 0 | BJ59: -3706 | BK59: 0 | BL59: 0 | BM59: 0 | BN59: 0 | BO59: 0 | BP59: 0 | BQ59: 0 | BR59: 0 | BS59: 0 | BT59: 0 | BU59: 0 | BV59: 0 | BW59: 0 | BX59: 0 | BY59: 0 | BZ59: 0 | CA59: 0 | CB59: 0 | CC59: 0 | CD59: 0 | CE59: 0 | CF59: 0 | CG59: 0 | CH59: 0 | CI59: 0 | CJ59: 0 | CK59: 0 | CL59: 0 | CM59: 0 | CN59: 0 | CO59: 0 | CP59: 0 | CQ59: 0 | CR59: 0 | CS59: 0 | CT59: 0 | CU59: 0 | CV59: 0 | CW59: 0 | CX59: 0 | CY59: 0 | CZ59: 0 | DA59: 0 | DB59: 0 | DC59: 0 | DD59: 0 | DE59: 0 | DF59: 0 | DG59: 0 | DH59: 0 | DI59: 0 | DJ59: 0 | DK59: 0 | DL59: 0 | DM59: 0 | DN59: 0 | DO59: 0 | DP59: 0 | DQ59: 0 | DR59: 0 | DS59: 0 | DT59: 0 | DU59: 0 | DV59: 0 | DW59: -4425 | DX59: 0 | DY59: 0 | DZ59: 0 | EA59: 0 | EB59: 0 | EC59: 0 | ED59: 0 | EE59: -8132
A60: 10. Austin Prosthetics Center | B60: 9 | C60: 0 | D60: 0 | E60: 0 | F60: 0 | G60: 0 | H60: 0 | I60: 0 | J60: 0 | K60: 0 | L60: 0 | M60: 0 | N60: 0 | O60: 0 | P60: 0 | Q60: 0 | R60: 0 | S60: 0 | T60: 0 | U60: 0 | V60: 0 | W60: 0 | X60: 0 | Y60: 0 | Z60: 0 | AA60: 0 | AB60: 0 | AC60: 0 | AD60: 0 | AE60: 0 | AF60: 0 | AG60: 0 | AH60: 0 | AI60: 0 | AJ60: 0 | AK60: 0 | AL60: 0 | AM60: 0 | AN60: 0 | AO60: 0 | AP60: 0 | AQ60: 0 | AR60: 0 | AS60: 0 | AT60: 0 | AU60: 0 | AV60: 0 | AW60: 0 | AX60: 0 | AY60: 0 | AZ60: 0 | BA60: 0 | BB60: 0 | BC60: 0 | BD60: 0 | BE60: 0 | BF60: 0 | BG60: 0 | BH60: 0 | BI60: 0 | BJ60: 0 | BK60: 0 | BL60: 0 | BM60: 0 | BN60: 0 | BO60: 0 | BP60: 0 | BQ60: 0 | BR60: 0 | BS60: 0 | BT60: 0 | BU60: -10603 | BV60: 0 | BW60: 0 | BX60: 0 | BY60: 0 | BZ60: 0 | CA60: 0 | CB60: 0 | CC60: 0 | CD60: 0 | CE60: 0 | CF60: 0 | CG60: 0 | CH60: 0 | CI60: 0 | CJ60: 0 | CK60: 0 | CL60: 0 | CM60: 0 | CN60: 0 | CO60: 0 | CP60: 0 | CQ60: 0 | CR60: 0 | CS60: 0 | CT60: 0 | CU60: 0 | CV60: 0 | CW60: 0 | CX60: 0 | CY60: 0 | CZ60: 0 | DA60: 0 | DB60: 0 | DC60: 0 | DD60: 0 | DE60: 0 | DF60: 0 | DG60: 0 | DH60: 0 | DI60: 0 | DJ60: 0 | DK60: 0 | DL60: 0 | DM60: 0 | DN60: 0 | DO60: 0 | DP60: 0 | DQ60: 0 | DR60: 0 | DS60: 0 | DT60: 0 | DU60: 0 | DV60: 0 | DW60: 0 | DX60: 0 | DY60: 0 | DZ60: 0 | EA60: 0 | EB60: 0 | EC60: 0 | ED60: 0 | EE60: -10603
A61: 11. Ignite Fitnez | B61: 10 | C61: 0 | D61: 0 | E61: 0 | F61: 0 | G61: 0 | H61: 0 | I61: 0 | J61: 0 | K61: 0 | L61: 0 | M61: 0 | N61: 0 | O61: 0 | P61: 0 | Q61: 0 | R61: -29410 | S61: -29410 | T61: -29410 | U61: -29410 | V61: -29410 | W61: 0 | X61: 0 | Y61: 0 | Z61: 0 | AA61: 0 | AB61: 0 | AC61: 0 | AD61: 0 | AE61: 0 | AF61: 0 | AG61: 0 | AH61: 0 | AI61: 0 | AJ61: 0 | AK61: 0 | AL61: 0 | AM61: 0 | AN61: 0 | AO61: 0 | AP61: 0 | AQ61: 0 | AR61: 0 | AS61: 0 | AT61: 0 | AU61: 0 | AV61: 0 | AW61: 0 | AX61: 0 | AY61: 0 | AZ61: 0 | BA61: 0 | BB61: 0 | BC61: 0 | BD61: 0 | BE61: 0 | BF61: 0 | BG61: 0 | BH61: 0 | BI61: 0 | BJ61: 0 | BK61: 0 | BL61: 0 | BM61: 0 | BN61: 0 | BO61: 0 | BP61: 0 | BQ61: 0 | BR61: 0 | BS61: 0 | BT61: 0 | BU61: 0 | BV61: 0 | BW61: 0 | BX61: 0 | BY61: 0 | BZ61: 0 | CA61: 0 | CB61: 0 | CC61: 0 | CD61: 0 | CE61: 0 | CF61: 0 | CG61: 0 | CH61: 0 | CI61: 0 | CJ61: 0 | CK61: 0 | CL61: 0 | CM61: 0 | CN61: 0 | CO61: 0 | CP61: 0 | CQ61: 0 | CR61: 0 | CS61: 0 | CT61: 0 | CU61: 0 | CV61: 0 | CW61: 0 | CX61: 0 | CY61: 0 | CZ61: 0 | DA61: 0 | DB61: 0 | DC61: 0 | DD61: 0 | DE61: 0 | DF61: 0 | DG61: -37255 | DH61: -18628 | DI61: 0 | DJ61: 0 | DK61: 0 | DL61: 0 | DM61: 0 | DN61: 0 | DO61: 0 | DP61: 0 | DQ61: 0 | DR61: 0 | DS61: 0 | DT61: 0 | DU61: 0 | DV61: 0 | DW61: 0 | DX61: 0 | DY61: 0 | DZ61: 0 | EA61: 0 | EB61: 0 | EC61: 0 | ED61: 0 | EE61: -202930
A62: Total Free Rent | C62: 0 | D62: 0 | E62: 0 | F62: 0 | G62: 0 | H62: 0 | I62: 0 | J62: -21644 | K62: -21644 | L62: -21644 | M62: 0 | N62: 0 | O62: 0 | P62: -15077 | Q62: -15077 | R62: -44486 | S62: -29410 | T62: -29410 | U62: -29410 | V62: -29410 | W62: 0 | X62: -7041 | Y62: 0 | Z62: 0 | AA62: -7740 | AB62: -7740 | AC62: -7740 | AD62: 0 | AE62: 0 | AF62: -13866 | AG62: 0 | AH62: 0 | AI62: 0 | AJ62: 0 | AK62: 0 | AL62: 0 | AM62: 0 | AN62: 0 | AO62: 0 | AP62: 0 | AQ62: 0 | AR62: 0 | AS62: 0 | AT62: 0 | AU62: 0 | AV62: 0 | AW62: 0 | AX62: 0 | AY62: 0 | AZ62: 0 | BA62: 0 | BB62: 0 | BC62: 0 | BD62: 0 | BE62: 0 | BF62: 0 | BG62: 0 | BH62: 0 | BI62: 0 | BJ62: -3706 | BK62: 0 | BL62: 0 | BM62: -20386 | BN62: 0 | BO62: 0 | BP62: 0 | BQ62: 0 | BR62: 0 | BS62: 0 | BT62: 0 | BU62: -10603 | BV62: 0 | BW62: -23259 | BX62: 0 | BY62: 0 | BZ62: 0 | CA62: 0 | CB62: 0 | CC62: -15730 | CD62: 0 | CE62: 0 | CF62: 0 | CG62: 0 | CH62: 0 | CI62: 0 | CJ62: 0 | CK62: -25979 | CL62: 0 | CM62: 0 | CN62: -8076 | CO62: 0 | CP62: 0 | CQ62: 0 | CR62: 0 | CS62: -16074 | CT62: 0 | CU62: 0 | CV62: 0 | CW62: 0 | CX62: 0 | CY62: 0 | CZ62: 0 | DA62: 0 | DB62: 0 | DC62: 0 | DD62: 0 | DE62: 0 | DF62: 0 | DG62: -37255 | DH62: -18628 | DI62: 0 | DJ62: 0 | DK62: 0 | DL62: 0 | DM62: 0 | DN62: 0 | DO62: 0 | DP62: 0 | DQ62: 0 | DR62: 0 | DS62: 0 | DT62: 0 | DU62: 0 | DV62: 0 | DW62: -4425 | DX62: 0 | DY62: 0 | DZ62: -23633 | EA62: 0 | EB62: 0 | EC62: 0 | ED62: 0 | EE62: -509090
A64: Scheduled Base Rent
A65: 1. Kitu Life, Inc. | B65: 1 | C65: 18191 | D65: 18191 | E65: 18191 | F65: 18191 | G65: 18191 | H65: 18191 | I65: 18191 | J65: 18191 | K65: 18692 | L65: 18692 | M65: 18692 | N65: 18692 | O65: 18692 | P65: 18692 | Q65: 18692 | R65: 18692 | S65: 18692 | T65: 18692 | U65: 18692 | V65: 18692 | W65: 19206 | X65: 19206 | Y65: 19206 | Z65: 19206 | AA65: 19206 | AB65: 19206 | AC65: 19206 | AD65: 19206 | AE65: 19206 | AF65: 19206 | AG65: 19206 | AH65: 19206 | AI65: 19734 | AJ65: 19734 | AK65: 19734 | AL65: 19734 | AM65: 19734 | AN65: 19734 | AO65: 19734 | AP65: 19734 | AQ65: 19734 | AR65: 19734 | AS65: 19734 | AT65: 19734 | AU65: 20276 | AV65: 20276 | AW65: 20276 | AX65: 20276 | AY65: 20276 | AZ65: 20276 | BA65: 20276 | BB65: 20276 | BC65: 20276 | BD65: 20276 | BE65: 20276 | BF65: 20276 | BG65: 20834 | BH65: 20834 | BI65: 20834 | BJ65: 20834 | BK65: 0 | BL65: 0 | BM65: 2265 | BN65: 22651 | BO65: 22651 | BP65: 22651 | BQ65: 22651 | BR65: 22651 | BS65: 22651 | BT65: 22651 | BU65: 22651 | BV65: 22651 | BW65: 22651 | BX65: 22651 | BY65: 23330 | BZ65: 23330 | CA65: 23330 | CB65: 23330 | CC65: 23330 | CD65: 23330 | CE65: 23330 | CF65: 23330 | CG65: 23330 | CH65: 23330 | CI65: 23330 | CJ65: 23330 | CK65: 24030 | CL65: 24030 | CM65: 24030 | CN65: 24030 | CO65: 24030 | CP65: 24030 | CQ65: 24030 | CR65: 24030 | CS65: 24030 | CT65: 24030 | CU65: 24030 | CV65: 24030 | CW65: 24751 | CX65: 24751 | CY65: 24751 | CZ65: 24751 | DA65: 24751 | DB65: 24751 | DC65: 24751 | DD65: 24751 | DE65: 24751 | DF65: 24751 | DG65: 24751 | DH65: 24751 | DI65: 25494 | DJ65: 25494 | DK65: 25494 | DL65: 25494 | DM65: 25494 | DN65: 25494 | DO65: 25494 | DP65: 25494 | DQ65: 25494 | DR65: 25494 | DS65: 25494 | DT65: 25494 | DU65: 26258 | DV65: 26258 | DW65: 26258 | DX65: 0 | DY65: 0 | DZ65: 2626 | EA65: 26258 | EB65: 26258 | EC65: 26258 | ED65: 26258 | EE65: 2772872
A66: 2. VACANT | B66: 2 | C66: 0 | D66: 0 | E66: 0 | F66: 0 | G66: 0 | H66: 0 | I66: 0 | J66: 0 | K66: 0 | L66: 0 | M66: 21644 | N66: 21644 | O66: 21644 | P66: 21644 | Q66: 21644 | R66: 21644 | S66: 21644 | T66: 21644 | U66: 21644 | V66: 22293 | W66: 22293 | X66: 22293 | Y66: 22293 | Z66: 22293 | AA66: 22293 | AB66: 22293 | AC66: 22293 | AD66: 22293 | AE66: 22293 | AF66: 22293 | AG66: 22293 | AH66: 22962 | AI66: 22962 | AJ66: 22962 | AK66: 22962 | AL66: 22962 | AM66: 22962 | AN66: 22962 | AO66: 22962 | AP66: 22962 | AQ66: 22962 | AR66: 22962 | AS66: 22962 | AT66: 23651 | AU66: 23651 | AV66: 23651 | AW66: 23651 | AX66: 23651 | AY66: 23651 | AZ66: 23651 | BA66: 23651 | BB66: 23651 | BC66: 23651 | BD66: 23651 | BE66: 23651 | BF66: 24360 | BG66: 24360 | BH66: 24360 | BI66: 24360 | BJ66: 24360 | BK66: 24360 | BL66: 24360 | BM66: 24360 | BN66: 24360 | BO66: 24360 | BP66: 24360 | BQ66: 24360 | BR66: 25091 | BS66: 25091 | BT66: 25091 | BU66: 0 | BV66: 0 | BW66: 2584 | BX66: 25844 | BY66: 25844 | BZ66: 25844 | CA66: 25844 | CB66: 25844 | CC66: 25844 | CD66: 25844 | CE66: 25844 | CF66: 25844 | CG66: 25844 | CH66: 25844 | CI66: 26619 | CJ66: 26619 | CK66: 26619 | CL66: 26619 | CM66: 26619 | CN66: 26619 | CO66: 26619 | CP66: 26619 | CQ66: 26619 | CR66: 26619 | CS66: 26619 | CT66: 26619 | CU66: 27418 | CV66: 27418 | CW66: 27418 | CX66: 27418 | CY66: 27418 | CZ66: 27418 | DA66: 27418 | DB66: 27418 | DC66: 27418 | DD66: 27418 | DE66: 27418 | DF66: 27418 | DG66: 28240 | DH66: 28240 | DI66: 28240 | DJ66: 28240 | DK66: 28240 | DL66: 28240 | DM66: 28240 | DN66: 28240 | DO66: 28240 | DP66: 28240 | DQ66: 28240 | DR66: 28240 | DS66: 29087 | DT66: 29087 | DU66: 29087 | DV66: 29087 | DW66: 29087 | DX66: 29087 | DY66: 29087 | DZ66: 29087 | EA66: 29087 | EB66: 29087 | EC66: 29087 | ED66: 29087 | EE66: 3012483
A67: 3. Saatva | B67: 3 | C67: 12208 | D67: 12208 | E67: 12208 | F67: 10750 | G67: 10750 | H67: 10750 | I67: 10750 | J67: 10750 | K67: 10750 | L67: 10750 | M67: 10750 | N67: 10750 | O67: 10750 | P67: 10750 | Q67: 10750 | R67: 13500 | S67: 13500 | T67: 13500 | U67: 13500 | V67: 13500 | W67: 13500 | X67: 13500 | Y67: 13500 | Z67: 13500 | AA67: 13500 | AB67: 13500 | AC67: 13500 | AD67: 0 | AE67: 0 | AF67: 1541 | AG67: 15406 | AH67: 15406 | AI67: 15406 | AJ67: 15406 | AK67: 15406 | AL67: 15406 | AM67: 15406 | AN67: 15406 | AO67: 15406 | AP67: 15406 | AQ67: 15406 | AR67: 15868 | AS67: 15868 | AT67: 15868 | AU67: 15868 | AV67: 15868 | AW67: 15868 | AX67: 15868 | AY67: 15868 | AZ67: 15868 | BA67: 15868 | BB67: 15868 | BC67: 15868 | BD67: 16344 | BE67: 16344 | BF67: 16344 | BG67: 16344 | BH67: 16344 | BI67: 16344 | BJ67: 16344 | BK67: 16344 | BL67: 16344 | BM67: 16344 | BN67: 16344 | BO67: 16344 | BP67: 16835 | BQ67: 16835 | BR67: 16835 | BS67: 16835 | BT67: 16835 | BU67: 16835 | BV67: 16835 | BW67: 16835 | BX67: 16835 | BY67: 16835 | BZ67: 16835 | CA67: 16835 | CB67: 17340 | CC67: 17340 | CD67: 17340 | CE67: 17340 | CF67: 17340 | CG67: 17340 | CH67: 17340 | CI67: 17340 | CJ67: 17340 | CK67: 17340 | CL67: 17340 | CM67: 17340 | CN67: 17860 | CO67: 17860 | CP67: 17860 | CQ67: 0 | CR67: 0 | CS67: 1786 | CT67: 17860 | CU67: 17860 | CV67: 17860 | CW67: 17860 | CX67: 17860 | CY67: 17860 | CZ67: 17860 | DA67: 17860 | DB67: 17860 | DC67: 17860 | DD67: 17860 | DE67: 18396 | DF67: 18396 | DG67: 18396 | DH67: 18396 | DI67: 18396 | DJ67: 18396 | DK67: 18396 | DL67: 18396 | DM67: 18396 | DN67: 18396 | DO67: 18396 | DP67: 18396 | DQ67: 18948 | DR67: 18948 | DS67: 18948 | DT67: 18948 | DU67: 18948 | DV67: 18948 | DW67: 18948 | DX67: 18948 | DY67: 18948 | DZ67: 18948 | EA67: 18948 | EB67: 18948 | EC67: 19516 | ED67: 19516 | EE67: 2034255
A68: 4. Fuse Architecture Studio | B68: 4 | C68: 6010 | D68: 6010 | E68: 6010 | F68: 6010 | G68: 6010 | H68: 6010 | I68: 6010 | J68: 6190 | K68: 6190 | L68: 6190 | M68: 6190 | N68: 6190 | O68: 6190 | P68: 6190 | Q68: 6190 | R68: 6190 | S68: 6190 | T68: 6190 | U68: 6190 | V68: 0 | W68: 0 | X68: 782 | Y68: 7823 | Z68: 7823 | AA68: 7823 | AB68: 7823 | AC68: 7823 | AD68: 7823 | AE68: 7823 | AF68: 7823 | AG68: 7823 | AH68: 7823 | AI68: 7823 | AJ68: 8058 | AK68: 8058 | AL68: 8058 | AM68: 8058 | AN68: 8058 | AO68: 8058 | AP68: 8058 | AQ68: 8058 | AR68: 8058 | AS68: 8058 | AT68: 8058 | AU68: 8058 | AV68: 8300 | AW68: 8300 | AX68: 8300 | AY68: 8300 | AZ68: 8300 | BA68: 8300 | BB68: 8300 | BC68: 8300 | BD68: 8300 | BE68: 8300 | BF68: 8300 | BG68: 8300 | BH68: 8549 | BI68: 8549 | BJ68: 8549 | BK68: 8549 | BL68: 8549 | BM68: 8549 | BN68: 8549 | BO68: 8549 | BP68: 8549 | BQ68: 8549 | BR68: 8549 | BS68: 8549 | BT68: 8805 | BU68: 8805 | BV68: 8805 | BW68: 8805 | BX68: 8805 | BY68: 8805 | BZ68: 8805 | CA68: 8805 | CB68: 8805 | CC68: 8805 | CD68: 8805 | CE68: 8805 | CF68: 9070 | CG68: 9070 | CH68: 9070 | CI68: 0 | CJ68: 0 | CK68: 934 | CL68: 9342 | CM68: 9342 | CN68: 9342 | CO68: 9342 | CP68: 9342 | CQ68: 9342 | CR68: 9342 | CS68: 9342 | CT68: 9342 | CU68: 9342 | CV68: 9342 | CW68: 9622 | CX68: 9622 | CY68: 9622 | CZ68: 9622 | DA68: 9622 | DB68: 9622 | DC68: 9622 | DD68: 9622 | DE68: 9622 | DF68: 9622 | DG68: 9622 | DH68: 9622 | DI68: 9911 | DJ68: 9911 | DK68: 9911 | DL68: 9911 | DM68: 9911 | DN68: 9911 | DO68: 9911 | DP68: 9911 | DQ68: 9911 | DR68: 9911 | DS68: 9911 | DT68: 9911 | DU68: 10208 | DV68: 10208 | DW68: 10208 | DX68: 10208 | DY68: 10208 | DZ68: 10208 | EA68: 10208 | EB68: 10208 | EC68: 10208 | ED68: 10208 | EE68: 1075105
A69: 5. Made In (sublessee to Geek Powered Studios) | B69: 5 | C69: 9850 | D69: 9850 | E69: 9850 | F69: 9850 | G69: 9850 | H69: 9850 | I69: 9850 | J69: 0 | K69: 0 | L69: 0 | M69: 0 | N69: 0 | O69: 0 | P69: 0 | Q69: 0 | R69: 0 | S69: 15077 | T69: 15077 | U69: 15077 | V69: 15077 | W69: 15077 | X69: 15077 | Y69: 15077 | Z69: 15077 | AA69: 15077 | AB69: 15529 | AC69: 15529 | AD69: 15529 | AE69: 15529 | AF69: 15529 | AG69: 15529 | AH69: 15529 | AI69: 15529 | AJ69: 15529 | AK69: 15529 | AL69: 15529 | AM69: 15529 | AN69: 15995 | AO69: 15995 | AP69: 15995 | AQ69: 15995 | AR69: 15995 | AS69: 15995 | AT69: 15995 | AU69: 15995 | AV69: 15995 | AW69: 15995 | AX69: 15995 | AY69: 15995 | AZ69: 16475 | BA69: 16475 | BB69: 16475 | BC69: 16475 | BD69: 16475 | BE69: 16475 | BF69: 16475 | BG69: 16475 | BH69: 16475 | BI69: 16475 | BJ69: 16475 | BK69: 16475 | BL69: 16969 | BM69: 16969 | BN69: 16969 | BO69: 16969 | BP69: 16969 | BQ69: 16969 | BR69: 16969 | BS69: 16969 | BT69: 16969 | BU69: 16969 | BV69: 16969 | BW69: 16969 | BX69: 17478 | BY69: 17478 | BZ69: 17478 | CA69: 0 | CB69: 0 | CC69: 1748 | CD69: 17478 | CE69: 17478 | CF69: 17478 | CG69: 17478 | CH69: 17478 | CI69: 17478 | CJ69: 17478 | CK69: 17478 | CL69: 17478 | CM69: 17478 | CN69: 17478 | CO69: 18003 | CP69: 18003 | CQ69: 18003 | CR69: 18003 | CS69: 18003 | CT69: 18003 | CU69: 18003 | CV69: 18003 | CW69: 18003 | CX69: 18003 | CY69: 18003 | CZ69: 18003 | DA69: 18543 | DB69: 18543 | DC69: 18543 | DD69: 18543 | DE69: 18543 | DF69: 18543 | DG69: 18543 | DH69: 18543 | DI69: 18543 | DJ69: 18543 | DK69: 18543 | DL69: 18543 | DM69: 19099 | DN69: 19099 | DO69: 19099 | DP69: 19099 | DQ69: 19099 | DR69: 19099 | DS69: 19099 | DT69: 19099 | DU69: 19099 | DV69: 19099 | DW69: 19099 | DX69: 19099 | DY69: 19672 | DZ69: 19672 | EA69: 19672 | EB69: 19672 | EC69: 19672 | ED69: 19672 | EE69: 2016467
A70: 6. Elmo 35, LLC | B70: 6 | C70: 15875 | D70: 15875 | E70: 15875 | F70: 15875 | G70: 15875 | H70: 15875 | I70: 15875 | J70: 15875 | K70: 15875 | L70: 15875 | M70: 15875 | N70: 15875 | O70: 16351 | P70: 16351 | Q70: 16351 | R70: 16351 | S70: 16351 | T70: 16351 | U70: 16351 | V70: 16351 | W70: 16351 | X70: 16351 | Y70: 16351 | Z70: 16351 | AA70: 16842 | AB70: 16842 | AC70: 16842 | AD70: 16842 | AE70: 16842 | AF70: 16842 | AG70: 16842 | AH70: 16842 | AI70: 16842 | AJ70: 16842 | AK70: 16842 | AL70: 16842 | AM70: 17347 | AN70: 17347 | AO70: 17347 | AP70: 17347 | AQ70: 17347 | AR70: 17347 | AS70: 17347 | AT70: 17347 | AU70: 17347 | AV70: 17347 | AW70: 17347 | AX70: 17347 | AY70: 17868 | AZ70: 17868 | BA70: 17868 | BB70: 17868 | BC70: 17868 | BD70: 17868 | BE70: 17868 | BF70: 17868 | BG70: 17868 | BH70: 17868 | BI70: 17868 | BJ70: 17868 | BK70: 18404 | BL70: 18404 | BM70: 18404 | BN70: 18404 | BO70: 18404 | BP70: 18404 | BQ70: 18404 | BR70: 18404 | BS70: 18404 | BT70: 18404 | BU70: 18404 | BV70: 18404 | BW70: 18956 | BX70: 18956 | BY70: 18956 | BZ70: 18956 | CA70: 18956 | CB70: 18956 | CC70: 18956 | CD70: 18956 | CE70: 18956 | CF70: 18956 | CG70: 18956 | CH70: 18956 | CI70: 0 | CJ70: 0 | CK70: 1952 | CL70: 19524 | CM70: 19524 | CN70: 19524 | CO70: 19524 | CP70: 19524 | CQ70: 19524 | CR70: 19524 | CS70: 19524 | CT70: 19524 | CU70: 19524 | CV70: 19524 | CW70: 20110 | CX70: 20110 | CY70: 20110 | CZ70: 20110 | DA70: 20110 | DB70: 20110 | DC70: 20110 | DD70: 20110 | DE70: 20110 | DF70: 20110 | DG70: 20110 | DH70: 20110 | DI70: 20713 | DJ70: 20713 | DK70: 20713 | DL70: 20713 | DM70: 20713 | DN70: 20713 | DO70: 20713 | DP70: 20713 | DQ70: 20713 | DR70: 20713 | DS70: 20713 | DT70: 20713 | DU70: 21335 | DV70: 21335 | DW70: 21335 | DX70: 21335 | DY70: 21335 | DZ70: 21335 | EA70: 21335 | EB70: 21335 | EC70: 21335 | ED70: 21335 | EE70: 2379656
A71: 7. Trihydro Corporation | B71: 7 | C71: 6010 | D71: 6010 | E71: 6010 | F71: 6010 | G71: 6010 | H71: 6010 | I71: 6190 | J71: 6190 | K71: 6190 | L71: 6190 | M71: 6190 | N71: 6190 | O71: 6190 | P71: 6190 | Q71: 6190 | R71: 6190 | S71: 6190 | T71: 6190 | U71: 0 | V71: 0 | W71: 0 | X71: 0 | Y71: 0 | Z71: 0 | AA71: 0 | AB71: 0 | AC71: 0 | AD71: 7740 | AE71: 7740 | AF71: 7740 | AG71: 7740 | AH71: 7740 | AI71: 7740 | AJ71: 7740 | AK71: 7740 | AL71: 7740 | AM71: 7972 | AN71: 7972 | AO71: 7972 | AP71: 7972 | AQ71: 7972 | AR71: 7972 | AS71: 7972 | AT71: 7972 | AU71: 7972 | AV71: 7972 | AW71: 7972 | AX71: 7972 | AY71: 8212 | AZ71: 8212 | BA71: 8212 | BB71: 8212 | BC71: 8212 | BD71: 8212 | BE71: 8212 | BF71: 8212 | BG71: 8212 | BH71: 8212 | BI71: 8212 | BJ71: 8212 | BK71: 8458 | BL71: 8458 | BM71: 8458 | BN71: 8458 | BO71: 8458 | BP71: 8458 | BQ71: 8458 | BR71: 8458 | BS71: 8458 | BT71: 8458 | BU71: 8458 | BV71: 8458 | BW71: 8712 | BX71: 8712 | BY71: 8712 | BZ71: 8712 | CA71: 8712 | CB71: 8712 | CC71: 8712 | CD71: 8712 | CE71: 8712 | CF71: 8712 | CG71: 8712 | CH71: 8712 | CI71: 8973 | CJ71: 8973 | CK71: 8973 | CL71: 0 | CM71: 0 | CN71: 897 | CO71: 8973 | CP71: 8973 | CQ71: 8973 | CR71: 8973 | CS71: 8973 | CT71: 8973 | CU71: 8973 | CV71: 8973 | CW71: 8973 | CX71: 8973 | CY71: 8973 | CZ71: 9242 | DA71: 9242 | DB71: 9242 | DC71: 9242 | DD71: 9242 | DE71: 9242 | DF71: 9242 | DG71: 9242 | DH71: 9242 | DI71: 9242 | DJ71: 9242 | DK71: 9242 | DL71: 9520 | DM71: 9520 | DN71: 9520 | DO71: 9520 | DP71: 9520 | DQ71: 9520 | DR71: 9520 | DS71: 9520 | DT71: 9520 | DU71: 9520 | DV71: 9520 | DW71: 9520 | DX71: 9805 | DY71: 9805 | DZ71: 9805 | EA71: 9805 | EB71: 9805 | EC71: 9805 | ED71: 9805 | EE71: 1000548
A72: 8. Urban ATX | B72: 07A | C72: 3252 | D72: 3252 | E72: 3252 | F72: 3252 | G72: 3252 | H72: 3252 | I72: 3252 | J72: 3350 | K72: 3350 | L72: 3350 | M72: 3350 | N72: 3350 | O72: 3350 | P72: 3350 | Q72: 3350 | R72: 3350 | S72: 3350 | T72: 3350 | U72: 3350 | V72: 3450 | W72: 3450 | X72: 3450 | Y72: 3450 | Z72: 3450 | AA72: 3450 | AB72: 3450 | AC72: 3450 | AD72: 3450 | AE72: 3450 | AF72: 3450 | AG72: 3450 | AH72: 3554 | AI72: 3554 | AJ72: 3554 | AK72: 3554 | AL72: 3554 | AM72: 3554 | AN72: 3554 | AO72: 3554 | AP72: 3554 | AQ72: 3554 | AR72: 3554 | AS72: 3554 | AT72: 3660 | AU72: 3660 | AV72: 3660 | AW72: 3660 | AX72: 3660 | AY72: 3660 | AZ72: 3660 | BA72: 3660 | BB72: 3660 | BC72: 3660 | BD72: 3660 | BE72: 3660 | BF72: 3660 | BG72: 3660 | BH72: 0 | BI72: 0 | BJ72: 412 | BK72: 4118 | BL72: 4118 | BM72: 4118 | BN72: 4118 | BO72: 4118 | BP72: 4118 | BQ72: 4118 | BR72: 4118 | BS72: 4118 | BT72: 4118 | BU72: 4118 | BV72: 4242 | BW72: 4242 | BX72: 4242 | BY72: 4242 | BZ72: 4242 | CA72: 4242 | CB72: 4242 | CC72: 4242 | CD72: 4242 | CE72: 4242 | CF72: 4242 | CG72: 4242 | CH72: 4369 | CI72: 4369 | CJ72: 4369 | CK72: 4369 | CL72: 4369 | CM72: 4369 | CN72: 4369 | CO72: 4369 | CP72: 4369 | CQ72: 4369 | CR72: 4369 | CS72: 4369 | CT72: 4500 | CU72: 4500 | CV72: 4500 | CW72: 4500 | CX72: 4500 | CY72: 4500 | CZ72: 4500 | DA72: 4500 | DB72: 4500 | DC72: 4500 | DD72: 4500 | DE72: 4500 | DF72: 4635 | DG72: 4635 | DH72: 4635 | DI72: 4635 | DJ72: 4635 | DK72: 4635 | DL72: 4635 | DM72: 4635 | DN72: 4635 | DO72: 4635 | DP72: 4635 | DQ72: 4635 | DR72: 4774 | DS72: 4774 | DT72: 4774 | DU72: 0 | DV72: 0 | DW72: 492 | DX72: 4917 | DY72: 4917 | DZ72: 4917 | EA72: 4917 | EB72: 4917 | EC72: 4917 | ED72: 4917 | EE72: 506141
A73: 9. Brinkley Sargent Winginton Architects | B73: 8 | C73: 5375 | D73: 5500 | E73: 5500 | F73: 5500 | G73: 5500 | H73: 5500 | I73: 5500 | J73: 5500 | K73: 5500 | L73: 5500 | M73: 5500 | N73: 5500 | O73: 5500 | P73: 6563 | Q73: 6563 | R73: 6563 | S73: 6563 | T73: 6563 | U73: 6563 | V73: 6563 | W73: 6563 | X73: 6563 | Y73: 6563 | Z73: 6563 | AA73: 6563 | AB73: 6760 | AC73: 6760 | AD73: 6760 | AE73: 6760 | AF73: 6760 | AG73: 6760 | AH73: 6760 | AI73: 6760 | AJ73: 6760 | AK73: 6760 | AL73: 6760 | AM73: 6760 | AN73: 6963 | AO73: 6963 | AP73: 6963 | AQ73: 6963 | AR73: 6963 | AS73: 6963 | AT73: 6963 | AU73: 6963 | AV73: 6963 | AW73: 6963 | AX73: 6963 | AY73: 6963 | AZ73: 7171 | BA73: 7171 | BB73: 7171 | BC73: 7171 | BD73: 7171 | BE73: 7171 | BF73: 7171 | BG73: 7171 | BH73: 7171 | BI73: 7171 | BJ73: 7171 | BK73: 7171 | BL73: 7387 | BM73: 7387 | BN73: 7387 | BO73: 7387 | BP73: 7387 | BQ73: 7387 | BR73: 7387 | BS73: 7387 | BT73: 7387 | BU73: 7387 | BV73: 7387 | BW73: 7387 | BX73: 7608 | BY73: 7608 | BZ73: 7608 | CA73: 7608 | CB73: 7608 | CC73: 7608 | CD73: 7608 | CE73: 7608 | CF73: 7608 | CG73: 7608 | CH73: 7608 | CI73: 7608 | CJ73: 7836 | CK73: 7836 | CL73: 7836 | CM73: 7836 | CN73: 7836 | CO73: 7836 | CP73: 7836 | CQ73: 7836 | CR73: 7836 | CS73: 7836 | CT73: 7836 | CU73: 7836 | CV73: 8071 | CW73: 8071 | CX73: 8071 | CY73: 8071 | CZ73: 8071 | DA73: 8071 | DB73: 8071 | DC73: 8071 | DD73: 8071 | DE73: 8071 | DF73: 8071 | DG73: 8071 | DH73: 8314 | DI73: 8314 | DJ73: 8314 | DK73: 8314 | DL73: 8314 | DM73: 8314 | DN73: 8314 | DO73: 8314 | DP73: 8314 | DQ73: 8314 | DR73: 8314 | DS73: 8314 | DT73: 8563 | DU73: 8563 | DV73: 8563 | DW73: 8563 | DX73: 8563 | DY73: 8563 | DZ73: 8563 | EA73: 8563 | EB73: 8563 | EC73: 8563 | ED73: 8563 | EE73: 965638
A74: 10. Austin Prosthetics Center | B74: 9 | C74: 7167 | D74: 7167 | E74: 7167 | F74: 7167 | G74: 7167 | H74: 7167 | I74: 7167 | J74: 7167 | K74: 7333 | L74: 7333 | M74: 7333 | N74: 7333 | O74: 7333 | P74: 7333 | Q74: 7333 | R74: 7333 | S74: 7333 | T74: 7333 | U74: 7333 | V74: 7333 | W74: 7500 | X74: 7500 | Y74: 7500 | Z74: 7500 | AA74: 7500 | AB74: 7500 | AC74: 7500 | AD74: 7500 | AE74: 7500 | AF74: 7500 | AG74: 7500 | AH74: 7500 | AI74: 7667 | AJ74: 7667 | AK74: 7667 | AL74: 7667 | AM74: 7667 | AN74: 7667 | AO74: 7667 | AP74: 7667 | AQ74: 7667 | AR74: 7667 | AS74: 7667 | AT74: 7667 | AU74: 7833 | AV74: 7833 | AW74: 7833 | AX74: 7833 | AY74: 7833 | AZ74: 7833 | BA74: 7833 | BB74: 7833 | BC74: 7833 | BD74: 7833 | BE74: 7833 | BF74: 7833 | BG74: 8000 | BH74: 8000 | BI74: 8000 | BJ74: 8000 | BK74: 8000 | BL74: 8000 | BM74: 8000 | BN74: 8000 | BO74: 8000 | BP74: 8000 | BQ74: 8000 | BR74: 8000 | BS74: 0 | BT74: 0 | BU74: 1178 | BV74: 11781 | BW74: 11781 | BX74: 11781 | BY74: 11781 | BZ74: 11781 | CA74: 11781 | CB74: 11781 | CC74: 11781 | CD74: 11781 | CE74: 11781 | CF74: 11781 | CG74: 12134 | CH74: 12134 | CI74: 12134 | CJ74: 12134 | CK74: 12134 | CL74: 12134 | CM74: 12134 | CN74: 12134 | CO74: 12134 | CP74: 12134 | CQ74: 12134 | CR74: 12134 | CS74: 12498 | CT74: 12498 | CU74: 12498 | CV74: 12498 | CW74: 12498 | CX74: 12498 | CY74: 12498 | CZ74: 12498 | DA74: 12498 | DB74: 12498 | DC74: 12498 | DD74: 12498 | DE74: 12873 | DF74: 12873 | DG74: 12873 | DH74: 12873 | DI74: 12873 | DJ74: 12873 | DK74: 12873 | DL74: 12873 | DM74: 12873 | DN74: 12873 | DO74: 12873 | DP74: 12873 | DQ74: 13259 | DR74: 13259 | DS74: 13259 | DT74: 13259 | DU74: 13259 | DV74: 13259 | DW74: 13259 | DX74: 13259 | DY74: 13259 | DZ74: 13259 | EA74: 13259 | EB74: 13259 | EC74: 13657 | ED74: 13657 | EE74: 1284585
A75: 11. Ignite Fitnez | B75: 10 | C75: 0 | D75: 0 | E75: 0 | F75: 0 | G75: 0 | H75: 0 | I75: 0 | J75: 0 | K75: 0 | L75: 0 | M75: 0 | N75: 0 | O75: 0 | P75: 0 | Q75: 0 | R75: 0 | S75: 0 | T75: 0 | U75: 0 | V75: 0 | W75: 29410 | X75: 29410 | Y75: 29410 | Z75: 29410 | AA75: 29410 | AB75: 29410 | AC75: 29410 | AD75: 30292 | AE75: 30292 | AF75: 30292 | AG75: 30292 | AH75: 30292 | AI75: 30292 | AJ75: 30292 | AK75: 30292 | AL75: 30292 | AM75: 30292 | AN75: 30292 | AO75: 30292 | AP75: 31201 | AQ75: 31201 | AR75: 31201 | AS75: 31201 | AT75: 31201 | AU75: 31201 | AV75: 31201 | AW75: 31201 | AX75: 31201 | AY75: 31201 | AZ75: 31201 | BA75: 31201 | BB75: 32137 | BC75: 32137 | BD75: 32137 | BE75: 32137 | BF75: 32137 | BG75: 32137 | BH75: 32137 | BI75: 32137 | BJ75: 32137 | BK75: 32137 | BL75: 32137 | BM75: 32137 | BN75: 33101 | BO75: 33101 | BP75: 33101 | BQ75: 33101 | BR75: 33101 | BS75: 33101 | BT75: 33101 | BU75: 33101 | BV75: 33101 | BW75: 33101 | BX75: 33101 | BY75: 33101 | BZ75: 34094 | CA75: 34094 | CB75: 34094 | CC75: 34094 | CD75: 34094 | CE75: 34094 | CF75: 34094 | CG75: 34094 | CH75: 34094 | CI75: 34094 | CJ75: 34094 | CK75: 34094 | CL75: 35116 | CM75: 35116 | CN75: 35116 | CO75: 35116 | CP75: 35116 | CQ75: 35116 | CR75: 35116 | CS75: 35116 | CT75: 35116 | CU75: 35116 | CV75: 35116 | CW75: 35116 | CX75: 36170 | CY75: 36170 | CZ75: 36170 | DA75: 36170 | DB75: 36170 | DC75: 0 | DD75: 0 | DE75: 0 | DF75: 0 | DG75: 0 | DH75: 18628 | DI75: 37255 | DJ75: 37255 | DK75: 37255 | DL75: 37255 | DM75: 37255 | DN75: 37255 | DO75: 37255 | DP75: 37255 | DQ75: 37255 | DR75: 37255 | DS75: 38373 | DT75: 38373 | DU75: 38373 | DV75: 38373 | DW75: 38373 | DX75: 38373 | DY75: 38373 | DZ75: 38373 | EA75: 38373 | EB75: 38373 | EC75: 38373 | ED75: 38373 | EE75: 3589644
A76: Total Scheduled Base Rent | C76: 83939 | D76: 84064 | E76: 84064 | F76: 82605 | G76: 82605 | H76: 82605 | I76: 82785 | J76: 73213 | K76: 73880 | L76: 73880 | M76: 95524 | N76: 95524 | O76: 96000 | P76: 97063 | Q76: 97063 | R76: 99813 | S76: 114890 | T76: 114890 | U76: 108699 | V76: 103259 | W76: 133349 | X76: 134132 | Y76: 141173 | Z76: 141173 | AA76: 141663 | AB76: 142312 | AC76: 142312 | AD76: 137435 | AE76: 137435 | AF76: 138976 | AG76: 152841 | AH76: 153613 | AI76: 154308 | AJ76: 154543 | AK76: 154543 | AL76: 154543 | AM76: 155280 | AN76: 155949 | AO76: 155949 | AP76: 156858 | AQ76: 156858 | AR76: 157320 | AS76: 157320 | AT76: 158115 | AU76: 158825 | AV76: 159067 | AW76: 159067 | AX76: 159067 | AY76: 159826 | AZ76: 160515 | BA76: 160515 | BB76: 161451 | BC76: 161451 | BD76: 161927 | BE76: 161927 | BF76: 162636 | BG76: 163361 | BH76: 159949 | BI76: 159949 | BJ76: 160361 | BK76: 144016 | BL76: 144725 | BM76: 146990 | BN76: 168340 | BO76: 168340 | BP76: 168830 | BQ76: 168830 | BR76: 169561 | BS76: 161561 | BT76: 161818 | BU76: 137905 | BV76: 148631 | BW76: 152021 | BX76: 176011 | BY76: 176691 | BZ76: 177684 | CA76: 160205 | CB76: 160710 | CC76: 162458 | CD76: 178189 | CE76: 178189 | CF76: 178453 | CG76: 178806 | CH76: 178934 | CI76: 151945 | CJ76: 152173 | CK76: 155760 | CL76: 173789 | CM76: 173789 | CN76: 175206 | CO76: 183806 | CP76: 183806 | CQ76: 165947 | CR76: 165947 | CS76: 168097 | CT76: 184302 | CU76: 185100 | CV76: 185335 | CW76: 186922 | CX76: 187976 | CY76: 187976 | CZ76: 188245 | DA76: 188785 | DB76: 188785 | DC76: 152615 | DD76: 152615 | DE76: 153526 | DF76: 153661 | DG76: 154483 | DH76: 173353 | DI76: 193615 | DJ76: 193615 | DK76: 193615 | DL76: 193892 | DM76: 194448 | DN76: 194448 | DO76: 194448 | DP76: 194448 | DQ76: 195386 | DR76: 195526 | DS76: 197490 | DT76: 197740 | DU76: 194649 | DV76: 194649 | DW76: 195141 | DX76: 173594 | DY76: 174167 | DZ76: 176792 | EA76: 200425 | EB76: 200425 | EC76: 201391 | ED76: 201391 | EE76: 20637394
C77: =12*(C76+12500-C62)/C20 -> 21.848024 | D77: =12*(D76+12500-D62)/D20 -> 21.876343 | E77: =12*(E76+12500-E62)/E20 -> 21.876343 | F77: =12*(F76-F62)/F20 -> 24.086602 | G77: =12*(G76-G62)/G20 -> 24.086602 | H77: =12*(H76-H62)/H20 -> 24.086602 | I77: =12*(I76-I62)/I20 -> 24.139087 | J77: =12*(J76-J62)/J20 -> 25.805577 | K77: =12*(K76-K62)/K20 -> 25.987032 | L77: =12*(L76-L62)/L20 -> 25.987032 | M77: =12*(M76-M62)/M20 -> 25.987032 | ... ED77: =12*(ED76-ED62)/ED20 -> 38.728418
A78: Fixed Steps
A79: 1. Kitu Life, Inc. | B79: 1 | C79: 0 | D79: 0 | E79: 0 | F79: 0 | G79: 0 | H79: 0 | I79: 0 | J79: 0 | K79: 500 | L79: 500 | M79: 500 | N79: 500 | O79: 500 | P79: 500 | Q79: 500 | R79: 500 | S79: 500 | T79: 500 | U79: 500 | V79: 500 | W79: 1014 | X79: 1014 | Y79: 1014 | Z79: 1014 | AA79: 1014 | AB79: 1014 | AC79: 1014 | AD79: 1014 | AE79: 1014 | AF79: 1014 | AG79: 1014 | AH79: 1014 | AI79: 1542 | AJ79: 1542 | AK79: 1542 | AL79: 1542 | AM79: 1542 | AN79: 1542 | AO79: 1542 | AP79: 1542 | AQ79: 1542 | AR79: 1542 | AS79: 1542 | AT79: 1542 | AU79: 2085 | AV79: 2085 | AW79: 2085 | AX79: 2085 | AY79: 2085 | AZ79: 2085 | BA79: 2085 | BB79: 2085 | BC79: 2085 | BD79: 2085 | BE79: 2085 | BF79: 2085 | BG79: 2643 | BH79: 2643 | BI79: 2643 | BJ79: 2643 | BK79: 0 | BL79: 0 | BM79: 0 | BN79: 0 | BO79: 0 | BP79: 0 | BQ79: 0 | BR79: 0 | BS79: 0 | BT79: 0 | BU79: 0 | BV79: 0 | BW79: 0 | BX79: 0 | BY79: 680 | BZ79: 680 | CA79: 680 | CB79: 680 | CC79: 680 | CD79: 680 | CE79: 680 | CF79: 680 | CG79: 680 | CH79: 680 | CI79: 680 | CJ79: 680 | CK79: 1379 | CL79: 1379 | CM79: 1379 | CN79: 1379 | CO79: 1379 | CP79: 1379 | CQ79: 1379 | CR79: 1379 | CS79: 1379 | CT79: 1379 | CU79: 1379 | CV79: 1379 | CW79: 2100 | CX79: 2100 | CY79: 2100 | CZ79: 2100 | DA79: 2100 | DB79: 2100 | DC79: 2100 | DD79: 2100 | DE79: 2100 | DF79: 2100 | DG79: 2100 | DH79: 2100 | DI79: 2843 | DJ79: 2843 | DK79: 2843 | DL79: 2843 | DM79: 2843 | DN79: 2843 | DO79: 2843 | DP79: 2843 | DQ79: 2843 | DR79: 2843 | DS79: 2843 | DT79: 2843 | DU79: 3608 | DV79: 3608 | DW79: 3608 | DX79: 0 | DY79: 0 | DZ79: 0 | EA79: 0 | EB79: 0 | EC79: 0 | ED79: 0 | EE79: 167125
A80: 2. VACANT | B80: 2 | C80: 0 | D80: 0 | E80: 0 | F80: 0 | G80: 0 | H80: 0 | I80: 0 | J80: 0 | K80: 0 | L80: 0 | M80: 0 | N80: 0 | O80: 0 | P80: 0 | Q80: 0 | R80: 0 | S80: 0 | T80: 0 | U80: 0 | V80: 649 | W80: 649 | X80: 649 | Y80: 649 | Z80: 649 | AA80: 649 | AB80: 649 | AC80: 649 | AD80: 649 | AE80: 649 | AF80: 649 | AG80: 649 | AH80: 1318 | AI80: 1318 | AJ80: 1318 | AK80: 1318 | AL80: 1318 | AM80: 1318 | AN80: 1318 | AO80: 1318 | AP80: 1318 | AQ80: 1318 | AR80: 1318 | AS80: 1318 | AT80: 2007 | AU80: 2007 | AV80: 2007 | AW80: 2007 | AX80: 2007 | AY80: 2007 | AZ80: 2007 | BA80: 2007 | BB80: 2007 | BC80: 2007 | BD80: 2007 | BE80: 2007 | BF80: 2716 | BG80: 2716 | BH80: 2716 | BI80: 2716 | BJ80: 2716 | BK80: 2716 | BL80: 2716 | BM80: 2716 | BN80: 2716 | BO80: 2716 | BP80: 2716 | BQ80: 2716 | BR80: 3447 | BS80: 3447 | BT80: 3447 | BU80: 0 | BV80: 0 | BW80: 0 | BX80: 0 | BY80: 0 | BZ80: 0 | CA80: 0 | CB80: 0 | CC80: 0 | CD80: 0 | CE80: 0 | CF80: 0 | CG80: 0 | CH80: 0 | CI80: 775 | CJ80: 775 | CK80: 775 | CL80: 775 | CM80: 775 | CN80: 775 | CO80: 775 | CP80: 775 | CQ80: 775 | CR80: 775 | CS80: 775 | CT80: 775 | CU80: 1574 | CV80: 1574 | CW80: 1574 | CX80: 1574 | CY80: 1574 | CZ80: 1574 | DA80: 1574 | DB80: 1574 | DC80: 1574 | DD80: 1574 | DE80: 1574 | DF80: 1574 | DG80: 2396 | DH80: 2396 | DI80: 2396 | DJ80: 2396 | DK80: 2396 | DL80: 2396 | DM80: 2396 | DN80: 2396 | DO80: 2396 | DP80: 2396 | DQ80: 2396 | DR80: 2396 | DS80: 3244 | DT80: 3244 | DU80: 3244 | DV80: 3244 | DW80: 3244 | DX80: 3244 | DY80: 3244 | DZ80: 3244 | EA80: 3244 | EB80: 3244 | EC80: 3244 | ED80: 3244 | EE80: 186502
A81: 3. Saatva | B81: 3 | C81: 0 | D81: 0 | E81: 0 | F81: 0 | G81: 0 | H81: 0 | I81: 0 | J81: 0 | K81: 0 | L81: 0 | M81: 0 | N81: 0 | O81: 0 | P81: 0 | Q81: 0 | R81: 0 | S81: 0 | T81: 0 | U81: 0 | V81: 0 | W81: 0 | X81: 0 | Y81: 0 | Z81: 0 | AA81: 0 | AB81: 0 | AC81: 0 | AD81: 0 | AE81: 0 | AF81: 0 | AG81: 0 | AH81: 0 | AI81: 0 | AJ81: 0 | AK81: 0 | AL81: 0 | AM81: 0 | AN81: 0 | AO81: 0 | AP81: 0 | AQ81: 0 | AR81: 462 | AS81: 462 | AT81: 462 | AU81: 462 | AV81: 462 | AW81: 462 | AX81: 462 | AY81: 462 | AZ81: 462 | BA81: 462 | BB81: 462 | BC81: 462 | BD81: 938 | BE81: 938 | BF81: 938 | BG81: 938 | BH81: 938 | BI81: 938 | BJ81: 938 | BK81: 938 | BL81: 938 | BM81: 938 | BN81: 938 | BO81: 938 | BP81: 1429 | BQ81: 1429 | BR81: 1429 | BS81: 1429 | BT81: 1429 | BU81: 1429 | BV81: 1429 | BW81: 1429 | BX81: 1429 | BY81: 1429 | BZ81: 1429 | CA81: 1429 | CB81: 1934 | CC81: 1934 | CD81: 1934 | CE81: 1934 | CF81: 1934 | CG81: 1934 | CH81: 1934 | CI81: 1934 | CJ81: 1934 | CK81: 1934 | CL81: 1934 | CM81: 1934 | CN81: 2454 | CO81: 2454 | CP81: 2454 | CQ81: 0 | CR81: 0 | CS81: 0 | CT81: 0 | CU81: 0 | CV81: 0 | CW81: 0 | CX81: 0 | CY81: 0 | CZ81: 0 | DA81: 0 | DB81: 0 | DC81: 0 | DD81: 0 | DE81: 536 | DF81: 536 | DG81: 536 | DH81: 536 | DI81: 536 | DJ81: 536 | DK81: 536 | DL81: 536 | DM81: 536 | DN81: 536 | DO81: 536 | DP81: 536 | DQ81: 1088 | DR81: 1088 | DS81: 1088 | DT81: 1088 | DU81: 1088 | DV81: 1088 | DW81: 1088 | DX81: 1088 | DY81: 1088 | DZ81: 1088 | EA81: 1088 | EB81: 1088 | EC81: 1656 | ED81: 1656 | EE81: 87306
A82: 4. Fuse Architecture Studio | B82: 4 | C82: 0 | D82: 0 | E82: 0 | F82: 0 | G82: 0 | H82: 0 | I82: 0 | J82: 0 | K82: 0 | L82: 0 | M82: 0 | N82: 0 | O82: 0 | P82: 0 | Q82: 0 | R82: 0 | S82: 0 | T82: 0 | U82: 0 | V82: 0 | W82: 0 | X82: 0 | Y82: 0 | Z82: 0 | AA82: 0 | AB82: 0 | AC82: 0 | AD82: 0 | AE82: 0 | AF82: 0 | AG82: 0 | AH82: 0 | AI82: 0 | AJ82: 235 | AK82: 235 | AL82: 235 | AM82: 235 | AN82: 235 | AO82: 235 | AP82: 235 | AQ82: 235 | AR82: 235 | AS82: 235 | AT82: 235 | AU82: 235 | AV82: 476 | AW82: 476 | AX82: 476 | AY82: 476 | AZ82: 476 | BA82: 476 | BB82: 476 | BC82: 476 | BD82: 476 | BE82: 476 | BF82: 476 | BG82: 476 | BH82: 725 | BI82: 725 | BJ82: 725 | BK82: 725 | BL82: 725 | BM82: 725 | BN82: 725 | BO82: 725 | BP82: 725 | BQ82: 725 | BR82: 725 | BS82: 725 | BT82: 982 | BU82: 982 | BV82: 982 | BW82: 982 | BX82: 982 | BY82: 982 | BZ82: 982 | CA82: 982 | CB82: 982 | CC82: 982 | CD82: 982 | CE82: 982 | CF82: 1246 | CG82: 1246 | CH82: 1246 | CI82: 0 | CJ82: 0 | CK82: 0 | CL82: 0 | CM82: 0 | CN82: 0 | CO82: 0 | CP82: 0 | CQ82: 0 | CR82: 0 | CS82: 0 | CT82: 0 | CU82: 0 | CV82: 0 | CW82: 280 | CX82: 280 | CY82: 280 | CZ82: 280 | DA82: 280 | DB82: 280 | DC82: 280 | DD82: 280 | DE82: 280 | DF82: 280 | DG82: 280 | DH82: 280 | DI82: 569 | DJ82: 569 | DK82: 569 | DL82: 569 | DM82: 569 | DN82: 569 | DO82: 569 | DP82: 569 | DQ82: 569 | DR82: 569 | DS82: 569 | DT82: 569 | DU82: 866 | DV82: 866 | DW82: 866 | DX82: 866 | DY82: 866 | DZ82: 866 | EA82: 866 | EB82: 866 | EC82: 866 | ED82: 866 | EE82: 51612
A83: 5. Made In (sublessee to Geek Powered Studios) | B83: 5 | C83: 0 | D83: 0 | E83: 0 | F83: 0 | G83: 0 | H83: 0 | I83: 0 | J83: 0 | K83: 0 | L83: 0 | M83: 0 | N83: 0 | O83: 0 | P83: 0 | Q83: 0 | R83: 0 | S83: 0 | T83: 0 | U83: 0 | V83: 0 | W83: 0 | X83: 0 | Y83: 0 | Z83: 0 | AA83: 0 | AB83: 452 | AC83: 452 | AD83: 452 | AE83: 452 | AF83: 452 | AG83: 452 | AH83: 452 | AI83: 452 | AJ83: 452 | AK83: 452 | AL83: 452 | AM83: 452 | AN83: 918 | AO83: 918 | AP83: 918 | AQ83: 918 | AR83: 918 | AS83: 918 | AT83: 918 | AU83: 918 | AV83: 918 | AW83: 918 | AX83: 918 | AY83: 918 | AZ83: 1398 | BA83: 1398 | BB83: 1398 | BC83: 1398 | BD83: 1398 | BE83: 1398 | BF83: 1398 | BG83: 1398 | BH83: 1398 | BI83: 1398 | BJ83: 1398 | BK83: 1398 | BL83: 1892 | BM83: 1892 | BN83: 1892 | BO83: 1892 | BP83: 1892 | BQ83: 1892 | BR83: 1892 | BS83: 1892 | BT83: 1892 | BU83: 1892 | BV83: 1892 | BW83: 1892 | BX83: 2401 | BY83: 2401 | BZ83: 2401 | CA83: 0 | CB83: 0 | CC83: 0 | CD83: 0 | CE83: 0 | CF83: 0 | CG83: 0 | CH83: 0 | CI83: 0 | CJ83: 0 | CK83: 0 | CL83: 0 | CM83: 0 | CN83: 0 | CO83: 524 | CP83: 524 | CQ83: 524 | CR83: 524 | CS83: 524 | CT83: 524 | CU83: 524 | CV83: 524 | CW83: 524 | CX83: 524 | CY83: 524 | CZ83: 524 | DA83: 1064 | DB83: 1064 | DC83: 1064 | DD83: 1064 | DE83: 1064 | DF83: 1064 | DG83: 1064 | DH83: 1064 | DI83: 1064 | DJ83: 1064 | DK83: 1064 | DL83: 1064 | DM83: 1621 | DN83: 1621 | DO83: 1621 | DP83: 1621 | DQ83: 1621 | DR83: 1621 | DS83: 1621 | DT83: 1621 | DU83: 1621 | DV83: 1621 | DW83: 1621 | DX83: 1621 | DY83: 2194 | DZ83: 2194 | EA83: 2194 | EB83: 2194 | EC83: 2194 | ED83: 2194 | EE83: 114809
A84: 6. Elmo 35, LLC | B84: 6 | C84: 0 | D84: 0 | E84: 0 | F84: 0 | G84: 0 | H84: 0 | I84: 0 | J84: 0 | K84: 0 | L84: 0 | M84: 0 | N84: 0 | O84: 476 | P84: 476 | Q84: 476 | R84: 476 | S84: 476 | T84: 476 | U84: 476 | V84: 476 | W84: 476 | X84: 476 | Y84: 476 | Z84: 476 | AA84: 967 | AB84: 967 | AC84: 967 | AD84: 967 | AE84: 967 | AF84: 967 | AG84: 967 | AH84: 967 | AI84: 967 | AJ84: 967 | AK84: 967 | AL84: 967 | AM84: 1472 | AN84: 1472 | AO84: 1472 | AP84: 1472 | AQ84: 1472 | AR84: 1472 | AS84: 1472 | AT84: 1472 | AU84: 1472 | AV84: 1472 | AW84: 1472 | AX84: 1472 | AY84: 1992 | AZ84: 1992 | BA84: 1992 | BB84: 1992 | BC84: 1992 | BD84: 1992 | BE84: 1992 | BF84: 1992 | BG84: 1992 | BH84: 1992 | BI84: 1992 | BJ84: 1992 | BK84: 2528 | BL84: 2528 | BM84: 2528 | BN84: 2528 | BO84: 2528 | BP84: 2528 | BQ84: 2528 | BR84: 2528 | BS84: 2528 | BT84: 2528 | BU84: 2528 | BV84: 2528 | BW84: 3081 | BX84: 3081 | BY84: 3081 | BZ84: 3081 | CA84: 3081 | CB84: 3081 | CC84: 3081 | CD84: 3081 | CE84: 3081 | CF84: 3081 | CG84: 3081 | CH84: 3081 | CI84: 0 | CJ84: 0 | CK84: 0 | CL84: 0 | CM84: 0 | CN84: 0 | CO84: 0 | CP84: 0 | CQ84: 0 | CR84: 0 | CS84: 0 | CT84: 0 | CU84: 0 | CV84: 0 | CW84: 586 | CX84: 586 | CY84: 586 | CZ84: 586 | DA84: 586 | DB84: 586 | DC84: 586 | DD84: 586 | DE84: 586 | DF84: 586 | DG84: 586 | DH84: 586 | DI84: 1189 | DJ84: 1189 | DK84: 1189 | DL84: 1189 | DM84: 1189 | DN84: 1189 | DO84: 1189 | DP84: 1189 | DQ84: 1189 | DR84: 1189 | DS84: 1189 | DT84: 1189 | DU84: 1810 | DV84: 1810 | DW84: 1810 | DX84: 1810 | DY84: 1810 | DZ84: 1810 | EA84: 1810 | EB84: 1810 | EC84: 1810 | ED84: 1810 | EE84: 165601
A85: 7. Trihydro Corporation | B85: 7 | C85: 0 | D85: 0 | E85: 0 | F85: 0 | G85: 0 | H85: 0 | I85: 0 | J85: 0 | K85: 0 | L85: 0 | M85: 0 | N85: 0 | O85: 0 | P85: 0 | Q85: 0 | R85: 0 | S85: 0 | T85: 0 | U85: 0 | V85: 0 | W85: 0 | X85: 0 | Y85: 0 | Z85: 0 | AA85: 0 | AB85: 0 | AC85: 0 | AD85: 0 | AE85: 0 | AF85: 0 | AG85: 0 | AH85: 0 | AI85: 0 | AJ85: 0 | AK85: 0 | AL85: 0 | AM85: 232 | AN85: 232 | AO85: 232 | AP85: 232 | AQ85: 232 | AR85: 232 | AS85: 232 | AT85: 232 | AU85: 232 | AV85: 232 | AW85: 232 | AX85: 232 | AY85: 471 | AZ85: 471 | BA85: 471 | BB85: 471 | BC85: 471 | BD85: 471 | BE85: 471 | BF85: 471 | BG85: 471 | BH85: 471 | BI85: 471 | BJ85: 471 | BK85: 718 | BL85: 718 | BM85: 718 | BN85: 718 | BO85: 718 | BP85: 718 | BQ85: 718 | BR85: 718 | BS85: 718 | BT85: 718 | BU85: 718 | BV85: 718 | BW85: 971 | BX85: 971 | BY85: 971 | BZ85: 971 | CA85: 971 | CB85: 971 | CC85: 971 | CD85: 971 | CE85: 971 | CF85: 971 | CG85: 971 | CH85: 971 | CI85: 1233 | CJ85: 1233 | CK85: 1233 | CL85: 0 | CM85: 0 | CN85: 0 | CO85: 0 | CP85: 0 | CQ85: 0 | CR85: 0 | CS85: 0 | CT85: 0 | CU85: 0 | CV85: 0 | CW85: 0 | CX85: 0 | CY85: 0 | CZ85: 269 | DA85: 269 | DB85: 269 | DC85: 269 | DD85: 269 | DE85: 269 | DF85: 269 | DG85: 269 | DH85: 269 | DI85: 269 | DJ85: 269 | DK85: 269 | DL85: 546 | DM85: 546 | DN85: 546 | DO85: 546 | DP85: 546 | DQ85: 546 | DR85: 546 | DS85: 546 | DT85: 546 | DU85: 546 | DV85: 546 | DW85: 546 | DX85: 832 | DY85: 832 | DZ85: 832 | EA85: 832 | EB85: 832 | EC85: 832 | ED85: 832 | EE85: 48024
A86: 8. Urban ATX | B86: 07A | C86: 0 | D86: 0 | E86: 0 | F86: 0 | G86: 0 | H86: 0 | I86: 0 | J86: 0 | K86: 0 | L86: 0 | M86: 0 | N86: 0 | O86: 0 | P86: 0 | Q86: 0 | R86: 0 | S86: 0 | T86: 0 | U86: 0 | V86: 0 | W86: 0 | X86: 0 | Y86: 0 | Z86: 0 | AA86: 0 | AB86: 0 | AC86: 0 | AD86: 0 | AE86: 0 | AF86: 0 | AG86: 0 | AH86: 0 | AI86: 0 | AJ86: 0 | AK86: 0 | AL86: 0 | AM86: 0 | AN86: 0 | AO86: 0 | AP86: 0 | AQ86: 0 | AR86: 0 | AS86: 0 | AT86: 0 | AU86: 0 | AV86: 0 | AW86: 0 | AX86: 0 | AY86: 0 | AZ86: 0 | BA86: 0 | BB86: 0 | BC86: 0 | BD86: 0 | BE86: 0 | BF86: 0 | BG86: 0 | BH86: 0 | BI86: 0 | BJ86: 0 | BK86: 0 | BL86: 0 | BM86: 0 | BN86: 0 | BO86: 0 | BP86: 0 | BQ86: 0 | BR86: 0 | BS86: 0 | BT86: 0 | BU86: 0 | BV86: 124 | BW86: 124 | BX86: 124 | BY86: 124 | BZ86: 124 | CA86: 124 | CB86: 124 | CC86: 124 | CD86: 124 | CE86: 124 | CF86: 124 | CG86: 124 | CH86: 251 | CI86: 251 | CJ86: 251 | CK86: 251 | CL86: 251 | CM86: 251 | CN86: 251 | CO86: 251 | CP86: 251 | CQ86: 251 | CR86: 251 | CS86: 251 | CT86: 382 | CU86: 382 | CV86: 382 | CW86: 382 | CX86: 382 | CY86: 382 | CZ86: 382 | DA86: 382 | DB86: 382 | DC86: 382 | DD86: 382 | DE86: 382 | DF86: 517 | DG86: 517 | DH86: 517 | DI86: 517 | DJ86: 517 | DK86: 517 | DL86: 517 | DM86: 517 | DN86: 517 | DO86: 517 | DP86: 517 | DQ86: 517 | DR86: 656 | DS86: 656 | DT86: 656 | DU86: 0 | DV86: 0 | DW86: 0 | DX86: 0 | DY86: 0 | DZ86: 0 | EA86: 0 | EB86: 0 | EC86: 0 | ED86: 0 | EE86: 17244
A87: 9. Brinkley Sargent Winginton Architects | B87: 8 | C87: 0 | D87: 0 | E87: 0 | F87: 0 | G87: 0 | H87: 0 | I87: 0 | J87: 0 | K87: 0 | L87: 0 | M87: 0 | N87: 0 | O87: 0 | P87: 0 | Q87: 0 | R87: 0 | S87: 0 | T87: 0 | U87: 0 | V87: 0 | W87: 0 | X87: 0 | Y87: 0 | Z87: 0 | AA87: 0 | AB87: 197 | AC87: 197 | AD87: 197 | AE87: 197 | AF87: 197 | AG87: 197 | AH87: 197 | AI87: 197 | AJ87: 197 | AK87: 197 | AL87: 197 | AM87: 197 | AN87: 400 | AO87: 400 | AP87: 400 | AQ87: 400 | AR87: 400 | AS87: 400 | AT87: 400 | AU87: 400 | AV87: 400 | AW87: 400 | AX87: 400 | AY87: 400 | AZ87: 609 | BA87: 609 | BB87: 609 | BC87: 609 | BD87: 609 | BE87: 609 | BF87: 609 | BG87: 609 | BH87: 609 | BI87: 609 | BJ87: 609 | BK87: 609 | BL87: 824 | BM87: 824 | BN87: 824 | BO87: 824 | BP87: 824 | BQ87: 824 | BR87: 824 | BS87: 824 | BT87: 824 | BU87: 824 | BV87: 824 | BW87: 824 | BX87: 0 | BY87: 0 | BZ87: 0 | CA87: 0 | CB87: 0 | CC87: 0 | CD87: 0 | CE87: 0 | CF87: 0 | CG87: 0 | CH87: 0 | CI87: 0 | CJ87: 228 | CK87: 228 | CL87: 228 | CM87: 228 | CN87: 228 | CO87: 228 | CP87: 228 | CQ87: 228 | CR87: 228 | CS87: 228 | CT87: 228 | CU87: 228 | CV87: 463 | CW87: 463 | CX87: 463 | CY87: 463 | CZ87: 463 | DA87: 463 | DB87: 463 | DC87: 463 | DD87: 463 | DE87: 463 | DF87: 463 | DG87: 463 | DH87: 705 | DI87: 705 | DJ87: 705 | DK87: 705 | DL87: 705 | DM87: 705 | DN87: 705 | DO87: 705 | DP87: 705 | DQ87: 705 | DR87: 705 | DS87: 705 | DT87: 955 | DU87: 955 | DV87: 955 | DW87: 955 | DX87: 955 | DY87: 955 | DZ87: 955 | EA87: 955 | EB87: 955 | EC87: 955 | ED87: 955 | EE87: 51614
A88: 10. Austin Prosthetics Center | B88: 9 | C88: 0 | D88: 0 | E88: 0 | F88: 0 | G88: 0 | H88: 0 | I88: 0 | J88: 0 | K88: 0 | L88: 0 | M88: 0 | N88: 0 | O88: 0 | P88: 0 | Q88: 0 | R88: 0 | S88: 0 | T88: 0 | U88: 0 | V88: 0 | W88: 0 | X88: 0 | Y88: 0 | Z88: 0 | AA88: 0 | AB88: 0 | AC88: 0 | AD88: 0 | AE88: 0 | AF88: 0 | AG88: 0 | AH88: 0 | AI88: 0 | AJ88: 0 | AK88: 0 | AL88: 0 | AM88: 0 | AN88: 0 | AO88: 0 | AP88: 0 | AQ88: 0 | AR88: 0 | AS88: 0 | AT88: 0 | AU88: 0 | AV88: 0 | AW88: 0 | AX88: 0 | AY88: 0 | AZ88: 0 | BA88: 0 | BB88: 0 | BC88: 0 | BD88: 0 | BE88: 0 | BF88: 0 | BG88: 0 | BH88: 0 | BI88: 0 | BJ88: 0 | BK88: 0 | BL88: 0 | BM88: 0 | BN88: 0 | BO88: 0 | BP88: 0 | BQ88: 0 | BR88: 0 | BS88: 0 | BT88: 0 | BU88: 0 | BV88: 0 | BW88: 0 | BX88: 0 | BY88: 0 | BZ88: 0 | CA88: 0 | CB88: 0 | CC88: 0 | CD88: 0 | CE88: 0 | CF88: 0 | CG88: 353 | CH88: 353 | CI88: 353 | CJ88: 353 | CK88: 353 | CL88: 353 | CM88: 353 | CN88: 353 | CO88: 353 | CP88: 353 | CQ88: 353 | CR88: 353 | CS88: 717 | CT88: 717 | CU88: 717 | CV88: 717 | CW88: 717 | CX88: 717 | CY88: 717 | CZ88: 717 | DA88: 717 | DB88: 717 | DC88: 717 | DD88: 717 | DE88: 1092 | DF88: 1092 | DG88: 1092 | DH88: 1092 | DI88: 1092 | DJ88: 1092 | DK88: 1092 | DL88: 1092 | DM88: 1092 | DN88: 1092 | DO88: 1092 | DP88: 1092 | DQ88: 1479 | DR88: 1479 | DS88: 1479 | DT88: 1479 | DU88: 1479 | DV88: 1479 | DW88: 1479 | DX88: 1479 | DY88: 1479 | DZ88: 1479 | EA88: 1479 | EB88: 1479 | EC88: 1876 | ED88: 1876 | EE88: 47455
A89: 11. Ignite Fitnez | B89: 10 | C89: 0 | D89: 0 | E89: 0 | F89: 0 | G89: 0 | H89: 0 | I89: 0 | J89: 0 | K89: 0 | L89: 0 | M89: 0 | N89: 0 | O89: 0 | P89: 0 | Q89: 0 | R89: 0 | S89: 0 | T89: 0 | U89: 0 | V89: 0 | W89: 0 | X89: 0 | Y89: 0 | Z89: 0 | AA89: 0 | AB89: 0 | AC89: 0 | AD89: 882 | AE89: 882 | AF89: 882 | AG89: 882 | AH89: 882 | AI89: 882 | AJ89: 882 | AK89: 882 | AL89: 882 | AM89: 882 | AN89: 882 | AO89: 882 | AP89: 1791 | AQ89: 1791 | AR89: 1791 | AS89: 1791 | AT89: 1791 | AU89: 1791 | AV89: 1791 | AW89: 1791 | AX89: 1791 | AY89: 1791 | AZ89: 1791 | BA89: 1791 | BB89: 2727 | BC89: 2727 | BD89: 2727 | BE89: 2727 | BF89: 2727 | BG89: 2727 | BH89: 2727 | BI89: 2727 | BJ89: 2727 | BK89: 2727 | BL89: 2727 | BM89: 2727 | BN89: 3691 | BO89: 3691 | BP89: 3691 | BQ89: 3691 | BR89: 3691 | BS89: 3691 | BT89: 3691 | BU89: 3691 | BV89: 3691 | BW89: 3691 | BX89: 3691 | BY89: 3691 | BZ89: 4684 | CA89: 4684 | CB89: 4684 | CC89: 4684 | CD89: 4684 | CE89: 4684 | CF89: 4684 | CG89: 4684 | CH89: 4684 | CI89: 4684 | CJ89: 4684 | CK89: 4684 | CL89: 5707 | CM89: 5707 | CN89: 5707 | CO89: 5707 | CP89: 5707 | CQ89: 5707 | CR89: 5707 | CS89: 5707 | CT89: 5707 | CU89: 5707 | CV89: 5707 | CW89: 5707 | CX89: 6760 | CY89: 6760 | CZ89: 6760 | DA89: 6760 | DB89: 6760 | DC89: 0 | DD89: 0 | DE89: 0 | DF89: 0 | DG89: 0 | DH89: 0 | DI89: 0 | DJ89: 0 | DK89: 0 | DL89: 0 | DM89: 0 | DN89: 0 | DO89: 0 | DP89: 0 | DQ89: 0 | DR89: 0 | DS89: 1118 | DT89: 1118 | DU89: 1118 | DV89: 1118 | DW89: 1118 | DX89: 1118 | DY89: 1118 | DZ89: 1118 | EA89: 1118 | EB89: 1118 | EC89: 1118 | ED89: 1118 | EE89: 281006
A90: Total Fixed Steps | C90: 0 | D90: 0 | E90: 0 | F90: 0 | G90: 0 | H90: 0 | I90: 0 | J90: 0 | K90: 500 | L90: 500 | M90: 500 | N90: 500 | O90: 977 | P90: 977 | Q90: 977 | R90: 977 | S90: 977 | T90: 977 | U90: 977 | V90: 1626 | W90: 2140 | X90: 2140 | Y90: 2140 | Z90: 2140 | AA90: 2630 | AB90: 3280 | AC90: 3280 | AD90: 4162 | AE90: 4162 | AF90: 4162 | AG90: 4162 | AH90: 4831 | AI90: 5359 | AJ90: 5593 | AK90: 5593 | AL90: 5593 | AM90: 6331 | AN90: 7000 | AO90: 7000 | AP90: 7908 | AQ90: 7908 | AR90: 8371 | AS90: 8371 | AT90: 9059 | AU90: 9602 | AV90: 9844 | AW90: 9844 | AX90: 9844 | AY90: 10603 | AZ90: 11292 | BA90: 11292 | BB90: 12228 | BC90: 12228 | BD90: 12704 | BE90: 12704 | BF90: 13414 | BG90: 13971 | BH90: 14220 | BI90: 14220 | BJ90: 14220 | BK90: 12360 | BL90: 13069 | BM90: 13069 | BN90: 14033 | BO90: 14033 | BP90: 14524 | BQ90: 14524 | BR90: 15255 | BS90: 15255 | BT90: 15511 | BU90: 12064 | BV90: 12187 | BW90: 12993 | BX90: 12679 | BY90: 13358 | BZ90: 14351 | CA90: 11950 | CB90: 12455 | CC90: 12455 | CD90: 12455 | CE90: 12455 | CF90: 12719 | CG90: 13072 | CH90: 13200 | CI90: 9910 | CJ90: 10138 | CK90: 10838 | CL90: 10628 | CM90: 10628 | CN90: 11148 | CO90: 11672 | CP90: 11672 | CQ90: 9219 | CR90: 9219 | CS90: 9583 | CT90: 9714 | CU90: 10512 | CV90: 10747 | CW90: 12334 | CX90: 13388 | CY90: 13388 | CZ90: 13657 | DA90: 14197 | DB90: 14197 | DC90: 7436 | DD90: 7436 | DE90: 8347 | DF90: 8482 | DG90: 9305 | DH90: 9547 | DI90: 11181 | DJ90: 11181 | DK90: 11181 | DL90: 11459 | DM90: 12015 | DN90: 12015 | DO90: 12015 | DP90: 12015 | DQ90: 12953 | DR90: 13092 | DS90: 15057 | DT90: 15306 | DU90: 16334 | DV90: 16334 | DW90: 16334 | DX90: 13012 | DY90: 13585 | DZ90: 13585 | EA90: 13585 | EB90: 13585 | EC90: 14551 | ED90: 14551 | EE90: 1218299
A92: Recoveries
A93: 1. Kitu Life, Inc. | B93: 1 | C93: 8018 | D93: 8018 | E93: 8018 | F93: 8018 | G93: 8018 | H93: 8018 | I93: 8018 | J93: 8018 | K93: 8018 | L93: 8018 | M93: 8018 | N93: 8018 | O93: 8432 | P93: 8432 | Q93: 8432 | R93: 8432 | S93: 8432 | T93: 8432 | U93: 8432 | V93: 8432 | W93: 8432 | X93: 8432 | Y93: 8432 | Z93: 8432 | AA93: 8800 | AB93: 8800 | AC93: 8800 | AD93: 8800 | AE93: 8800 | AF93: 8800 | AG93: 8800 | AH93: 8800 | AI93: 8800 | AJ93: 8800 | AK93: 8800 | AL93: 8800 | AM93: 9089 | AN93: 9089 | AO93: 9089 | AP93: 9089 | AQ93: 9089 | AR93: 9089 | AS93: 9089 | AT93: 9089 | AU93: 9089 | AV93: 9089 | AW93: 9089 | AX93: 9089 | AY93: 9358 | AZ93: 9358 | BA93: 9358 | BB93: 9358 | BC93: 9358 | BD93: 9358 | BE93: 9358 | BF93: 9358 | BG93: 9358 | BH93: 9358 | BI93: 9358 | BJ93: 9358 | BK93: 0 | BL93: 0 | BM93: 9580 | BN93: 9580 | BO93: 9580 | BP93: 9580 | BQ93: 9580 | BR93: 9580 | BS93: 9580 | BT93: 9580 | BU93: 9580 | BV93: 9580 | BW93: 9893 | BX93: 9893 | BY93: 9893 | BZ93: 9893 | CA93: 9893 | CB93: 9893 | CC93: 9893 | CD93: 9893 | CE93: 9893 | CF93: 9893 | CG93: 9893 | CH93: 9893 | CI93: 10156 | CJ93: 10156 | CK93: 10156 | CL93: 10156 | CM93: 10156 | CN93: 10156 | CO93: 10156 | CP93: 10156 | CQ93: 10156 | CR93: 10156 | CS93: 10156 | CT93: 10156 | CU93: 10452 | CV93: 10452 | CW93: 10452 | CX93: 10452 | CY93: 10452 | CZ93: 10452 | DA93: 10452 | DB93: 10452 | DC93: 10452 | DD93: 10452 | DE93: 10452 | DF93: 10452 | DG93: 10821 | DH93: 10821 | DI93: 10821 | DJ93: 10821 | DK93: 10821 | DL93: 10821 | DM93: 10821 | DN93: 10821 | DO93: 10821 | DP93: 10821 | DQ93: 10821 | DR93: 10821 | DS93: 11130 | DT93: 11130 | DU93: 11130 | DV93: 11130 | DW93: 11130 | DX93: 0 | DY93: 0 | DZ93: 11130 | EA93: 11130 | EB93: 11130 | EC93: 11130 | ED93: 11130 | EE93: 1227339
A94: 2. VACANT | B94: 2 | C94: 0 | D94: 0 | E94: 0 | F94: 0 | G94: 0 | H94: 0 | I94: 0 | J94: 8882 | K94: 8882 | L94: 8882 | M94: 8882 | N94: 8882 | O94: 9341 | P94: 9341 | Q94: 9341 | R94: 9341 | S94: 9341 | T94: 9341 | U94: 9341 | V94: 9341 | W94: 9341 | X94: 9341 | Y94: 9341 | Z94: 9341 | AA94: 9748 | AB94: 9748 | AC94: 9748 | AD94: 9748 | AE94: 9748 | AF94: 9748 | AG94: 9748 | AH94: 9748 | AI94: 9748 | AJ94: 9748 | AK94: 9748 | AL94: 9748 | AM94: 10068 | AN94: 10068 | AO94: 10068 | AP94: 10068 | AQ94: 10068 | AR94: 10068 | AS94: 10068 | AT94: 10068 | AU94: 10068 | AV94: 10068 | AW94: 10068 | AX94: 10068 | AY94: 10366 | AZ94: 10366 | BA94: 10366 | BB94: 10366 | BC94: 10366 | BD94: 10366 | BE94: 10366 | BF94: 10366 | BG94: 10366 | BH94: 10366 | BI94: 10366 | BJ94: 10366 | BK94: 10613 | BL94: 10613 | BM94: 10613 | BN94: 10613 | BO94: 10613 | BP94: 10613 | BQ94: 10613 | BR94: 10613 | BS94: 10613 | BT94: 10613 | BU94: 0 | BV94: 0 | BW94: 10959 | BX94: 10959 | BY94: 10959 | BZ94: 10959 | CA94: 10959 | CB94: 10959 | CC94: 10959 | CD94: 10959 | CE94: 10959 | CF94: 10959 | CG94: 10959 | CH94: 10959 | CI94: 11250 | CJ94: 11250 | CK94: 11250 | CL94: 11250 | CM94: 11250 | CN94: 11250 | CO94: 11250 | CP94: 11250 | CQ94: 11250 | CR94: 11250 | CS94: 11250 | CT94: 11250 | CU94: 11578 | CV94: 11578 | CW94: 11578 | CX94: 11578 | CY94: 11578 | CZ94: 11578 | DA94: 11578 | DB94: 11578 | DC94: 11578 | DD94: 11578 | DE94: 11578 | DF94: 11578 | DG94: 11987 | DH94: 11987 | DI94: 11987 | DJ94: 11987 | DK94: 11987 | DL94: 11987 | DM94: 11987 | DN94: 11987 | DO94: 11987 | DP94: 11987 | DQ94: 11987 | DR94: 11987 | DS94: 12329 | DT94: 12329 | DU94: 12329 | DV94: 12329 | DW94: 12329 | DX94: 12329 | DY94: 12329 | DZ94: 12329 | EA94: 12329 | EB94: 12329 | EC94: 12329 | ED94: 12329 | EE94: 1322047
A95: 3. Saatva | B95: 3 | C95: 5950 | D95: 5950 | E95: 5950 | F95: 5950 | G95: 5950 | H95: 5950 | I95: 5950 | J95: 5950 | K95: 5950 | L95: 5950 | M95: 5950 | N95: 5950 | O95: 6258 | P95: 6258 | Q95: 6258 | R95: 6258 | S95: 6258 | T95: 6258 | U95: 6258 | V95: 6258 | W95: 6258 | X95: 6258 | Y95: 6258 | Z95: 6258 | AA95: 6530 | AB95: 6530 | AC95: 6530 | AD95: 0 | AE95: 0 | AF95: 6540 | AG95: 6540 | AH95: 6540 | AI95: 6540 | AJ95: 6540 | AK95: 6540 | AL95: 6540 | AM95: 6755 | AN95: 6755 | AO95: 6755 | AP95: 6755 | AQ95: 6755 | AR95: 6755 | AS95: 6755 | AT95: 6755 | AU95: 6755 | AV95: 6755 | AW95: 6755 | AX95: 6755 | AY95: 6955 | AZ95: 6955 | BA95: 6955 | BB95: 6955 | BC95: 6955 | BD95: 6955 | BE95: 6955 | BF95: 6955 | BG95: 6955 | BH95: 6955 | BI95: 6955 | BJ95: 6955 | BK95: 7120 | BL95: 7120 | BM95: 7120 | BN95: 7120 | BO95: 7120 | BP95: 7120 | BQ95: 7120 | BR95: 7120 | BS95: 7120 | BT95: 7120 | BU95: 7120 | BV95: 7120 | BW95: 7353 | BX95: 7353 | BY95: 7353 | BZ95: 7353 | CA95: 7353 | CB95: 7353 | CC95: 7353 | CD95: 7353 | CE95: 7353 | CF95: 7353 | CG95: 7353 | CH95: 7353 | CI95: 7548 | CJ95: 7548 | CK95: 7548 | CL95: 7548 | CM95: 7548 | CN95: 7548 | CO95: 7548 | CP95: 7548 | CQ95: 0 | CR95: 0 | CS95: 7548 | CT95: 7548 | CU95: 7768 | CV95: 7768 | CW95: 7768 | CX95: 7768 | CY95: 7768 | CZ95: 7768 | DA95: 7768 | DB95: 7768 | DC95: 7768 | DD95: 7768 | DE95: 7768 | DF95: 7768 | DG95: 8043 | DH95: 8043 | DI95: 8043 | DJ95: 8043 | DK95: 8043 | DL95: 8043 | DM95: 8043 | DN95: 8043 | DO95: 8043 | DP95: 8043 | DQ95: 8043 | DR95: 8043 | DS95: 8272 | DT95: 8272 | DU95: 8272 | DV95: 8272 | DW95: 8272 | DX95: 8272 | DY95: 8272 | DZ95: 8272 | EA95: 8272 | EB95: 8272 | EC95: 8272 | ED95: 8272 | EE95: 914552
A96: 4. Fuse Architecture Studio | B96: 4 | C96: 2975 | D96: 2975 | E96: 2975 | F96: 2975 | G96: 2975 | H96: 2975 | I96: 2975 | J96: 2975 | K96: 2975 | L96: 2975 | M96: 2975 | N96: 2975 | O96: 3129 | P96: 3129 | Q96: 3129 | R96: 3129 | S96: 3129 | T96: 3129 | U96: 3129 | V96: 0 | W96: 0 | X96: 3278 | Y96: 3278 | Z96: 3278 | AA96: 3421 | AB96: 3421 | AC96: 3421 | AD96: 3421 | AE96: 3421 | AF96: 3421 | AG96: 3421 | AH96: 3421 | AI96: 3421 | AJ96: 3421 | AK96: 3421 | AL96: 3421 | AM96: 3533 | AN96: 3533 | AO96: 3533 | AP96: 3533 | AQ96: 3533 | AR96: 3533 | AS96: 3533 | AT96: 3533 | AU96: 3533 | AV96: 3533 | AW96: 3533 | AX96: 3533 | AY96: 3638 | AZ96: 3638 | BA96: 3638 | BB96: 3638 | BC96: 3638 | BD96: 3638 | BE96: 3638 | BF96: 3638 | BG96: 3638 | BH96: 3638 | BI96: 3638 | BJ96: 3638 | BK96: 3724 | BL96: 3724 | BM96: 3724 | BN96: 3724 | BO96: 3724 | BP96: 3724 | BQ96: 3724 | BR96: 3724 | BS96: 3724 | BT96: 3724 | BU96: 3724 | BV96: 3724 | BW96: 3846 | BX96: 3846 | BY96: 3846 | BZ96: 3846 | CA96: 3846 | CB96: 3846 | CC96: 3846 | CD96: 3846 | CE96: 3846 | CF96: 3846 | CG96: 3846 | CH96: 3846 | CI96: 0 | CJ96: 0 | CK96: 3948 | CL96: 3948 | CM96: 3948 | CN96: 3948 | CO96: 3948 | CP96: 3948 | CQ96: 3948 | CR96: 3948 | CS96: 3948 | CT96: 3948 | CU96: 4063 | CV96: 4063 | CW96: 4063 | CX96: 4063 | CY96: 4063 | CZ96: 4063 | DA96: 4063 | DB96: 4063 | DC96: 4063 | DD96: 4063 | DE96: 4063 | DF96: 4063 | DG96: 4207 | DH96: 4207 | DI96: 4207 | DJ96: 4207 | DK96: 4207 | DL96: 4207 | DM96: 4207 | DN96: 4207 | DO96: 4207 | DP96: 4207 | DQ96: 4207 | DR96: 4207 | DS96: 4327 | DT96: 4327 | DU96: 4327 | DV96: 4327 | DW96: 4327 | DX96: 4327 | DY96: 4327 | DZ96: 4327 | EA96: 4327 | EB96: 4327 | EC96: 4327 | ED96: 4327 | EE96: 476026
A97: 5. Made In (sublessee to Geek Powered Studios) | B97: 5 | C97: 5950 | D97: 5950 | E97: 5950 | F97: 5950 | G97: 5950 | H97: 5950 | I97: 5950 | J97: 0 | K97: 0 | L97: 0 | M97: 0 | N97: 0 | O97: 0 | P97: 6317 | Q97: 6317 | R97: 6317 | S97: 6317 | T97: 6317 | U97: 6317 | V97: 6317 | W97: 6317 | X97: 6317 | Y97: 6317 | Z97: 6317 | AA97: 6592 | AB97: 6592 | AC97: 6592 | AD97: 6592 | AE97: 6592 | AF97: 6592 | AG97: 6592 | AH97: 6592 | AI97: 6592 | AJ97: 6592 | AK97: 6592 | AL97: 6592 | AM97: 6809 | AN97: 6809 | AO97: 6809 | AP97: 6809 | AQ97: 6809 | AR97: 6809 | AS97: 6809 | AT97: 6809 | AU97: 6809 | AV97: 6809 | AW97: 6809 | AX97: 6809 | AY97: 7011 | AZ97: 7011 | BA97: 7011 | BB97: 7011 | BC97: 7011 | BD97: 7011 | BE97: 7011 | BF97: 7011 | BG97: 7011 | BH97: 7011 | BI97: 7011 | BJ97: 7011 | BK97: 7177 | BL97: 7177 | BM97: 7177 | BN97: 7177 | BO97: 7177 | BP97: 7177 | BQ97: 7177 | BR97: 7177 | BS97: 7177 | BT97: 7177 | BU97: 7177 | BV97: 7177 | BW97: 7412 | BX97: 7412 | BY97: 7412 | BZ97: 7412 | CA97: 0 | CB97: 0 | CC97: 7412 | CD97: 7412 | CE97: 7412 | CF97: 7412 | CG97: 7412 | CH97: 7412 | CI97: 7609 | CJ97: 7609 | CK97: 7609 | CL97: 7609 | CM97: 7609 | CN97: 7609 | CO97: 7609 | CP97: 7609 | CQ97: 7609 | CR97: 7609 | CS97: 7609 | CT97: 7609 | CU97: 7830 | CV97: 7830 | CW97: 7830 | CX97: 7830 | CY97: 7830 | CZ97: 7830 | DA97: 7830 | DB97: 7830 | DC97: 7830 | DD97: 7830 | DE97: 7830 | DF97: 7830 | DG97: 8107 | DH97: 8107 | DI97: 8107 | DJ97: 8107 | DK97: 8107 | DL97: 8107 | DM97: 8107 | DN97: 8107 | DO97: 8107 | DP97: 8107 | DQ97: 8107 | DR97: 8107 | DS97: 8338 | DT97: 8338 | DU97: 8338 | DV97: 8338 | DW97: 8338 | DX97: 8338 | DY97: 8338 | DZ97: 8338 | EA97: 8338 | EB97: 8338 | EC97: 8338 | ED97: 8338 | EE97: 898940
A98: 6. Elmo 35, LLC | B98: 6 | C98: 6515 | D98: 6515 | E98: 6515 | F98: 6515 | G98: 6515 | H98: 6515 | I98: 6515 | J98: 6515 | K98: 6515 | L98: 6515 | M98: 6515 | N98: 6515 | O98: 6851 | P98: 6851 | Q98: 6851 | R98: 6851 | S98: 6851 | T98: 6851 | U98: 6851 | V98: 6851 | W98: 6851 | X98: 6851 | Y98: 6851 | Z98: 6851 | AA98: 7150 | AB98: 7150 | AC98: 7150 | AD98: 7150 | AE98: 7150 | AF98: 7150 | AG98: 7150 | AH98: 7150 | AI98: 7150 | AJ98: 7150 | AK98: 7150 | AL98: 7150 | AM98: 7385 | AN98: 7385 | AO98: 7385 | AP98: 7385 | AQ98: 7385 | AR98: 7385 | AS98: 7385 | AT98: 7385 | AU98: 7385 | AV98: 7385 | AW98: 7385 | AX98: 7385 | AY98: 7603 | AZ98: 7603 | BA98: 7603 | BB98: 7603 | BC98: 7603 | BD98: 7603 | BE98: 7603 | BF98: 7603 | BG98: 7603 | BH98: 7603 | BI98: 7603 | BJ98: 7603 | BK98: 7784 | BL98: 7784 | BM98: 7784 | BN98: 7784 | BO98: 7784 | BP98: 7784 | BQ98: 7784 | BR98: 7784 | BS98: 7784 | BT98: 7784 | BU98: 7784 | BV98: 7784 | BW98: 8038 | BX98: 8038 | BY98: 8038 | BZ98: 8038 | CA98: 8038 | CB98: 8038 | CC98: 8038 | CD98: 8038 | CE98: 8038 | CF98: 8038 | CG98: 8038 | CH98: 8038 | CI98: 0 | CJ98: 0 | CK98: 8252 | CL98: 8252 | CM98: 8252 | CN98: 8252 | CO98: 8252 | CP98: 8252 | CQ98: 8252 | CR98: 8252 | CS98: 8252 | CT98: 8252 | CU98: 8492 | CV98: 8492 | CW98: 8492 | CX98: 8492 | CY98: 8492 | CZ98: 8492 | DA98: 8492 | DB98: 8492 | DC98: 8492 | DD98: 8492 | DE98: 8492 | DF98: 8492 | DG98: 8792 | DH98: 8792 | DI98: 8792 | DJ98: 8792 | DK98: 8792 | DL98: 8792 | DM98: 8792 | DN98: 8792 | DO98: 8792 | DP98: 8792 | DQ98: 8792 | DR98: 8792 | DS98: 9043 | DT98: 9043 | DU98: 9043 | DV98: 9043 | DW98: 9043 | DX98: 9043 | DY98: 9043 | DZ98: 9043 | EA98: 9043 | EB98: 9043 | EC98: 9043 | ED98: 9043 | EE98: 1014354
A99: 7. Trihydro Corporation | B99: 7 | C99: 2975 | D99: 2975 | E99: 2975 | F99: 2975 | G99: 2975 | H99: 2975 | I99: 2975 | J99: 2975 | K99: 2975 | L99: 2975 | M99: 2975 | N99: 2975 | O99: 3129 | P99: 3129 | Q99: 3129 | R99: 3129 | S99: 3129 | T99: 3129 | U99: 0 | V99: 0 | W99: 0 | X99: 0 | Y99: 0 | Z99: 0 | AA99: 3286 | AB99: 3286 | AC99: 3286 | AD99: 3286 | AE99: 3286 | AF99: 3286 | AG99: 3286 | AH99: 3286 | AI99: 3286 | AJ99: 3286 | AK99: 3286 | AL99: 3286 | AM99: 3394 | AN99: 3394 | AO99: 3394 | AP99: 3394 | AQ99: 3394 | AR99: 3394 | AS99: 3394 | AT99: 3394 | AU99: 3394 | AV99: 3394 | AW99: 3394 | AX99: 3394 | AY99: 3494 | AZ99: 3494 | BA99: 3494 | BB99: 3494 | BC99: 3494 | BD99: 3494 | BE99: 3494 | BF99: 3494 | BG99: 3494 | BH99: 3494 | BI99: 3494 | BJ99: 3494 | BK99: 3577 | BL99: 3577 | BM99: 3577 | BN99: 3577 | BO99: 3577 | BP99: 3577 | BQ99: 3577 | BR99: 3577 | BS99: 3577 | BT99: 3577 | BU99: 3577 | BV99: 3577 | BW99: 3694 | BX99: 3694 | BY99: 3694 | BZ99: 3694 | CA99: 3694 | CB99: 3694 | CC99: 3694 | CD99: 3694 | CE99: 3694 | CF99: 3694 | CG99: 3694 | CH99: 3694 | CI99: 3792 | CJ99: 3792 | CK99: 3792 | CL99: 0 | CM99: 0 | CN99: 3792 | CO99: 3792 | CP99: 3792 | CQ99: 3792 | CR99: 3792 | CS99: 3792 | CT99: 3792 | CU99: 3903 | CV99: 3903 | CW99: 3903 | CX99: 3903 | CY99: 3903 | CZ99: 3903 | DA99: 3903 | DB99: 3903 | DC99: 3903 | DD99: 3903 | DE99: 3903 | DF99: 3903 | DG99: 4041 | DH99: 4041 | DI99: 4041 | DJ99: 4041 | DK99: 4041 | DL99: 4041 | DM99: 4041 | DN99: 4041 | DO99: 4041 | DP99: 4041 | DQ99: 4041 | DR99: 4041 | DS99: 4156 | DT99: 4156 | DU99: 4156 | DV99: 4156 | DW99: 4156 | DX99: 4156 | DY99: 4156 | DZ99: 4156 | EA99: 4156 | EB99: 4156 | EC99: 4156 | ED99: 4156 | EE99: 446943
A100: 8. Urban ATX | B100: 07A | C100: 1488 | D100: 1488 | E100: 1488 | F100: 1488 | G100: 1488 | H100: 1488 | I100: 1488 | J100: 1488 | K100: 1488 | L100: 1488 | M100: 1488 | N100: 1488 | O100: 1564 | P100: 1564 | Q100: 1564 | R100: 1564 | S100: 1564 | T100: 1564 | U100: 1564 | V100: 1564 | W100: 1564 | X100: 1564 | Y100: 1564 | Z100: 1564 | AA100: 1633 | AB100: 1633 | AC100: 1633 | AD100: 1633 | AE100: 1633 | AF100: 1633 | AG100: 1633 | AH100: 1633 | AI100: 1633 | AJ100: 1633 | AK100: 1633 | AL100: 1633 | AM100: 1686 | AN100: 1686 | AO100: 1686 | AP100: 1686 | AQ100: 1686 | AR100: 1686 | AS100: 1686 | AT100: 1686 | AU100: 1686 | AV100: 1686 | AW100: 1686 | AX100: 1686 | AY100: 1736 | AZ100: 1736 | BA100: 1736 | BB100: 1736 | BC100: 1736 | BD100: 1736 | BE100: 1736 | BF100: 1736 | BG100: 1736 | BH100: 0 | BI100: 0 | BJ100: 1752 | BK100: 1794 | BL100: 1794 | BM100: 1794 | BN100: 1794 | BO100: 1794 | BP100: 1794 | BQ100: 1794 | BR100: 1794 | BS100: 1794 | BT100: 1794 | BU100: 1794 | BV100: 1794 | BW100: 1853 | BX100: 1853 | BY100: 1853 | BZ100: 1853 | CA100: 1853 | CB100: 1853 | CC100: 1853 | CD100: 1853 | CE100: 1853 | CF100: 1853 | CG100: 1853 | CH100: 1853 | CI100: 1902 | CJ100: 1902 | CK100: 1902 | CL100: 1902 | CM100: 1902 | CN100: 1902 | CO100: 1902 | CP100: 1902 | CQ100: 1902 | CR100: 1902 | CS100: 1902 | CT100: 1902 | CU100: 1957 | CV100: 1957 | CW100: 1957 | CX100: 1957 | CY100: 1957 | CZ100: 1957 | DA100: 1957 | DB100: 1957 | DC100: 1957 | DD100: 1957 | DE100: 1957 | DF100: 1957 | DG100: 2026 | DH100: 2026 | DI100: 2026 | DJ100: 2026 | DK100: 2026 | DL100: 2026 | DM100: 2026 | DN100: 2026 | DO100: 2026 | DP100: 2026 | DQ100: 2026 | DR100: 2026 | DS100: 2084 | DT100: 2084 | DU100: 0 | DV100: 0 | DW100: 2084 | DX100: 2084 | DY100: 2084 | DZ100: 2084 | EA100: 2084 | EB100: 2084 | EC100: 2084 | ED100: 2084 | EE100: 229056
A101: 9. Brinkley Sargent Winginton Architects | B101: 8 | C101: 2975 | D101: 2975 | E101: 2975 | F101: 2975 | G101: 2975 | H101: 2975 | I101: 2975 | J101: 2975 | K101: 2975 | L101: 2975 | M101: 2975 | N101: 2975 | O101: 3129 | P101: 3159 | Q101: 3159 | R101: 3159 | S101: 3159 | T101: 3159 | U101: 3159 | V101: 3159 | W101: 3159 | X101: 3159 | Y101: 3159 | Z101: 3159 | AA101: 3297 | AB101: 3297 | AC101: 3297 | AD101: 3297 | AE101: 3297 | AF101: 3297 | AG101: 3297 | AH101: 3297 | AI101: 3297 | AJ101: 3297 | AK101: 3297 | AL101: 3297 | AM101: 3405 | AN101: 3405 | AO101: 3405 | AP101: 3405 | AQ101: 3405 | AR101: 3405 | AS101: 3405 | AT101: 3405 | AU101: 3405 | AV101: 3405 | AW101: 3405 | AX101: 3405 | AY101: 3506 | AZ101: 3506 | BA101: 3506 | BB101: 3506 | BC101: 3506 | BD101: 3506 | BE101: 3506 | BF101: 3506 | BG101: 3506 | BH101: 3506 | BI101: 3506 | BJ101: 3506 | BK101: 3589 | BL101: 3589 | BM101: 3589 | BN101: 3589 | BO101: 3589 | BP101: 3589 | BQ101: 3589 | BR101: 3589 | BS101: 3589 | BT101: 3589 | BU101: 3589 | BV101: 3589 | BW101: 3707 | BX101: 3707 | BY101: 3707 | BZ101: 3707 | CA101: 3707 | CB101: 3707 | CC101: 3707 | CD101: 3707 | CE101: 3707 | CF101: 3707 | CG101: 3707 | CH101: 3707 | CI101: 3805 | CJ101: 3805 | CK101: 3805 | CL101: 3805 | CM101: 3805 | CN101: 3805 | CO101: 3805 | CP101: 3805 | CQ101: 3805 | CR101: 3805 | CS101: 3805 | CT101: 3805 | CU101: 3916 | CV101: 3916 | CW101: 3916 | CX101: 3916 | CY101: 3916 | CZ101: 3916 | DA101: 3916 | DB101: 3916 | DC101: 3916 | DD101: 3916 | DE101: 3916 | DF101: 3916 | DG101: 4054 | DH101: 4054 | DI101: 4054 | DJ101: 4054 | DK101: 4054 | DL101: 4054 | DM101: 4054 | DN101: 4054 | DO101: 4054 | DP101: 4054 | DQ101: 4054 | DR101: 4054 | DS101: 4170 | DT101: 4170 | DU101: 4170 | DV101: 4170 | DW101: 4170 | DX101: 4170 | DY101: 4170 | DZ101: 4170 | EA101: 4170 | EB101: 4170 | EC101: 4170 | ED101: 4170 | EE101: 474958
A102: 10. Austin Prosthetics Center | B102: 9 | C102: 3967 | D102: 3967 | E102: 3967 | F102: 3967 | G102: 3967 | H102: 3967 | I102: 3967 | J102: 3967 | K102: 3967 | L102: 3967 | M102: 3967 | N102: 3967 | O102: 4172 | P102: 4172 | Q102: 4172 | R102: 4172 | S102: 4172 | T102: 4172 | U102: 4172 | V102: 4172 | W102: 4172 | X102: 4172 | Y102: 4172 | Z102: 4172 | AA102: 4354 | AB102: 4354 | AC102: 4354 | AD102: 4354 | AE102: 4354 | AF102: 4354 | AG102: 4354 | AH102: 4354 | AI102: 4354 | AJ102: 4354 | AK102: 4354 | AL102: 4354 | AM102: 4497 | AN102: 4497 | AO102: 4497 | AP102: 4497 | AQ102: 4497 | AR102: 4497 | AS102: 4497 | AT102: 4497 | AU102: 4497 | AV102: 4497 | AW102: 4497 | AX102: 4497 | AY102: 4630 | AZ102: 4630 | BA102: 4630 | BB102: 4630 | BC102: 4630 | BD102: 4630 | BE102: 4630 | BF102: 4630 | BG102: 4630 | BH102: 4630 | BI102: 4630 | BJ102: 4630 | BK102: 4740 | BL102: 4740 | BM102: 4740 | BN102: 4740 | BO102: 4740 | BP102: 4740 | BQ102: 4740 | BR102: 4740 | BS102: 0 | BT102: 0 | BU102: 4983 | BV102: 4983 | BW102: 5146 | BX102: 5146 | BY102: 5146 | BZ102: 5146 | CA102: 5146 | CB102: 5146 | CC102: 5146 | CD102: 5146 | CE102: 5146 | CF102: 5146 | CG102: 5146 | CH102: 5146 | CI102: 5282 | CJ102: 5282 | CK102: 5282 | CL102: 5282 | CM102: 5282 | CN102: 5282 | CO102: 5282 | CP102: 5282 | CQ102: 5282 | CR102: 5282 | CS102: 5282 | CT102: 5282 | CU102: 5436 | CV102: 5436 | CW102: 5436 | CX102: 5436 | CY102: 5436 | CZ102: 5436 | DA102: 5436 | DB102: 5436 | DC102: 5436 | DD102: 5436 | DE102: 5436 | DF102: 5436 | DG102: 5628 | DH102: 5628 | DI102: 5628 | DJ102: 5628 | DK102: 5628 | DL102: 5628 | DM102: 5628 | DN102: 5628 | DO102: 5628 | DP102: 5628 | DQ102: 5628 | DR102: 5628 | DS102: 5789 | DT102: 5789 | DU102: 5789 | DV102: 5789 | DW102: 5789 | DX102: 5789 | DY102: 5789 | DZ102: 5789 | EA102: 5789 | EB102: 5789 | EC102: 5789 | ED102: 5789 | EE102: 634676
A103: 11. Ignite Fitnez | B103: 10 | C103: 0 | D103: 0 | E103: 0 | F103: 0 | G103: 0 | H103: 0 | I103: 0 | J103: 0 | K103: 0 | L103: 0 | M103: 0 | N103: 0 | O103: 0 | P103: 0 | Q103: 0 | R103: 12322 | S103: 12322 | T103: 12322 | U103: 12322 | V103: 12322 | W103: 12322 | X103: 12322 | Y103: 12322 | Z103: 12322 | AA103: 12859 | AB103: 12859 | AC103: 12859 | AD103: 12859 | AE103: 12859 | AF103: 12859 | AG103: 12859 | AH103: 12859 | AI103: 12859 | AJ103: 12859 | AK103: 12859 | AL103: 12859 | AM103: 13282 | AN103: 13282 | AO103: 13282 | AP103: 13282 | AQ103: 13282 | AR103: 13282 | AS103: 13282 | AT103: 13282 | AU103: 13282 | AV103: 13282 | AW103: 13282 | AX103: 13282 | AY103: 13675 | AZ103: 13675 | BA103: 13675 | BB103: 13675 | BC103: 13675 | BD103: 13675 | BE103: 13675 | BF103: 13675 | BG103: 13675 | BH103: 13675 | BI103: 13675 | BJ103: 13675 | BK103: 14000 | BL103: 14000 | BM103: 14000 | BN103: 14000 | BO103: 14000 | BP103: 14000 | BQ103: 14000 | BR103: 14000 | BS103: 14000 | BT103: 14000 | BU103: 14000 | BV103: 14000 | BW103: 14458 | BX103: 14458 | BY103: 14458 | BZ103: 14458 | CA103: 14458 | CB103: 14458 | CC103: 14458 | CD103: 14458 | CE103: 14458 | CF103: 14458 | CG103: 14458 | CH103: 14458 | CI103: 14842 | CJ103: 14842 | CK103: 14842 | CL103: 14842 | CM103: 14842 | CN103: 14842 | CO103: 14842 | CP103: 14842 | CQ103: 14842 | CR103: 14842 | CS103: 14842 | CT103: 14842 | CU103: 15274 | CV103: 15274 | CW103: 15274 | CX103: 15274 | CY103: 15274 | CZ103: 15274 | DA103: 15274 | DB103: 15274 | DC103: 0 | DD103: 0 | DE103: 0 | DF103: 0 | DG103: 15813 | DH103: 15813 | DI103: 15813 | DJ103: 15813 | DK103: 15813 | DL103: 15813 | DM103: 15813 | DN103: 15813 | DO103: 15813 | DP103: 15813 | DQ103: 15813 | DR103: 15813 | DS103: 16265 | DT103: 16265 | DU103: 16265 | DV103: 16265 | DW103: 16265 | DX103: 16265 | DY103: 16265 | DZ103: 16265 | EA103: 16265 | EB103: 16265 | EC103: 16265 | ED103: 16265 | EE103: 1615432
A104: Total Recoveries | C104: 40813 | D104: 40813 | E104: 40813 | F104: 40813 | G104: 40813 | H104: 40813 | I104: 40813 | J104: 43744 | K104: 43744 | L104: 43744 | M104: 43744 | N104: 43744 | O104: 46005 | P104: 52352 | Q104: 52352 | R104: 64674 | S104: 64674 | T104: 64674 | U104: 61546 | V104: 58417 | W104: 58417 | X104: 61695 | Y104: 61695 | Z104: 61695 | AA104: 67668 | AB104: 67668 | AC104: 67668 | AD104: 61138 | AE104: 61138 | AF104: 67678 | AG104: 67678 | AH104: 67678 | AI104: 67678 | AJ104: 67678 | AK104: 67678 | AL104: 67678 | AM104: 69904 | AN104: 69904 | AO104: 69904 | AP104: 69904 | AQ104: 69904 | AR104: 69904 | AS104: 69904 | AT104: 69904 | AU104: 69904 | AV104: 69904 | AW104: 69904 | AX104: 69904 | AY104: 71973 | AZ104: 71973 | BA104: 71973 | BB104: 71973 | BC104: 71973 | BD104: 71973 | BE104: 71973 | BF104: 71973 | BG104: 71973 | BH104: 70237 | BI104: 70237 | BJ104: 71989 | BK104: 64120 | BL104: 64120 | BM104: 73700 | BN104: 73700 | BO104: 73700 | BP104: 73700 | BQ104: 73700 | BR104: 73700 | BS104: 68960 | BT104: 68960 | BU104: 63330 | BV104: 63330 | BW104: 76359 | BX104: 76359 | BY104: 76359 | BZ104: 76359 | CA104: 68947 | CB104: 68947 | CC104: 76359 | CD104: 76359 | CE104: 76359 | CF104: 76359 | CG104: 76359 | CH104: 76359 | CI104: 66186 | CJ104: 66186 | CK104: 78386 | CL104: 74594 | CM104: 74594 | CN104: 78386 | CO104: 78386 | CP104: 78386 | CQ104: 70838 | CR104: 70838 | CS104: 78386 | CT104: 78386 | CU104: 80670 | CV104: 80670 | CW104: 80670 | CX104: 80670 | CY104: 80670 | CZ104: 80670 | DA104: 80670 | DB104: 80670 | DC104: 65396 | DD104: 65396 | DE104: 65396 | DF104: 65396 | DG104: 83518 | DH104: 83518 | DI104: 83518 | DJ104: 83518 | DK104: 83518 | DL104: 83518 | DM104: 83518 | DN104: 83518 | DO104: 83518 | DP104: 83518 | DQ104: 83518 | DR104: 83518 | DS104: 85902 | DT104: 85902 | DU104: 83818 | DV104: 83818 | DW104: 85902 | DX104: 74772 | DY104: 74772 | DZ104: 85902 | EA104: 85902 | EB104: 85902 | EC104: 85902 | ED104: 85902 | EE104: 9254324
A106: Tenant Income
A107: 1. Kitu Life, Inc. | B107: 1 | C107: 26209 | D107: 26209 | E107: 26209 | F107: 26209 | G107: 26209 | H107: 26209 | I107: 26209 | J107: 26209 | K107: 26709 | L107: 26709 | M107: 26709 | N107: 26709 | O107: 27124 | P107: 27124 | Q107: 27124 | R107: 27124 | S107: 27124 | T107: 27124 | U107: 27124 | V107: 27124 | W107: 27638 | X107: 27638 | Y107: 27638 | Z107: 27638 | AA107: 28005 | AB107: 28005 | AC107: 28005 | AD107: 28005 | AE107: 28005 | AF107: 28005 | AG107: 28005 | AH107: 28005 | AI107: 28533 | AJ107: 28533 | AK107: 28533 | AL107: 28533 | AM107: 28823 | AN107: 28823 | AO107: 28823 | AP107: 28823 | AQ107: 28823 | AR107: 28823 | AS107: 28823 | AT107: 28823 | AU107: 29365 | AV107: 29365 | AW107: 29365 | AX107: 29365 | AY107: 29634 | AZ107: 29634 | BA107: 29634 | BB107: 29634 | BC107: 29634 | BD107: 29634 | BE107: 29634 | BF107: 29634 | BG107: 30192 | BH107: 30192 | BI107: 30192 | BJ107: 30192 | BK107: 0 | BL107: 0 | BM107: 11846 | BN107: 32231 | BO107: 32231 | BP107: 32231 | BQ107: 32231 | BR107: 32231 | BS107: 32231 | BT107: 32231 | BU107: 32231 | BV107: 32231 | BW107: 32544 | BX107: 32544 | BY107: 33224 | BZ107: 33224 | CA107: 33224 | CB107: 33224 | CC107: 33224 | CD107: 33224 | CE107: 33224 | CF107: 33224 | CG107: 33224 | CH107: 33224 | CI107: 33486 | CJ107: 33486 | CK107: 34186 | CL107: 34186 | CM107: 34186 | CN107: 34186 | CO107: 34186 | CP107: 34186 | CQ107: 34186 | CR107: 34186 | CS107: 34186 | CT107: 34186 | CU107: 34482 | CV107: 34482 | CW107: 35203 | CX107: 35203 | CY107: 35203 | CZ107: 35203 | DA107: 35203 | DB107: 35203 | DC107: 35203 | DD107: 35203 | DE107: 35203 | DF107: 35203 | DG107: 35572 | DH107: 35572 | DI107: 36315 | DJ107: 36315 | DK107: 36315 | DL107: 36315 | DM107: 36315 | DN107: 36315 | DO107: 36315 | DP107: 36315 | DQ107: 36315 | DR107: 36315 | DS107: 36624 | DT107: 36624 | DU107: 37388 | DV107: 37388 | DW107: 37388 | DX107: 0 | DY107: 0 | DZ107: 13756 | EA107: 37388 | EB107: 37388 | EC107: 37388 | ED107: 37388 | EE107: 4000211
...

Sheet Charts
B3: =+Assumptions!B2 -> Westview Austin
B4: Deal Snapshot
A6: x | B6: Property Overview
B7: Property Type | D7: Office | F7: Year Built/Renovated | I7: 1954 / 2018
B8: NRA (SF) | D8: =Assumptions!$F$7 -> 100166 | F8: Market | I8: Austin
B9: Current Occupancy | D9: 0.93 | F9: Submarket | I9: Downtown
B10: Parking Stalls | D10: 1.7 / 1,000 | F10: Sponsor | I10: Arc Capital Partners
A12: x | B12: Sources & Uses
G13: At Close | H13: Lease Up | I13: Total | J13: $ PSF | K13: %
B14: Debt | G14: =+Assumptions!F48 -> 37700 | H14: =+SUM(G49:K49) -> 1300 | I14: =+G14+H14 -> 39000 | J14: =+I14/$D$8*1000 -> 389.35367 | K14: =+I14/$I$17 -> 0.64254266
B15: Equity | G15: =(G$32-G$14-G16) -> 21436.25 | H15: =(H$32-H$14-H16) -> 61.525417 | I15: =+G15+H15 -> 21497.775 | J15: =+I15/$D$8*1000 -> 214.62148 | K15: =+I15/$I$17 -> 0.35418558
B16: Project Cash Flow | G16: 0 | H16: =+Assumptions!J69 -> 198.58358 | I16: =+G16+H16 -> 198.58358 | J16: =+I16/$D$8*1000 -> 1.9825448 | K16: =+I16/$I$17 -> 0.0032717545
B17: Total Sources | G17: =SUM(G14:G16) -> 59136.25 | H17: =SUM(H14:H16) -> 1560.109 | I17: =SUM(I14:I16) -> 60696.359 | J17: =SUM(J14:J16) -> 605.9577 | K17: =SUM(K14:K16) -> 1
B19: =+Assumptions!H51 -> Purchase Price | G19: =+Assumptions!C12 -> 58250 | H19: 0 | I19: =+G19+H19 -> 58250 | J19: =+I19/$D$8*1000 -> 581.53465 | K19: =+I19/$I$32 -> 0.95969513
B20: =+Assumptions!H52 -> Closing Costs | G20: =+Assumptions!C13 -> 691.25 | H20: 0 | I20: =+G20+H20 -> 691.25 | J20: =+I20/$D$8*1000 -> 6.9010443 | K20: =+I20/$I$32 -> 0.011388657
B21: =+Assumptions!H53 -> Operating Losses | G21: 0 | H21: =+Assumptions!J53 -> 0 | I21: =+G21+H21 -> 0 | J21: =+I21/$D$8*1000 -> 0 | K21: =+I21/$I$32 -> 0
B22: =+Assumptions!H54 -> CapEx - Building Cost | G22: =+Assumptions!C16 -> 0 | H22: =+Assumptions!J54-G22 -> 300 | I22: =+G22+H22 -> 300 | J22: =+I22/$D$8*1000 -> 2.9950283 | K22: =+I22/$I$32 -> 0.0049426359
B23: =+Assumptions!H55 -> Construction Costs - Site Work | G23: 0 | H23: =+Assumptions!J55 -> 0 | I23: =+G23+H23 -> 0 | J23: =+I23/$D$8*1000 -> 0 | K23: =+I23/$I$32 -> 0
B24: =+Assumptions!H56 -> Soft Costs | G24: 0 | H24: =+Assumptions!J56 -> 0 | I24: =+G24+H24 -> 0 | J24: =+I24/$D$8*1000 -> 0 | K24: =+I24/$I$32 -> 0
B25: =+Assumptions!H57 -> Contingency | G25: 0 | H25: =+Assumptions!J57 -> 0 | I25: =+G25+H25 -> 0 | J25: =+I25/$D$8*1000 -> 0 | K25: =+I25/$I$32 -> 0
B26: =+Assumptions!H58 -> Other Fees/ General Conditions | G26: 0 | H26: =+Assumptions!J58 -> 0 | I26: =+G26+H26 -> 0 | J26: =+I26/$D$8*1000 -> 0 | K26: =+I26/$I$32 -> 0
B27: =+Assumptions!H59 -> Capital Reserves and Deferred Maint. | G27: 0 | H27: =+Assumptions!J59 -> 64.257 | I27: =+G27+H27 -> 64.257 | J27: =+I27/$D$8*1000 -> 0.6415051 | K27: =+I27/$I$32 -> 0.0010586632
B28: =+Assumptions!H60 -> TIs | G28: =+Assumptions!C22 -> 0 | H28: =+Assumptions!J60-G28 -> 839.326 | I28: =+G28+H28 -> 839.326 | J28: =+I28/$D$8*1000 -> 8.3793503 | K28: =+I28/$I$32 -> 0.013828276
B29: =+Assumptions!H61 -> LCs | G29: =+Assumptions!C23 -> 0 | H29: =+Assumptions!J61-G29 -> 356.526 | I29: =+G29+H29 -> 356.526 | J29: =+I29/$D$8*1000 -> 3.5593515 | K29: =+I29/$I$32 -> 0.0058739273
B30: =+Assumptions!H62 -> Loan Closing Costs & Fees | G30: =+Assumptions!C25 -> 195 | H30: =+'Monthly Cash Flow'!I110+'Monthly Cash Flow'!I108+'Monthly Cash Flow'!I107-'Monthly Cash Flow'!K107 -> 0 | I30: =+G30+H30 -> 195 | J30: =+I30/$D$8*1000 -> 1.9467684 | K30: =+I30/$I$32 -> 0.0032127133
B31: =+Assumptions!H63 -> Capitalized Interest | H31: =+Assumptions!J63 -> 0 | I31: =+G31+H31 -> 0 | J31: =+I31/$D$8*1000 -> 0 | K31: =+I31/$I$32 -> 0
B32: Total Uses | G32: =SUM(G19:G31) -> 59136.25 | H32: =SUM(H19:H31) -> 1560.109 | I32: =SUM(I19:I31) -> 60696.359 | J32: =SUM(J19:J31) -> 605.9577 | K32: =SUM(K19:K31) -> 1
A34: x | B34: Cash Flows
B35: Year | F35: Yr 0 | G35: 1 | H35: 2 | I35: 3 | J35: 4 | K35: 5 | L35: 6 | M35: 7 | N35: 8
B36: Year Ending | G36: =EOMONTH(Assumptions!I6, 11) -> 45016 | H36: =EOMONTH(G36, 12) -> 45382 | I36: =EOMONTH(H36, 12) -> 45747 | J36: =EOMONTH(I36, 12) -> 46112 | K36: =EOMONTH(J36, 12) -> 46477 | L36: =EOMONTH(K36, 12) -> 46843 | M36: =EOMONTH(L36, 12) -> 47208 | N36: =EOMONTH(M36, 12) -> 47573 | O36: Total
B37: Revenues | F37: =+'Monthly Cash Flow'!EV60 -> 0 | G37: =+'Monthly Cash Flow'!EW60-G38 -> 5865.991 | H37: =+'Monthly Cash Flow'!EX60-H38 -> 6251.194 | I37: =+'Monthly Cash Flow'!EY60-I38 -> 6350.333 | J37: =+'Monthly Cash Flow'!EZ60-J38 -> 6582.783 | K37: =+'Monthly Cash Flow'!FA60-K38 -> 6741.434 | L37: =+'Monthly Cash Flow'!FB60-L38 -> 7115.357 | M37: =+'Monthly Cash Flow'!FC60-M38 -> 7131.287 | N37: =+'Monthly Cash Flow'!FD60-N38 -> 7529.736 | O37: =SUM(F37:N37) -> 53568.115
B38: Rental Abatement | F38: =+'Monthly Cash Flow'!EV54 -> 0 | G38: =+'Monthly Cash Flow'!EW54 -> -3.453 | H38: =+'Monthly Cash Flow'!EX54 -> -180.771 | I38: =+'Monthly Cash Flow'!EY54 -> 0 | J38: =+'Monthly Cash Flow'!EZ54 -> 0 | K38: =+'Monthly Cash Flow'!FA54 -> -173.328 | L38: =+'Monthly Cash Flow'!FB54 -> 0 | M38: =+'Monthly Cash Flow'!FC54 -> -184.231 | N38: =+'Monthly Cash Flow'!FD54 -> -31.976 | O38: =SUM(F38:N38) -> -573.759
B39: Operating Expenses | F39: =+'Monthly Cash Flow'!EV70 -> 0 | G39: =-'Monthly Cash Flow'!EW70 -> -2432.83 | H39: =-'Monthly Cash Flow'!EX70 -> -2518.432 | I39: =-'Monthly Cash Flow'!EY70 -> -2607.076 | J39: =-'Monthly Cash Flow'!EZ70 -> -2694.681 | K39: =-'Monthly Cash Flow'!FA70 -> -2776.414 | L39: =-'Monthly Cash Flow'!FB70 -> -2887.779 | M39: =-'Monthly Cash Flow'!FC70 -> -2973.717 | N39: =-'Monthly Cash Flow'!FD70 -> -3093.074 | O39: =SUM(F39:N39) -> -21984.003
B40: Net Operating Income | F40: 0 | G40: =SUM(G37:G39) -> 3429.708 | H40: =SUM(H37:H39) -> 3551.991 | I40: =SUM(I37:I39) -> 3743.257 | J40: =SUM(J37:J39) -> 3888.102 | K40: =SUM(K37:K39) -> 3791.692 | L40: =SUM(L37:L39) -> 4227.578 | M40: =SUM(M37:M39) -> 3973.339 | N40: =SUM(N37:N39) -> 4404.686 | O40: =SUM(F40:N40) -> 31010.353
B41: =Assumptions!B16 -> CapEx - Building Cost | F41: =-'Monthly Cash Flow'!EV21 -> 0 | G41: =-'Monthly Cash Flow'!EW21 -> -300 | H41: =-'Monthly Cash Flow'!EX21 -> 0 | I41: =-'Monthly Cash Flow'!EY21 -> 0 | J41: =-'Monthly Cash Flow'!EZ21 -> 0 | K41: =-'Monthly Cash Flow'!FA21 -> 0 | L41: =-'Monthly Cash Flow'!FB21 -> 0 | M41: =-'Monthly Cash Flow'!FC21 -> 0 | N41: =-'Monthly Cash Flow'!FD21 -> 0 | O41: =SUM(F41:N41) -> -300
B42: =Assumptions!B17 -> Construction Costs - Site Work | F42: =-'Monthly Cash Flow'!EV22 -> 0 | G42: =-'Monthly Cash Flow'!EW22 -> 0 | H42: =-'Monthly Cash Flow'!EX22 -> 0 | I42: =-'Monthly Cash Flow'!EY22 -> 0 | J42: =-'Monthly Cash Flow'!EZ22 -> 0 | K42: =-'Monthly Cash Flow'!FA22 -> 0 | L42: =-'Monthly Cash Flow'!FB22 -> 0 | M42: =-'Monthly Cash Flow'!FC22 -> 0 | N42: =-'Monthly Cash Flow'!FD22 -> 0 | O42: =SUM(F42:N42) -> 0
B43: TIs/LCs/Soft Costs/Other | F43: 0 | G43: =-SUM('Monthly Cash Flow'!EW28:EW29,'Monthly Cash Flow'!EW31:EW32,'Monthly Cash Flow'!EW23:EW25,'Monthly Cash Flow'!EW35) -> -388.844 | H43: =-SUM('Monthly Cash Flow'!EX28:EX29,'Monthly Cash Flow'!EX31:EX32,'Monthly Cash Flow'!EX23:EX25,'Monthly Cash Flow'!EX35) -> -849.212 | I43: =-SUM('Monthly Cash Flow'!EY28:EY29,'Monthly Cash Flow'!EY31:EY32,'Monthly Cash Flow'!EY23:EY25,'Monthly Cash Flow'!EY35) -> -22.053 | J43: =-SUM('Monthly Cash Flow'!EZ28:EZ29,'Monthly Cash Flow'!EZ31:EZ32,'Monthly Cash Flow'!EZ23:EZ25,'Monthly Cash Flow'!EZ35) -> -22.716 | K43: =-SUM('Monthly Cash Flow'!FA28:FA29,'Monthly Cash Flow'!FA31:FA32,'Monthly Cash Flow'!FA23:FA25,'Monthly Cash Flow'!FA35) -> -689.131 | L43: =-SUM('Monthly Cash Flow'!FB28:FB29,'Monthly Cash Flow'!FB31:FB32,'Monthly Cash Flow'!FB23:FB25,'Monthly Cash Flow'!FB35) -> -24.096 | M43: =-SUM('Monthly Cash Flow'!FC28:FC29,'Monthly Cash Flow'!FC31:FC32,'Monthly Cash Flow'!FC23:FC25,'Monthly Cash Flow'!FC35) -> -891.166 | N43: =-SUM('Monthly Cash Flow'!FD28:FD29,'Monthly Cash Flow'!FD31:FD32,'Monthly Cash Flow'!FD23:FD25,'Monthly Cash Flow'!FD35) -> -25.569 | O43: =SUM(F43:N43) -> -2912.787
B44: Leasing / CapEx Reserve (Funding / Release) | F44: =-SUM('Monthly Cash Flow'!EV28:EV29,'Monthly Cash Flow'!EV31:EV32,'Monthly Cash Flow'!EV23:EV25,'Monthly Cash Flow'!EV35) -> 0 | G44: =+'Monthly Cash Flow'!EW211 -> 0 | H44: =+'Monthly Cash Flow'!EX211 -> -66.776 | I44: =+'Monthly Cash Flow'!EY211 -> 66.776 | J44: =+'Monthly Cash Flow'!EZ211 -> 0 | K44: =+'Monthly Cash Flow'!FA211 -> 0 | L44: =+'Monthly Cash Flow'!FB202 -> 0 | M44: =+'Monthly Cash Flow'!FC202 -> 0 | N44: =+'Monthly Cash Flow'!FD202 -> 0 | O44: =SUM(F44:N44) -> 4.1211479e-13
B45: Asset Management Fee | F45: 0 | G45: ='Monthly Cash Flow'!EW89 -> 0 | H45: ='Monthly Cash Flow'!EX89 -> 0 | I45: ='Monthly Cash Flow'!EY89 -> 0 | J45: ='Monthly Cash Flow'!EZ89 -> 0 | K45: ='Monthly Cash Flow'!FA89 -> 0 | L45: ='Monthly Cash Flow'!FB89 -> 0 | O45: =SUM(F45:N45) -> 0
B46: Debt Service | F46: =+'Monthly Cash Flow'!EV209+'Monthly Cash Flow'!EV210 -> 0 | G46: =+'Monthly Cash Flow'!EW209+'Monthly Cash Flow'!EW210 -> -1717.3217 | H46: =+'Monthly Cash Flow'!EX209+'Monthly Cash Flow'!EX210 -> -1726.7575 | I46: =+'Monthly Cash Flow'!EY209+'Monthly Cash Flow'!EY210 -> -1722.0396 | J46: =+'Monthly Cash Flow'!EZ209+'Monthly Cash Flow'!EZ210 -> 0 | K46: =+'Monthly Cash Flow'!FA209+'Monthly Cash Flow'!FA210 -> 0 | L46: =+'Monthly Cash Flow'!FB209+'Monthly Cash Flow'!FB210 -> 0 | M46: =+'Monthly Cash Flow'!FC209+'Monthly Cash Flow'!FC210 -> 0 | N46: =+'Monthly Cash Flow'!FD209+'Monthly Cash Flow'!FD210 -> 0 | O46: =SUM(F46:N46) -> -5166.1187
B47: Cash Flows after Debt Service | F47: =SUM(F40:F46) -> 0 | G47: =SUM(G40:G46) -> 1023.5423 | H47: =SUM(H40:H46) -> 909.2455 | I47: =SUM(I40:I46) -> 2065.9404 | J47: =SUM(J40:J46) -> 3865.386 | K47: =SUM(K40:K46) -> 3102.561 | L47: =SUM(L40:L46) -> 4203.482 | M47: =SUM(M40:M46) -> 3082.173 | N47: =SUM(N40:N46) -> 4379.117 | O47: =SUM(F47:N47) -> 22631.447
B48: Acquisition and Disposition | F48: =+'Monthly Cash Flow'!EV200 -> -58941.25 | G48: =+'Monthly Cash Flow'!EW200 -> 0 | H48: =+'Monthly Cash Flow'!EX200 -> 0 | I48: =+'Monthly Cash Flow'!EY200 -> 66942.974 | J48: =+'Monthly Cash Flow'!EZ200 -> 0 | K48: =+'Monthly Cash Flow'!FA200 -> 0 | L48: =+'Monthly Cash Flow'!FB200 -> 0 | M48: =+'Monthly Cash Flow'!FC200 -> 0 | N48: =+'Monthly Cash Flow'!FD200 -> 0 | O48: =SUM(F48:N48) -> 8001.7236
B49: New Debt, net | F49: =+'Monthly Cash Flow'!EV207+'Monthly Cash Flow'!EV208 -> 37700 | G49: =+'Monthly Cash Flow'!EW207+'Monthly Cash Flow'!EW208 -> 668.051 | H49: =+'Monthly Cash Flow'!EX207+'Monthly Cash Flow'!EX208 -> 631.949 | I49: =+'Monthly Cash Flow'!EY207+'Monthly Cash Flow'!EY208 -> 0 | J49: =+'Monthly Cash Flow'!EZ207+'Monthly Cash Flow'!EZ208 -> 0 | K49: =+'Monthly Cash Flow'!FA207+'Monthly Cash Flow'!FA208 -> 0 | L49: =+'Monthly Cash Flow'!FB207+'Monthly Cash Flow'!FB208 -> 0 | M49: =+'Monthly Cash Flow'!FC207+'Monthly Cash Flow'!FC208 -> 0 | N49: =+'Monthly Cash Flow'!FD207+'Monthly Cash Flow'!FD208 -> 0 | O49: =SUM(F49:N49) -> 39000
B50: Financing Cost | F50: =+'Monthly Cash Flow'!EV212+'Monthly Cash Flow'!EV213 -> -195 | G50: =+'Monthly Cash Flow'!EW212+'Monthly Cash Flow'!EW213 -> 0 | H50: =+'Monthly Cash Flow'!EX212+'Monthly Cash Flow'!EX213 -> 0 | I50: =+'Monthly Cash Flow'!EY212+'Monthly Cash Flow'!EY213 -> 0 | J50: =+'Monthly Cash Flow'!EZ212+'Monthly Cash Flow'!EZ213 -> 0 | K50: =+'Monthly Cash Flow'!FA212+'Monthly Cash Flow'!FA213 -> 0 | L50: =+'Monthly Cash Flow'!FB212+'Monthly Cash Flow'!FB213 -> 0 | M50: =+'Monthly Cash Flow'!FC212+'Monthly Cash Flow'!FC213 -> 0 | N50: =+'Monthly Cash Flow'!FD212+'Monthly Cash Flow'!FD213 -> 0 | O50: =SUM(F50:N50) -> -195
B51: Loan Repayment | F51: =+'Monthly Cash Flow'!EV214 -> 0 | G51: =+'Monthly Cash Flow'!EW214 -> 0 | H51: =+'Monthly Cash Flow'!EX214 -> 0 | I51: =+'Monthly Cash Flow'!EY214 -> -39000 | J51: =+'Monthly Cash Flow'!EZ214 -> 0 | K51: =+'Monthly Cash Flow'!FA214 -> 0 | L51: =+'Monthly Cash Flow'!FB214 -> 0 | M51: =+'Monthly Cash Flow'!FC214 -> 0 | N51: =+'Monthly Cash Flow'!FD214 -> 0 | O51: =SUM(F51:N51) -> -39000
B52: Leveraged Cash Flows | F52: =SUM(F47:F51) -> -21436.25 | G52: =SUM(G47:G51) -> 1691.5933 | H52: =SUM(H47:H51) -> 1541.1945 | I52: =SUM(I47:I51) -> 30008.914 | J52: =SUM(J47:J51) -> 3865.386 | K52: =SUM(K47:K51) -> 3102.561 | L52: =SUM(L47:L51) -> 4203.482 | M52: =SUM(M47:M51) -> 3082.173 | N52: =SUM(N47:N51) -> 4379.117 | O52: =SUM(F52:N52) -> 30438.171
B53: NOI Growth Rate | G53: n/a | H53: n/a | I53: n/a | J53: n/a | K53: n/a | L53: n/a | M53: n/a | N53: n/a
B54: Avg Occupancy (Prior to Vacancy Allowance) | G54: =AVERAGEIF('Monthly Cash Flow'!$L$13:$EM$13, Charts!G35, 'Monthly Cash Flow'!$L$45:$EM$45) -> 0.93313938 | H54: =AVERAGEIF('Monthly Cash Flow'!$L$13:$EM$13, Charts!H35, 'Monthly Cash Flow'!$L$45:$EM$45) -> 0.97518785 | I54: =AVERAGEIF('Monthly Cash Flow'!$L$13:$EM$13, Charts!I35, 'Monthly Cash Flow'!$L$45:$EM$45) -> 0.99706654 | J54: =AVERAGEIF('Monthly Cash Flow'!$L$13:$EM$13, Charts!J35, 'Monthly Cash Flow'!$L$45:$EM$45) -> 1 | K54: =AVERAGEIF('Monthly Cash Flow'!$L$13:$EM$13, Charts!K35, 'Monthly Cash Flow'!$L$45:$EM$45) -> 0.97437587 | L54: =AVERAGEIF('Monthly Cash Flow'!$L$13:$EM$13, Charts!L35, 'Monthly Cash Flow'!$L$45:$EM$45) -> 0.98777363 | M54: =AVERAGEIF('Monthly Cash Flow'!$L$13:$EM$13, Charts!M35, 'Monthly Cash Flow'!$L$45:$EM$45) -> 0.98816631 | N54: =AVERAGEIF('Monthly Cash Flow'!$L$13:$EM$13, Charts!N35, 'Monthly Cash Flow'!$L$45:$EM$45) -> 0.99179196
B55: In-Place Rents (Annual PSF) | G55: =AVERAGEIF('Lease Audit Report'!$D$5:$ED$5, Charts!G35, 'Lease Audit Report'!$D$77:$ED$77) -> 24.668484 | H55: =AVERAGEIF('Lease Audit Report'!$D$5:$ED$5, Charts!H35, 'Lease Audit Report'!$D$77:$ED$77) -> 28.101492 | I55: =AVERAGEIF('Lease Audit Report'!$D$5:$ED$5, Charts!I35, 'Lease Audit Report'!$D$77:$ED$77) -> 29.541252 | J55: =AVERAGEIF('Lease Audit Report'!$D$5:$ED$5, Charts!J35, 'Lease Audit Report'!$D$77:$ED$77) -> 30.462529 | K55: =AVERAGEIF('Lease Audit Report'!$D$5:$ED$5, Charts!K35, 'Lease Audit Report'!$D$77:$ED$77) -> 31.377497 | L55: =AVERAGEIF('Lease Audit Report'!$D$5:$ED$5, Charts!L35, 'Lease Audit Report'!$D$77:$ED$77) -> 32.85948 | M55: =AVERAGEIF('Lease Audit Report'!$D$5:$ED$5, Charts!M35, 'Lease Audit Report'!$D$77:$ED$77) -> 34.23841 | N55: =AVERAGEIF('Lease Audit Report'!$D$5:$ED$5, Charts!N35, 'Lease Audit Report'!$D$77:$ED$77) -> 35.238817
B56: Return on Cost | F56: =('Argus Drop'!I52-'Argus Drop'!I25)*12/1000/Charts!G19 -> 0.058813391 | G56: =IF(G40<0,"n/a ",G40/SUM($I$19:$I$31)) -> 0.056505992 | H56: =IF(H40<0,"n/a ",H40/SUM($I$19:$I$31)) -> 0.05852066 | I56: =IF(I40<0,"n/a ",I40/SUM($I$19:$I$31)) -> 0.061671854 | J56: =IF(J40<0,"n/a ",J40/SUM($I$19:$I$31)) -> 0.064058241 | K56: =IF(K40<0,"n/a ",K40/SUM($I$19:$I$31)) -> 0.062469843 | L56: =IF(L40<0,"n/a ",L40/SUM($I$19:$I$31)) -> 0.069651262 | M56: =IF(M40<0,"n/a ",M40/SUM($I$19:$I$31)) -> 0.065462559 | N56: =IF(N40<0,"n/a ",N40/SUM($I$19:$I$31)) -> 0.072569196
B57: Leveraged Cash-on-Cash (Does not Include TI/LC) | G57: =IF(G47<0,"n/a ",IF(G35<=Assumptions!$L$14/12, (G47+-G43-G44-G41)/SUM($I$15:$I$16), "n/a")) -> 0.078925055 | H57: =IF(H47<0,"n/a ",IF(H35<=Assumptions!$L$14/12, (H47+-H43-H44)/SUM($I$15:$I$16), "n/a")) -> 0.084126258 | I57: =IF(I47<0,"n/a ",IF(I35<=Assumptions!$L$14/12, (I47+-I43-I44)/SUM($I$15:$I$16), "n/a")) -> 0.093159291 | J57: =IF(J47<0,"n/a ",IF(J35<=Assumptions!$L$14/12, (J47+-J43-J44)/SUM($I$15:$I$16), "n/a")) -> n/a | K57: =IF(K47<0,"n/a ",IF(K35<=Assumptions!$L$14/12, (K47+-K43-K44)/SUM($I$15:$I$16), "n/a")) -> n/a | L57: =IF(L47<0,"n/a ",IF(L35<=Assumptions!$L$14/12, (L47+L49+L50-L43)/SUM($I$15:$I$15), "n/a")) -> n/a | M57: =IF(M47<0,"n/a ",IF(M35<=Assumptions!$L$14/12, (M47+M49+M50-M43)/SUM($I$15:$I$15), "n/a")) -> n/a | N57: =IF(N47<0,"n/a ",IF(N35<=Assumptions!$L$14/12, (N47+N49+N50-N43)/SUM($I$15:$I$15), "n/a")) -> n/a
A59: x | B59: Returns Summary
H60: IRR | I60: Multiple | J60: Contribution | K60: Profit
B61: Unleveraged Returns | H61: =+Assumptions!Q9 -> 0.094694969 | I61: =+Assumptions!R9 -> 1.2902816 | J61: =+Assumptions!S9 -> 59137.645 | K61: =+Assumptions!T9 -> 17166.571
B62: Profit from Cash Flow | H62: n/a | I62: n/a | J62: n/a | K62: =K61-K63 -> 10243.764 | Q62: =+K62/K61 -> 0.59672748
B63: Profit from Appreciation | H63: n/a | I63: n/a | J63: n/a | K63: =+Assumptions!L25-Assumptions!E27 -> 6922.8062
B64: Leveraged Returns | H64: =+Assumptions!Q10 -> 0.17302634 | I64: =+Assumptions!R10 -> 1.5491476 | J64: =+Assumptions!S10 -> 21497.775 | K64: =+Assumptions!T10 -> 11805.452
B65: ="(1) Assumes exit cap of " & TEXT(Assumptions!$L$19, "0.00%") & " which results in sale price of " & TEXT(Assumptions!K25, "$#") & " psf." -> (1) Assumes exit cap of 5.75% which results in sale price of $675 psf.

Sheet Assumptions
E1: 1 | F1: Circ Trigger
B2: Westview Austin | AC2: =NOW() -> 46199.891
B3: ($ in thousands, except psf amounts)
B5: Land Summary | H5: Project Timing | J5: Start | K5: Duration | L5: End
B6: Land SF | E6: =F6/43560 -> 1.03 | F6: =43560*1.03 -> 44866.8 | H6: Purchase Date | I6: 44652 | N6: Project Return Summary
B7: Building SF | F7: 100166 | H7: Acquisition | L7: =J7+K7 -> 0 | Q7: Base Case
B8: Implied FAR | F8: =F7/F6 -> 2.2325194 | H8: =+B16 -> CapEx - Building Cost | J8: 6 | K8: 6 | L8: =J8+K8 -> 12 | Q8: IRR | R8: Multiple | S8: Contribution | T8: Profit
H9: =+B17 -> Construction Costs - Site Work | J9: 1 | K9: 6 | L9: =J9+K9 -> 7 | N9: Unleveraged Returns | Q9: =+'Monthly Cash Flow'!I95 -> 0.094694969 | R9: =+'Monthly Cash Flow'!I94 -> 1.2902816 | S9: =+'Monthly Cash Flow'!I93 -> 59137.645 | T9: ='Monthly Cash Flow'!I92 -> 17166.571
B10: Acquisition Costs | H10: =+B18 -> Soft Costs | J10: 3 | K10: 3 | L10: =J10+K10 -> 6 | N10: Leveraged Returns | Q10: =+'Monthly Cash Flow'!I244 -> 0.17302634 | R10: =+'Monthly Cash Flow'!I243 -> 1.5491476 | S10: =+'Monthly Cash Flow'!I242 -> 21497.775 | T10: =+'Monthly Cash Flow'!I241 -> 11805.452
C11: At Close | D11: PSF* | E11: At Stabilization | F11: PSF* | H11: =+B19 -> Contingency | J11: 6 | K11: 6 | L11: =J11+K11 -> 12
B12: Purchase Price | C12: 58250 | D12: =C12/F7*1000 -> 581.53465 | E12: =C12 -> 58250 | F12: =E12/F7*1000 -> 581.53465 | H12: =+B20 -> Other Fees/ General Conditions | J12: 1 | K12: 6 | L12: =J12+K12 -> 7
B13: =C13/C12 -> 0.011866953 | C13: =400+0.005*C12 -> 691.25 | D13: =C13/F7*1000 -> 6.9010443 | E13: =C13 -> 691.25 | F13: =E13/F7*1000 -> 6.9010443 | N13: 36-Month Hold
B14: Total Acquisition Costs | C14: =SUM(C12:C13) -> 58941.25 | D14: =C14/F7*1000 -> 588.4357 | E14: =SUM(E12:E13) -> 58941.25 | F14: =E14/F7*1000 -> 588.4357 | H14: Project Sale | I14: =EOMONTH(I6,L14-1) -> 45747 | L14: 36 | N14: Exit Price vs CapEx - Levered IRR
B15: Operating Losses | C15: 0 | D15: =C15/F7*1000 -> 0 | E15: ='Monthly Cash Flow'!I111 -> 0 | F15: =E15/$F$7*1000 -> 0 | O15: Exit Price / Exit Cap Rate
B16: CapEx - Building Cost | C16: 0 | D16: =C16/F7*1000 -> 0 | E16: 300 | F16: =E16/$F$7*1000 -> 2.9950283 | H16: Exit Assumptions | K16: $ per GLA | L16: % of Total | O16: =1000*($L$18/O17)/$F$7 -> 739.36351 | P16: =1000*($L$18/P17)/$F$7 -> 705.75608 | Q16: =1000*($L$18/Q17)/$F$7 -> 675.07103 | R16: =1000*($L$18/R17)/$F$7 -> 646.94307 | S16: =1000*($L$18/S17)/$F$7 -> 621.06535
B17: Construction Costs - Site Work | C17: 0 | D17: =C17/F7*1000 -> 0 | E17: =+F17*$F$7/1000 -> 0 | F17: 0 | H17: Year of Sale | L17: =L14 -> 36 | N17: =Q10 -> 0.17302634 | O17: 0.0525 | P17: 0.055 | Q17: 0.0575 | R17: 0.06 | S17: 0.0625
B18: Soft Costs | C18: 0 | D18: =C18/F7*1000 -> 0 | E18: 0 | F18: =E18/$F$7*1000 -> 0 | H18: Forward NOI | L18: =SUM(OFFSET('Monthly Cash Flow'!K$72,0,Assumptions!$L$17+1,1,12))-SUM(OFFSET('Monthly Cash Flow'!K$54,0,Assumptions!$L$17+1,1,12)) -> 3888.102 | N18: 200 | O18: 0.24873503 | P18: 0.21101027 | Q18: 0.17427506 | R18: 0.13834121 | S18: 0.10303187
B19: Contingency | C19: =G19*(C16+C18) -> 0 | D19: =C19/F7*1000 -> 0 | E19: =+G19*E16 -> 0 | F19: =E19/$F$7*1000 -> 0 | G19: 0 | H19: Exit Cap Rate | L19: 0.0575 | N19: 300 | O19: 0.24763742 | P19: 0.20983979 | Q19: 0.17302634 | R19: 0.13700804 | S19: 0.10160698
B20: Other Fees/ General Conditions | C20: 0 | D20: =C20/F7*1000 -> 0 | E20: 0 | F20: =E20/$F$7*1000 -> 0 | H20: Gross Exit Value | K20: =L20/F7*1000 -> 675.07103 | L20: =MAX(L18/L19) -> 67619.165 | N20: 400 | O20: 0.2458865 | P20: 0.20809007 | Q20: 0.17127756 | R20: 0.13525996 | S20: 0.099859315
B21: Capital Reserves and Deferred Maint. | C21: 0 | D21: =C21/F7*1000 -> 0 | E21: =+J39 -> 64.257 | F21: =+E21*1000/$F$7 -> 0.6415051 | H21: Rental Abatement Credit | L21: =+SUM(OFFSET('Monthly Cash Flow'!K$54,0,Assumptions!$L$17+1,1,12)) -> 0 | N21: 500 | O21: 0.24411519 | P21: 0.20632377 | Q21: 0.16951603 | R21: 0.13350297 | S21: 0.098106629
B22: TIs | C22: 0 | D22: =C22/F7*1000 -> 0 | E22: =+J40 -> 839.326 | F22: =+E22*1000/$F$7 -> 8.3793503 | H22: TI/LC Credit | L22: =-SUM(OFFSET('Monthly Cash Flow'!K$28,0,Assumptions!$L$17+1,1,12))-SUM(OFFSET('Monthly Cash Flow'!K$31,0,Assumptions!$L$17+1,1,12)) -> 0 | N22: 600 | O22: 0.24233871 | P22: 0.20455402 | Q22: 0.16775277 | R22: 0.13174598 | S22: 0.096355671
B23: LCs | C23: 0 | D23: =C23/F7*1000 -> 0 | E23: =+J41 -> 356.526 | F23: =+E23*1000/$F$7 -> 3.5593515 | H23: Gross Exit Value (Post Abatement/TI/LC Credit) | K23: =L23/F7*1000 -> 675.07103 | L23: =+L20+SUM(L21:L22) -> 67619.165
B24: Total Unleveraged Basis | C24: =SUM(C14:C23) -> 58941.25 | D24: =C24/F7*1000 -> 588.4357 | E24: =SUM(E14:E23) -> 60501.359 | F24: =E24/F7*1000 -> 604.01093
B25: Loan Closing Costs & Fees | C25: =+F36+F38 -> 195 | D25: =C25/F7*1000 -> 1.9467684 | E25: =SUM('Monthly Cash Flow'!I107:I110) -> 195 | F25: =E25/F7*1000 -> 1.9467684 | H25: Total Gross Exit Proceeds | K25: =L25/F7*1000 -> 675.07103 | L25: =L23 -> 67619.165 | N25: 40-Month Hold
B26: Capitalized Interest | C26: 0 | D26: =C26/F7*1000 -> 0 | E26: ='Monthly Cash Flow'!I153 -> 0 | F26: =E26/F7*1000 -> 0 | H26: Sales Costs | K26: 0.01 | L26: =-L25*K26 -> -676.19165 | N26: Exit Price vs CapEx - Levered IRR
B27: Total Leveraged Basis | C27: =SUM(C24:C26) -> 59136.25 | D27: =C27/F7*1000 -> 590.38247 | E27: =SUM(E24:E26) -> 60696.359 | F27: =E27/F7*1000 -> 605.9577 | H27: Net Exit Proceeds | K27: =L27/F7*1000 -> 668.32032 | L27: =SUM(L25:L26) -> 66942.974 | O27: Exit Price / Exit Cap Rate
O28: 754.17017 | P28: 719.88971 | Q28: 688.59016 | R28: 659.8989 | S28: 633.50295
B29: Financing Assumptions (Acquisition Loan) | H29: Unleveraged Sources and Uses | N29: 0.18228523 | O29: 0.0525 | P29: 0.055 | Q29: 0.0575 | R29: 0.06 | S29: 0.0625
B30: Total Debt | F30: =+F53 -> 39000 | H30: Project Uses | J30: Amount | K30: % | L30: $ Per NRSF | N30: 200 | O30: 0.24423246 | P30: 0.21147026 | Q30: 0.17953365 | R30: 0.1482667 | S30: 0.11752319
B31: Total Equity | F31: =+F54-F30 -> 21696.359 | H31: Purchase Price | J31: ='Monthly Cash Flow'!$I$17 -> 58250 | K31: =J31/$J$42 -> 0.96278829 | L31: =J31/F7*1000 -> 581.53465 | N31: 300 | O31: 0.2432985 | P31: 0.21047315 | Q31: 0.17846887 | R31: 0.14712904 | S31: 0.11630664
B32: Interest Rate | C32: Floating Rate | D32: 0 | E32: =+'1 mos LIBOR'!M22 -> 0.0207761 | F32: =+D33 -> 0 | H32: Closing Costs | J32: ='Monthly Cash Flow'!$I$18 -> 691.25 | K32: =J32/$J$42 -> 0.011425363 | L32: =J32/F7*1000 -> 6.9010443 | N32: 400 | O32: 0.24170801 | P32: 0.20888268 | Q32: 0.17687818 | R32: 0.14553788 | S32: 0.11471474
B33: Loan Closing Month | C33: Fixed Rate | F33: 0 | H33: Operating Losses | J33: =+'Monthly Cash Flow'!I85 -> 0 | K33: =J33/$J$42 -> 0 | L33: =J33/F7*1000 -> 0 | N33: 500 | O33: 0.24009957 | P33: 0.20727727 | Q33: 0.17527555 | R33: 0.14393781 | S33: 0.11311697
B34: Libor Floor | C34: Floor | D34: 0.04355 | H34: =+B16 -> CapEx - Building Cost | J34: ='Monthly Cash Flow'!$I21 -> 300 | K34: =J34/$J$42 -> 0.0049585663 | L34: =J34/F7*1000 -> 2.9950283 | N34: 600 | O34: 0.23848676 | P34: 0.20566884 | Q34: 0.17367128 | R34: 0.14233746 | S34: 0.1115203
B35: Servicing Fee | F35: 0 | H35: =+B17 -> Construction Costs - Site Work | J35: ='Monthly Cash Flow'!$I22 -> 0 | K35: =J35/$J$42 -> 0 | L35: =J35/F7*1000 -> 0
B36: Loan Fees (Bank And Broker) | E36: 0.005 | F36: =+IF(E1=0,0,E36*F30) -> 195 | H36: =+B18 -> Soft Costs | J36: ='Monthly Cash Flow'!$I23 -> 0 | K36: =J36/$J$42 -> 0 | L36: =J36/F7*1000 -> 0
B37: Exit Fee | E37: 0 | F37: =+IF(E1=0,0,E37*F30) -> 0 | H37: =+B19 -> Contingency | J37: ='Monthly Cash Flow'!$I24 -> 0 | K37: =J37/$J$42 -> 0 | L37: =J37/F7*1000 -> 0
B38: Loan Closing Costs | E38: =+F38/F30 -> 0 | F38: 0 | H38: =+B20 -> Other Fees/ General Conditions | J38: ='Monthly Cash Flow'!$I25 -> 0 | K38: =J38/$J$42 -> 0 | L38: =J38/F7*1000 -> 0
B39: Loan Extension Fee | C39: 37 | D39: =+C39+12 -> 49 | E39: 0 | F39: =+IF(E1=0,0,E39*F30) -> 0 | H39: =+B21 -> Capital Reserves and Deferred Maint. | J39: =+'Monthly Cash Flow'!I35 -> 64.257 | K39: =J39/$J$42 -> 0.0010620753 | L39: =J39/F7*1000 -> 0.6415051
B40: I/O Period (Months) | F40: 60 | H40: =+B22 -> TIs | J40: =+'Monthly Cash Flow'!I30 -> 839.326 | K40: =J40/$J$42 -> 0.013872845 | L40: =J40/F7*1000 -> 8.3793503
B41: Amortization Period (Years) | E41: 30 | F41: =(E41*12) -> 360 | H41: =+B23 -> LCs | J41: =+'Monthly Cash Flow'!I33 -> 356.526 | K41: =J41/$J$42 -> 0.0058928594 | L41: =J41/F7*1000 -> 3.5593515
B42: TI/LC Force Funding | F42: 25 | H42: Total Uses | J42: =SUM(J31:J41) -> 60501.359 | K42: =SUM(K31:K41) -> 1 | L42: =SUM(L31:L41) -> 604.01093
B43: CapEx Force Funding | F43: 19
B44: Distribution Holdback | C44: End Date | D44: 0 | E44: Holdback Per Month | F44: 0 | H44: Project Sources | J44: Amount | K44: % | L44: $ Per GLA
B45: Interest Rate Type | F45: 1 | H45: Unleveraged Equity | J45: ='Monthly Cash Flow'!I87 -> 196.395 | K45: =J45/$J$47 -> 0.0032461254 | L45: =J45/F7*1000 -> 1.9606952
B46: Acquisition Costs | F46: =IF($E$50=0,C27,'Monthly Cash Flow'!K118) -> 59136.25 | H46: Project Cash Flow | J46: =-'Monthly Cash Flow'!I86 -> 60304.964 | K46: =J46/$J$47 -> 0.99675387 | L46: =J46/F7*1000 -> 602.05024
B47: Initial LTC | F47: =+F48/F46 -> 0.63751083 | H47: Total Sources | J47: =SUM(J45:J46) -> 60501.359 | K47: =SUM(K45:K46) -> 1 | L47: =SUM(L45:L46) -> 604.01093
B48: Total Initial Loan Proceeds | F48: 37700
H49: Leveraged Sources and Uses
B50: Future Variable Contribution | E50: 1 | F50: =+SUM(E22:E23) -> 1195.852 | H50: Project Uses (Debt) | J50: Amount | K50: % | L50: $ Per GLA
B51: CapEx Holdback | F51: 300 | H51: =+H31 -> Purchase Price | J51: ='Monthly Cash Flow'!$I$17 -> 58250 | K51: =J51/$J$64 -> 0.95969513 | L51: =J51/F7*1000 -> 581.53465
B52: TI/LC Holdback | F52: 1000 | H52: =+H32 -> Closing Costs | J52: =+J32 -> 691.25 | K52: =J52/$J$64 -> 0.011388657 | L52: =J52/F7*1000 -> 6.9010443
B53: Total Proceeds | E53: 39000 | F53: =SUM(F48, F51:F52) -> 39000 | H53: =+H33 -> Operating Losses | J53: =+J33 -> 0 | K53: =J53/$J$64 -> 0 | L53: =J53/F7*1000 -> 0
B54: Total Costs | F54: =+J64 -> 60696.359 | H54: =+H34 -> CapEx - Building Cost | J54: =+J34 -> 300 | K54: =J54/$J$64 -> 0.0049426359 | L54: =J54/F7*1000 -> 2.9950283
B55: Blended LTC | F55: =+F53/F54 -> 0.64254266 | H55: =+H35 -> Construction Costs - Site Work | J55: =+J35 -> 0 | K55: =J55/$J$64 -> 0 | L55: =J55/F7*1000 -> 0
B56: Debt Funding | H56: =+H36 -> Soft Costs | J56: =+J36 -> 0 | K56: =J56/$J$64 -> 0 | L56: =J56/F7*1000 -> 0
B57: Pay Interest on Fully Funded Amount Day 1? | F57: 1 | H57: =+H37 -> Contingency | J57: =+J37 -> 0 | K57: =J57/$J$64 -> 0 | L57: =J57/F7*1000 -> 0
B58: Year 1 Debt Service | F58: =-SUM('Monthly Cash Flow'!L209:W209) -> 1717.3217 | H58: =+H38 -> Other Fees/ General Conditions | J58: =+J38 -> 0 | K58: =J58/$J$64 -> 0 | L58: =J58/F7*1000 -> 0
B59: Year 4 Debt Service | F59: =-SUM('Monthly Cash Flow'!AV209:BG209) -> 0 | H59: =+H39 -> Capital Reserves and Deferred Maint. | J59: =+J39 -> 64.257 | K59: =J59/$J$64 -> 0.0010586632 | L59: =J59/F7*1000 -> 0.6415051
B60: TI / Reserve Monthly Funding | C60: 8347 | E60: Funding Threshold | F60: 200 | H60: =+H40 -> TIs | J60: =+J40 -> 839.326 | K60: =J60/$J$64 -> 0.013828276 | L60: =J60/F7*1000 -> 8.3793503
B61: NOI | C61: Yr 1 | D61: =+Charts!G40-Charts!G38 -> 3433.161 | E61: Extension Term | F61: =(4*SUM('Monthly Cash Flow'!BH60:BJ60)-SUM('Monthly Cash Flow'!BH54:BJ54))-SUM('Monthly Cash Flow'!BH70:BS70) -> 4046.882 | H61: =+H41 -> LCs | J61: =+J41 -> 356.526 | K61: =J61/$J$64 -> 0.0058739273 | L61: =J61/F7*1000 -> 3.5593515
B62: DSCR Cash Management Test (Yr 1 NOI) (1.15x Requirement) | F62: =+D61/F58 -> 1.9991368 | H62: Loan Closing Costs & Fees | J62: =SUM('Monthly Cash Flow'!$I$107:$I$109,'Monthly Cash Flow'!I110) -> 195 | K62: =J62/$J$64 -> 0.0032127133 | L62: =J62/F7*1000 -> 1.9467684
B63: DSCR Test (Extension) (1.35x Requirement) | F63: =+F61/F59 -> #DIV/0! | H63: Capitalized Interest | J63: ='Monthly Cash Flow'!$I$153 -> 0 | K63: =J63/$J$64 -> 0 | L63: =J63/F7*1000 -> 0
B64: Debt Yield Test | C64: Yr 1 | D64: =+D61/$F$48 -> 0.091065279 | E64: Extension (Req. 8.0%) | F64: =+F61/$F$30 -> 0.10376621 | H64: Total Uses | J64: =SUM(J51:J63) -> 60696.359 | K64: =SUM(K51:K63) -> 1 | L64: =SUM(L51:L63) -> 605.9577
B66: Financing Assumptions (Permanent Loan) | F66: 0 | H66: Project Sources (Debt) | J66: Amount | K66: % | L66: $ Per GLA
B67: Total Debt | F67: =IF($F$66=0,0,F84) -> 0 | H67: Debt Financing | J67: =F30 -> 39000 | K67: =J67/$J$70 -> 0.64254266 | L67: =J67/F7*1000 -> 389.35367
B68: Total Equity | F68: =F69-F67 -> 0 | H68: Equity Investment | J68: =+F31-J69 -> 21497.775 | K68: =J68/$J$70 -> 0.35418558 | L68: =J68/F7*1000 -> 214.62148
B69: Variable Contribution | F69: ='Monthly Cash Flow'!I175 -> 0 | H69: Project Cash Flow | J69: ='Monthly Cash Flow'!$I$116 -> 198.58358 | K69: =J69/$J$70 -> 0.0032717545 | L69: =J69/F7*1000 -> 1.9825448
B70: Interest Rate | C70: Floating Rate | D70: 225 | E70: =+E32 -> 0.0207761 | F70: =(D70/10000)+E70 -> 0.0432761 | H70: Total Sources | J70: =SUM(J67:J69) -> 60696.359 | K70: =SUM(K67:K69) -> 1 | L70: =SUM(L67:L69) -> 605.9577
B71: Loan Closing Month | C71: Fixed Rate | D71: 0.04 | F71: 25
B72: Libor Floor | C72: Floor | D72: 0
B73: Loan Fees (Bank And Broker) | E73: 0.0075 | F73: =+IF($E$1=0,0,E73*F67) -> 0 | V73: 0
B74: Loan Closing Costs | E74: =IFERROR(F74/F67,"n/a") -> n/a | F74: 200
B75: I/O Period (Months) | F75: 60
B76: Amortization Period (Years) | E76: 30 | F76: =(E76*12) -> 360
B77: Interest Rate Type | F77: 0
B78: Stabilized Forward NOI | C78: Month of Stabalization | D78: =+F71 -> 25 | F78: =SUM(OFFSET('Monthly Cash Flow'!$K$78,0,D78,1,12)) -> 3743.257
B79: Stressed DSCR | E79: =(F78/(F81*F84)) -> 1.3704856 | F79: 1.25
B80: Debt Yield | E80: =F78/F84 -> 0.082229139 | F80: 0.08
B81: Stressed Interest Rate | F81: 0.06
B82: Max LTC | E82: =+F84/E27 -> 0.75 | F82: 0.75
B84: Max Proceeds | F84: =MIN((F78/F79)/F81, F78/F80, F82*E27) -> 45522.269
B85: Debt Funding | F85: 1

Sheet Closing Costs
C3: ACM Survey | D3: Partner | E3: 5965
C4: Tax Study | D4: Ryan | E4: 750
C5: Survey | E5: 2500
C6: Lease Abstracts | D6: LeaseProbe | E6: 2275
C7: Phase I | D7: Partner | E7: 2800
C8: PCA | D8: Partner | E8: 4800
C9: Transaction Legal | E9: 40000 | F9: Placeholder from Bev/Rob
C10: Debt Broker | E10: =0.005*39000000 -> 195000
C11: Title and Escrow Costs | E11: 22409 | F11: Placeholder from Bev/Rob
C12: Lender Legal | E12: 73000 | F12: Placeholder from Bev/Rob
C13: Loan Closing Costs | E13: 12970 | F13: Placeholder from Bev/Rob
C14: Lender Fee | E14: 25000
C15: Escrow Service | E15: 750 | F15: Placeholder from Bev/Rob
C16: Acquisition Fee | E16: =0.005*Assumptions!C12*1000 -> 291250
C17: Belay Counsel | E17: 12983
C18: PZR | E18: 2098
C19: Total | E19: =SUM(E3:E18) -> 694550

Sheet Monthly Cash Flow
B2: =#REF! -> #REF! | F2: =#REF! -> #REF! | K2: 1 | L2: =K2*(1+$F2)^(1/12) -> #REF! | M2: =L2*(1+$F2)^(1/12) -> #REF! | N2: =M2*(1+$F2)^(1/12) -> #REF! | O2: =N2*(1+$F2)^(1/12) -> #REF! | P2: =O2*(1+$F2)^(1/12) -> #REF! | Q2: =P2*(1+$F2)^(1/12) -> #REF! | R2: =Q2*(1+$F2)^(1/12) -> #REF! | S2: =R2*(1+$F2)^(1/12) -> #REF! | ... EM2: =EL2*(1+$F2)^(1/12) -> #REF!
B3: =#REF! -> #REF! | F3: =#REF! -> #REF! | K3: 1 | L3: =K3*(1+$F3)^(1/12) -> #REF! | M3: =L3*(1+$F3)^(1/12) -> #REF! | N3: =M3*(1+$F3)^(1/12) -> #REF! | O3: =N3*(1+$F3)^(1/12) -> #REF! | P3: =O3*(1+$F3)^(1/12) -> #REF! | Q3: =P3*(1+$F3)^(1/12) -> #REF! | R3: =Q3*(1+$F3)^(1/12) -> #REF! | S3: =R3*(1+$F3)^(1/12) -> #REF! | ... EM3: =EL3*(1+$F3)^(1/12) -> #REF!
B4: =#REF! -> #REF! | F4: =#REF! -> #REF! | K4: 1 | L4: =K4*(1+$F4)^(1/12) -> #REF! | M4: =L4*(1+$F4)^(1/12) -> #REF! | N4: =M4*(1+$F4)^(1/12) -> #REF! | O4: =N4*(1+$F4)^(1/12) -> #REF! | P4: =O4*(1+$F4)^(1/12) -> #REF! | Q4: =P4*(1+$F4)^(1/12) -> #REF! | R4: =Q4*(1+$F4)^(1/12) -> #REF! | S4: =R4*(1+$F4)^(1/12) -> #REF! | ... EM4: =EL4*(1+$F4)^(1/12) -> #REF!
B5: =#REF! -> #REF! | F5: =#REF! -> #REF! | K5: 1 | L5: =K5*(1+$F5)^(1/12) -> #REF! | M5: =L5*(1+$F5)^(1/12) -> #REF! | N5: =M5*(1+$F5)^(1/12) -> #REF! | O5: =N5*(1+$F5)^(1/12) -> #REF! | P5: =O5*(1+$F5)^(1/12) -> #REF! | Q5: =P5*(1+$F5)^(1/12) -> #REF! | R5: =Q5*(1+$F5)^(1/12) -> #REF! | S5: =R5*(1+$F5)^(1/12) -> #REF! | ... EM5: =EL5*(1+$F5)^(1/12) -> #REF!
B6: =#REF! -> #REF! | F6: =#REF! -> #REF! | K6: 1 | L6: =$K6*(1+$F6)^(L$12/12) -> #REF! | M6: =$K6*(1+$F6)^(M$12/12) -> #REF! | N6: =$K6*(1+$F6)^(N$12/12) -> #REF! | O6: =$K6*(1+$F6)^(O$12/12) -> #REF! | P6: =$K6*(1+$F6)^(P$12/12) -> #REF! | Q6: =$K6*(1+$F6)^(Q$12/12) -> #REF! | R6: =$K6*(1+$F6)^(R$12/12) -> #REF! | S6: =$K6*(1+$F6)^(S$12/12) -> #REF! | ... EM6: =$K6*(1+$F6)^(EM$12/12) -> #REF!
B7: LIBOR Curve | K7: =IFERROR(INDEX('1 mos LIBOR'!$M$3:$M$122,MATCH('Monthly Cash Flow'!K$14,'1 mos LIBOR'!$N$3:$N$122,0)),J7) -> 0 | L7: =IFERROR(INDEX('1 mos LIBOR'!$M$3:$M$122,MATCH('Monthly Cash Flow'!L$14,'1 mos LIBOR'!$N$3:$N$122,0)),K7) -> 0.0044407 | M7: =IFERROR(INDEX('1 mos LIBOR'!$M$3:$M$122,MATCH('Monthly Cash Flow'!M$14,'1 mos LIBOR'!$N$3:$N$122,0)),L7) -> 0.0076526 | N7: =IFERROR(INDEX('1 mos LIBOR'!$M$3:$M$122,MATCH('Monthly Cash Flow'!N$14,'1 mos LIBOR'!$N$3:$N$122,0)),M7) -> 0.0096968 | O7: =IFERROR(INDEX('1 mos LIBOR'!$M$3:$M$122,MATCH('Monthly Cash Flow'!O$14,'1 mos LIBOR'!$N$3:$N$122,0)),N7) -> 0.0106726 | P7: =IFERROR(INDEX('1 mos LIBOR'!$M$3:$M$122,MATCH('Monthly Cash Flow'!P$14,'1 mos LIBOR'!$N$3:$N$122,0)),O7) -> 0.0126868 | Q7: =IFERROR(INDEX('1 mos LIBOR'!$M$3:$M$122,MATCH('Monthly Cash Flow'!Q$14,'1 mos LIBOR'!$N$3:$N$122,0)),P7) -> 0.0126872 | R7: =IFERROR(INDEX('1 mos LIBOR'!$M$3:$M$122,MATCH('Monthly Cash Flow'!R$14,'1 mos LIBOR'!$N$3:$N$122,0)),Q7) -> 0.0152942 | ... EM7: =IFERROR(INDEX('1 mos LIBOR'!$M$3:$M$122,MATCH('Monthly Cash Flow'!EM$14,'1 mos LIBOR'!$N$3:$N$122,0)),EL7) -> 0.0194349
B10: =+Assumptions!B2 -> Westview Austin
B11: Monthly Project Cash Flow
B12: ($ in thousands, except psf amounts) | K12: =Assumptions!J7 -> 0 | L12: =K12+1 -> 1 | M12: =L12+1 -> 2 | N12: =M12+1 -> 3 | O12: =N12+1 -> 4 | P12: =O12+1 -> 5 | Q12: =P12+1 -> 6 | R12: =Q12+1 -> 7 | S12: =R12+1 -> 8 | ... EM12: =EL12+1 -> 132 | EP12: Annual Project Cash Flows
K13: =ROUNDUP(K12/12,0) -> 0 | L13: =ROUNDUP(L12/12,0) -> 1 | M13: =ROUNDUP(M12/12,0) -> 1 | N13: =ROUNDUP(N12/12,0) -> 1 | O13: =ROUNDUP(O12/12,0) -> 1 | P13: =ROUNDUP(P12/12,0) -> 1 | Q13: =ROUNDUP(Q12/12,0) -> 1 | R13: =ROUNDUP(R12/12,0) -> 1 | ... EM13: =ROUNDUP(EM12/12,0) -> 11 | EV13: 0 | EW13: =EV13+1 -> 1 | EX13: =EW13+1 -> 2 | EY13: =EX13+1 -> 3 | EZ13: =EY13+1 -> 4 | FA13: =EZ13+1 -> 5 | FB13: =FA13+1 -> 6 | FC13: =FB13+1 -> 7 | FD13: =FC13+1 -> 8
K14: =+Assumptions!I6 -> 44652 | L14: =EOMONTH(K14,0) -> 44681 | M14: =EOMONTH(L14,1) -> 44712 | N14: =EOMONTH(M14,1) -> 44742 | O14: =EOMONTH(N14,1) -> 44773 | P14: =EOMONTH(O14,1) -> 44804 | Q14: =EOMONTH(P14,1) -> 44834 | R14: =EOMONTH(Q14,1) -> 44865 | S14: =EOMONTH(R14,1) -> 44895 | T14: =EOMONTH(S14,1) -> 44926 | ... EM14: =EOMONTH(EL14,1) -> 48669 | ET14: 12 Months Ending: | EV14: =IF(EV$13=0,EOMONTH($K$14,0),EOMONTH(EU$14,12)) -> 44681 | EW14: =IF(EW$13=0,EOMONTH($K$14,0),EOMONTH(EV$14,12)) -> 45046 | EX14: =IF(EX$13=0,EOMONTH($K$14,0),EOMONTH(EW$14,12)) -> 45412 | EY14: =IF(EY$13=0,EOMONTH($K$14,0),EOMONTH(EX$14,12)) -> 45777 | EZ14: =IF(EZ$13=0,EOMONTH($K$14,0),EOMONTH(EY$14,12)) -> 46142 | FA14: =IF(FA$13=0,EOMONTH($K$14,0),EOMONTH(EZ$14,12)) -> 46507 | FB14: =IF(FB$13=0,EOMONTH($K$14,0),EOMONTH(FA$14,12)) -> 46873 | FC14: =IF(FC$13=0,EOMONTH($K$14,0),EOMONTH(FB$14,12)) -> 47238 | FD14: =IF(FD$13=0,EOMONTH($K$14,0),EOMONTH(FC$14,12)) -> 47603
B15: Unleveraged Costs | I15: Total | EP15: =B15 -> Unleveraged Costs | ET15: Total
B16: Acquisition Costs | EP16: =B16 -> Acquisition Costs
B17: =Assumptions!B12 -> Purchase Price | I17: =SUM(K17:EM17) -> 58250 | K17: =Assumptions!C12 -> 58250 | L17: 0 | M17: 0 | N17: 0 | O17: 0 | P17: 0 | Q17: 0 | R17: 0 | S17: 0 | T17: 0 | U17: 0 | V17: 0 | W17: 0 | X17: 0 | Y17: 0 | Z17: 0 | AA17: 0 | AB17: 0 | AC17: 0 | AD17: 0 | AE17: 0 | AF17: 0 | AG17: 0 | AH17: 0 | AI17: 0 | AJ17: 0 | AK17: 0 | AL17: 0 | AM17: 0 | AN17: 0 | AO17: 0 | AP17: 0 | AQ17: 0 | AR17: 0 | AS17: 0 | AT17: 0 | AU17: 0 | AV17: 0 | AW17: 0 | AX17: 0 | AY17: 0 | AZ17: 0 | BA17: 0 | BB17: 0 | BC17: 0 | BD17: 0 | BE17: 0 | BF17: 0 | BG17: 0 | BH17: 0 | BI17: 0 | BJ17: 0 | BK17: 0 | BL17: 0 | BM17: 0 | BN17: 0 | BO17: 0 | BP17: 0 | BQ17: 0 | BR17: 0 | BS17: 0 | BT17: 0 | BU17: 0 | BV17: 0 | BW17: 0 | BX17: 0 | BY17: 0 | BZ17: 0 | CA17: 0 | CB17: 0 | CC17: 0 | CD17: 0 | CE17: 0 | CF17: 0 | CG17: 0 | CH17: 0 | CI17: 0 | CJ17: 0 | CK17: 0 | CL17: 0 | CM17: 0 | CN17: 0 | CO17: 0 | CP17: 0 | CQ17: 0 | CR17: 0 | CS17: 0 | CT17: 0 | CU17: 0 | CV17: 0 | CW17: 0 | CX17: 0 | CY17: 0 | CZ17: 0 | DA17: 0 | DB17: 0 | DC17: 0 | DD17: 0 | DE17: 0 | DF17: 0 | DG17: 0 | DH17: 0 | DI17: 0 | DJ17: 0 | DK17: 0 | DL17: 0 | DM17: 0 | DN17: 0 | DO17: 0 | DP17: 0 | DQ17: 0 | DR17: 0 | DS17: 0 | DT17: 0 | DU17: 0 | DV17: 0 | DW17: 0 | DX17: 0 | DY17: 0 | DZ17: 0 | EA17: 0 | EB17: 0 | EC17: 0 | ED17: 0 | EE17: 0 | EF17: 0 | EG17: 0 | EH17: 0 | EI17: 0 | EJ17: 0 | EK17: 0 | EL17: 0 | EM17: 0 | EP17: =B17 -> Purchase Price | ET17: =SUM(EV17:FD17) -> 58250 | EV17: =SUMIF($K$13:$EM$13,EV$13,$K17:$EM17) -> 58250 | EW17: =SUMIF($K$13:$EM$13,EW$13,$K17:$EM17) -> 0 | EX17: =SUMIF($K$13:$EM$13,EX$13,$K17:$EM17) -> 0 | EY17: =SUMIF($K$13:$EM$13,EY$13,$K17:$EM17) -> 0 | EZ17: =SUMIF($K$13:$EM$13,EZ$13,$K17:$EM17) -> 0 | FA17: =SUMIF($K$13:$EM$13,FA$13,$K17:$EM17) -> 0 | FB17: =SUMIF($K$13:$EM$13,FB$13,$K17:$EM17) -> 0 | FC17: =SUMIF($K$13:$EM$13,FC$13,$K17:$EM17) -> 0 | FD17: =SUMIF($K$13:$EM$13,FD$13,$K17:$EM17) -> 0
B18: =Assumptions!B13 -> 0.011866953 | I18: =SUM(K18:EM18) -> 691.25 | K18: =Assumptions!C13 -> 691.25 | L18: 0 | M18: 0 | N18: 0 | O18: 0 | P18: 0 | Q18: 0 | R18: 0 | S18: 0 | T18: 0 | U18: 0 | V18: 0 | W18: 0 | X18: 0 | Y18: 0 | Z18: 0 | AA18: 0 | AB18: 0 | AC18: 0 | AD18: 0 | AE18: 0 | AF18: 0 | AG18: 0 | AH18: 0 | AI18: 0 | AJ18: 0 | AK18: 0 | AL18: 0 | AM18: 0 | AN18: 0 | AO18: 0 | AP18: 0 | AQ18: 0 | AR18: 0 | AS18: 0 | AT18: 0 | AU18: 0 | AV18: 0 | AW18: 0 | AX18: 0 | AY18: 0 | AZ18: 0 | BA18: 0 | BB18: 0 | BC18: 0 | BD18: 0 | BE18: 0 | BF18: 0 | BG18: 0 | BH18: 0 | BI18: 0 | BJ18: 0 | BK18: 0 | BL18: 0 | BM18: 0 | BN18: 0 | BO18: 0 | BP18: 0 | BQ18: 0 | BR18: 0 | BS18: 0 | BT18: 0 | BU18: 0 | BV18: 0 | BW18: 0 | BX18: 0 | BY18: 0 | BZ18: 0 | CA18: 0 | CB18: 0 | CC18: 0 | CD18: 0 | CE18: 0 | CF18: 0 | CG18: 0 | CH18: 0 | CI18: 0 | CJ18: 0 | CK18: 0 | CL18: 0 | CM18: 0 | CN18: 0 | CO18: 0 | CP18: 0 | CQ18: 0 | CR18: 0 | CS18: 0 | CT18: 0 | CU18: 0 | CV18: 0 | CW18: 0 | CX18: 0 | CY18: 0 | CZ18: 0 | DA18: 0 | DB18: 0 | DC18: 0 | DD18: 0 | DE18: 0 | DF18: 0 | DG18: 0 | DH18: 0 | DI18: 0 | DJ18: 0 | DK18: 0 | DL18: 0 | DM18: 0 | DN18: 0 | DO18: 0 | DP18: 0 | DQ18: 0 | DR18: 0 | DS18: 0 | DT18: 0 | DU18: 0 | DV18: 0 | DW18: 0 | DX18: 0 | DY18: 0 | DZ18: 0 | EA18: 0 | EB18: 0 | EC18: 0 | ED18: 0 | EE18: 0 | EF18: 0 | EG18: 0 | EH18: 0 | EI18: 0 | EJ18: 0 | EK18: 0 | EL18: 0 | EM18: 0 | EP18: =B18 -> 0.011866953 | ET18: =SUM(EV18:FD18) -> 691.25 | EV18: =SUMIF($K$13:$EM$13,EV$13,$K18:$EM18) -> 691.25 | EW18: =SUMIF($K$13:$EM$13,EW$13,$K18:$EM18) -> 0 | EX18: =SUMIF($K$13:$EM$13,EX$13,$K18:$EM18) -> 0 | EY18: =SUMIF($K$13:$EM$13,EY$13,$K18:$EM18) -> 0 | EZ18: =SUMIF($K$13:$EM$13,EZ$13,$K18:$EM18) -> 0 | FA18: =SUMIF($K$13:$EM$13,FA$13,$K18:$EM18) -> 0 | FB18: =SUMIF($K$13:$EM$13,FB$13,$K18:$EM18) -> 0 | FC18: =SUMIF($K$13:$EM$13,FC$13,$K18:$EM18) -> 0 | FD18: =SUMIF($K$13:$EM$13,FD$13,$K18:$EM18) -> 0
B19: Total Acquisition Costs | I19: =SUM(K19:EM19) -> 58941.25 | K19: =SUBTOTAL(9,K17:K18) -> 58941.25 | L19: =SUBTOTAL(9,L17:L18) -> 0 | M19: =SUBTOTAL(9,M17:M18) -> 0 | N19: =SUBTOTAL(9,N17:N18) -> 0 | O19: =SUBTOTAL(9,O17:O18) -> 0 | P19: =SUBTOTAL(9,P17:P18) -> 0 | Q19: =SUBTOTAL(9,Q17:Q18) -> 0 | R19: =SUBTOTAL(9,R17:R18) -> 0 | ... EM19: =SUBTOTAL(9,EM17:EM18) -> 0 | EP19: =B19 -> Total Acquisition Costs | ET19: =SUM(EV19:FD19) -> 58941.25 | EV19: =SUMIF($K$13:$EM$13,EV$13,$K19:$EM19) -> 58941.25 | EW19: =SUMIF($K$13:$EM$13,EW$13,$K19:$EM19) -> 0 | EX19: =SUMIF($K$13:$EM$13,EX$13,$K19:$EM19) -> 0 | EY19: =SUMIF($K$13:$EM$13,EY$13,$K19:$EM19) -> 0 | EZ19: =SUMIF($K$13:$EM$13,EZ$13,$K19:$EM19) -> 0 | FA19: =SUMIF($K$13:$EM$13,FA$13,$K19:$EM19) -> 0 | FB19: =SUMIF($K$13:$EM$13,FB$13,$K19:$EM19) -> 0 | FC19: =SUMIF($K$13:$EM$13,FC$13,$K19:$EM19) -> 0 | FD19: =SUMIF($K$13:$EM$13,FD$13,$K19:$EM19) -> 0
F20: Start | G20: End | H20: Budget
A21: HC | B21: =+Assumptions!B16 -> CapEx - Building Cost | F21: =Assumptions!$J8 -> 6 | G21: =Assumptions!$L8 -> 12 | H21: =Assumptions!$E16 -> 300 | I21: =SUMIF($L$12:$EM$12,"<="&Assumptions!$L$14,'Monthly Cash Flow'!L21:EM21) -> 300 | K21: =+Assumptions!C16 -> 0 | L21: =IF(AND(L$12>=$F21,L$12<$G21),$H21/($G21-$F21),0) -> 0 | M21: =IF(AND(M$12>=$F21,M$12<$G21),$H21/($G21-$F21),0) -> 0 | N21: =IF(AND(N$12>=$F21,N$12<$G21),$H21/($G21-$F21),0) -> 0 | O21: =IF(AND(O$12>=$F21,O$12<$G21),$H21/($G21-$F21),0) -> 0 | P21: =IF(AND(P$12>=$F21,P$12<$G21),$H21/($G21-$F21),0) -> 0 | Q21: =IF(AND(Q$12>=$F21,Q$12<$G21),$H21/($G21-$F21),0) -> 50 | R21: =IF(AND(R$12>=$F21,R$12<$G21),$H21/($G21-$F21),0) -> 50 | S21: =IF(AND(S$12>=$F21,S$12<$G21),$H21/($G21-$F21),0) -> 50 | ... EM21: =IF(AND(EM$12>=$F21,EM$12<$G21),$H21/($G21-$F21),0) -> 0 | EP21: =+B21 -> CapEx - Building Cost | ET21: =SUM(EV21:FD21) -> 300 | EV21: =SUMIF($K$13:$EM$13,EV$13,$K21:$EM21) -> 0 | EW21: =SUMIF($K$13:$EM$13,EW$13,$K21:$EM21) -> 300 | EX21: =SUMIF($K$13:$EM$13,EX$13,$K21:$EM21) -> 0 | EY21: =SUMIF($K$13:$EM$13,EY$13,$K21:$EM21) -> 0 | EZ21: =SUMIF($K$13:$EM$13,EZ$13,$K21:$EM21) -> 0 | FA21: =SUMIF($K$13:$EM$13,FA$13,$K21:$EM21) -> 0 | FB21: =SUMIF($K$13:$EM$13,FB$13,$K21:$EM21) -> 0 | FC21: =SUMIF($K$13:$EM$13,FC$13,$K21:$EM21) -> 0 | FD21: =SUMIF($K$13:$EM$13,FD$13,$K21:$EM21) -> 0
B22: =+Assumptions!B17 -> Construction Costs - Site Work | F22: =Assumptions!$J9 -> 1 | G22: =Assumptions!$L9 -> 7 | H22: =Assumptions!$E17 -> 0 | I22: =SUMIF($K$12:$EM$12,"<="&Assumptions!$L$14,'Monthly Cash Flow'!K22:EM22) -> 0 | K22: =IF(AND(K$12>=$F22,K$12<$G22),$H22/($G22-$F22),0) -> 0 | L22: =IF(AND(L$12>=$F22,L$12<$G22),$H22/($G22-$F22),0) -> 0 | M22: =IF(AND(M$12>=$F22,M$12<$G22),$H22/($G22-$F22),0) -> 0 | N22: =IF(AND(N$12>=$F22,N$12<$G22),$H22/($G22-$F22),0) -> 0 | O22: =IF(AND(O$12>=$F22,O$12<$G22),$H22/($G22-$F22),0) -> 0 | P22: =IF(AND(P$12>=$F22,P$12<$G22),$H22/($G22-$F22),0) -> 0 | Q22: =IF(AND(Q$12>=$F22,Q$12<$G22),$H22/($G22-$F22),0) -> 0 | R22: =IF(AND(R$12>=$F22,R$12<$G22),$H22/($G22-$F22),0) -> 0 | ... EM22: =IF(AND(EM$12>=$F22,EM$12<$G22),$H22/($G22-$F22),0) -> 0 | EP22: =+B22 -> Construction Costs - Site Work | ET22: =SUM(EV22:FD22) -> 0 | EV22: =SUMIF($K$13:$EM$13,EV$13,$K22:$EM22) -> 0 | EW22: =SUMIF($K$13:$EM$13,EW$13,$K22:$EM22) -> 0 | EX22: =SUMIF($K$13:$EM$13,EX$13,$K22:$EM22) -> 0 | EY22: =SUMIF($K$13:$EM$13,EY$13,$K22:$EM22) -> 0 | EZ22: =SUMIF($K$13:$EM$13,EZ$13,$K22:$EM22) -> 0 | FA22: =SUMIF($K$13:$EM$13,FA$13,$K22:$EM22) -> 0 | FB22: =SUMIF($K$13:$EM$13,FB$13,$K22:$EM22) -> 0 | FC22: =SUMIF($K$13:$EM$13,FC$13,$K22:$EM22) -> 0 | FD22: =SUMIF($K$13:$EM$13,FD$13,$K22:$EM22) -> 0
B23: =+Assumptions!B18 -> Soft Costs | F23: =Assumptions!$J10 -> 3 | G23: =Assumptions!$L10 -> 6 | H23: =Assumptions!$E18 -> 0 | I23: =SUMIF($K$12:$EM$12,"<="&Assumptions!$L$14,'Monthly Cash Flow'!K23:EM23) -> 0 | K23: =IF(AND(K$12>=$F$23,K$12<$G$23),$H$23/($G$23-$F$23),0) -> 0 | L23: =IF(AND(L$12>=$F$23,L$12<$G$23),$H$23/($G$23-$F$23),0) -> 0 | M23: =IF(AND(M$12>=$F$23,M$12<$G$23),$H$23/($G$23-$F$23),0) -> 0 | N23: =IF(AND(N$12>=$F$23,N$12<$G$23),$H$23/($G$23-$F$23),0) -> 0 | O23: =IF(AND(O$12>=$F$23,O$12<$G$23),$H$23/($G$23-$F$23),0) -> 0 | P23: =IF(AND(P$12>=$F$23,P$12<$G$23),$H$23/($G$23-$F$23),0) -> 0 | Q23: =IF(AND(Q$12>=$F$23,Q$12<$G$23),$H$23/($G$23-$F$23),0) -> 0 | R23: =IF(AND(R$12>=$F$23,R$12<$G$23),$H$23/($G$23-$F$23),0) -> 0 | ... EM23: =IF(AND(EM$12>=$F$23,EM$12<$G$23),$H$23/($G$23-$F$23),0) -> 0 | EP23: =+B23 -> Soft Costs | ET23: =SUM(EV23:FD23) -> 0 | EV23: =SUMIF($K$13:$EM$13,EV$13,$K23:$EM23) -> 0 | EW23: =SUMIF($K$13:$EM$13,EW$13,$K23:$EM23) -> 0 | EX23: =SUMIF($K$13:$EM$13,EX$13,$K23:$EM23) -> 0 | EY23: =SUMIF($K$13:$EM$13,EY$13,$K23:$EM23) -> 0 | EZ23: =SUMIF($K$13:$EM$13,EZ$13,$K23:$EM23) -> 0 | FA23: =SUMIF($K$13:$EM$13,FA$13,$K23:$EM23) -> 0 | FB23: =SUMIF($K$13:$EM$13,FB$13,$K23:$EM23) -> 0 | FC23: =SUMIF($K$13:$EM$13,FC$13,$K23:$EM23) -> 0 | FD23: =SUMIF($K$13:$EM$13,FD$13,$K23:$EM23) -> 0
B24: =+Assumptions!B19 -> Contingency | F24: =Assumptions!$J11 -> 6 | G24: =Assumptions!$L11 -> 12 | H24: =Assumptions!$E19 -> 0 | I24: =SUMIF($K$12:$EM$12,"<="&Assumptions!$L$14,'Monthly Cash Flow'!K24:EM24) -> 0 | K24: =IF(AND(K$12>=$F$24,K$12<$G$24),$H$24/($G$24-$F$24),0) -> 0 | L24: =IF(AND(L$12>=$F$24,L$12<$G$24),$H$24/($G$24-$F$24),0) -> 0 | M24: =IF(AND(M$12>=$F$24,M$12<$G$24),$H$24/($G$24-$F$24),0) -> 0 | N24: =IF(AND(N$12>=$F$24,N$12<$G$24),$H$24/($G$24-$F$24),0) -> 0 | O24: =IF(AND(O$12>=$F$24,O$12<$G$24),$H$24/($G$24-$F$24),0) -> 0 | P24: =IF(AND(P$12>=$F$24,P$12<$G$24),$H$24/($G$24-$F$24),0) -> 0 | Q24: =IF(AND(Q$12>=$F$24,Q$12<$G$24),$H$24/($G$24-$F$24),0) -> 0 | R24: =IF(AND(R$12>=$F$24,R$12<$G$24),$H$24/($G$24-$F$24),0) -> 0 | ... EM24: =IF(AND(EM$12>=$F$24,EM$12<$G$24),$H$24/($G$24-$F$24),0) -> 0 | EP24: =+B24 -> Contingency | ET24: =SUM(EV24:FD24) -> 0 | EV24: =SUMIF($K$13:$EM$13,EV$13,$K24:$EM24) -> 0 | EW24: =SUMIF($K$13:$EM$13,EW$13,$K24:$EM24) -> 0 | EX24: =SUMIF($K$13:$EM$13,EX$13,$K24:$EM24) -> 0 | EY24: =SUMIF($K$13:$EM$13,EY$13,$K24:$EM24) -> 0 | EZ24: =SUMIF($K$13:$EM$13,EZ$13,$K24:$EM24) -> 0 | FA24: =SUMIF($K$13:$EM$13,FA$13,$K24:$EM24) -> 0 | FB24: =SUMIF($K$13:$EM$13,FB$13,$K24:$EM24) -> 0 | FC24: =SUMIF($K$13:$EM$13,FC$13,$K24:$EM24) -> 0 | FD24: =SUMIF($K$13:$EM$13,FD$13,$K24:$EM24) -> 0
B25: =+Assumptions!B20 -> Other Fees/ General Conditions | F25: =Assumptions!$J12 -> 1 | G25: =Assumptions!$L12 -> 7 | H25: =Assumptions!$E20 -> 0 | I25: =SUMIF($K$12:$EM$12,"<="&Assumptions!$L$14,'Monthly Cash Flow'!K25:EM25) -> 0 | K25: =IF(AND(K$12>=$F$25,K$12<$G$25),$H$25/($G$25-$F$25),0) -> 0 | L25: =IF(AND(L$12>=$F$25,L$12<$G$25),$H$25/($G$25-$F$25),0) -> 0 | M25: =IF(AND(M$12>=$F$25,M$12<$G$25),$H$25/($G$25-$F$25),0) -> 0 | N25: =IF(AND(N$12>=$F$25,N$12<$G$25),$H$25/($G$25-$F$25),0) -> 0 | O25: =IF(AND(O$12>=$F$25,O$12<$G$25),$H$25/($G$25-$F$25),0) -> 0 | P25: =IF(AND(P$12>=$F$25,P$12<$G$25),$H$25/($G$25-$F$25),0) -> 0 | Q25: =IF(AND(Q$12>=$F$25,Q$12<$G$25),$H$25/($G$25-$F$25),0) -> 0 | R25: =IF(AND(R$12>=$F$25,R$12<$G$25),$H$25/($G$25-$F$25),0) -> 0 | ... EM25: =IF(AND(EM$12>=$F$25,EM$12<$G$25),$H$25/($G$25-$F$25),0) -> 0 | EP25: =+B25 -> Other Fees/ General Conditions | ET25: =SUM(EV25:FD25) -> 0 | EV25: =SUMIF($K$13:$EM$13,EV$13,$K25:$EM25) -> 0 | EW25: =SUMIF($K$13:$EM$13,EW$13,$K25:$EM25) -> 0 | EX25: =SUMIF($K$13:$EM$13,EX$13,$K25:$EM25) -> 0 | EY25: =SUMIF($K$13:$EM$13,EY$13,$K25:$EM25) -> 0 | EZ25: =SUMIF($K$13:$EM$13,EZ$13,$K25:$EM25) -> 0 | FA25: =SUMIF($K$13:$EM$13,FA$13,$K25:$EM25) -> 0 | FB25: =SUMIF($K$13:$EM$13,FB$13,$K25:$EM25) -> 0 | FC25: =SUMIF($K$13:$EM$13,FC$13,$K25:$EM25) -> 0 | FD25: =SUMIF($K$13:$EM$13,FD$13,$K25:$EM25) -> 0
B27: Leasing Costs | EP27: =B27 -> Leasing Costs
A28: TI | B28: Tenant Improvements | I28: =SUMIF($L$12:$EM$12,"<="&Assumptions!$L$14,'Monthly Cash Flow'!L28:EM28) -> 839.326 | K28: =+Assumptions!C22 -> 0 | L28: =IFERROR(OFFSET('ARGUS '!$B$3, MATCH($A28, 'ARGUS '!$A$3:$A$179, 0)-1,MATCH(L$14, 'ARGUS '!$B$4:$LG$4, 0)-1,1,1)/1000, 0) -> 0 | M28: =IFERROR(OFFSET('ARGUS '!$B$3, MATCH($A28, 'ARGUS '!$A$3:$A$179, 0)-1,MATCH(M$14, 'ARGUS '!$B$4:$LG$4, 0)-1,1,1)/1000, 0) -> 0 | N28: =IFERROR(OFFSET('ARGUS '!$B$3, MATCH($A28, 'ARGUS '!$A$3:$A$179, 0)-1,MATCH(N$14, 'ARGUS '!$B$4:$LG$4, 0)-1,1,1)/1000, 0) -> 0 | O28: =IFERROR(OFFSET('ARGUS '!$B$3, MATCH($A28, 'ARGUS '!$A$3:$A$179, 0)-1,MATCH(O$14, 'ARGUS '!$B$4:$LG$4, 0)-1,1,1)/1000, 0) -> 0 | P28: =IFERROR(OFFSET('ARGUS '!$B$3, MATCH($A28, 'ARGUS '!$A$3:$A$179, 0)-1,MATCH(P$14, 'ARGUS '!$B$4:$LG$4, 0)-1,1,1)/1000, 0) -> 0 | Q28: =IFERROR(OFFSET('ARGUS '!$B$3, MATCH($A28, 'ARGUS '!$A$3:$A$179, 0)-1,MATCH(Q$14, 'ARGUS '!$B$4:$LG$4, 0)-1,1,1)/1000, 0) -> 46.8 | R28: =IFERROR(OFFSET('ARGUS '!$B$3, MATCH($A28, 'ARGUS '!$A$3:$A$179, 0)-1,MATCH(R$14, 'ARGUS '!$B$4:$LG$4, 0)-1,1,1)/1000, 0) -> 46.8 | S28: =IFERROR(OFFSET('ARGUS '!$B$3, MATCH($A28, 'ARGUS '!$A$3:$A$179, 0)-1,MATCH(S$14, 'ARGUS '!$B$4:$LG$4, 0)-1,1,1)/1000, 0) -> 46.8 | ... EM28: =IFERROR(OFFSET('ARGUS '!$B$3, MATCH($A28, 'ARGUS '!$A$3:$A$179, 0)-1,MATCH(EM$14, 'ARGUS '!$B$4:$LG$4, 0)-1,1,1)/1000, 0) -> 0 | EP28: =B28 -> Tenant Improvements | ET28: =SUM(EV28:FD28) -> 1766.244 | EV28: =SUMIF($K$13:$EM$13,EV$13,$K28:$EM28) -> 0 | EW28: =SUMIF($K$13:$EM$13,EW$13,$K28:$EM28) -> 342.4 | EX28: =SUMIF($K$13:$EM$13,EX$13,$K28:$EM28) -> 496.926 | EY28: =SUMIF($K$13:$EM$13,EY$13,$K28:$EM28) -> 0 | EZ28: =SUMIF($K$13:$EM$13,EZ$13,$K28:$EM28) -> 0 | FA28: =SUMIF($K$13:$EM$13,FA$13,$K28:$EM28) -> 401.688 | FB28: =SUMIF($K$13:$EM$13,FB$13,$K28:$EM28) -> 0 | FC28: =SUMIF($K$13:$EM$13,FC$13,$K28:$EM28) -> 525.23 | FD28: =SUMIF($K$13:$EM$13,FD$13,$K28:$EM28) -> 0
EP29: =B29 -> 0 | ET29: =SUM(EV29:FD29) -> 0 | EV29: =SUMIF($K$13:$EM$13,EV$13,$K29:$EM29) -> 0 | EW29: =SUMIF($K$13:$EM$13,EW$13,$K29:$EM29) -> 0 | EX29: =SUMIF($K$13:$EM$13,EX$13,$K29:$EM29) -> 0 | EY29: =SUMIF($K$13:$EM$13,EY$13,$K29:$EM29) -> 0 | EZ29: =SUMIF($K$13:$EM$13,EZ$13,$K29:$EM29) -> 0 | FA29: =SUMIF($K$13:$EM$13,FA$13,$K29:$EM29) -> 0 | FB29: =SUMIF($K$13:$EM$13,FB$13,$K29:$EM29) -> 0 | FC29: =SUMIF($K$13:$EM$13,FC$13,$K29:$EM29) -> 0 | FD29: =SUMIF($K$13:$EM$13,FD$13,$K29:$EM29) -> 0
