Workbook
Name _: #REF!
Name _______________: #REF!
Name ________EXP1: #REF!
Name __C: #REF!
Name _1_96100: #REF!
Name _1201T1: #REF!
Name _1202T1: #N/A
Name _1206T1: #REF!
Name _1207T1: #REF!
Name _1208T1: #REF!
Name _1210T1: #REF!
Name _1211T1: #REF!
Name _1216T1: #REF!
Name _1217T1: #REF!
Name _1218T1: #REF!
Name _1219T1: #REF!
Name _1220T1: #REF!
Name _1220T2: #REF!
Name _1221T1: #REF!
Name _1222T1: #REF!
Name _1223T1: #REF!
Name _1224T1: #REF!
Name _1226T2: #REF!
Name _1231T: #REF!
Name _1231T1: #REF!
Name _1233T1: #REF!
Name _1234T2: #REF!
Name _1235T1: #REF!
Name _1236T1: #REF!
Name _1238T1: #REF!
Name _1239T1: #REF!
Name _1239T3: #REF!
Name _1240T1: #REF!
Name _1248T3: #REF!
Name _1251T1: #REF!
Name _1251T2: #REF!
Name _1252T1: #REF!
Name _1252T2: #REF!
Name _1256T1: #REF!
Name _1257T1: #REF!
Name _1258T1: #REF!
Name _1260T1: #REF!
Name _1260T2: #REF!
Name _1261T1: #REF!
Name _1262T1: #REF!
Name _1264T1: #REF!
Name _1265T1: #REF!
Name _1268T2: #REF!
Name _1273T1: #REF!
Name _1276T1: #REF!
Name _1280T1: #REF!
Name _1281T1: #REF!
Name _1992: #REF!
Name _1993: #REF!
Name _1994: #REF!
Name _450: #REF!
Name _450.INT: #REF!
Name _451: #REF!
Name _451.INT: #REF!
Name _502: #REF!

Sheet Disclaimer
B3: =+Assumptions!B2 -> Chapman Plaza
B4: =TODAY() -> 46153
B6: DISCLAIMER
B7: This confidential summary contains forward-looking statements that are not historical facts. These forward-looking statements include statements, express or implied, regarding the current expectations, estimates, projections, opinions and beliefs of the Arc Capital Partners LLC ("Company"), as well as certain assumptions on which those statements are based. Such forward-looking statements are subject to risks, uncertainties and other factors that may cause actual events to differ materially from any anticipated development and no assurance can be given that the Company, or any investment vehicle that may be formed or managed by the Company in the future, will achieve the projected returns. The pro forma information set forth in this confidential summary is shown for illustration purposes only and should not be relied upon. No representation or assurance is made that any potential investor will or is likely to achieve results comparable to those shown or will make any profit or will be able to avoid incurring substantial losses. The information contained herein is confidential and intended solely for use by the Company and persons to whom the Company has delivered this document. This confidential summary is not to be reproduced or distributed to any third party. The recipient, by accepting this document, agrees to this restriction and to return the document to the Company upon request. The pro forma information reflects the Company’s judgment, based on current circumstances, of the most likely set of conditions and its most likely course of action. The assumptions disclosed herein are those that the Company believes are significant to the pro forma information or are key factors upon which the financial results of the Company and any potential real estate investment opportunity depend. Some assumptions inevitably will not materialize and unanticipated events and circumstances may occur subsequent to the date of this information. Therefore, the actual results achieved during the forecast period will vary from the forecast, and the variations may be material. None of the Company, its managers, officers, directors, employees or affiliates assume any responsibility to notify recipients of any updates to this pro forma information if there are changes to the assumptions or results. Recipients are encouraged to consult with their own professional advisors concerning this pro forma information, including the assumptions used. The Company will make available additional information upon request concerning the pro forma information to the extent it is readily available to the Company at no additional cost and the Company is not otherwise restricted from providing such information.

Sheet Major Changes 2023
B2: Lease Up Revisions (2020, 2021 and 2022)
E3: Base Rent Assumptions | I3: Lease up Assumption | L3: TIs PSF Assumption
D4: Term | E4: 2020 | F4: 2021 | G4: 2022 | H4: Delta | I4: 2020 | J4: 2021 | K4: 2022 | L4: 2020 | M4: 2021 | N4: 2022 | O4: Delta
B5: 200 | C5: VACANT | D5: 5 years | E5: 3.5 | F5: 2.5 | G5: 2.5 | H5: =F5-G5 -> 0 | I5: 44196 | J5: 44593 | K5: 44835 | L5: 80 | M5: 100 | N5: 100 | O5: =N5-M5 -> 0
B6: 300 | C6: VACANT | D6: 5 years | E6: 3.5 | F6: 2.5 | G6: 2.5 | H6: =F6-G6 -> 0 | I6: 44196 | J6: 44470 | K6: 44835 | L6: 25 | M6: 25 | N6: 45 | O6: =N6-M6 -> 20
B11: Current Rent Roll
E12: Base Rent (PSF) | J12: Rent Renewal | N12: Renewal TI Assumptions
B13: Suite # | C13: Tenant | D13: Lease Expiration | E13: 2020 | F13: 2021 | G13: 2022 | M13: Delta | N13: 2019 | O13: 2020 | P13: 2021 | Q13: Delta | R13: Comments
B14: 10/180 | C14: Shibuyala | D14: 44834 | E14: 5.75 | F14: 6 | M14: 0 | N14: 40 | O14: 40 | P14: 18.03 | Q14: =P14-O14 -> -21.97 | R14: Expansion space buildout completed
B15: 010, 020 | C15: Baekjeong | E15: 5.5 | F15: 5.75 | M15: 0 | N15: 0 | O15: 0 | P15: 17.5 | Q15: =P15-O15 -> 17.5 | R15: Current
B16: 40 | C16: Starbucks | D16: 46904 | E16: 5.5 | F16: 5.5 | M16: 0 | N16: 75 | O16: 75 | P16: 21.52 | Q16: =P16-O16 -> -53.48 | R16: Current
B17: 50 | C17: Kazunori (LOI) | D17: =EOMONTH(L17,15*12-1) -> 5479 | E17: 6 | F17: 5.25 | N17: 75 | O17: 50 | P17: 60 | Q17: =P17-O17 -> 10 | R17: Signed lease expected week of 12/7/2020
B18: 65 | C18: Project 11 11 (LOI) | D18: 46204 | E18: 4.6 | F18: 3.75 | M18: 0 | N18: 50 | O18: 50 | P18: 35 | Q18: =P18-O18 -> -15 | R18: Interested in the Gaam #300 space
B19: 70 | C19: Escala | D19: 45291 | E19: 5.75 | F19: 5.5 | M19: 0 | N19: 20 | O19: 20 | P19: 22.17 | Q19: =P19-O19 -> 2.17 | R19: Current
B20: 80 | C20: GER Bar | D20: 47422 | E20: 5.08 | F20: 4.5 | M20: 2 | N20: 50 | O20: 50 | P20: 22.17 | Q20: =P20-O20 -> -27.83 | R20: Payment plan has been accepted by tenant
B21: 150 | C21: Hikari | D21: 45107 | E21: 6 | F21: 5.5 | M21: 0 | N21: 0 | O21: 0 | P21: 18.57 | Q21: =P21-O21 -> 18.57 | R21: Current
B22: 110 | C22: Toe Bang | D22: 44985 | E22: 5.4207829 | F22: 5.5 | M22: 0 | N22: 0 | O22: 0 | P22: 18.57 | Q22: =P22-O22 -> 18.57 | R22: Payment plan in progress for $133k+ in A/R
B23: 120, 140 | C23: Tiger Sugar Boba | D23: 44681 | E23: 5.5 | F23: 6 | M23: 0 | N23: 40 | O23: 40 | P23: 19.7 | Q23: =P23-O23 -> -20.3 | R23: TI buildout approved, construction to commence Dec-2020
B24: 160 | C24: Silver Lake Ramen | D24: 47269 | E24: 6.14 | F24: 6 | M24: 2 | N24: 50 | O24: 50 | P24: 22.17 | Q24: =P24-O24 -> -27.83 | R24: Current
B25: 130 | C25: Quarters | D25: 45138 | E25: 5.25 | F25: 5.5 | M25: 0 | N25: 0 | O25: 0 | P25: 18.57 | Q25: =P25-O25 -> 18.57 | R25: Current
B26: 170 | C26: Uncle Tetsu | E26: 0 | F26: 0 | G26: 5.75
B28: Total/Weighted Average | E28: =AVERAGE(E3:E7) -> 675.66667 | F28: =AVERAGE(F3:F7) -> 675.33333 | H28: =AVERAGE(H3:H7) -> 0 | N28: =AVERAGE(N3:N7) -> 722.33333 | O28: =AVERAGE(O3:O7) -> 10 | P28: =AVERAGE(P4:P7) -> #DIV/0! | Q28: =AVERAGE(Q3:Q7) -> #DIV/0!
B30: Other Major Revisions (2022 vs 2021 Business Plan)
B31: Assumptions ($'s in 000's) | O31: 2021 | P31: 2022 | Q31: Delta | R31: Comments
B32: Exit Cap Rate | O32: 0.05 | Q32: 0 | R32: Current broker feedback is 4.50% - 5.25%
B33: Sale Date | O33: 45291 | Q33: 36 | R33: New stabilization period, optionality for early sale
B34: CapEx Budget (2021 Forecast) | O34: =Assumptions!M92 -> 0 | Q34: =O34-#REF! -> #REF! | R34: CapEx (with optionality) planned for 2021
B35: Net Parking Income (annual) | O35: =13*12 -> 156 | Q35: =O35-#REF! -> #REF! | R35: Signed license agreement with PCAM
B36: Event & Kiosk Income (annual) | O36: 60 | Q36: =O36-#REF! -> #REF! | R36: Revised $5k/mo event assumption & removed kiosk income
B37: Patio SF (BOMA) | Q37: 371.3 | R37: Includes Silver Lake Ramen patio
B39: Refinance (June 2021)
B40: Total Proceeds | O40: =Assumptions!F62 -> 22133.64 | Q40: =O40-#REF! -> #REF! | R40: Approx. proceeds expected
B41: TI/LC Reserve | O41: Incl. above | Q41: - | R41: Approx. proceeds expected
B42: CapEx Reserve | O42: Incl. above | Q42: - | R42: Approx. proceeds expected
B43: Pricing | O43: =Assumptions!D65 -> 490 | Q43: =O43-#REF! -> #REF! | R43: Change from UBS terms to new lender post-Covid
B44: Loan Origination/Broker Fee & Exit Fee | O44: 1.0% / 0.50% | R44: Proforma
B47: (1) Tenant Improvements for new leases are blended at $50/sf for new leases and $0/sf for renewals, with 65% renewal probability
C48: =PMT(4.5%/12,360,-1)*12 -> 0.060802237
B50: Projected Returns Summary
D51: 2020 | E51: 2021 | F51: 2022 | G51: 2023
B52: Assumptions1,2
B53: Sales Date | D53: 44166 | E53: 45261 | F53: 44896 | G53: =Assumptions!I17 -> 45657
B54: Sales Price | D54: 49509 | E54: 58201 | F54: 50485 | G54: =Assumptions!L23 -> 56809.52
B55: Sales Price/SF | D55: 1166 | E55: 1403 | F55: 1217 | G55: =Assumptions!K23 -> 1369.9274
B56: Capped NOI | D56: 2474 | E56: 2910 | F56: 2018 | G56: =Assumptions!L21 -> 2690.476
B57: Cap Rate | D57: 0.05 | E57: 0.05 | F57: 0.0425 | G57: =Assumptions!L22 -> 0.05
B58: Unleveraged Returns
B59: IRR | D59: 0.116 | E59: 0.077 | F59: 0.059 | G59: =Assumptions!O22 -> 0.057904282
B60: Multiple | D60: 1.58 | E60: 1.68 | F60: 1.42 | G60: ='Monthly Cash Flow'!I95 -> 1.55
B61: Contribution | D61: 32854 | E61: 36954 | F61: 36367 | G61: =Assumptions!Q22 -> 37647.066
B62: Profit | D62: 19169 | E62: 25260 | F62: 15327 | G62: =Assumptions!R22 -> 20705.888
B63: Leveraged Returns
B64: IRR | D64: 0.162 | E64: 0.124 | F64: 0.087 | G64: =Assumptions!O23 -> 0.071606448
B65: Multiple | D65: 1.93 | E65: 2.26 | F65: 1.63 | G65: =Assumptions!P23 -> 1.7510529
B66: Contribution | D66: 14248 | E66: 16032 | F66: 16904 | G66: =Assumptions!Q23 -> 15882.232
B67: Profit | D67: 13248 | E67: 20152 | F67: 10358 | G67: =Assumptions!R23 -> 11928.396
B69: Original UW (2017 Business Plan)
D70: IRR | E70: Multiple | F70: Contribution | G70: Profit
B71: Unleveraged Returns | D71: 0.12188486 | E71: 1.7049647 | F71: 36167.51 | G71: 25496.817
B72: Profit from Cash Flow | D72: n/a | E72: n/a | F72: n/a | G72: 11082.133
B73: Profit from Appreciation | D73: n/a | E73: n/a | F73: n/a | G73: 14414.684
B74: Leveraged Returns | D74: 0.1596777 | E74: 1.9684087 | F74: 17044.402 | G74: 16505.947
B76: Source
B77: 2022 Returns: Chapman Plaza - 2022 Business Plan Model
B78: 2021 Returns: Chapman Plaza - 2021 Business Plan Model
B79: 2020 Returns: Chapman Plaza - 2020 Business Plan Model - VF Belay 5 Cap
B80: 2019 Returns: Chapman Plaza - 2019 Business Plan Model v2
B81: Original UW: Chapman Plaza Model_2016-11-04_v97
B83: Sensitivity Chart - Levered IRR and EM
D84: =Assumptions!U30 -> 45291 | E84: =Assumptions!V30 -> 45473 | F84: =Assumptions!W30 -> 45565 | G84: =Assumptions!X30 -> 45657
C85: =Assumptions!T31 -> 0.0425 | D85: =Assumptions!U31 -> 9.0% / 1.8x | E85: =Assumptions!V31 -> 11.4% / 2.3x | F85: =Assumptions!W31 -> 11.1% / 2.3x | G85: =Assumptions!X31 -> 10.9% / 2.3x
C86: =Assumptions!T32 -> 0.045 | D86: =Assumptions!U32 -> 7.4% / 1.7x | E86: =Assumptions!V32 -> 10.1% / 2.1x | F86: =Assumptions!W32 -> 9.8% / 2.1x | G86: =Assumptions!X32 -> 9.6% / 2.1x
C87: =Assumptions!T33 -> 0.0475 | D87: =Assumptions!U33 -> 5.9% / 1.5x | E87: =Assumptions!V33 -> 8.7% / 1.9x | F87: =Assumptions!W33 -> 8.5% / 1.9x | G87: =Assumptions!X33 -> 8.4% / 1.9x
C88: =Assumptions!T34 -> 0.05 | D88: =Assumptions!U34 -> 4.4% / 1.4x | E88: =Assumptions!V34 -> 7.4% / 1.7x | F88: =Assumptions!W34 -> 7.2% / 1.7x | G88: =Assumptions!X34 -> 7.2% / 1.8x
C89: =Assumptions!T35 -> 0.0525 | D89: =Assumptions!U35 -> 2.9% / 1.2x | E89: =Assumptions!V35 -> 6.2% / 1.6x | F89: =Assumptions!W35 -> 6.0% / 1.6x | G89: =Assumptions!X35 -> 6.0% / 1.6x
C90: =Assumptions!T36 -> 0.055 | D90: =Assumptions!U36 -> 1.4% / 1.1x | E90: =Assumptions!V36 -> 4.9% / 1.4x | F90: =Assumptions!W36 -> 4.8% / 1.4x | G90: =Assumptions!X36 -> 4.8% / 1.5x
B92: Sensitivity Chart - Sales Price ('000)
D93: =D84 -> 45291 | E93: =E84 -> 45473 | F93: =F84 -> 45565 | G93: =G84 -> 45657
C94: =Assumptions!T44 -> 0.0425 | D94: =Assumptions!U44 -> 58343.435 | E94: =Assumptions!V44 -> 65528.494 | F94: =Assumptions!W44 -> 65916.706 | G94: =Assumptions!X44 -> 66305.318
C95: =Assumptions!T45 -> 0.045 | D95: =Assumptions!U45 -> 55268.8 | E95: =Assumptions!V45 -> 62054.689 | F95: =Assumptions!W45 -> 62421.333 | G95: =Assumptions!X45 -> 62788.356
C96: =Assumptions!T46 -> 0.0475 | D96: =Assumptions!U46 -> 52517.811 | E96: =Assumptions!V46 -> 58946.547 | F96: =Assumptions!W46 -> 59293.895 | G96: =Assumptions!X46 -> 59641.6
C97: =Assumptions!T47 -> 0.05 | D97: =Assumptions!U47 -> 50041.92 | E97: =Assumptions!V47 -> 56149.22 | F97: =Assumptions!W47 -> 56479.2 | G97: =Assumptions!X47 -> 56809.52
C98: =Assumptions!T48 -> 0.0525 | D98: =Assumptions!U48 -> 47801.829 | E98: =Assumptions!V48 -> 53618.305 | F98: =Assumptions!W48 -> 53932.571 | G98: =Assumptions!X48 -> 54247.162
C99: =Assumptions!T49 -> 0.055 | D99: =Assumptions!U49 -> 45765.382 | E99: =Assumptions!V49 -> 51317.473 | F99: =Assumptions!W49 -> 51617.455 | G99: =Assumptions!X49 -> 51917.745
B100: Note:
B101: 1. 2022 and 2023 sales price includes $3MM land price added to the value of improvements
B102: 2. 2023 net exit proceeds include 5% of ULA tax to the sales price

Sheet Charts
B3: =+Assumptions!B2 -> Chapman Plaza
B4: Deal Snapshot
A6: x | B6: Property Overview
B7: Property Type | D7: Retail | F7: Year Built/Renovated | I7: 1928/2017
B8: NRA (SF) | D8: =Assumptions!$F$7 -> 41469 | F8: Market | I8: Los Angeles
B9: Current Occupancy | D9: 0.6 | F9: Submarket | I9: Koreatown
B10: Parking Stalls | D10: 102 | F10: Sponsor | I10: Arc Capital Partners
A12: x | B12: Sources & Uses
G13: At Close | H13: Lease Up | I13: Total | J13: $ PSF | K13: %
B14: Debt | G14: =+Assumptions!F46 -> 19541 | H14: =+Assumptions!F49 -> 2254.794 | I14: =+G14+H14 -> 21795.794 | J14: =+I14/$D$8*1000 -> 525.59247 | K14: =+I14/$I$17 -> 0.52847275
B15: Equity | G15: =(G$29-G$14-G16) -> 13708 | H15: =(H$29-H$14-H16) -> 5624.7811 | I15: =+G15+H15 -> 19332.781 | J15: =+I15/$D$8*1000 -> 466.19839 | K15: =+I15/$I$17 -> 0.46875319
B16: Project Cash Flow | G16: 0 | H16: =+Assumptions!J69 -> 114.41053 | I16: =+G16+H16 -> 114.41053 | J16: =+I16/$D$8*1000 -> 2.7589411 | K16: =+I16/$I$17 -> 0.0027740603
B17: Total Sources | G17: =SUM(G14:G16) -> 33249 | H17: =SUM(H14:H16) -> 7993.9856 | I17: =SUM(I14:I16) -> 41242.986 | J17: =SUM(J14:J16) -> 994.5498 | K17: =SUM(K14:K16) -> 1
B19: =+Assumptions!H53 -> Purchase Price | G19: =+Assumptions!C12 -> 30000 | H19: 0 | I19: =+G19+H19 -> 30000 | J19: =+I19/$D$8*1000 -> 723.43196 | K19: =+I19/$I$29 -> 0.72739642
B20: Reserves Funded at Close | G20: =-'Monthly Cash Flow'!$K$180 -> 2473 | H20: 0 | I20: =+G20+H20 -> 2473 | J20: =+I20/$D$8*1000 -> 59.634908 | K20: =+I20/$I$29 -> 0.059961711
B21: =+Assumptions!H54 -> Closing Costs | G21: =+Assumptions!C13 -> 206 | H21: 0 | I21: =+G21+H21 -> 206 | J21: =+I21/$D$8*1000 -> 4.9675661 | K21: =+I21/$I$29 -> 0.0049947887
B22: =+Assumptions!H56 -> Operating Losses | G22: 0 | H22: =+Assumptions!J56 -> 499.20616 | I22: =+G22+H22 -> 499.20616 | J22: =+I22/$D$8*1000 -> 12.038056 | K22: =+I22/$I$29 -> 0.012104026
B23: =+Assumptions!H57 -> CapEx | G23: 0 | H23: =+Assumptions!J57 -> 2314.3238 | I23: =+G23+H23 -> 2314.3238 | J23: =+I23/$D$8*1000 -> 55.808526 | K23: =+I23/$I$29 -> 0.05611436
B24: =+Assumptions!H58 -> Soft Costs | G24: 0 | H24: =+Assumptions!J58 -> 823.309 | I24: =+G24+H24 -> 823.309 | J24: =+I24/$D$8*1000 -> 19.853601 | K24: =+I24/$I$29 -> 0.019962401
B25: =+Assumptions!H59 -> Contingency | G25: 0 | H25: =+Assumptions!J59 -> 0 | I25: =+G25+H25 -> 0 | J25: =+I25/$D$8*1000 -> 0 | K25: =+I25/$I$29 -> 0
B26: =+Assumptions!H61 -> TIs | G26: 0 | H26: =+Assumptions!J61 -> 2716.711 | I26: =+G26+H26 -> 2716.711 | J26: =+I26/$D$8*1000 -> 65.511852 | K26: =+I26/$I$29 -> 0.065870862
B27: =+Assumptions!H62 -> LCs | G27: 0 | H27: =+Assumptions!J62 -> 976.22775 | I27: =+G27+H27 -> 976.22775 | J27: =+I27/$D$8*1000 -> 23.541145 | K27: =+I27/$I$29 -> 0.023670152
B28: =+Assumptions!H63 -> Loan Closing Costs & Fees | G28: =+Assumptions!C24 -> 570 | H28: =+'Monthly Cash Flow'!I110+'Monthly Cash Flow'!I108+'Monthly Cash Flow'!I107-'Monthly Cash Flow'!K107 -> 664.20794 | I28: =+G28+H28 -> 1234.2079 | J28: =+I28/$D$8*1000 -> 29.762182 | K28: =+I28/$I$29 -> 0.029925281
B29: Total Uses | G29: =SUM(G19:G28) -> 33249 | H29: =SUM(H19:H28) -> 7993.9856 | I29: =SUM(I19:I28) -> 41242.986 | J29: =SUM(J19:J28) -> 994.5498 | K29: =SUM(K19:K28) -> 1
A31: x | B31: Cash Flows
F32: Year 0 | G32: 1 | H32: 2 | I32: 3 | J32: 4 | K32: 5 | L32: 6 | M32: 7 | N32: 8 | O32: Total
B33: Revenues | F33: =+'Monthly Cash Flow'!HN62 -> 0 | G33: =+'Monthly Cash Flow'!HO62-G34 -> 2481.425 | H33: =+'Monthly Cash Flow'!HP62-H34 -> 2653.2109 | I33: =+'Monthly Cash Flow'!HQ62-I34 -> 2822.0617 | J33: =+'Monthly Cash Flow'!HR62-J34 -> 3141.6924 | K33: =+'Monthly Cash Flow'!HS62-K34 -> 2780.3238 | L33: =+'Monthly Cash Flow'!HT62-L34 -> 3082.3794 | M33: =+'Monthly Cash Flow'!HU62-M34 -> 3532.1282 | N33: =+'Monthly Cash Flow'!HV62-N34 -> 3797.647 | O33: =SUM(F33:N33) -> 24290.869
B34: Rental Abatement | F34: =+'Monthly Cash Flow'!HN56 -> 0 | G34: =+'Monthly Cash Flow'!HO56 -> -53.115 | H34: =+'Monthly Cash Flow'!HP56 -> -121.70247 | I34: =+'Monthly Cash Flow'!HQ56 -> -104.91229 | J34: =+'Monthly Cash Flow'!HR56 -> -114.87685 | K34: =+'Monthly Cash Flow'!HS56 -> -59.26107 | L34: =+'Monthly Cash Flow'!HT56 -> -27.20017 | M34: =+'Monthly Cash Flow'!HU56 -> -48.75893 | N34: =+'Monthly Cash Flow'!HV56 -> -6.775 | O34: =SUM(F34:N34) -> -536.60178
B35: Operating Expenses | F35: =+'Monthly Cash Flow'!HN74 -> 0 | G35: =-'Monthly Cash Flow'!HO74 -> -1588.5911 | H35: =-'Monthly Cash Flow'!HP74 -> -1562.0958 | I35: =-'Monthly Cash Flow'!HQ74 -> -1425.7339 | J35: =-'Monthly Cash Flow'!HR74 -> -1581.2866 | K35: =-'Monthly Cash Flow'!HS74 -> -1978.2159 | L35: =-'Monthly Cash Flow'!HT74 -> -1771.2262 | M35: =-'Monthly Cash Flow'!HU74 -> -1759.31 | N35: =-'Monthly Cash Flow'!HV74 -> -1828.583 | O35: =SUM(F35:N35) -> -13495.042
B36: Net Operating Income | F36: 0 | G36: =SUM(G33:G35) -> 839.71891 | H36: =SUM(H33:H35) -> 969.41268 | I36: =SUM(I33:I35) -> 1291.4156 | J36: =SUM(J33:J35) -> 1445.5289 | K36: =SUM(K33:K35) -> 742.84688 | L36: =SUM(L33:L35) -> 1283.953 | M36: =SUM(M33:M35) -> 1724.0593 | N36: =SUM(N33:N35) -> 1962.289 | O36: =SUM(F36:N36) -> 10259.224
B37: =Assumptions!B17 -> CapEx | F37: =-'Monthly Cash Flow'!HN26 -> 0 | G37: =-'Monthly Cash Flow'!HO26 -> -84.0285 | H37: =-'Monthly Cash Flow'!HP26 -> -1211.4883 | I37: =-'Monthly Cash Flow'!HQ26 -> -22.651 | J37: =-'Monthly Cash Flow'!HR26 -> -180.858 | K37: =-'Monthly Cash Flow'!HS26 -> -65.924 | L37: =-'Monthly Cash Flow'!HT26 -> -259.374 | M37: =-'Monthly Cash Flow'!HU26 -> -310.31746 | N37: =-'Monthly Cash Flow'!HV26 -> -179.68254 | O37: =SUM(F37:N37) -> -2314.3238
B38: TIs/LCs/Soft Costs/Other | F38: =-SUM('Monthly Cash Flow'!HN33:HN33,'Monthly Cash Flow'!HN36:HN36,'Monthly Cash Flow'!HN29:HN30,'Monthly Cash Flow'!HN39) -> 0 | G38: =-SUM('Monthly Cash Flow'!HO33:HO33,'Monthly Cash Flow'!HO36:HO36,'Monthly Cash Flow'!HO29:HO30,'Monthly Cash Flow'!HO39) -> -209.71683 | H38: =-SUM('Monthly Cash Flow'!HP33:HP33,'Monthly Cash Flow'!HP36:HP36,'Monthly Cash Flow'!HP29:HP30,'Monthly Cash Flow'!HP39) -> -758.88951 | I38: =-SUM('Monthly Cash Flow'!HQ33:HQ33,'Monthly Cash Flow'!HQ36:HQ36,'Monthly Cash Flow'!HQ29:HQ30,'Monthly Cash Flow'!HQ39) -> -429.41721 | J38: =-SUM('Monthly Cash Flow'!HR33:HR33,'Monthly Cash Flow'!HR36:HR36,'Monthly Cash Flow'!HR29:HR30,'Monthly Cash Flow'!HR39) -> -516.28246 | K38: =-SUM('Monthly Cash Flow'!HS33:HS33,'Monthly Cash Flow'!HS36:HS36,'Monthly Cash Flow'!HS29:HS30,'Monthly Cash Flow'!HS39) -> 0 | L38: =-SUM('Monthly Cash Flow'!HT33:HT33,'Monthly Cash Flow'!HT36:HT36,'Monthly Cash Flow'!HT29:HT30,'Monthly Cash Flow'!HT39) -> -248.5883 | M38: =-SUM('Monthly Cash Flow'!HU33:HU33,'Monthly Cash Flow'!HU36:HU36,'Monthly Cash Flow'!HU29:HU30,'Monthly Cash Flow'!HU39) -> -207.14543 | N38: =-SUM('Monthly Cash Flow'!HV33:HV33,'Monthly Cash Flow'!HV36:HV36,'Monthly Cash Flow'!HV29:HV30,'Monthly Cash Flow'!HV39) -> -2146.208 | O38: =SUM(F38:N38) -> -4516.2477
B39: Debt Service | F39: =+'Monthly Cash Flow'!HN182+'Monthly Cash Flow'!HN183 -> 0 | G39: =+'Monthly Cash Flow'!HO182+'Monthly Cash Flow'!HO183 -> -1191.4756 | H39: =+'Monthly Cash Flow'!HP182+'Monthly Cash Flow'!HP183 -> -1425.4419 | I39: =+'Monthly Cash Flow'!HQ182+'Monthly Cash Flow'!HQ183 -> -1730.8324 | J39: =+'Monthly Cash Flow'!HR182+'Monthly Cash Flow'!HR183 -> -1528.2517 | K39: =+'Monthly Cash Flow'!HS182+'Monthly Cash Flow'!HS183 -> -1273.8617 | L39: =+'Monthly Cash Flow'!HT182+'Monthly Cash Flow'!HT183 -> -1200.9664 | M39: =+'Monthly Cash Flow'!HU182+'Monthly Cash Flow'!HU183 -> -1473.2061 | N39: =+'Monthly Cash Flow'!HV182+'Monthly Cash Flow'!HV183 -> -1793.0433 | O39: =SUM(F39:N39) -> -11617.079
B40: Cash Flows after Debt Service | F40: =SUM(F36:F39) -> 0 | G40: =SUM(G36:G39) -> -645.50202 | H40: =SUM(H36:H39) -> -2426.4069 | I40: =SUM(I36:I39) -> -891.48502 | J40: =SUM(J36:J39) -> -779.86323 | K40: =SUM(K36:K39) -> -596.93878 | L40: =SUM(L36:L39) -> -424.97568 | M40: =SUM(M36:M39) -> -266.60966 | N40: =SUM(N36:N39) -> -2156.6448 | O40: =SUM(F40:N40) -> -8188.4261
B41: Acquisition and Disposition | F41: =+'Monthly Cash Flow'!HN174+'Monthly Cash Flow'!HN180 -> -32679 | G41: =+'Monthly Cash Flow'!HO174 -> 0 | H41: =+'Monthly Cash Flow'!HP174 -> 0 | I41: =+'Monthly Cash Flow'!HQ174 -> 0 | J41: =+'Monthly Cash Flow'!HR174 -> 0 | K41: =+'Monthly Cash Flow'!HS174 -> 0 | L41: =+'Monthly Cash Flow'!HT174 -> 0 | M41: =+'Monthly Cash Flow'!HU174 -> 0 | N41: =+'Monthly Cash Flow'!HV174 -> 0 | O41: =SUM(F41:N41) -> -32679
B42: New Debt, net | F42: =+'Monthly Cash Flow'!HN179+'Monthly Cash Flow'!HN181 -> 19541 | G42: =+'Monthly Cash Flow'!HO179+'Monthly Cash Flow'!HO181 -> 293.74533 | H42: =+'Monthly Cash Flow'!HP179+'Monthly Cash Flow'!HP181 -> 1961.0487 | I42: =+'Monthly Cash Flow'!HQ179+'Monthly Cash Flow'!HQ181 -> 1.4708235e-12 | J42: =+'Monthly Cash Flow'!HR179+'Monthly Cash Flow'!HR181 -> -4.938272e-13 | K42: =+'Monthly Cash Flow'!HS179+'Monthly Cash Flow'!HS181 -> 22133.64 | L42: =+'Monthly Cash Flow'!HT179+'Monthly Cash Flow'!HT181 -> 507.9623 | M42: =+'Monthly Cash Flow'!HU179+'Monthly Cash Flow'!HU181 -> 517.46289 | N42: =+'Monthly Cash Flow'!HV179+'Monthly Cash Flow'!HV181 -> 2325.8905 | O42: =SUM(F42:N42) -> 47280.75
B43: Financing Cost | F43: =+'Monthly Cash Flow'!HN184+'Monthly Cash Flow'!HN185 -> -570 | G43: =+'Monthly Cash Flow'!HO184+'Monthly Cash Flow'!HO185 -> 0 | H43: =+'Monthly Cash Flow'!HP184+'Monthly Cash Flow'!HP185 -> 0 | I43: =+'Monthly Cash Flow'!HQ184+'Monthly Cash Flow'!HQ185 -> 0 | J43: =+'Monthly Cash Flow'!HR184+'Monthly Cash Flow'!HR185 -> -108.97897 | K43: =+'Monthly Cash Flow'!HS184+'Monthly Cash Flow'!HS185 -> -920.11164 | L43: =+'Monthly Cash Flow'!HT184+'Monthly Cash Flow'!HT185 -> 0 | M43: =+'Monthly Cash Flow'!HU184+'Monthly Cash Flow'!HU185 -> 0 | N43: =+'Monthly Cash Flow'!HV184+'Monthly Cash Flow'!HV185 -> 0 | O43: =SUM(F43:N43) -> -1599.0906
B44: Loan Repayment | F44: =+'Monthly Cash Flow'!HN186 -> 0 | G44: =+'Monthly Cash Flow'!HO186 -> 0 | H44: =+'Monthly Cash Flow'!HP186 -> 0 | I44: =+'Monthly Cash Flow'!HQ186 -> 0 | J44: =+'Monthly Cash Flow'!HR186 -> 0 | K44: =+'Monthly Cash Flow'!HS186 -> -21795.794 | L44: =+'Monthly Cash Flow'!HT186 -> 0 | M44: =+'Monthly Cash Flow'!HU186 -> 0 | N44: =+'Monthly Cash Flow'!HV186 -> 0 | O44: =SUM(F44:N44) -> -21795.794
B45: Leveraged Cash Flows | F45: =SUM(F40:F44) -> -13708 | G45: =SUM(G40:G44) -> -351.75669 | H45: =SUM(H40:H44) -> -465.35827 | I45: =SUM(I40:I44) -> -891.48502 | J45: =SUM(J40:J44) -> -888.8422 | K45: =SUM(K40:K44) -> -1179.2045 | L45: =SUM(L40:L44) -> 82.98662 | M45: =SUM(M40:M44) -> 250.85323 | N45: =SUM(N40:N44) -> 169.24573 | O45: =SUM(F45:N45) -> -16981.561
B46: NOI Growth Rate | G46: n/a | H46: n/a | I46: n/a | J46: n/a | K46: n/a | L46: n/a | M46: n/a | N46: n/a
B47: Return on Cost | G47: =IF(G36<0,"n/a ",G36/SUM($I$19:$I$28)) -> 0.020360284 | H47: =IF(H36<0,"n/a ",H36/SUM($I$19:$I$28)) -> 0.02350491 | I47: =IF(I36<0,"n/a ",I36/SUM($I$19:$I$28)) -> 0.031312369 | J47: =IF(J36<0,"n/a ",J36/SUM($I$19:$I$28)) -> 0.035049085 | K47: =IF(K36<0,"n/a ",K36/SUM($I$19:$I$28)) -> 0.018011472 | L47: =IF(L36<0,"n/a ",L36/SUM($I$19:$I$28)) -> 0.031131428 | M47: =IF(M36<0,"n/a ",M36/SUM($I$19:$I$28)) -> 0.041802485 | N47: =IF(N36<0,"n/a ",N36/SUM($I$19:$I$28)) -> 0.047578733
B48: Leveraged Cash-on-Cash | G48: =IF(G40<0,"n/a ",IF(G32<=Assumptions!$L$17/12, (G40+G42+G43)/SUM($I$15:$I$15), "n/a")) -> n/a | H48: =IF(H40<0,"n/a ",IF(H32<=Assumptions!$L$17/12, (H40+H42+H43)/SUM($I$15:$I$15), "n/a")) -> n/a | I48: =IF(I40<0,"n/a ",IF(I32<=Assumptions!$L$17/12, (I40+I42+I43)/SUM($I$15:$I$15), "n/a")) -> n/a | J48: =IF(J40<0,"n/a ",IF(J32<=Assumptions!$L$17/12, (J40+J42+J43)/SUM($I$15:$I$15), "n/a")) -> n/a | K48: =IF(K40<0,"n/a ",IF(K32<=Assumptions!$L$17/12, (K40+K42+K43)/SUM($I$15:$I$15), "n/a")) -> n/a | L48: =IF(L40<0,"n/a ",IF(L32<=Assumptions!$L$17/12, (L40+L42+L43)/SUM($I$15:$I$15), "n/a")) -> n/a | M48: =IF(M40<0,"n/a ",IF(M32<=Assumptions!$L$17/12, (M40+M42+M43)/SUM($I$15:$I$15), "n/a")) -> n/a | N48: =IF(N40<0,"n/a ",IF(N32<=Assumptions!$L$17/12, (N40+N42+N43)/SUM($I$15:$I$15), "n/a")) -> n/a
A50: x | B50: Returns Summary
H51: IRR | I51: Multiple | J51: Contribution | K51: Profit
B52: Unleveraged Returns | H52: =+Assumptions!O22 -> 0.057904282 | I52: =+Assumptions!P22 -> 1.55 | J52: =+Assumptions!Q22 -> 37647.066 | K52: =+Assumptions!R22 -> 20705.888
B53: Profit from Cash Flow | H53: n/a | I53: n/a | J53: n/a | K53: =K52-K54 -> 7806.6996
B54: Profit from Appreciation | H54: n/a | I54: n/a | J54: n/a | K54: =+Assumptions!L29-Assumptions!E26 -> 12899.189
B55: Leveraged Returns | H55: =+Assumptions!O23 -> 0.071606448 | I55: =+Assumptions!P23 -> 1.7510529 | J55: =+Assumptions!Q23 -> 15882.232 | K55: =+Assumptions!R23 -> 11928.396
B56: LP Equity | H56: =+Assumptions!O24 -> 0.071606448 | I56: =+Assumptions!P24 -> 1.7510529 | J56: =+Assumptions!Q24 -> 15564.587 | K56: =+Assumptions!R24 -> 11689.828
B57: GP Equity | H57: =+Assumptions!O25 -> 0.071606448 | I57: =+Assumptions!P25 -> 1.7510529 | J57: =+Assumptions!Q25 -> 317.64464 | K57: =+Assumptions!R25 -> 238.56792
B58: ="(1) Assumes exit cap of " & TEXT(Assumptions!$L$22, "0.00%") & " which results in sale price of " & TEXT(Assumptions!K29, "$#,###") & " psf" -> (1) Assumes exit cap of 5.00% which results in sale price of $1,300 psf
B60: Notes
B61: - | C61: Yr. 5 includes large bad debt expense

Sheet Assumptions
E1: 1 | F1: Circ Trigger
B2: Chapman Plaza | R2: =NOW() -> 46153.526
B3: ($ in thousands, except psf amounts)
B5: Land Summary | H5: Project Timing | J5: Start | K5: Duration | L5: End | N5: Joint Venture Terms | T5: Sensitivity Chart - Sales Date vs Cap Rate
B6: Land SF | E6: 1.57 | F6: =43560*E6 -> 68389.2 | H6: Purchase Date | I6: 42552 | N6: Investor Contribution | R6: 0.98
B7: Building FAR SF | F7: 41469 | H7: Acquisition | L7: =J7+K7 -> 0 | P7: Hurdle | Q7: Distribution % | T7: =O23 -> 0.071606448 | U7: 90 | V7: 96 | W7: 99 | X7: 102
B8: Implied FAR | F8: =F7/F6 -> 0.60636767 | H8: =+B17 -> CapEx | N8: Waterfall Structure (TBD) | P8: Rate | Q8: Investors | R8: Arc | T8: 0.0425 | U8: 0.089910141 | V8: 0.11410877 | W8: 0.11095428 | X8: 0.10869942
H9: Suite 300 | I9: =HLOOKUP(J9,'Monthly Cash Flow'!$K$13:$GT$15,3) -> 44592 | J9: 67 | K9: 1 | L9: =J9+K9 -> 68 | N9: Capital Contribution | Q9: 1 | R9: =1-Q9 -> 0 | T9: =T8+0.25% -> 0.045 | U9: 0.074231014 | V9: 0.10050105 | W9: 0.097788948 | X9: 0.096009633
B10: Acquisition Costs | H10: Suite 170 | I10: =HLOOKUP(J10,'Monthly Cash Flow'!$K$13:$GT$15,3) -> 44592 | J10: 67 | K10: 3 | L10: =J10+K10 -> 70 | N10: Tier 1 | P10: 0.09 | Q10: 1 | R10: =1-Q10 -> 0 | T10: =T9+0.25% -> 0.0475 | U10: 0.058861801 | V10: 0.08727015 | W10: 0.084982792 | X10: 0.083666947
C11: At Close | D11: PSF* | E11: At Stabilization | F11: PSF* | H11: Courtyard | I11: =HLOOKUP(J11,'Monthly Cash Flow'!$K$13:$GT$15,3) -> 44712 | J11: 71 | K11: 3 | L11: =J11+K11 -> 74 | N11: Tier 2 | P11: 0.09 | Q11: =1-R11 -> 1 | R11: 0 | T11: =T10+0.25% -> 0.05 | U11: 0.043713734 | V11: 0.074345776 | W11: 0.072468033 | X11: 0.071606448
B12: Purchase Price | C12: 30000 | D12: =C12/$F$7*1000 -> 723.43196 | E12: =C12 -> 30000 | F12: =E12/$F$7*1000 -> 723.43196 | H12: =+B18 -> Soft Costs | N12: Capital Events | T12: =T11+0.25% -> 0.0525 | U12: 0.028703257 | V12: 0.061664852 | W12: 0.060183766 | X12: 0.059769842
B13: =C13/C12 -> 0.0068666667 | C13: 206 | D13: =C13/$F$7*1000 -> 4.9675661 | E13: =C13 -> 206 | F13: =E13/$F$7*1000 -> 4.9675661 | H13: Suite 200 | I13: =HLOOKUP(J13,'Monthly Cash Flow'!$K$13:$GT$15,3) -> 44620 | J13: 68 | K13: 3 | L13: =J13+K13 -> 71 | N13: Tier 3 | P13: 0.09 | Q13: 1 | R13: =1-Q13 -> 0 | T13: =T12+0.25% -> 0.055 | U13: 0.013749281 | V13: 0.049169555 | W13: 0.048074076 | X13: 0.048103681
B14: Working Capital & Reserves | C14: 160 | D14: =C14/$F$7*1000 -> 3.8583038 | E14: =C14 -> 160 | F14: =E14/$F$7*1000 -> 3.8583038 | H14: Courtyard | I14: =HLOOKUP(J14,'Monthly Cash Flow'!$K$13:$GT$15,3) -> 44620 | J14: 68 | K14: 3 | L14: =J14+K14 -> 71 | N14: Return of Capital | Q14: 1 | R14: =1-Q14 -> 0 | T14: =T13+0.25% -> 0.0575 | U14: -0.0012294725 | V14: 0.036805722 | W14: 0.036086467 | X14: 0.036557886
B15: Total Acquisition Costs | C15: =SUM(C12:C14) -> 30366 | D15: =C15/F7*1000 -> 732.25783 | E15: =SUM(E12:E14) -> 30366 | F15: =E15/F7*1000 -> 732.25783 | N15: Tier 4 | P15: 0.12 | Q15: 0.9 | R15: =1-Q15 -> 0.1
B16: Operating Losses | C16: 0 | D16: =C16/F7*1000 -> 0 | E16: ='Monthly Cash Flow'!I111 -> 499.20616 | F16: =E16/$F$7*1000 -> 12.038056 | N16: Tier 5 | P16: 0.15 | Q16: 0.7 | R16: =1-Q16 -> 0.3
B17: CapEx | C17: 0 | D17: =C17/F7*1000 -> 0 | E17: =+'Monthly Cash Flow'!H26 -> 2314.3238 | F17: =E17/$F$7*1000 -> 55.808526 | H17: Project Sale | I17: =EOMONTH(I6,L17-1) -> 45657 | L17: =99+3 -> 102 | N17: Remainder | Q17: 0.6 | R17: =1-Q17 -> 0.4
B18: Soft Costs | C18: 0 | D18: =C18/F7*1000 -> 0 | E18: ='Monthly Cash Flow'!H29 -> 823.309 | F18: =E18/$F$7*1000 -> 19.853601 | T18: =$P$23 -> 1.7510529 | U18: =U7 -> 90 | V18: =V7 -> 96 | W18: =W7 -> 99 | X18: =X7 -> 102
B19: Contingency | C19: =0.1*(C17+C18) -> 0 | D19: =C19/F7*1000 -> 0 | E19: ='Monthly Cash Flow'!H30 -> 0 | F19: =E19/$F$7*1000 -> 0 | H19: Exit Assumptions | K19: $ per GLA | L19: % of Total | N19: Project Return Summary | T19: 0.0425 | U19: 1.8441502 | V19: 2.2783901 | W19: 2.2891963 | X19: 2.3119466
B20: Capital Reserves | C20: 0 | D20: =C20/F7*1000 -> 0 | E20: =+J41 -> 0 | F20: =+E20*1000/$F$7 -> 0 | H20: Year of Sale | L20: =L17 -> 102 | O20: Base Case | T20: =T19+0.25% -> 0.045 | U20: 1.662539 | V20: 2.0732009 | W20: 2.0827331 | X20: 2.1042082
B21: TIs | C21: 0 | D21: =C21/F7*1000 -> 0 | E21: =+J42 -> 2716.711 | F21: =+E21*1000/$F$7 -> 65.511852 | H21: Forward NOI (add back free rent) | L21: =SUM(OFFSET('Monthly Cash Flow'!K$76,0,Assumptions!$L$20+1,1,12))-SUM(OFFSET('Monthly Cash Flow'!K$56,0,Assumptions!$L$20+1,1,12)) -> 2690.476 | O21: IRR | P21: Multiple | Q21: Contribution | R21: Profit | T21: =T20+0.25% -> 0.0475 | U21: 1.5000447 | V21: 1.8896105 | W21: 1.8980029 | X21: 1.918337
B22: LCs | C22: 0 | D22: =C22/F7*1000 -> 0 | E22: =+J43 -> 976.22775 | F22: =+E22*1000/$F$7 -> 23.541145 | H22: Exit Cap Rate | L22: 0.05 | N22: Unleveraged Returns | O22: =+'Monthly Cash Flow'!I96 -> 0.057904282 | P22: =+'Monthly Cash Flow'!I95 -> 1.55 | Q22: =+'Monthly Cash Flow'!I94 -> 37647.066 | R22: ='Monthly Cash Flow'!I93 -> 20705.888 | T22: =T21+0.25% -> 0.05 | U22: 1.3537998 | V22: 1.7243791 | W22: 1.7317457 | X22: 1.7510529
B23: Total Unleveraged Basis | C23: =SUM(C15:C22) -> 30366 | D23: =C23/F7*1000 -> 732.25783 | E23: =SUM(E15:E22) -> 37695.778 | F23: =E23/F7*1000 -> 909.01101 | H23: Gross Exit Value | K23: =L23/F7*1000 -> 1369.9274 | L23: =(MAX(L21/L22))+3000 -> 56809.52 | N23: Leveraged Returns | O23: ='Monthly Cash Flow'!$I$200 -> 0.071606448 | P23: ='Monthly Cash Flow'!$I$199 -> 1.7510529 | Q23: ='Monthly Cash Flow'!$I$198 -> 15882.232 | R23: ='Monthly Cash Flow'!I197 -> 11928.396 | T23: =T22+0.25% -> 0.0525 | U23: 1.221483 | V23: 1.5748841 | W23: 1.5813225 | X23: 1.5997006
B24: Loan Closing Costs & Fees | C24: 570 | D24: =C24/F7*1000 -> 13.745207 | E24: =SUM('Monthly Cash Flow'!I107:I110) -> 1599.0906 | F24: =E24/F7*1000 -> 38.561109 | H24: Rental Abatement Credit | L24: =+SUM(OFFSET('Monthly Cash Flow'!K$56,0,Assumptions!$L$20+1,1,12)) -> 0 | N24: LP Equity | O24: =+Waterfall!G133 -> 0.071606448 | P24: =+Waterfall!G135 -> 1.7510529 | Q24: =-Waterfall!G123 -> 15564.587 | R24: =+Waterfall!G134 -> 11689.828 | T24: =T23+0.25% -> 0.055 | U24: 1.1011951 | V24: 1.4389795 | W24: 1.4445742 | X24: 1.4621076
B25: Capitalized Interest | C25: 0 | D25: =C25/F7*1000 -> 0 | E25: ='Monthly Cash Flow'!I150 -> 1715.5169 | F25: =E25/F7*1000 -> 41.368659 | H25: TI/LC Credit | L25: =-SUM(OFFSET('Monthly Cash Flow'!K$33,0,Assumptions!$L$20+1,1,12))-SUM(OFFSET('Monthly Cash Flow'!K$36,0,Assumptions!$L$20+1,1,12)) -> -59.47 | N25: GP Equity | O25: =+Waterfall!G164 -> 0.071606448 | P25: =+Waterfall!G163 -> 1.7510529 | Q25: =-Waterfall!G138 -> 317.64464 | R25: =+Waterfall!G161 -> 238.56792 | T25: =T24+0.25% -> 0.0575 | U25: 0.99136691 | V25: 1.3148927 | W25: 1.319717 | X25: 1.3364792
B26: Total Leveraged Basis | C26: =SUM(C23:C25) -> 30936 | D26: =C26/F7*1000 -> 746.00304 | E26: =SUM(E23:E25) -> 41010.385 | F26: =E26/F7*1000 -> 988.94078 | H26: ULA Tax | L26: =L23*-5% -> -2840.476
H27: Gross Exit Value (Post Abatement/TI/LC Credit, ULA) | K27: =L27/F7*1000 -> 1299.997 | L27: =+L23+SUM(L24:L26) -> 53909.574 | N27: Free Cash Flow Hold Back
B28: Financing Assumptions (Acquisition Loan) | O28: Start | P28: End
B29: Total Debt | F29: =+F50 -> 21795.794 | H29: Total Gross Exit Proceeds | K29: =L29/F7*1000 -> 1299.997 | L29: =L27 -> 53909.574 | N29: Holdback | O29: 1 | P29: 25 | T29: Sensitivity Chart - Sales Date vs Cap Rate
B30: Total Equity | F30: =+F51-F29 -> 16705.367 | H30: Sales Costs | K30: 0.0125 | L30: =-L29*K30 -> -673.86968 | U30: =EOMONTH($I$6,U7-1) -> 45291 | V30: =EOMONTH($I$6,V7-1) -> 45473 | W30: =EOMONTH($I$6,W7-1) -> 45565 | X30: =EOMONTH($I$6,X7-1) -> 45657
B31: Interest Rate | C31: Floating Rate | D31: 525 | E31: =LIBOR!M34 -> 0.0012929 | F31: =+D32 -> 0.09 | H31: Net Exit Proceeds | K31: =L31/F7*1000 -> 1283.747 | L31: =SUM(L29:L30) -> 53235.704 | T31: =T8 -> 0.0425 | U31: =TEXT(U8,"0.0%")&" / "&TEXT(U19,"0.0x") -> 9.0% / 1.8x | V31: =TEXT(V8,"0.0%")&" / "&TEXT(V19,"0.0x") -> 11.4% / 2.3x | W31: =TEXT(W8,"0.0%")&" / "&TEXT(W19,"0.0x") -> 11.1% / 2.3x | X31: =TEXT(X8,"0.0%")&" / "&TEXT(X19,"0.0x") -> 10.9% / 2.3x | AE31: TEXT(V8,"0.0%")&" / "&TEXT(V19,"0.0x")
B32: Loan Closing Month | C32: Fixed Rate | D32: 0.09 | F32: 0 | T32: =T9 -> 0.045 | U32: =TEXT(U9,"0.0%")&" / "&TEXT(U20,"0.0x") -> 7.4% / 1.7x | V32: =TEXT(V9,"0.0%")&" / "&TEXT(V20,"0.0x") -> 10.1% / 2.1x | W32: =TEXT(W9,"0.0%")&" / "&TEXT(W20,"0.0x") -> 9.8% / 2.1x | X32: =TEXT(X9,"0.0%")&" / "&TEXT(X20,"0.0x") -> 9.6% / 2.1x
B33: Libor Floor | C33: Floor | D33: 0.005 | H33: Unleveraged Sources and Uses | T33: =T10 -> 0.0475 | U33: =TEXT(U10,"0.0%")&" / "&TEXT(U21,"0.0x") -> 5.9% / 1.5x | V33: =TEXT(V10,"0.0%")&" / "&TEXT(V21,"0.0x") -> 8.7% / 1.9x | W33: =TEXT(W10,"0.0%")&" / "&TEXT(W21,"0.0x") -> 8.5% / 1.9x | X33: =TEXT(X10,"0.0%")&" / "&TEXT(X21,"0.0x") -> 8.4% / 1.9x
B34: Servicing Fee | F34: 0 | H34: Project Uses | J34: Amount | K34: % | L34: $ Per NRSF | T34: =T11 -> 0.05 | U34: =TEXT(U11,"0.0%")&" / "&TEXT(U22,"0.0x") -> 4.4% / 1.4x | V34: =TEXT(V11,"0.0%")&" / "&TEXT(V22,"0.0x") -> 7.4% / 1.7x | W34: =TEXT(W11,"0.0%")&" / "&TEXT(W22,"0.0x") -> 7.2% / 1.7x | X34: =TEXT(X11,"0.0%")&" / "&TEXT(X22,"0.0x") -> 7.2% / 1.8x
B35: Loan Fees (Bank And Broker) | E35: 0.01 | F35: =C24 -> 570 | H35: Purchase Price | J35: ='Monthly Cash Flow'!$I$18 -> 30000 | K35: =J35/$J$44 -> 0.79923747 | L35: =J35/F7*1000 -> 723.43196 | T35: =T12 -> 0.0525 | U35: =TEXT(U12,"0.0%")&" / "&TEXT(U23,"0.0x") -> 2.9% / 1.2x | V35: =TEXT(V12,"0.0%")&" / "&TEXT(V23,"0.0x") -> 6.2% / 1.6x | W35: =TEXT(W12,"0.0%")&" / "&TEXT(W23,"0.0x") -> 6.0% / 1.6x | X35: =TEXT(X12,"0.0%")&" / "&TEXT(X23,"0.0x") -> 6.0% / 1.6x
B36: Exit Fee | E36: 0.005 | F36: =+IF(E1=0,0,E36*F29) -> 108.97897 | H36: Closing Costs | J36: ='Monthly Cash Flow'!$I$19 -> 206 | K36: =J36/$J$44 -> 0.0054880973 | L36: =J36/F7*1000 -> 4.9675661 | T36: =T13 -> 0.055 | U36: =TEXT(U13,"0.0%")&" / "&TEXT(U24,"0.0x") -> 1.4% / 1.1x | V36: =TEXT(V13,"0.0%")&" / "&TEXT(V24,"0.0x") -> 4.9% / 1.4x | W36: =TEXT(W13,"0.0%")&" / "&TEXT(W24,"0.0x") -> 4.8% / 1.4x | X36: =TEXT(X13,"0.0%")&" / "&TEXT(X24,"0.0x") -> 4.8% / 1.5x
B37: Loan Closing Costs | E37: =+F37/F29 -> 0 | F37: 0 | H37: Operating Losses | J37: =+'Monthly Cash Flow'!I88 -> 499.20616 | K37: =J37/$J$44 -> 0.013299476 | L37: =J37/F7*1000 -> 12.038056 | T37: =T14 -> 0.0575 | U37: =TEXT(U14,"0.0%")&" / "&TEXT(U25,"0.0x") -> -0.1% / 1.0x | V37: =TEXT(V14,"0.0%")&" / "&TEXT(V25,"0.0x") -> 3.7% / 1.3x | W37: =TEXT(W14,"0.0%")&" / "&TEXT(W25,"0.0x") -> 3.6% / 1.3x | X37: =TEXT(X14,"0.0%")&" / "&TEXT(X25,"0.0x") -> 3.7% / 1.3x
B38: Loan Extension Fee | C38: 48 | D38: 999 | E38: 0.005 | F38: =+IF(E1=0,0,E38*F29) -> 108.97897 | H38: =+B17 -> CapEx | J38: ='Monthly Cash Flow'!$I26 -> 2314.3238 | K38: =J38/$J$44 -> 0.061656476 | L38: =J38/F7*1000 -> 55.808526
B39: I/O Period (Months) | C39: =EOMONTH(I6,C38) -> 44043 | F39: 60 | H39: =+B18 -> Soft Costs | J39: ='Monthly Cash Flow'!$I29 -> 823.309 | K39: =J39/$J$44 -> 0.02193398 | L39: =J39/F7*1000 -> 19.853601
B40: Amortization Period (Years) | E40: 30 | F40: =(E40*12) -> 360 | H40: =+B19 -> Contingency | J40: ='Monthly Cash Flow'!$I30 -> 0 | K40: =J40/$J$44 -> 0 | L40: =J40/F7*1000 -> 0
B41: TI/LC Force Funding | E41: =EOMONTH($I$6,F41-1) -> 43465 | F41: 30 | H41: =+B20 -> Capital Reserves | J41: =+'Monthly Cash Flow'!I39 -> 0 | K41: =J41/$J$44 -> 0 | L41: =J41/F7*1000 -> 0
B42: CapEx Force Funding | E42: =EOMONTH($I$6,F42-1) -> 43281 | F42: 24 | H42: =+B21 -> TIs | J42: =+'Monthly Cash Flow'!I34 -> 2716.711 | K42: =J42/$J$44 -> 0.072376574 | L42: =J42/F7*1000 -> 65.511852 | T42: Sensitivity Chart - Sales Date / Sales Price
B43: Interest Rate Type | F43: 1 | H43: =+B22 -> LCs | J43: =+'Monthly Cash Flow'!I37 -> 976.22775 | K43: =J43/$J$44 -> 0.026007926 | L43: =J43/F7*1000 -> 23.541145 | T43: =L23 -> 56809.52 | U43: =U18 -> 90 | V43: =V18 -> 96 | W43: =W18 -> 99 | X43: =X18 -> 102
B44: Acquisition Costs | F44: =IF($E$48=0,C15,'Monthly Cash Flow'!K118) -> 30776 | H44: Total Uses | J44: =SUM(J35:J43) -> 37535.778 | K44: =SUM(K35:K43) -> 1 | L44: =SUM(L35:L43) -> 905.15271 | T44: =T19 -> 0.0425 | U44: 58343.435 | V44: 65528.494 | W44: 65916.706 | X44: 66305.318
B45: Initial LTC | F45: =+F46/F44 -> 0.63494281 | T45: =T20 -> 0.045 | U45: 55268.8 | V45: 62054.689 | W45: 62421.333 | X45: 62788.356
B46: Total Initial Loan Proceeds | F46: 19541 | H46: Project Sources | J46: Amount | K46: % | L46: $ Per GLA | T46: =T21 -> 0.0475 | U46: 52517.811 | V46: 58946.547 | W46: 59293.895 | X46: 59641.6
H47: Unleveraged Equity | J47: ='Monthly Cash Flow'!I90 -> 4020.7345 | K47: =J47/$J$49 -> 0.10711739 | L47: =J47/F7*1000 -> 96.957596 | T47: =T22 -> 0.05 | U47: 50041.92 | V47: 56149.22 | W47: 56479.2 | X47: 56809.52
B48: Future Variable Contribution | E48: 1 | F48: 2254.794 | H48: Project Cash Flow | J48: =-'Monthly Cash Flow'!I89 -> 33515.043 | K48: =J48/$J$49 -> 0.89288261 | L48: =J48/F7*1000 -> 808.19511 | T48: =T23 -> 0.0525 | U48: 47801.829 | V48: 53618.305 | W48: 53932.571 | X48: 54247.162
B49: Max Future Proceeds | E49: 1 | F49: =E49*F48 -> 2254.794 | H49: Total Sources | J49: =SUM(J47:J48) -> 37535.778 | K49: =SUM(K47:K48) -> 1 | L49: =SUM(L47:L48) -> 905.15271 | T49: =T24 -> 0.055 | U49: 45765.382 | V49: 51317.473 | W49: 51617.455 | X49: 51917.745
B50: Total Proceeds | F50: =F46+F49 -> 21795.794 | T50: =T25 -> 0.0575 | U50: 43906.017 | V50: 49216.713 | W50: 49503.652 | X50: 49790.887
B51: Total Costs | F51: 38501.161 | H51: Leveraged Sources and Uses
B52: Blended LTC | F52: =F50/F51 -> 0.56610745 | H52: Project Uses (Debt) | J52: Amount | K52: % | L52: $ Per GLA
B53: Debt Funding | H53: =+H35 -> Purchase Price | J53: ='Monthly Cash Flow'!$I$18 -> 30000 | K53: =J53/$J$64 -> 0.72101747 | L53: =J53/F7*1000 -> 723.43196 | T53: 9% Unlevered Return
B54: Year 1 Debt Service | F54: =-SUM('Monthly Cash Flow'!L182:W182) -> 1191.4756 | H54: =+H36 -> Closing Costs | J54: =J36 -> 206 | K54: =J54/$J$64 -> 0.0049509866 | L54: =J54/F7*1000 -> 4.9675661 | T54: Sales Value | U54: Exit Timing | V54: NOI | W54: Multiple | X54: Cap
B55: Year 4 Debt Service | F55: =-SUM('Monthly Cash Flow'!AV182:BG182) -> 1528.2517 | H55: Reserves Funded at Close | J55: =-'Monthly Cash Flow'!$K$180 -> 2473 | K55: =J55/$J$64 -> 0.059435874 | L55: =J55/$F$7*1000 -> 59.634908 | T55: $61.8M | U55: 44896 | V55: $2.21M | W55: 1.7x | X55: 0.036
B56: NOI | C56: Yr 1 | D56: =+Charts!G36-Charts!G34 -> 892.83391 | E56: Extension Term | F56: =(4*SUM('Monthly Cash Flow'!BH62:BJ62)-SUM('Monthly Cash Flow'!BH56:BJ56))-SUM('Monthly Cash Flow'!BH74:BS74) -> 1058.4086 | H56: =+H37 -> Operating Losses | J56: =+J37 -> 499.20616 | K56: =J56/$J$64 -> 0.011997879 | L56: =J56/F7*1000 -> 12.038056 | T56: $59.5M | U56: 44713 | V56: 2.18M | W56: 1.63x | X56: 0.0367
B57: DSCR Cash Management Test (Yr 1 NOI) (1.15x Requirement) | F57: =+D56/F54 -> 0.7493514 | H57: =+H38 -> CapEx | J57: =+J38 -> 2314.3238 | K57: =J57/$J$64 -> 0.055622262 | L57: =J57/F7*1000 -> 55.808526
B58: DSCR Test (Extension) (1.35x Requirement) | F58: =+F56/F55 -> 0.69256174 | H58: =+H39 -> Soft Costs | J58: =+J39 -> 823.309 | K58: =J58/$J$64 -> 0.019787339 | L58: =J58/F7*1000 -> 19.853601
B59: Debt Yield Test | C59: Yr 1 | D59: =+D56/$F$46 -> 0.045690288 | E59: Extension (Req. 8.0%) | F59: =+F56/$F$29 -> 0.048560224 | H59: =+H40 -> Contingency | J59: =+J40 -> 0 | K59: =J59/$J$64 -> 0 | L59: =J59/F7*1000 -> 0
H60: =+H41 -> Capital Reserves | J60: 0 | K60: =J60/$J$64 -> 0 | L60: =J60/F7*1000 -> 0
B61: Financing Assumptions (Refi Loan) | F61: 1 | H61: =+H42 -> TIs | J61: =+J42 -> 2716.711 | K61: =J61/$J$64 -> 0.065293203 | L61: =J61/F7*1000 -> 65.511852
B62: Total Debt | F62: =F76 -> 22133.64 | H62: =+H43 -> LCs | J62: =+J43 -> 976.22775 | K62: =J62/$J$64 -> 0.023462575 | L62: =J62/F7*1000 -> 23.541145 | N62: =J70-J64 -> -126.50204
B63: Total Equity | F63: 0 | H63: Loan Closing Costs & Fees | J63: =SUM('Monthly Cash Flow'!I107:I110) -> 1599.0906 | K63: =J63/$J$64 -> 0.038432409 | L63: =J63/F7*1000 -> 38.561109
B64: Variable Contribution | F64: ='Monthly Cash Flow'!#REF! -> #REF! | H64: Total Uses | J64: =SUM(J53:J63) -> 41607.868 | K64: =SUM(K53:K63) -> 1 | L64: =SUM(L53:L63) -> 1003.3487
B65: Interest Rate | C65: Floating Rate | D65: 490 | E65: =+E31 -> 0.0012929 | F65: =(D65/10000)+E65 -> 0.0502929 | N65: =J64-J70 -> 126.50204
B66: Loan Closing Month | C66: Fixed Rate | D66: 0.052 | F66: 60 | H66: Project Sources (Debt) | J66: Amount | K66: % | L66: $ Per GLA
B67: Libor Floor | C67: Floor | D67: 0.052 | H67: Debt Financing | J67: =-'Monthly Cash Flow'!I170 -> 25484.956 | K67: =J67/$J$70 -> 0.61437117 | L67: =J67/F7*1000 -> 614.55438
B68: Loan Fees (Bank And Broker) | E68: 0.01 | F68: =(255000+191250)/1000 -> 446.25 | H68: Equity Investment | J68: 15882 | K68: =J68/$J$70 -> 0.38287071 | L68: =J68/F7*1000 -> 382.98488
B69: Exit Fee | E69: 0.005 | F69: =+IF(F61=0,0,E69*F62) -> 110.6682 | H69: Project Cash Flow | J69: ='Monthly Cash Flow'!$I$116 -> 114.41053 | K69: =J69/$J$70 -> 0.0027581187 | L69: =J69/F7*1000 -> 2.7589411
B70: Loan Closing Costs | E70: =IFERROR(F70/F62,"n/a") -> 0.016485434 | F70: =(336086.72+28795.95)/1000 -> 364.88267 | H70: Total Sources | J70: =SUM(J67:J69) -> 41481.366 | K70: =SUM(K67:K69) -> 1 | L70: =SUM(L67:L69) -> 1000.2982
B71: I/O Period (Months) | F71: 60
B72: Amortization Period (Years) | E72: 30 | F72: =(E72*12) -> 360 | H72: CapEx Forecast
B73: Interest Rate Type | F73: 1 | H73: Project Uses | L73: Budget (2023)
B74: Stabilized Forward NOI | C74: Month of Stabalization | D74: =+F66 -> 60 | E74: =HLOOKUP(D74,'Monthly Cash Flow'!$K$13:$GT$15,3) -> 44377 | F74: =SUM(OFFSET('Monthly Cash Flow'!$K$82,0,D74,1,12)) -> 1399.2273 | H74: Hard Costs | L74: (000)
B75: Initla LTC | E75: =+F76/E26 -> 0.53970817 | F75: 0.65 | H75: Common Area | L75: 240
B76: Total Initial Loan Proceeds | F76: =22133639.97/1000 -> 22133.64 | H76: Suite 300 Elevator | L76: 250
B78: Future Variable Contribution | E78: 1 | F78: =25500-F76 -> 3366.36 | H78: Total Hard Costs | L78: =SUM(L75:L77) -> 490
B79: Max Future Proceeds | E79: 1 | F79: =F78*E79 -> 3366.36
B80: Total Proceeds | F80: =F79+F76 -> 25500 | H80: Soft Costs
B81: Total Costs | F81: =41746717/1000 -> 41746.717 | H81: Courtyard Refresh | L81: 15
F82: =F81-F79 -> 38380.357 | H82: Suite 300 Elevator | L82: 10
F83: =F82-J67 -> 12895.401
H84: Total Soft Costs | L84: =SUM(L81:L83) -> 25
H85: Total Costs | L85: =L84+L78 -> 515
H91: Suite 200 Budget (Unused)
H92: Hard Cost
H93: Suite 200 LL Work | L93: =446400/1000 -> 446.4
H94: Suite 200 Elevator | L94: =376800/1000 -> 376.8
H95: Soft Cost
H96: Suite 200 LL Work | L96: =43800/1000 -> 43.8
H97: Suite 200 Elevator | L97: =60950/1000 -> 60.95

Sheet Monthly Cash Flow
K2: 1 | L2: =K2*(1+$F2)^(1/12) -> 1 | M2: =L2*(1+$F2)^(1/12) -> 1 | N2: =M2*(1+$F2)^(1/12) -> 1 | O2: =N2*(1+$F2)^(1/12) -> 1 | P2: =O2*(1+$F2)^(1/12) -> 1 | Q2: =P2*(1+$F2)^(1/12) -> 1 | R2: =Q2*(1+$F2)^(1/12) -> 1 | S2: =R2*(1+$F2)^(1/12) -> 1 | ... BY2: =BX2*(1+$F2)^(1/12) -> 1 | CB2: =CA2*(1+$F2)^(1/12) -> 0 | CC2: =CB2*(1+$F2)^(1/12) -> 0 | CD2: =CC2*(1+$F2)^(1/12) -> 0 | CE2: =CD2*(1+$F2)^(1/12) -> 0 | CF2: =CE2*(1+$F2)^(1/12) -> 0 | CG2: =CF2*(1+$F2)^(1/12) -> 0 | CH2: =CG2*(1+$F2)^(1/12) -> 0 | CI2: =CH2*(1+$F2)^(1/12) -> 0 | ... CR2: =CQ2*(1+$F2)^(1/12) -> 0 | CU2: =CT2*(1+$F2)^(1/12) -> 0 | CV2: =CU2*(1+$F2)^(1/12) -> 0 | CW2: =CV2*(1+$F2)^(1/12) -> 0 | CX2: =CW2*(1+$F2)^(1/12) -> 0 | CY2: =CX2*(1+$F2)^(1/12) -> 0 | CZ2: =CY2*(1+$F2)^(1/12) -> 0 | DA2: =CZ2*(1+$F2)^(1/12) -> 0 | DB2: =DA2*(1+$F2)^(1/12) -> 0 | ... EL2: =EK2*(1+$F2)^(1/12) -> 0 | GS2: =EL2*(1+$F2)^(1/12) -> 0
K3: 1 | L3: =K3*(1+$F3)^(1/12) -> 1 | M3: =L3*(1+$F3)^(1/12) -> 1 | N3: =M3*(1+$F3)^(1/12) -> 1 | O3: =N3*(1+$F3)^(1/12) -> 1 | P3: =O3*(1+$F3)^(1/12) -> 1 | Q3: =P3*(1+$F3)^(1/12) -> 1 | R3: =Q3*(1+$F3)^(1/12) -> 1 | S3: =R3*(1+$F3)^(1/12) -> 1 | ... BY3: =BX3*(1+$F3)^(1/12) -> 1 | CB3: =CA3*(1+$F3)^(1/12) -> 0 | CC3: =CB3*(1+$F3)^(1/12) -> 0 | CD3: =CC3*(1+$F3)^(1/12) -> 0 | CE3: =CD3*(1+$F3)^(1/12) -> 0 | CF3: =CE3*(1+$F3)^(1/12) -> 0 | CG3: =CF3*(1+$F3)^(1/12) -> 0 | CH3: =CG3*(1+$F3)^(1/12) -> 0 | CI3: =CH3*(1+$F3)^(1/12) -> 0 | ... CR3: =CQ3*(1+$F3)^(1/12) -> 0 | CU3: =CT3*(1+$F3)^(1/12) -> 0 | CV3: =CU3*(1+$F3)^(1/12) -> 0 | CW3: =CV3*(1+$F3)^(1/12) -> 0 | CX3: =CW3*(1+$F3)^(1/12) -> 0 | CY3: =CX3*(1+$F3)^(1/12) -> 0 | CZ3: =CY3*(1+$F3)^(1/12) -> 0 | DA3: =CZ3*(1+$F3)^(1/12) -> 0 | DB3: =DA3*(1+$F3)^(1/12) -> 0 | ... EL3: =EK3*(1+$F3)^(1/12) -> 0 | GS3: =EL3*(1+$F3)^(1/12) -> 0
K4: 1 | L4: =K4*(1+$F4)^(1/12) -> 1 | M4: =L4*(1+$F4)^(1/12) -> 1 | N4: =M4*(1+$F4)^(1/12) -> 1 | O4: =N4*(1+$F4)^(1/12) -> 1 | P4: =O4*(1+$F4)^(1/12) -> 1 | Q4: =P4*(1+$F4)^(1/12) -> 1 | R4: =Q4*(1+$F4)^(1/12) -> 1 | S4: =R4*(1+$F4)^(1/12) -> 1 | ... BY4: =BX4*(1+$F4)^(1/12) -> 1 | CB4: =CA4*(1+$F4)^(1/12) -> 0 | CC4: =CB4*(1+$F4)^(1/12) -> 0 | CD4: =CC4*(1+$F4)^(1/12) -> 0 | CE4: =CD4*(1+$F4)^(1/12) -> 0 | CF4: =CE4*(1+$F4)^(1/12) -> 0 | CG4: =CF4*(1+$F4)^(1/12) -> 0 | CH4: =CG4*(1+$F4)^(1/12) -> 0 | CI4: =CH4*(1+$F4)^(1/12) -> 0 | ... CR4: =CQ4*(1+$F4)^(1/12) -> 0 | CU4: =CT4*(1+$F4)^(1/12) -> 0 | CV4: =CU4*(1+$F4)^(1/12) -> 0 | CW4: =CV4*(1+$F4)^(1/12) -> 0 | CX4: =CW4*(1+$F4)^(1/12) -> 0 | CY4: =CX4*(1+$F4)^(1/12) -> 0 | CZ4: =CY4*(1+$F4)^(1/12) -> 0 | DA4: =CZ4*(1+$F4)^(1/12) -> 0 | DB4: =DA4*(1+$F4)^(1/12) -> 0 | ... EL4: =EK4*(1+$F4)^(1/12) -> 0 | GS4: =EL4*(1+$F4)^(1/12) -> 0
K5: 1 | L5: =K5*(1+$F5)^(1/12) -> 1 | M5: =L5*(1+$F5)^(1/12) -> 1 | N5: =M5*(1+$F5)^(1/12) -> 1 | O5: =N5*(1+$F5)^(1/12) -> 1 | P5: =O5*(1+$F5)^(1/12) -> 1 | Q5: =P5*(1+$F5)^(1/12) -> 1 | R5: =Q5*(1+$F5)^(1/12) -> 1 | S5: =R5*(1+$F5)^(1/12) -> 1 | ... BY5: =BX5*(1+$F5)^(1/12) -> 1 | CB5: =CA5*(1+$F5)^(1/12) -> 0 | CC5: =CB5*(1+$F5)^(1/12) -> 0 | CD5: =CC5*(1+$F5)^(1/12) -> 0 | CE5: =CD5*(1+$F5)^(1/12) -> 0 | CF5: =CE5*(1+$F5)^(1/12) -> 0 | CG5: =CF5*(1+$F5)^(1/12) -> 0 | CH5: =CG5*(1+$F5)^(1/12) -> 0 | CI5: =CH5*(1+$F5)^(1/12) -> 0 | ... CR5: =CQ5*(1+$F5)^(1/12) -> 0 | CU5: =CT5*(1+$F5)^(1/12) -> 0 | CV5: =CU5*(1+$F5)^(1/12) -> 0 | CW5: =CV5*(1+$F5)^(1/12) -> 0 | CX5: =CW5*(1+$F5)^(1/12) -> 0 | CY5: =CX5*(1+$F5)^(1/12) -> 0 | CZ5: =CY5*(1+$F5)^(1/12) -> 0 | DA5: =CZ5*(1+$F5)^(1/12) -> 0 | DB5: =DA5*(1+$F5)^(1/12) -> 0 | ... EL5: =EK5*(1+$F5)^(1/12) -> 0 | GS5: =EL5*(1+$F5)^(1/12) -> 0
K6: 1 | L6: =$K6*(1+$F6)^(L$13/12) -> 1 | M6: =$K6*(1+$F6)^(M$13/12) -> 1 | N6: =$K6*(1+$F6)^(N$13/12) -> 1 | O6: =$K6*(1+$F6)^(O$13/12) -> 1 | P6: =$K6*(1+$F6)^(P$13/12) -> 1 | Q6: =$K6*(1+$F6)^(Q$13/12) -> 1 | R6: =$K6*(1+$F6)^(R$13/12) -> 1 | S6: =$K6*(1+$F6)^(S$13/12) -> 1 | ... BY6: =$K6*(1+$F6)^(BY$13/12) -> 1 | CB6: =$K6*(1+$F6)^(CB$13/12) -> 1 | CC6: =$K6*(1+$F6)^(CC$13/12) -> 1 | CD6: =$K6*(1+$F6)^(CD$13/12) -> 1 | CE6: =$K6*(1+$F6)^(CE$13/12) -> 1 | CF6: =$K6*(1+$F6)^(CF$13/12) -> 1 | CG6: =$K6*(1+$F6)^(CG$13/12) -> 1 | CH6: =$K6*(1+$F6)^(CH$13/12) -> 1 | CI6: =$K6*(1+$F6)^(CI$13/12) -> 1 | ... CR6: =$K6*(1+$F6)^(CR$13/12) -> 1 | CU6: =$K6*(1+$F6)^(CU$13/12) -> 1 | CV6: =$K6*(1+$F6)^(CV$13/12) -> 1 | CW6: =$K6*(1+$F6)^(CW$13/12) -> 1 | CX6: =$K6*(1+$F6)^(CX$13/12) -> 1 | CY6: =$K6*(1+$F6)^(CY$13/12) -> 1 | CZ6: =$K6*(1+$F6)^(CZ$13/12) -> 1 | DA6: =$K6*(1+$F6)^(DA$13/12) -> 1 | DB6: =$K6*(1+$F6)^(DB$13/12) -> 1 | ... EL6: =$K6*(1+$F6)^(EL$13/12) -> 1 | GS6: =$K6*(1+$F6)^(GT$13/12) -> 1
B7: LIBOR Curve | K7: =IFERROR(INDEX(LIBOR!$M$3:$M$122,MATCH('Monthly Cash Flow'!K$15,LIBOR!$N$3:$N$122,0)),J7) -> 0 | L7: =IFERROR(INDEX(LIBOR!$M$3:$M$122,MATCH('Monthly Cash Flow'!L$15,LIBOR!$N$3:$N$122,0)),K7) -> 0 | M7: =IFERROR(INDEX(LIBOR!$M$3:$M$122,MATCH('Monthly Cash Flow'!M$15,LIBOR!$N$3:$N$122,0)),L7) -> 0 | N7: =IFERROR(INDEX(LIBOR!$M$3:$M$122,MATCH('Monthly Cash Flow'!N$15,LIBOR!$N$3:$N$122,0)),M7) -> 0 | O7: =IFERROR(INDEX(LIBOR!$M$3:$M$122,MATCH('Monthly Cash Flow'!O$15,LIBOR!$N$3:$N$122,0)),N7) -> 0 | P7: =IFERROR(INDEX(LIBOR!$M$3:$M$122,MATCH('Monthly Cash Flow'!P$15,LIBOR!$N$3:$N$122,0)),O7) -> 0 | Q7: =IFERROR(INDEX(LIBOR!$M$3:$M$122,MATCH('Monthly Cash Flow'!Q$15,LIBOR!$N$3:$N$122,0)),P7) -> 0 | R7: =IFERROR(INDEX(LIBOR!$M$3:$M$122,MATCH('Monthly Cash Flow'!R$15,LIBOR!$N$3:$N$122,0)),Q7) -> 0 | ... BY7: =IFERROR(INDEX(LIBOR!$M$3:$M$122,MATCH('Monthly Cash Flow'!BY$15,LIBOR!$N$3:$N$122,0)),BX7) -> 0.0015071 | CB7: =IFERROR(INDEX(LIBOR!$M$3:$M$122,MATCH('Monthly Cash Flow'!CB$15,LIBOR!$N$3:$N$122,0)),CA7) -> 0.0015849 | CC7: =IFERROR(INDEX(LIBOR!$M$3:$M$122,MATCH('Monthly Cash Flow'!CC$15,LIBOR!$N$3:$N$122,0)),CB7) -> 0.0015552 | CD7: =IFERROR(INDEX(LIBOR!$M$3:$M$122,MATCH('Monthly Cash Flow'!CD$15,LIBOR!$N$3:$N$122,0)),CC7) -> 0.001517 | CE7: =IFERROR(INDEX(LIBOR!$M$3:$M$122,MATCH('Monthly Cash Flow'!CE$15,LIBOR!$N$3:$N$122,0)),CD7) -> 0.0014938 | CF7: =IFERROR(INDEX(LIBOR!$M$3:$M$122,MATCH('Monthly Cash Flow'!CF$15,LIBOR!$N$3:$N$122,0)),CE7) -> 0.0014702 | CG7: =IFERROR(INDEX(LIBOR!$M$3:$M$122,MATCH('Monthly Cash Flow'!CG$15,LIBOR!$N$3:$N$122,0)),CF7) -> 0.0014851 | CH7: =IFERROR(INDEX(LIBOR!$M$3:$M$122,MATCH('Monthly Cash Flow'!CH$15,LIBOR!$N$3:$N$122,0)),CG7) -> 0.0015347 | CI7: =IFERROR(INDEX(LIBOR!$M$3:$M$122,MATCH('Monthly Cash Flow'!CI$15,LIBOR!$N$3:$N$122,0)),CH7) -> 0.0015907 | ... CR7: =IFERROR(INDEX(LIBOR!$M$3:$M$122,MATCH('Monthly Cash Flow'!CR$15,LIBOR!$N$3:$N$122,0)),CQ7) -> 0.0495866 | CU7: =IFERROR(INDEX(LIBOR!$M$3:$M$122,MATCH('Monthly Cash Flow'!CU$15,LIBOR!$N$3:$N$122,0)),CT7) -> 0.0471558 | CV7: =IFERROR(INDEX(LIBOR!$M$3:$M$122,MATCH('Monthly Cash Flow'!CV$15,LIBOR!$N$3:$N$122,0)),CU7) -> 0.0461346 | CW7: =IFERROR(INDEX(LIBOR!$M$3:$M$122,MATCH('Monthly Cash Flow'!CW$15,LIBOR!$N$3:$N$122,0)),CV7) -> 0.0450652 | CX7: =IFERROR(INDEX(LIBOR!$M$3:$M$122,MATCH('Monthly Cash Flow'!CX$15,LIBOR!$N$3:$N$122,0)),CW7) -> 0.0440782 | CY7: =IFERROR(INDEX(LIBOR!$M$3:$M$122,MATCH('Monthly Cash Flow'!CY$15,LIBOR!$N$3:$N$122,0)),CX7) -> 0.0429112 | CZ7: =IFERROR(INDEX(LIBOR!$M$3:$M$122,MATCH('Monthly Cash Flow'!CZ$15,LIBOR!$N$3:$N$122,0)),CY7) -> 0.0416869 | DA7: =IFERROR(INDEX(LIBOR!$M$3:$M$122,MATCH('Monthly Cash Flow'!DA$15,LIBOR!$N$3:$N$122,0)),CZ7) -> 0.0405943 | DB7: =IFERROR(INDEX(LIBOR!$M$3:$M$122,MATCH('Monthly Cash Flow'!DB$15,LIBOR!$N$3:$N$122,0)),DA7) -> 0.0394062 | ... EL7: =IFERROR(INDEX(LIBOR!$M$3:$M$122,MATCH('Monthly Cash Flow'!EL$15,LIBOR!$N$3:$N$122,0)),EK7) -> 0.0325073 | GS7: =IFERROR(INDEX(LIBOR!$M$3:$M$122,MATCH('Monthly Cash Flow'!GT$15,LIBOR!$N$3:$N$122,0)),EL7) -> 0.0325073
CB9: =SUM(CB22:CD22)*1000 -> 0
B10: =+Assumptions!B2 -> Chapman Plaza | BN10: =BM13+120 -> 174
B11: Monthly Project Cash Flow | CL11: 1 | CM11: =CL11+1 -> 2 | CN11: =CM11+1 -> 3 | CO11: =CN11+1 -> 4 | CP11: =CO11+1 -> 5 | CQ11: =CP11+1 -> 6 | CR11: =CQ11+1 -> 7 | CS11: =CR11+1 -> 8 | CT11: =CS11+1 -> 9 | ... HA11: =GZ11+1 -> 120 | HG11: =HF11+1 -> 1
B12: ($ in thousands, except psf amounts) | L12: Actuals | M12: Actuals | N12: Actuals | O12: Actuals | P12: Actuals | Q12: Actuals | R12: Actuals | S12: Actuals | T12: Actuals | U12: Actuals | V12: Actuals | W12: Actuals | X12: Actuals | Y12: Actuals | Z12: Actuals | AA12: Actuals | AB12: Actuals | AC12: Actuals | AD12: Actuals | AE12: Actuals | AF12: Actuals | AG12: Actuals | AH12: Actuals | AI12: Actuals | AJ12: Actuals | AK12: Actuals | AL12: Actuals | AM12: Actuals | AN12: Actuals | AO12: Actuals | AP12: Actuals | AQ12: Actuals | AR12: Actuals | AS12: Actuals | AT12: Actuals | AU12: Actuals | AV12: Actuals | AW12: Actuals | AX12: Actuals | AY12: Actuals | AZ12: Actuals | BA12: Actuals | BB12: Actuals | BC12: Actuals | BD12: Actuals | BE12: Actuals | BF12: Actuals | BG12: Actuals | BH12: Actuals | BI12: Actuals | BJ12: Actuals | BK12: Actuals | BL12: Actuals | BM12: Actuals | BN12: Actuals | BO12: Actuals | BP12: Actuals | BQ12: Actuals | BR12: Actuals | BS12: Actuals | BT12: Actuals | BU12: Actuals | BV12: Actuals | BW12: Actuals | BX12: Actuals | BY12: Actuals | BZ12: Actuals | CA12: Actuals | CB12: Actuals | CC12: Actuals | CD12: Actuals | CE12: Actuals | CF12: Actuals | CG12: Actuals | CH12: Actuals | CI12: Proforma | CJ12: Proforma | CK12: Proforma | CL12: Proforma | CM12: Proforma | CN12: Proforma | CO12: Proforma | CP12: Proforma | CQ12: Proforma | CR12: Proforma | CS12: Proforma | CT12: Proforma | CU12: Proforma | CV12: Proforma | CW12: Proforma | CX12: Proforma | CY12: Proforma | CZ12: Proforma | DA12: Proforma | DB12: Proforma | DC12: Proforma | DD12: Proforma | DE12: Proforma | DF12: Proforma | DG12: Proforma | DH12: Proforma | DI12: Proforma | DJ12: Proforma | DK12: Proforma | DL12: Proforma | DM12: Proforma | DN12: Proforma | DO12: Proforma | DP12: Proforma | DQ12: Proforma | DR12: Proforma | DS12: Proforma | DT12: Proforma | DU12: Proforma | DV12: Proforma | DW12: Proforma | DX12: Proforma | DY12: Proforma | DZ12: Proforma | EA12: Proforma | EB12: Proforma | EC12: Proforma | ED12: Proforma | EE12: Proforma | EF12: Proforma | EG12: Proforma | EH12: Proforma | EI12: Proforma | EJ12: Proforma | EK12: Proforma | EL12: Proforma | EM12: Proforma | EN12: Proforma | EO12: Proforma | EP12: Proforma | EQ12: Proforma | ER12: Proforma | ES12: Proforma | ET12: Proforma | EU12: Proforma | EV12: Proforma | EW12: Proforma | EX12: Proforma | EY12: Proforma | EZ12: Proforma | FA12: Proforma | FB12: Proforma | FC12: Proforma | FD12: Proforma | FE12: Proforma | FF12: Proforma | FG12: Proforma | FH12: Proforma | FI12: Proforma | FJ12: Proforma | FK12: Proforma | FL12: Proforma | FM12: Proforma | FN12: Proforma | FO12: Proforma | FP12: Proforma | FQ12: Proforma | FR12: Proforma | FS12: Proforma | FT12: Proforma | FU12: Proforma | FV12: Proforma | FW12: Proforma | FX12: Proforma | FY12: Proforma | FZ12: Proforma | GA12: Proforma | GB12: Proforma | GC12: Proforma | GD12: Proforma | GE12: Proforma | GF12: Proforma | GG12: Proforma | GH12: Proforma | GI12: Proforma | GJ12: Proforma | GK12: Proforma | GL12: Proforma | GM12: Proforma | GN12: Proforma | GO12: Proforma | GP12: Proforma | GQ12: Proforma | GR12: Proforma | GS12: Proforma | GT12: Proforma | GU12: Proforma | GV12: Proforma | GW12: Proforma | GX12: Proforma | GY12: Proforma | GZ12: Proforma | HA12: Proforma | HF12: 1
B13: Current Month | C13: 79 | D13: =HLOOKUP(C13,$L$13:$GT$15,3) -> 44957 | K13: =Assumptions!J7 -> 0 | L13: =K13+1 -> 1 | M13: =L13+1 -> 2 | N13: =M13+1 -> 3 | O13: =N13+1 -> 4 | P13: =O13+1 -> 5 | Q13: =P13+1 -> 6 | R13: =Q13+1 -> 7 | S13: =R13+1 -> 8 | ... HA13: =GZ13+1 -> 198 | HH13: Annual Project Cash Flows
K14: =ROUNDUP(K13/12,0) -> 0 | L14: =ROUNDUP(L13/12,0) -> 1 | M14: =ROUNDUP(M13/12,0) -> 1 | N14: =ROUNDUP(N13/12,0) -> 1 | O14: =ROUNDUP(O13/12,0) -> 1 | P14: =ROUNDUP(P13/12,0) -> 1 | Q14: =ROUNDUP(Q13/12,0) -> 1 | R14: =ROUNDUP(R13/12,0) -> 1 | ... HA14: =ROUNDUP(HA13/12,0) -> 17 | HN14: 0 | HO14: =HN14+1 -> 1 | HP14: =HO14+1 -> 2 | HQ14: =HP14+1 -> 3 | HR14: =HQ14+1 -> 4 | HS14: =HR14+1 -> 5 | HT14: =HS14+1 -> 6 | HU14: =HT14+1 -> 7 | HV14: =HU14+1 -> 8
K15: =+Assumptions!I6 -> 42552 | L15: =EOMONTH(K15,0) -> 42582 | M15: =EOMONTH(L15,1) -> 42613 | N15: =EOMONTH(M15,1) -> 42643 | O15: =EOMONTH(N15,1) -> 42674 | P15: =EOMONTH(O15,1) -> 42704 | Q15: =EOMONTH(P15,1) -> 42735 | R15: =EOMONTH(Q15,1) -> 42766 | S15: =EOMONTH(R15,1) -> 42794 | T15: =EOMONTH(S15,1) -> 42825 | ... HA15: =EOMONTH(GZ15,1) -> 48579 | HG15: 1 | HL15: 12 Months Ending: | HN15: =IF(HN$14=0,EOMONTH($K$15,0),EOMONTH(HM$15,12)) -> 42582 | HO15: =IF(HO$14=0,EOMONTH($K$15,0),EOMONTH(HN$15,12)) -> 42947 | HP15: =IF(HP$14=0,EOMONTH($K$15,0),EOMONTH(HO$15,12)) -> 43312 | HQ15: =IF(HQ$14=0,EOMONTH($K$15,0),EOMONTH(HP$15,12)) -> 43677 | HR15: =IF(HR$14=0,EOMONTH($K$15,0),EOMONTH(HQ$15,12)) -> 44043 | HS15: =IF(HS$14=0,EOMONTH($K$15,0),EOMONTH(HR$15,12)) -> 44408 | HT15: =IF(HT$14=0,EOMONTH($K$15,0),EOMONTH(HS$15,12)) -> 44773 | HU15: =IF(HU$14=0,EOMONTH($K$15,0),EOMONTH(HT$15,12)) -> 45138 | HV15: =IF(HV$14=0,EOMONTH($K$15,0),EOMONTH(HU$15,12)) -> 45504
B16: Unleveraged Costs | I16: Total | HF16: x | HG16: =HG15+1 -> 2 | HH16: =B16 -> Unleveraged Costs | HL16: Total
B17: Acquisition Costs | HF17: x | HG17: =HG16+1 -> 3 | HH17: =B17 -> Acquisition Costs
B18: =Assumptions!B12 -> Purchase Price | I18: =SUM(K18:GT18) -> 30000 | K18: =Assumptions!C12 -> 30000 | L18: 0 | M18: 0 | N18: 0 | O18: 0 | P18: 0 | Q18: 0 | R18: 0 | S18: 0 | T18: 0 | U18: 0 | V18: 0 | W18: 0 | X18: 0 | Y18: 0 | Z18: 0 | AA18: 0 | AB18: 0 | AC18: 0 | AD18: 0 | AE18: 0 | AF18: 0 | AG18: 0 | AH18: 0 | AI18: 0 | AJ18: 0 | AK18: 0 | AL18: 0 | AM18: 0 | AN18: 0 | AO18: 0 | AP18: 0 | AQ18: 0 | AR18: 0 | AS18: 0 | AT18: 0 | AU18: 0 | AV18: 0 | AW18: 0 | AX18: 0 | AY18: 0 | AZ18: 0 | BA18: 0 | BB18: 0 | BC18: 0 | BD18: 0 | BE18: 0 | BF18: 0 | BG18: 0 | BH18: 0 | BI18: 0 | BJ18: 0 | BK18: 0 | BL18: 0 | BM18: 0 | BN18: 0 | BO18: 0 | BP18: 0 | BQ18: 0 | BR18: 0 | BS18: 0 | BT18: 0 | BU18: 0 | BV18: 0 | BW18: 0 | BX18: 0 | BY18: 0 | BZ18: 0 | CA18: 0 | CB18: 0 | CC18: 0 | CD18: 0 | CE18: 0 | CF18: 0 | CG18: 0 | CH18: 0 | CI18: 0 | CJ18: 0 | CK18: 0 | CL18: 0 | CM18: 0 | CN18: 0 | CO18: 0 | CP18: 0 | CQ18: 0 | CR18: 0 | CS18: 0 | CT18: 0 | CU18: 0 | CV18: 0 | CW18: 0 | CX18: 0 | CY18: 0 | CZ18: 0 | DA18: 0 | DB18: 0 | DC18: 0 | DD18: 0 | DE18: 0 | DF18: 0 | DG18: 0 | DH18: 0 | DI18: 0 | DJ18: 0 | DK18: 0 | DL18: 0 | DM18: 0 | DN18: 0 | DO18: 0 | DP18: 0 | DQ18: 0 | DR18: 0 | DS18: 0 | DT18: 0 | DU18: 0 | DV18: 0 | DW18: 0 | DX18: 0 | DY18: 0 | DZ18: 0 | EA18: 0 | EB18: 0 | EC18: 0 | ED18: 0 | EE18: 0 | EF18: 0 | EG18: 0 | EH18: 0 | EI18: 0 | EJ18: 0 | EK18: 0 | EL18: 0 | EM18: 0 | EN18: 0 | EO18: 0 | EP18: 0 | EQ18: 0 | ER18: 0 | ES18: 0 | ET18: 0 | EU18: 0 | EV18: 0 | EW18: 0 | EX18: 0 | EY18: 0 | EZ18: 0 | FA18: 0 | FB18: 0 | FC18: 0 | FD18: 0 | FE18: 0 | FF18: 0 | FG18: 0 | FH18: 0 | FI18: 0 | FJ18: 0 | FK18: 0 | FL18: 0 | FM18: 0 | FN18: 0 | FO18: 0 | FP18: 0 | FQ18: 0 | FR18: 0 | FS18: 0 | FT18: 0 | FU18: 0 | FV18: 0 | FW18: 0 | FX18: 0 | FY18: 0 | FZ18: 0 | GA18: 0 | GB18: 0 | GC18: 0 | GD18: 0 | GE18: 0 | GF18: 0 | GG18: 0 | GH18: 0 | GI18: 0 | GJ18: 0 | GK18: 0 | GL18: 0 | GM18: 0 | GN18: 0 | GO18: 0 | GP18: 0 | GQ18: 0 | GR18: 0 | GS18: 0 | GT18: 0 | GU18: 0 | GV18: 0 | GW18: 0 | GX18: 0 | GY18: 0 | GZ18: 0 | HA18: 0 | HF18: x | HG18: =HG17+1 -> 4 | HH18: =B18 -> Purchase Price | HL18: =SUM(HN18:HV18) -> 30000 | HN18: =SUMIF($K$14:$GT$14,HN$14,$K18:$GT18) -> 30000 | HO18: =SUMIF($K$14:$GT$14,HO$14,$K18:$GT18) -> 0 | HP18: =SUMIF($K$14:$GT$14,HP$14,$K18:$GT18) -> 0 | HQ18: =SUMIF($K$14:$GT$14,HQ$14,$K18:$GT18) -> 0 | HR18: =SUMIF($K$14:$GT$14,HR$14,$K18:$GT18) -> 0 | HS18: =SUMIF($K$14:$GT$14,HS$14,$K18:$GT18) -> 0 | HT18: =SUMIF($K$14:$GT$14,HT$14,$K18:$GT18) -> 0 | HU18: =SUMIF($K$14:$GT$14,HU$14,$K18:$GT18) -> 0 | HV18: =SUMIF($K$14:$GT$14,HV$14,$K18:$GT18) -> 0
B19: =Assumptions!B13 -> 0.0068666667 | I19: =SUM(K19:GT19) -> 206 | K19: =Assumptions!C13 -> 206 | L19: 0 | M19: 0 | N19: 0 | O19: 0 | P19: 0 | Q19: 0 | R19: 0 | S19: 0 | T19: 0 | U19: 0 | V19: 0 | W19: 0 | X19: 0 | Y19: 0 | Z19: 0 | AA19: 0 | AB19: 0 | AC19: 0 | AD19: 0 | AE19: 0 | AF19: 0 | AG19: 0 | AH19: 0 | AI19: 0 | AJ19: 0 | AK19: 0 | AL19: 0 | AM19: 0 | AN19: 0 | AO19: 0 | AP19: 0 | AQ19: 0 | AR19: 0 | AS19: 0 | AT19: 0 | AU19: 0 | AV19: 0 | AW19: 0 | AX19: 0 | AY19: 0 | AZ19: 0 | BA19: 0 | BB19: 0 | BC19: 0 | BD19: 0 | BE19: 0 | BF19: 0 | BG19: 0 | BH19: 0 | BI19: 0 | BJ19: 0 | BK19: 0 | BL19: 0 | BM19: 0 | BN19: 0 | BO19: 0 | BP19: 0 | BQ19: 0 | BR19: 0 | BS19: 0 | BT19: 0 | BU19: 0 | BV19: 0 | BW19: 0 | BX19: 0 | BY19: 0 | BZ19: 0 | CA19: 0 | CB19: 0 | CC19: 0 | CD19: 0 | CE19: 0 | CF19: 0 | CG19: 0 | CH19: 0 | CI19: 0 | CJ19: 0 | CK19: 0 | CL19: 0 | CM19: 0 | CN19: 0 | CO19: 0 | CP19: 0 | CQ19: 0 | CR19: 0 | CS19: 0 | CT19: 0 | CU19: 0 | CV19: 0 | CW19: 0 | CX19: 0 | CY19: 0 | CZ19: 0 | DA19: 0 | DB19: 0 | DC19: 0 | DD19: 0 | DE19: 0 | DF19: 0 | DG19: 0 | DH19: 0 | DI19: 0 | DJ19: 0 | DK19: 0 | DL19: 0 | DM19: 0 | DN19: 0 | DO19: 0 | DP19: 0 | DQ19: 0 | DR19: 0 | DS19: 0 | DT19: 0 | DU19: 0 | DV19: 0 | DW19: 0 | DX19: 0 | DY19: 0 | DZ19: 0 | EA19: 0 | EB19: 0 | EC19: 0 | ED19: 0 | EE19: 0 | EF19: 0 | EG19: 0 | EH19: 0 | EI19: 0 | EJ19: 0 | EK19: 0 | EL19: 0 | EM19: 0 | EN19: 0 | EO19: 0 | EP19: 0 | EQ19: 0 | ER19: 0 | ES19: 0 | ET19: 0 | EU19: 0 | EV19: 0 | EW19: 0 | EX19: 0 | EY19: 0 | EZ19: 0 | FA19: 0 | FB19: 0 | FC19: 0 | FD19: 0 | FE19: 0 | FF19: 0 | FG19: 0 | FH19: 0 | FI19: 0 | FJ19: 0 | FK19: 0 | FL19: 0 | FM19: 0 | FN19: 0 | FO19: 0 | FP19: 0 | FQ19: 0 | FR19: 0 | FS19: 0 | FT19: 0 | FU19: 0 | FV19: 0 | FW19: 0 | FX19: 0 | FY19: 0 | FZ19: 0 | GA19: 0 | GB19: 0 | GC19: 0 | GD19: 0 | GE19: 0 | GF19: 0 | GG19: 0 | GH19: 0 | GI19: 0 | GJ19: 0 | GK19: 0 | GL19: 0 | GM19: 0 | GN19: 0 | GO19: 0 | GP19: 0 | GQ19: 0 | GR19: 0 | GS19: 0 | GT19: 0 | GU19: 0 | GV19: 0 | GW19: 0 | GX19: 0 | GY19: 0 | GZ19: 0 | HA19: 0 | HF19: x | HG19: =HG18+1 -> 5 | HH19: =B19 -> 0.0068666667 | HL19: =SUM(HN19:HV19) -> 206 | HN19: =SUMIF($K$14:$GT$14,HN$14,$K19:$GT19) -> 206 | HO19: =SUMIF($K$14:$GT$14,HO$14,$K19:$GT19) -> 0 | HP19: =SUMIF($K$14:$GT$14,HP$14,$K19:$GT19) -> 0 | HQ19: =SUMIF($K$14:$GT$14,HQ$14,$K19:$GT19) -> 0 | HR19: =SUMIF($K$14:$GT$14,HR$14,$K19:$GT19) -> 0 | HS19: =SUMIF($K$14:$GT$14,HS$14,$K19:$GT19) -> 0 | HT19: =SUMIF($K$14:$GT$14,HT$14,$K19:$GT19) -> 0 | HU19: =SUMIF($K$14:$GT$14,HU$14,$K19:$GT19) -> 0 | HV19: =SUMIF($K$14:$GT$14,HV$14,$K19:$GT19) -> 0
B20: Total Acquisition Costs | I20: =SUM(K20:GT20) -> 30206 | K20: =SUBTOTAL(9,K18:K19) -> 30206 | L20: =SUBTOTAL(9,L18:L19) -> 0 | M20: =SUBTOTAL(9,M18:M19) -> 0 | N20: =SUBTOTAL(9,N18:N19) -> 0 | O20: =SUBTOTAL(9,O18:O19) -> 0 | P20: =SUBTOTAL(9,P18:P19) -> 0 | Q20: =SUBTOTAL(9,Q18:Q19) -> 0 | R20: =SUBTOTAL(9,R18:R19) -> 0 | ... HA20: =SUBTOTAL(9,HA18:HA19) -> 0 | HF20: x | HG20: =HG19+1 -> 6 | HH20: =B20 -> Total Acquisition Costs | HL20: =SUM(HN20:HV20) -> 30206 | HN20: =SUMIF($K$14:$GT$14,HN$14,$K20:$GT20) -> 30206 | HO20: =SUMIF($K$14:$GT$14,HO$14,$K20:$GT20) -> 0 | HP20: =SUMIF($K$14:$GT$14,HP$14,$K20:$GT20) -> 0 | HQ20: =SUMIF($K$14:$GT$14,HQ$14,$K20:$GT20) -> 0 | HR20: =SUMIF($K$14:$GT$14,HR$14,$K20:$GT20) -> 0 | HS20: =SUMIF($K$14:$GT$14,HS$14,$K20:$GT20) -> 0 | HT20: =SUMIF($K$14:$GT$14,HT$14,$K20:$GT20) -> 0 | HU20: =SUMIF($K$14:$GT$14,HU$14,$K20:$GT20) -> 0 | HV20: =SUMIF($K$14:$GT$14,HV$14,$K20:$GT20) -> 0
C21: Start | E21: End | F21: ="Costs to Date"&" - "&TEXT($D$13,"mmm-yy") -> Costs to Date - Jan-23 | G21: New Budget | H21: Budget | HF21: x | HG21: =HG20+1 -> 7
B22: CapEx 2023
B23: Suite 300 Elevator | C23: 80 | E23: 88 | G23: =Assumptions!L76 -> 250 | H23: =G23 -> 250 | I23: =SUMIF($K$13:$GT$13,"<="&Assumptions!$L$17,'Monthly Cash Flow'!K23:GT23) -> 250 | CE23: =IF(AND(CE$13>=$C23,CE$13<=$E23),($H23-SUM($K23:CD23))/(($E23-CE$13+1)),0) -> 0 | CF23: =IF(AND(CF$13>=$C23,CF$13<=$E23),($H23-SUM($K23:CE23))/(($E23-CF$13+1)),0) -> 0 | CG23: =IF(AND(CG$13>=$C23,CG$13<=$E23),($H23-SUM($K23:CF23))/(($E23-CG$13+1)),0) -> 0 | CH23: =IF(AND(CH$13>=$C23,CH$13<=$E23),($H23-SUM($K23:CG23))/(($E23-CH$13+1)),0) -> 0 | CI23: =IF(AND(CI$13>=$C23,CI$13<=$E23),($H23-SUM($K23:CH23))/(($E23-CI$13+1)),0) -> 0 | CJ23: =IF(AND(CJ$13>=$C23,CJ$13<=$E23),($H23-SUM($K23:CI23))/(($E23-CJ$13+1)),0) -> 0 | CK23: =IF(AND(CK$13>=$C23,CK$13<=$E23),($H23-SUM($K23:CJ23))/(($E23-CK$13+1)),0) -> 0 | CL23: =IF(AND(CL$13>=$C23,CL$13<=$E23),($H23-SUM($K23:CK23))/(($E23-CL$13+1)),0) -> 0 | ... GT23: =IF(AND(GT$13>=$C23,GT$13<=$E23),($H23-SUM($K23:GS23))/(($E23-GT$13+1)),0) -> 0 | HF23: x | HG23: =HG22+1 -> 1
B24: Common Area | C24: 80 | E24: 86 | F24: =SUMIF($K$13:$GT$13,"<="&$C$13,'Monthly Cash Flow'!K24:GT24) -> 0 | G24: =Assumptions!L75 -> 240 | H24: =G24 -> 240 | I24: =SUMIF($K$13:$GT$13,"<="&Assumptions!$L$17,'Monthly Cash Flow'!K24:GT24) -> 240 | L24: 0 | M24: 0 | N24: 0 | O24: 0 | P24: 0 | Q24: 0 | R24: 0 | S24: 0 | T24: 0 | U24: 0 | V24: 0 | W24: 0 | X24: 0 | Y24: 0 | Z24: 0 | AA24: 0 | AB24: 0 | AC24: 0 | AD24: 0 | AE24: 0 | AF24: 0 | AG24: 0 | AH24: 0 | AI24: 0 | AJ24: 0 | AK24: 0 | AL24: 0 | AM24: 0 | AN24: 0 | AO24: 0 | AP24: 0 | AQ24: 0 | AR24: 0 | AS24: 0 | AT24: 0 | AU24: 0 | AV24: 0 | AW24: 0 | AX24: 0 | AY24: 0 | AZ24: 0 | BA24: 0 | BB24: 0 | BC24: 0 | BD24: 0 | BE24: 0 | BF24: 0 | BG24: 0 | BH24: 0 | BI24: 0 | BJ24: 0 | BK24: 0 | BL24: =IF(AND(BL$13>=$C24,BL$13<=$E24),($H24-SUM($K24:BK24))/(($E24-BL$13+1)),0) -> 0 | BM24: =IF(AND(BM$13>=$C24,BM$13<=$E24),($H24-SUM($K24:BL24))/(($E24-BM$13+1)),0) -> 0 | BN24: =IF(AND(BN$13>=$C24,BN$13<=$E24),($H24-SUM($K24:BM24))/(($E24-BN$13+1)),0) -> 0 | BO24: =IF(AND(BO$13>=$C24,BO$13<=$E24),($H24-SUM($K24:BN24))/(($E24-BO$13+1)),0) -> 0 | BP24: =IF(AND(BP$13>=$C24,BP$13<=$E24),($H24-SUM($K24:BO24))/(($E24-BP$13+1)),0) -> 0 | BQ24: =IF(AND(BQ$13>=$C24,BQ$13<=$E24),($H24-SUM($K24:BP24))/(($E24-BQ$13+1)),0) -> 0 | BR24: =IF(AND(BR$13>=$C24,BR$13<=$E24),($H24-SUM($K24:BQ24))/(($E24-BR$13+1)),0) -> 0 | BS24: =IF(AND(BS$13>=$C24,BS$13<=$E24),($H24-SUM($K24:BR24))/(($E24-BS$13+1)),0) -> 0 | ... GS24: =IF(AND(GS$13>=$C24,GS$13<=$E24),($H24-SUM($K24:GR24))/(($E24-GS$13+1)),0) -> 0
B25: Historical CapEx Spends | C25: 1 | E25: 66 | F25: =SUMIF($K$13:$GT$13,"<="&$C$13,'Monthly Cash Flow'!K25:GT25) -> 1824.3238 | H25: =SUM(F25:G25) -> 1824.3238 | I25: =SUMIF($K$13:$GT$13,"<="&Assumptions!$L$17,'Monthly Cash Flow'!K25:GT25) -> 1824.3238 | K25: 0 | L25: 0 | M25: 0 | N25: 0 | O25: 0 | P25: 0 | Q25: 0 | R25: 0 | S25: 0 | T25: 0 | U25: 36.0885 | V25: 0 | W25: 47.94 | X25: 0 | Y25: 0 | Z25: 232.8555 | AA25: 0 | AB25: 361.59281 | AC25: 0 | AD25: 0 | AE25: 403.9507 | AF25: 67.99761 | AG25: 145.09164 | AH25: 0 | AI25: 0 | AJ25: 0 | AK25: 0 | AL25: 1.98 | AM25: 0 | AN25: 16.798 | AO25: 0 | AP25: 0 | AQ25: 3.873 | AR25: 0 | AS25: 0 | AT25: 0 | AU25: 0 | AV25: 0 | AW25: 0 | AX25: 0 | AY25: 15.5 | AZ25: 0 | BA25: 0 | BB25: 0 | BC25: 142.1 | BD25: 23.258 | BE25: 0 | BF25: 0 | BG25: 0 | BH25: 0 | BI25: 0 | BJ25: 0 | BK25: 0 | BL25: 0 | BM25: 0 | BN25: 0 | BO25: 0 | BP25: 0 | BQ25: 0 | BR25: =65924/1000 -> 65.924 | BS25: 0 | BT25: 0 | BU25: 0 | BV25: 0 | BW25: 0 | BX25: 0 | BY25: =84080/1000 -> 84.08 | BZ25: 0 | CA25: 0 | CB25: 0 | CC25: 0 | CD25: =(80957/1000)+(94337/1000) -> 175.294 | CE25: 0 | CF25: 0 | CG25: 0 | CH25: 0 | CI25: =IF(AND(CI$13>=$C25,CI$13<=$E25),($H25-SUM($K25:CH25))/(($E25-CI$13+1)),0) -> 0 | CJ25: =IF(AND(CJ$13>=$C25,CJ$13<=$E25),($H25-SUM($K25:CI25))/(($E25-CJ$13+1)),0) -> 0 | CK25: =IF(AND(CK$13>=$C25,CK$13<=$E25),($H25-SUM($K25:CJ25))/(($E25-CK$13+1)),0) -> 0 | CL25: =IF(AND(CL$13>=$C25,CL$13<=$E25),($H25-SUM($K25:CK25))/(($E25-CL$13+1)),0) -> 0 | CM25: =IF(AND(CM$13>=$C25,CM$13<=$E25),($H25-SUM($K25:CL25))/(($E25-CM$13+1)),0) -> 0 | CN25: =IF(AND(CN$13>=$C25,CN$13<=$E25),($H25-SUM($K25:CM25))/(($E25-CN$13+1)),0) -> 0 | CO25: =IF(AND(CO$13>=$C25,CO$13<=$E25),($H25-SUM($K25:CN25))/(($E25-CO$13+1)),0) -> 0 | CP25: =IF(AND(CP$13>=$C25,CP$13<=$E25),($H25-SUM($K25:CO25))/(($E25-CP$13+1)),0) -> 0 | ... GT25: =IF(AND(GT$13>=$C25,GT$13<=$E25),($H25-SUM($K25:GS25))/(($E25-GT$13+1)),0) -> 0 | HF25: x | HG25: =HG23+1 -> 2
A26: HC | B26: =+Assumptions!B17 -> CapEx | G26: =SUM(G22:G25) -> 490 | H26: =SUM(H22:H25) -> 2314.3238 | I26: =SUMIF($K$13:$GT$13,"<="&Assumptions!$L$17,'Monthly Cash Flow'!K26:GT26) -> 2314.3238 | K26: =SUBTOTAL(9,K22:K25) -> 0 | L26: =SUBTOTAL(9,L22:L25) -> 0 | M26: =SUBTOTAL(9,M22:M25) -> 0 | N26: =SUBTOTAL(9,N22:N25) -> 0 | O26: =SUBTOTAL(9,O22:O25) -> 0 | P26: =SUBTOTAL(9,P22:P25) -> 0 | Q26: =SUBTOTAL(9,Q22:Q25) -> 0 | R26: =SUBTOTAL(9,R22:R25) -> 0 | ... BV26: =SUBTOTAL(9,BV22:BV25) -> 0 | BW26: =SUBTOTAL(9,BW23:BW25) -> 0 | BX26: =SUBTOTAL(9,BX23:BX25) -> 0 | BY26: =SUBTOTAL(9,BY22:BY25) -> 84.08 | BZ26: =SUBTOTAL(9,BZ22:BZ25) -> 0 | CA26: =SUBTOTAL(9,CA22:CA25) -> 0 | CB26: =SUBTOTAL(9,CB22:CB25) -> 0 | CC26: =SUBTOTAL(9,CC22:CC25) -> 0 | CD26: =SUBTOTAL(9,CD22:CD25) -> 175.294 | CE26: =SUBTOTAL(9,CE22:CE25) -> 0 | CF26: =SUBTOTAL(9,CF22:CF25) -> 0 | ... GT26: =SUBTOTAL(9,GT22:GT25) -> 0 | HF26: x | HG26: =HG25+1 -> 3 | HH26: =+B26 -> CapEx | HL26: =SUM(HN26:HV26) -> 2314.3238 | HN26: =SUMIF($K$14:$GT$14,HN$14,$K26:$GT26) -> 0 | HO26: =SUMIF($K$14:$GT$14,HO$14,$K26:$GT26) -> 84.0285 | HP26: =SUMIF($K$14:$GT$14,HP$14,$K26:$GT26) -> 1211.4883 | HQ26: =SUMIF($K$14:$GT$14,HQ$14,$K26:$GT26) -> 22.651 | HR26: =SUMIF($K$14:$GT$14,HR$14,$K26:$GT26) -> 180.858 | HS26: =SUMIF($K$14:$GT$14,HS$14,$K26:$GT26) -> 65.924 | HT26: =SUMIF($K$14:$GT$14,HT$14,$K26:$GT26) -> 259.374 | HU26: =SUMIF($K$14:$GT$14,HU$14,$K26:$GT26) -> 310.31746 | HV26: =SUMIF($K$14:$GT$14,HV$14,$K26:$GT26) -> 179.68254
B27: Soft Costs | C27: =Assumptions!J13 -> 68 | E27: 71 | F27: =SUMIF($K$13:$GT$13,"<="&$C$13,'Monthly Cash Flow'!K27:GT27) -> 798.309 | H27: =SUM(F27:G27) -> 798.309 | I27: =SUMIF($K$13:$GT$13,"<="&Assumptions!$L$17,'Monthly Cash Flow'!K27:GT27) -> 798.309 | K27: 0 | L27: 0 | M27: 0 | N27: 0 | O27: 0 | P27: 0 | Q27: 0 | R27: 0 | S27: 0 | T27: 0 | U27: 138.72733 | V27: 0 | W27: 0 | X27: 0 | Y27: 0 | Z27: 226.13481 | AA27: 0 | AB27: 87.18598 | AC27: 0 | AD27: 0 | AE27: 83.58834 | AF27: 79.022689 | AG27: 49.54032 | AH27: 0 | AI27: 4.365 | AJ27: 0 | AK27: 0 | AL27: 5.449 | AM27: 0 | AN27: 11.14665 | AO27: 0 | AP27: 0 | AQ27: 5.652 | AR27: 0 | AS27: 0 | AT27: 0 | AU27: 0 | AV27: 0 | AW27: 0 | AX27: 0 | AY27: 0 | AZ27: 0 | BA27: 0 | BB27: 0 | BC27: 0 | BD27: 0 | BE27: 0 | BF27: 0 | BG27: 0 | BH27: 0 | BI27: 0 | BJ27: 0 | BK27: 0 | BL27: 0 | BM27: 0 | BN27: 0 | BO27: 0 | BP27: 0 | BQ27: 0 | BR27: 0 | BS27: 0 | BT27: 0 | BU27: 0 | BV27: 0 | BW27: 0 | BX27: =5506.62/1000 -> 5.50662 | BY27: =3253.83/1000 -> 3.25383 | BZ27: 0 | CA27: =2500/1000 -> 2.5 | CB27: =5000/1000 -> 5 | CC27: 0 | CD27: =2000/1000 -> 2 | CE27: 0 | CF27: =(52949.96/1000)+(14000/1000) -> 66.94996 | CG27: =IF(AND(CG$13>=$C27,CG$13<=$E27),($H27-SUM($K27:CF27))/(($E27-CG$13+1)),0) -> 0 | CH27: =22286.47/1000 -> 22.28647 | CI27: =IF(AND(CI$13>=$C27,CI$13<=$E27),($H27-SUM($K27:CH27))/(($E27-CI$13+1)),0) -> 0 | CJ27: =IF(AND(CJ$13>=$C27,CJ$13<=$E27),($H27-SUM($K27:CI27))/(($E27-CJ$13+1)),0) -> 0 | CK27: =IF(AND(CK$13>=$C27,CK$13<=$E27),($H27-SUM($K27:CJ27))/(($E27-CK$13+1)),0) -> 0 | CL27: =IF(AND(CL$13>=$C27,CL$13<=$E27),($H27-SUM($K27:CK27))/(($E27-CL$13+1)),0) -> 0 | CM27: =IF(AND(CM$13>=$C27,CM$13<=$E27),($H27-SUM($K27:CL27))/(($E27-CM$13+1)),0) -> 0 | CN27: =IF(AND(CN$13>=$C27,CN$13<=$E27),($H27-SUM($K27:CM27))/(($E27-CN$13+1)),0) -> 0 | CO27: =IF(AND(CO$13>=$C27,CO$13<=$E27),($H27-SUM($K27:CN27))/(($E27-CO$13+1)),0) -> 0 | CP27: =IF(AND(CP$13>=$C27,CP$13<=$E27),($H27-SUM($K27:CO27))/(($E27-CP$13+1)),0) -> 0 | ... GT27: =IF(AND(GT$13>=$C27,GT$13<=$E27),($H27-SUM($K27:GS27))/(($E27-GT$13+1)),0) -> 0 | HF27: x | HG27: =HG26+1 -> 4
B28: 2023 Soft Costs | C28: 80 | E28: 83 | F28: =SUMIF($K$13:$GT$13,"<="&$C$13,'Monthly Cash Flow'!K28:GT28) -> 0 | G28: =Assumptions!L84 -> 25 | H28: =G28 -> 25 | I28: =SUMIF($K$13:$GT$13,"<="&Assumptions!$L$17,'Monthly Cash Flow'!K28:GT28) -> 25 | K28: 0 | L28: 0 | M28: 0 | N28: 0 | O28: 0 | P28: 0 | Q28: 0 | R28: 0 | S28: 0 | T28: 0 | U28: 0 | V28: 0 | W28: 0 | X28: 0 | Y28: 0 | Z28: 0 | AA28: 0 | AB28: 0 | AC28: 0 | AD28: 0 | AE28: 0 | AF28: 0 | AG28: 0 | AH28: 0 | AI28: 0 | AJ28: 0 | AK28: 0 | AL28: 0 | AM28: 0 | AN28: 0 | AO28: 0 | AP28: 0 | AQ28: 0 | AR28: 0 | AS28: 0 | AT28: 0 | AU28: 0 | AV28: 0 | AW28: 0 | AX28: 0 | AY28: 0 | AZ28: 0 | BA28: 0 | BB28: 0 | BC28: 0 | BD28: 0 | BE28: 0 | BF28: 0 | BG28: 0 | BH28: 0 | BI28: 0 | BJ28: 0 | BK28: 0 | BL28: =IF(AND(BL$13>=$C28,BL$13<=$E28),($H28-SUM($K28:BK28))/(($E28-BL$13+1)),0) -> 0 | BM28: =IF(AND(BM$13>=$C28,BM$13<=$E28),($H28-SUM($K28:BL28))/(($E28-BM$13+1)),0) -> 0 | BN28: =IF(AND(BN$13>=$C28,BN$13<=$E28),($H28-SUM($K28:BM28))/(($E28-BN$13+1)),0) -> 0 | BO28: =IF(AND(BO$13>=$C28,BO$13<=$E28),($H28-SUM($K28:BN28))/(($E28-BO$13+1)),0) -> 0 | BP28: =IF(AND(BP$13>=$C28,BP$13<=$E28),($H28-SUM($K28:BO28))/(($E28-BP$13+1)),0) -> 0 | BQ28: =IF(AND(BQ$13>=$C28,BQ$13<=$E28),($H28-SUM($K28:BP28))/(($E28-BQ$13+1)),0) -> 0 | BR28: =IF(AND(BR$13>=$C28,BR$13<=$E28),($H28-SUM($K28:BQ28))/(($E28-BR$13+1)),0) -> 0 | BS28: =IF(AND(BS$13>=$C28,BS$13<=$E28),($H28-SUM($K28:BR28))/(($E28-BS$13+1)),0) -> 0 | ... GT28: =IF(AND(GT$13>=$C28,GT$13<=$E28),($H28-SUM($K28:GS28))/(($E28-GT$13+1)),0) -> 0 | HF28: x | HG28: =HG27+1 -> 5
B29: =+Assumptions!B18 -> Soft Costs | G29: =SUM(G27:G28) -> 25 | H29: =SUM(H27:H28) -> 823.309 | I29: =SUMIF($K$13:$GT$13,"<="&Assumptions!$L$17,'Monthly Cash Flow'!K29:GT29) -> 823.309 | K29: =SUBTOTAL(9,K27:K28) -> 0 | L29: =SUBTOTAL(9,L27:L28) -> 0 | M29: =SUBTOTAL(9,M27:M28) -> 0 | N29: =SUBTOTAL(9,N27:N28) -> 0 | O29: =SUBTOTAL(9,O27:O28) -> 0 | P29: =SUBTOTAL(9,P27:P28) -> 0 | Q29: =SUBTOTAL(9,Q27:Q28) -> 0 | R29: =SUBTOTAL(9,R27:R28) -> 0 | ... GT29: =SUBTOTAL(9,GT27:GT28) -> 0 | HF29: x | HG29: =HG28+1 -> 6 | HH29: =+B29 -> Soft Costs | HL29: =SUM(HN29:HV29) -> 823.309 | HN29: =SUMIF($K$14:$GT$14,HN$14,$K29:$GT29) -> 0 | HO29: =SUMIF($K$14:$GT$14,HO$14,$K29:$GT29) -> 138.72733 | HP29: =SUMIF($K$14:$GT$14,HP$14,$K29:$GT29) -> 529.83714 | HQ29: =SUMIF($K$14:$GT$14,HQ$14,$K29:$GT29) -> 22.24765 | HR29: =SUMIF($K$14:$GT$14,HR$14,$K29:$GT29) -> 0 | HS29: =SUMIF($K$14:$GT$14,HS$14,$K29:$GT29) -> 0 | HT29: =SUMIF($K$14:$GT$14,HT$14,$K29:$GT29) -> 18.26045 | HU29: =SUMIF($K$14:$GT$14,HU$14,$K29:$GT29) -> 114.23643 | HV29: =SUMIF($K$14:$GT$14,HV$14,$K29:$GT29) -> 0
B30: =+Assumptions!B19 -> Contingency | C30: =Assumptions!$J15 -> 0 | E30: =Assumptions!$L15 -> 0 | F30: =SUMIF($K$13:$GT$13,"<="&$C$13,'Monthly Cash Flow'!K30:GT30) -> 0 | H30: 0 | I30: =SUMIF($K$13:$GT$13,"<="&Assumptions!$L$17,'Monthly Cash Flow'!K30:GT30) -> 0 | K30: =IF(AND(K$13>=$C$30,K$13<$E$30),$H$30/($E$30-$C$30),0) -> 0 | L30: =IF(AND(L$13>=$C$30,L$13<$E$30),$H$30/($E$30-$C$30),0) -> 0 | M30: =IF(AND(M$13>=$C$30,M$13<$E$30),$H$30/($E$30-$C$30),0) -> 0 | N30: =IF(AND(N$13>=$C$30,N$13<$E$30),$H$30/($E$30-$C$30),0) -> 0 | O30: =IF(AND(O$13>=$C$30,O$13<$E$30),$H$30/($E$30-$C$30),0) -> 0 | P30: =IF(AND(P$13>=$C$30,P$13<$E$30),$H$30/($E$30-$C$30),0) -> 0 | Q30: =IF(AND(Q$13>=$C$30,Q$13<$E$30),$H$30/($E$30-$C$30),0) -> 0 | R30: =IF(AND(R$13>=$C$30,R$13<$E$30),$H$30/($E$30-$C$30),0) -> 0 | ... GT30: =IF(AND(GT$13>=$C$30,GT$13<$E$30),$H$30/($E$30-$C$30),0) -> 0 | HF30: x | HG30: =HG29+1 -> 7 | HH30: =+B30 -> Contingency | HL30: =SUM(HN30:HV30) -> 0 | HN30: =SUMIF($K$14:$GT$14,HN$14,$K30:$GT30) -> 0 | HO30: =SUMIF($K$14:$GT$14,HO$14,$K30:$GT30) -> 0 | HP30: =SUMIF($K$14:$GT$14,HP$14,$K30:$GT30) -> 0 | HQ30: =SUMIF($K$14:$GT$14,HQ$14,$K30:$GT30) -> 0 | HR30: =SUMIF($K$14:$GT$14,HR$14,$K30:$GT30) -> 0 | HS30: =SUMIF($K$14:$GT$14,HS$14,$K30:$GT30) -> 0 | HT30: =SUMIF($K$14:$GT$14,HT$14,$K30:$GT30) -> 0 | HU30: =SUMIF($K$14:$GT$14,HU$14,$K30:$GT30) -> 0 | HV30: =SUMIF($K$14:$GT$14,HV$14,$K30:$GT30) -> 0
HF31: x | HG31: =HG30+1 -> 8
B32: Leasing Costs | HF32: x | HG32: =HG31+1 -> 9 | HH32: =B32 -> Leasing Costs
A33: TI | B33: Tenant Improvements | I33: =SUMIF($K$13:$GT$13,"<="&Assumptions!$L$17,'Monthly Cash Flow'!K33:GT33) -> 2716.711 | K33: 0 | L33: 0 | M33: 0 | N33: 0 | O33: 0 | P33: 0 | Q33: 0 | R33: 0 | S33: 0 | T33: 0 | U33: 0 | V33: 0 | W33: 41.12 | X33: 0 | Y33: 0 | Z33: 0 | AA33: 0 | AB33: 0 | AC33: 0 | AD33: 0 | AE33: 0 | AF33: 0 | AG33: 73.629 | AH33: 0 | AI33: 0 | AJ33: 0 | AK33: 0 | AL33: 170.175 | AM33: 0 | AN33: 0 | AO33: 0 | AP33: 93.04 | AQ33: 0 | AR33: 0 | AS33: 0 | AT33: 0 | AU33: 0 | AV33: 0 | AW33: 205.825 | AX33: 0 | AY33: 0 | AZ33: 54.72 | BA33: 88.185 | BB33: 0 | BC33: 0 | BD33: 0 | BE33: 0 | BF33: 0 | BG33: 0 | BH33: 0 | BI33: 0 | BJ33: 0 | BK33: 0 | BL33: =IFERROR(OFFSET(ARGUS!$A$3, MATCH($A33, ARGUS!$A$3:$A$176, 0)-1,MATCH(EOMONTH(BL$15,1), ARGUS!$B$4:$LG$4, 0)-1,1,1)/1000, 0) -> 0 | BM33: =IFERROR(OFFSET(ARGUS!$A$3, MATCH($A33, ARGUS!$A$3:$A$176, 0)-1,MATCH(EOMONTH(BM$15,1), ARGUS!$B$4:$LG$4, 0)-1,1,1)/1000, 0) -> 0 | BN33: =IFERROR(OFFSET(ARGUS!$A$3, MATCH($A33, ARGUS!$A$3:$A$176, 0)-1,MATCH(EOMONTH(BN$15,1), ARGUS!$B$4:$LG$4, 0)-1,1,1)/1000, 0) -> 0 | BO33: =IFERROR(OFFSET(ARGUS!$A$3, MATCH($A33, ARGUS!$A$3:$A$176, 0)-1,MATCH(EOMONTH(BO$15,1), ARGUS!$B$4:$LG$4, 0)-1,1,1)/1000, 0) -> 0 | BP33: =IFERROR(OFFSET(ARGUS!$A$3, MATCH($A33, ARGUS!$A$3:$A$176, 0)-1,MATCH(EOMONTH(BP$15,1), ARGUS!$B$4:$LG$4, 0)-1,1,1)/1000, 0) -> 0 | BQ33: =IFERROR(OFFSET(ARGUS!$A$3, MATCH($A33, ARGUS!$A$3:$A$176, 0)-1,MATCH(EOMONTH(BQ$15,1), ARGUS!$B$4:$LG$4, 0)-1,1,1)/1000, 0) -> 0 | BR33: =IFERROR(OFFSET(ARGUS!$A$3, MATCH($A33, ARGUS!$A$3:$A$176, 0)-1,MATCH(EOMONTH(BR$15,1), ARGUS!$B$4:$LG$4, 0)-1,1,1)/1000, 0) -> 0 | BS33: =IFERROR(OFFSET(ARGUS!$A$3, MATCH($A33, ARGUS!$A$3:$A$176, 0)-1,MATCH(EOMONTH(BS$15,1), ARGUS!$B$4:$LG$4, 0)-1,1,1)/1000, 0) -> 0 | ... BZ33: =IFERROR(OFFSET(ARGUS!$A$3, MATCH($A33, ARGUS!$A$3:$A$176, 0)-1,MATCH(EOMONTH(BZ$15,1), ARGUS!$B$4:$LG$4, 0)-1,1,1)/1000, 0) -> 0 | CA33: =96915/1000 -> 96.915 | CB33: =IFERROR(OFFSET(ARGUS!$A$3, MATCH($A33, ARGUS!$A$3:$A$176, 0)-1,MATCH(EOMONTH(CB$15,1), ARGUS!$B$4:$LG$4, 0)-1,1,1)/1000, 0) -> 0 | CC33: =IFERROR(OFFSET(ARGUS!$A$3, MATCH($A33, ARGUS!$A$3:$A$176, 0)-1,MATCH(EOMONTH(CC$15,1), ARGUS!$B$4:$LG$4, 0)-1,1,1)/1000, 0) -> 0 | CD33: =102360/1000 -> 102.36 | CE33: =IFERROR(OFFSET(ARGUS!$A$3, MATCH($A33, ARGUS!$A$3:$A$176, 0)-1,MATCH(EOMONTH(CE$15,1), ARGUS!$B$4:$LG$4, 0)-1,1,1)/1000, 0) -> 0 | CF33: =IFERROR(OFFSET(ARGUS!$A$3, MATCH($A33, ARGUS!$A$3:$A$176, 0)-1,MATCH(EOMONTH(CF$15,1), ARGUS!$B$4:$LG$4, 0)-1,1,1)/1000, 0) -> 0 | CG33: =IFERROR(OFFSET(ARGUS!$A$3, MATCH($A33, ARGUS!$A$3:$A$176, 0)-1,MATCH(EOMONTH(CG$15,1), ARGUS!$B$4:$LG$4, 0)-1,1,1)/1000, 0) -> 0 | CH33: =IFERROR(OFFSET(ARGUS!$A$3, MATCH($A33, ARGUS!$A$3:$A$176, 0)-1,MATCH(EOMONTH(CH$15,1), ARGUS!$B$4:$LG$4, 0)-1,1,1)/1000, 0) -> 0 | CI33: =IFERROR(OFFSET(ARGUS!$A$3, MATCH($A33, ARGUS!$A$3:$A$176, 0)-1,MATCH(EOMONTH(CI$15,1), ARGUS!$B$4:$LG$4, 0)-1,1,1)/1000, 0) -> 0 | CJ33: =IFERROR(OFFSET(ARGUS!$A$3, MATCH($A33, ARGUS!$A$3:$A$176, 0)-1,MATCH(EOMONTH(CJ$15,1), ARGUS!$B$4:$LG$4, 0)-1,1,1)/1000, 0) -> 0 | CK33: =IFERROR(OFFSET(ARGUS!$A$3, MATCH($A33, ARGUS!$A$3:$A$176, 0)-1,MATCH(EOMONTH(CK$15,1), ARGUS!$B$4:$LG$4, 0)-1,1,1)/1000, 0) -> 0 | CL33: =IFERROR(OFFSET(ARGUS!$A$3, MATCH($A33, ARGUS!$A$3:$A$176, 0)-1,MATCH(EOMONTH(CL$15,1), ARGUS!$B$4:$LG$4, 0)-1,1,1)/1000, 0) -> 0 | ... GT33: =IFERROR(OFFSET(ARGUS!$A$3, MATCH($A33, ARGUS!$A$3:$A$176, 0)-1,MATCH(EOMONTH(GT$15,1), ARGUS!$B$4:$LG$4, 0)-1,1,1)/1000, 0) -> 0 | HF33: x | HG33: =HG32+1 -> 10 | HH33: =B33 -> Tenant Improvements | HL33: =SUM(HN33:HV33) -> 2716.711 | HN33: =SUMIF($K$14:$GT$14,HN$14,$K33:$GT33) -> 0 | HO33: =SUMIF($K$14:$GT$14,HO$14,$K33:$GT33) -> 41.12 | HP33: =SUMIF($K$14:$GT$14,HP$14,$K33:$GT33) -> 73.629 | HQ33: =SUMIF($K$14:$GT$14,HQ$14,$K33:$GT33) -> 263.215 | HR33: =SUMIF($K$14:$GT$14,HR$14,$K33:$GT33) -> 348.73 | HS33: =SUMIF($K$14:$GT$14,HS$14,$K33:$GT33) -> 0 | HT33: =SUMIF($K$14:$GT$14,HT$14,$K33:$GT33) -> 199.275 | HU33: =SUMIF($K$14:$GT$14,HU$14,$K33:$GT33) -> 65.7 | HV33: =SUMIF($K$14:$GT$14,HV$14,$K33:$GT33) -> 1725.042
B34: Total TI Allowance | I34: =SUMIF($K$13:$GT$13,"<="&Assumptions!$L$17,'Monthly Cash Flow'!K34:GT34) -> 2716.711 | K34: =SUBTOTAL(9,K33:K33) -> 0 | L34: =IF(L$13<=Assumptions!$L$17,SUBTOTAL(9,L33:L33),0) -> 0 | M34: =IF(M$13<=Assumptions!$L$17,SUBTOTAL(9,M33:M33),0) -> 0 | N34: =IF(N$13<=Assumptions!$L$17,SUBTOTAL(9,N33:N33),0) -> 0 | O34: =IF(O$13<=Assumptions!$L$17,SUBTOTAL(9,O33:O33),0) -> 0 | P34: =IF(P$13<=Assumptions!$L$17,SUBTOTAL(9,P33:P33),0) -> 0 | Q34: =IF(Q$13<=Assumptions!$L$17,SUBTOTAL(9,Q33:Q33),0) -> 0 | R34: =IF(R$13<=Assumptions!$L$17,SUBTOTAL(9,R33:R33),0) -> 0 | S34: =IF(S$13<=Assumptions!$L$17,SUBTOTAL(9,S33:S33),0) -> 0 | ... GT34: =IF(GT$13<=Assumptions!$L$17,SUBTOTAL(9,GT33:GT33),0) -> 0 | HF34: x | HG34: =#REF!+1 -> #REF! | HH34: =B34 -> Total TI Allowance | HL34: =SUM(HN34:HV34) -> 2716.711 | HN34: =SUMIF($K$14:$GT$14,HN$14,$K34:$GT34) -> 0 | HO34: =SUMIF($K$14:$GT$14,HO$14,$K34:$GT34) -> 41.12 | HP34: =SUMIF($K$14:$GT$14,HP$14,$K34:$GT34) -> 73.629 | HQ34: =SUMIF($K$14:$GT$14,HQ$14,$K34:$GT34) -> 263.215 | HR34: =SUMIF($K$14:$GT$14,HR$14,$K34:$GT34) -> 348.73 | HS34: =SUMIF($K$14:$GT$14,HS$14,$K34:$GT34) -> 0 | HT34: =SUMIF($K$14:$GT$14,HT$14,$K34:$GT34) -> 199.275 | HU34: =SUMIF($K$14:$GT$14,HU$14,$K34:$GT34) -> 65.7 | HV34: =SUMIF($K$14:$GT$14,HV$14,$K34:$GT34) -> 1725.042
A36: LC | B36: Leasing Commissions | I36: =SUMIF($K$13:$GT$13,"<="&Assumptions!$L$17,'Monthly Cash Flow'!K36:GT36) -> 976.22775 | K36: 0 | L36: 0 | M36: 0 | N36: 0 | O36: 0 | P36: 0 | Q36: 0 | R36: 0 | S36: 0 | T36: 0 | U36: 10.16091 | V36: 0 | W36: 19.70859 | X36: 3.60214 | Y36: 0 | Z36: 3.20147 | AA36: 0 | AB36: 9.54768 | AC36: 0 | AD36: 2.28e-15 | AE36: 0 | AF36: 60.946202 | AG36: 0 | AH36: 0 | AI36: 78.12588 | AJ36: 0 | AK36: 0 | AL36: 41.66988 | AM36: 0 | AN36: 4.167 | AO36: 0 | AP36: 65.716534 | AQ36: 32.40115 | AR36: 0 | AS36: 0 | AT36: 0 | AU36: 0 | AV36: 0 | AW36: 51.2 | AX36: 0 | AY36: -19 | AZ36: 74.10646 | BA36: 61.246 | BB36: 0 | BC36: 0 | BD36: 0 | BE36: 0 | BF36: 0 | BG36: 0 | BH36: 0 | BI36: 0 | BJ36: 0 | BK36: 0 | BL36: =IFERROR(OFFSET(ARGUS!$A$3, MATCH($A36, ARGUS!$A$3:$A$176, 0)-1,MATCH(EOMONTH(BL$15,1), ARGUS!$B$4:$LG$4, 0)-1,1,1)/1000, 0) -> 0 | BM36: =IFERROR(OFFSET(ARGUS!$A$3, MATCH($A36, ARGUS!$A$3:$A$176, 0)-1,MATCH(EOMONTH(BM$15,1), ARGUS!$B$4:$LG$4, 0)-1,1,1)/1000, 0) -> 0 | BN36: 0 | BO36: 0 | BP36: 0 | BQ36: 0 | BR36: 0 | BS36: 0 | BT36: 0 | BU36: 0 | BV36: 0 | BW36: =9345.19/1000 -> 9.34519 | BX36: =21707.66/1000 -> 21.70766 | BY36: =IFERROR(OFFSET(ARGUS!$A$3, MATCH($A36, ARGUS!$A$3:$A$176, 0)-1,MATCH(EOMONTH(BY$15,1), ARGUS!$B$4:$LG$4, 0)-1,1,1)/1000, 0) -> 0 | BZ36: =IFERROR(OFFSET(ARGUS!$A$3, MATCH($A36, ARGUS!$A$3:$A$176, 0)-1,MATCH(EOMONTH(BZ$15,1), ARGUS!$B$4:$LG$4, 0)-1,1,1)/1000, 0) -> 0 | CA36: =IFERROR(OFFSET(ARGUS!$A$3, MATCH($A36, ARGUS!$A$3:$A$176, 0)-1,MATCH(EOMONTH(CA$15,1), ARGUS!$B$4:$LG$4, 0)-1,1,1)/1000, 0) -> 0 | CB36: =IFERROR(OFFSET(ARGUS!$A$3, MATCH($A36, ARGUS!$A$3:$A$176, 0)-1,MATCH(EOMONTH(CB$15,1), ARGUS!$B$4:$LG$4, 0)-1,1,1)/1000, 0) -> 0 | CC36: =IFERROR(OFFSET(ARGUS!$A$3, MATCH($A36, ARGUS!$A$3:$A$176, 0)-1,MATCH(EOMONTH(CC$15,1), ARGUS!$B$4:$LG$4, 0)-1,1,1)/1000, 0) -> 0 | CD36: =IFERROR(OFFSET(ARGUS!$A$3, MATCH($A36, ARGUS!$A$3:$A$176, 0)-1,MATCH(EOMONTH(CD$15,1), ARGUS!$B$4:$LG$4, 0)-1,1,1)/1000, 0) -> 0 | CE36: =IFERROR(OFFSET(ARGUS!$A$3, MATCH($A36, ARGUS!$A$3:$A$176, 0)-1,MATCH(EOMONTH(CE$15,1), ARGUS!$B$4:$LG$4, 0)-1,1,1)/1000, 0) -> 0 | CF36: =IFERROR(OFFSET(ARGUS!$A$3, MATCH($A36, ARGUS!$A$3:$A$176, 0)-1,MATCH(EOMONTH(CF$15,1), ARGUS!$B$4:$LG$4, 0)-1,1,1)/1000, 0) -> 0 | ... GT36: =IFERROR(OFFSET(ARGUS!$A$3, MATCH($A36, ARGUS!$A$3:$A$176, 0)-1,MATCH(EOMONTH(GT$15,1), ARGUS!$B$4:$LG$4, 0)-1,1,1)/1000, 0) -> 0 | HF36: x | HG36: =HG34+1 -> #REF! | HH36: =B36 -> Leasing Commissions | HL36: =SUM(HN36:HV36) -> 976.22775 | HN36: =SUMIF($K$14:$GT$14,HN$14,$K36:$GT36) -> 0 | HO36: =SUMIF($K$14:$GT$14,HO$14,$K36:$GT36) -> 29.8695 | HP36: =SUMIF($K$14:$GT$14,HP$14,$K36:$GT36) -> 155.42337 | HQ36: =SUMIF($K$14:$GT$14,HQ$14,$K36:$GT36) -> 143.95456 | HR36: =SUMIF($K$14:$GT$14,HR$14,$K36:$GT36) -> 167.55246 | HS36: =SUMIF($K$14:$GT$14,HS$14,$K36:$GT36) -> 0 | HT36: =SUMIF($K$14:$GT$14,HT$14,$K36:$GT36) -> 31.05285 | HU36: =SUMIF($K$14:$GT$14,HU$14,$K36:$GT36) -> 27.209 | HV36: =SUMIF($K$14:$GT$14,HV$14,$K36:$GT36) -> 421.166
B37: Total Leasing Commissions | I37: =SUMIF($K$13:$GT$13,"<="&Assumptions!$L$17,'Monthly Cash Flow'!K37:GT37) -> 976.22775 | K37: =SUBTOTAL(9,K36:K36) -> 0 | L37: =IF(L$13<=Assumptions!$L$17,SUBTOTAL(9,L36:L36),0) -> 0 | M37: =IF(M$13<=Assumptions!$L$17,SUBTOTAL(9,M36:M36),0) -> 0 | N37: =IF(N$13<=Assumptions!$L$17,SUBTOTAL(9,N36:N36),0) -> 0 | O37: =IF(O$13<=Assumptions!$L$17,SUBTOTAL(9,O36:O36),0) -> 0 | P37: =IF(P$13<=Assumptions!$L$17,SUBTOTAL(9,P36:P36),0) -> 0 | Q37: =IF(Q$13<=Assumptions!$L$17,SUBTOTAL(9,Q36:Q36),0) -> 0 | R37: =IF(R$13<=Assumptions!$L$17,SUBTOTAL(9,R36:R36),0) -> 0 | S37: =IF(S$13<=Assumptions!$L$17,SUBTOTAL(9,S36:S36),0) -> 0 | ... GT37: =IF(GT$13<=Assumptions!$L$17,SUBTOTAL(9,GT36:GT36),0) -> 0 | HF37: x | HG37: =#REF!+1 -> #REF! | HH37: =B37 -> Total Leasing Commissions | HL37: =SUM(HN37:HV37) -> 976.22775 | HN37: =SUMIF($K$14:$GT$14,HN$14,$K37:$GT37) -> 0 | HO37: =SUMIF($K$14:$GT$14,HO$14,$K37:$GT37) -> 29.8695 | HP37: =SUMIF($K$14:$GT$14,HP$14,$K37:$GT37) -> 155.42337 | HQ37: =SUMIF($K$14:$GT$14,HQ$14,$K37:$GT37) -> 143.95456 | HR37: =SUMIF($K$14:$GT$14,HR$14,$K37:$GT37) -> 167.55246 | HS37: =SUMIF($K$14:$GT$14,HS$14,$K37:$GT37) -> 0 | HT37: =SUMIF($K$14:$GT$14,HT$14,$K37:$GT37) -> 31.05285 | HU37: =SUMIF($K$14:$GT$14,HU$14,$K37:$GT37) -> 27.209 | HV37: =SUMIF($K$14:$GT$14,HV$14,$K37:$GT37) -> 421.166
HF38: x | HG38: =HG37+1 -> #REF!
A39: 14 | B39: Capital Reserves | I39: =SUMIF($K$13:$GT$13,"<="&Assumptions!$L$17,'Monthly Cash Flow'!K39:GT39) -> 0 | K39: 0 | L39: =IFERROR(OFFSET(ARGUS!$B$3, MATCH($A39, ARGUS!$A$3:$A$176, 0)-1,MATCH(L$15, ARGUS!$B$4:$LG$4, 0)-1,1,1)/1000, 0) -> 0 | M39: =IFERROR(OFFSET(ARGUS!$B$3, MATCH($A39, ARGUS!$A$3:$A$176, 0)-1,MATCH(M$15, ARGUS!$B$4:$LG$4, 0)-1,1,1)/1000, 0) -> 0 | N39: =IFERROR(OFFSET(ARGUS!$A$3, MATCH($A39, ARGUS!$A$3:$A$176, 0)-1,MATCH(EOMONTH(N$15,1), ARGUS!$B$4:$LG$4, 0)-1,1,1)/1000, 0) -> 0 | O39: =IFERROR(OFFSET(ARGUS!$A$3, MATCH($A39, ARGUS!$A$3:$A$176, 0)-1,MATCH(EOMONTH(O$15,1), ARGUS!$B$4:$LG$4, 0)-1,1,1)/1000, 0) -> 0 | P39: =IFERROR(OFFSET(ARGUS!$A$3, MATCH($A39, ARGUS!$A$3:$A$176, 0)-1,MATCH(EOMONTH(P$15,1), ARGUS!$B$4:$LG$4, 0)-1,1,1)/1000, 0) -> 0 | Q39: =IFERROR(OFFSET(ARGUS!$A$3, MATCH($A39, ARGUS!$A$3:$A$176, 0)-1,MATCH(EOMONTH(Q$15,1), ARGUS!$B$4:$LG$4, 0)-1,1,1)/1000, 0) -> 0 | R39: =IFERROR(OFFSET(ARGUS!$A$3, MATCH($A39, ARGUS!$A$3:$A$176, 0)-1,MATCH(EOMONTH(R$15,1), ARGUS!$B$4:$LG$4, 0)-1,1,1)/1000, 0) -> 0 | S39: =IFERROR(OFFSET(ARGUS!$A$3, MATCH($A39, ARGUS!$A$3:$A$176, 0)-1,MATCH(EOMONTH(S$15,1), ARGUS!$B$4:$LG$4, 0)-1,1,1)/1000, 0) -> 0 | T39: =IFERROR(OFFSET(ARGUS!$A$3, MATCH($A39, ARGUS!$A$3:$A$176, 0)-1,MATCH(EOMONTH(T$15,1), ARGUS!$B$4:$LG$4, 0)-1,1,1)/1000, 0) -> 0 | U39: =IFERROR(OFFSET(ARGUS!$A$3, MATCH($A39, ARGUS!$A$3:$A$176, 0)-1,MATCH(EOMONTH(U$15,1), ARGUS!$B$4:$LG$4, 0)-1,1,1)/1000, 0) -> 0 | ... GT39: =IFERROR(OFFSET(ARGUS!$A$3, MATCH($A39, ARGUS!$A$3:$A$176, 0)-1,MATCH(EOMONTH(GT$15,1), ARGUS!$B$4:$LG$4, 0)-1,1,1)/1000, 0) -> 0 | HF39: x | HG39: =HG38+1 -> #REF! | HH39: =+B39 -> Capital Reserves | HL39: =SUM(HN39:HV39) -> 0 | HN39: =SUMIF($K$14:$GT$14,HN$14,$K39:$GT39) -> 0 | HO39: =SUMIF($K$14:$GT$14,HO$14,$K39:$GT39) -> 0 | HP39: =SUMIF($K$14:$GT$14,HP$14,$K39:$GT39) -> 0 | HQ39: =SUMIF($K$14:$GT$14,HQ$14,$K39:$GT39) -> 0 | HR39: =SUMIF($K$14:$GT$14,HR$14,$K39:$GT39) -> 0 | HS39: =SUMIF($K$14:$GT$14,HS$14,$K39:$GT39) -> 0 | HT39: =SUMIF($K$14:$GT$14,HT$14,$K39:$GT39) -> 0 | HU39: =SUMIF($K$14:$GT$14,HU$14,$K39:$GT39) -> 0 | HV39: =SUMIF($K$14:$GT$14,HV$14,$K39:$GT39) -> 0
HF40: x | HG40: =HG39+1 -> #REF!
B41: Total Unlevered Costs | I41: =SUMIF($K$13:$GT$13,"<="&Assumptions!$L$17,'Monthly Cash Flow'!K41:GT41) -> 37036.572 | K41: =SUBTOTAL(9,K18:K39) -> 30206 | L41: =IF(L13<=Assumptions!$L$17,SUBTOTAL(9,L18:L39),0) -> 0 | M41: =IF(M13<=Assumptions!$L$17,SUBTOTAL(9,M18:M39),0) -> 0 | N41: =IF(N13<=Assumptions!$L$17,SUBTOTAL(9,N18:N39),0) -> 0 | O41: =IF(O13<=Assumptions!$L$17,SUBTOTAL(9,O18:O39),0) -> 0 | P41: =IF(P13<=Assumptions!$L$17,SUBTOTAL(9,P18:P39),0) -> 0 | Q41: =IF(Q13<=Assumptions!$L$17,SUBTOTAL(9,Q18:Q39),0) -> 0 | R41: =IF(R13<=Assumptions!$L$17,SUBTOTAL(9,R18:R39),0) -> 0 | S41: =IF(S13<=Assumptions!$L$17,SUBTOTAL(9,S18:S39),0) -> 0 | ... GT41: =IF(GT13<=Assumptions!$L$17,SUBTOTAL(9,GT18:GT39),0) -> 0 | HF41: x | HG41: =HG40+1 -> #REF! | HH41: =B41 -> Total Unlevered Costs | HL41: =SUM(HN41:HV41) -> 37036.572 | HN41: =SUMIF($K$14:$GT$14,HN$14,$K41:$GT41) -> 30206 | HO41: =SUMIF($K$14:$GT$14,HO$14,$K41:$GT41) -> 293.74533 | HP41: =SUMIF($K$14:$GT$14,HP$14,$K41:$GT41) -> 1970.3778 | HQ41: =SUMIF($K$14:$GT$14,HQ$14,$K41:$GT41) -> 452.06821 | HR41: =SUMIF($K$14:$GT$14,HR$14,$K41:$GT41) -> 697.14046 | HS41: =SUMIF($K$14:$GT$14,HS$14,$K41:$GT41) -> 65.924 | HT41: =SUMIF($K$14:$GT$14,HT$14,$K41:$GT41) -> 507.9623 | HU41: =SUMIF($K$14:$GT$14,HU$14,$K41:$GT41) -> 517.46289 | HV41: =SUMIF($K$14:$GT$14,HV$14,$K41:$GT41) -> 2325.8905
HF42: x | HG42: =HG41+1 -> #REF!
HF43: x | HG43: =HG42+1 -> #REF!
B44: Office SF Absorbed | G44: TI Buildout Period | I44: =SUMIF($K$13:$GT$13,"<="&Assumptions!$L$17,'Monthly Cash Flow'!K44:GT44) -> 0 | K44: =IF(K$13>$F46,OFFSET(K$46,0,-$F44),0) -> 0 | L44: =+L45-K45 -> 0 | M44: =+M45-L45 -> 0 | N44: =+N45-M45 -> 0 | O44: =+O45-N45 -> 0 | P44: =+P45-O45 -> 0 | Q44: =+Q45-P45 -> 0 | R44: =+R45-Q45 -> 0 | S44: =+S45-R45 -> 0 | ... GT44: =+GT45-GS45 -> 0 | HF44: x | HG44: =HG43+1 -> #REF! | HH44: =B44 -> Office SF Absorbed | HL44: =SUM(HN44:HV44) -> 0 | HN44: =SUMIF($K$14:$GT$14,HN$14,$K44:$GT44) -> 0 | HO44: =SUMIF($K$14:$GT$14,HO$14,$K44:$GT44) -> 0 | HP44: =SUMIF($K$14:$GT$14,HP$14,$K44:$GT44) -> 0 | HQ44: =SUMIF($K$14:$GT$14,HQ$14,$K44:$GT44) -> 0 | HR44: =SUMIF($K$14:$GT$14,HR$14,$K44:$GT44) -> 0 | HS44: =SUMIF($K$14:$GT$14,HS$14,$K44:$GT44) -> 0 | HT44: =SUMIF($K$14:$GT$14,HT$14,$K44:$GT44) -> 0 | HU44: =SUMIF($K$14:$GT$14,HU$14,$K44:$GT44) -> 0 | HV44: =SUMIF($K$14:$GT$14,HV$14,$K44:$GT44) -> 0
B45: Total Leased SF @ New Rate | I45: =SUM(I43:I44) -> 0 | K45: =SUBTOTAL(9,K43:K44) -> 0 | L45: =IFERROR(OFFSET(#REF!, MATCH(" Total Area",#REF!, 0)-1, MATCH(L15,#REF!, 0)-1), 0) -> 0 | M45: =IFERROR(OFFSET(#REF!, MATCH(" Total Area",#REF!, 0)-1, MATCH(M15,#REF!, 0)-1), 0) -> 0 | N45: =IFERROR(OFFSET(#REF!, MATCH(" Total Area",#REF!, 0)-1, MATCH(N15,#REF!, 0)-1), 0) -> 0 | O45: =IFERROR(OFFSET(#REF!, MATCH(" Total Area",#REF!, 0)-1, MATCH(O15,#REF!, 0)-1), 0) -> 0 | P45: =IFERROR(OFFSET(#REF!, MATCH(" Total Area",#REF!, 0)-1, MATCH(P15,#REF!, 0)-1), 0) -> 0 | Q45: =IFERROR(OFFSET(#REF!, MATCH(" Total Area",#REF!, 0)-1, MATCH(Q15,#REF!, 0)-1), 0) -> 0 | R45: =IFERROR(OFFSET(#REF!, MATCH(" Total Area",#REF!, 0)-1, MATCH(R15,#REF!, 0)-1), 0) -> 0 | S45: =IFERROR(OFFSET(#REF!, MATCH(" Total Area",#REF!, 0)-1, MATCH(S15,#REF!, 0)-1), 0) -> 0 | ... GT45: =IFERROR(OFFSET(#REF!, MATCH(" Total Area",#REF!, 0)-1, MATCH(GT15,#REF!, 0)-1), 0) -> 0 | HF45: x | HG45: =HG44+1 -> #REF! | HH45: =B45 -> Total Leased SF @ New Rate | HL45: =SUM(HL43:HL44) -> 0 | HN45: =SUMIF($K$14:$GT$14,HN$14,$K45:$GT45) -> 0 | HO45: =SUM(HO43:HO44) -> 0 | HP45: =SUM(HP43:HP44) -> 0 | HQ45: =SUM(HQ43:HQ44) -> 0 | HR45: =SUM(HR43:HR44) -> 0 | HS45: =SUM(HS43:HS44) -> 0 | HT45: =SUM(HT43:HT44) -> 0 | HU45: =SUM(HU43:HU44) -> 0 | HV45: =SUM(HV43:HV44) -> 0
B46: Office SF Leased | I46: =SUMIF($K$13:$GT$13,"<="&Assumptions!$L$17,'Monthly Cash Flow'!K46:GT46) -> 0 | L46: =+L44 -> 0 | M46: =+M44 -> 0 | N46: =+N44 -> 0 | O46: =+O44 -> 0 | P46: =+P44 -> 0 | Q46: =+Q44 -> 0 | R46: =+R44 -> 0 | S46: =+S44 -> 0 | ... GT46: =+GT44 -> 0 | HF46: x | HG46: =HG45+1 -> #REF! | HH46: =B46 -> Office SF Leased | HL46: =SUM(HN46:HV46) -> 0 | HN46: =SUMIF($K$14:$GT$14,HN$14,$K46:$GT46) -> 0 | HO46: =SUMIF($K$14:$GT$14,HO$14,$K46:$GT46) -> 0 | HP46: =SUMIF($K$14:$GT$14,HP$14,$K46:$GT46) -> 0 | HQ46: =SUMIF($K$14:$GT$14,HQ$14,$K46:$GT46) -> 0 | HR46: =SUMIF($K$14:$GT$14,HR$14,$K46:$GT46) -> 0 | HS46: =SUMIF($K$14:$GT$14,HS$14,$K46:$GT46) -> 0 | HT46: =SUMIF($K$14:$GT$14,HT$14,$K46:$GT46) -> 0 | HU46: =SUMIF($K$14:$GT$14,HU$14,$K46:$GT46) -> 0 | HV46: =SUMIF($K$14:$GT$14,HV$14,$K46:$GT46) -> 0
HF47: x | HG47: =HG46+1 -> #REF!
B48: Total Office Occupancy (Old & New) | K48: =K45 -> 0 | L48: =L45 -> 0 | M48: =M45 -> 0 | N48: =N45 -> 0 | O48: =O45 -> 0 | P48: =P45 -> 0 | Q48: =Q45 -> 0 | R48: =R45 -> 0 | ... GT48: =GT45 -> 0 | HF48: x | HG48: =HG47+1 -> #REF!
B49: Proforma Occupancy % | K49: =K48/Assumptions!$F$7 -> 0 | L49: =(L55+L61)/L54+1 -> 1 | M49: =(M55+M61)/M54+1 -> 1 | N49: =(N55+N61)/N54+1 -> 1 | O49: =(O55+O61)/O54+1 -> 1 | P49: =(P55+P61)/P54+1 -> 1 | Q49: =(Q55+Q61)/Q54+1 -> 1 | R49: =(R55+R61)/R54+1 -> 1 | S49: =(S55+S61)/S54+1 -> 1 | ... GT49: =(GT55+GT61)/GT54+1 -> 0.94992708 | HF49: x | HG49: =HG48+1 -> #REF!
HF50: x | HG50: =HG49+1 -> #REF!
B51: New Project Revenues | HF51: x | HG51: =HG50+1 -> #REF! | HH51: =B51 -> New Project Revenues
HF52: x | HG52: =HG51+1 -> #REF!
B53: Retail | HF53: x | HG53: =HG52+1 -> #REF! | HH53: =B53 -> Retail
A54: 1 | B54: Potential Base Rent | I54: =SUMIF($K$13:$GT$13,"<="&Assumptions!$L$17,'Monthly Cash Flow'!K54:GT54) -> 15821.277 | L54: =Historicals!D3 -> 111.19469 | M54: =Historicals!E3 -> 112.08559 | N54: =Historicals!F3 -> 116.37649 | O54: =Historicals!G3 -> 111.89584 | P54: =Historicals!H3 -> 111.72 | Q54: =Historicals!I3 -> 109.71383 | R54: =Historicals!J3 -> 107.67871 | S54: =Historicals!K3 -> 102.30149 | ... CH54: =Historicals!BZ3 -> 160.54263 | CI54: =IFERROR(OFFSET(ARGUS!$A$3, MATCH($A54, ARGUS!$A$3:$A$176, 0)-1,MATCH(EOMONTH(CI$15,1), ARGUS!$B$4:$LG$4, 0)-1,1,1)/1000, 0) -> 191.442 | CJ54: =IFERROR(OFFSET(ARGUS!$A$3, MATCH($A54, ARGUS!$A$3:$A$176, 0)-1,MATCH(EOMONTH(CJ$15,1), ARGUS!$B$4:$LG$4, 0)-1,1,1)/1000, 0) -> 192.47 | CK54: =IFERROR(OFFSET(ARGUS!$A$3, MATCH($A54, ARGUS!$A$3:$A$176, 0)-1,MATCH(EOMONTH(CK$15,1), ARGUS!$B$4:$LG$4, 0)-1,1,1)/1000, 0) -> 192.47 | CL54: =IFERROR(OFFSET(ARGUS!$A$3, MATCH($A54, ARGUS!$A$3:$A$176, 0)-1,MATCH(EOMONTH(CL$15,1), ARGUS!$B$4:$LG$4, 0)-1,1,1)/1000, 0) -> 193.017 | CM54: =IFERROR(OFFSET(ARGUS!$A$3, MATCH($A54, ARGUS!$A$3:$A$176, 0)-1,MATCH(EOMONTH(CM$15,1), ARGUS!$B$4:$LG$4, 0)-1,1,1)/1000, 0) -> 193.017 | CN54: =IFERROR(OFFSET(ARGUS!$A$3, MATCH($A54, ARGUS!$A$3:$A$176, 0)-1,MATCH(EOMONTH(CN$15,1), ARGUS!$B$4:$LG$4, 0)-1,1,1)/1000, 0) -> 193.51 | CO54: =IFERROR(OFFSET(ARGUS!$A$3, MATCH($A54, ARGUS!$A$3:$A$176, 0)-1,MATCH(EOMONTH(CO$15,1), ARGUS!$B$4:$LG$4, 0)-1,1,1)/1000, 0) -> 193.51 | CP54: =IFERROR(OFFSET(ARGUS!$A$3, MATCH($A54, ARGUS!$A$3:$A$176, 0)-1,MATCH(EOMONTH(CP$15,1), ARGUS!$B$4:$LG$4, 0)-1,1,1)/1000, 0) -> 193.707 | ... GT54: =IFERROR(OFFSET(ARGUS!$A$3, MATCH($A54, ARGUS!$A$3:$A$176, 0)-1,MATCH(EOMONTH(GT$15,1), ARGUS!$B$4:$LG$4, 0)-1,1,1)/1000, 0) -> 219.42 | HF54: x | HG54: =HG53+1 -> #REF! | HH54: =B54 -> Potential Base Rent | HL54: =SUM(HN54:HV54) -> 14569.888 | HN54: =SUMIF($K$14:$GT$14,HN$14,$K54:$GT54) -> 0 | HO54: =SUMIF($K$14:$GT$14,HO$14,$K54:$GT54) -> 1384.1558 | HP54: =SUMIF($K$14:$GT$14,HP$14,$K54:$GT54) -> 1517.3739 | HQ54: =SUMIF($K$14:$GT$14,HQ$14,$K54:$GT54) -> 1646.1152 | HR54: =SUMIF($K$14:$GT$14,HR$14,$K54:$GT54) -> 1858.7961 | HS54: =SUMIF($K$14:$GT$14,HS$14,$K54:$GT54) -> 1661.6027 | HT54: =SUMIF($K$14:$GT$14,HT$14,$K54:$GT54) -> 1805.1816 | HU54: =SUMIF($K$14:$GT$14,HU$14,$K54:$GT54) -> 2212.1021 | HV54: =SUMIF($K$14:$GT$14,HV$14,$K54:$GT54) -> 2484.561
A55: 2 | B55: Absorption & Turnover Vacancy | I55: =SUMIF($K$13:$GT$13,"<="&Assumptions!$L$17,'Monthly Cash Flow'!K55:GT55) -> -594.525 | L55: =Historicals!D4 -> 0 | M55: =Historicals!E4 -> 0 | N55: =Historicals!F4 -> 0 | O55: =Historicals!G4 -> 0 | P55: =Historicals!H4 -> 0 | Q55: =Historicals!I4 -> 0 | R55: =Historicals!J4 -> 0 | S55: =Historicals!K4 -> 0 | ... CH55: =Historicals!BZ4 -> 0 | CI55: =IFERROR(OFFSET(ARGUS!$A$3, MATCH($A55, ARGUS!$A$3:$A$176, 0)-1,MATCH(EOMONTH(CI$15,1), ARGUS!$B$4:$LG$4, 0)-1,1,1)/1000, 0) -> -30.559 | CJ55: =IFERROR(OFFSET(ARGUS!$A$3, MATCH($A55, ARGUS!$A$3:$A$176, 0)-1,MATCH(EOMONTH(CJ$15,1), ARGUS!$B$4:$LG$4, 0)-1,1,1)/1000, 0) -> -30.559 | CK55: =IFERROR(OFFSET(ARGUS!$A$3, MATCH($A55, ARGUS!$A$3:$A$176, 0)-1,MATCH(EOMONTH(CK$15,1), ARGUS!$B$4:$LG$4, 0)-1,1,1)/1000, 0) -> -30.559 | CL55: =IFERROR(OFFSET(ARGUS!$A$3, MATCH($A55, ARGUS!$A$3:$A$176, 0)-1,MATCH(EOMONTH(CL$15,1), ARGUS!$B$4:$LG$4, 0)-1,1,1)/1000, 0) -> -30.559 | CM55: =IFERROR(OFFSET(ARGUS!$A$3, MATCH($A55, ARGUS!$A$3:$A$176, 0)-1,MATCH(EOMONTH(CM$15,1), ARGUS!$B$4:$LG$4, 0)-1,1,1)/1000, 0) -> -30.559 | CN55: =IFERROR(OFFSET(ARGUS!$A$3, MATCH($A55, ARGUS!$A$3:$A$176, 0)-1,MATCH(EOMONTH(CN$15,1), ARGUS!$B$4:$LG$4, 0)-1,1,1)/1000, 0) -> -30.559 | CO55: =IFERROR(OFFSET(ARGUS!$A$3, MATCH($A55, ARGUS!$A$3:$A$176, 0)-1,MATCH(EOMONTH(CO$15,1), ARGUS!$B$4:$LG$4, 0)-1,1,1)/1000, 0) -> -30.559 | CP55: =IFERROR(OFFSET(ARGUS!$A$3, MATCH($A55, ARGUS!$A$3:$A$176, 0)-1,MATCH(EOMONTH(CP$15,1), ARGUS!$B$4:$LG$4, 0)-1,1,1)/1000, 0) -> -23.399 | ... GT55: =IFERROR(OFFSET(ARGUS!$A$3, MATCH($A55, ARGUS!$A$3:$A$176, 0)-1,MATCH(EOMONTH(GT$15,1), ARGUS!$B$4:$LG$4, 0)-1,1,1)/1000, 0) -> 0 | HF55: x | HG55: =HG54+1 -> #REF! | HH55: =B55 -> Absorption & Turnover Vacancy | HL55: =SUM(HN55:HV55) -> -594.525 | HN55: =SUMIF($K$14:$GT$14,HN$14,$K55:$GT55) -> 0 | HO55: =SUMIF($K$14:$GT$14,HO$14,$K55:$GT55) -> 0 | HP55: =SUMIF($K$14:$GT$14,HP$14,$K55:$GT55) -> 0 | HQ55: =SUMIF($K$14:$GT$14,HQ$14,$K55:$GT55) -> 0 | HR55: =SUMIF($K$14:$GT$14,HR$14,$K55:$GT55) -> 0 | HS55: =SUMIF($K$14:$GT$14,HS$14,$K55:$GT55) -> 0 | HT55: =SUMIF($K$14:$GT$14,HT$14,$K55:$GT55) -> 0 | HU55: =SUMIF($K$14:$GT$14,HU$14,$K55:$GT55) -> -260.711 | HV55: =SUMIF($K$14:$GT$14,HV$14,$K55:$GT55) -> -333.814
A56: 3 | B56: Free Rent | I56: =SUMIF($K$13:$GT$13,"<="&Assumptions!$L$17,'Monthly Cash Flow'!K56:GT56) -> -536.60178 | L56: =Historicals!D5 -> 0 | M56: =Historicals!E5 -> 0 | N56: =Historicals!F5 -> 0 | O56: =Historicals!G5 -> 0 | P56: =Historicals!H5 -> 0 | Q56: =Historicals!I5 -> 0 | R56: =Historicals!J5 -> 0 | S56: =Historicals!K5 -> 0 | ... CH56: =Historicals!BZ5 -> -10.38375 | CI56: =IFERROR(OFFSET(ARGUS!$A$3, MATCH($A56, ARGUS!$A$3:$A$176, 0)-1,MATCH(EOMONTH(CI$15,1), ARGUS!$B$4:$LG$4, 0)-1,1,1)/1000, 0) -> -27.128 | CJ56: =IFERROR(OFFSET(ARGUS!$A$3, MATCH($A56, ARGUS!$A$3:$A$176, 0)-1,MATCH(EOMONTH(CJ$15,1), ARGUS!$B$4:$LG$4, 0)-1,1,1)/1000, 0) -> 0 | CK56: =IFERROR(OFFSET(ARGUS!$A$3, MATCH($A56, ARGUS!$A$3:$A$176, 0)-1,MATCH(EOMONTH(CK$15,1), ARGUS!$B$4:$LG$4, 0)-1,1,1)/1000, 0) -> 0 | CL56: =IFERROR(OFFSET(ARGUS!$A$3, MATCH($A56, ARGUS!$A$3:$A$176, 0)-1,MATCH(EOMONTH(CL$15,1), ARGUS!$B$4:$LG$4, 0)-1,1,1)/1000, 0) -> 0 | CM56: =IFERROR(OFFSET(ARGUS!$A$3, MATCH($A56, ARGUS!$A$3:$A$176, 0)-1,MATCH(EOMONTH(CM$15,1), ARGUS!$B$4:$LG$4, 0)-1,1,1)/1000, 0) -> 0 | CN56: =IFERROR(OFFSET(ARGUS!$A$3, MATCH($A56, ARGUS!$A$3:$A$176, 0)-1,MATCH(EOMONTH(CN$15,1), ARGUS!$B$4:$LG$4, 0)-1,1,1)/1000, 0) -> 0 | CO56: =IFERROR(OFFSET(ARGUS!$A$3, MATCH($A56, ARGUS!$A$3:$A$176, 0)-1,MATCH(EOMONTH(CO$15,1), ARGUS!$B$4:$LG$4, 0)-1,1,1)/1000, 0) -> 0 | CP56: =IFERROR(OFFSET(ARGUS!$A$3, MATCH($A56, ARGUS!$A$3:$A$176, 0)-1,MATCH(EOMONTH(CP$15,1), ARGUS!$B$4:$LG$4, 0)-1,1,1)/1000, 0) -> 0 | ... GT56: =IFERROR(OFFSET(ARGUS!$A$3, MATCH($A56, ARGUS!$A$3:$A$176, 0)-1,MATCH(EOMONTH(GT$15,1), ARGUS!$B$4:$LG$4, 0)-1,1,1)/1000, 0) -> 0 | HF56: x | HG56: =HG55+1 -> #REF! | HH56: =B56 -> Free Rent | HL56: =SUM(HN56:HV56) -> -536.60178 | HN56: =SUMIF($K$14:$GT$14,HN$14,$K56:$GT56) -> 0 | HO56: =SUMIF($K$14:$GT$14,HO$14,$K56:$GT56) -> -53.115 | HP56: =SUMIF($K$14:$GT$14,HP$14,$K56:$GT56) -> -121.70247 | HQ56: =SUMIF($K$14:$GT$14,HQ$14,$K56:$GT56) -> -104.91229 | HR56: =SUMIF($K$14:$GT$14,HR$14,$K56:$GT56) -> -114.87685 | HS56: =SUMIF($K$14:$GT$14,HS$14,$K56:$GT56) -> -59.26107 | HT56: =SUMIF($K$14:$GT$14,HT$14,$K56:$GT56) -> -27.20017 | HU56: =SUMIF($K$14:$GT$14,HU$14,$K56:$GT56) -> -48.75893 | HV56: =SUMIF($K$14:$GT$14,HV$14,$K56:$GT56) -> -6.775
A57: 4 | B57: Total Expense Recoveries | I57: =SUMIF($K$13:$GT$13,"<="&Assumptions!$L$17,'Monthly Cash Flow'!K57:GT57) -> 9648.983 | L57: =Historicals!D6 -> 62.98453 | M57: =Historicals!E6 -> 62.98453 | N57: =Historicals!F6 -> 62.98453 | O57: =Historicals!G6 -> 65.05819 | P57: =Historicals!H6 -> 61.24428 | Q57: =Historicals!I6 -> 61.68743 | R57: =Historicals!J6 -> 64.99071 | S57: =Historicals!K6 -> 121.40012 | ... CH57: =Historicals!BZ6 -> 96.70992 | CI57: =IFERROR(OFFSET(ARGUS!$A$3, MATCH($A57, ARGUS!$A$3:$A$176, 0)-1,MATCH(EOMONTH(CI$15,1), ARGUS!$B$4:$LG$4, 0)-1,1,1)/1000, 0) -> 98.519 | CJ57: =IFERROR(OFFSET(ARGUS!$A$3, MATCH($A57, ARGUS!$A$3:$A$176, 0)-1,MATCH(EOMONTH(CJ$15,1), ARGUS!$B$4:$LG$4, 0)-1,1,1)/1000, 0) -> 98.519 | CK57: =IFERROR(OFFSET(ARGUS!$A$3, MATCH($A57, ARGUS!$A$3:$A$176, 0)-1,MATCH(EOMONTH(CK$15,1), ARGUS!$B$4:$LG$4, 0)-1,1,1)/1000, 0) -> 98.519 | CL57: =IFERROR(OFFSET(ARGUS!$A$3, MATCH($A57, ARGUS!$A$3:$A$176, 0)-1,MATCH(EOMONTH(CL$15,1), ARGUS!$B$4:$LG$4, 0)-1,1,1)/1000, 0) -> 101.755 | CM57: =IFERROR(OFFSET(ARGUS!$A$3, MATCH($A57, ARGUS!$A$3:$A$176, 0)-1,MATCH(EOMONTH(CM$15,1), ARGUS!$B$4:$LG$4, 0)-1,1,1)/1000, 0) -> 101.755 | CN57: =IFERROR(OFFSET(ARGUS!$A$3, MATCH($A57, ARGUS!$A$3:$A$176, 0)-1,MATCH(EOMONTH(CN$15,1), ARGUS!$B$4:$LG$4, 0)-1,1,1)/1000, 0) -> 101.755 | CO57: =IFERROR(OFFSET(ARGUS!$A$3, MATCH($A57, ARGUS!$A$3:$A$176, 0)-1,MATCH(EOMONTH(CO$15,1), ARGUS!$B$4:$LG$4, 0)-1,1,1)/1000, 0) -> 101.755 | CP57: =IFERROR(OFFSET(ARGUS!$A$3, MATCH($A57, ARGUS!$A$3:$A$176, 0)-1,MATCH(EOMONTH(CP$15,1), ARGUS!$B$4:$LG$4, 0)-1,1,1)/1000, 0) -> 107.065 | ... GT57: =IFERROR(OFFSET(ARGUS!$A$3, MATCH($A57, ARGUS!$A$3:$A$176, 0)-1,MATCH(EOMONTH(GT$15,1), ARGUS!$B$4:$LG$4, 0)-1,1,1)/1000, 0) -> 178.873 | HF57: x | HG57: =HG56+1 -> #REF! | HH57: =B57 -> Total Expense Recoveries | HL57: =SUM(HN57:HV57) -> 8751.833 | HN57: =SUMIF($K$14:$GT$14,HN$14,$K57:$GT57) -> 0 | HO57: =SUMIF($K$14:$GT$14,HO$14,$K57:$GT57) -> 1011.3474 | HP57: =SUMIF($K$14:$GT$14,HP$14,$K57:$GT57) -> 1024.1612 | HQ57: =SUMIF($K$14:$GT$14,HQ$14,$K57:$GT57) -> 1049.4354 | HR57: =SUMIF($K$14:$GT$14,HR$14,$K57:$GT57) -> 1167.1594 | HS57: =SUMIF($K$14:$GT$14,HS$14,$K57:$GT57) -> 1004.1078 | HT57: =SUMIF($K$14:$GT$14,HT$14,$K57:$GT57) -> 1003.169 | HU57: =SUMIF($K$14:$GT$14,HU$14,$K57:$GT57) -> 1206.5018 | HV57: =SUMIF($K$14:$GT$14,HV$14,$K57:$GT57) -> 1285.951
A58: 6 | B58: Parking Revenue | I58: =SUMIF($K$13:$GT$13,"<="&Assumptions!$L$17,'Monthly Cash Flow'!K58:GT58) -> 1462.3986 | L58: =Historicals!D7 -> 0 | M58: =Historicals!E7 -> 8.6 | N58: =Historicals!F7 -> 4.3 | O58: =Historicals!G7 -> 4.3 | P58: =Historicals!H7 -> 4.3 | Q58: =Historicals!I7 -> 4.3 | R58: =Historicals!J7 -> 4.3 | S58: =Historicals!K7 -> 4.3 | ... CH58: =Historicals!BZ7 -> 23.14199 | CI58: =IFERROR(OFFSET(ARGUS!$A$3, MATCH($A58, ARGUS!$A$3:$A$176, 0)-1,MATCH(EOMONTH(CI$15,1), ARGUS!$B$4:$LG$4, 0)-1,1,1)/1000, 0) -> 27 | CJ58: =IFERROR(OFFSET(ARGUS!$A$3, MATCH($A58, ARGUS!$A$3:$A$176, 0)-1,MATCH(EOMONTH(CJ$15,1), ARGUS!$B$4:$LG$4, 0)-1,1,1)/1000, 0) -> 27 | CK58: =IFERROR(OFFSET(ARGUS!$A$3, MATCH($A58, ARGUS!$A$3:$A$176, 0)-1,MATCH(EOMONTH(CK$15,1), ARGUS!$B$4:$LG$4, 0)-1,1,1)/1000, 0) -> 27 | CL58: =IFERROR(OFFSET(ARGUS!$A$3, MATCH($A58, ARGUS!$A$3:$A$176, 0)-1,MATCH(EOMONTH(CL$15,1), ARGUS!$B$4:$LG$4, 0)-1,1,1)/1000, 0) -> 27.81 | CM58: =IFERROR(OFFSET(ARGUS!$A$3, MATCH($A58, ARGUS!$A$3:$A$176, 0)-1,MATCH(EOMONTH(CM$15,1), ARGUS!$B$4:$LG$4, 0)-1,1,1)/1000, 0) -> 27.81 | CN58: =IFERROR(OFFSET(ARGUS!$A$3, MATCH($A58, ARGUS!$A$3:$A$176, 0)-1,MATCH(EOMONTH(CN$15,1), ARGUS!$B$4:$LG$4, 0)-1,1,1)/1000, 0) -> 27.81 | CO58: =IFERROR(OFFSET(ARGUS!$A$3, MATCH($A58, ARGUS!$A$3:$A$176, 0)-1,MATCH(EOMONTH(CO$15,1), ARGUS!$B$4:$LG$4, 0)-1,1,1)/1000, 0) -> 27.81 | CP58: =IFERROR(OFFSET(ARGUS!$A$3, MATCH($A58, ARGUS!$A$3:$A$176, 0)-1,MATCH(EOMONTH(CP$15,1), ARGUS!$B$4:$LG$4, 0)-1,1,1)/1000, 0) -> 27.81 | ... GT58: =IFERROR(OFFSET(ARGUS!$A$3, MATCH($A58, ARGUS!$A$3:$A$176, 0)-1,MATCH(EOMONTH(GT$15,1), ARGUS!$B$4:$LG$4, 0)-1,1,1)/1000, 0) -> 36.286 | HF58: x | HG58: =HG57+1 -> #REF! | HH58: =B58 -> Parking Revenue | HL58: =SUM(HN58:HV58) -> 1290.5346 | HN58: =SUMIF($K$14:$GT$14,HN$14,$K58:$GT58) -> 0 | HO58: =SUMIF($K$14:$GT$14,HO$14,$K58:$GT58) -> 51.6 | HP58: =SUMIF($K$14:$GT$14,HP$14,$K58:$GT58) -> 84 | HQ58: =SUMIF($K$14:$GT$14,HQ$14,$K58:$GT58) -> 77 | HR58: =SUMIF($K$14:$GT$14,HR$14,$K58:$GT58) -> 76.7617 | HS58: =SUMIF($K$14:$GT$14,HS$14,$K58:$GT58) -> 99.22095 | HT58: =SUMIF($K$14:$GT$14,HT$14,$K58:$GT58) -> 225.37297 | HU58: =SUMIF($K$14:$GT$14,HU$14,$K58:$GT58) -> 337.85498 | HV58: =SUMIF($K$14:$GT$14,HV$14,$K58:$GT58) -> 338.724
A59: 5 | B59: Other Revenue | I59: =SUMIF($K$13:$GT$13,"<="&Assumptions!$L$17,'Monthly Cash Flow'!K59:GT59) -> 286.68249 | L59: =Historicals!D8 -> 0 | M59: =Historicals!E8 -> 0 | N59: =Historicals!F8 -> 3.1431 | O59: =Historicals!G8 -> 9.32102 | P59: =Historicals!H8 -> 0 | Q59: =Historicals!I8 -> 4.46697 | R59: =Historicals!J8 -> 3.80335 | S59: =Historicals!K8 -> 11.8861 | ... CH59: =Historicals!BZ8 -> 2.70079 | CI59: =IFERROR(OFFSET(ARGUS!$A$3, MATCH($A59, ARGUS!$A$3:$A$176, 0)-1,MATCH(EOMONTH(CI$15,1), ARGUS!$B$4:$LG$4, 0)-1,1,1)/1000, 0) -> 3.132 | CJ59: =IFERROR(OFFSET(ARGUS!$A$3, MATCH($A59, ARGUS!$A$3:$A$176, 0)-1,MATCH(EOMONTH(CJ$15,1), ARGUS!$B$4:$LG$4, 0)-1,1,1)/1000, 0) -> 3.132 | CK59: =IFERROR(OFFSET(ARGUS!$A$3, MATCH($A59, ARGUS!$A$3:$A$176, 0)-1,MATCH(EOMONTH(CK$15,1), ARGUS!$B$4:$LG$4, 0)-1,1,1)/1000, 0) -> 3.132 | CL59: =IFERROR(OFFSET(ARGUS!$A$3, MATCH($A59, ARGUS!$A$3:$A$176, 0)-1,MATCH(EOMONTH(CL$15,1), ARGUS!$B$4:$LG$4, 0)-1,1,1)/1000, 0) -> 3.147 | CM59: =IFERROR(OFFSET(ARGUS!$A$3, MATCH($A59, ARGUS!$A$3:$A$176, 0)-1,MATCH(EOMONTH(CM$15,1), ARGUS!$B$4:$LG$4, 0)-1,1,1)/1000, 0) -> 3.147 | CN59: =IFERROR(OFFSET(ARGUS!$A$3, MATCH($A59, ARGUS!$A$3:$A$176, 0)-1,MATCH(EOMONTH(CN$15,1), ARGUS!$B$4:$LG$4, 0)-1,1,1)/1000, 0) -> 3.147 | CO59: =IFERROR(OFFSET(ARGUS!$A$3, MATCH($A59, ARGUS!$A$3:$A$176, 0)-1,MATCH(EOMONTH(CO$15,1), ARGUS!$B$4:$LG$4, 0)-1,1,1)/1000, 0) -> 3.147 | CP59: =IFERROR(OFFSET(ARGUS!$A$3, MATCH($A59, ARGUS!$A$3:$A$176, 0)-1,MATCH(EOMONTH(CP$15,1), ARGUS!$B$4:$LG$4, 0)-1,1,1)/1000, 0) -> 3.147 | ... GT59: =IFERROR(OFFSET(ARGUS!$A$3, MATCH($A59, ARGUS!$A$3:$A$176, 0)-1,MATCH(EOMONTH(GT$15,1), ARGUS!$B$4:$LG$4, 0)-1,1,1)/1000, 0) -> 0.672 | HF59: x | HG59: =HG58+1 -> #REF! | HH59: =B59 -> Other Revenue | HL59: =SUM(HN59:HV59) -> 283.50249 | HN59: =SUMIF($K$14:$GT$14,HN$14,$K59:$GT59) -> 0 | HO59: =SUMIF($K$14:$GT$14,HO$14,$K59:$GT59) -> 34.32191 | HP59: =SUMIF($K$14:$GT$14,HP$14,$K59:$GT59) -> 27.67585 | HQ59: =SUMIF($K$14:$GT$14,HQ$14,$K59:$GT59) -> 49.51106 | HR59: =SUMIF($K$14:$GT$14,HR$14,$K59:$GT59) -> 38.97518 | HS59: =SUMIF($K$14:$GT$14,HS$14,$K59:$GT59) -> 15.39234 | HT59: =SUMIF($K$14:$GT$14,HT$14,$K59:$GT59) -> 48.65578 | HU59: =SUMIF($K$14:$GT$14,HU$14,$K59:$GT59) -> 36.38037 | HV59: =SUMIF($K$14:$GT$14,HV$14,$K59:$GT59) -> 32.59
A60: 24 | B60: Potential Gross Revenue | I60: =SUMIF($K$13:$GT$13,"<="&Assumptions!$L$17,'Monthly Cash Flow'!K60:GT60) -> 26088.215 | L60: =SUM(L54:L59) -> 174.17922 | M60: =SUM(M54:M59) -> 183.67012 | N60: =SUM(N54:N59) -> 186.80412 | O60: =SUM(O54:O59) -> 190.57505 | P60: =SUM(P54:P59) -> 177.26428 | Q60: =SUM(Q54:Q59) -> 180.16823 | R60: =SUM(R54:R59) -> 180.77277 | S60: =SUM(S54:S59) -> 239.88771 | ... GT60: =SUM(GT54:GT59) -> 435.251 | HF60: x | HG60: =HG59+1 -> #REF! | HH60: =B60 -> Potential Gross Revenue | HL60: =SUM(HN60:HV60) -> 23764.632 | HN60: =SUMIF($K$14:$GT$14,HN$14,$K60:$GT60) -> 0 | HO60: =SUMIF($K$14:$GT$14,HO$14,$K60:$GT60) -> 2428.31 | HP60: =SUMIF($K$14:$GT$14,HP$14,$K60:$GT60) -> 2531.5085 | HQ60: =SUMIF($K$14:$GT$14,HQ$14,$K60:$GT60) -> 2717.1494 | HR60: =SUMIF($K$14:$GT$14,HR$14,$K60:$GT60) -> 3026.8155 | HS60: =SUMIF($K$14:$GT$14,HS$14,$K60:$GT60) -> 2721.0628 | HT60: =SUMIF($K$14:$GT$14,HT$14,$K60:$GT60) -> 3055.1792 | HU60: =SUMIF($K$14:$GT$14,HU$14,$K60:$GT60) -> 3483.3693 | HV60: =SUMIF($K$14:$GT$14,HV$14,$K60:$GT60) -> 3801.237
A61: 7 | B61: Vacancy Allowance | G61: Check | H61: =IF(ABS(SUM(I54:I59, I61)-I62)<1, "YES", "ERROR") -> YES | I61: =SUMIF($K$13:$GT$13,"<="&Assumptions!$L$17,'Monthly Cash Flow'!K61:GT61) -> -73.158 | L61: 0 | M61: 0 | N61: 0 | O61: 0 | P61: 0 | Q61: 0 | R61: 0 | S61: 0 | T61: 0 | U61: 0 | V61: 0 | W61: 0 | X61: 0 | Y61: 0 | Z61: 0 | AA61: 0 | AB61: 0 | AC61: 0 | AD61: 0 | AE61: 0 | AF61: 0 | AG61: 0 | AH61: 0 | AI61: 0 | AJ61: 0 | AK61: 0 | AL61: 0 | AM61: 0 | AN61: 0 | AO61: 0 | AP61: 0 | AQ61: 0 | AR61: 0 | AS61: 0 | AT61: 0 | AU61: 0 | AV61: 0 | AW61: 0 | AX61: 0 | AY61: 0 | AZ61: 0 | BA61: 0 | BB61: 0 | BC61: 0 | BD61: 0 | BE61: 0 | BF61: 0 | BG61: 0 | BH61: 0 | BI61: 0 | BJ61: 0 | BK61: 0 | BL61: =IFERROR(OFFSET(ARGUS!$A$3, MATCH($A61, ARGUS!$A$3:$A$176, 0)-1,MATCH(EOMONTH(BL$15,1), ARGUS!$B$4:$LG$4, 0)-1,1,1)/1000, 0) -> 0 | BM61: =IFERROR(OFFSET(ARGUS!$A$3, MATCH($A61, ARGUS!$A$3:$A$176, 0)-1,MATCH(EOMONTH(BM$15,1), ARGUS!$B$4:$LG$4, 0)-1,1,1)/1000, 0) -> 0 | BN61: =IFERROR(OFFSET(ARGUS!$A$3, MATCH($A61, ARGUS!$A$3:$A$176, 0)-1,MATCH(EOMONTH(BN$15,1), ARGUS!$B$4:$LG$4, 0)-1,1,1)/1000, 0) -> 0 | BO61: =IFERROR(OFFSET(ARGUS!$A$3, MATCH($A61, ARGUS!$A$3:$A$176, 0)-1,MATCH(EOMONTH(BO$15,1), ARGUS!$B$4:$LG$4, 0)-1,1,1)/1000, 0) -> 0 | BP61: =IFERROR(OFFSET(ARGUS!$A$3, MATCH($A61, ARGUS!$A$3:$A$176, 0)-1,MATCH(EOMONTH(BP$15,1), ARGUS!$B$4:$LG$4, 0)-1,1,1)/1000, 0) -> 0 | BQ61: =IFERROR(OFFSET(ARGUS!$A$3, MATCH($A61, ARGUS!$A$3:$A$176, 0)-1,MATCH(EOMONTH(BQ$15,1), ARGUS!$B$4:$LG$4, 0)-1,1,1)/1000, 0) -> 0 | BR61: =IFERROR(OFFSET(ARGUS!$A$3, MATCH($A61, ARGUS!$A$3:$A$176, 0)-1,MATCH(EOMONTH(BR$15,1), ARGUS!$B$4:$LG$4, 0)-1,1,1)/1000, 0) -> 0 | BS61: =IFERROR(OFFSET(ARGUS!$A$3, MATCH($A61, ARGUS!$A$3:$A$176, 0)-1,MATCH(EOMONTH(BS$15,1), ARGUS!$B$4:$LG$4, 0)-1,1,1)/1000, 0) -> 0 | ... CH61: =IFERROR(OFFSET(ARGUS!$A$3, MATCH($A61, ARGUS!$A$3:$A$176, 0)-1,MATCH(EOMONTH(CH$15,1), ARGUS!$B$4:$LG$4, 0)-1,1,1)/1000, 0) -> 0 | CI61: 0 | CJ61: 0 | CK61: 0 | CL61: 0 | CM61: 0 | CN61: 0 | CO61: 0 | CP61: 0 | CQ61: 0 | CR61: 0 | CS61: 0 | CT61: 0 | CU61: 0 | CV61: 0 | CW61: 0 | CX61: 0 | CY61: 0 | CZ61: 0 | DA61: 0 | DB61: 0 | DC61: =IFERROR(OFFSET(ARGUS!$A$3, MATCH($A61, ARGUS!$A$3:$A$176, 0)-1,MATCH(EOMONTH(DC$15,1), ARGUS!$B$4:$LG$4, 0)-1,1,1)/1000, 0) -> -10.365 | DD61: =IFERROR(OFFSET(ARGUS!$A$3, MATCH($A61, ARGUS!$A$3:$A$176, 0)-1,MATCH(EOMONTH(DD$15,1), ARGUS!$B$4:$LG$4, 0)-1,1,1)/1000, 0) -> -10.365 | DE61: =IFERROR(OFFSET(ARGUS!$A$3, MATCH($A61, ARGUS!$A$3:$A$176, 0)-1,MATCH(EOMONTH(DE$15,1), ARGUS!$B$4:$LG$4, 0)-1,1,1)/1000, 0) -> -10.365 | DF61: =IFERROR(OFFSET(ARGUS!$A$3, MATCH($A61, ARGUS!$A$3:$A$176, 0)-1,MATCH(EOMONTH(DF$15,1), ARGUS!$B$4:$LG$4, 0)-1,1,1)/1000, 0) -> -10.365 | DG61: =IFERROR(OFFSET(ARGUS!$A$3, MATCH($A61, ARGUS!$A$3:$A$176, 0)-1,MATCH(EOMONTH(DG$15,1), ARGUS!$B$4:$LG$4, 0)-1,1,1)/1000, 0) -> -10.566 | DH61: =IFERROR(OFFSET(ARGUS!$A$3, MATCH($A61, ARGUS!$A$3:$A$176, 0)-1,MATCH(EOMONTH(DH$15,1), ARGUS!$B$4:$LG$4, 0)-1,1,1)/1000, 0) -> -10.566 | DI61: =IFERROR(OFFSET(ARGUS!$A$3, MATCH($A61, ARGUS!$A$3:$A$176, 0)-1,MATCH(EOMONTH(DI$15,1), ARGUS!$B$4:$LG$4, 0)-1,1,1)/1000, 0) -> -10.566 | DJ61: =IFERROR(OFFSET(ARGUS!$A$3, MATCH($A61, ARGUS!$A$3:$A$176, 0)-1,MATCH(EOMONTH(DJ$15,1), ARGUS!$B$4:$LG$4, 0)-1,1,1)/1000, 0) -> -10.566 | ... GT61: =IFERROR(OFFSET(ARGUS!$A$3, MATCH($A61, ARGUS!$A$3:$A$176, 0)-1,MATCH(EOMONTH(GT$15,1), ARGUS!$B$4:$LG$4, 0)-1,1,1)/1000, 0) -> -10.987 | HF61: x | HG61: =HG60+1 -> #REF! | HH61: =B61 -> Vacancy Allowance | HL61: =SUM(HN61:HV61) -> -10.365 | HN61: =SUMIF($K$14:$GT$14,HN$14,$K61:$GT61) -> 0 | HO61: =SUMIF($K$14:$GT$14,HO$14,$K61:$GT61) -> 0 | HP61: =SUMIF($K$14:$GT$14,HP$14,$K61:$GT61) -> 0 | HQ61: =SUMIF($K$14:$GT$14,HQ$14,$K61:$GT61) -> 0 | HR61: =SUMIF($K$14:$GT$14,HR$14,$K61:$GT61) -> 0 | HS61: =SUMIF($K$14:$GT$14,HS$14,$K61:$GT61) -> 0 | HT61: =SUMIF($K$14:$GT$14,HT$14,$K61:$GT61) -> 0 | HU61: =SUMIF($K$14:$GT$14,HU$14,$K61:$GT61) -> 0 | HV61: =SUMIF($K$14:$GT$14,HV$14,$K61:$GT61) -> -10.365
A62: 26 | B62: Effective Gross Revenue | I62: =SUMIF($K$13:$GT$13,"<="&Assumptions!$L$17,'Monthly Cash Flow'!K62:GT62) -> 26015.057 | L62: =+L60+L61 -> 174.17922 | M62: =+M60+M61 -> 183.67012 | N62: =+N60+N61 -> 186.80412 | O62: =+O60+O61 -> 190.57505 | P62: =+P60+P61 -> 177.26428 | Q62: =+Q60+Q61 -> 180.16823 | R62: =+R60+R61 -> 180.77277 | S62: =+S60+S61 -> 239.88771 | ... GT62: =+GT60+GT61 -> 424.264 | HF62: x | HG62: =HG61+1 -> #REF! | HH62: =B62 -> Effective Gross Revenue | HL62: =SUM(HN62:HV62) -> 23754.267 | HN62: =SUMIF($K$14:$GT$14,HN$14,$K62:$GT62) -> 0 | HO62: =SUMIF($K$14:$GT$14,HO$14,$K62:$GT62) -> 2428.31 | HP62: =SUMIF($K$14:$GT$14,HP$14,$K62:$GT62) -> 2531.5085 | HQ62: =SUMIF($K$14:$GT$14,HQ$14,$K62:$GT62) -> 2717.1494 | HR62: =SUMIF($K$14:$GT$14,HR$14,$K62:$GT62) -> 3026.8155 | HS62: =SUMIF($K$14:$GT$14,HS$14,$K62:$GT62) -> 2721.0628 | HT62: =SUMIF($K$14:$GT$14,HT$14,$K62:$GT62) -> 3055.1792 | HU62: =SUMIF($K$14:$GT$14,HU$14,$K62:$GT62) -> 3483.3693 | HV62: =SUMIF($K$14:$GT$14,HV$14,$K62:$GT62) -> 3790.872
HF63: x | HG63: =HG62+1 -> #REF!
HF64: x | HG64: =HG63+1 -> #REF!
A65: 8 | B65: Common Area Maintenance | I65: =SUMIF($K$13:$GT$13,"<="&Assumptions!$L$17,'Monthly Cash Flow'!K65:GT65) -> 4611.8578 | L65: =Historicals!D13 -> 20.73232 | M65: =Historicals!E13 -> 41.57492 | N65: =Historicals!F13 -> 23.13331 | O65: =Historicals!G13 -> 10.1014 | P65: =Historicals!H13 -> 23.60387 | Q65: =Historicals!I13 -> 25.00292 | R65: =Historicals!J13 -> 23.6635 | S65: =Historicals!K13 -> 23.42751 | ... CH65: =Historicals!BZ13 -> 32.24538 | CI65: =IFERROR(OFFSET(ARGUS!$A$3, MATCH($A65, ARGUS!$A$3:$A$176, 0)-1,MATCH(EOMONTH(CI$15,1), ARGUS!$B$4:$LG$4, 0)-1,1,1)/1000, 0) -> 81.687 | CJ65: =IFERROR(OFFSET(ARGUS!$A$3, MATCH($A65, ARGUS!$A$3:$A$176, 0)-1,MATCH(EOMONTH(CJ$15,1), ARGUS!$B$4:$LG$4, 0)-1,1,1)/1000, 0) -> 81.687 | CK65: =IFERROR(OFFSET(ARGUS!$A$3, MATCH($A65, ARGUS!$A$3:$A$176, 0)-1,MATCH(EOMONTH(CK$15,1), ARGUS!$B$4:$LG$4, 0)-1,1,1)/1000, 0) -> 81.687 | CL65: =IFERROR(OFFSET(ARGUS!$A$3, MATCH($A65, ARGUS!$A$3:$A$176, 0)-1,MATCH(EOMONTH(CL$15,1), ARGUS!$B$4:$LG$4, 0)-1,1,1)/1000, 0) -> 84.138 | CM65: =IFERROR(OFFSET(ARGUS!$A$3, MATCH($A65, ARGUS!$A$3:$A$176, 0)-1,MATCH(EOMONTH(CM$15,1), ARGUS!$B$4:$LG$4, 0)-1,1,1)/1000, 0) -> 84.138 | CN65: =IFERROR(OFFSET(ARGUS!$A$3, MATCH($A65, ARGUS!$A$3:$A$176, 0)-1,MATCH(EOMONTH(CN$15,1), ARGUS!$B$4:$LG$4, 0)-1,1,1)/1000, 0) -> 84.138 | CO65: =IFERROR(OFFSET(ARGUS!$A$3, MATCH($A65, ARGUS!$A$3:$A$176, 0)-1,MATCH(EOMONTH(CO$15,1), ARGUS!$B$4:$LG$4, 0)-1,1,1)/1000, 0) -> 84.138 | CP65: =IFERROR(OFFSET(ARGUS!$A$3, MATCH($A65, ARGUS!$A$3:$A$176, 0)-1,MATCH(EOMONTH(CP$15,1), ARGUS!$B$4:$LG$4, 0)-1,1,1)/1000, 0) -> 84.138 | ... GT65: =IFERROR(OFFSET(ARGUS!$A$3, MATCH($A65, ARGUS!$A$3:$A$176, 0)-1,MATCH(EOMONTH(GT$15,1), ARGUS!$B$4:$LG$4, 0)-1,1,1)/1000, 0) -> 109.78 | HF65: x | HG65: =HG64+1 -> #REF! | HH65: =B65 -> Common Area Maintenance | HL65: =SUM(HN65:HV65) -> 4091.8858 | HN65: =SUMIF($K$14:$GT$14,HN$14,$K65:$GT65) -> 0 | HO65: =SUMIF($K$14:$GT$14,HO$14,$K65:$GT65) -> 207.44256 | HP65: =SUMIF($K$14:$GT$14,HP$14,$K65:$GT65) -> 530.21385 | HQ65: =SUMIF($K$14:$GT$14,HQ$14,$K65:$GT65) -> 357.0314 | HR65: =SUMIF($K$14:$GT$14,HR$14,$K65:$GT65) -> 398.66913 | HS65: =SUMIF($K$14:$GT$14,HS$14,$K65:$GT65) -> 342.30242 | HT65: =SUMIF($K$14:$GT$14,HT$14,$K65:$GT65) -> 395.38201 | HU65: =SUMIF($K$14:$GT$14,HU$14,$K65:$GT65) -> 836.04443 | HV65: =SUMIF($K$14:$GT$14,HV$14,$K65:$GT65) -> 1024.8
A66: 13 | B66: General & Administrative | I66: =SUMIF($K$13:$GT$13,"<="&Assumptions!$L$17,'Monthly Cash Flow'!K66:GT66) -> 1715.6644 | L66: =Historicals!D14 -> 10.761 | M66: =Historicals!E14 -> 9.65 | N66: =Historicals!F14 -> 13.9885 | O66: =Historicals!G14 -> 39.0742 | P66: =Historicals!H14 -> 9.37764 | Q66: =Historicals!I14 -> 82.84792 | R66: =Historicals!J14 -> 11.8 | S66: =Historicals!K14 -> 2.8 | ... CH66: =Historicals!BZ14 -> 4.55564 | CI66: =IFERROR(OFFSET(ARGUS!$A$3, MATCH($A66, ARGUS!$A$3:$A$176, 0)-1,MATCH(EOMONTH(CI$15,1), ARGUS!$B$4:$LG$4, 0)-1,1,1)/1000, 0) -> 11.925 | CJ66: =IFERROR(OFFSET(ARGUS!$A$3, MATCH($A66, ARGUS!$A$3:$A$176, 0)-1,MATCH(EOMONTH(CJ$15,1), ARGUS!$B$4:$LG$4, 0)-1,1,1)/1000, 0) -> 11.925 | CK66: =IFERROR(OFFSET(ARGUS!$A$3, MATCH($A66, ARGUS!$A$3:$A$176, 0)-1,MATCH(EOMONTH(CK$15,1), ARGUS!$B$4:$LG$4, 0)-1,1,1)/1000, 0) -> 11.925 | CL66: =IFERROR(OFFSET(ARGUS!$A$3, MATCH($A66, ARGUS!$A$3:$A$176, 0)-1,MATCH(EOMONTH(CL$15,1), ARGUS!$B$4:$LG$4, 0)-1,1,1)/1000, 0) -> 12.224 | CM66: =IFERROR(OFFSET(ARGUS!$A$3, MATCH($A66, ARGUS!$A$3:$A$176, 0)-1,MATCH(EOMONTH(CM$15,1), ARGUS!$B$4:$LG$4, 0)-1,1,1)/1000, 0) -> 12.224 | CN66: =IFERROR(OFFSET(ARGUS!$A$3, MATCH($A66, ARGUS!$A$3:$A$176, 0)-1,MATCH(EOMONTH(CN$15,1), ARGUS!$B$4:$LG$4, 0)-1,1,1)/1000, 0) -> 12.224 | CO66: =IFERROR(OFFSET(ARGUS!$A$3, MATCH($A66, ARGUS!$A$3:$A$176, 0)-1,MATCH(EOMONTH(CO$15,1), ARGUS!$B$4:$LG$4, 0)-1,1,1)/1000, 0) -> 12.224 | CP66: =IFERROR(OFFSET(ARGUS!$A$3, MATCH($A66, ARGUS!$A$3:$A$176, 0)-1,MATCH(EOMONTH(CP$15,1), ARGUS!$B$4:$LG$4, 0)-1,1,1)/1000, 0) -> 12.224 | ... GT66: =IFERROR(OFFSET(ARGUS!$A$3, MATCH($A66, ARGUS!$A$3:$A$176, 0)-1,MATCH(EOMONTH(GT$15,1), ARGUS!$B$4:$LG$4, 0)-1,1,1)/1000, 0) -> 15.356 | HF66: x | HG66: =HG65+1 -> #REF! | HH66: =B66 -> General & Administrative | HL66: =SUM(HN66:HV66) -> 1640.4725 | HN66: =SUMIF($K$14:$GT$14,HN$14,$K66:$GT66) -> 0 | HO66: =SUMIF($K$14:$GT$14,HO$14,$K66:$GT66) -> 415.40838 | HP66: =SUMIF($K$14:$GT$14,HP$14,$K66:$GT66) -> -8.67407 | HQ66: =SUMIF($K$14:$GT$14,HQ$14,$K66:$GT66) -> 34.3798 | HR66: =SUMIF($K$14:$GT$14,HR$14,$K66:$GT66) -> 162.35634 | HS66: =SUMIF($K$14:$GT$14,HS$14,$K66:$GT66) -> 628.35821 | HT66: =SUMIF($K$14:$GT$14,HT$14,$K66:$GT66) -> 137.46249 | HU66: =SUMIF($K$14:$GT$14,HU$14,$K66:$GT66) -> 122.6453 | HV66: =SUMIF($K$14:$GT$14,HV$14,$K66:$GT66) -> 148.536
B67: Contract Services | I67: =SUMIF($K$13:$GT$13,"<="&Assumptions!$L$17,'Monthly Cash Flow'!K67:GT67) -> 0 | L67: =Historicals!D15 -> 0 | M67: =Historicals!E15 -> 0 | N67: =Historicals!F15 -> 0 | O67: =Historicals!G15 -> 0 | P67: =Historicals!H15 -> 0 | Q67: =Historicals!I15 -> 0 | R67: =Historicals!J15 -> 0 | S67: =Historicals!K15 -> 0 | ... CH67: =Historicals!BZ15 -> 0 | CI67: =IFERROR(OFFSET(ARGUS!$A$3, MATCH($A67, ARGUS!$A$3:$A$176, 0)-1,MATCH(EOMONTH(CI$15,1), ARGUS!$B$4:$LG$4, 0)-1,1,1)/1000, 0) -> 0 | CJ67: =IFERROR(OFFSET(ARGUS!$A$3, MATCH($A67, ARGUS!$A$3:$A$176, 0)-1,MATCH(EOMONTH(CJ$15,1), ARGUS!$B$4:$LG$4, 0)-1,1,1)/1000, 0) -> 0 | CK67: =IFERROR(OFFSET(ARGUS!$A$3, MATCH($A67, ARGUS!$A$3:$A$176, 0)-1,MATCH(EOMONTH(CK$15,1), ARGUS!$B$4:$LG$4, 0)-1,1,1)/1000, 0) -> 0 | CL67: =IFERROR(OFFSET(ARGUS!$A$3, MATCH($A67, ARGUS!$A$3:$A$176, 0)-1,MATCH(EOMONTH(CL$15,1), ARGUS!$B$4:$LG$4, 0)-1,1,1)/1000, 0) -> 0 | CM67: =IFERROR(OFFSET(ARGUS!$A$3, MATCH($A67, ARGUS!$A$3:$A$176, 0)-1,MATCH(EOMONTH(CM$15,1), ARGUS!$B$4:$LG$4, 0)-1,1,1)/1000, 0) -> 0 | CN67: =IFERROR(OFFSET(ARGUS!$A$3, MATCH($A67, ARGUS!$A$3:$A$176, 0)-1,MATCH(EOMONTH(CN$15,1), ARGUS!$B$4:$LG$4, 0)-1,1,1)/1000, 0) -> 0 | CO67: =IFERROR(OFFSET(ARGUS!$A$3, MATCH($A67, ARGUS!$A$3:$A$176, 0)-1,MATCH(EOMONTH(CO$15,1), ARGUS!$B$4:$LG$4, 0)-1,1,1)/1000, 0) -> 0 | CP67: =IFERROR(OFFSET(ARGUS!$A$3, MATCH($A67, ARGUS!$A$3:$A$176, 0)-1,MATCH(EOMONTH(CP$15,1), ARGUS!$B$4:$LG$4, 0)-1,1,1)/1000, 0) -> 0 | ... GT67: =IFERROR(OFFSET(ARGUS!$A$3, MATCH($A67, ARGUS!$A$3:$A$176, 0)-1,MATCH(EOMONTH(GT$15,1), ARGUS!$B$4:$LG$4, 0)-1,1,1)/1000, 0) -> 0 | HF67: x | HG67: =HG66+1 -> #REF! | HH67: =B67 -> Contract Services | HL67: =SUM(HN67:HV67) -> 0 | HN67: =SUMIF($K$14:$GT$14,HN$14,$K67:$GT67) -> 0 | HO67: =SUMIF($K$14:$GT$14,HO$14,$K67:$GT67) -> 0 | HP67: =SUMIF($K$14:$GT$14,HP$14,$K67:$GT67) -> 0 | HQ67: =SUMIF($K$14:$GT$14,HQ$14,$K67:$GT67) -> 0 | HR67: =SUMIF($K$14:$GT$14,HR$14,$K67:$GT67) -> 0 | HS67: =SUMIF($K$14:$GT$14,HS$14,$K67:$GT67) -> 0 | HT67: =SUMIF($K$14:$GT$14,HT$14,$K67:$GT67) -> 0 | HU67: =SUMIF($K$14:$GT$14,HU$14,$K67:$GT67) -> 0 | HV67: =SUMIF($K$14:$GT$14,HV$14,$K67:$GT67) -> 0
A68: 9 | B68: Utilities | I68: =SUMIF($K$13:$GT$13,"<="&Assumptions!$L$17,'Monthly Cash Flow'!K68:GT68) -> 3043.1622 | L68: =Historicals!D16 -> 36.95091 | M68: =Historicals!E16 -> 49.02688 | N68: =Historicals!F16 -> 42.76975 | O68: =Historicals!G16 -> 33.19602 | P68: =Historicals!H16 -> 25.88346 | Q68: =Historicals!I16 -> 35.14288 | R68: =Historicals!J16 -> 33.65774 | S68: =Historicals!K16 -> 32.82673 | ... CH68: =Historicals!BZ16 -> 62.17483 | CI68: =IFERROR(OFFSET(ARGUS!$A$3, MATCH($A68, ARGUS!$A$3:$A$176, 0)-1,MATCH(EOMONTH(CI$15,1), ARGUS!$B$4:$LG$4, 0)-1,1,1)/1000, 0) -> 0 | CJ68: =IFERROR(OFFSET(ARGUS!$A$3, MATCH($A68, ARGUS!$A$3:$A$176, 0)-1,MATCH(EOMONTH(CJ$15,1), ARGUS!$B$4:$LG$4, 0)-1,1,1)/1000, 0) -> 0 | CK68: =IFERROR(OFFSET(ARGUS!$A$3, MATCH($A68, ARGUS!$A$3:$A$176, 0)-1,MATCH(EOMONTH(CK$15,1), ARGUS!$B$4:$LG$4, 0)-1,1,1)/1000, 0) -> 0 | CL68: =IFERROR(OFFSET(ARGUS!$A$3, MATCH($A68, ARGUS!$A$3:$A$176, 0)-1,MATCH(EOMONTH(CL$15,1), ARGUS!$B$4:$LG$4, 0)-1,1,1)/1000, 0) -> 0 | CM68: =IFERROR(OFFSET(ARGUS!$A$3, MATCH($A68, ARGUS!$A$3:$A$176, 0)-1,MATCH(EOMONTH(CM$15,1), ARGUS!$B$4:$LG$4, 0)-1,1,1)/1000, 0) -> 0 | CN68: =IFERROR(OFFSET(ARGUS!$A$3, MATCH($A68, ARGUS!$A$3:$A$176, 0)-1,MATCH(EOMONTH(CN$15,1), ARGUS!$B$4:$LG$4, 0)-1,1,1)/1000, 0) -> 0 | CO68: =IFERROR(OFFSET(ARGUS!$A$3, MATCH($A68, ARGUS!$A$3:$A$176, 0)-1,MATCH(EOMONTH(CO$15,1), ARGUS!$B$4:$LG$4, 0)-1,1,1)/1000, 0) -> 0 | CP68: =IFERROR(OFFSET(ARGUS!$A$3, MATCH($A68, ARGUS!$A$3:$A$176, 0)-1,MATCH(EOMONTH(CP$15,1), ARGUS!$B$4:$LG$4, 0)-1,1,1)/1000, 0) -> 0 | ... GT68: =IFERROR(OFFSET(ARGUS!$A$3, MATCH($A68, ARGUS!$A$3:$A$176, 0)-1,MATCH(EOMONTH(GT$15,1), ARGUS!$B$4:$LG$4, 0)-1,1,1)/1000, 0) -> 0 | HF68: x | HG68: =HG67+1 -> #REF! | HH68: =B68 -> Utilities | HL68: =SUM(HN68:HV68) -> 3043.1622 | HN68: =SUMIF($K$14:$GT$14,HN$14,$K68:$GT68) -> 0 | HO68: =SUMIF($K$14:$GT$14,HO$14,$K68:$GT68) -> 445.67181 | HP68: =SUMIF($K$14:$GT$14,HP$14,$K68:$GT68) -> 463.00145 | HQ68: =SUMIF($K$14:$GT$14,HQ$14,$K68:$GT68) -> 464.98296 | HR68: =SUMIF($K$14:$GT$14,HR$14,$K68:$GT68) -> 453.10074 | HS68: =SUMIF($K$14:$GT$14,HS$14,$K68:$GT68) -> 411.28447 | HT68: =SUMIF($K$14:$GT$14,HT$14,$K68:$GT68) -> 621.02669 | HU68: =SUMIF($K$14:$GT$14,HU$14,$K68:$GT68) -> 184.09407 | HV68: =SUMIF($K$14:$GT$14,HV$14,$K68:$GT68) -> 0
A69: 10 | B69: Insurance | I69: =SUMIF($K$13:$GT$13,"<="&Assumptions!$L$17,'Monthly Cash Flow'!K69:GT69) -> 980.27931 | L69: =Historicals!D17 -> 7.568 | M69: =Historicals!E17 -> 7.99461 | N69: =Historicals!F17 -> 7.43886 | O69: =Historicals!G17 -> 7.6241 | P69: =Historicals!H17 -> 7.6241 | Q69: =Historicals!I17 -> 7.6241 | R69: =Historicals!J17 -> 7.53491 | S69: =Historicals!K17 -> 7.5349 | ... CH69: =Historicals!BZ17 -> 4.17896 | CI69: =IFERROR(OFFSET(ARGUS!$A$3, MATCH($A69, ARGUS!$A$3:$A$176, 0)-1,MATCH(EOMONTH(CI$15,1), ARGUS!$B$4:$LG$4, 0)-1,1,1)/1000, 0) -> 12.09 | CJ69: =IFERROR(OFFSET(ARGUS!$A$3, MATCH($A69, ARGUS!$A$3:$A$176, 0)-1,MATCH(EOMONTH(CJ$15,1), ARGUS!$B$4:$LG$4, 0)-1,1,1)/1000, 0) -> 12.09 | CK69: =IFERROR(OFFSET(ARGUS!$A$3, MATCH($A69, ARGUS!$A$3:$A$176, 0)-1,MATCH(EOMONTH(CK$15,1), ARGUS!$B$4:$LG$4, 0)-1,1,1)/1000, 0) -> 12.09 | CL69: =IFERROR(OFFSET(ARGUS!$A$3, MATCH($A69, ARGUS!$A$3:$A$176, 0)-1,MATCH(EOMONTH(CL$15,1), ARGUS!$B$4:$LG$4, 0)-1,1,1)/1000, 0) -> 12.453 | CM69: =IFERROR(OFFSET(ARGUS!$A$3, MATCH($A69, ARGUS!$A$3:$A$176, 0)-1,MATCH(EOMONTH(CM$15,1), ARGUS!$B$4:$LG$4, 0)-1,1,1)/1000, 0) -> 12.453 | CN69: =IFERROR(OFFSET(ARGUS!$A$3, MATCH($A69, ARGUS!$A$3:$A$176, 0)-1,MATCH(EOMONTH(CN$15,1), ARGUS!$B$4:$LG$4, 0)-1,1,1)/1000, 0) -> 12.453 | CO69: =IFERROR(OFFSET(ARGUS!$A$3, MATCH($A69, ARGUS!$A$3:$A$176, 0)-1,MATCH(EOMONTH(CO$15,1), ARGUS!$B$4:$LG$4, 0)-1,1,1)/1000, 0) -> 12.453 | CP69: =IFERROR(OFFSET(ARGUS!$A$3, MATCH($A69, ARGUS!$A$3:$A$176, 0)-1,MATCH(EOMONTH(CP$15,1), ARGUS!$B$4:$LG$4, 0)-1,1,1)/1000, 0) -> 12.453 | ... GT69: =IFERROR(OFFSET(ARGUS!$A$3, MATCH($A69, ARGUS!$A$3:$A$176, 0)-1,MATCH(EOMONTH(GT$15,1), ARGUS!$B$4:$LG$4, 0)-1,1,1)/1000, 0) -> 16.248 | HF69: x | HG69: =HG68+1 -> #REF! | HH69: =B69 -> Insurance | HL69: =SUM(HN69:HV69) -> 903.32331 | HN69: =SUMIF($K$14:$GT$14,HN$14,$K69:$GT69) -> 0 | HO69: =SUMIF($K$14:$GT$14,HO$14,$K69:$GT69) -> 90.6135 | HP69: =SUMIF($K$14:$GT$14,HP$14,$K69:$GT69) -> 93.8655 | HQ69: =SUMIF($K$14:$GT$14,HQ$14,$K69:$GT69) -> 82.65839 | HR69: =SUMIF($K$14:$GT$14,HR$14,$K69:$GT69) -> 94.53592 | HS69: =SUMIF($K$14:$GT$14,HS$14,$K69:$GT69) -> 124.35726 | HT69: =SUMIF($K$14:$GT$14,HT$14,$K69:$GT69) -> 142.0939 | HU69: =SUMIF($K$14:$GT$14,HU$14,$K69:$GT69) -> 123.52484 | HV69: =SUMIF($K$14:$GT$14,HV$14,$K69:$GT69) -> 151.674
A70: 11 | B70: Management Fee | I70: =SUMIF($K$13:$GT$13,"<="&Assumptions!$L$17,'Monthly Cash Flow'!K70:GT70) -> 715.50003 | L70: =Historicals!D18 -> 8.77858 | M70: =Historicals!E18 -> 5.19885 | N70: =Historicals!F18 -> 6.50919 | O70: =Historicals!G18 -> 30.78193 | P70: =Historicals!H18 -> 6.71635 | Q70: =Historicals!I18 -> -20.78193 | R70: =Historicals!J18 -> 6.40832 | S70: =Historicals!K18 -> 5.35588 | ... CH70: =Historicals!BZ18 -> 9.76567 | CI70: =IFERROR(OFFSET(ARGUS!$A$3, MATCH($A70, ARGUS!$A$3:$A$176, 0)-1,MATCH(EOMONTH(CI$15,1), ARGUS!$B$4:$LG$4, 0)-1,1,1)/1000, 0) -> 6.318 | CJ70: =IFERROR(OFFSET(ARGUS!$A$3, MATCH($A70, ARGUS!$A$3:$A$176, 0)-1,MATCH(EOMONTH(CJ$15,1), ARGUS!$B$4:$LG$4, 0)-1,1,1)/1000, 0) -> 7.022 | CK70: =IFERROR(OFFSET(ARGUS!$A$3, MATCH($A70, ARGUS!$A$3:$A$176, 0)-1,MATCH(EOMONTH(CK$15,1), ARGUS!$B$4:$LG$4, 0)-1,1,1)/1000, 0) -> 7.022 | CL70: =IFERROR(OFFSET(ARGUS!$A$3, MATCH($A70, ARGUS!$A$3:$A$176, 0)-1,MATCH(EOMONTH(CL$15,1), ARGUS!$B$4:$LG$4, 0)-1,1,1)/1000, 0) -> 7.137 | CM70: =IFERROR(OFFSET(ARGUS!$A$3, MATCH($A70, ARGUS!$A$3:$A$176, 0)-1,MATCH(EOMONTH(CM$15,1), ARGUS!$B$4:$LG$4, 0)-1,1,1)/1000, 0) -> 7.137 | CN70: =IFERROR(OFFSET(ARGUS!$A$3, MATCH($A70, ARGUS!$A$3:$A$176, 0)-1,MATCH(EOMONTH(CN$15,1), ARGUS!$B$4:$LG$4, 0)-1,1,1)/1000, 0) -> 7.15 | CO70: =IFERROR(OFFSET(ARGUS!$A$3, MATCH($A70, ARGUS!$A$3:$A$176, 0)-1,MATCH(EOMONTH(CO$15,1), ARGUS!$B$4:$LG$4, 0)-1,1,1)/1000, 0) -> 7.15 | CP70: =IFERROR(OFFSET(ARGUS!$A$3, MATCH($A70, ARGUS!$A$3:$A$176, 0)-1,MATCH(EOMONTH(CP$15,1), ARGUS!$B$4:$LG$4, 0)-1,1,1)/1000, 0) -> 7.466 | ... GT70: =IFERROR(OFFSET(ARGUS!$A$3, MATCH($A70, ARGUS!$A$3:$A$176, 0)-1,MATCH(EOMONTH(GT$15,1), ARGUS!$B$4:$LG$4, 0)-1,1,1)/1000, 0) -> 10.607 | HF70: x | HG70: =HG69+1 -> #REF! | HH70: =B70 -> Management Fee | HL70: =SUM(HN70:HV70) -> 658.98103 | HN70: =SUMIF($K$14:$GT$14,HN$14,$K70:$GT70) -> 0 | HO70: =SUMIF($K$14:$GT$14,HO$14,$K70:$GT70) -> 77.13635 | HP70: =SUMIF($K$14:$GT$14,HP$14,$K70:$GT70) -> 82.76229 | HQ70: =SUMIF($K$14:$GT$14,HQ$14,$K70:$GT70) -> 84.95558 | HR70: =SUMIF($K$14:$GT$14,HR$14,$K70:$GT70) -> 87.4742 | HS70: =SUMIF($K$14:$GT$14,HS$14,$K70:$GT70) -> 71.29041 | HT70: =SUMIF($K$14:$GT$14,HT$14,$K70:$GT70) -> 79.72953 | HU70: =SUMIF($K$14:$GT$14,HU$14,$K70:$GT70) -> 83.65967 | HV70: =SUMIF($K$14:$GT$14,HV$14,$K70:$GT70) -> 91.973
A71: 30 | B71: Parking | I71: =SUMIF($K$13:$GT$13,"<="&Assumptions!$L$17,'Monthly Cash Flow'!K71:GT71) -> 0 | L71: =Historicals!D19 -> 0 | M71: =Historicals!E19 -> 0 | N71: =Historicals!F19 -> 0 | O71: =Historicals!G19 -> 0 | P71: =Historicals!H19 -> 0 | Q71: =Historicals!I19 -> 0 | R71: =Historicals!J19 -> 0 | S71: =Historicals!K19 -> 0 | ... CH71: =Historicals!BZ19 -> 0 | CI71: =IFERROR(OFFSET(ARGUS!$A$3, MATCH($A71, ARGUS!$A$3:$A$176, 0)-1,MATCH(EOMONTH(CI$15,1), ARGUS!$B$4:$LG$4, 0)-1,1,1)/1000, 0) -> 0 | CJ71: =IFERROR(OFFSET(ARGUS!$A$3, MATCH($A71, ARGUS!$A$3:$A$176, 0)-1,MATCH(EOMONTH(CJ$15,1), ARGUS!$B$4:$LG$4, 0)-1,1,1)/1000, 0) -> 0 | CK71: =IFERROR(OFFSET(ARGUS!$A$3, MATCH($A71, ARGUS!$A$3:$A$176, 0)-1,MATCH(EOMONTH(CK$15,1), ARGUS!$B$4:$LG$4, 0)-1,1,1)/1000, 0) -> 0 | CL71: =IFERROR(OFFSET(ARGUS!$A$3, MATCH($A71, ARGUS!$A$3:$A$176, 0)-1,MATCH(EOMONTH(CL$15,1), ARGUS!$B$4:$LG$4, 0)-1,1,1)/1000, 0) -> 0 | CM71: =IFERROR(OFFSET(ARGUS!$A$3, MATCH($A71, ARGUS!$A$3:$A$176, 0)-1,MATCH(EOMONTH(CM$15,1), ARGUS!$B$4:$LG$4, 0)-1,1,1)/1000, 0) -> 0 | CN71: =IFERROR(OFFSET(ARGUS!$A$3, MATCH($A71, ARGUS!$A$3:$A$176, 0)-1,MATCH(EOMONTH(CN$15,1), ARGUS!$B$4:$LG$4, 0)-1,1,1)/1000, 0) -> 0 | CO71: =IFERROR(OFFSET(ARGUS!$A$3, MATCH($A71, ARGUS!$A$3:$A$176, 0)-1,MATCH(EOMONTH(CO$15,1), ARGUS!$B$4:$LG$4, 0)-1,1,1)/1000, 0) -> 0 | CP71: =IFERROR(OFFSET(ARGUS!$A$3, MATCH($A71, ARGUS!$A$3:$A$176, 0)-1,MATCH(EOMONTH(CP$15,1), ARGUS!$B$4:$LG$4, 0)-1,1,1)/1000, 0) -> 0 | ... GT71: =IFERROR(OFFSET(ARGUS!$A$3, MATCH($A71, ARGUS!$A$3:$A$176, 0)-1,MATCH(EOMONTH(GT$15,1), ARGUS!$B$4:$LG$4, 0)-1,1,1)/1000, 0) -> 0 | HF71: x | HG71: =HG70+1 -> #REF! | HH71: =B71 -> Parking | HL71: =SUM(HN71:HV71) -> 0 | HN71: =SUMIF($K$14:$GT$14,HN$14,$K71:$GT71) -> 0 | HO71: =SUMIF($K$14:$GT$14,HO$14,$K71:$GT71) -> 0 | HP71: =SUMIF($K$14:$GT$14,HP$14,$K71:$GT71) -> 0 | HQ71: =SUMIF($K$14:$GT$14,HQ$14,$K71:$GT71) -> 0 | HR71: =SUMIF($K$14:$GT$14,HR$14,$K71:$GT71) -> 0 | HS71: =SUMIF($K$14:$GT$14,HS$14,$K71:$GT71) -> 0 | HT71: =SUMIF($K$14:$GT$14,HT$14,$K71:$GT71) -> 0 | HU71: =SUMIF($K$14:$GT$14,HU$14,$K71:$GT71) -> 0 | HV71: =SUMIF($K$14:$GT$14,HV$14,$K71:$GT71) -> 0
A72: 12 | B72: Real Estate Taxes | I72: =SUMIF($K$13:$GT$13,"<="&Assumptions!$L$17,'Monthly Cash Flow'!K72:GT72) -> 3366.0597 | L72: =Historicals!D20 -> 30.8 | M72: =Historicals!E20 -> 30.8 | N72: =Historicals!F20 -> 30.8 | O72: =Historicals!G20 -> 46.12409 | P72: =Historicals!H20 -> 34.63102 | Q72: =Historicals!I20 -> -2.88902 | R72: =Historicals!J20 -> 31.56873 | S72: =Historicals!K20 -> 31.67909 | ... CH72: =Historicals!BZ20 -> 32.20887 | CI72: =IFERROR(OFFSET(ARGUS!$A$3, MATCH($A72, ARGUS!$A$3:$A$176, 0)-1,MATCH(EOMONTH(CI$15,1), ARGUS!$B$4:$LG$4, 0)-1,1,1)/1000, 0) -> 32.809 | CJ72: =IFERROR(OFFSET(ARGUS!$A$3, MATCH($A72, ARGUS!$A$3:$A$176, 0)-1,MATCH(EOMONTH(CJ$15,1), ARGUS!$B$4:$LG$4, 0)-1,1,1)/1000, 0) -> 32.809 | CK72: =IFERROR(OFFSET(ARGUS!$A$3, MATCH($A72, ARGUS!$A$3:$A$176, 0)-1,MATCH(EOMONTH(CK$15,1), ARGUS!$B$4:$LG$4, 0)-1,1,1)/1000, 0) -> 32.809 | CL72: =IFERROR(OFFSET(ARGUS!$A$3, MATCH($A72, ARGUS!$A$3:$A$176, 0)-1,MATCH(EOMONTH(CL$15,1), ARGUS!$B$4:$LG$4, 0)-1,1,1)/1000, 0) -> 33.793 | CM72: =IFERROR(OFFSET(ARGUS!$A$3, MATCH($A72, ARGUS!$A$3:$A$176, 0)-1,MATCH(EOMONTH(CM$15,1), ARGUS!$B$4:$LG$4, 0)-1,1,1)/1000, 0) -> 33.793 | CN72: =IFERROR(OFFSET(ARGUS!$A$3, MATCH($A72, ARGUS!$A$3:$A$176, 0)-1,MATCH(EOMONTH(CN$15,1), ARGUS!$B$4:$LG$4, 0)-1,1,1)/1000, 0) -> 33.793 | CO72: =IFERROR(OFFSET(ARGUS!$A$3, MATCH($A72, ARGUS!$A$3:$A$176, 0)-1,MATCH(EOMONTH(CO$15,1), ARGUS!$B$4:$LG$4, 0)-1,1,1)/1000, 0) -> 33.793 | CP72: =IFERROR(OFFSET(ARGUS!$A$3, MATCH($A72, ARGUS!$A$3:$A$176, 0)-1,MATCH(EOMONTH(CP$15,1), ARGUS!$B$4:$LG$4, 0)-1,1,1)/1000, 0) -> 33.793 | ... GT72: =IFERROR(OFFSET(ARGUS!$A$3, MATCH($A72, ARGUS!$A$3:$A$176, 0)-1,MATCH(EOMONTH(GT$15,1), ARGUS!$B$4:$LG$4, 0)-1,1,1)/1000, 0) -> 44.093 | HF72: x | HG72: =HG71+1 -> #REF! | HH72: =B72 -> Real Estate Taxes | HL72: =SUM(HN72:HV72) -> 3157.2177 | HN72: =SUMIF($K$14:$GT$14,HN$14,$K72:$GT72) -> 0 | HO72: =SUMIF($K$14:$GT$14,HO$14,$K72:$GT72) -> 352.31851 | HP72: =SUMIF($K$14:$GT$14,HP$14,$K72:$GT72) -> 400.92676 | HQ72: =SUMIF($K$14:$GT$14,HQ$14,$K72:$GT72) -> 401.72574 | HR72: =SUMIF($K$14:$GT$14,HR$14,$K72:$GT72) -> 385.1503 | HS72: =SUMIF($K$14:$GT$14,HS$14,$K72:$GT72) -> 400.62313 | HT72: =SUMIF($K$14:$GT$14,HT$14,$K72:$GT72) -> 395.53154 | HU72: =SUMIF($K$14:$GT$14,HU$14,$K72:$GT72) -> 409.3417 | HV72: =SUMIF($K$14:$GT$14,HV$14,$K72:$GT72) -> 411.6
HF73: x | HG73: =HG72+1 -> #REF!
A74: OpEx | B74: Total Operating Expenses | I74: =SUMIF($K$13:$GT$13,"<="&Assumptions!$L$17,'Monthly Cash Flow'!K74:GT74) -> 14432.523 | L74: =SUM(L65:L72) -> 115.59081 | M74: =SUM(M65:M72) -> 144.24526 | N74: =SUM(N65:N72) -> 124.63961 | O74: =SUM(O65:O72) -> 166.90174 | P74: =SUM(P65:P72) -> 107.83644 | Q74: =SUM(Q65:Q72) -> 126.94687 | R74: =SUM(R65:R72) -> 114.6332 | S74: =SUM(S65:S72) -> 103.62411 | ... GT74: =SUM(GT65:GT72) -> 196.084 | HF74: x | HG74: =HG73+1 -> #REF! | HH74: =B74 -> Total Operating Expenses | HL74: =SUM(HN74:HV74) -> 13495.042 | HN74: =SUMIF($K$14:$GT$14,HN$14,$K74:$GT74) -> 0 | HO74: =SUMIF($K$14:$GT$14,HO$14,$K74:$GT74) -> 1588.5911 | HP74: =SUMIF($K$14:$GT$14,HP$14,$K74:$GT74) -> 1562.0958 | HQ74: =SUMIF($K$14:$GT$14,HQ$14,$K74:$GT74) -> 1425.7339 | HR74: =SUMIF($K$14:$GT$14,HR$14,$K74:$GT74) -> 1581.2866 | HS74: =SUMIF($K$14:$GT$14,HS$14,$K74:$GT74) -> 1978.2159 | HT74: =SUMIF($K$14:$GT$14,HT$14,$K74:$GT74) -> 1771.2262 | HU74: =SUMIF($K$14:$GT$14,HU$14,$K74:$GT74) -> 1759.31 | HV74: =SUMIF($K$14:$GT$14,HV$14,$K74:$GT74) -> 1828.583
HF75: x | HG75: =HG74+1 -> #REF!
A76: NOI | B76: Net Operating Income | I76: =SUMIF($K$13:$GT$13,"<="&Assumptions!$L$17,'Monthly Cash Flow'!K76:GT76) -> 11582.533 | L76: =L62-L74 -> 58.58841 | M76: =M62-M74 -> 39.42486 | N76: =N62-N74 -> 62.16451 | O76: =O62-O74 -> 23.67331 | P76: =P62-P74 -> 69.42784 | Q76: =Q62-Q74 -> 53.22136 | R76: =R62-R74 -> 66.13957 | S76: =S62-S74 -> 136.2636 | ... GT76: =GT62-GT74 -> 228.18 | HF76: x | HG76: =HG75+1 -> #REF! | HH76: =B76 -> Net Operating Income | HL76: =SUM(HN76:HV76) -> 10259.224 | HN76: =SUMIF($K$14:$GT$14,HN$14,$K76:$GT76) -> 0 | HO76: =SUMIF($K$14:$GT$14,HO$14,$K76:$GT76) -> 839.71891 | HP76: =SUMIF($K$14:$GT$14,HP$14,$K76:$GT76) -> 969.41268 | HQ76: =SUMIF($K$14:$GT$14,HQ$14,$K76:$GT76) -> 1291.4156 | HR76: =SUMIF($K$14:$GT$14,HR$14,$K76:$GT76) -> 1445.5289 | HS76: =SUMIF($K$14:$GT$14,HS$14,$K76:$GT76) -> 742.84688 | HT76: =SUMIF($K$14:$GT$14,HT$14,$K76:$GT76) -> 1283.953 | HU76: =SUMIF($K$14:$GT$14,HU$14,$K76:$GT76) -> 1724.0593 | HV76: =SUMIF($K$14:$GT$14,HV$14,$K76:$GT76) -> 1962.289
B77: Argus Check | CI77: =CI76-(ARGUS!B42/1000) -> 9.679 | CJ77: =CJ76-(ARGUS!C42/1000) -> 9.679 | CK77: =CK76-(ARGUS!D42/1000) -> 9.679 | CL77: =CL76-(ARGUS!E42/1000) -> 9.68 | CM77: =CM76-(ARGUS!F42/1000) -> 9.68 | CN77: =CN76-(ARGUS!G42/1000) -> 9.679 | CO77: =CO76-(ARGUS!H42/1000) -> 9.679 | CP77: =CP76-(ARGUS!I42/1000) -> 9.679 | ... GT77: =GT76-(ARGUS!DM42/1000) -> -0.001 | HF77: x | HG77: =HG76+1 -> #REF!
HF78: x | HG78: =HG77+1 -> #REF!
B79: Total Potential NOI | I79: =SUMIF($K$13:$GT$13,"<="&Assumptions!$L$17,'Monthly Cash Flow'!K79:GT79) -> 11582.533 | L79: =+L76 -> 58.58841 | M79: =+M76 -> 39.42486 | N79: =+N76 -> 62.16451 | O79: =+O76 -> 23.67331 | P79: =+P76 -> 69.42784 | Q79: =+Q76 -> 53.22136 | R79: =+R76 -> 66.13957 | S79: =+S76 -> 136.2636 | ... GT79: =+GT76 -> 228.18 | HF79: x | HG79: =HG78+1 -> #REF! | HH79: =B79 -> Total Potential NOI | HL79: =SUM(HN79:HV79) -> 10259.224 | HN79: =SUMIF($K$14:$GT$14,HN$14,$K79:$GT79) -> 0 | HO79: =SUMIF($K$14:$GT$14,HO$14,$K79:$GT79) -> 839.71891 | HP79: =SUMIF($K$14:$GT$14,HP$14,$K79:$GT79) -> 969.41268 | HQ79: =SUMIF($K$14:$GT$14,HQ$14,$K79:$GT79) -> 1291.4156 | HR79: =SUMIF($K$14:$GT$14,HR$14,$K79:$GT79) -> 1445.5289 | HS79: =SUMIF($K$14:$GT$14,HS$14,$K79:$GT79) -> 742.84688 | HT79: =SUMIF($K$14:$GT$14,HT$14,$K79:$GT79) -> 1283.953 | HU79: =SUMIF($K$14:$GT$14,HU$14,$K79:$GT79) -> 1724.0593 | HV79: =SUMIF($K$14:$GT$14,HV$14,$K79:$GT79) -> 1962.289
B80: Total Actual NOI | I80: =SUMIF($K$13:$GT$13,"<="&Assumptions!$L$17,'Monthly Cash Flow'!K80:GT80) -> 11582.533 | L80: =IF(L13<=Assumptions!$L$17,'Monthly Cash Flow'!L79,0) -> 58.58841 | M80: =IF(M13<=Assumptions!$L$17,'Monthly Cash Flow'!M79,0) -> 39.42486 | N80: =IF(N13<=Assumptions!$L$17,'Monthly Cash Flow'!N79,0) -> 62.16451 | O80: =IF(O13<=Assumptions!$L$17,'Monthly Cash Flow'!O79,0) -> 23.67331 | P80: =IF(P13<=Assumptions!$L$17,'Monthly Cash Flow'!P79,0) -> 69.42784 | Q80: =IF(Q13<=Assumptions!$L$17,'Monthly Cash Flow'!Q79,0) -> 53.22136 | R80: =IF(R13<=Assumptions!$L$17,'Monthly Cash Flow'!R79,0) -> 66.13957 | S80: =IF(S13<=Assumptions!$L$17,'Monthly Cash Flow'!S79,0) -> 136.2636 | ... GT80: =IF(GT13<=Assumptions!$L$17,'Monthly Cash Flow'!GT79,0) -> 0 | HF80: x | HG80: =HG79+1 -> #REF! | HH80: =B80 -> Total Actual NOI | HL80: =SUM(HN80:HV80) -> 10259.224 | HN80: =SUMIF($K$14:$GT$14,HN$14,$K80:$GT80) -> 0 | HO80: =SUMIF($K$14:$GT$14,HO$14,$K80:$GT80) -> 839.71891 | HP80: =SUMIF($K$14:$GT$14,HP$14,$K80:$GT80) -> 969.41268 | HQ80: =SUMIF($K$14:$GT$14,HQ$14,$K80:$GT80) -> 1291.4156 | HR80: =SUMIF($K$14:$GT$14,HR$14,$K80:$GT80) -> 1445.5289 | HS80: =SUMIF($K$14:$GT$14,HS$14,$K80:$GT80) -> 742.84688 | HT80: =SUMIF($K$14:$GT$14,HT$14,$K80:$GT80) -> 1283.953 | HU80: =SUMIF($K$14:$GT$14,HU$14,$K80:$GT80) -> 1724.0593 | HV80: =SUMIF($K$14:$GT$14,HV$14,$K80:$GT80) -> 1962.289
B81: Return on Cost | L81: =IF(L$13>12,SUM(OFFSET(L$79,0,0,1,-12))/SUM($J87:L87),0) -> 0 | M81: =IF(M$13>12,SUM(OFFSET(M$79,0,0,1,-12))/SUM($J87:M87),0) -> 0 | N81: =IF(N$13>12,SUM(OFFSET(N$79,0,0,1,-12))/SUM($J87:N87),0) -> 0 | O81: =IF(O$13>12,SUM(OFFSET(O$79,0,0,1,-12))/SUM($J87:O87),0) -> 0 | P81: =IF(P$13>12,SUM(OFFSET(P$79,0,0,1,-12))/SUM($J87:P87),0) -> 0 | Q81: =IF(Q$13>12,SUM(OFFSET(Q$79,0,0,1,-12))/SUM($J87:Q87),0) -> 0 | R81: =IF(R$13>12,SUM(OFFSET(R$79,0,0,1,-12))/SUM($J87:R87),0) -> 0 | S81: =IF(S$13>12,SUM(OFFSET(S$79,0,0,1,-12))/SUM($J87:S87),0) -> 0 | ... GT81: =IF(GT$13>12,SUM(OFFSET(GT$79,0,0,1,-12))/SUM($J87:GT87),0) -> 0.072482033 | HF81: x | HG81: =HG80+1 -> #REF! | HH81: =B81 -> Return on Cost | HN81: =SUMIF($K$14:$GT$14,HN$14,$K81:$GT81) -> 0 | HO81: =SUMIF($K$14:$GT$14,HO$14,$K81:$GT81) -> 0 | HP81: =SUMIF($K$14:$GT$14,HP$14,$K81:$GT81) -> 0.33691383 | HQ81: =SUMIF($K$14:$GT$14,HQ$14,$K81:$GT81) -> 0.41661 | HR81: =SUMIF($K$14:$GT$14,HR$14,$K81:$GT81) -> 0.50927042 | HS81: =SUMIF($K$14:$GT$14,HS$14,$K81:$GT81) -> 0.34440668 | HT81: =SUMIF($K$14:$GT$14,HT$14,$K81:$GT81) -> 0.40233432 | HU81: =SUMIF($K$14:$GT$14,HU$14,$K81:$GT81) -> 0.53094602 | HV81: =SUMIF($K$14:$GT$14,HV$14,$K81:$GT81) -> 0.61347455
B82: NOI With Free Rent | K82: =+K79-K56 -> 0 | L82: =+L79-L56 -> 58.58841 | M82: =+M79-M56 -> 39.42486 | N82: =+N79-N56 -> 62.16451 | O82: =+O79-O56 -> 23.67331 | P82: =+P79-P56 -> 69.42784 | Q82: =+Q79-Q56 -> 53.22136 | R82: =+R79-R56 -> 66.13957 | ... GT82: =+GT79-GT56 -> 228.18 | HF82: x | HG82: =HG81+1 -> #REF! | HH82: =B82 -> NOI With Free Rent
B83: Delta | K83: =K79-K82 -> 0 | L83: =L79-L82 -> 0 | M83: =M79-M82 -> 0 | N83: =N79-N82 -> 0 | O83: =O79-O82 -> 0 | P83: =P79-P82 -> 0 | Q83: =Q79-Q82 -> 0 | R83: =R79-R82 -> 0 | ... GT83: =GT79-GT82 -> 0 | HF83: x | HG83: =HG82+1 -> #REF!
HF84: x | HG84: =HG83+1 -> #REF!
B85: Net Exit Proceeds | I85: =SUMIF($K$13:$GT$13,"<="&Assumptions!$L$17,'Monthly Cash Flow'!K85:GT85) -> 53235.704 | K85: =IF(K$13=Assumptions!$L$20,Assumptions!$L$31,0) -> 0 | L85: =IF(L$13=Assumptions!$L$20,Assumptions!$L$31,0) -> 0 | M85: =IF(M$13=Assumptions!$L$20,Assumptions!$L$31,0) -> 0 | N85: =IF(N$13=Assumptions!$L$20,Assumptions!$L$31,0) -> 0 | O85: =IF(O$13=Assumptions!$L$20,Assumptions!$L$31,0) -> 0 | P85: =IF(P$13=Assumptions!$L$20,Assumptions!$L$31,0) -> 0 | Q85: =IF(Q$13=Assumptions!$L$20,Assumptions!$L$31,0) -> 0 | R85: =IF(R$13=Assumptions!$L$20,Assumptions!$L$31,0) -> 0 | ... CJ85: =IF(CJ$13=Assumptions!$L$20,Assumptions!$L$31,0) -> 0 | CK85: =(IF(CK$13=Assumptions!$L$20,Assumptions!$L$31,0)) -> 0 | CL85: =IF(CL$13=Assumptions!$L$20,Assumptions!$L$31,0) -> 0 | CM85: =IF(CM$13=Assumptions!$L$20,Assumptions!$L$31,0) -> 0 | CN85: =IF(CN$13=Assumptions!$L$20,Assumptions!$L$31,0) -> 0 | CO85: =IF(CO$13=Assumptions!$L$20,Assumptions!$L$31,0) -> 0 | CP85: =IF(CP$13=Assumptions!$L$20,Assumptions!$L$31,0) -> 0 | CQ85: =IF(CQ$13=Assumptions!$L$20,Assumptions!$L$31,0) -> 0 | CR85: =IF(CR$13=Assumptions!$L$20,Assumptions!$L$31,0) -> 0 | CS85: =IF(CS$13=Assumptions!$L$20,Assumptions!$L$31,0) -> 0 | ... GT85: =IF(GT$13=Assumptions!$L$20,Assumptions!$L$31,0) -> 0 | HF85: x | HG85: =HG84+1 -> #REF! | HH85: =B85 -> Net Exit Proceeds | HL85: =SUM(HN85:HV85) -> 0 | HN85: =SUMIF($K$14:$GT$14,HN$14,$K85:$GT85) -> 0 | HO85: =SUMIF($K$14:$GT$14,HO$14,$K85:$GT85) -> 0 | HP85: =SUMIF($K$14:$GT$14,HP$14,$K85:$GT85) -> 0 | HQ85: =SUMIF($K$14:$GT$14,HQ$14,$K85:$GT85) -> 0 | HR85: =SUMIF($K$14:$GT$14,HR$14,$K85:$GT85) -> 0 | HS85: =SUMIF($K$14:$GT$14,HS$14,$K85:$GT85) -> 0 | HT85: =SUMIF($K$14:$GT$14,HT$14,$K85:$GT85) -> 0 | HU85: =SUMIF($K$14:$GT$14,HU$14,$K85:$GT85) -> 0 | HV85: =SUMIF($K$14:$GT$14,HV$14,$K85:$GT85) -> 0
HF86: x | HG86: =HG85+1 -> #REF!
B87: Unleveraged Costs | I87: =SUMIF($K$13:$GT$13,"<="&Assumptions!$L$17,'Monthly Cash Flow'!K87:GT87) -> 37036.572 | K87: =IF(K$13<=Assumptions!$L$17,'Monthly Cash Flow'!K41,0) -> 30206 | L87: =IF(L$13<=Assumptions!$L$17,'Monthly Cash Flow'!L41,0) -> 0 | M87: =IF(M$13<=Assumptions!$L$17,'Monthly Cash Flow'!M41,0) -> 0 | N87: =IF(N$13<=Assumptions!$L$17,'Monthly Cash Flow'!N41,0) -> 0 | O87: =IF(O$13<=Assumptions!$L$17,'Monthly Cash Flow'!O41,0) -> 0 | P87: =IF(P$13<=Assumptions!$L$17,'Monthly Cash Flow'!P41,0) -> 0 | Q87: =IF(Q$13<=Assumptions!$L$17,'Monthly Cash Flow'!Q41,0) -> 0 | R87: =IF(R$13<=Assumptions!$L$17,'Monthly Cash Flow'!R41,0) -> 0 | ... GT87: =IF(GT$13<=Assumptions!$L$17,'Monthly Cash Flow'!GT41,0) -> 0 | HF87: x | HG87: =HG86+1 -> #REF! | HH87: =B87 -> Unleveraged Costs | HL87: =SUM(HN87:HV87) -> 37036.572 | HN87: =SUMIF($K$14:$GT$14,HN$14,$K87:$GT87) -> 30206 | HO87: =SUMIF($K$14:$GT$14,HO$14,$K87:$GT87) -> 293.74533 | HP87: =SUMIF($K$14:$GT$14,HP$14,$K87:$GT87) -> 1970.3778 | HQ87: =SUMIF($K$14:$GT$14,HQ$14,$K87:$GT87) -> 452.06821 | HR87: =SUMIF($K$14:$GT$14,HR$14,$K87:$GT87) -> 697.14046 | HS87: =SUMIF($K$14:$GT$14,HS$14,$K87:$GT87) -> 65.924 | HT87: =SUMIF($K$14:$GT$14,HT$14,$K87:$GT87) -> 507.9623 | HU87: =SUMIF($K$14:$GT$14,HU$14,$K87:$GT87) -> 517.46289 | HV87: =SUMIF($K$14:$GT$14,HV$14,$K87:$GT87) -> 2325.8905
B88: Operating Losses | I88: =SUMIF($K$13:$GT$13,"<="&Assumptions!$L$17,'Monthly Cash Flow'!K88:GT88) -> 499.20616 | K88: =-MIN(K80,0) -> 0 | L88: =-MIN(L80,0) -> 0 | M88: =-MIN(M80,0) -> 0 | N88: =-MIN(N80,0) -> 0 | O88: =-MIN(O80,0) -> 0 | P88: =-MIN(P80,0) -> 0 | Q88: =-MIN(Q80,0) -> 0 | R88: =-MIN(R80,0) -> 0 | ... GT88: =-MIN(GT80,0) -> 0 | HF88: x | HG88: =HG87+1 -> #REF! | HH88: =B88 -> Operating Losses | HN88: =SUMIF($K$14:$GT$14,HN$14,$K88:$GT88) -> 0 | HO88: =SUMIF($K$14:$GT$14,HO$14,$K88:$GT88) -> 129.80023 | HP88: =SUMIF($K$14:$GT$14,HP$14,$K88:$GT88) -> 5.03171 | HQ88: =SUMIF($K$14:$GT$14,HQ$14,$K88:$GT88) -> 0 | HR88: =SUMIF($K$14:$GT$14,HR$14,$K88:$GT88) -> 0 | HS88: =SUMIF($K$14:$GT$14,HS$14,$K88:$GT88) -> 364.37422 | HT88: =SUMIF($K$14:$GT$14,HT$14,$K88:$GT88) -> 0 | HU88: =SUMIF($K$14:$GT$14,HU$14,$K88:$GT88) -> 0 | HV88: =SUMIF($K$14:$GT$14,HV$14,$K88:$GT88) -> 0
B89: Less Cash Flow from Operations | I89: =SUMIF($K$13:$GT$13,"<="&Assumptions!$L$17,'Monthly Cash Flow'!K89:GT89) -> -33515.043 | K89: =-MAX(MIN(K87,K80),0) -> -30206 | L89: =-MAX(MIN(L87,L80),0) -> 0 | M89: =-MAX(MIN(M87,M80),0) -> 0 | N89: =-MAX(MIN(N87,N80),0) -> 0 | O89: =-MAX(MIN(O87,O80),0) -> 0 | P89: =-MAX(MIN(P87,P80),0) -> 0 | Q89: =-MAX(MIN(Q87,Q80),0) -> 0 | R89: =-MAX(MIN(R87,R80),0) -> 0 | ... GT89: =-MAX(MIN(GT87,GT80),0) -> 0 | HF89: x | HG89: =HG88+1 -> #REF! | HH89: =B89 -> Less Cash Flow from Operations | HL89: =SUM(HN89:HV89) -> -33515.043 | HN89: =SUMIF($K$14:$GT$14,HN$14,$K89:$GT89) -> -30206 | HO89: =SUMIF($K$14:$GT$14,HO$14,$K89:$GT89) -> -154.67081 | HP89: =SUMIF($K$14:$GT$14,HP$14,$K89:$GT89) -> -506.63946 | HQ89: =SUMIF($K$14:$GT$14,HQ$14,$K89:$GT89) -> -309.22237 | HR89: =SUMIF($K$14:$GT$14,HR$14,$K89:$GT89) -> -441.12438 | HS89: =SUMIF($K$14:$GT$14,HS$14,$K89:$GT89) -> -59.42177 | HT89: =SUMIF($K$14:$GT$14,HT$14,$K89:$GT89) -> -242.13566 | HU89: =SUMIF($K$14:$GT$14,HU$14,$K89:$GT89) -> -514.4964 | HV89: =SUMIF($K$14:$GT$14,HV$14,$K89:$GT89) -> -1081.3323
B90: Unleveraged Equity Investment | I90: =SUMIF($K$13:$GT$13,"<="&Assumptions!$L$17,'Monthly Cash Flow'!K90:GT90) -> 4020.7345 | K90: =SUM(K87:K89) -> 0 | L90: =SUM(L87:L89) -> 0 | M90: =SUM(M87:M89) -> 0 | N90: =SUM(N87:N89) -> 0 | O90: =SUM(O87:O89) -> 0 | P90: =SUM(P87:P89) -> 0 | Q90: =SUM(Q87:Q89) -> 0 | R90: =SUM(R87:R89) -> 0 | ... GT90: =SUM(GT87:GT89) -> 0 | HF90: x | HG90: =HG89+1 -> #REF! | HH90: =B90 -> Unleveraged Equity Investment | HL90: =SUM(HN90:HV90) -> 4020.7345 | HN90: =SUMIF($K$14:$GT$14,HN$14,$K90:$GT90) -> 0 | HO90: =SUMIF($K$14:$GT$14,HO$14,$K90:$GT90) -> 268.87475 | HP90: =SUMIF($K$14:$GT$14,HP$14,$K90:$GT90) -> 1468.77 | HQ90: =SUMIF($K$14:$GT$14,HQ$14,$K90:$GT90) -> 142.84584 | HR90: =SUMIF($K$14:$GT$14,HR$14,$K90:$GT90) -> 256.01608 | HS90: =SUMIF($K$14:$GT$14,HS$14,$K90:$GT90) -> 370.87645 | HT90: =SUMIF($K$14:$GT$14,HT$14,$K90:$GT90) -> 265.82664 | HU90: =SUMIF($K$14:$GT$14,HU$14,$K90:$GT90) -> 2.9664921 | HV90: =SUMIF($K$14:$GT$14,HV$14,$K90:$GT90) -> 1244.5583
I91: =SUMIF($K$13:$GT$13,"<="&Assumptions!$L$17,'Monthly Cash Flow'!K91:GT91) -> -7075.7777 | L91: =-SUM(L85:L89,L80) -> -58.58841 | M91: =-SUM(M85:M89,M80) -> -39.42486 | N91: =-SUM(N85:N89,N80) -> -62.16451 | O91: =-SUM(O85:O89,O80) -> -23.67331 | P91: =-SUM(P85:P89,P80) -> -69.42784 | Q91: =-SUM(Q85:Q89,Q80) -> -53.22136 | R91: =-SUM(R85:R89,R80) -> -66.13957 | S91: =-SUM(S85:S89,S80) -> -136.2636 | ... BK91: =-SUM(BK85:BK89,BK80) -> -147.14487 | HF91: x | HG91: =HG90+1 -> #REF! | HL91: =SUM(HN91:HV91) -> -7075.7777 | HN91: =SUMIF($K$14:$GT$14,HN$14,$K91:$GT91) -> 0 | HO91: =SUMIF($K$14:$GT$14,HO$14,$K91:$GT91) -> -1108.5937 | HP91: =SUMIF($K$14:$GT$14,HP$14,$K91:$GT91) -> -2438.1827 | HQ91: =SUMIF($K$14:$GT$14,HQ$14,$K91:$GT91) -> -1434.2614 | HR91: =SUMIF($K$14:$GT$14,HR$14,$K91:$GT91) -> -1701.545 | HS91: =SUMIF($K$14:$GT$14,HS$14,$K91:$GT91) -> -393.19498 | HT91: =SUMIF($K$14:$GT$14,HT$14,$K91:$GT91) -> 0 | HU91: =SUMIF($K$14:$GT$14,HU$14,$K91:$GT91) -> 0 | HV91: =SUMIF($K$14:$GT$14,HV$14,$K91:$GT91) -> 0
B92: Unleveraged Cash Flow | I92: =SUMIF($K$13:$GT$13,"<="&Assumptions!$L$17,'Monthly Cash Flow'!K92:GT92) -> 20705.888 | K92: =-K41+K80+K85 -> -30206 | L92: =-L41+L80+L85+L91 -> 0 | M92: =-M41+M80+M85+M91 -> 0 | N92: =-N41+N80+N85+N91 -> 0 | O92: =-O41+O80+O85+O91 -> 0 | P92: =-P41+P80+P85+P91 -> 0 | Q92: =-Q41+Q80+Q85+Q91 -> 0 | R92: =-R41+R80+R85+R91 -> 0 | S92: =-S41+S80+S85+S91 -> 0 | ... BK92: =-BK41+BK80+BK85+BK91 -> 0 | BL92: =-BL41+BL80+BL85 -> 112.02142 | BM92: =-BM41+BM80+BM85 -> 9.83114 | BN92: =-BN41+BN80+BN85 -> 105.67253 | BO92: =-BO41+BO80+BO85 -> 107.25182 | BP92: =-BP41+BP80+BP85 -> 19.22065 | BQ92: =-BQ41+BQ80+BQ85 -> 112.327 | BR92: =-BR41+BR80+BR85 -> -6.50223 | BS92: =-BS41+BS80+BS85 -> 188.27979 | ... GT92: =-GT41+GT80+GT85 -> 0 | HF92: x | HG92: =HG91+1 -> #REF! | HH92: =B92 -> Unleveraged Cash Flow | HL92: =SUM(HN92:HV92) -> -33853.125 | HN92: =SUMIF($K$14:$GT$14,HN$14,$K92:$GT92) -> -30206 | HO92: =SUMIF($K$14:$GT$14,HO$14,$K92:$GT92) -> -562.62008 | HP92: =SUMIF($K$14:$GT$14,HP$14,$K92:$GT92) -> -3439.1478 | HQ92: =SUMIF($K$14:$GT$14,HQ$14,$K92:$GT92) -> -594.91406 | HR92: =SUMIF($K$14:$GT$14,HR$14,$K92:$GT92) -> -953.15654 | HS92: =SUMIF($K$14:$GT$14,HS$14,$K92:$GT92) -> 283.7279 | HT92: =SUMIF($K$14:$GT$14,HT$14,$K92:$GT92) -> 775.99072 | HU92: =SUMIF($K$14:$GT$14,HU$14,$K92:$GT92) -> 1206.5964 | HV92: =SUMIF($K$14:$GT$14,HV$14,$K92:$GT92) -> -363.60154
B93: Profit | I93: =I92 -> 20705.888 | HF93: x | HH93: =B93 -> Profit | HL93: =HL92 -> -33853.125
B94: Investment | I94: =-SUMIF(K92:GT92,"<0") -> 37647.066 | HF94: x | HH94: =B94 -> Investment | HL94: =-SUMIF(HN92:HV92,"<0") -> 36119.44
B95: Multiple | I95: =I93/I94+1 -> 1.55 | HF95: x | HH95: =B95 -> Multiple | HL95: =HL93/HL94+1 -> 0.062745021
B96: IRR | I96: =XIRR(K92:GT92,$K$15:$GT$15) -> 0.057904282 | HF96: x | HH96: =B96 -> IRR | HL96: =I96 -> 0.057904282
HF97: x
B98: Leverage Cash Flows | HF98: x | HH98: =B98 -> Leverage Cash Flows
HF99: x
B100: NOI | I100: =SUMIF($K$13:$GT$13,"<="&Assumptions!$L$17,'Monthly Cash Flow'!K100:GT100) -> 12081.739 | K100: =MAX(0,K80) -> 0 | L100: =MAX(0,L80) -> 58.58841 | M100: =MAX(0,M80) -> 39.42486 | N100: =MAX(0,N80) -> 62.16451 | O100: =MAX(0,O80) -> 23.67331 | P100: =MAX(0,P80) -> 69.42784 | Q100: =MAX(0,Q80) -> 53.22136 | R100: =MAX(0,R80) -> 66.13957 | ... GC100: =MAX(0,GC80) -> 0 | GP100: =MAX(0,GP80) -> 0 | GQ100: =MAX(0,GQ80) -> 0 | GR100: =MAX(0,GR80) -> 0 | GS100: =MAX(0,GS80) -> 0 | GT100: =MAX(0,GT80) -> 0 | HF100: x | HH100: =B100 -> NOI | HL100: =SUM(HN100:HV100) -> 10758.43 | HN100: =SUMIF($K$14:$GT$14,HN$14,$K100:$GT100) -> 0 | HO100: =SUMIF($K$14:$GT$14,HO$14,$K100:$GT100) -> 969.51914 | HP100: =SUMIF($K$14:$GT$14,HP$14,$K100:$GT100) -> 974.44439 | HQ100: =SUMIF($K$14:$GT$14,HQ$14,$K100:$GT100) -> 1291.4156 | HR100: =SUMIF($K$14:$GT$14,HR$14,$K100:$GT100) -> 1445.5289 | HS100: =SUMIF($K$14:$GT$14,HS$14,$K100:$GT100) -> 1107.2211 | HT100: =SUMIF($K$14:$GT$14,HT$14,$K100:$GT100) -> 1283.953 | HU100: =SUMIF($K$14:$GT$14,HU$14,$K100:$GT100) -> 1724.0593 | HV100: =SUMIF($K$14:$GT$14,HV$14,$K100:$GT100) -> 1962.289
B101: Replacement Reserves | I101: =SUMIF($K$13:$GT$13,"<="&Assumptions!$L$17,'Monthly Cash Flow'!K101:GT101) -> 0 | K101: 0 | L101: =L39 -> 0 | M101: =M39 -> 0 | N101: =N39 -> 0 | O101: =O39 -> 0 | P101: =P39 -> 0 | Q101: =Q39 -> 0 | R101: =R39 -> 0 | S101: =S39 -> 0 | ... GC101: =GC39 -> 0 | GP101: =GP39 -> 0 | GQ101: =GQ39 -> 0 | GR101: =GR39 -> 0 | GS101: =GS39 -> 0 | GT101: =GT39 -> 0 | HF101: x
B102: Less Debt Service | I102: =SUMIF($K$13:$GT$13,"<="&Assumptions!$L$17,'Monthly Cash Flow'!K102:GT102) -> -12580.977 | K102: =-MIN(K100,K148) -> 0 | L102: =+L182+L183 -> -99.81788 | M102: =+M182+M183 -> -107.07263 | N102: =+N182+N183 -> -93.75655 | O102: =+O182+O183 -> -97.47707 | P102: =+P182+P183 -> -93.8024 | Q102: =+Q182+Q183 -> -97.24742 | R102: =+R182+R183 -> -97.71427 | S102: =+S182+S183 -> -94.31804 | ... GC102: =+GC182+GC183 -> 0 | GP102: =+GP182+GP183 -> 0 | GQ102: =+GQ182+GQ183 -> 0 | GR102: =+GR182+GR183 -> 0 | GS102: =+GS182+GS183 -> 0 | GT102: =+GT182+GT183 -> 0 | HF102: x | HH102: =B102 -> Less Debt Service | HL102: =SUM(HN102:HV102) -> -11617.079 | HN102: =SUMIF($K$14:$GT$14,HN$14,$K102:$GT102) -> 0 | HO102: =SUMIF($K$14:$GT$14,HO$14,$K102:$GT102) -> -1191.4756 | HP102: =SUMIF($K$14:$GT$14,HP$14,$K102:$GT102) -> -1425.4419 | HQ102: =SUMIF($K$14:$GT$14,HQ$14,$K102:$GT102) -> -1730.8324 | HR102: =SUMIF($K$14:$GT$14,HR$14,$K102:$GT102) -> -1528.2517 | HS102: =SUMIF($K$14:$GT$14,HS$14,$K102:$GT102) -> -1273.8617 | HT102: =SUMIF($K$14:$GT$14,HT$14,$K102:$GT102) -> -1200.9664 | HU102: =SUMIF($K$14:$GT$14,HU$14,$K102:$GT102) -> -1473.2061 | HV102: =SUMIF($K$14:$GT$14,HV$14,$K102:$GT102) -> -1793.0433
B103: Cash Flow After Debt Service | I103: =SUMIF($K$13:$GT$13,"<="&Assumptions!$L$17,'Monthly Cash Flow'!K103:GT103) -> -499.23713 | K103: =SUM(K100:K102) -> 0 | L103: =SUM(L100:L102) -> -41.22947 | M103: =SUM(M100:M102) -> -67.64777 | N103: =SUM(N100:N102) -> -31.59204 | O103: =SUM(O100:O102) -> -73.80376 | P103: =SUM(P100:P102) -> -24.37456 | Q103: =SUM(Q100:Q102) -> -44.02606 | R103: =SUM(R100:R102) -> -31.5747 | ... GC103: =SUM(GC100:GC102) -> 0 | GP103: =SUM(GP100:GP102) -> 0 | GQ103: =SUM(GQ100:GQ102) -> 0 | GR103: =SUM(GR100:GR102) -> 0 | GS103: =SUM(GS100:GS102) -> 0 | GT103: =SUM(GT100:GT102) -> 0 | HF103: x | HH103: =B103 -> Cash Flow After Debt Service | HL103: =SUM(HN103:HV103) -> -858.64848 | HN103: =SUMIF($K$14:$GT$14,HN$14,$K103:$GT103) -> 0 | HO103: =SUMIF($K$14:$GT$14,HO$14,$K103:$GT103) -> -221.95646 | HP103: =SUMIF($K$14:$GT$14,HP$14,$K103:$GT103) -> -450.99746 | HQ103: =SUMIF($K$14:$GT$14,HQ$14,$K103:$GT103) -> -439.41681 | HR103: =SUMIF($K$14:$GT$14,HR$14,$K103:$GT103) -> -82.72277 | HS103: =SUMIF($K$14:$GT$14,HS$14,$K103:$GT103) -> -166.64056 | HT103: =SUMIF($K$14:$GT$14,HT$14,$K103:$GT103) -> 82.98662 | HU103: =SUMIF($K$14:$GT$14,HU$14,$K103:$GT103) -> 250.85323 | HV103: =SUMIF($K$14:$GT$14,HV$14,$K103:$GT103) -> 169.24573
...

Sheet Historicals
AT1: Linked to 2020 Sheet
C2: Historicals | D2: 42582 | E2: =EOMONTH(D2,1) -> 42613 | F2: =EOMONTH(E2,1) -> 42643 | G2: =EOMONTH(F2,1) -> 42674 | H2: =EOMONTH(G2,1) -> 42704 | I2: =EOMONTH(H2,1) -> 42735 | J2: =EOMONTH(I2,1) -> 42766 | K2: =EOMONTH(J2,1) -> 42794 | L2: =EOMONTH(K2,1) -> 42825 | ... BZ2: =EOMONTH(BY2,1) -> 44834
B3: PGR | C3: Potential Base Rent | D3: =SUMIF($A$32:$A$268,$B3,D$32:D$268)/1000-D5 -> 111.19469 | E3: =SUMIF($A$32:$A$268,$B3,E$32:E$268)/1000-E5 -> 112.08559 | F3: =SUMIF($A$32:$A$268,$B3,F$32:F$268)/1000-F5 -> 116.37649 | G3: =SUMIF($A$32:$A$268,$B3,G$32:G$268)/1000-G5 -> 111.89584 | H3: =SUMIF($A$32:$A$268,$B3,H$32:H$268)/1000-H5 -> 111.72 | I3: =SUMIF($A$32:$A$268,$B3,I$32:I$268)/1000-I5 -> 109.71383 | J3: =SUMIF($A$32:$A$268,$B3,J$32:J$268)/1000-J5 -> 107.67871 | K3: =SUMIF($A$32:$A$268,$B3,K$32:K$268)/1000-K5 -> 102.30149 | ... AS3: =SUMIF($A$32:$A$268,$B3,AS$32:AS$268)/1000-AS5 -> 157.90381 | AT3: =SUMIF('2020'!$A:$A,$B3,'2020'!D:D)/1000 -> 175.36307 | AU3: =SUMIF('2020'!$A:$A,$B3,'2020'!E:E)/1000 -> 131.34564 | AV3: =SUMIF('2020'!$A:$A,$B3,'2020'!F:F)/1000 -> 153.98707 | AW3: =SUMIF('2020'!$A:$A,$B3,'2020'!G:G)/1000 -> 153.98707 | AX3: =SUMIF('2020'!$A:$A,$B3,'2020'!H:H)/1000 -> 159.50756 | AY3: =SUMIF('2020'!$A:$A,$B3,'2020'!I:I)/1000 -> 146.71283 | AZ3: =SUMIF('2020'!$A:$A,$B3,'2020'!J:J)/1000 -> 146.71283 | BA3: =SUMIF('2020'!$A:$A,$B3,'2020'!K:K)/1000 -> 147.72592 | BB3: =SUMIF('2020'!$A:$A,$B3,'2020'!L:L)/1000 -> 147.91536 | BC3: =SUMIF('2020'!$A:$A,$B3,'2020'!M:M)/1000 -> 148.23485 | BD3: =SUMIF('2020'!$A:$A,$B3,'2020'!N:N)/1000 -> 155.6739 | BE3: =SUMIF('2020'!$A:$A,$B3,'2020'!O:O)/1000 -> 156.29788 | BF3: =SUMIF('2021'!$A:$A,$B3,'2021'!D:D)/1000 -> 136.86797 | BG3: =SUMIF('2021'!$A:$A,$B3,'2021'!E:E)/1000 -> 136.86797 | BH3: =SUMIF('2021'!$A:$A,$B3,'2021'!F:F)/1000 -> 72.60166 | BI3: =SUMIF('2021'!$A:$A,$B3,'2021'!G:G)/1000 -> 137.33262 | BJ3: =SUMIF('2021'!$A:$A,$B3,'2021'!H:H)/1000 -> 137.51862 | BK3: =SUMIF('2021'!$A:$A,$B3,'2021'!I:I)/1000 -> 137.85316 | BL3: =SUMIF('2021'!$A:$A,$B3,'2021'!J:J)/1000 -> 137.85316 | BM3: =SUMIF('2021'!$A:$A,$B3,'2021'!K:K)/1000 -> 150.18858 | BN3: =SUMIF('2021'!$A:$A,$B3,'2021'!L:L)/1000 -> 141.49274 | BO3: =SUMIF('2021'!$A:$A,$B3,'2021'!M:M)/1000 -> 150.82108 | BP3: =SUMIF('2021'!$A:$A,$B3,'2021'!N:N)/1000 -> 150.82108 | BQ3: =SUMIF('2021'!$A:$A,$B3,'2021'!O:O)/1000 -> 157.57866 | BR3: =SUMIF('2022'!$A:$A,$B3,'2022'!D:D)/1000 -> 151.35253 | BS3: =SUMIF('2022'!$A:$A,$B3,'2022'!E:E)/1000 -> 153.53873 | BT3: =SUMIF('2022'!$A:$A,$B3,'2022'!F:F)/1000 -> 154.08808 | BU3: =SUMIF('2022'!$A:$A,$B3,'2022'!G:G)/1000 -> 146.24198 | BV3: =SUMIF('2022'!$A:$A,$B3,'2022'!H:H)/1000 -> 155.41321 | BW3: =SUMIF('2022'!$A:$A,$B3,'2022'!I:I)/1000 -> 155.79179 | BX3: =SUMIF('2022'!$A:$A,$B3,'2022'!J:J)/1000 -> 156.28437 | BY3: =SUMIF('2022'!$A:$A,$B3,'2022'!K:K)/1000 -> 157.38013 | BZ3: =SUMIF('2022'!$A:$A,$B3,'2022'!L:L)/1000 -> 160.54263
B4: Abs | C4: Absorption & Turnover Vacancy | D4: =SUMIF($A$32:$A$268,$B4,D$32:D$268)/1000 -> 0 | E4: =SUMIF($A$32:$A$268,$B4,E$32:E$268)/1000 -> 0 | F4: =SUMIF($A$32:$A$268,$B4,F$32:F$268)/1000 -> 0 | G4: =SUMIF($A$32:$A$268,$B4,G$32:G$268)/1000 -> 0 | H4: =SUMIF($A$32:$A$268,$B4,H$32:H$268)/1000 -> 0 | I4: =SUMIF($A$32:$A$268,$B4,I$32:I$268)/1000 -> 0 | J4: =SUMIF($A$32:$A$268,$B4,J$32:J$268)/1000 -> 0 | K4: =SUMIF($A$32:$A$268,$B4,K$32:K$268)/1000 -> 0 | ... AS4: =SUMIF($A$32:$A$268,$B4,AS$32:AS$268)/1000 -> 0 | AT4: =SUMIF('2020'!$A:$A,$B4,'2020'!D:D)/1000 -> 0 | AU4: =SUMIF('2020'!$A:$A,$B4,'2020'!E:E)/1000 -> 0 | AV4: =SUMIF('2020'!$A:$A,$B4,'2020'!F:F)/1000 -> 0 | AW4: =SUMIF('2020'!$A:$A,$B4,'2020'!G:G)/1000 -> 0 | AX4: =SUMIF('2020'!$A:$A,$B4,'2020'!H:H)/1000 -> 0 | AY4: =SUMIF('2020'!$A:$A,$B4,'2020'!I:I)/1000 -> 0 | AZ4: =SUMIF('2020'!$A:$A,$B4,'2020'!J:J)/1000 -> 0 | BA4: =SUMIF('2020'!$A:$A,$B4,'2020'!K:K)/1000 -> 0 | BB4: =SUMIF('2020'!$A:$A,$B4,'2020'!L:L)/1000 -> 0 | BC4: =SUMIF('2020'!$A:$A,$B4,'2020'!M:M)/1000 -> 0 | BD4: =SUMIF('2020'!$A:$A,$B4,'2020'!N:N)/1000 -> 0 | BE4: =SUMIF('2020'!$A:$A,$B4,'2020'!O:O)/1000 -> 0 | BF4: =SUMIF('2021'!$A:$A,$B4,'2021'!D:D)/1000 -> 0 | BG4: =SUMIF('2021'!$A:$A,$B4,'2021'!E:E)/1000 -> 0 | BH4: =SUMIF('2021'!$A:$A,$B4,'2021'!F:F)/1000 -> 0 | BI4: =SUMIF('2021'!$A:$A,$B4,'2021'!G:G)/1000 -> 0 | BJ4: =SUMIF('2021'!$A:$A,$B4,'2021'!H:H)/1000 -> 0 | BK4: =SUMIF('2021'!$A:$A,$B4,'2021'!I:I)/1000 -> 0 | BL4: =SUMIF('2021'!$A:$A,$B4,'2021'!J:J)/1000 -> 0 | BM4: =SUMIF('2021'!$A:$A,$B4,'2021'!K:K)/1000 -> 0 | BN4: =SUMIF('2021'!$A:$A,$B4,'2021'!L:L)/1000 -> 0 | BO4: =SUMIF('2021'!$A:$A,$B4,'2021'!M:M)/1000 -> 0 | BP4: =SUMIF('2021'!$A:$A,$B4,'2021'!N:N)/1000 -> 0 | BQ4: =SUMIF('2021'!$A:$A,$B4,'2021'!O:O)/1000 -> 0 | BR4: =SUMIF('2022'!$A:$A,$B4,'2022'!D:D)/1000 -> 0 | BS4: =SUMIF('2022'!$A:$A,$B4,'2022'!E:E)/1000 -> 0 | BT4: =SUMIF('2022'!$A:$A,$B4,'2022'!F:F)/1000 -> 0 | BU4: =SUMIF('2022'!$A:$A,$B4,'2022'!G:G)/1000 -> 0 | BV4: =SUMIF('2022'!$A:$A,$B4,'2022'!H:H)/1000 -> 0 | BW4: =SUMIF('2022'!$A:$A,$B4,'2022'!I:I)/1000 -> 0 | BX4: =SUMIF('2022'!$A:$A,$B4,'2022'!J:J)/1000 -> 0 | BY4: =SUMIF('2022'!$A:$A,$B4,'2022'!K:K)/1000 -> 0 | BZ4: =SUMIF('2022'!$A:$A,$B4,'2022'!L:L)/1000 -> 0
B5: Free | C5: Free Rent | D5: =SUMIF($A$32:$A$268,$B5,D$32:D$268)/1000 -> 0 | E5: =SUMIF($A$32:$A$268,$B5,E$32:E$268)/1000 -> 0 | F5: =SUMIF($A$32:$A$268,$B5,F$32:F$268)/1000 -> 0 | G5: =SUMIF($A$32:$A$268,$B5,G$32:G$268)/1000 -> 0 | H5: =SUMIF($A$32:$A$268,$B5,H$32:H$268)/1000 -> 0 | I5: =SUMIF($A$32:$A$268,$B5,I$32:I$268)/1000 -> 0 | J5: =SUMIF($A$32:$A$268,$B5,J$32:J$268)/1000 -> 0 | K5: =SUMIF($A$32:$A$268,$B5,K$32:K$268)/1000 -> 0 | ... AS5: =SUMIF($A$32:$A$268,$B5,AS$32:AS$268)/1000 -> -17.90183 | AT5: =SUMIF('2020'!$A:$A,$B5,'2020'!D:D)/1000 -> -5.95175 | AU5: =SUMIF('2020'!$A:$A,$B5,'2020'!E:E)/1000 -> 0 | AV5: =SUMIF('2020'!$A:$A,$B5,'2020'!F:F)/1000 -> -15.48834 | AW5: =SUMIF('2020'!$A:$A,$B5,'2020'!G:G)/1000 -> 0 | AX5: =SUMIF('2020'!$A:$A,$B5,'2020'!H:H)/1000 -> 0 | AY5: =SUMIF('2020'!$A:$A,$B5,'2020'!I:I)/1000 -> 0 | AZ5: =SUMIF('2020'!$A:$A,$B5,'2020'!J:J)/1000 -> 0 | BA5: =SUMIF('2020'!$A:$A,$B5,'2020'!K:K)/1000 -> -11.24718 | BB5: =SUMIF('2020'!$A:$A,$B5,'2020'!L:L)/1000 -> 0 | BC5: =SUMIF('2020'!$A:$A,$B5,'2020'!M:M)/1000 -> 0 | BD5: =SUMIF('2020'!$A:$A,$B5,'2020'!N:N)/1000 -> -33.85875 | BE5: =SUMIF('2020'!$A:$A,$B5,'2020'!O:O)/1000 -> 0 | BF5: =SUMIF('2021'!$A:$A,$B5,'2021'!D:D)/1000 -> -14.15514 | BG5: =SUMIF('2021'!$A:$A,$B5,'2021'!E:E)/1000 -> 0 | BH5: =SUMIF('2021'!$A:$A,$B5,'2021'!F:F)/1000 -> 0 | BI5: =SUMIF('2021'!$A:$A,$B5,'2021'!G:G)/1000 -> 0 | BJ5: =SUMIF('2021'!$A:$A,$B5,'2021'!H:H)/1000 -> 0 | BK5: =SUMIF('2021'!$A:$A,$B5,'2021'!I:I)/1000 -> 0 | BL5: =SUMIF('2021'!$A:$A,$B5,'2021'!J:J)/1000 -> 0 | BM5: =SUMIF('2021'!$A:$A,$B5,'2021'!K:K)/1000 -> -11.24718 | BN5: =SUMIF('2021'!$A:$A,$B5,'2021'!L:L)/1000 -> 0 | BO5: =SUMIF('2021'!$A:$A,$B5,'2021'!M:M)/1000 -> 0 | BP5: =SUMIF('2021'!$A:$A,$B5,'2021'!N:N)/1000 -> 0 | BQ5: =SUMIF('2021'!$A:$A,$B5,'2021'!O:O)/1000 -> 0 | BR5: =SUMIF('2022'!$A:$A,$B5,'2022'!D:D)/1000 -> 0 | BS5: =SUMIF('2022'!$A:$A,$B5,'2022'!E:E)/1000 -> -15.95299 | BT5: =SUMIF('2022'!$A:$A,$B5,'2022'!F:F)/1000 -> 0 | BU5: =SUMIF('2022'!$A:$A,$B5,'2022'!G:G)/1000 -> 0 | BV5: =SUMIF('2022'!$A:$A,$B5,'2022'!H:H)/1000 -> 0 | BW5: =SUMIF('2022'!$A:$A,$B5,'2022'!I:I)/1000 -> 0 | BX5: =SUMIF('2022'!$A:$A,$B5,'2022'!J:J)/1000 -> 0 | BY5: =SUMIF('2022'!$A:$A,$B5,'2022'!K:K)/1000 -> -11.24718 | BZ5: =SUMIF('2022'!$A:$A,$B5,'2022'!L:L)/1000 -> -10.38375
B6: ExpRec | C6: Total Expense Recoveries | D6: =SUMIF($A$32:$A$268,$B6,D$32:D$268)/1000 -> 62.98453 | E6: =SUMIF($A$32:$A$268,$B6,E$32:E$268)/1000 -> 62.98453 | F6: =SUMIF($A$32:$A$268,$B6,F$32:F$268)/1000 -> 62.98453 | G6: =SUMIF($A$32:$A$268,$B6,G$32:G$268)/1000 -> 65.05819 | H6: =SUMIF($A$32:$A$268,$B6,H$32:H$268)/1000 -> 61.24428 | I6: =SUMIF($A$32:$A$268,$B6,I$32:I$268)/1000 -> 61.68743 | J6: =SUMIF($A$32:$A$268,$B6,J$32:J$268)/1000 -> 64.99071 | K6: =SUMIF($A$32:$A$268,$B6,K$32:K$268)/1000 -> 121.40012 | ... AS6: =SUMIF($A$32:$A$268,$B6,AS$32:AS$268)/1000 -> 103.47271 | AT6: =SUMIF('2020'!$A:$A,$B6,'2020'!D:D)/1000 -> 97.731 | AU6: =SUMIF('2020'!$A:$A,$B6,'2020'!E:E)/1000 -> 101.403 | AV6: =SUMIF('2020'!$A:$A,$B6,'2020'!F:F)/1000 -> 92.576 | AW6: =SUMIF('2020'!$A:$A,$B6,'2020'!G:G)/1000 -> 88.95975 | AX6: =SUMIF('2020'!$A:$A,$B6,'2020'!H:H)/1000 -> 110.094 | AY6: =SUMIF('2020'!$A:$A,$B6,'2020'!I:I)/1000 -> 94.673 | AZ6: =SUMIF('2020'!$A:$A,$B6,'2020'!J:J)/1000 -> 94.673 | BA6: =SUMIF('2020'!$A:$A,$B6,'2020'!K:K)/1000 -> 102.58631 | BB6: =SUMIF('2020'!$A:$A,$B6,'2020'!L:L)/1000 -> 94.673 | BC6: =SUMIF('2020'!$A:$A,$B6,'2020'!M:M)/1000 -> 94.673 | BD6: =SUMIF('2020'!$A:$A,$B6,'2020'!N:N)/1000 -> 94.673 | BE6: =SUMIF('2020'!$A:$A,$B6,'2020'!O:O)/1000 -> 95.013 | BF6: =SUMIF('2021'!$A:$A,$B6,'2021'!D:D)/1000 -> 65.48765 | BG6: =SUMIF('2021'!$A:$A,$B6,'2021'!E:E)/1000 -> 79.311 | BH6: =SUMIF('2021'!$A:$A,$B6,'2021'!F:F)/1000 -> 46.10488 | BI6: =SUMIF('2021'!$A:$A,$B6,'2021'!G:G)/1000 -> 78.97098 | BJ6: =SUMIF('2021'!$A:$A,$B6,'2021'!H:H)/1000 -> 78.971 | BK6: =SUMIF('2021'!$A:$A,$B6,'2021'!I:I)/1000 -> 78.971 | BL6: =SUMIF('2021'!$A:$A,$B6,'2021'!J:J)/1000 -> 41.86101 | BM6: =SUMIF('2021'!$A:$A,$B6,'2021'!K:K)/1000 -> 78.971 | BN6: =SUMIF('2021'!$A:$A,$B6,'2021'!L:L)/1000 -> 72.23762 | BO6: =SUMIF('2021'!$A:$A,$B6,'2021'!M:M)/1000 -> 87.23246 | BP6: =SUMIF('2021'!$A:$A,$B6,'2021'!N:N)/1000 -> 87.51 | BQ6: =SUMIF('2021'!$A:$A,$B6,'2021'!O:O)/1000 -> 90.04148 | BR6: =SUMIF('2022'!$A:$A,$B6,'2022'!D:D)/1000 -> 100.76062 | BS6: =SUMIF('2022'!$A:$A,$B6,'2022'!E:E)/1000 -> 96.54242 | BT6: =SUMIF('2022'!$A:$A,$B6,'2022'!F:F)/1000 -> 96.54242 | BU6: =SUMIF('2022'!$A:$A,$B6,'2022'!G:G)/1000 -> 89.74594 | BV6: =SUMIF('2022'!$A:$A,$B6,'2022'!H:H)/1000 -> 96.54242 | BW6: =SUMIF('2022'!$A:$A,$B6,'2022'!I:I)/1000 -> 65.18159 | BX6: =SUMIF('2022'!$A:$A,$B6,'2022'!J:J)/1000 -> 96.54242 | BY6: =SUMIF('2022'!$A:$A,$B6,'2022'!K:K)/1000 -> 96.54242 | BZ6: =SUMIF('2022'!$A:$A,$B6,'2022'!L:L)/1000 -> 96.70992
B7: Park | C7: Unassigned Parking Revenue | D7: =SUMIF($A$32:$A$268,$B7,D$32:D$268)/1000 -> 0 | E7: =SUMIF($A$32:$A$268,$B7,E$32:E$268)/1000 -> 8.6 | F7: =SUMIF($A$32:$A$268,$B7,F$32:F$268)/1000 -> 4.3 | G7: =SUMIF($A$32:$A$268,$B7,G$32:G$268)/1000 -> 4.3 | H7: =SUMIF($A$32:$A$268,$B7,H$32:H$268)/1000 -> 4.3 | I7: =SUMIF($A$32:$A$268,$B7,I$32:I$268)/1000 -> 4.3 | J7: =SUMIF($A$32:$A$268,$B7,J$32:J$268)/1000 -> 4.3 | K7: =SUMIF($A$32:$A$268,$B7,K$32:K$268)/1000 -> 4.3 | ... AS7: =SUMIF($A$32:$A$268,$B7,AS$32:AS$268)/1000 -> 13 | AT7: =SUMIF('2020'!$A:$A,$B7,'2020'!D:D)/1000 -> 13 | AU7: =SUMIF('2020'!$A:$A,$B7,'2020'!E:E)/1000 -> 4.4648 | AV7: =SUMIF('2020'!$A:$A,$B7,'2020'!F:F)/1000 -> 2.2324 | AW7: =SUMIF('2020'!$A:$A,$B7,'2020'!G:G)/1000 -> 2.2324 | AX7: =SUMIF('2020'!$A:$A,$B7,'2020'!H:H)/1000 -> -2.2324 | AY7: =SUMIF('2020'!$A:$A,$B7,'2020'!I:I)/1000 -> 0 | AZ7: =SUMIF('2020'!$A:$A,$B7,'2020'!J:J)/1000 -> 0 | BA7: =SUMIF('2020'!$A:$A,$B7,'2020'!K:K)/1000 -> 14.62452 | BB7: =SUMIF('2020'!$A:$A,$B7,'2020'!L:L)/1000 -> 18.47358 | BC7: =SUMIF('2020'!$A:$A,$B7,'2020'!M:M)/1000 -> 12.21216 | BD7: =SUMIF('2020'!$A:$A,$B7,'2020'!N:N)/1000 -> 0.20646 | BE7: =SUMIF('2020'!$A:$A,$B7,'2020'!O:O)/1000 -> 8.22241 | BF7: =SUMIF('2021'!$A:$A,$B7,'2021'!D:D)/1000 -> 0 | BG7: =SUMIF('2021'!$A:$A,$B7,'2021'!E:E)/1000 -> 0 | BH7: =SUMIF('2021'!$A:$A,$B7,'2021'!F:F)/1000 -> 9.67717 | BI7: =SUMIF('2021'!$A:$A,$B7,'2021'!G:G)/1000 -> 11.27635 | BJ7: =SUMIF('2021'!$A:$A,$B7,'2021'!H:H)/1000 -> 0 | BK7: =SUMIF('2021'!$A:$A,$B7,'2021'!I:I)/1000 -> 24.5283 | BL7: =SUMIF('2021'!$A:$A,$B7,'2021'!J:J)/1000 -> 25.9332 | BM7: =SUMIF('2021'!$A:$A,$B7,'2021'!K:K)/1000 -> 20.7015 | BN7: =SUMIF('2021'!$A:$A,$B7,'2021'!L:L)/1000 -> 16.83405 | BO7: =SUMIF('2021'!$A:$A,$B7,'2021'!M:M)/1000 -> 16.83405 | BP7: =SUMIF('2021'!$A:$A,$B7,'2021'!N:N)/1000 -> 24.31917 | BQ7: =SUMIF('2021'!$A:$A,$B7,'2021'!O:O)/1000 -> -11.72946 | BR7: =SUMIF('2022'!$A:$A,$B7,'2022'!D:D)/1000 -> 18.5 | BS7: =SUMIF('2022'!$A:$A,$B7,'2022'!E:E)/1000 -> 18.5 | BT7: =SUMIF('2022'!$A:$A,$B7,'2022'!F:F)/1000 -> 16.226 | BU7: =SUMIF('2022'!$A:$A,$B7,'2022'!G:G)/1000 -> 26.99582 | BV7: =SUMIF('2022'!$A:$A,$B7,'2022'!H:H)/1000 -> 30.25864 | BW7: =SUMIF('2022'!$A:$A,$B7,'2022'!I:I)/1000 -> 22 | BX7: =SUMIF('2022'!$A:$A,$B7,'2022'!J:J)/1000 -> 39.27395 | BY7: =SUMIF('2022'!$A:$A,$B7,'2022'!K:K)/1000 -> 27.57904 | BZ7: =SUMIF('2022'!$A:$A,$B7,'2022'!L:L)/1000 -> 23.14199
B8: OtherRev | C8: Other Revenue | D8: =SUMIF($A$32:$A$268,$B8,D$32:D$268)/1000-D7 -> 0 | E8: =SUMIF($A$32:$A$268,$B8,E$32:E$268)/1000-E7 -> 0 | F8: =SUMIF($A$32:$A$268,$B8,F$32:F$268)/1000-F7 -> 3.1431 | G8: =SUMIF($A$32:$A$268,$B8,G$32:G$268)/1000-G7 -> 9.32102 | H8: =SUMIF($A$32:$A$268,$B8,H$32:H$268)/1000-H7 -> 0 | I8: =SUMIF($A$32:$A$268,$B8,I$32:I$268)/1000-I7 -> 4.46697 | J8: =SUMIF($A$32:$A$268,$B8,J$32:J$268)/1000-J7 -> 3.80335 | K8: =SUMIF($A$32:$A$268,$B8,K$32:K$268)/1000-K7 -> 11.8861 | ... AS8: =SUMIF($A$32:$A$268,$B8,AS$32:AS$268)/1000-AS7 -> 20.78072 | AT8: =SUMIF('2020'!$A:$A,$B8,'2020'!D:D)/1000 -> 0.069 | AU8: =SUMIF('2020'!$A:$A,$B8,'2020'!E:E)/1000 -> 0.069 | AV8: =SUMIF('2020'!$A:$A,$B8,'2020'!F:F)/1000 -> 0.069 | AW8: =SUMIF('2020'!$A:$A,$B8,'2020'!G:G)/1000 -> 0.069 | AX8: =SUMIF('2020'!$A:$A,$B8,'2020'!H:H)/1000 -> 0.069 | AY8: =SUMIF('2020'!$A:$A,$B8,'2020'!I:I)/1000 -> 0.069 | AZ8: =SUMIF('2020'!$A:$A,$B8,'2020'!J:J)/1000 -> 0.069 | BA8: =SUMIF('2020'!$A:$A,$B8,'2020'!K:K)/1000 -> 0.069 | BB8: =SUMIF('2020'!$A:$A,$B8,'2020'!L:L)/1000 -> 0.069 | BC8: =SUMIF('2020'!$A:$A,$B8,'2020'!M:M)/1000 -> 0.069 | BD8: =SUMIF('2020'!$A:$A,$B8,'2020'!N:N)/1000 -> 0.069 | BE8: =SUMIF('2020'!$A:$A,$B8,'2020'!O:O)/1000 -> 0.069 | BF8: =SUMIF('2021'!$A:$A,$B8,'2021'!D:D)/1000 -> 0.069 | BG8: =SUMIF('2021'!$A:$A,$B8,'2021'!E:E)/1000 -> 0.069 | BH8: =SUMIF('2021'!$A:$A,$B8,'2021'!F:F)/1000 -> -0.3795 | BI8: =SUMIF('2021'!$A:$A,$B8,'2021'!G:G)/1000 -> 0.069 | BJ8: =SUMIF('2021'!$A:$A,$B8,'2021'!H:H)/1000 -> 2.70079 | BK8: =SUMIF('2021'!$A:$A,$B8,'2021'!I:I)/1000 -> 12.45005 | BL8: =SUMIF('2021'!$A:$A,$B8,'2021'!J:J)/1000 -> 4.95005 | BM8: =SUMIF('2021'!$A:$A,$B8,'2021'!K:K)/1000 -> 4.95005 | BN8: =SUMIF('2021'!$A:$A,$B8,'2021'!L:L)/1000 -> 4.95005 | BO8: =SUMIF('2021'!$A:$A,$B8,'2021'!M:M)/1000 -> 4.95005 | BP8: =SUMIF('2021'!$A:$A,$B8,'2021'!N:N)/1000 -> 4.95005 | BQ8: =SUMIF('2021'!$A:$A,$B8,'2021'!O:O)/1000 -> 2.70079 | BR8: =SUMIF('2022'!$A:$A,$B8,'2022'!D:D)/1000 -> 2.70079 | BS8: =SUMIF('2022'!$A:$A,$B8,'2022'!E:E)/1000 -> 2.70079 | BT8: =SUMIF('2022'!$A:$A,$B8,'2022'!F:F)/1000 -> 7.70079 | BU8: =SUMIF('2022'!$A:$A,$B8,'2022'!G:G)/1000 -> 2.70079 | BV8: =SUMIF('2022'!$A:$A,$B8,'2022'!H:H)/1000 -> 2.70079 | BW8: =SUMIF('2022'!$A:$A,$B8,'2022'!I:I)/1000 -> 2.70079 | BX8: =SUMIF('2022'!$A:$A,$B8,'2022'!J:J)/1000 -> 2.70079 | BY8: =SUMIF('2022'!$A:$A,$B8,'2022'!K:K)/1000 -> 2.70079 | BZ8: =SUMIF('2022'!$A:$A,$B8,'2022'!L:L)/1000 -> 2.70079
B9: PGR | C9: Potential Gross Revenue | D9: =SUM(D3:D8) -> 174.17922 | E9: =SUM(E3:E8) -> 183.67012 | F9: =SUM(F3:F8) -> 186.80412 | G9: =SUM(G3:G8) -> 190.57505 | H9: =SUM(H3:H8) -> 177.26428 | I9: =SUM(I3:I8) -> 180.16823 | J9: =SUM(J3:J8) -> 180.77277 | K9: =SUM(K3:K8) -> 239.88771 | ... BZ9: =SUM(BZ3:BZ8) -> 272.71158
B10: Vac | C10: Vacancy Allowance | D10: =SUMIF($A$32:$A$268,$B10,D$32:D$268)/1000 -> 0 | E10: =SUMIF($A$32:$A$268,$B10,E$32:E$268)/1000 -> 0 | F10: =SUMIF($A$32:$A$268,$B10,F$32:F$268)/1000 -> 0 | G10: =SUMIF($A$32:$A$268,$B10,G$32:G$268)/1000 -> 0 | H10: =SUMIF($A$32:$A$268,$B10,H$32:H$268)/1000 -> 0 | I10: =SUMIF($A$32:$A$268,$B10,I$32:I$268)/1000 -> 0 | J10: =SUMIF($A$32:$A$268,$B10,J$32:J$268)/1000 -> 0 | K10: =SUMIF($A$32:$A$268,$B10,K$32:K$268)/1000 -> 0 | ... AS10: =SUMIF($A$32:$A$268,$B10,AS$32:AS$268)/1000 -> 0 | AT10: =SUMIF('2020'!$A:$A,$B10,'2020'!D:D)/1000 -> 0 | AU10: =SUMIF('2020'!$A:$A,$B10,'2020'!E:E)/1000 -> 0 | AV10: =SUMIF('2020'!$A:$A,$B10,'2020'!F:F)/1000 -> 0 | AW10: =SUMIF('2020'!$A:$A,$B10,'2020'!G:G)/1000 -> 0 | AX10: =SUMIF('2020'!$A:$A,$B10,'2020'!H:H)/1000 -> 0 | AY10: =SUMIF('2020'!$A:$A,$B10,'2020'!I:I)/1000 -> 0 | AZ10: =SUMIF('2020'!$A:$A,$B10,'2020'!J:J)/1000 -> 0 | BA10: =SUMIF('2020'!$A:$A,$B10,'2020'!K:K)/1000 -> 0 | BB10: =SUMIF('2020'!$A:$A,$B10,'2020'!L:L)/1000 -> 0 | BC10: =SUMIF('2020'!$A:$A,$B10,'2020'!M:M)/1000 -> 0 | BD10: =SUMIF('2020'!$A:$A,$B10,'2020'!N:N)/1000 -> 0 | BE10: =SUMIF('2020'!$A:$A,$B10,'2020'!O:O)/1000 -> 0 | BF10: =SUMIF('2021'!$A:$A,$B10,'2021'!D:D)/1000 -> 0 | BG10: =SUMIF('2021'!$A:$A,$B10,'2021'!E:E)/1000 -> 0 | BH10: =SUMIF('2021'!$A:$A,$B10,'2021'!F:F)/1000 -> 0 | BI10: =SUMIF('2021'!$A:$A,$B10,'2021'!G:G)/1000 -> 0 | BJ10: =SUMIF('2021'!$A:$A,$B10,'2021'!H:H)/1000 -> 0 | BK10: =SUMIF('2021'!$A:$A,$B10,'2021'!I:I)/1000 -> 0 | BL10: =SUMIF('2021'!$A:$A,$B10,'2021'!J:J)/1000 -> 0 | BM10: =SUMIF('2021'!$A:$A,$B10,'2021'!K:K)/1000 -> 0 | BN10: =SUMIF('2021'!$A:$A,$B10,'2021'!L:L)/1000 -> 0 | BO10: =SUMIF('2021'!$A:$A,$B10,'2021'!M:M)/1000 -> 0 | BP10: =SUMIF('2021'!$A:$A,$B10,'2021'!N:N)/1000 -> 0 | BQ10: =SUMIF('2021'!$A:$A,$B10,'2021'!O:O)/1000 -> 0 | BR10: =SUMIF('2022'!$A:$A,$B10,'2022'!D:D)/1000 -> 0 | BS10: =SUMIF('2022'!$A:$A,$B10,'2022'!E:E)/1000 -> 0 | BT10: =SUMIF('2022'!$A:$A,$B10,'2022'!F:F)/1000 -> 0 | BU10: =SUMIF('2022'!$A:$A,$B10,'2022'!G:G)/1000 -> 0 | BV10: =SUMIF('2022'!$A:$A,$B10,'2022'!H:H)/1000 -> 0 | BW10: =SUMIF('2022'!$A:$A,$B10,'2022'!I:I)/1000 -> 0 | BX10: =SUMIF('2022'!$A:$A,$B10,'2022'!J:J)/1000 -> 0 | BY10: =SUMIF('2022'!$A:$A,$B10,'2022'!K:K)/1000 -> 0 | BZ10: =SUMIF('2022'!$A:$A,$B10,'2022'!L:L)/1000 -> 0
B11: EGR | C11: Effective Gross Revenue | D11: =D9-D10 -> 174.17922 | E11: =E9-E10 -> 183.67012 | F11: =F9-F10 -> 186.80412 | G11: =G9-G10 -> 190.57505 | H11: =H9-H10 -> 177.26428 | I11: =I9-I10 -> 180.16823 | J11: =J9-J10 -> 180.77277 | K11: =K9-K10 -> 239.88771 | ... BZ11: =BZ9-BZ10 -> 272.71158
B13: CAM | C13: Common Area Maintenance | D13: =SUMIF($A$32:$A$268,$B13,D$32:D$268)/1000-D14-D16-D17-D18-D20 -> 20.73232 | E13: =SUMIF($A$32:$A$268,$B13,E$32:E$268)/1000-E14-E16-E17-E18-E20 -> 41.57492 | F13: =SUMIF($A$32:$A$268,$B13,F$32:F$268)/1000-F14-F16-F17-F18-F20 -> 23.13331 | G13: =SUMIF($A$32:$A$268,$B13,G$32:G$268)/1000-G14-G16-G17-G18-G20 -> 10.1014 | H13: =SUMIF($A$32:$A$268,$B13,H$32:H$268)/1000-H14-H16-H17-H18-H20 -> 23.60387 | I13: =SUMIF($A$32:$A$268,$B13,I$32:I$268)/1000-I14-I16-I17-I18-I20 -> 25.00292 | J13: =SUMIF($A$32:$A$268,$B13,J$32:J$268)/1000-J14-J16-J17-J18-J20 -> 23.6635 | K13: =SUMIF($A$32:$A$268,$B13,K$32:K$268)/1000-K14-K16-K17-K18-K20 -> 23.42751 | ... AS13: =SUMIF($A$32:$A$268,$B13,AS$32:AS$268)/1000-AS14-AS16-AS17-AS18-AS20 -> 40.83427 | AT13: =SUMIF('2020'!$A:$A,Historicals!$B13,'2020'!D:D)/1000-AT14-AT16-AT17-AT18-AT20 -> 49.85516 | AU13: =SUMIF('2020'!$A:$A,Historicals!$B13,'2020'!E:E)/1000-AU14-AU16-AU17-AU18-AU20 -> 23.953 | AV13: =SUMIF('2020'!$A:$A,Historicals!$B13,'2020'!F:F)/1000-AV14-AV16-AV17-AV18-AV20 -> 22.7747 | AW13: =SUMIF('2020'!$A:$A,Historicals!$B13,'2020'!G:G)/1000-AW14-AW16-AW17-AW18-AW20 -> 35.67805 | AX13: =SUMIF('2020'!$A:$A,Historicals!$B13,'2020'!H:H)/1000-AX14-AX16-AX17-AX18-AX20 -> 34.28743 | AY13: =SUMIF('2020'!$A:$A,Historicals!$B13,'2020'!I:I)/1000-AY14-AY16-AY17-AY18-AY20 -> 11.586 | AZ13: =SUMIF('2020'!$A:$A,Historicals!$B13,'2020'!J:J)/1000-AZ14-AZ16-AZ17-AZ18-AZ20 -> 19.16208 | BA13: =SUMIF('2020'!$A:$A,Historicals!$B13,'2020'!K:K)/1000-BA14-BA16-BA17-BA18-BA20 -> 43.94939 | BB13: =SUMIF('2020'!$A:$A,Historicals!$B13,'2020'!L:L)/1000-BB14-BB16-BB17-BB18-BB20 -> 39.02227 | BC13: =SUMIF('2020'!$A:$A,Historicals!$B13,'2020'!M:M)/1000-BC14-BC16-BC17-BC18-BC20 -> 8.91987 | BD13: =SUMIF('2020'!$A:$A,Historicals!$B13,'2020'!N:N)/1000-BD14-BD16-BD17-BD18-BD20 -> 10.58373 | BE13: =SUMIF('2020'!$A:$A,Historicals!$B13,'2020'!O:O)/1000-BE14-BE16-BE17-BE18-BE20 -> 61.5207 | BF13: =SUMIF('2021'!$A:$A,$B13,'2021'!D:D)/1000- BF14-BF16-BF17-BF18-BF20 -> 18.86547 | BG13: =SUMIF('2021'!$A:$A,$B13,'2021'!E:E)/1000- BG14-BG16-BG17-BG18-BG20 -> 25.4403 | BH13: =SUMIF('2021'!$A:$A,$B13,'2021'!F:F)/1000- BH14-BH16-BH17-BH18-BH20 -> 29.23425 | BI13: =SUMIF('2021'!$A:$A,$B13,'2021'!G:G)/1000- BI14-BI16-BI17-BI18-BI20 -> 42.58455 | BJ13: =SUMIF('2021'!$A:$A,$B13,'2021'!H:H)/1000- BJ14-BJ16-BJ17-BJ18-BJ20 -> 25.4052 | BK13: =SUMIF('2021'!$A:$A,$B13,'2021'!I:I)/1000- BK14-BK16-BK17-BK18-BK20 -> 17.61461 | BL13: =SUMIF('2021'!$A:$A,$B13,'2021'!J:J)/1000- BL14-BL16-BL17-BL18-BL20 -> 21.12995 | BM13: =SUMIF('2021'!$A:$A,$B13,'2021'!K:K)/1000- BM14-BM16-BM17-BM18-BM20 -> 44.30655 | BN13: =SUMIF('2021'!$A:$A,$B13,'2021'!L:L)/1000- BN14-BN16-BN17-BN18-BN20 -> 27.8656 | BO13: =SUMIF('2021'!$A:$A,$B13,'2021'!M:M)/1000- BO14-BO16-BO17-BO18-BO20 -> 9.16 | BP13: =SUMIF('2021'!$A:$A,$B13,'2021'!N:N)/1000- BP14-BP16-BP17-BP18-BP20 -> 58.10855 | BQ13: =SUMIF('2021'!$A:$A,$B13,'2021'!O:O)/1000- BQ14-BQ16-BQ17-BQ18-BQ20 -> 9.7943 | BR13: =SUMIF('2022'!$A:$A,$B13,'2022'!D:D)/1000- BR14-BR16-BR17-BR18-BR20 -> 0.105 | BS13: =SUMIF('2022'!$A:$A,$B13,'2022'!E:E)/1000- BS14-BS16-BS17-BS18-BS20 -> 54.51493 | BT13: =SUMIF('2022'!$A:$A,$B13,'2022'!F:F)/1000- BT14-BT16-BT17-BT18-BT20 -> 32.96366 | BU13: =SUMIF('2022'!$A:$A,$B13,'2022'!G:G)/1000- BU14-BU16-BU17-BU18-BU20 -> 19.94585 | BV13: =SUMIF('2022'!$A:$A,$B13,'2022'!H:H)/1000- BV14-BV16-BV17-BV18-BV20 -> 77.60094 | BW13: =SUMIF('2022'!$A:$A,$B13,'2022'!I:I)/1000- BW14-BW16-BW17-BW18-BW20 -> 39.88668 | BX13: =SUMIF('2022'!$A:$A,$B13,'2022'!J:J)/1000- BX14-BX16-BX17-BX18-BX20 -> 19.7167 | BY13: =SUMIF('2022'!$A:$A,$B13,'2022'!K:K)/1000- BY14-BY16-BY17-BY18-BY20 -> 34.19335 | BZ13: =SUMIF('2022'!$A:$A,$B13,'2022'!L:L)/1000- BZ14-BZ16-BZ17-BZ18-BZ20 -> 32.24538
B14: G&A | C14: General & Administrative | D14: =SUMIF($A$32:$A$268,$B14,D$32:D$268)/1000 -> 10.761 | E14: =SUMIF($A$32:$A$268,$B14,E$32:E$268)/1000 -> 9.65 | F14: =SUMIF($A$32:$A$268,$B14,F$32:F$268)/1000 -> 13.9885 | G14: =SUMIF($A$32:$A$268,$B14,G$32:G$268)/1000 -> 39.0742 | H14: =SUMIF($A$32:$A$268,$B14,H$32:H$268)/1000 -> 9.37764 | I14: =SUMIF($A$32:$A$268,$B14,I$32:I$268)/1000 -> 82.84792 | J14: =SUMIF($A$32:$A$268,$B14,J$32:J$268)/1000 -> 11.8 | K14: =SUMIF($A$32:$A$268,$B14,K$32:K$268)/1000 -> 2.8 | ... AS14: =SUMIF($A$32:$A$268,$B14,AS$32:AS$268)/1000 -> 21.06263 | AT14: =SUMIF('2020'!$A:$A,$B14,'2020'!D:D)/1000 -> 33.27991 | AU14: =SUMIF('2020'!$A:$A,$B14,'2020'!E:E)/1000 -> 13.51703 | AV14: =SUMIF('2020'!$A:$A,$B14,'2020'!F:F)/1000 -> 10.63757 | AW14: =SUMIF('2020'!$A:$A,$B14,'2020'!G:G)/1000 -> 7.87209 | AX14: =SUMIF('2020'!$A:$A,$B14,'2020'!H:H)/1000 -> 12.53284 | AY14: =SUMIF('2020'!$A:$A,$B14,'2020'!I:I)/1000 -> 17.18189 | AZ14: =SUMIF('2020'!$A:$A,$B14,'2020'!J:J)/1000 -> 4.16546 | BA14: =SUMIF('2020'!$A:$A,$B14,'2020'!K:K)/1000 -> 5.25375 | BB14: =SUMIF('2020'!$A:$A,$B14,'2020'!L:L)/1000 -> 494.29508 | BC14: =SUMIF('2020'!$A:$A,$B14,'2020'!M:M)/1000 -> 3.30458 | BD14: =SUMIF('2020'!$A:$A,$B14,'2020'!N:N)/1000 -> 7.43486 | BE14: =SUMIF('2020'!$A:$A,$B14,'2020'!O:O)/1000 -> 109.0819 | BF14: =SUMIF('2021'!$A:$A,$B14,'2021'!D:D)/1000 -> 3.0751 | BG14: =SUMIF('2021'!$A:$A,$B14,'2021'!E:E)/1000 -> 4.63074 | BH14: =SUMIF('2021'!$A:$A,$B14,'2021'!F:F)/1000 -> -18.78759 | BI14: =SUMIF('2021'!$A:$A,$B14,'2021'!G:G)/1000 -> 6.63085 | BJ14: =SUMIF('2021'!$A:$A,$B14,'2021'!H:H)/1000 -> 3.24329 | BK14: =SUMIF('2021'!$A:$A,$B14,'2021'!I:I)/1000 -> 6.03019 | BL14: =SUMIF('2021'!$A:$A,$B14,'2021'!J:J)/1000 -> 3.64526 | BM14: =SUMIF('2021'!$A:$A,$B14,'2021'!K:K)/1000 -> 8.26792 | BN14: =SUMIF('2021'!$A:$A,$B14,'2021'!L:L)/1000 -> 4.11343 | BO14: =SUMIF('2021'!$A:$A,$B14,'2021'!M:M)/1000 -> 4.86856 | BP14: =SUMIF('2021'!$A:$A,$B14,'2021'!N:N)/1000 -> 4.51388 | BQ14: =SUMIF('2021'!$A:$A,$B14,'2021'!O:O)/1000 -> 8.67923 | BR14: =SUMIF('2022'!$A:$A,$B14,'2022'!D:D)/1000 -> 9.46855 | BS14: =SUMIF('2022'!$A:$A,$B14,'2022'!E:E)/1000 -> 67.35895 | BT14: =SUMIF('2022'!$A:$A,$B14,'2022'!F:F)/1000 -> 6.17868 | BU14: =SUMIF('2022'!$A:$A,$B14,'2022'!G:G)/1000 -> 9.54734 | BV14: =SUMIF('2022'!$A:$A,$B14,'2022'!H:H)/1000 -> 4.19021 | BW14: =SUMIF('2022'!$A:$A,$B14,'2022'!I:I)/1000 -> 6.63048 | BX14: =SUMIF('2022'!$A:$A,$B14,'2022'!J:J)/1000 -> 4.3971 | BY14: =SUMIF('2022'!$A:$A,$B14,'2022'!K:K)/1000 -> 4.57356 | BZ14: =SUMIF('2022'!$A:$A,$B14,'2022'!L:L)/1000 -> 4.55564
C15: Contract Services | D15: =SUMIF($A$32:$A$268,$B15,D$32:D$268)/1000 -> 0 | E15: =SUMIF($A$32:$A$268,$B15,E$32:E$268)/1000 -> 0 | F15: =SUMIF($A$32:$A$268,$B15,F$32:F$268)/1000 -> 0 | G15: =SUMIF($A$32:$A$268,$B15,G$32:G$268)/1000 -> 0 | H15: =SUMIF($A$32:$A$268,$B15,H$32:H$268)/1000 -> 0 | I15: =SUMIF($A$32:$A$268,$B15,I$32:I$268)/1000 -> 0 | J15: =SUMIF($A$32:$A$268,$B15,J$32:J$268)/1000 -> 0 | K15: =SUMIF($A$32:$A$268,$B15,K$32:K$268)/1000 -> 0 | ... AS15: =SUMIF($A$32:$A$268,$B15,AS$32:AS$268)/1000 -> 0 | AT15: =SUMIF('2020'!$A:$A,$B15,'2020'!D:D)/1000 -> 0 | AU15: =SUMIF('2020'!$A:$A,$B15,'2020'!E:E)/1000 -> 0 | AV15: =SUMIF('2020'!$A:$A,$B15,'2020'!F:F)/1000 -> 0 | AW15: =SUMIF('2020'!$A:$A,$B15,'2020'!G:G)/1000 -> 0 | AX15: =SUMIF('2020'!$A:$A,$B15,'2020'!H:H)/1000 -> 0 | AY15: =SUMIF('2020'!$A:$A,$B15,'2020'!I:I)/1000 -> 0 | AZ15: =SUMIF('2020'!$A:$A,$B15,'2020'!J:J)/1000 -> 0 | BA15: =SUMIF('2020'!$A:$A,$B15,'2020'!K:K)/1000 -> 0 | BB15: =SUMIF('2020'!$A:$A,$B15,'2020'!L:L)/1000 -> 0 | BC15: =SUMIF('2020'!$A:$A,$B15,'2020'!M:M)/1000 -> 0 | BD15: =SUMIF('2020'!$A:$A,$B15,'2020'!N:N)/1000 -> 0 | BE15: =SUMIF('2020'!$A:$A,$B15,'2020'!O:O)/1000 -> 0
B16: Util | C16: Utilities | D16: =SUMIF($A$32:$A$268,$B16,D$32:D$268)/1000 -> 36.95091 | E16: =SUMIF($A$32:$A$268,$B16,E$32:E$268)/1000 -> 49.02688 | F16: =SUMIF($A$32:$A$268,$B16,F$32:F$268)/1000 -> 42.76975 | G16: =SUMIF($A$32:$A$268,$B16,G$32:G$268)/1000 -> 33.19602 | H16: =SUMIF($A$32:$A$268,$B16,H$32:H$268)/1000 -> 25.88346 | I16: =SUMIF($A$32:$A$268,$B16,I$32:I$268)/1000 -> 35.14288 | J16: =SUMIF($A$32:$A$268,$B16,J$32:J$268)/1000 -> 33.65774 | K16: =SUMIF($A$32:$A$268,$B16,K$32:K$268)/1000 -> 32.82673 | ... AS16: =SUMIF($A$32:$A$268,$B16,AS$32:AS$268)/1000 -> 37.18128 | AT16: =SUMIF('2020'!$A:$A,$B16,'2020'!D:D)/1000 -> 35.18414 | AU16: =SUMIF('2020'!$A:$A,$B16,'2020'!E:E)/1000 -> 40.95059 | AV16: =SUMIF('2020'!$A:$A,$B16,'2020'!F:F)/1000 -> 37.37495 | AW16: =SUMIF('2020'!$A:$A,$B16,'2020'!G:G)/1000 -> 14.15519 | AX16: =SUMIF('2020'!$A:$A,$B16,'2020'!H:H)/1000 -> 20.68571 | AY16: =SUMIF('2020'!$A:$A,$B16,'2020'!I:I)/1000 -> 28.69636 | AZ16: =SUMIF('2020'!$A:$A,$B16,'2020'!J:J)/1000 -> 47.81166 | BA16: =SUMIF('2020'!$A:$A,$B16,'2020'!K:K)/1000 -> 37.55956 | BB16: =SUMIF('2020'!$A:$A,$B16,'2020'!L:L)/1000 -> 46.99177 | BC16: =SUMIF('2020'!$A:$A,$B16,'2020'!M:M)/1000 -> 39.61443 | BD16: =SUMIF('2020'!$A:$A,$B16,'2020'!N:N)/1000 -> 37.23637 | BE16: =SUMIF('2020'!$A:$A,$B16,'2020'!O:O)/1000 -> 31.28131 | BF16: =SUMIF('2021'!$A:$A,$B16,'2021'!D:D)/1000 -> 12.76914 | BG16: =SUMIF('2021'!$A:$A,$B16,'2021'!E:E)/1000 -> 26.23879 | BH16: =SUMIF('2021'!$A:$A,$B16,'2021'!F:F)/1000 -> 40.39637 | BI16: =SUMIF('2021'!$A:$A,$B16,'2021'!G:G)/1000 -> 16.31327 | BJ16: =SUMIF('2021'!$A:$A,$B16,'2021'!H:H)/1000 -> 83.09098 | BK16: =SUMIF('2021'!$A:$A,$B16,'2021'!I:I)/1000 -> -8.01918 | BL16: =SUMIF('2021'!$A:$A,$B16,'2021'!J:J)/1000 -> 75.67395 | BM16: =SUMIF('2021'!$A:$A,$B16,'2021'!K:K)/1000 -> 72.18423 | BN16: =SUMIF('2021'!$A:$A,$B16,'2021'!L:L)/1000 -> 53.18394 | BO16: =SUMIF('2021'!$A:$A,$B16,'2021'!M:M)/1000 -> 25.9091 | BP16: =SUMIF('2021'!$A:$A,$B16,'2021'!N:N)/1000 -> 52.21073 | BQ16: =SUMIF('2021'!$A:$A,$B16,'2021'!O:O)/1000 -> 47.30492 | BR16: =SUMIF('2022'!$A:$A,$B16,'2022'!D:D)/1000 -> 30.08344 | BS16: =SUMIF('2022'!$A:$A,$B16,'2022'!E:E)/1000 -> 64.64001 | BT16: =SUMIF('2022'!$A:$A,$B16,'2022'!F:F)/1000 -> 49.04384 | BU16: =SUMIF('2022'!$A:$A,$B16,'2022'!G:G)/1000 -> 50.48085 | BV16: =SUMIF('2022'!$A:$A,$B16,'2022'!H:H)/1000 -> 50.49065 | BW16: =SUMIF('2022'!$A:$A,$B16,'2022'!I:I)/1000 -> 49.82103 | BX16: =SUMIF('2022'!$A:$A,$B16,'2022'!J:J)/1000 -> 62.49631 | BY16: =SUMIF('2022'!$A:$A,$B16,'2022'!K:K)/1000 -> 59.42293 | BZ16: =SUMIF('2022'!$A:$A,$B16,'2022'!L:L)/1000 -> 62.17483
B17: Ins | C17: Insurance | D17: =SUMIF($A$32:$A$268,$B17,D$32:D$268)/1000 -> 7.568 | E17: =SUMIF($A$32:$A$268,$B17,E$32:E$268)/1000 -> 7.99461 | F17: =SUMIF($A$32:$A$268,$B17,F$32:F$268)/1000 -> 7.43886 | G17: =SUMIF($A$32:$A$268,$B17,G$32:G$268)/1000 -> 7.6241 | H17: =SUMIF($A$32:$A$268,$B17,H$32:H$268)/1000 -> 7.6241 | I17: =SUMIF($A$32:$A$268,$B17,I$32:I$268)/1000 -> 7.6241 | J17: =SUMIF($A$32:$A$268,$B17,J$32:J$268)/1000 -> 7.53491 | K17: =SUMIF($A$32:$A$268,$B17,K$32:K$268)/1000 -> 7.5349 | ... AS17: =SUMIF($A$32:$A$268,$B17,AS$32:AS$268)/1000 -> 7.95182 | AT17: =SUMIF('2020'!$A:$A,$B17,'2020'!D:D)/1000 -> 7.80452 | AU17: =SUMIF('2020'!$A:$A,$B17,'2020'!E:E)/1000 -> 7.9371 | AV17: =SUMIF('2020'!$A:$A,$B17,'2020'!F:F)/1000 -> 7.93729 | AW17: =SUMIF('2020'!$A:$A,$B17,'2020'!G:G)/1000 -> 7.93709 | AX17: =SUMIF('2020'!$A:$A,$B17,'2020'!H:H)/1000 -> 7.9371 | AY17: =SUMIF('2020'!$A:$A,$B17,'2020'!I:I)/1000 -> 7.93709 | AZ17: =SUMIF('2020'!$A:$A,$B17,'2020'!J:J)/1000 -> 2.63965 | BA17: =SUMIF('2020'!$A:$A,$B17,'2020'!K:K)/1000 -> 16.26532 | BB17: =SUMIF('2020'!$A:$A,$B17,'2020'!L:L)/1000 -> 7.22873 | BC17: =SUMIF('2020'!$A:$A,$B17,'2020'!M:M)/1000 -> 13.54173 | BD17: =SUMIF('2020'!$A:$A,$B17,'2020'!N:N)/1000 -> 11.98522 | BE17: =SUMIF('2020'!$A:$A,$B17,'2020'!O:O)/1000 -> 10.38523 | BF17: =SUMIF('2021'!$A:$A,$B17,'2021'!D:D)/1000 -> 10.38523 | BG17: =SUMIF('2021'!$A:$A,$B17,'2021'!E:E)/1000 -> 10.38523 | BH17: =SUMIF('2021'!$A:$A,$B17,'2021'!F:F)/1000 -> 10.38523 | BI17: =SUMIF('2021'!$A:$A,$B17,'2021'!G:G)/1000 -> 10.38523 | BJ17: =SUMIF('2021'!$A:$A,$B17,'2021'!H:H)/1000 -> 10.38523 | BK17: =SUMIF('2021'!$A:$A,$B17,'2021'!I:I)/1000 -> 10.38523 | BL17: =SUMIF('2021'!$A:$A,$B17,'2021'!J:J)/1000 -> 11.22628 | BM17: =SUMIF('2021'!$A:$A,$B17,'2021'!K:K)/1000 -> 11.22628 | BN17: =SUMIF('2021'!$A:$A,$B17,'2021'!L:L)/1000 -> 8.06978 | BO17: =SUMIF('2021'!$A:$A,$B17,'2021'!M:M)/1000 -> 8.06978 | BP17: =SUMIF('2021'!$A:$A,$B17,'2021'!N:N)/1000 -> 24.29623 | BQ17: =SUMIF('2021'!$A:$A,$B17,'2021'!O:O)/1000 -> 7.42073 | BR17: =SUMIF('2022'!$A:$A,$B17,'2022'!D:D)/1000 -> 11.96413 | BS17: =SUMIF('2022'!$A:$A,$B17,'2022'!E:E)/1000 -> 11.96413 | BT17: =SUMIF('2022'!$A:$A,$B17,'2022'!F:F)/1000 -> 11.96413 | BU17: =SUMIF('2022'!$A:$A,$B17,'2022'!G:G)/1000 -> 11.96413 | BV17: =SUMIF('2022'!$A:$A,$B17,'2022'!H:H)/1000 -> 11.96413 | BW17: =SUMIF('2022'!$A:$A,$B17,'2022'!I:I)/1000 -> 11.96417 | BX17: =SUMIF('2022'!$A:$A,$B17,'2022'!J:J)/1000 -> 10.27729 | BY17: =SUMIF('2022'!$A:$A,$B17,'2022'!K:K)/1000 -> -1.91941 | BZ17: =SUMIF('2022'!$A:$A,$B17,'2022'!L:L)/1000 -> 4.17896
B18: Mgmt | C18: Management Fee | D18: =SUMIF($A$32:$A$268,$B18,D$32:D$268)/1000 -> 8.77858 | E18: =SUMIF($A$32:$A$268,$B18,E$32:E$268)/1000 -> 5.19885 | F18: =SUMIF($A$32:$A$268,$B18,F$32:F$268)/1000 -> 6.50919 | G18: =SUMIF($A$32:$A$268,$B18,G$32:G$268)/1000 -> 30.78193 | H18: =SUMIF($A$32:$A$268,$B18,H$32:H$268)/1000 -> 6.71635 | I18: =SUMIF($A$32:$A$268,$B18,I$32:I$268)/1000 -> -20.78193 | J18: =SUMIF($A$32:$A$268,$B18,J$32:J$268)/1000 -> 6.40832 | K18: =SUMIF($A$32:$A$268,$B18,K$32:K$268)/1000 -> 5.35588 | ... AS18: =SUMIF($A$32:$A$268,$B18,AS$32:AS$268)/1000 -> 7.10512 | AT18: =SUMIF('2020'!$A:$A,$B18,'2020'!D:D)/1000 -> 7.25034 | AU18: =SUMIF('2020'!$A:$A,$B18,'2020'!E:E)/1000 -> 14.41863 | AV18: =SUMIF('2020'!$A:$A,$B18,'2020'!F:F)/1000 -> 6.7867 | AW18: =SUMIF('2020'!$A:$A,$B18,'2020'!G:G)/1000 -> 5 | AX18: =SUMIF('2020'!$A:$A,$B18,'2020'!H:H)/1000 -> 6.3442 | AY18: =SUMIF('2020'!$A:$A,$B18,'2020'!I:I)/1000 -> 5 | AZ18: =SUMIF('2020'!$A:$A,$B18,'2020'!J:J)/1000 -> 5 | BA18: =SUMIF('2020'!$A:$A,$B18,'2020'!K:K)/1000 -> 5 | BB18: =SUMIF('2020'!$A:$A,$B18,'2020'!L:L)/1000 -> 6.8791 | BC18: =SUMIF('2020'!$A:$A,$B18,'2020'!M:M)/1000 -> 5.92012 | BD18: =SUMIF('2020'!$A:$A,$B18,'2020'!N:N)/1000 -> 5 | BE18: =SUMIF('2020'!$A:$A,$B18,'2020'!O:O)/1000 -> 5 | BF18: =SUMIF('2021'!$A:$A,$B18,'2021'!D:D)/1000 -> 5 | BG18: =SUMIF('2021'!$A:$A,$B18,'2021'!E:E)/1000 -> 6.18006 | BH18: =SUMIF('2021'!$A:$A,$B18,'2021'!F:F)/1000 -> 8.25329 | BI18: =SUMIF('2021'!$A:$A,$B18,'2021'!G:G)/1000 -> 6.90604 | BJ18: =SUMIF('2021'!$A:$A,$B18,'2021'!H:H)/1000 -> 5.14193 | BK18: =SUMIF('2021'!$A:$A,$B18,'2021'!I:I)/1000 -> 7.00987 | BL18: =SUMIF('2021'!$A:$A,$B18,'2021'!J:J)/1000 -> 5.35447 | BM18: =SUMIF('2021'!$A:$A,$B18,'2021'!K:K)/1000 -> 6.0891 | BN18: =SUMIF('2021'!$A:$A,$B18,'2021'!L:L)/1000 -> 5.34905 | BO18: =SUMIF('2021'!$A:$A,$B18,'2021'!M:M)/1000 -> 5.42085 | BP18: =SUMIF('2021'!$A:$A,$B18,'2021'!N:N)/1000 -> 5.41004 | BQ18: =SUMIF('2021'!$A:$A,$B18,'2021'!O:O)/1000 -> 5.48489 | BR18: =SUMIF('2022'!$A:$A,$B18,'2022'!D:D)/1000 -> 7.28035 | BS18: =SUMIF('2022'!$A:$A,$B18,'2022'!E:E)/1000 -> 9.42523 | BT18: =SUMIF('2022'!$A:$A,$B18,'2022'!F:F)/1000 -> 7.64309 | BU18: =SUMIF('2022'!$A:$A,$B18,'2022'!G:G)/1000 -> 6.95981 | BV18: =SUMIF('2022'!$A:$A,$B18,'2022'!H:H)/1000 -> 10.31265 | BW18: =SUMIF('2022'!$A:$A,$B18,'2022'!I:I)/1000 -> 5 | BX18: =SUMIF('2022'!$A:$A,$B18,'2022'!J:J)/1000 -> 5 | BY18: =SUMIF('2022'!$A:$A,$B18,'2022'!K:K)/1000 -> 5 | BZ18: =SUMIF('2022'!$A:$A,$B18,'2022'!L:L)/1000 -> 9.76567
B19: ParkExp | C19: Parking | D19: =SUMIF($A$32:$A$268,$B19,D$32:D$268)/1000 -> 0 | E19: =SUMIF($A$32:$A$268,$B19,E$32:E$268)/1000 -> 0 | F19: =SUMIF($A$32:$A$268,$B19,F$32:F$268)/1000 -> 0 | G19: =SUMIF($A$32:$A$268,$B19,G$32:G$268)/1000 -> 0 | H19: =SUMIF($A$32:$A$268,$B19,H$32:H$268)/1000 -> 0 | I19: =SUMIF($A$32:$A$268,$B19,I$32:I$268)/1000 -> 0 | J19: =SUMIF($A$32:$A$268,$B19,J$32:J$268)/1000 -> 0 | K19: =SUMIF($A$32:$A$268,$B19,K$32:K$268)/1000 -> 0 | ... AS19: =SUMIF($A$32:$A$268,$B19,AS$32:AS$268)/1000 -> 0 | AT19: =SUMIF('2020'!$A:$A,$B19,'2020'!D:D)/1000 -> 0 | AU19: =SUMIF('2020'!$A:$A,$B19,'2020'!E:E)/1000 -> 0 | AV19: =SUMIF('2020'!$A:$A,$B19,'2020'!F:F)/1000 -> 0 | AW19: =SUMIF('2020'!$A:$A,$B19,'2020'!G:G)/1000 -> 0 | AX19: =SUMIF('2020'!$A:$A,$B19,'2020'!H:H)/1000 -> 0 | AY19: =SUMIF('2020'!$A:$A,$B19,'2020'!I:I)/1000 -> 0 | AZ19: =SUMIF('2020'!$A:$A,$B19,'2020'!J:J)/1000 -> 0 | BA19: =SUMIF('2020'!$A:$A,$B19,'2020'!K:K)/1000 -> 0 | BB19: =SUMIF('2020'!$A:$A,$B19,'2020'!L:L)/1000 -> 0 | BC19: =SUMIF('2020'!$A:$A,$B19,'2020'!M:M)/1000 -> 0 | BD19: =SUMIF('2020'!$A:$A,$B19,'2020'!N:N)/1000 -> 0 | BE19: =SUMIF('2020'!$A:$A,$B19,'2020'!O:O)/1000 -> 0 | BF19: =SUMIF('2021'!$A:$A,$B19,'2021'!D:D)/1000 -> 0 | BG19: =SUMIF('2021'!$A:$A,$B19,'2021'!E:E)/1000 -> 0 | BH19: =SUMIF('2021'!$A:$A,$B19,'2021'!F:F)/1000 -> 0 | BI19: =SUMIF('2021'!$A:$A,$B19,'2021'!G:G)/1000 -> 0 | BJ19: =SUMIF('2021'!$A:$A,$B19,'2021'!H:H)/1000 -> 0 | BK19: =SUMIF('2021'!$A:$A,$B19,'2021'!I:I)/1000 -> 0 | BL19: =SUMIF('2021'!$A:$A,$B19,'2021'!J:J)/1000 -> 0 | BM19: =SUMIF('2021'!$A:$A,$B19,'2021'!K:K)/1000 -> 0 | BN19: =SUMIF('2021'!$A:$A,$B19,'2021'!L:L)/1000 -> 0 | BO19: =SUMIF('2021'!$A:$A,$B19,'2021'!M:M)/1000 -> 0 | BP19: =SUMIF('2021'!$A:$A,$B19,'2021'!N:N)/1000 -> 0 | BQ19: =SUMIF('2021'!$A:$A,$B19,'2021'!O:O)/1000 -> 0 | BR19: =SUMIF('2022'!$A:$A,$B19,'2022'!D:D)/1000 -> 0 | BS19: =SUMIF('2022'!$A:$A,$B19,'2022'!E:E)/1000 -> 0 | BT19: =SUMIF('2022'!$A:$A,$B19,'2022'!F:F)/1000 -> 0 | BU19: =SUMIF('2022'!$A:$A,$B19,'2022'!G:G)/1000 -> 0 | BV19: =SUMIF('2022'!$A:$A,$B19,'2022'!H:H)/1000 -> 0 | BW19: =SUMIF('2022'!$A:$A,$B19,'2022'!I:I)/1000 -> 0 | BX19: =SUMIF('2022'!$A:$A,$B19,'2022'!J:J)/1000 -> 0 | BY19: =SUMIF('2022'!$A:$A,$B19,'2022'!K:K)/1000 -> 0 | BZ19: =SUMIF('2022'!$A:$A,$B19,'2022'!L:L)/1000 -> 0
B20: Tax | C20: Real Estate Taxes | D20: =SUMIF($A$32:$A$268,$B20,D$32:D$268)/1000 -> 30.8 | E20: =SUMIF($A$32:$A$268,$B20,E$32:E$268)/1000 -> 30.8 | F20: =SUMIF($A$32:$A$268,$B20,F$32:F$268)/1000 -> 30.8 | G20: =SUMIF($A$32:$A$268,$B20,G$32:G$268)/1000 -> 46.12409 | H20: =SUMIF($A$32:$A$268,$B20,H$32:H$268)/1000 -> 34.63102 | I20: =SUMIF($A$32:$A$268,$B20,I$32:I$268)/1000 -> -2.88902 | J20: =SUMIF($A$32:$A$268,$B20,J$32:J$268)/1000 -> 31.56873 | K20: =SUMIF($A$32:$A$268,$B20,K$32:K$268)/1000 -> 31.67909 | ... AS20: =SUMIF($A$32:$A$268,$B20,AS$32:AS$268)/1000 -> 31.20076 | AT20: =SUMIF('2020'!$A:$A,$B20,'2020'!D:D)/1000 -> 34.96776 | AU20: =SUMIF('2020'!$A:$A,$B20,'2020'!E:E)/1000 -> 31.99826 | AV20: =SUMIF('2020'!$A:$A,$B20,'2020'!F:F)/1000 -> 37.66313 | AW20: =SUMIF('2020'!$A:$A,$B20,'2020'!G:G)/1000 -> 32.22342 | AX20: =SUMIF('2020'!$A:$A,$B20,'2020'!H:H)/1000 -> 31.08821 | AY20: =SUMIF('2020'!$A:$A,$B20,'2020'!I:I)/1000 -> 33.08823 | AZ20: =SUMIF('2020'!$A:$A,$B20,'2020'!J:J)/1000 -> 31.08821 | BA20: =SUMIF('2020'!$A:$A,$B20,'2020'!K:K)/1000 -> 31.26821 | BB20: =SUMIF('2020'!$A:$A,$B20,'2020'!L:L)/1000 -> 31.08821 | BC20: =SUMIF('2020'!$A:$A,$B20,'2020'!M:M)/1000 -> 36.74341 | BD20: =SUMIF('2020'!$A:$A,$B20,'2020'!N:N)/1000 -> 32.50201 | BE20: =SUMIF('2020'!$A:$A,$B20,'2020'!O:O)/1000 -> 32.50201 | BF20: =SUMIF('2021'!$A:$A,$B20,'2021'!D:D)/1000 -> 32.50201 | BG20: =SUMIF('2021'!$A:$A,$B20,'2021'!E:E)/1000 -> 36.12103 | BH20: =SUMIF('2021'!$A:$A,$B20,'2021'!F:F)/1000 -> 39.30201 | BI20: =SUMIF('2021'!$A:$A,$B20,'2021'!G:G)/1000 -> 32.50201 | BJ20: =SUMIF('2021'!$A:$A,$B20,'2021'!H:H)/1000 -> 32.50201 | BK20: =SUMIF('2021'!$A:$A,$B20,'2021'!I:I)/1000 -> 32.502 | BL20: =SUMIF('2021'!$A:$A,$B20,'2021'!J:J)/1000 -> 34.50201 | BM20: =SUMIF('2021'!$A:$A,$B20,'2021'!K:K)/1000 -> 32.50201 | BN20: =SUMIF('2021'!$A:$A,$B20,'2021'!L:L)/1000 -> 32.50201 | BO20: =SUMIF('2021'!$A:$A,$B20,'2021'!M:M)/1000 -> 31.15838 | BP20: =SUMIF('2021'!$A:$A,$B20,'2021'!N:N)/1000 -> 32.1661 | BQ20: =SUMIF('2021'!$A:$A,$B20,'2021'!O:O)/1000 -> 32.16608 | BR20: =SUMIF('2022'!$A:$A,$B20,'2022'!D:D)/1000 -> 32.16609 | BS20: =SUMIF('2022'!$A:$A,$B20,'2022'!E:E)/1000 -> 32.16609 | BT20: =SUMIF('2022'!$A:$A,$B20,'2022'!F:F)/1000 -> 39.49685 | BU20: =SUMIF('2022'!$A:$A,$B20,'2022'!G:G)/1000 -> 32.16609 | BV20: =SUMIF('2022'!$A:$A,$B20,'2022'!H:H)/1000 -> 32.37373 | BW20: =SUMIF('2022'!$A:$A,$B20,'2022'!I:I)/1000 -> 32.1661 | BX20: =SUMIF('2022'!$A:$A,$B20,'2022'!J:J)/1000 -> 34.1661 | BY20: =SUMIF('2022'!$A:$A,$B20,'2022'!K:K)/1000 -> 41.78173 | BZ20: =SUMIF('2022'!$A:$A,$B20,'2022'!L:L)/1000 -> 32.20887
C21: Total Operating Expenses | D21: =SUM(D13:D20) -> 115.59081 | E21: =SUM(E13:E20) -> 144.24526 | F21: =SUM(F13:F20) -> 124.63961 | G21: =SUM(G13:G20) -> 166.90174 | H21: =SUM(H13:H20) -> 107.83644 | I21: =SUM(I13:I20) -> 126.94687 | J21: =SUM(J13:J20) -> 114.6332 | K21: =SUM(K13:K20) -> 103.62411 | ... BZ21: =SUM(BZ13:BZ20) -> 145.12935
B23: NOI | C23: Net Operating Income | D23: =D11-D21 -> 58.58841 | E23: =E11-E21 -> 39.42486 | F23: =F11-F21 -> 62.16451 | G23: =G11-G21 -> 23.67331 | H23: =H11-H21 -> 69.42784 | I23: =I11-I21 -> 53.22136 | J23: =J11-J21 -> 66.13957 | K23: =K11-K21 -> 136.2636 | ... BZ23: =BZ11-BZ21 -> 127.58223
D24: =D23=(D227/1000) -> TRUE | E24: =E23=(E227/1000) -> TRUE | F24: =F23=(F227/1000) -> TRUE | G24: =G23=(G227/1000) -> TRUE | H24: =H23=(H227/1000) -> TRUE | I24: =I23=(I227/1000) -> TRUE | J24: =J23=(J227/1000) -> TRUE | K24: =K23=(K227/1000) -> TRUE | ... AS24: =AS23=(AS227/1000) -> TRUE | AT24: =AT23=('2020'!D158/1000) -> TRUE | AU24: =AU23=('2020'!E158/1000) -> TRUE | AV24: =AV23=('2020'!F158/1000) -> TRUE | AW24: =AW23=('2020'!G158/1000) -> TRUE | AX24: =AX23=('2020'!H158/1000) -> TRUE | AY24: =AY23=('2020'!I158/1000) -> TRUE | AZ24: =AZ23=('2020'!J158/1000) -> TRUE | BA24: =BA23=('2020'!K158/1000) -> TRUE | ... BE24: =BE23=('2020'!O158/1000) -> FALSE | BF24: =BF23=('2021'!D149/1000) -> TRUE | BG24: =BG23=('2021'!E149/1000) -> TRUE | BH24: =BH23=('2021'!F149/1000) -> TRUE | BI24: =BI23=('2021'!G149/1000) -> TRUE | BJ24: =BJ23=('2021'!H149/1000) -> TRUE | BK24: =BK23=('2021'!I149/1000) -> TRUE | BL24: =BL23=('2021'!J149/1000) -> TRUE | BM24: =BM23=('2021'!K149/1000) -> TRUE | ... BQ24: =BQ23=('2021'!O149/1000) -> TRUE | BR24: =BR23=('2022'!D125/1000) -> TRUE | BS24: =BS23=('2022'!E125/1000) -> TRUE | BT24: =BT23=('2022'!F125/1000) -> TRUE | BU24: =BU23=('2022'!G125/1000) -> TRUE | BV24: =BV23=('2022'!H125/1000) -> TRUE | BW24: =BW23=('2022'!I125/1000) -> TRUE | BX24: =BX23=('2022'!J125/1000) -> TRUE | BY24: =BY23=('2022'!K125/1000) -> TRUE | BZ24: =BZ23=('2022'!L125/1000) -> TRUE
B25: Int | C25: Interest | D25: =SUMIF($A$32:$A$268,$B25,D$32:D$268)/1000 -> 99.81788 | E25: =SUMIF($A$32:$A$268,$B25,E$32:E$268)/1000 -> 107.07263 | F25: =SUMIF($A$32:$A$268,$B25,F$32:F$268)/1000 -> 93.75655 | G25: =SUMIF($A$32:$A$268,$B25,G$32:G$268)/1000 -> 97.47707 | H25: =SUMIF($A$32:$A$268,$B25,H$32:H$268)/1000 -> 93.8024 | I25: =SUMIF($A$32:$A$268,$B25,I$32:I$268)/1000 -> 97.24742 | J25: =SUMIF($A$32:$A$268,$B25,J$32:J$268)/1000 -> 97.71427 | K25: =SUMIF($A$32:$A$268,$B25,K$32:K$268)/1000 -> 94.31804 | ... AS25: =SUMIF($A$32:$A$268,$B25,AS$32:AS$268)/1000 -> 131.68058 | AT25: =SUMIF('2020'!$A$6:$A$183,Historicals!$B25,'2020'!D$6:D$183)/1000 -> 131.19252 | AU25: =SUMIF('2020'!$A$6:$A$183,Historicals!$B25,'2020'!E$6:E$183)/1000 -> 121.62235 | AV25: =SUMIF('2020'!$A$6:$A$183,Historicals!$B25,'2020'!F$6:F$183)/1000 -> 129.67227 | AW25: =SUMIF('2020'!$A$6:$A$183,Historicals!$B25,'2020'!G$6:G$183)/1000 -> 108.16163 | AX25: =SUMIF('2020'!$A$6:$A$183,Historicals!$B25,'2020'!H$6:H$183)/1000 -> 113.8128 | AY25: =SUMIF('2020'!$A$6:$A$183,Historicals!$B25,'2020'!I$6:I$183)/1000 -> 104.43818 | AZ25: =SUMIF('2020'!$A$6:$A$183,Historicals!$B25,'2020'!J$6:J$183)/1000 -> 107.91946 | BA25: =SUMIF('2020'!$A$6:$A$183,Historicals!$B25,'2020'!K$6:K$183)/1000 -> 107.91946 | ... BE25: =SUMIF('2020'!$A$6:$A$183,Historicals!$B25,'2020'!O$6:O$183)/1000 -> 107.91946 | BF25: =SUMIF('2021'!$A:$A,$B25,'2021'!D:D)/1000 -> 107.91945 | BG25: =SUMIF('2021'!$A:$A,$B25,'2021'!E:E)/1000 -> 97.47563 | BH25: =SUMIF('2021'!$A:$A,$B25,'2021'!F:F)/1000 -> 107.91945 | BI25: =SUMIF('2021'!$A:$A,$B25,'2021'!G:G)/1000 -> 104.43818 | BJ25: =SUMIF('2021'!$A:$A,$B25,'2021'!H:H)/1000 -> 107.91946 | BK25: =SUMIF('2021'!$A:$A,$B25,'2021'!I:I)/1000 -> 107.63529 | BL25: =SUMIF('2021'!$A:$A,$B25,'2021'!J:J)/1000 -> 99.10953 | BM25: =SUMIF('2021'!$A:$A,$B25,'2021'!K:K)/1000 -> 99.10952 | BN25: =SUMIF('2021'!$A:$A,$B25,'2021'!L:L)/1000 -> 95.91244 | BO25: =SUMIF('2021'!$A:$A,$B25,'2021'!M:M)/1000 -> 99.10951 | BP25: =SUMIF('2021'!$A:$A,$B25,'2021'!N:N)/1000 -> 96.31616 | BQ25: =SUMIF('2021'!$A:$A,$B25,'2021'!O:O)/1000 -> 100.07224 | BR25: =SUMIF('2022'!$A:$A,$B25,'2022'!D:D)/1000 -> 100.07224 | BS25: =SUMIF('2022'!$A:$A,$B25,'2022'!E:E)/1000 -> 90.38783 | BT25: =SUMIF('2022'!$A:$A,$B25,'2022'!F:F)/1000 -> 101.28279 | BU25: =SUMIF('2022'!$A:$A,$B25,'2022'!G:G)/1000 -> 100.18088 | BV25: =SUMIF('2022'!$A:$A,$B25,'2022'!H:H)/1000 -> 110.84981 | BW25: =SUMIF('2022'!$A:$A,$B25,'2022'!I:I)/1000 -> 108.56345 | BX25: =SUMIF('2022'!$A:$A,$B25,'2022'!J:J)/1000 -> 133.17431 | BY25: =SUMIF('2022'!$A:$A,$B25,'2022'!K:K)/1000 -> 141.79045 | BZ25: =SUMIF('2022'!$A:$A,$B25,'2022'!L:L)/1000 -> 112.83533
B26: LoanFee | C26: Loan Fee | D26: =SUMIF($A$32:$A$268,$B26,D$32:D$268)/1000 -> 11.59471 | E26: =SUMIF($A$32:$A$268,$B26,E$32:E$268)/1000 -> 11.59471 | F26: =SUMIF($A$32:$A$268,$B26,F$32:F$268)/1000 -> 11.37483 | G26: =SUMIF($A$32:$A$268,$B26,G$32:G$268)/1000 -> 11.52141 | H26: =SUMIF($A$32:$A$268,$B26,H$32:H$268)/1000 -> 11.52141 | I26: =SUMIF($A$32:$A$268,$B26,I$32:I$268)/1000 -> 495.42085 | J26: =SUMIF($A$32:$A$268,$B26,J$32:J$268)/1000 -> 0 | K26: =SUMIF($A$32:$A$268,$B26,K$32:K$268)/1000 -> 0 | ... AS26: =SUMIF($A$32:$A$268,$B26,AS$32:AS$268)/1000 -> 0 | AT26: =SUMIF('2020'!$A$6:$A$183,Historicals!$B26,'2020'!D$6:D$183)/1000 -> 0 | AU26: =SUMIF('2020'!$A$6:$A$183,Historicals!$B26,'2020'!E$6:E$183)/1000 -> 0 | AV26: =SUMIF('2020'!$A$6:$A$183,Historicals!$B26,'2020'!F$6:F$183)/1000 -> 0 | AW26: =SUMIF('2020'!$A$6:$A$183,Historicals!$B26,'2020'!G$6:G$183)/1000 -> 0 | AX26: =SUMIF('2020'!$A$6:$A$183,Historicals!$B26,'2020'!H$6:H$183)/1000 -> 0 | AY26: =SUMIF('2020'!$A$6:$A$183,Historicals!$B26,'2020'!I$6:I$183)/1000 -> 0 | AZ26: =SUMIF('2020'!$A$6:$A$183,Historicals!$B26,'2020'!J$6:J$183)/1000 -> 0 | BA26: =SUMIF('2020'!$A$6:$A$183,Historicals!$B26,'2020'!K$6:K$183)/1000 -> 0 | ... BE26: =SUMIF('2020'!$A$6:$A$183,Historicals!$B26,'2020'!O$6:O$183)/1000 -> 0 | BF26: =SUMIF('2021'!$A:$A,$B26,'2021'!D:D)/1000 -> 0 | BG26: =SUMIF('2021'!$A:$A,$B26,'2021'!E:E)/1000 -> 0 | BH26: =SUMIF('2021'!$A:$A,$B26,'2021'!F:F)/1000 -> -18.62625 | BI26: =SUMIF('2021'!$A:$A,$B26,'2021'!G:G)/1000 -> 0 | BJ26: =SUMIF('2021'!$A:$A,$B26,'2021'!H:H)/1000 -> 0 | BK26: =SUMIF('2021'!$A:$A,$B26,'2021'!I:I)/1000 -> 840.87529 | BL26: =SUMIF('2021'!$A:$A,$B26,'2021'!J:J)/1000 -> 0 | BM26: =SUMIF('2021'!$A:$A,$B26,'2021'!K:K)/1000 -> -53.317 | BN26: =SUMIF('2021'!$A:$A,$B26,'2021'!L:L)/1000 -> 0 | BO26: =SUMIF('2021'!$A:$A,$B26,'2021'!M:M)/1000 -> -6 | BP26: =SUMIF('2021'!$A:$A,$B26,'2021'!N:N)/1000 -> 0 | BQ26: =SUMIF('2021'!$A:$A,$B26,'2021'!O:O)/1000 -> 0 | BR26: =SUMIF('2022'!$A:$A,$B26,'2022'!D:D)/1000 -> 0 | BS26: =SUMIF('2022'!$A:$A,$B26,'2022'!E:E)/1000 -> 0 | BT26: =SUMIF('2022'!$A:$A,$B26,'2022'!F:F)/1000 -> 0 | BU26: =SUMIF('2022'!$A:$A,$B26,'2022'!G:G)/1000 -> 0 | BV26: =SUMIF('2022'!$A:$A,$B26,'2022'!H:H)/1000 -> 0 | BW26: =SUMIF('2022'!$A:$A,$B26,'2022'!I:I)/1000 -> 0 | BX26: =SUMIF('2022'!$A:$A,$B26,'2022'!J:J)/1000 -> 0 | BY26: =SUMIF('2022'!$A:$A,$B26,'2022'!K:K)/1000 -> 0 | BZ26: =SUMIF('2022'!$A:$A,$B26,'2022'!L:L)/1000 -> 0
B28: Chapman-Arc LLC (14890)
B29: Statement (12 months)
B30: Period = Jul 2016-Jun 2017
B31: Book = Accrual,External,FMV ; Tree = ysi_is
D32: 42582 | E32: =EOMONTH(D32,1) -> 42613 | F32: =EOMONTH(E32,1) -> 42643 | G32: =EOMONTH(F32,1) -> 42674 | H32: =EOMONTH(G32,1) -> 42704 | I32: =EOMONTH(H32,1) -> 42735 | J32: =EOMONTH(I32,1) -> 42766 | K32: =EOMONTH(J32,1) -> 42794 | L32: =EOMONTH(K32,1) -> 42825 | ... BD32: =EOMONTH(BC32,1) -> 44165
B33: 40000-000 | C33: INCOME (LOSS) STATEMENT
B35: 40000-010 | C35: NET OPERATING INCOME (LOSS)
B37: 40000-100 | C37: OPERATING REVENUE
B38: 40001-000 | C38: Rent Revenue
B39: 40010-000 | C39: Base Rent
