Workbook
Name IQ_CH: 110000
Name IQ_CQ: 5000
Name IQ_CY: 10000
Name IQ_DAILY: 500000
Name IQ_FH: 100000
Name IQ_FQ: 500
Name IQ_FY: 1000
Name IQ_LTM: 2000
Name IQ_MONTH: 15000
Name IQ_NTM: 6000
Name IQ_WEEK: 50000
Name IQ_YTD: 3000

Sheet Cover
C9: CA South Development
C11: =+Dashboard!C5 -> 1425 4th Ave
C14: Preliminary
C16: =TODAY() -> 45037

Sheet Massing

Sheet Sheet2
C5: Mad Dog | D5: Charlotte
B6: Hard cost | C6: ='Budget Detail'!K66+'Budget Detail'!K68 -> 35728298 | D6: 30500000
B7: Total GSF | C7: =Assumptions!K34 -> 195551 | D7: 146824
B8: $/GSF | C8: =C6/C7 -> 182.70578 | D8: =D6/D7 -> 207.73171
B10: Interior Built SF | C10: =Assumptions!J36 -> 135381 | D10: 123355
B11: $/SF | C11: =C6/C10 -> 263.90925 | D11: =D6/D10 -> 247.25386
C13: =C7-C10 -> 60170 | D13: =D7-D10 -> 23469

Sheet Sheet1
B2: Hard Cost Comparison
C3: O'Neil Budget | D3: O'Neil Budget (Ben's Revisions) | E3: 1425 Budget Last Sent to Argosy | F3: 1425 Budget Current Update to Acieve 5.5% ROC
B5: Hard Costs | C5: 38130142 | D5: 36700000 | E5: 35008771 | F5: ='Budget Detail'!K68++'Budget Detail'!K66 -> 35728298
B6: Gross SF | C6: 196602 | D6: 196602 | E6: 196602 | F6: 196602
B7: $/SF | C7: =C5/C6 -> 193.94585 | D7: =D5/D6 -> 186.67155 | E7: =E5/E6 -> 178.06925 | F7: =F5/F6 -> 181.72907
B10: Hard Cost Comparison
C11: 1425 Budget Current Update to Acieve 5.5% ROC | D11: 405 40th Budget
B12: Hard Costs | C12: =F5 -> 35728298 | D12: 33058410
B13: Gross SF | C13: =F6 -> 196602 | D13: 149267
B14: $/SF | C14: =C12/C13 -> 181.72907 | D14: =D12/D13 -> 221.47166
E15: =(D14-C14)/C14 -> 0.21869144

Sheet Dashboard
B5: Name | C5: =Assumptions!E3 -> 1425 4th Ave
B6: Asset Class | C6: =Assumptions!E4 -> Multifamily
B7: Asset Disposition | C7: Stabilized Sale
B8: Leasable / Saleable SF | C8: =Assumptions!J35 -> 103297
B10: Residential Program Summary
B11: Unit Type | C11: Count | D11: Unit % | E11: Unit Size | F11: Total LSF | G11: LSF % | H11: Gross Annual Rent | I11: Rent/Unit | J11: Rent/Bedroom | K11: Rent/LSF | M11: Bed/Unit
B12: =Assumptions!B28 -> Studio | C12: =Assumptions!C28 -> 12 | D12: =C12/$C$18 -> 0.091603053 | E12: =Assumptions!E28 -> 458 | F12: =Assumptions!F28 -> 5496 | G12: =F12/$F$18 -> 0.053205805 | H12: =I12*C12*12 -> 216000 | I12: ='Rent Comps'!D70 -> 1500 | J12: =I12/M12 -> 1500 | K12: =I12/E12 -> 3.2751092 | M12: 1
B13: =Assumptions!B29 -> 1 bed | C13: =Assumptions!C29 -> 76 | D13: =C13/$C$18 -> 0.58015267 | E13: =Assumptions!E29 -> 702.18421 | F13: =Assumptions!F29 -> 53366 | G13: =F13/$F$18 -> 0.51662681 | H13: =I13*C13*12 -> 1732800 | I13: ='Rent Comps'!D71 -> 1900 | J13: =I13/M13 -> 1900 | K13: =I13/E13 -> 2.7058427 | M13: 1
B14: =Assumptions!B30 -> 2 Bed | C14: =Assumptions!C30 -> 37 | D14: =C14/$C$18 -> 0.28244275 | E14: =Assumptions!E30 -> 1016.8919 | F14: =Assumptions!F30 -> 37625 | G14: =F14/$F$18 -> 0.36424098 | H14: =I14*C14*12 -> 1287600 | I14: ='Rent Comps'!D72 -> 2900 | J14: =I14/M14 -> 1450 | K14: =I14/E14 -> 2.8518272 | M14: 2
B15: =Assumptions!B31 -> 2 Bed Plus | C15: =Assumptions!C31 -> 2 | D15: =C15/$C$18 -> 0.015267176 | E15: =Assumptions!E31 -> 1485 | F15: =Assumptions!F31 -> 2970 | G15: =F15/$F$18 -> 0.028752045 | H15: =I15*C15*12 -> 84000 | I15: ='Rent Comps'!D73 -> 3500 | J15: =I15/M15 -> 1750 | K15: =I15/E15 -> 2.3569024 | M15: 2
B16: Live/Work | C16: =Assumptions!C32 -> 4 | D16: =C16/$C$18 -> 0.030534351 | E16: =Assumptions!E32 -> 960 | F16: =Assumptions!F32 -> 3840 | G16: =F16/$F$18 -> 0.037174361 | H16: =I16*C16*12 -> 139200 | I16: ='Rent Comps'!D74 -> 2900 | J16: =I16/M16 -> 966.66667 | K16: =IFERROR(I16/E16,0) -> 3.0208333 | M16: 3
B18: Total | C18: =SUM(C12:C17) -> 131 | D18: =SUM(D12:D17) -> 1 | E18: =F18/C18 -> 788.52672 | F18: =SUM(F12:F17) -> 103297 | G18: =SUM(G12:G17) -> 1 | H18: =SUM(H12:H17) -> 3459600 | I18: =SUMPRODUCT(I12:I17,C12:C17)/C18 -> 2200.7634 | J18: =SUMPRODUCT(M12:M17,C12:C17,J12:J17)/SUMPRODUCT(M12:M17,C12:C17) -> 1619.6629 | K18: =I18/E18 -> 2.7909813
B20: STR Unit Mix / Rates
B21: Unit Type | C21: Count | D21: Unit % | E21: Unit Size | F21: Total LSF | G21: LSF % | H21: Gross Expected Revenue | I21: ADR | J21: Vacancy | K21: RevPar
B22: =B12 -> Studio | C22: =Assumptions!C28 -> 12 | D22: =C22/$C$26 -> 0.091603053 | E22: =Assumptions!E28 -> 458 | F22: =E22*C22 -> 5496 | G22: =F22/$F$26 -> 0.053205805 | H22: =((I22*365)*C22)*(1-J22) -> 830886 | I22: ='Assumptions MH'!E71 -> 271 | J22: =1-'Assumptions MH'!D71 -> 0.3 | K22: =I22*(1-J22) -> 189.7
B23: 1 bed | C23: =Assumptions!C29+Assumptions!C32 -> 80 | D23: =C23/$C$26 -> 0.61068702 | E23: =((Assumptions!C29*Assumptions!E29)+(Assumptions!C32*Assumptions!E32))/(Assumptions!C29+Assumptions!C32) -> 715.075 | F23: =E23*C23 -> 57206 | G23: =F23/$F$26 -> 0.55380118 | H23: =((I23*365)*C23)*(1-J23) -> 5539240 | I23: ='Assumptions MH'!E72 -> 271 | J23: =1-'Assumptions MH'!D72 -> 0.3 | K23: =I23*(1-J23) -> 189.7
B24: 2 Bed | C24: =Assumptions!C30+Assumptions!C31 -> 39 | D24: =C24/$C$26 -> 0.29770992 | E24: =((Assumptions!C30*Assumptions!E30)+(Assumptions!C31*Assumptions!E31))/(Assumptions!C30+Assumptions!C31) -> 1040.8974 | F24: =E24*C24 -> 40595 | G24: =F24/$F$26 -> 0.39299302 | H24: =((I24*365)*C24)*(1-J24) -> 2700379.5 | I24: ='Assumptions MH'!E73 -> 271 | J24: =1-'Assumptions MH'!D73 -> 0.3 | K24: =I24*(1-J24) -> 189.7
B26: Total | C26: =SUM(C22:C25) -> 131 | D26: =SUM(D22:D25) -> 1 | E26: =F26/C26 -> 788.52672 | F26: =SUM(F22:F25) -> 103297 | G26: =SUM(G22:G25) -> 1 | H26: =((I26*365)*C26)*(1-J26) -> 9070505.5 | I26: =SUMPRODUCT(I22:I25,C22:C25)/C26 -> 271 | J26: =1-(K26/I26) -> 0.3 | K26: =SUMPRODUCT(K22:K25,C22:C25)/C26 -> 189.7
B28: Uses | G28: Return-On-Cost | J28: Trended | K28: Un-Trended
C29: Total | D29: % Total | E29: $/LSF | G29: Stabilized Year | J29: 3
B30: Land | C30: =Assumptions!N12 -> 5200000 | D30: =+C30/C$37 -> 0.094572528 | E30: =C30/$C$8 -> 50.340281 | G30: Rent Growth at Stabilization | J30: ='Assumptions MH'!T6 -> 0.03
B31: Construction Costs + Contingency | C31: =Assumptions!N27 -> 38440298 | D31: =+C31/C$37 -> 0.69911464 | E31: =C31/$C$8 -> 372.13373 | G31: Expense Growth at Stabilization | J31: ='Assumptions MH'!T9 -> 0.03
B32: Soft Costs + Contingency | C32: =Assumptions!N33-C36-C34 -> 8322236.8 | D32: =+C32/C$37 -> 0.15135672 | E32: =C32/$C$8 -> 80.566103 | G32: Net Revenue - Residential | J32: =K32*(1+$J$30)^($J$29-1) -> 9622899.3 | K32: =H26 -> 9070505.5
B33: TI | C33: ='Budget Detail'!$K$72 -> 0 | D33: =+C33/C$37 -> 0 | E33: =C33/$C$8 -> 0
B34: Lease-Up Costs | C34: =Assumptions!E16+Assumptions!E20 -> 300000 | D34: =+C34/C$37 -> 0.0054561074 | E34: =C34/$C$8 -> 2.904247 | G34: Parking Income | J34: =K34*(1+$J$30)^($J$29-1) -> 429533.21 | K34: =(('Assumptions MH'!L41*'Assumptions MH'!L42*'Assumptions MH'!L43*'Assumptions MH'!L44*'Assumptions MH'!L45)*365)*0.75 -> 404876.25
B35: Total Budget | C35: =SUM(C30:C34) -> 52262535 | D35: =+C35/C$37 -> 0.9505 | E35: =SUM(E30:E34) -> 505.94436 | G35: Net Revenue | J35: =SUM(J32:J34) -> 10052432 | K35: =SUM(K32:K34) -> 9475381.8
B36: Construction Loan D/S | C36: ='Budget Detail'!K22+'Budget Detail'!K23 -> 2721720.6 | D36: =+C36/C$37 -> 0.0495 | E36: =C36/$C$8 -> 26.348496 | G36: Opex & Profit Split(1) | J36: =K36*(1+$J$31)^($J$29-1) -> -5588397.6 | K36: =(-'Stabalized NOI'!F42-'Stabalized NOI'!F63-'Stabalized NOI'!F69-'Stabalized NOI'!F80-'Stabalized NOI'!F86)-('RE Tax'!J44*Dashboard!C26)-((Assumptions!$I$82*Assumptions!$C$34)*12) -> -5267600.7
B37: Total Budget w/ Loan | C37: =SUM(C35:C36) -> 54984255 | D37: =+C37/C$37 -> 1 | E37: =C37/$C$8 -> 532.29286 | G37: Operating Income | J37: =J35+J36 -> 4464034.9 | K37: =K35+K36 -> 4207781
G38: Total Development Costs(2) | J38: =K38 -> 54984255 | K38: =C37 -> 54984255 | M38: =K37/K35 -> 0.44407509 | N38: <--- Profit Margin
G39: ROC | J39: =J37/J38 -> 0.081187512 | K39: =K37/K38 -> 0.076527017
B40: Sources | G40: (1) Inclusive of MH 10% profit split
D41: Total | E41: % Total | G41: (2) Inclusive of lease-up costs & interest reserve
B42: Debt | D42: ='Monthly-CF'!I109+'Monthly-CF'!I116 -> 32990553 | E42: =D42/$D$44 -> 0.6
B43: Equity | D43: ='Monthly-CF'!F105 -> 21993702 | E43: =D43/$D$44 -> 0.4 | G43: Exit Assumptions | K43: Residential | P43: DO NOT DELETE
B44: Total Sources & Uses | D44: =SUM(D42:D43) -> 54984255 | E44: =+SUM(E42:E43) -> 1 | G44: Exit Cap Rate | K44: =Assumptions!M55 -> 0.0525 | P44: =K37/K44 -> 80148210
B45: LP Equity | D45: =-SUMIFS('Monthly-Waterfall'!I58:DY58,'Monthly-Waterfall'!I58:DY58,"<"&0) -> 19794332 | E45: =+D45/D43 -> 0.9 | G45: Selling Costs | K45: =Assumptions!M56 -> 0.0125 | P45: =-P44*K45 -> -1001852.6
B46: GP / Sponsor Equity | D46: =-SUMIFS('Monthly-Waterfall'!I59:DY59,'Monthly-Waterfall'!I59:DY59,"<"&0) -> 2199370.2 | E46: =+D46/D43 -> 0.1 | G46: Exit Year(1) | K46: =Assumptions!M57 -> 10 | P46: =SUM(P44:P45) -> 79146357
B47: * Cost of debt assumes 300 bps + SOFR | P47: =P46/C18 -> 604170.67
G48: Residential | I48: Total | J48: $/Unit | K48: $/LSF
B49: Schedule | G49: Terminal Value | I49: =I51-I50 -> 86491038 | J49: =I49/$C$18 -> 660236.93 | K49: =I49/$F$18 -> 837.30445
D50: Start | E50: End | G50: Selling Costs | I50: =-I51*K45 -> -1067790.6 | J50: =I50/$C$18 -> -8151.0732 | K50: =I50/$F$18 -> -10.337092
B51: Construction Period | D51: =Assumptions!F13 -> 3 | E51: =Assumptions!G13 -> 19 | G51: Net Exit Proceeds | I51: ='Monthly-CF'!I62 -> 85423247 | J51: =I51/$C$18 -> 652085.86 | K51: =I51/$F$18 -> 826.96736
B52: Lease-Up Period | D52: =E51+1 -> 20 | E52: =D52+'Assumptions MH'!W36 -> 32 | G52: (1) Assumes end-of-year sale
B53: Stabilized Occupancy | D53: =E52 -> 32
B54: Exit | D54: =Assumptions!M57*12 -> 120
B56: Returns
C57: Profit | D57: IRR | E57: EQMx
B58: Project Un-Levered | C58: ='Monthly-CF'!I98 -> 65495876 | D58: ='Monthly-CF'!E99 -> 0.10644599 | E58: =(C58+D43)/D43 -> 3.9779378
B59: Project Levered | C59: ='Monthly-CF'!I129 -> 49098976 | D59: ='Monthly-CF'!E140 -> 0.17306911 | E59: =(C59+D43)/D43 -> 3.2324107
B60: Limited Partner | C60: =SUM('Monthly-Waterfall'!I58:DY58) -> 35615956 | D60: ='Monthly-Waterfall'!E58 -> 0.15477971 | E60: =(C60+D45)/D45 -> 2.7993007
B61: General Partner | C61: =SUM('Monthly-Waterfall'!I63:DY63) -> 13483020 | D61: =IFERROR('Monthly-Waterfall'!E63,"") -> 0.27251419 | E61: =(C61+D46)/D46 -> 7.1304005
G63: Check
G64: Profit | K64: ='Annual-CF'!I128-Dashboard!C59 -> 0
G65: Total Sources | K65: =D44-'Monthly-CF'!F105-'Monthly-CF'!I109-'Monthly-CF'!I116 -> -3.7252903e-09
G66: Sources & Uses | K66: =D44-C37 -> 0
G67: Equity Source | K67: =SUM(D45:D46)-D43 -> 0
G68: Monthly Check | K68: =C37+'Monthly-CF'!I76+'Monthly-CF'!I86 -> 1.4901161e-08
B71: Notes/Comments

Sheet Assumptions
D3: NAME | E3: 1425 4th Ave
D4: SUMMARY | E4: Multifamily | R4: FALSE
D5: DATE
D6: TYPE | E6: STABILIZED SALE
B8: Development Budget
B10: Development Budget Assumptions
B11: % of Tot. | C11: $ / LSQFT | D11: Detail | E11: Amount | F11: Start | G11: End | J11: ACRES | K11: SF | L11: $/SF | N11: Total | P11: / Unit
B12: =+E12/$E$23 -> 0.072848359 | C12: =E12/$J$35 -> 50.340281 | D12: Land | E12: =N12 -> 5200000 | F12: 1 | G12: 1 | I12: Land | J12: 1.12 | K12: =+J12*43650 -> 48888 | L12: =N12/K12 -> 106.36557 | N12: 5200000 | P12: =N12/C34 -> 39694.656
B13: =+E13/$E$23 -> 0.53852165 | C13: =E13/$J$35 -> 372.13373 | D13: Construction Costs + Contingency | E13: =N27 -> 38440298 | F13: ='Monthly-CF'!F70 -> 3 | G13: ='Monthly-CF'!H70 -> 19 | J13: Leaseable
B14: =+E14/$E$23 -> 0.11658871 | C14: =E14/$J$35 -> 80.566103 | D14: Soft Costs + Contingency | E14: =N33-E19-E18-E20 -> 8322236.8 | F14: ='Monthly-CF'!F71 -> 2 | G14: ='Monthly-CF'!H81 -> 0 | I14: Total investment acquisition
B15: =+E15/$E$23 -> 0 | C15: =E15/$J$35 -> 0 | D15: TI | E15: ='Budget Detail'!K72 -> 0 | F15: =G13-1 -> 18 | I15: Multi-Family | J15: x | K15: =F34 -> 103297 | L15: =N15/K15 -> 345.87934 | N15: ='Budget Detail'!K66+'Budget Detail'!K68 -> 35728298
B16: =+E16/$E$23 -> 0 | C16: =E16/$J$35 -> 0 | D16: LC | F16: =INDEX('Monthly-CF'!$L$10:$EA$10,MATCH(Assumptions!$H$59,'Monthly-CF'!$L$13:$EA$13,0)) -> 1 | G16: =INDEX('Monthly-CF'!$L$10:$EA$10,MATCH(Assumptions!$J$59,'Monthly-CF'!$L$13:$EA$13,0)) -> 1 | I16: Commercial | J16: x | K16: =F41 -> 0 | L16: 0
B17: =+E17/$E$23 -> 0.72795872 | C17: =E17/$J$35 -> 503.04011 | D17: Total before Interest | E17: =SUM(E10:E16) -> 51962535 | F17: =MIN(F12:F16) -> 1 | G17: =MAX(G12:G16) -> 19 | I17: Amenity / Unleaseable Space | K17: =F37+F38+F36+F39 -> 32084 | L17: 0
B18: =+E18/$E$23 -> 0.0034663091 | C18: =E18/$J$35 -> 2.3953179 | D18: Financing Costs | E18: =-'Monthly-CF'!I93 -> 247429.15 | F18: =INDEX('Monthly-CF'!$L$10:$EA$10,MATCH(-Assumptions!$E$18,'Monthly-CF'!$L$93:$EA$93,0)) -> 8 | G18: =F18 -> 8
B19: =+E19/$E$23 -> 0.034663091 | C19: =E19/$J$35 -> 23.953179 | D19: Const. Interest Reserve | E19: =-'Monthly-CF'!I94 -> 2474291.5
B20: =+E20/$E$23 -> 0.0042027899 | C20: =E20/$J$35 -> 2.904247 | D20: Op Inc Loss | E20: =-'Monthly-CF'!I75-'Monthly-CF'!I85 -> 300000 | I20: Garage | K20: =F45 -> 60170 | L20: 0
B21: =+E21/$E$23 -> 0.77029091 | C21: =E21/$J$35 -> 532.29286 | D21: Total Costs | E21: =SUM(E17:E20) -> 54984255
B22: =+E22/$E$23 -> 0.22970909 | C22: =E22/$J$35 -> 158.73549 | D22: Stab. Interest Exp | E22: =-'Monthly-CF'!I127 -> 16396900
B23: =+E23/$E$23 -> 1 | C23: =E23/$J$35 -> 691.02835 | D23: Costs + Stab Interest | E23: =SUM(E21:E22) -> 71381155
I24: Building Permits / Fees | N24: ='Budget Detail'!K65 -> 412125
B25: MF Unit Mix Assumptions | I25: Other Hard Costs | N25: ='Budget Detail'!K73+SUM('Budget Detail'!K69:K71) -> 513460
B26: Type | C26: Count | D26: Unit % | E26: Unit Size | F26: Total SF | G26: SF% Allocation | I26: Construction Contingency | M26: ='Budget Detail'!E67 -> 0.05 | N26: ='Budget Detail'!K67 -> 1786414.9
I27: Construction - Hard Costs | K27: =SUM(K15:K25) -> 195551 | L27: =N27/K27 -> 196.57428 | M27: =N27/SUM(K15:K19) -> 283.9416 | N27: =SUM(N15:N26) -> 38440298 | P27: =SUM(N26,N15:N23)/SUM(K15:K17) -> 277.10471
B28: Studio | C28: ='Unit Detail'!D23 -> 12 | D28: =C28/$C$34 -> 0.091603053 | E28: ='Unit Detail'!E23 -> 458 | F28: =E28*C28 -> 5496 | G28: =F28/$F$34 -> 0.053205805 | I28: Architect / Engineer | K28: =$K$27 -> 195551 | L28: =N28/K28 -> 6.9497729 | N28: ='Budget Detail'!K36+'Budget Detail'!K39 -> 1359035.1 | P28: =N28/$C$34 -> 10374.313
B29: 1 bed | C29: ='Unit Detail'!D24 -> 76 | D29: =C29/$C$34 -> 0.58015267 | E29: ='Unit Detail'!E24 -> 702.18421 | F29: =E29*C29 -> 53366 | G29: =F29/$F$34 -> 0.51662681 | I29: Project Manager | K29: =$K$27 -> 195551 | L29: =N29/K29 -> 0 | N29: ='Budget Detail'!K40 -> 0 | P29: =N29/$C$34 -> 0
B30: 2 Bed | C30: ='Unit Detail'!D25 -> 37 | D30: =C30/$C$34 -> 0.28244275 | E30: ='Unit Detail'!E25 -> 1016.8919 | F30: =E30*C30 -> 37625 | G30: =F30/$F$34 -> 0.36424098 | I30: Developer Fee | K30: =$K$27 -> 195551 | L30: =N30/K30 -> 8.5534497 | M30: ='Budget Detail'!E76 -> 0 | N30: ='Budget Detail'!K76+'Budget Detail'!K77 -> 1672635.6 | P30: =N30/$C$34 -> 12768.211
B31: 2 Bed Plus | C31: ='Unit Detail'!D26 -> 2 | D31: =C31/$C$34 -> 0.015267176 | E31: ='Unit Detail'!E26 -> 1485 | F31: =E31*C31 -> 2970 | G31: =F31/$F$34 -> 0.028752045
B32: Loft | C32: ='Unit Detail'!D27 -> 4 | D32: =C32/$C$34 -> 0.030534351 | E32: ='Unit Detail'!E27 -> 960 | F32: =E32*C32 -> 3840 | G32: =F32/$F$34 -> 0.037174361 | I32: Other Soft Costs | K32: =$K$27 -> 195551 | L32: =N32/K32 -> 42.507002 | N32: =SUM(,'Budget Detail'!K10:K18,'Budget Detail'!K22:K29,'Budget Detail'!K43,'Budget Detail'!K62,'Budget Detail'!K76:K77)-SUM(N28:N31) -> 8312286.7
I33: Construction - Soft Costs | N33: =SUM(N28:N32) -> 11343957
B34: Total | C34: =SUM(C27:C33) -> 131 | D34: =C34/$C$34 -> 1 | E34: =F34/C34 -> 788.52672 | F34: =SUM(F27:F33) -> 103297 | G34: =SUM(G27:G33) -> 1 | I34: Total Development Costs | K34: =K27 -> 195551 | L34: =N34/K34 -> 281.17604 | N34: =N33+N27+N12 -> 54984255
I35: Leaseable SF | J35: =SUMIFS(K15:K24,J15:J24,"x") -> 103297 | L35: =N34/$J$35 -> 532.29286
B36: Lobby | F36: ='Unit Detail'!F36 -> 3372 | I36: Interior Built SF | J36: =SUM(K15:K19) -> 135381
B37: Common Area / Courtyard | J37: =+J35/J36 -> 0.76300958
B38: Amenity Area | F38: ='Unit Detail'!F37+'Unit Detail'!F38+'Unit Detail'!F39 -> 10578
B39: Unleaseable Area | F39: 18134
B40: GSF Residential | F40: =SUM(F33:F39) -> 135381
B41: Retail Area
B42: Total Gross SF | F42: =SUM(F40:F41) -> 135381
B43: Total Leasable SF | F43: =F41+F34 -> 103297
B45: Garage SF | F45: 60170
B46: Garage Spaces | F46: 145
B51: Cash Flow Assumptions
B53: Asset Assumptions | G53: Rent/Occupancy Assumptions | L53: Sale Assumptions
C54: =Assumptions!I15 -> Multi-Family | D54: =Assumptions!I16 -> Commercial | E54: Total | H54: =Assumptions!C54 -> Multi-Family | I54: =Assumptions!D54 -> Commercial | J54: Ancillary Fees | L54: Residential Operations
B55: LSF | C55: =F34 -> 103297 | D55: =Assumptions!K16 -> 0 | E55: =+SUM(C55:D55) -> 103297 | G55: $ / SQFT | H55: ='Rent Comps'!D21 -> 2.7909813 | I55: 2.75 | J55: =Assumptions!J70/Assumptions!C55/12 -> 0.18144767 | L55: Exit Cap Rate | M55: 0.0525
B56: Dev Costs / SF | C56: =Assumptions!L15 -> 345.87934 | D56: =Assumptions!$L$16 -> 0 | E56: =+($C$55*C56+$D$55*D56)/$E$55 -> 345.87934 | G56: Rent Escalator | H56: 0.04 | I56: =+H56 -> 0.04 | J56: =+H56 -> 0.04 | L56: Selling Costs | M56: 0.0125
B57: TI / SF | C57: 0 | D57: 0 | E57: =+($C$55*C57+$D$55*D57)/$E$55 -> 0 | G57: $ / Unit | H57: =(H55*F34)/C34 -> 2200.7634 | L57: Selling Year | M57: =ROUND((M58-'Monthly-CF'!L8)/360,0) -> 10
H58: Start | I58: Lease-up % | J58: End | L58: Exit Date | M58: 48730
B59: Financing Assumptions | G59: Occ - Multi-Family | H59: 0 | I59: 0 | J59: 0 | L59: Commercial Operations
B60: Construction Financing | G60: Occ - Commercial | H60: 0 | I60: 0 | J60: 0 | L60: Exit Cap Rate | M60: 0.06
B61: LTC | E61: 0.6 | G61: Occ - Ancillary Fees | H61: 0 | I61: 0 | J61: 0 | L61: Selling Costs | M61: 0.013
B62: Opening fee | E62: 0.0075 | L62: Selling Year | M62: =ROUND((M63-'Monthly-CF'!L8)/360,0) -> 10
B63: Annual Interests | D63: See Forward Curve ---> | E63: 0 | G63: Ancillary Fee Assumptions | L63: Exit Date | M63: 48730
B64: Int Res (Ramp Mths) | H64: Annual Amt | I64: Utilization | J64: Total
B65: Recap Financing | G65: Pet Fee | H65: =60*12 -> 720 | I65: 0.35 | J65: =I65*H65*Assumptions!$M$77 -> 33012 | L65: Debt Details
B66: LTV | E66: 0.65 | G66: Storage | H66: =(100*12) -> 1200 | I66: 0.9 | J66: =(H66*I66)*23 -> 24840
B67: =B62 -> Opening fee | E67: 0.005 | G67: Misc. Other Income | H67: 600 | I67: 0.9 | J67: =I67*H67*Assumptions!$M$77 -> 70740 | L67: Financing Costs | M67: ='Budget Detail'!K22 -> 247429.15
B68: Annual Interests | E68: 0.055 | G68: Parking - First Spot | H68: 720 | I68: 0.95 | J68: =I68*H68*Assumptions!$M$77 -> 89604 | L68: Const. Interest Reserve | M68: ='Budget Detail'!K23 -> 2474291.5
B69: Amortization Period | E69: 25 | G69: Parking - Reserved | H69: =100*12 -> 1200 | I69: 0.4 | J69: =I69*H69*($F$46-$M$77) -> 6720 | L69: Lease Commissions | M69: 0
B70: Refi - Date | E70: 45869 | G70: Total | J70: =SUM(J65:J69) -> 224916 | L70: Yr -1 Op Inc Loss | M70: =-'Monthly-CF'!I75-'Monthly-CF'!I85 -> 300000
B71: Cap Rate | E71: =M55 -> 0.0525 | G71: Parking / Unit | J71: =(J68+J69)/$M$77 -> 735.29771 | L71: Open Yr | M71: =ROUNDUP(Assumptions!F16/12,0)+1 -> 2
G72: Misc. Other Income / Unit | J72: =(J65+J67)/$M$77 -> 792
B74: Investment Summary | G74: Expense Assumptions | L74: Residential Summary
B75: EQUITY | I75: Multi-Family | J75: Commercial | L75: LSF | M75: =C55 -> 103297
B76: LOAN | G76: Commissions (%) | I76: 0 | J76: 0.06 | L76: Unit Size | M76: =M75/M77 -> 788.52672
B77: TOTAL | G77: Rent Concessions (Mths) | I77: 1 | J77: 2 | L77: Unit Count | M77: =C34 -> 131
G78: Capital Reserves (PSF) | I78: 0.25 | J78: 1.2 | L78: Op Exp ($ / Unit) | M78: ='Opex MF'!C27 -> 8304.7662
G79: Op Ex (Margin) | I79: =I80/Assumptions!H55 -> 0.31446536 | J79: 0.25 | L79: Total Op Exp. | M79: =M78*M77 -> 1087924.4
G80: Monthly Op Exp ($ / SF) | I80: =Assumptions!M80/12 -> 0.87766697 | J80: =J79*Assumptions!I55 -> 0.6875 | L80: Annual Op Exp ($ / SF) | M80: =M79/M75 -> 10.532004
G81: Annual Expense Increase | I81: 0.03 | J81: =+I81 -> 0.03
G82: STR Property Insurance | I82: 175
B85: Sensitivity Analysis: Leveraged IRR
D87: Exit Cap Rate
B88: Purchase Price $/SF | C88: #REF! | D88: =E88-$AA$40 -> 0.045 | E88: =F88-$AA$40 -> 0.045 | F88: 0.045 | G88: =F88+$AA$41 -> 0.045 | H88: =G88+$AA$41 -> 0.045 | K88: 0.005 | L88: Increments - Row
C89: =C90-$AA$42 -> 45 | K89: 5 | L89: Increments - Column
C90: =C91-$AA$42 -> 45
C91: 45 | L91: <--- IRR Check
C92: =C91+$AA$42 -> 45
C93: =C92+$AA$42 -> 45
C94: =C93+$AA$42 -> 45
C95: =C94+$AA$42 -> 45
C96: =C95+$AA$42 -> 45
C97: =C96+$AA$42 -> 45
C98: =C97+$AA$42 -> 45

Sheet Assumptions MH
B2: 1425 4th Ave (Nashville, TN) | Mint House Management Agreement Model
B3: Assumptions MH
B5: Deal Overview | I5: Rate Assumption | N5: Model Inputs | S5: Growth Rates | V5: =+W6&" Structure" -> Prioritized Hurdle Structure | Y5: Profit Share Assumptions
B6: Deal Name | G6: 1425 4th Ave | I6: Data Source | K6: Weight | L6: ADR | N6: Category | O6: Short Term | P6: Long Term | Q6: Blended | S6: ADR Annual Inflation | T6: 0.03 | V6: Type | W6: Prioritized Hurdle | Y6: Min. Monthly Pmt Growth | Z6: =+T7 -> 0.03
B7: Address | G7: 1425 4th Avenue South | I7: Mint House | K7: 0 | L7: 0 | N7: Number of Units | O7: =G29 -> 131 | P7: =G30 -> 0 | Q7: =G31 -> 131 | S7: Multifamily Rent Growth | T7: 0.03 | V7: Year # | W7: MF Rent % | Y7: Y1 MF Ramp | Z7: 0.685
B8: Market | G8: Nashville | I8: Comps - STR | K8: 0.25 | L8: 217.4433 | N8: ADR | O8: ='Assumptions MH'!L15 -> 271 | P8: =+'Assumptions MH'!L9 -> 0 | Q8: =SUMPRODUCT(O8:P8,$O$7:$P$7)/$Q$7 -> 271 | S8: Other Revenue Growth | T8: 0.03 | V8: 1 | W8: 0 | Y8: Margin on MF Rent [2] | Z8: 0.7
B9: City | G9: Nashville | I9: Comps - LTL | K9: 0 | L9: 0 | N9: Occupancy | O9: =+'Assumptions MH'!L27 -> 0.7 | P9: 0.75 | Q9: =SUMPRODUCT(O9:P9,$O$7:$P$7)/$Q$7 -> 0.7 | S9: Expense Growth | T9: 0.03 | V9: 2 | W9: 0
B10: State | G10: TN | I10: Smith Travel Research | K10: 0.55 | L10: 278.16259 | N10: RevPAR | O10: =PRODUCT(O8:O9) -> 189.7 | P10: =PRODUCT(P8:P9) -> 0 | Q10: =SUMPRODUCT(O10:P10,$O$7:$P$7)/$Q$7 -> 189.7 | S10: Hurdle Growth | V10: 3 | W10: 0 | Y10: Minimum Monthly Payment
B11: Zip Code | G11: 37210 | I11: Forward Rate Shop | K11: 0.2 | L11: 319.60761 | N11: Cleanings (per turn) | O11: 65 | P11: 60 | Q11: =SUMPRODUCT(O11:P11,$O$7:$P$7)/$Q$7 -> 65 | V11: 4 | W11: 0 | Y11: Year # | Z11: MF Rent %
B12: Submarket | G12: Wedgewood-Houston | I12: Market - T12 | K12: 0 | L12: 232.23069 | N12: Consumables (per turn) | O12: 10 | P12: 10 | Q12: =SUMPRODUCT(O12:P12,$O$7:$P$7)/$Q$7 -> 10 | S12: ADR Growth Rate | V12: 5 | W12: 0 | Y12: 1 | Z12: 0.6
B13: Total Property Units | G13: =Assumptions!C34 -> 131 | I13: Market - 2019 | K13: 0 | L13: 221.23977 | N13: OSE (per turn) | O13: 20 | P13: 20 | Q13: =SUMPRODUCT(O13:P13,$O$7:$P$7)/$Q$7 -> 20 | S13: Year | T13: Growth Rate | V13: 6 | W13: 0 | Y13: 2 | Z13: 0.5
B14: Year Built | G14: 2025 | I14: Manual | K14: 0 | L14: 0 | N14: Guest Services - Labor | O14: =+'Staffing Model MH'!H20 -> 298.94635 | P14: =+'Staffing Model MH'!H20 -> 298.94635 | Q14: =SUMPRODUCT(O14:P14,$O$7:$P$7)/$Q$7 -> 298.94635 | S14: 1 | T14: 0.03 | V14: 7 | W14: 0 | Y14: 3 | Z14: 0.4
B15: Year Renovated | G15: na | I15: Blended | K15: =SUM(K7:K14) -> 1 | L15: =ROUND(SUMPRODUCT(K7:K14,L7:L14),0) -> 271 | N15: G&A: Salaries & Benefits | O15: =+'Staffing Model MH'!H28 -> 283.80252 | P15: =+'Staffing Model MH'!H28 -> 283.80252 | Q15: =SUMPRODUCT(O15:P15,$O$7:$P$7)/$Q$7 -> 283.80252 | S15: 2 | T15: 0.03 | V15: 8 | W15: 0 | Y15: 4 | Z15: 0.4
B16: Multifamily Class | G16: A | N16: G&A: Operating Supplies | O16: 5 | P16: 20 | Q16: 5 | S16: 3 | T16: 0.03 | V16: 9 | W16: 0 | Y16: 5 | Z16: 0.4
I17: Occupancy Assumption | N17: Credit Card Fees | O17: 0.03 | P17: 0.03 | Q17: =SUMPRODUCT(O17:P17,$O$7:$P$7)/$Q$7 -> 0.03 | S17: 4 | T17: 0.03 | V17: 10 | W17: 0 | Y17: 6 | Z17: 0.4
B18: General Assumptions | I18: Data Source | K18: Weight | L18: Occupancy | N18: Utilities | O18: 100 | P18: 100 | Q18: =SUMPRODUCT(O18:P18,$O$7:$P$7)/$Q$7 -> 100 | S18: 5 | T18: 0.03 | Y18: 7 | Z18: 0.4
B19: Property Type | G19: Short Term | I19: Mint House | K19: 0 | L19: 0 | N19: In-Unit Maintenance | O19: 30 | P19: 35 | Q19: =SUMPRODUCT(O19:P19,$O$7:$P$7)/$Q$7 -> 30 | S19: 6 | T19: 0.03 | V19: Incentive Management Fee | Y19: 8 | Z19: 0.4
B20: Analysis Start | F20: Create calc based on development completion ---> | G20: 45658 | I20: Comps - STR | K20: 0 | L20: 0.75300254 | N20: Shared Services | O20: 150 | P20: 150 | Q20: =SUMPRODUCT(O20:P20,$O$7:$P$7)/$Q$7 -> 150 | S20: 7 | T20: 0.03 | V20: Year # | W20: MH Split (%) | Y20: 9 | Z20: 0.4
B21: Full Building | G21: 1 | I21: Smith Travel Research | K21: 0 | L21: 0.74090957 | N21: Sales & Marketing - Payroll | O21: ='Staffing Model MH'!$H$32 -> 97.455391 | P21: ='Staffing Model MH'!$H$32 -> 97.455391 | Q21: =SUMPRODUCT(O21:P21,$O$7:$P$7)/$Q$7 -> 97.455391 | S21: 8 | T21: 0.03 | V21: 1 | W21: 0.15 | Y21: 10 | Z21: 0.4
B22: Inflation Adjustment | G22: 1 | I22: Market - T12 | K22: 0 | L22: 0.64218422 | N22: Sales & Marketing - Direct to Consumer | O22: 0.005 | P22: 0.01 | Q22: =SUMPRODUCT(O22:P22,$O$7:$P$7)/$Q$7 -> 0.005 | S22: 9 | T22: 0.03 | V22: 2 | W22: 0.15
B23: ADR Recovery Year to 2019 | G23: 2022 | I23: Market - 2019 | K23: 0 | L23: 0.70739798 | N23: Platform Fees / Customer Acquisition | O23: 0.07 | P23: 0.045 | Q23: =SUMPRODUCT(O23:P23,$O$7:$P$7)/$Q$7 -> 0.07 | S23: 10 | T23: 0.03 | V23: 3 | W23: 0.15 | Y23: Profit Share
B24: Inflation Years | G24: =IF(YEAR(G20)-$G$23<0,0,ROUNDDOWN(YEAR(G20)-G23,0))*G22 -> 3 | I24: Manual | K24: 1 | L24: 0.7 | N24: Wifi / Cable | O24: 75 | P24: 75 | Q24: =SUMPRODUCT(O24:P24,$O$7:$P$7)/$Q$7 -> 75 | V24: 4 | W24: 0.15 | Y24: Year # | Z24: Owner Split (%)
B25: FF&E Financing | G25: Upfront | N25: Occupancy & Sales Tax (% of Rev) | O25: 0.1475 | P25: 0 | Q25: =SUMPRODUCT(O25:P25,$O$7:$P$7)/$Q$7 -> 0.1475 | S25: Average Length of Stay | V25: 5 | W25: 0.15 | Y25: 1 | Z25: 0.9
N26: Tax Pass Through | O26: 1 | P26: 1 | Q26: =SUMPRODUCT(O26:P26,$O$7:$P$7)/$Q$7 -> 1 | S26: Year | T26: ALOS | V26: 6 | W26: 0.15 | Y26: 2 | Z26: 0.9
B27: Unit Inputs | I27: Blended | K27: =SUM(K19:K24) -> 1 | L27: =ROUND(SUMPRODUCT(K19:K24,L19:L24),2) -> 0.7 | N27: Information Technology | O27: 0.02 | P27: 0.02 | Q27: =SUMPRODUCT(O27:P27,$O$7:$P$7)/$Q$7 -> 0.02 | S27: 1 | T27: 6 | V27: 7 | W27: 0.15 | Y27: 3 | Z27: 0.9
C28: Studio | D28: 1 Bed | E28: 2 Bed | F28: 3 Bed | G28: Total / AVG | N28: Management Fee | O28: 0.05 | P28: 0.05 | Q28: =SUMPRODUCT(O28:P28,$O$7:$P$7)/$Q$7 -> 0.05 | S28: 2 | T28: 6 | V28: 8 | W28: 0.15 | Y28: 4 | Z28: 0.9
B29: =IF($G$19<>"Long Term","Short Term Units (STR)","") -> Short Term Units (STR) | C29: =Assumptions!C28 -> 12 | D29: =Assumptions!C29+Assumptions!C32 -> 80 | E29: =Assumptions!C30+Assumptions!C31 -> 39 | F29: 0 | G29: =SUM(C29:F29) -> 131 | I29: Ramp | N29: Liability, FF&E Insurance / Permits | O29: 40 | P29: 40 | Q29: =SUMPRODUCT(O29:P29,$O$7:$P$7)/$Q$7 -> 40 | S29: 3 | T29: 6 | V29: 9 | W29: 0.15 | Y29: 5 | Z29: 0.9
B30: =IF($G$19<>"Short Term","Long Term Units (LTL)","") | G30: =SUM(C30:F30) -> 0 | I30: Start Date | L30: =+'Assumptions MH'!G20 -> 45658 | N30: Property Insurance | O30: 0 | P30: 60 | Q30: =SUMPRODUCT(O30:P30,$O$7:$P$7)/$Q$7 -> 0 | S30: 4 | T30: 6 | V30: 10 | W30: 0.15 | Y30: 6 | Z30: 0.9
B31: Blended Units | C31: =SUM(C29:C30) -> 12 | D31: =SUM(D29:D30) -> 80 | E31: =SUM(E29:E30) -> 39 | F31: =SUM(F29:F30) -> 0 | G31: =SUM(C31:F31) -> 131 | I31: Initial Ramp | L31: 0.35 | N31: Maintenance, Supplies, Subcontracting | O31: 90 | P31: 40 | Q31: =SUMPRODUCT(O31:P31,$O$7:$P$7)/$Q$7 -> 90 | S31: 5 | T31: 6 | Y31: 7 | Z31: 0.9
I32: Months to Stabilization | L32: 18 | S32: 6 | T32: 6 | V32: Multifamily Assumptions | Y32: 8 | Z32: 0.9
B33: Avg. Unit Size | C33: =Assumptions!E28 -> 458 | D33: =((Assumptions!C29*Assumptions!E29)+(Assumptions!C32*Assumptions!E32))/(Assumptions!C29+Assumptions!C32) -> 715.075 | E33: =((Assumptions!C30*Assumptions!E30)+(Assumptions!C31*Assumptions!E31))/(Assumptions!C30+Assumptions!C31) -> 1040.8974 | F33: 0 | G33: =SUMPRODUCT(C33:F33,$C$31:$F$31)/$G$31 -> 788.52672 | I33: Start Month | J33: End Month | K33: Step Up/Mo | L33: % Ramped | N33: Tax Assumptions | S33: 7 | T33: 6 | V33: Margin on MF Rent | W33: 0.581 | Y33: 9 | Z33: 0.9
I34: 1 | J34: 8 | K34: 0.0625 | L34: =+IF(J34>L32,"ERROR",MIN(L31+K34*(J34-I34),1)) -> 0.7875 | N34: Est. Property Taxes / Unit | S34: 8 | T34: 6 | V34: Multifamily Ramp | W34: 0 | Y34: 10 | Z34: 0.9
B35: =IF($G$19<>"Long Term","Multifamily Rent PSF - STR","") -> Multifamily Rent PSF - STR | C35: 3.4934498 | D35: 2.991453 | E35: 3.0365034 | F35: 0 | G35: =IFERROR(SUMPRODUCT(C35:F35,$C$29:$F$29)/$G$29,0) -> 3.0508494 | I35: =+IF(J34>=$L$32,"",J34+1) -> 9 | J35: =+IF(J34>=$L$32,"",L32) -> 18 | K35: =IFERROR(IF((1-L34)/(J35-I35+1)>0,(1-L34)/(J35-I35+1),0),"") -> 0.02125 | L35: =IFERROR(MIN(L34+K35*(J35-I35+1),1),"") -> 1 | N35: Est. STR Property Taxes | S35: 9 | T35: 6 | V35: Units Leased per Month | W35: 11
B36: =IF($G$19<>"Short Term","Multifamily Rent PSF - LTL","") | G36: =IFERROR(SUMPRODUCT(C36:F36,$C$30:$F$30)/$G$30,0) -> 0 | I36: ADR Recession Downturn | L36: 1 | N36: Source: Ownership | S36: 10 | T36: 6 | V36: MF Months to Stabilize | W36: =ROUNDUP(G31/W35,0) -> 12 | Y36: [2] To reflect staffing management, and leasing costs;
B37: Blended Rent PSF | C37: =IFERROR(SUMPRODUCT(C35:C36,C$29:C$30)/C$31,0) -> 3.4934498 | D37: =IFERROR(SUMPRODUCT(D35:D36,D$29:D$30)/D$31,0) -> 2.991453 | E37: =IFERROR(SUMPRODUCT(E35:E36,E$29:E$30)/E$31,0) -> 3.0365034 | F37: =IFERROR(SUMPRODUCT(F35:F36,F$29:F$30)/F$31,0) -> 0 | G37: =SUMPRODUCT(C37:F37,C31:F31)/G31 -> 3.0508494 | I37: Recession Recovery Rate | L37: 1 | V37: Y1 Multifamily Ramp % | W37: =IF(W34=1,SUM(W39:W50)/($G$31*12),1) -> 1 | Y37: fixed expenses (RE taxes, maintenance and insurance)
I38: Owner Priority Ramp | L38: 1 | N38: Ground Lease | S38: Capital Improvement | V38: Month # | W38: Units Ramped | Y38: not included
B39: =IF($G$19<>"Long Term","Multifamily Rent per Unit - STR","") -> Multifamily Rent per Unit - STR | C39: =C35*C33 -> 1600 | D39: =D35*D33 -> 2139.1132 | E39: =E35*E33 -> 3160.6886 | F39: =F35*F33 -> 0 | G39: =IFERROR(SUMPRODUCT(C39:F39,$C$29:$F$29)/$G$29,0) -> 2393.8619 | N39: Ground Lease | Q39: 0 | S39: Year | T39: FF&E Reserve | V39: 1 | W39: =+W35 -> 11
B40: =IF($G$19<>"Short Term","Multifamily Rent per Unit - LTL","") | C40: =C36*C33 -> 0 | D40: =D36*D33 -> 0 | E40: =E36*E33 -> 0 | F40: =F36*F33 -> 0 | G40: =IFERROR(SUMPRODUCT(C40:F40,$C$30:$F$30)/$G$30,0) -> 0 | I40: Parking [1] | S40: 1 | T40: 0 | V40: 2 | W40: =IF(COUNTA(V$39:V40)<$W$36,W39+$W$35,$G$31) -> 22
B41: Blended Rent per Unit | C41: =IFERROR(SUMPRODUCT(C39:C40,C$29:C$30)/C$31,0) -> 1600 | D41: =IFERROR(SUMPRODUCT(D39:D40,D$29:D$30)/D$31,0) -> 2139.1132 | E41: =IFERROR(SUMPRODUCT(E39:E40,E$29:E$30)/E$31,0) -> 3160.6886 | F41: =IFERROR(SUMPRODUCT(F39:F40,F$29:F$30)/F$31,0) -> 0 | G41: =SUMPRODUCT(C41:F41,C31:F31)/G31 -> 2393.8619 | I41: Parking Spots | L41: =Assumptions!$F$46 -> 145 | S41: 2 | T41: 0.01 | V41: 3 | W41: =IF(COUNTA(V$39:V41)<$W$36,W40+$W$35,$G$31) -> 33
I42: Mint House Nightly Rate | L42: 30 | S42: 3 | T42: 0.02 | V42: 4 | W42: =IF(COUNTA(V$39:V42)<$W$36,W41+$W$35,$G$31) -> 44
B43: =IF($G$19<>"Long Term","Multifamily Rent per Month - STR","") -> Multifamily Rent per Month - STR | C43: =C39*C29 -> 19200 | D43: =D39*D29 -> 171129.06 | E43: =E39*E29 -> 123266.85 | F43: =F39*F29 -> 0 | G43: =SUM(C43:F43) -> 313595.91 | I43: Parking Allocation | L43: 1 | S43: 4 | T43: 0.03 | V43: 5 | W43: =IF(COUNTA(V$39:V43)<$W$36,W42+$W$35,$G$31) -> 55
B44: =IF($G$19<>"Short Term","Multifamily Rent per Month - LTL","") | C44: =C40*C30 -> 0 | D44: =D40*D30 -> 0 | E44: =E40*E30 -> 0 | F44: =F40*F30 -> 0 | G44: =SUM(C44:F44) -> 0 | I44: Net Margin | L44: 0.85 | S44: 5 | T44: 0.04 | V44: 6 | W44: =IF(COUNTA(V$39:V44)<$W$36,W43+$W$35,$G$31) -> 66
B45: Blended Rent per Month | C45: =SUM(C43:C44) -> 19200 | D45: =SUM(D43:D44) -> 171129.06 | E45: =SUM(E43:E44) -> 123266.85 | F45: =SUM(F43:F44) -> 0 | G45: =SUM(C45:F45) -> 313595.91 | I45: Parking Capture Rate | L45: 0.4 | S45: 6 | T45: 0.05 | V45: 7 | W45: =IF(COUNTA(V$39:V45)<$W$36,W44+$W$35,$G$31) -> 77
S46: 7 | T46: 0.05 | V46: 8 | W46: =IF(COUNTA(V$39:V46)<$W$36,W45+$W$35,$G$31) -> 88
B47: =IF($G$19<>"Long Term","Multifamily Annual Rent - STR","") -> Multifamily Annual Rent - STR | C47: =C43*12 -> 230400 | D47: =D43*12 -> 2053548.7 | E47: =E43*12 -> 1479202.2 | F47: =F43*12 -> 0 | G47: =SUM(C47:F47) -> 3763151 | I47: Parking Rate Comps | S47: 8 | T47: 0.05 | V47: 9 | W47: =IF(COUNTA(V$39:V47)<$W$36,W46+$W$35,$G$31) -> 99
B48: =IF($G$19<>"Short Term","Multifamily Annual Rent - LTL","") | C48: =C44*12 -> 0 | D48: =D44*12 -> 0 | E48: =E44*12 -> 0 | F48: =F44*12 -> 0 | G48: =SUM(C48:F48) -> 0 | I48: Hotel / Property Name | L48: Rate | S48: 9 | T48: 0.05 | V48: 10 | W48: =IF(COUNTA(V$39:V48)<$W$36,W47+$W$35,$G$31) -> 110
B49: Blended Annual Rent | C49: =SUM(C47:C48) -> 230400 | D49: =SUM(D47:D48) -> 2053548.7 | E49: =SUM(E47:E48) -> 1479202.2 | F49: =SUM(F47:F48) -> 0 | G49: =SUM(G47:G48) -> 3763151 | I49: Locale South Gulch - Nashville | L49: 30 | S49: 10 | T49: 0.05 | V49: 11 | W49: =IF(COUNTA(V$39:V49)<$W$36,W48+$W$35,$G$31) -> 121
I50: Locale at Infinity Lofts Gulch | L50: 30 | V50: 12 | W50: =IF(COUNTA(V$39:V50)<$W$36,W49+$W$35,$G$31) -> 131
B51: =+IF(G25="Upfront","FF&E",G25) -> FF&E | I51: Locale Music Row | L51: 30
B52: Unit Type | C52: Studio | D52: 1 Bed | E52: 2 Bed | F52: 3 Bed | G52: AVG | I52: Sentral SoBro | L52: 35
B53: 1 | G53: =IFERROR(SUMPRODUCT(C53:F53,$C$31:$F$31)/$G$31,"") -> 0 | I53: BentoLiving Chestnut Hill | L53: 28
B54: 2 | G54: =IFERROR(SUMPRODUCT(C54:F54,$C$31:$F$31)/$G$31,"") -> 0 | I54: Average Rate: | L54: =AVERAGE(L49:L53) -> 30.6
B55: 3 | G55: =IFERROR(SUMPRODUCT(C55:F55,$C$31:$F$31)/$G$31,"") -> 0
I56: [1] Assumes Self-Parking onsite
B57: Upfront Costs Build
B58: Unit Type | C58: Studio | D58: 1 Bed | E58: 2 Bed | F58: 3 Bed | G58: AVG
B59: Moving & Logistics (per unit per year)
B60: 1 | G60: =IFERROR(SUMPRODUCT(C60:F60,$C$31:$F$31)/SUM($C$29:$F$29),"") -> 0
B61: Total Upfront FF&E | C61: 17500 | D61: 18600 | E61: 25000 | F61: 29440 | G61: =SUMPRODUCT(C61:F61,C31:F31) -> 2673000 | I61: =G61/131 -> 20404.58
B62: FF&E Reimbursement | G62: 0
B63: Upfront FF&E per Unit | G63: =G61/G31 -> 20404.58
B64: Owner Reimbursement for FF&E | G64: 1
B65: Amount Reimbursed | G65: =G61*G64 -> 2673000
B66: MH Key Money | G66: =(1-G64)*G61 -> 0
B67: Reimbursement Period | G67: 5
B68: Amount Reimbursed per Period | G68: =G62*G65/G67 -> 0
B70: Unit Type | C70: Quantity | D70: Occupancy | E70: Hotel ADR | F70: Adj. ADR [1] | G70: ADR Prem. [2] | I70: ADR + Premium
B71: Studio | C71: =C29 -> 12 | D71: =$L$27 -> 0.7 | E71: =$L$15 -> 271 | F71: =+E71*(1+$T$6)^($G$24) -> 296.12902 | G71: 0 | I71: =+F71*(1+G71) -> 296.12902
B72: 1 Bedroom | C72: =D29 -> 80 | D72: =$L$27 -> 0.7 | E72: =$L$15 -> 271 | F72: =+E72*(1+$T$6)^($G$24) -> 296.12902 | G72: 0 | I72: =+F72*(1+G72) -> 296.12902
B73: 2 Bedroom | C73: =E29 -> 39 | D73: =$L$27 -> 0.7 | E73: =$L$15 -> 271 | F73: =+E73*(1+$T$6)^($G$24) -> 296.12902 | G73: 0 | I73: =+F73*(1+G73) -> 296.12902
B74: 3 Bedroom
B75: Totals / Averages: | C75: =SUM(C71:C74) -> 131 | D75: =SUMPRODUCT(D71:D74,$C$71:$C$74)/$C$75 -> 0.7 | E75: =SUMPRODUCT(E71:E74,$C$71:$C$74)/$C$75 -> 271 | F75: =SUMPRODUCT(F71:F74,$C$71:$C$74)/$C$75 -> 296.12902 | I75: =SUMPRODUCT(I71:I74,$C$71:$C$74)/$C$75 -> 296.12902
I77: =I75-$L$15 -> 25.129017

Sheet Budget Detail
B5: Build Tools COA
B7: CATEGORY CODE | C7: CATEGORY NAME | D7: Key for CF | E7: % EST. | G7: Spent To Date | H7: Remaining Costs | I7: Phase 1 | J7: Phase 2 | K7: Total | L7: Notes:
B8: 100 | C8: Land / Project Purchase
B9: 110 | C9: Project Purchase | D9: Land | G9: 5200000 | H9: =K9-G9 -> 0 | I9: =K9 -> 5200000 | K9: =Assumptions!N12 -> 5200000
B10: 115 | C10: Acquisition Fee | D10: Soft Costs (Excl. D/S) | E10: 0 | G10: 0 | H10: =K10-G10 -> 0 | I10: =K10 -> 0 | K10: =E10*K9 -> 0
B11: 120 | C11: Broker Fee | D11: Soft Costs (Excl. D/S) | E11: 0 | G11: 0 | H11: =K11-G11 -> 0 | I11: =K11 -> 0 | K11: =K9*E11 -> 0
B12: 130 | C12: Closing Costs | D12: Soft Costs (Excl. D/S) | G12: 12017 | H12: =K12-G12 -> 7983 | I12: =K12 -> 20000 | K12: 20000
B13: 135 | C13: Transfer Taxes | D13: Soft Costs (Excl. D/S) | G13: 19241 | H13: =K13-G13 -> 37936.836 | I13: =K13 -> 57177.836 | K13: =19241+0.115*((Dashboard!$D$42-2000)/100) -> 57177.836 | L13: Realty transfer tax: $0.37 per $100 of purchase price for the realty transfer; Mortgage tax: $0.115 per $100 of indebtedness. (The first $2,000 of the debt is exempt from taxation.)
B14: 140 | C14: Survey | D14: Soft Costs (Excl. D/S) | G14: 4542.57 | H14: =K14-G14 -> 0 | I14: =K14 -> 4542.57 | K14: 4542.57 | L14: Paid $4,542 through 11.15.2022 / Raegan Smith survey included in Civil line
B15: 150 | C15: Title | D15: Soft Costs (Excl. D/S) | G15: 0 | H15: =K15-G15 -> 2850 | I15: =K15 -> 2850 | K15: 2850
B16: 160 | C16: Geotechnical | D16: Soft Costs (Excl. D/S) | G16: 25506.11 | H16: =K16-G16 -> 4950 | I16: =K16 -> 30456.11 | K16: =12500+13006.11+4950 -> 30456.11 | L16: Terracon invoices / infiltration testing
B17: 170 | C17: Environmental | D17: Soft Costs (Excl. D/S) | G17: 16350 | H17: =K17-G17 -> 0 | I17: =K17 -> 16350 | K17: 16350 | L17: Phase 1 & 2
B18: 180 | C18: Due Diligence - Other | D18: Soft Costs (Excl. D/S) | G18: 16424.28 | H18: =K18-G18 -> 3575.72 | I18: =K18 -> 20000 | K18: 20000 | O18: Property Tax Estimate
C19: Total Land / Project Purchase | G19: =SUM(G9:G18) -> 5294081 | H19: =SUM(H9:H18) -> 57295.556 | I19: =SUM(I9:I18) -> 5351376.5 | J19: =SUM(J9:J18) -> 0 | K19: =SUM(K9:K18) -> 5351376.5 | P19: 44926 | Q19: =EOMONTH(P19,12) -> 45291 | R19: =EOMONTH(Q19,12) -> 45657 | S19: =EOMONTH(R19,12) -> 46022
O20: Total Market Value | P20: ='Tax Projection'!B15 -> 5200000 | Q20: ='Tax Projection'!B20 -> 32108209 | R20: ='Tax Projection'!B26 -> 43640298 | S20: ='Tax Projection'!B32 -> 44160298
B21: 200 | C21: Finance | I21: =K21 -> 0 | O21: Value Per Unit | P21: =P20/Assumptions!$M$77 -> 39694.656 | Q21: =Q20/Assumptions!$M$77 -> 245100.83 | R21: =R20/Assumptions!$M$77 -> 333132.05 | S21: =S20/Assumptions!$M$77 -> 337101.51
B22: 210 | C22: Loan Origination Fee | D22: Loan Fees | E22: =Assumptions!E62 -> 0.0075 | G22: 0 | H22: =K22-G22 -> 247429.15 | I22: =K22 -> 247429.15 | K22: =-'Monthly-CF'!I73 -> 247429.15
B23: 220 | C23: Loan Interest | D23: Interest | G23: 0 | H23: =K23-G23 -> 2474291.5 | I23: =K23 -> 2474291.5 | K23: ='Monthly-CF'!I109*7.5% -> 2474291.5 | L23: Assumes 12 months of debt service on fully drawn loan at 7.5% interest rate | O23: Assessment Ratio | P23: 0.4 | Q23: =P23 -> 0.4 | R23: =Q23 -> 0.4 | S23: =R23 -> 0.4
B24: 230 | C24: Real Estate Taxes | D24: Soft Costs (Excl. D/S) | G24: 29810.56 | H24: =K24-G24 -> 432120.96 | I24: =K24 -> 461931.52 | K24: =SUM('RE Tax'!G43:H43) -> 461931.52 | L24: See "RE Tax" tab for detail | O24: Tax Rate | P24: ='Tax Projection'!B17 -> 0.0335376 | Q24: ='Tax Projection'!B22 -> 0.034208352 | R24: ='Tax Projection'!B28 -> 0.034892519 | S24: ='Tax Projection'!B34 -> 0.035590369
B25: 240 | C25: Accounting | D25: Soft Costs (Excl. D/S) | G25: 3338.3 | H25: =K25-G25 -> 21661.7 | I25: =K25 -> 25000 | K25: 25000 | L25: Third party tax prep / accounting services | O25: Est. Valuation Haircut
B26: 250 | C26: Entity Expenses | D26: Soft Costs (Excl. D/S) | G26: 2493.47 | H26: =K26-G26 -> -2493.47 | I26: =K26 -> 0 | K26: 0 | O26: Assesed Value | P26: =P20*P23 -> 2080000 | Q26: =Q20*Q23 -> 12843283 | R26: =R20*R23 -> 17456119 | S26: =S20*S23 -> 17664119
B27: 260 | C27: Lease Up Costs | D27: Soft Costs (Excl. D/S) | G27: 0 | H27: =K27-G27 -> 0 | I27: =K27 -> 0 | K27: =Assumptions!M69 -> 0
B28: 270 | C28: Operating Expense Loss | G28: 0 | H28: =K28-G28 -> 300000 | I28: =K28 -> 300000 | K28: 300000 | O28: Est. Property Taxes Payable | P28: =P26*P24*(1-P25) -> 69758.208 | Q28: =Q26*Q24*(1-Q25) -> 439347.56 | R28: =R26*R24*(1-R25) -> 609087.97 | S28: =S26*S24*(1-S25) -> 628672.53
B29: 280 | C29: Financing Fees - Other | D29: Soft Costs (Excl. D/S) | G29: =+SUM(G30:G32) -> 400000 | H29: =K29-G29 -> 334905.53 | I29: =K29 -> 734905.53 | K29: =+SUM(K30:K32) -> 734905.53
C30: Debt Placement Fee | E30: 0.01 | G30: 0 | H30: =K30-G30 -> 329905.53 | I30: =K30 -> 329905.53 | K30: =E30*'Monthly-CF'!$I$109 -> 329905.53 | O30: Est. Payable during Constr. Period | P30: =SUM(P28:P29) -> 69758.208
C31: Land Loan / Carry Costs | G31: 400000 | H31: =K31-G31 -> 0 | I31: =K31 -> 400000 | K31: =G31 -> 400000 | O31: Taxes per Unit | Q31: =Q28/Assumptions!$C$34 -> 3353.7982 | R31: =R28/Assumptions!$C$34 -> 4649.5265 | S31: =S28/Assumptions!$C$34 -> 4799.0269
C32: Appraisal | G32: 0 | H32: =K32-G32 -> 5000 | I32: =K32 -> 5000 | K32: 5000
C33: Total Finance | G33: =SUM(G22:G29) -> 435642.33 | H33: =SUM(H22:H29) -> 3807915.4 | I33: =SUM(I22:I29) -> 4243557.7 | J33: =SUM(J22:J29) -> 0 | K33: =SUM(K22:K29) -> 4243557.7
B35: 300 | C35: Consultants | D35: Soft Costs (Excl. D/S) | G35: 0 | H35: =K35-G35 -> 0 | I35: =K35 -> 0
B36: 310 | C36: Architectural | D36: Soft Costs (Excl. D/S) | G36: 1036221.6 | H36: =K36-G36 -> 163778.38 | I36: =K36 -> 1200000 | K36: =630000+508450+61550 -> 1200000 | L36: Includes contracts for Pettas and Comma Design / added ~$60K to account for Comma construction admin and additional services
B37: 320 | C37: Landscape Architecture | D37: Soft Costs (Excl. D/S) | G37: 28325 | H37: =K37-G37 -> 1675 | I37: =K37 -> 30000 | K37: 30000 | L37: KVD Landscape Contract
B38: 330 | C38: Interior Design | D38: Soft Costs (Excl. D/S) | G38: 0 | H38: =K38-G38 -> 25000 | I38: =K38 -> 25000 | K38: 25000 | L38: Allowance
B39: 340 | C39: Civil Engineering | D39: Soft Costs (Excl. D/S) | G39: 119035.05 | H39: =K39-G39 -> 40000 | I39: =K39 -> 159035.05 | K39: =119035.05+40000 -> 159035.05 | L39: Includes Thomas & Hutton contract ($83.8K)/ $14k for traffic study / $17K Raegan Smith for Survey // $40K Soil management plan
B40: 350 | C40: Project Management / Coordination | D40: Soft Costs (Excl. D/S) | G40: 0 | H40: =K40-G40 -> 0 | I40: =K40 -> 0
G41: 0 | H41: =K41-G41 -> 0 | K41: 0
B42: 370 | C42: Consultants - Other | D42: Soft Costs (Excl. D/S) | G42: 660 | H42: =K42-G42 -> 49340 | I42: =K42 -> 50000 | K42: 50000 | L42: Allowance
C43: Total Consultants | G43: =SUM(G36:G42) -> 1184241.7 | H43: =SUM(H36:H42) -> 279793.38 | I43: =SUM(I36:I42) -> 1464035.1 | J43: =SUM(J36:J42) -> 0 | K43: =SUM(K36:K42) -> 1464035.1
B45: 400 | C45: Soft Costs | D45: Soft Costs (Excl. D/S) | G45: 0 | H45: =K45-G45 -> 0 | I45: =K45 -> 0
B46: 410 | C46: Insurance | D46: Soft Costs (Excl. D/S) | E46: 0.006 | F46: =K46/(K66+K68) -> 0.01440119 | G46: 689 | H46: =K46-G46 -> 513841 | I46: =K46 -> 514530 | K46: 514530 | L46: Builders Risk quote from Gallagher - 3.23.2303
B47: 420 | C47: Marketing | D47: Soft Costs (Excl. D/S) | G47: 0 | H47: =K47-G47 -> 30000 | I47: =K47 -> 30000 | K47: 30000
B48: 430 | C48: Model / Staging | D48: Soft Costs (Excl. D/S) | G48: 0 | H48: =K48-G48 -> 30000 | I48: =K48 -> 30000 | K48: 30000 | L48: Est Cost for model unit staging
B49: 440 | C49: Legal Fees | D49: Soft Costs (Excl. D/S) | G49: 27759.5 | H49: =K49-G49 -> 202063 | I49: =K49 -> 229822.5 | K49: =29822.5+200000 -> 229822.5 | L49: $29k paid to date; $200k allowance // Includes environmental attorney
B50: 450 | C50: Testing / Special Inspections | D50: Soft Costs (Excl. D/S) | E50: 0.0025 | G50: 0 | H50: =K50-G50 -> 135000 | I50: =K50 -> 135000 | K50: 135000 | L50: Pie Town at $97K / increased to reflect current cost environment
B51: 455 | C51: FF&E | D51: Soft Costs (Excl. D/S) | G51: 0 | H51: =K51-G51 -> 2798000 | I51: =K51 -> 2798000 | K51: =125000+'Assumptions MH'!$G$61 -> 2798000 | L51: Allowance - FFE // $125K for common area and amenity FF&E, $2.6mm for room FF&E
C52: Leasing Office | G52: 0 | H52: =K52-G52 -> 0 | I52: =K52 -> 0
C53: Janitorial/Storage | G53: 0 | H53: =K53-G53 -> 0 | I53: =K53 -> 0
C54: Fitness | G54: 0 | H54: =K54-G54 -> 0 | I54: =K54 -> 0
C55: Corridor Art | G55: 0 | H55: =K55-G55 -> 0 | I55: =K55 -> 0
C56: Lobby | G56: 0 | H56: =K56-G56 -> 0 | I56: =K56 -> 0
C57: Business Lounge | G57: 0 | H57: =K57-G57 -> 0 | I57: =K57 -> 0
C58: Pet Washing Area | G58: 0 | H58: =K58-G58 -> 0 | I58: =K58 -> 0
C59: Pool Deck Area | G59: 0 | H59: =K59-G59 -> 0 | I59: =K59 -> 0
C60: Window Treatments | G60: 0 | H60: =K60-G60 -> 0 | I60: =K60 -> 0
B61: 460 | C61: Soft Costs - Other | D61: Soft Costs (Excl. D/S) | G61: 542.86 | H61: =K61-G61 -> 74457.14 | I61: =K61 -> 75000 | K61: 75000 | L61: Soft cost contingency
C62: Total Soft Costs | G62: =SUM(G46:G51,G61) -> 28991.36 | H62: =SUM(H46:H51,H61) -> 3783361.1 | I62: =SUM(I46:I51,I61) -> 3812352.5 | J62: =SUM(J46:J51,J61) -> 0 | K62: =SUM(K46:K51,K61) -> 3812352.5
B64: 500 | C64: Hard Costs | I64: =K64 -> 0
B65: 510 | C65: Building Permits / Fees | D65: Hard Costs | E65: 0.01 | G65: 119915 | H65: =K65-G65 -> 292210 | I65: =K65 -> 412125 | K65: =281500+130625 -> 412125 | L65: Sewer Capacity fees ($218,500) + Water Capacity Fees ($130,625)
B66: 520 | C66: Construction | D66: Hard Costs | E66: 258 | G66: 0 | H66: =K66-G66 -> 33941883 | I66: =K66 -> 33941883 | K66: =(E66*Assumptions!$J$36)-'Budget Detail'!K68+800000 -> 33941883
B67: 530 | C67: Construction Contingency | D67: Hard Costs | E67: 0.05 | G67: 0 | H67: =K67-G67 -> 1786414.9 | I67: =K67 -> 1786414.9 | K67: =E67*(K66+K68) -> 1786414.9
B68: 540 | C68: Construction Retainage Holding Account | D68: Hard Costs | E68: 0.05 | G68: 0 | H68: =K68-G68 -> 1786414.9 | I68: =K68 -> 1786414.9 | K68: =E68*SUM(Assumptions!N15:N23) -> 1786414.9
B69: 550 | C69: Utilities | D69: Hard Costs | G69: 960 | H69: =K69-G69 -> 30000 | I69: =K69 -> 30960 | K69: =160*131+10000 -> 30960 | L69: Oates water meters @$160/unit + $10,000 allowance | O69: =-'Budget Detail'!J19-'Budget Detail'!J33-'Budget Detail'!J43-'Budget Detail'!J62+'Budget Detail'!J23+'Budget Detail'!J22-I59 -> 0
B70: 560 | C70: Signage / Graphics | D70: Hard Costs | G70: 0 | H70: =K70-G70 -> 77000 | I70: =K70 -> 77000 | K70: =50000+27000 -> 77000 | L70: $50K includes allowance for exterior signage // $27K for design
B71: 570 | C71: AV / Security | D71: Hard Costs | G71: 0 | H71: =K71-G71 -> 200000 | I71: =K71 -> 200000 | K71: 200000 | L71: Proposal from Access DNSI
B72: 580 | C72: Tenant Improvements | D72: Hard Costs | G72: 0 | H72: =K72-G72 -> 0 | I72: =K72 -> 0 | K72: =Assumptions!D57*Assumptions!F41 -> 0
B73: 590 | C73: Hard Costs - Other | D73: Hard Costs | G73: 0 | H73: =K73-G73 -> 205500 | I73: =K73 -> 205500 | K73: 205500 | L73: 2.5K Fence // $183K for soil haul-off // $20K potholing 4th Ave.
C74: Total Hard Costs | G74: =SUM(G65:G73) -> 120875 | H74: =SUM(H65:H73) -> 38319423 | I74: =SUM(I65:I73) -> 38440298 | J74: =SUM(J65:J73) -> 0 | K74: =SUM(K65:K73) -> 38440298
D76: Dev Fess | E76: 0 | G76: 0 | H76: =K76-G76 -> 0
B77: 360 | C77: Developer Fee - CAS | D77: Dev Fess | E77: 0.0375 | G77: 0 | H77: =K77-G77 -> 1672635.6 | I77: =((+I24+I25+I31+I43+I62+I74)*$E$77) -> 1672635.6 | K77: =((+K24+K25+K31+K43+K62+K74)*$E$77) -> 1672635.6
C79: Total Project Budget | G79: =G74+G62+G43+G33+G19+G76+G77 -> 7063831.3 | H79: =H74+H62+H43+H33+H19+H76+H77 -> 47920424 | I79: =I74+I62+I43+I33+I19+I76+I77 -> 54984255 | J79: =J74+J62+J43+J33+J19+J76+J77 -> 0 | K79: =K74+K62+K43+K33+K19+K76+K77 -> 54984255
C80: Check | H80: =K79-H79-G79 -> 0 | I80: ='Monthly-CF'!I76+'Budget Detail'!I79 -> 0 | J80: ='Monthly-CF'!I86+'Budget Detail'!J79 -> 0 | K80: =K79-Assumptions!E21 -> 0
G82: 6707552.1 | K82: =K77/19 -> 88033.455
G83: 264870.18
D84: 130000 | G84: =SUM(G82:G83) -> 6972422.3
D85: =D84/12 -> 10833.333 | G85: =G84-G79 -> -91409.05

Sheet Annual-CF
W1: x
W2: x
W3: x
W4: x
C5: Annual Cash Flow | W5: x
W6: x
W7: x
L8: =EOMONTH('Monthly-CF'!L8,11) -> 45443 | M8: =EOMONTH(L8,12) -> 45808 | N8: =EOMONTH(M8,12) -> 46173 | O8: =EOMONTH(N8,12) -> 46538 | P8: =EOMONTH(O8,12) -> 46904 | Q8: =EOMONTH(P8,12) -> 47269 | R8: =EOMONTH(Q8,12) -> 47634 | S8: =EOMONTH(R8,12) -> 47999 | T8: =EOMONTH(S8,12) -> 48365 | U8: =EOMONTH(T8,12) -> 48730 | W8: x
L9: 1 | M9: =L9+1 -> 2 | N9: =M9+1 -> 3 | O9: =N9+1 -> 4 | P9: =O9+1 -> 5 | Q9: =P9+1 -> 6 | R9: =Q9+1 -> 7 | S9: =R9+1 -> 8 | T9: =S9+1 -> 9 | U9: =T9+1 -> 10 | W9: x
I10: Total | W10: x
D11: Residential Summary
D12: Occupancy | W12: x
D13: Occ - Multi-Family Ph.1 | I13: =MAX(L13:U13) -> 0 | L13: =_xlfn.MAXIFS('Monthly-CF'!$L13:$EA13,'Monthly-CF'!$L$9:$EA$9,'Annual-CF'!L$9) -> 0 | M13: =_xlfn.MAXIFS('Monthly-CF'!$L13:$EA13,'Monthly-CF'!$L$9:$EA$9,'Annual-CF'!M$9) -> 0 | N13: =_xlfn.MAXIFS('Monthly-CF'!$L13:$EA13,'Monthly-CF'!$L$9:$EA$9,'Annual-CF'!N$9) -> 0 | O13: =_xlfn.MAXIFS('Monthly-CF'!$L13:$EA13,'Monthly-CF'!$L$9:$EA$9,'Annual-CF'!O$9) -> 0 | P13: =_xlfn.MAXIFS('Monthly-CF'!$L13:$EA13,'Monthly-CF'!$L$9:$EA$9,'Annual-CF'!P$9) -> 0 | Q13: =_xlfn.MAXIFS('Monthly-CF'!$L13:$EA13,'Monthly-CF'!$L$9:$EA$9,'Annual-CF'!Q$9) -> 0 | R13: =_xlfn.MAXIFS('Monthly-CF'!$L13:$EA13,'Monthly-CF'!$L$9:$EA$9,'Annual-CF'!R$9) -> 0 | S13: =_xlfn.MAXIFS('Monthly-CF'!$L13:$EA13,'Monthly-CF'!$L$9:$EA$9,'Annual-CF'!S$9) -> 0 | ... U13: =_xlfn.MAXIFS('Monthly-CF'!$L13:$EA13,'Monthly-CF'!$L$9:$EA$9,'Annual-CF'!U$9) -> 0 | W13: x
D14: Occ - Multi-Family Ph.2 | I14: =MAX(L14:U14) -> 0 | L14: =_xlfn.MAXIFS('Monthly-CF'!$L14:$EA14,'Monthly-CF'!$L$9:$EA$9,'Annual-CF'!L$9) -> 0 | M14: =_xlfn.MAXIFS('Monthly-CF'!$L14:$EA14,'Monthly-CF'!$L$9:$EA$9,'Annual-CF'!M$9) -> 0 | N14: =_xlfn.MAXIFS('Monthly-CF'!$L14:$EA14,'Monthly-CF'!$L$9:$EA$9,'Annual-CF'!N$9) -> 0 | O14: =_xlfn.MAXIFS('Monthly-CF'!$L14:$EA14,'Monthly-CF'!$L$9:$EA$9,'Annual-CF'!O$9) -> 0 | P14: =_xlfn.MAXIFS('Monthly-CF'!$L14:$EA14,'Monthly-CF'!$L$9:$EA$9,'Annual-CF'!P$9) -> 0 | Q14: =_xlfn.MAXIFS('Monthly-CF'!$L14:$EA14,'Monthly-CF'!$L$9:$EA$9,'Annual-CF'!Q$9) -> 0 | R14: =_xlfn.MAXIFS('Monthly-CF'!$L14:$EA14,'Monthly-CF'!$L$9:$EA$9,'Annual-CF'!R$9) -> 0 | S14: =_xlfn.MAXIFS('Monthly-CF'!$L14:$EA14,'Monthly-CF'!$L$9:$EA$9,'Annual-CF'!S$9) -> 0 | ... U14: =_xlfn.MAXIFS('Monthly-CF'!$L14:$EA14,'Monthly-CF'!$L$9:$EA$9,'Annual-CF'!U$9) -> 0 | W14: x
D15: =CONCATENATE("Occ - ",Assumptions!$J$54) -> Occ - Ancillary Fees | I15: =MAX(L15:U15) -> 0 | L15: =_xlfn.MAXIFS('Monthly-CF'!$L15:$EA15,'Monthly-CF'!$L$9:$EA$9,'Annual-CF'!L$9) -> 0 | M15: =_xlfn.MAXIFS('Monthly-CF'!$L15:$EA15,'Monthly-CF'!$L$9:$EA$9,'Annual-CF'!M$9) -> 0 | N15: =_xlfn.MAXIFS('Monthly-CF'!$L15:$EA15,'Monthly-CF'!$L$9:$EA$9,'Annual-CF'!N$9) -> 0 | O15: =_xlfn.MAXIFS('Monthly-CF'!$L15:$EA15,'Monthly-CF'!$L$9:$EA$9,'Annual-CF'!O$9) -> 0 | P15: =_xlfn.MAXIFS('Monthly-CF'!$L15:$EA15,'Monthly-CF'!$L$9:$EA$9,'Annual-CF'!P$9) -> 0 | Q15: =_xlfn.MAXIFS('Monthly-CF'!$L15:$EA15,'Monthly-CF'!$L$9:$EA$9,'Annual-CF'!Q$9) -> 0 | R15: =_xlfn.MAXIFS('Monthly-CF'!$L15:$EA15,'Monthly-CF'!$L$9:$EA$9,'Annual-CF'!R$9) -> 0 | S15: =_xlfn.MAXIFS('Monthly-CF'!$L15:$EA15,'Monthly-CF'!$L$9:$EA$9,'Annual-CF'!S$9) -> 0 | ... U15: =_xlfn.MAXIFS('Monthly-CF'!$L15:$EA15,'Monthly-CF'!$L$9:$EA$9,'Annual-CF'!U$9) -> 0 | W15: x
W16: x
D17: Leased SF | L17: 0 | M17: =Assumptions!$H$56 -> 0.04 | N17: =((1+M17)*(1+Assumptions!$H$56))-1 -> 0.0816 | O17: =((1+N17)*(1+Assumptions!$H$56))-1 -> 0.124864 | P17: =((1+O17)*(1+Assumptions!$H$56))-1 -> 0.16985856 | Q17: =((1+P17)*(1+Assumptions!$H$56))-1 -> 0.2166529 | R17: =((1+Q17)*(1+Assumptions!$H$56))-1 -> 0.26531902 | S17: =((1+R17)*(1+Assumptions!$H$56))-1 -> 0.31593178 | T17: =((1+S17)*(1+Assumptions!$H$56))-1 -> 0.36856905 | U17: =((1+T17)*(1+Assumptions!$H$56))-1 -> 0.42331181 | W17: x
D18: PSF - Multi-Family Ph.1 | I18: =MAX(L18:U18) -> 0 | L18: =_xlfn.MAXIFS('Monthly-CF'!$L18:$EA18,'Monthly-CF'!$L$9:$EA$9,'Annual-CF'!L$9) -> 0 | M18: =_xlfn.MAXIFS('Monthly-CF'!$L18:$EA18,'Monthly-CF'!$L$9:$EA$9,'Annual-CF'!M$9) -> 0 | N18: =_xlfn.MAXIFS('Monthly-CF'!$L18:$EA18,'Monthly-CF'!$L$9:$EA$9,'Annual-CF'!N$9) -> 0 | O18: =_xlfn.MAXIFS('Monthly-CF'!$L18:$EA18,'Monthly-CF'!$L$9:$EA$9,'Annual-CF'!O$9) -> 0 | P18: =_xlfn.MAXIFS('Monthly-CF'!$L18:$EA18,'Monthly-CF'!$L$9:$EA$9,'Annual-CF'!P$9) -> 0 | Q18: =_xlfn.MAXIFS('Monthly-CF'!$L18:$EA18,'Monthly-CF'!$L$9:$EA$9,'Annual-CF'!Q$9) -> 0 | R18: =_xlfn.MAXIFS('Monthly-CF'!$L18:$EA18,'Monthly-CF'!$L$9:$EA$9,'Annual-CF'!R$9) -> 0 | S18: =_xlfn.MAXIFS('Monthly-CF'!$L18:$EA18,'Monthly-CF'!$L$9:$EA$9,'Annual-CF'!S$9) -> 0 | ... U18: =_xlfn.MAXIFS('Monthly-CF'!$L18:$EA18,'Monthly-CF'!$L$9:$EA$9,'Annual-CF'!U$9) -> 0 | W18: x
D19: PSF - Multi-Family Ph.2 | I19: =MAX(L19:U19) -> 0 | L19: =_xlfn.MAXIFS('Monthly-CF'!$L19:$EA19,'Monthly-CF'!$L$9:$EA$9,'Annual-CF'!L$9) -> 0 | M19: =_xlfn.MAXIFS('Monthly-CF'!$L19:$EA19,'Monthly-CF'!$L$9:$EA$9,'Annual-CF'!M$9) -> 0 | N19: =_xlfn.MAXIFS('Monthly-CF'!$L19:$EA19,'Monthly-CF'!$L$9:$EA$9,'Annual-CF'!N$9) -> 0 | O19: =_xlfn.MAXIFS('Monthly-CF'!$L19:$EA19,'Monthly-CF'!$L$9:$EA$9,'Annual-CF'!O$9) -> 0 | P19: =_xlfn.MAXIFS('Monthly-CF'!$L19:$EA19,'Monthly-CF'!$L$9:$EA$9,'Annual-CF'!P$9) -> 0 | Q19: =_xlfn.MAXIFS('Monthly-CF'!$L19:$EA19,'Monthly-CF'!$L$9:$EA$9,'Annual-CF'!Q$9) -> 0 | R19: =_xlfn.MAXIFS('Monthly-CF'!$L19:$EA19,'Monthly-CF'!$L$9:$EA$9,'Annual-CF'!R$9) -> 0 | S19: =_xlfn.MAXIFS('Monthly-CF'!$L19:$EA19,'Monthly-CF'!$L$9:$EA$9,'Annual-CF'!S$9) -> 0 | ... U19: =_xlfn.MAXIFS('Monthly-CF'!$L19:$EA19,'Monthly-CF'!$L$9:$EA$9,'Annual-CF'!U$9) -> 0 | W19: x
D20: =CONCATENATE("PSF - ",Assumptions!J54) -> PSF - Ancillary Fees | I20: =MAX(L20:U20) -> 0 | L20: =_xlfn.MAXIFS('Monthly-CF'!$L20:$EA20,'Monthly-CF'!$L$9:$EA$9,'Annual-CF'!L$9) -> 0 | M20: =_xlfn.MAXIFS('Monthly-CF'!$L20:$EA20,'Monthly-CF'!$L$9:$EA$9,'Annual-CF'!M$9) -> 0 | N20: =_xlfn.MAXIFS('Monthly-CF'!$L20:$EA20,'Monthly-CF'!$L$9:$EA$9,'Annual-CF'!N$9) -> 0 | O20: =_xlfn.MAXIFS('Monthly-CF'!$L20:$EA20,'Monthly-CF'!$L$9:$EA$9,'Annual-CF'!O$9) -> 0 | P20: =_xlfn.MAXIFS('Monthly-CF'!$L20:$EA20,'Monthly-CF'!$L$9:$EA$9,'Annual-CF'!P$9) -> 0 | Q20: =_xlfn.MAXIFS('Monthly-CF'!$L20:$EA20,'Monthly-CF'!$L$9:$EA$9,'Annual-CF'!Q$9) -> 0 | R20: =_xlfn.MAXIFS('Monthly-CF'!$L20:$EA20,'Monthly-CF'!$L$9:$EA$9,'Annual-CF'!R$9) -> 0 | S20: =_xlfn.MAXIFS('Monthly-CF'!$L20:$EA20,'Monthly-CF'!$L$9:$EA$9,'Annual-CF'!S$9) -> 0 | ... U20: =_xlfn.MAXIFS('Monthly-CF'!$L20:$EA20,'Monthly-CF'!$L$9:$EA$9,'Annual-CF'!U$9) -> 0 | W20: x
W21: x
D22: Revenue | W22: x
D23: Revenue - Multi-Family Ph.1 | I23: =SUM(K23:U23) -> 0 | L23: =SUMIFS('Monthly-CF'!$L23:$EA23,'Monthly-CF'!$L$9:$EA$9,'Annual-CF'!L$9) -> 0 | M23: =SUMIFS('Monthly-CF'!$L23:$EA23,'Monthly-CF'!$L$9:$EA$9,'Annual-CF'!M$9) -> 0 | N23: =SUMIFS('Monthly-CF'!$L23:$EA23,'Monthly-CF'!$L$9:$EA$9,'Annual-CF'!N$9) -> 0 | O23: =SUMIFS('Monthly-CF'!$L23:$EA23,'Monthly-CF'!$L$9:$EA$9,'Annual-CF'!O$9) -> 0 | P23: =SUMIFS('Monthly-CF'!$L23:$EA23,'Monthly-CF'!$L$9:$EA$9,'Annual-CF'!P$9) -> 0 | Q23: =SUMIFS('Monthly-CF'!$L23:$EA23,'Monthly-CF'!$L$9:$EA$9,'Annual-CF'!Q$9) -> 0 | R23: =SUMIFS('Monthly-CF'!$L23:$EA23,'Monthly-CF'!$L$9:$EA$9,'Annual-CF'!R$9) -> 0 | S23: =SUMIFS('Monthly-CF'!$L23:$EA23,'Monthly-CF'!$L$9:$EA$9,'Annual-CF'!S$9) -> 0 | ... U23: =SUMIFS('Monthly-CF'!$L23:$EA23,'Monthly-CF'!$L$9:$EA$9,'Annual-CF'!U$9) -> 0 | W23: x
D24: Revenue - Multi-Family Ph.2 | I24: =SUM(K24:U24) -> 0 | L24: =SUMIFS('Monthly-CF'!$L24:$EA24,'Monthly-CF'!$L$9:$EA$9,'Annual-CF'!L$9) -> 0 | M24: =SUMIFS('Monthly-CF'!$L24:$EA24,'Monthly-CF'!$L$9:$EA$9,'Annual-CF'!M$9) -> 0 | N24: =SUMIFS('Monthly-CF'!$L24:$EA24,'Monthly-CF'!$L$9:$EA$9,'Annual-CF'!N$9) -> 0 | O24: =SUMIFS('Monthly-CF'!$L24:$EA24,'Monthly-CF'!$L$9:$EA$9,'Annual-CF'!O$9) -> 0 | P24: =SUMIFS('Monthly-CF'!$L24:$EA24,'Monthly-CF'!$L$9:$EA$9,'Annual-CF'!P$9) -> 0 | Q24: =SUMIFS('Monthly-CF'!$L24:$EA24,'Monthly-CF'!$L$9:$EA$9,'Annual-CF'!Q$9) -> 0 | R24: =SUMIFS('Monthly-CF'!$L24:$EA24,'Monthly-CF'!$L$9:$EA$9,'Annual-CF'!R$9) -> 0 | S24: =SUMIFS('Monthly-CF'!$L24:$EA24,'Monthly-CF'!$L$9:$EA$9,'Annual-CF'!S$9) -> 0 | ... U24: =SUMIFS('Monthly-CF'!$L24:$EA24,'Monthly-CF'!$L$9:$EA$9,'Annual-CF'!U$9) -> 0 | W24: x
D25: =CONCATENATE("Revenue - ",Assumptions!J$54) -> Revenue - Ancillary Fees | I25: =SUM(K25:U25) -> 0 | L25: =SUMIFS('Monthly-CF'!$L25:$EA25,'Monthly-CF'!$L$9:$EA$9,'Annual-CF'!L$9) -> 0 | M25: =SUMIFS('Monthly-CF'!$L25:$EA25,'Monthly-CF'!$L$9:$EA$9,'Annual-CF'!M$9) -> 0 | N25: =SUMIFS('Monthly-CF'!$L25:$EA25,'Monthly-CF'!$L$9:$EA$9,'Annual-CF'!N$9) -> 0 | O25: =SUMIFS('Monthly-CF'!$L25:$EA25,'Monthly-CF'!$L$9:$EA$9,'Annual-CF'!O$9) -> 0 | P25: =SUMIFS('Monthly-CF'!$L25:$EA25,'Monthly-CF'!$L$9:$EA$9,'Annual-CF'!P$9) -> 0 | Q25: =SUMIFS('Monthly-CF'!$L25:$EA25,'Monthly-CF'!$L$9:$EA$9,'Annual-CF'!Q$9) -> 0 | R25: =SUMIFS('Monthly-CF'!$L25:$EA25,'Monthly-CF'!$L$9:$EA$9,'Annual-CF'!R$9) -> 0 | S25: =SUMIFS('Monthly-CF'!$L25:$EA25,'Monthly-CF'!$L$9:$EA$9,'Annual-CF'!S$9) -> 0 | ... U25: =SUMIFS('Monthly-CF'!$L25:$EA25,'Monthly-CF'!$L$9:$EA$9,'Annual-CF'!U$9) -> 0 | W25: x
W26: x
D27: Rent Concessions | I27: =SUM(K27:U27) -> 0 | L27: =SUMIFS('Monthly-CF'!$L27:$EA27,'Monthly-CF'!$L$9:$EA$9,'Annual-CF'!L$9) -> 0 | M27: =SUMIFS('Monthly-CF'!$L27:$EA27,'Monthly-CF'!$L$9:$EA$9,'Annual-CF'!M$9) -> 0 | N27: =SUMIFS('Monthly-CF'!$L27:$EA27,'Monthly-CF'!$L$9:$EA$9,'Annual-CF'!N$9) -> 0 | O27: =SUMIFS('Monthly-CF'!$L27:$EA27,'Monthly-CF'!$L$9:$EA$9,'Annual-CF'!O$9) -> 0 | P27: =SUMIFS('Monthly-CF'!$L27:$EA27,'Monthly-CF'!$L$9:$EA$9,'Annual-CF'!P$9) -> 0 | Q27: =SUMIFS('Monthly-CF'!$L27:$EA27,'Monthly-CF'!$L$9:$EA$9,'Annual-CF'!Q$9) -> 0 | R27: =SUMIFS('Monthly-CF'!$L27:$EA27,'Monthly-CF'!$L$9:$EA$9,'Annual-CF'!R$9) -> 0 | S27: =SUMIFS('Monthly-CF'!$L27:$EA27,'Monthly-CF'!$L$9:$EA$9,'Annual-CF'!S$9) -> 0 | ... U27: =SUMIFS('Monthly-CF'!$L27:$EA27,'Monthly-CF'!$L$9:$EA$9,'Annual-CF'!U$9) -> 0 | W27: x
D28: Net Revenue | I28: =SUM(K28:U28) -> 0 | L28: =SUM(L23:L25)+SUM(L27:L27) -> 0 | M28: =SUM(M23:M25)+SUM(M27:M27) -> 0 | N28: =SUM(N23:N25)+SUM(N27:N27) -> 0 | O28: =SUM(O23:O25)+SUM(O27:O27) -> 0 | P28: =SUM(P23:P25)+SUM(P27:P27) -> 0 | Q28: =SUM(Q23:Q25)+SUM(Q27:Q27) -> 0 | R28: =SUM(R23:R25)+SUM(R27:R27) -> 0 | S28: =SUM(S23:S25)+SUM(S27:S27) -> 0 | ... U28: =SUM(U23:U25)+SUM(U27:U27) -> 0 | W28: x
W29: x
L30: 0 | M30: =Assumptions!$I$81 -> 0.03 | N30: =((1+M30)*(1+Assumptions!$I$81))-1 -> 0.0609 | O30: =((1+N30)*(1+Assumptions!$I$81))-1 -> 0.092727 | P30: =((1+O30)*(1+Assumptions!$I$81))-1 -> 0.12550881 | Q30: =((1+P30)*(1+Assumptions!$I$81))-1 -> 0.15927407 | R30: =((1+Q30)*(1+Assumptions!$I$81))-1 -> 0.1940523 | S30: =((1+R30)*(1+Assumptions!$I$81))-1 -> 0.22987387 | T30: =((1+S30)*(1+Assumptions!$I$81))-1 -> 0.26677008 | U30: =((1+T30)*(1+Assumptions!$I$81))-1 -> 0.30477318 | W30: x
D31: Op Exp - Multi-Family Ph.1 | I31: =SUM(K31:U31) -> 0 | L31: =SUMIFS('Monthly-CF'!$L31:$EA31,'Monthly-CF'!$L$9:$EA$9,'Annual-CF'!L$9) -> 0 | M31: =SUMIFS('Monthly-CF'!$L31:$EA31,'Monthly-CF'!$L$9:$EA$9,'Annual-CF'!M$9) -> 0 | N31: =SUMIFS('Monthly-CF'!$L31:$EA31,'Monthly-CF'!$L$9:$EA$9,'Annual-CF'!N$9) -> 0 | O31: =SUMIFS('Monthly-CF'!$L31:$EA31,'Monthly-CF'!$L$9:$EA$9,'Annual-CF'!O$9) -> 0 | P31: =SUMIFS('Monthly-CF'!$L31:$EA31,'Monthly-CF'!$L$9:$EA$9,'Annual-CF'!P$9) -> 0 | Q31: =SUMIFS('Monthly-CF'!$L31:$EA31,'Monthly-CF'!$L$9:$EA$9,'Annual-CF'!Q$9) -> 0 | R31: =SUMIFS('Monthly-CF'!$L31:$EA31,'Monthly-CF'!$L$9:$EA$9,'Annual-CF'!R$9) -> 0 | S31: =SUMIFS('Monthly-CF'!$L31:$EA31,'Monthly-CF'!$L$9:$EA$9,'Annual-CF'!S$9) -> 0 | ... U31: =SUMIFS('Monthly-CF'!$L31:$EA31,'Monthly-CF'!$L$9:$EA$9,'Annual-CF'!U$9) -> 0 | W31: x
D32: Op Exp - Multi-Family Ph. 2 | I32: =SUM(K32:U32) -> 0 | L32: =SUMIFS('Monthly-CF'!$L32:$EA32,'Monthly-CF'!$L$9:$EA$9,'Annual-CF'!L$9) -> 0 | M32: =SUMIFS('Monthly-CF'!$L32:$EA32,'Monthly-CF'!$L$9:$EA$9,'Annual-CF'!M$9) -> 0 | N32: =SUMIFS('Monthly-CF'!$L32:$EA32,'Monthly-CF'!$L$9:$EA$9,'Annual-CF'!N$9) -> 0 | O32: =SUMIFS('Monthly-CF'!$L32:$EA32,'Monthly-CF'!$L$9:$EA$9,'Annual-CF'!O$9) -> 0 | P32: =SUMIFS('Monthly-CF'!$L32:$EA32,'Monthly-CF'!$L$9:$EA$9,'Annual-CF'!P$9) -> 0 | Q32: =SUMIFS('Monthly-CF'!$L32:$EA32,'Monthly-CF'!$L$9:$EA$9,'Annual-CF'!Q$9) -> 0 | R32: =SUMIFS('Monthly-CF'!$L32:$EA32,'Monthly-CF'!$L$9:$EA$9,'Annual-CF'!R$9) -> 0 | S32: =SUMIFS('Monthly-CF'!$L32:$EA32,'Monthly-CF'!$L$9:$EA$9,'Annual-CF'!S$9) -> 0 | ... U32: =SUMIFS('Monthly-CF'!$L32:$EA32,'Monthly-CF'!$L$9:$EA$9,'Annual-CF'!U$9) -> 0 | W32: x
D33: Total Operating Expenses | I33: =SUM(K33:U33) -> 0 | L33: =SUMIFS('Monthly-CF'!$L33:$EA33,'Monthly-CF'!$L$9:$EA$9,'Annual-CF'!L$9) -> 0 | M33: =SUMIFS('Monthly-CF'!$L33:$EA33,'Monthly-CF'!$L$9:$EA$9,'Annual-CF'!M$9) -> 0 | N33: =SUMIFS('Monthly-CF'!$L33:$EA33,'Monthly-CF'!$L$9:$EA$9,'Annual-CF'!N$9) -> 0 | O33: =SUMIFS('Monthly-CF'!$L33:$EA33,'Monthly-CF'!$L$9:$EA$9,'Annual-CF'!O$9) -> 0 | P33: =SUMIFS('Monthly-CF'!$L33:$EA33,'Monthly-CF'!$L$9:$EA$9,'Annual-CF'!P$9) -> 0 | Q33: =SUMIFS('Monthly-CF'!$L33:$EA33,'Monthly-CF'!$L$9:$EA$9,'Annual-CF'!Q$9) -> 0 | R33: =SUMIFS('Monthly-CF'!$L33:$EA33,'Monthly-CF'!$L$9:$EA$9,'Annual-CF'!R$9) -> 0 | S33: =SUMIFS('Monthly-CF'!$L33:$EA33,'Monthly-CF'!$L$9:$EA$9,'Annual-CF'!S$9) -> 0 | ... U33: =SUMIFS('Monthly-CF'!$L33:$EA33,'Monthly-CF'!$L$9:$EA$9,'Annual-CF'!U$9) -> 0 | W33: x
D34: Operating Income | I34: =SUM(K34:U34) -> 0 | L34: =L28+L33 -> 0 | M34: =M28+M33 -> 0 | N34: =N28+N33 -> 0 | O34: =O28+O33 -> 0 | P34: =P28+P33 -> 0 | Q34: =Q28+Q33 -> 0 | R34: =R28+R33 -> 0 | S34: =S28+S33 -> 0 | ... U34: =U28+U33 -> 0 | W34: x
W35: x
D36: Capital Reserve | I36: =SUM(K36:U36) -> 0 | L36: =SUMIFS('Monthly-CF'!$L36:$EA36,'Monthly-CF'!$L$9:$EA$9,'Annual-CF'!L$9) -> 0 | M36: =SUMIFS('Monthly-CF'!$L36:$EA36,'Monthly-CF'!$L$9:$EA$9,'Annual-CF'!M$9) -> 0 | N36: =SUMIFS('Monthly-CF'!$L36:$EA36,'Monthly-CF'!$L$9:$EA$9,'Annual-CF'!N$9) -> 0 | O36: =SUMIFS('Monthly-CF'!$L36:$EA36,'Monthly-CF'!$L$9:$EA$9,'Annual-CF'!O$9) -> 0 | P36: =SUMIFS('Monthly-CF'!$L36:$EA36,'Monthly-CF'!$L$9:$EA$9,'Annual-CF'!P$9) -> 0 | Q36: =SUMIFS('Monthly-CF'!$L36:$EA36,'Monthly-CF'!$L$9:$EA$9,'Annual-CF'!Q$9) -> 0 | R36: =SUMIFS('Monthly-CF'!$L36:$EA36,'Monthly-CF'!$L$9:$EA$9,'Annual-CF'!R$9) -> 0 | S36: =SUMIFS('Monthly-CF'!$L36:$EA36,'Monthly-CF'!$L$9:$EA$9,'Annual-CF'!S$9) -> 0 | ... U36: =SUMIFS('Monthly-CF'!$L36:$EA36,'Monthly-CF'!$L$9:$EA$9,'Annual-CF'!U$9) -> 0 | W36: x
D37: Operating Cash flow - Residential | I37: =SUM(K37:U37) -> 0 | L37: =L34+L36 -> 0 | M37: =M34+M36 -> 0 | N37: =N34+N36 -> 0 | O37: =O34+O36 -> 0 | P37: =P34+P36 -> 0 | Q37: =Q34+Q36 -> 0 | R37: =R34+R36 -> 0 | S37: =S34+S36 -> 0 | ... U37: =U34+U36 -> 0 | W37: x
W38: x
D39: Residential Summary - STR / MF | W39: x
D41: Income to Owner - After FF&E | I41: =SUM(K41:U41) -> 42410997 | L41: =SUMIFS('Monthly-CF'!$L41:$EA41,'Monthly-CF'!$L$9:$EA$9,'Annual-CF'!L$9) -> 0 | M41: =SUMIFS('Monthly-CF'!$L41:$EA41,'Monthly-CF'!$L$9:$EA$9,'Annual-CF'!M$9) -> 1008353.1 | N41: =SUMIFS('Monthly-CF'!$L41:$EA41,'Monthly-CF'!$L$9:$EA$9,'Annual-CF'!N$9) -> 4124076.8 | O41: =SUMIFS('Monthly-CF'!$L41:$EA41,'Monthly-CF'!$L$9:$EA$9,'Annual-CF'!O$9) -> 5125001.3 | P41: =SUMIFS('Monthly-CF'!$L41:$EA41,'Monthly-CF'!$L$9:$EA$9,'Annual-CF'!P$9) -> 5170334.9 | Q41: =SUMIFS('Monthly-CF'!$L41:$EA41,'Monthly-CF'!$L$9:$EA$9,'Annual-CF'!Q$9) -> 5202640.3 | R41: =SUMIFS('Monthly-CF'!$L41:$EA41,'Monthly-CF'!$L$9:$EA$9,'Annual-CF'!R$9) -> 5250319 | S41: =SUMIFS('Monthly-CF'!$L41:$EA41,'Monthly-CF'!$L$9:$EA$9,'Annual-CF'!S$9) -> 5342025.9 | ... U41: =SUMIFS('Monthly-CF'!$L41:$EA41,'Monthly-CF'!$L$9:$EA$9,'Annual-CF'!U$9) -> 5667355.3 | W41: x
D42: Less: Insurance | I42: =SUM(K42:U42) -> -2713323.9 | L42: =SUMIFS('Monthly-CF'!$L42:$EA42,'Monthly-CF'!$L$9:$EA$9,'Annual-CF'!L$9) -> 0 | M42: =SUMIFS('Monthly-CF'!$L42:$EA42,'Monthly-CF'!$L$9:$EA$9,'Annual-CF'!M$9) -> -118063.75 | N42: =SUMIFS('Monthly-CF'!$L42:$EA42,'Monthly-CF'!$L$9:$EA$9,'Annual-CF'!N$9) -> -291853.59 | O42: =SUMIFS('Monthly-CF'!$L42:$EA42,'Monthly-CF'!$L$9:$EA$9,'Annual-CF'!O$9) -> -300609.2 | P42: =SUMIFS('Monthly-CF'!$L42:$EA42,'Monthly-CF'!$L$9:$EA$9,'Annual-CF'!P$9) -> -309627.47 | Q42: =SUMIFS('Monthly-CF'!$L42:$EA42,'Monthly-CF'!$L$9:$EA$9,'Annual-CF'!Q$9) -> -318916.3 | R42: =SUMIFS('Monthly-CF'!$L42:$EA42,'Monthly-CF'!$L$9:$EA$9,'Annual-CF'!R$9) -> -328483.79 | S42: =SUMIFS('Monthly-CF'!$L42:$EA42,'Monthly-CF'!$L$9:$EA$9,'Annual-CF'!S$9) -> -338338.3 | ... U42: =SUMIFS('Monthly-CF'!$L42:$EA42,'Monthly-CF'!$L$9:$EA$9,'Annual-CF'!U$9) -> -358943.1
D43: Less: RE Tax | I43: =SUM(K43:U43) -> -4640788.6 | L43: =SUMIFS('Monthly-CF'!$L43:$EA43,'Monthly-CF'!$L$9:$EA$9,'Annual-CF'!L$9) -> 0 | M43: =SUMIFS('Monthly-CF'!$L43:$EA43,'Monthly-CF'!$L$9:$EA$9,'Annual-CF'!M$9) -> -164128.87 | N43: =SUMIFS('Monthly-CF'!$L43:$EA43,'Monthly-CF'!$L$9:$EA$9,'Annual-CF'!N$9) -> -493937.58 | O43: =SUMIFS('Monthly-CF'!$L43:$EA43,'Monthly-CF'!$L$9:$EA$9,'Annual-CF'!O$9) -> -496407.26 | P43: =SUMIFS('Monthly-CF'!$L43:$EA43,'Monthly-CF'!$L$9:$EA$9,'Annual-CF'!P$9) -> -498889.3 | Q43: =SUMIFS('Monthly-CF'!$L43:$EA43,'Monthly-CF'!$L$9:$EA$9,'Annual-CF'!Q$9) -> -501383.75 | R43: =SUMIFS('Monthly-CF'!$L43:$EA43,'Monthly-CF'!$L$9:$EA$9,'Annual-CF'!R$9) -> -503890.67 | S43: =SUMIFS('Monthly-CF'!$L43:$EA43,'Monthly-CF'!$L$9:$EA$9,'Annual-CF'!S$9) -> -471137.77 | ... U43: =SUMIFS('Monthly-CF'!$L43:$EA43,'Monthly-CF'!$L$9:$EA$9,'Annual-CF'!U$9) -> -766923.13 | W43: x
D44: Income to Owner - After FF&E & RE Tax | I44: =SUM(K44:U44) -> 35056884 | L44: =SUMIFS('Monthly-CF'!$L44:$EA44,'Monthly-CF'!$L$9:$EA$9,'Annual-CF'!L$9) -> 0 | M44: =SUMIFS('Monthly-CF'!$L44:$EA44,'Monthly-CF'!$L$9:$EA$9,'Annual-CF'!M$9) -> 726160.53 | N44: =SUMIFS('Monthly-CF'!$L44:$EA44,'Monthly-CF'!$L$9:$EA$9,'Annual-CF'!N$9) -> 3338285.7 | O44: =SUMIFS('Monthly-CF'!$L44:$EA44,'Monthly-CF'!$L$9:$EA$9,'Annual-CF'!O$9) -> 4327984.8 | P44: =SUMIFS('Monthly-CF'!$L44:$EA44,'Monthly-CF'!$L$9:$EA$9,'Annual-CF'!P$9) -> 4361818.1 | Q44: =SUMIFS('Monthly-CF'!$L44:$EA44,'Monthly-CF'!$L$9:$EA$9,'Annual-CF'!Q$9) -> 4382340.2 | R44: =SUMIFS('Monthly-CF'!$L44:$EA44,'Monthly-CF'!$L$9:$EA$9,'Annual-CF'!R$9) -> 4417944.5 | S44: =SUMIFS('Monthly-CF'!$L44:$EA44,'Monthly-CF'!$L$9:$EA$9,'Annual-CF'!S$9) -> 4532549.9 | ... U44: =SUMIFS('Monthly-CF'!$L44:$EA44,'Monthly-CF'!$L$9:$EA$9,'Annual-CF'!U$9) -> 4541489.1 | W44: x
D45: Commercial Summary | W45: x
W46: x
D47: =CONCATENATE("Occ - ",Assumptions!$D$54) -> Occ - Commercial | I47: =MAX(L47:U47) -> 0 | L47: =_xlfn.MAXIFS('Monthly-CF'!$L48:$EA48,'Monthly-CF'!$L$9:$EA$9,'Annual-CF'!L$9) -> 0 | M47: =_xlfn.MAXIFS('Monthly-CF'!$L48:$EA48,'Monthly-CF'!$L$9:$EA$9,'Annual-CF'!M$9) -> 0 | N47: =_xlfn.MAXIFS('Monthly-CF'!$L48:$EA48,'Monthly-CF'!$L$9:$EA$9,'Annual-CF'!N$9) -> 0 | O47: =_xlfn.MAXIFS('Monthly-CF'!$L48:$EA48,'Monthly-CF'!$L$9:$EA$9,'Annual-CF'!O$9) -> 0 | P47: =_xlfn.MAXIFS('Monthly-CF'!$L48:$EA48,'Monthly-CF'!$L$9:$EA$9,'Annual-CF'!P$9) -> 0 | Q47: =_xlfn.MAXIFS('Monthly-CF'!$L48:$EA48,'Monthly-CF'!$L$9:$EA$9,'Annual-CF'!Q$9) -> 0 | R47: =_xlfn.MAXIFS('Monthly-CF'!$L48:$EA48,'Monthly-CF'!$L$9:$EA$9,'Annual-CF'!R$9) -> 0 | S47: =_xlfn.MAXIFS('Monthly-CF'!$L48:$EA48,'Monthly-CF'!$L$9:$EA$9,'Annual-CF'!S$9) -> 0 | ... U47: =_xlfn.MAXIFS('Monthly-CF'!$L48:$EA48,'Monthly-CF'!$L$9:$EA$9,'Annual-CF'!U$9) -> 0 | W47: x
D48: =CONCATENATE("PSF - ",Assumptions!I54) -> PSF - Commercial | I48: =MAX(L48:U48) -> 0 | L48: =_xlfn.MAXIFS('Monthly-CF'!$L49:$EA49,'Monthly-CF'!$L$9:$EA$9,'Annual-CF'!L$9) -> 0 | M48: =_xlfn.MAXIFS('Monthly-CF'!$L49:$EA49,'Monthly-CF'!$L$9:$EA$9,'Annual-CF'!M$9) -> 0 | N48: =_xlfn.MAXIFS('Monthly-CF'!$L49:$EA49,'Monthly-CF'!$L$9:$EA$9,'Annual-CF'!N$9) -> 0 | O48: =_xlfn.MAXIFS('Monthly-CF'!$L49:$EA49,'Monthly-CF'!$L$9:$EA$9,'Annual-CF'!O$9) -> 0 | P48: =_xlfn.MAXIFS('Monthly-CF'!$L49:$EA49,'Monthly-CF'!$L$9:$EA$9,'Annual-CF'!P$9) -> 0 | Q48: =_xlfn.MAXIFS('Monthly-CF'!$L49:$EA49,'Monthly-CF'!$L$9:$EA$9,'Annual-CF'!Q$9) -> 0 | R48: =_xlfn.MAXIFS('Monthly-CF'!$L49:$EA49,'Monthly-CF'!$L$9:$EA$9,'Annual-CF'!R$9) -> 0 | S48: =_xlfn.MAXIFS('Monthly-CF'!$L49:$EA49,'Monthly-CF'!$L$9:$EA$9,'Annual-CF'!S$9) -> 0 | ... U48: =_xlfn.MAXIFS('Monthly-CF'!$L49:$EA49,'Monthly-CF'!$L$9:$EA$9,'Annual-CF'!U$9) -> 0 | W48: x
W49: x
D50: =CONCATENATE("Revenue - ",Assumptions!$I$54) -> Revenue - Commercial | I50: =SUM(K50:U50) -> 0 | L50: =SUMIFS('Monthly-CF'!$L51:$EA51,'Monthly-CF'!$L$9:$EA$9,'Annual-CF'!L$9) -> 0 | M50: =SUMIFS('Monthly-CF'!$L51:$EA51,'Monthly-CF'!$L$9:$EA$9,'Annual-CF'!M$9) -> 0 | N50: =SUMIFS('Monthly-CF'!$L51:$EA51,'Monthly-CF'!$L$9:$EA$9,'Annual-CF'!N$9) -> 0 | O50: =SUMIFS('Monthly-CF'!$L51:$EA51,'Monthly-CF'!$L$9:$EA$9,'Annual-CF'!O$9) -> 0 | P50: =SUMIFS('Monthly-CF'!$L51:$EA51,'Monthly-CF'!$L$9:$EA$9,'Annual-CF'!P$9) -> 0 | Q50: =SUMIFS('Monthly-CF'!$L51:$EA51,'Monthly-CF'!$L$9:$EA$9,'Annual-CF'!Q$9) -> 0 | R50: =SUMIFS('Monthly-CF'!$L51:$EA51,'Monthly-CF'!$L$9:$EA$9,'Annual-CF'!R$9) -> 0 | S50: =SUMIFS('Monthly-CF'!$L51:$EA51,'Monthly-CF'!$L$9:$EA$9,'Annual-CF'!S$9) -> 0 | ... U50: =SUMIFS('Monthly-CF'!$L51:$EA51,'Monthly-CF'!$L$9:$EA$9,'Annual-CF'!U$9) -> 0 | W50: x
D51: CAM | I51: =SUM(K51:U51) -> 0 | L51: =SUMIFS('Monthly-CF'!$L52:$EA52,'Monthly-CF'!$L$9:$EA$9,'Annual-CF'!L$9) -> 0 | M51: =SUMIFS('Monthly-CF'!$L52:$EA52,'Monthly-CF'!$L$9:$EA$9,'Annual-CF'!M$9) -> 0 | N51: =SUMIFS('Monthly-CF'!$L52:$EA52,'Monthly-CF'!$L$9:$EA$9,'Annual-CF'!N$9) -> 0 | O51: =SUMIFS('Monthly-CF'!$L52:$EA52,'Monthly-CF'!$L$9:$EA$9,'Annual-CF'!O$9) -> 0 | P51: =SUMIFS('Monthly-CF'!$L52:$EA52,'Monthly-CF'!$L$9:$EA$9,'Annual-CF'!P$9) -> 0 | Q51: =SUMIFS('Monthly-CF'!$L52:$EA52,'Monthly-CF'!$L$9:$EA$9,'Annual-CF'!Q$9) -> 0 | R51: =SUMIFS('Monthly-CF'!$L52:$EA52,'Monthly-CF'!$L$9:$EA$9,'Annual-CF'!R$9) -> 0 | S51: =SUMIFS('Monthly-CF'!$L52:$EA52,'Monthly-CF'!$L$9:$EA$9,'Annual-CF'!S$9) -> 0 | ... U51: =SUMIFS('Monthly-CF'!$L52:$EA52,'Monthly-CF'!$L$9:$EA$9,'Annual-CF'!U$9) -> 0 | W51: x
D52: Net Revenue | I52: =SUM(K52:U52) -> 0 | L52: =SUM(L50:L51) -> 0 | M52: =SUM(M50:M51) -> 0 | N52: =SUM(N50:N51) -> 0 | O52: =SUM(O50:O51) -> 0 | P52: =SUM(P50:P51) -> 0 | Q52: =SUM(Q50:Q51) -> 0 | R52: =SUM(R50:R51) -> 0 | S52: =SUM(S50:S51) -> 0 | ... U52: =SUM(U50:U51) -> 0 | W52: x
D53: Commissions | I53: =SUM(K53:U53) -> 0 | L53: =SUMIFS('Monthly-CF'!$L54:$EA54,'Monthly-CF'!$L$9:$EA$9,'Annual-CF'!L$9) -> 0 | M53: =SUMIFS('Monthly-CF'!$L54:$EA54,'Monthly-CF'!$L$9:$EA$9,'Annual-CF'!M$9) -> 0 | N53: =SUMIFS('Monthly-CF'!$L54:$EA54,'Monthly-CF'!$L$9:$EA$9,'Annual-CF'!N$9) -> 0 | O53: =SUMIFS('Monthly-CF'!$L54:$EA54,'Monthly-CF'!$L$9:$EA$9,'Annual-CF'!O$9) -> 0 | P53: =SUMIFS('Monthly-CF'!$L54:$EA54,'Monthly-CF'!$L$9:$EA$9,'Annual-CF'!P$9) -> 0 | Q53: =SUMIFS('Monthly-CF'!$L54:$EA54,'Monthly-CF'!$L$9:$EA$9,'Annual-CF'!Q$9) -> 0 | R53: =SUMIFS('Monthly-CF'!$L54:$EA54,'Monthly-CF'!$L$9:$EA$9,'Annual-CF'!R$9) -> 0 | S53: =SUMIFS('Monthly-CF'!$L54:$EA54,'Monthly-CF'!$L$9:$EA$9,'Annual-CF'!S$9) -> 0 | ... U53: =SUMIFS('Monthly-CF'!$L54:$EA54,'Monthly-CF'!$L$9:$EA$9,'Annual-CF'!U$9) -> 0 | W53: x
D54: =CONCATENATE("Op Exp - ",Assumptions!D$54) -> Op Exp - Commercial | I54: =SUM(K54:U54) -> 0 | L54: =SUMIFS('Monthly-CF'!$L55:$EA55,'Monthly-CF'!$L$9:$EA$9,'Annual-CF'!L$9) -> 0 | M54: =SUMIFS('Monthly-CF'!$L55:$EA55,'Monthly-CF'!$L$9:$EA$9,'Annual-CF'!M$9) -> 0 | N54: =SUMIFS('Monthly-CF'!$L55:$EA55,'Monthly-CF'!$L$9:$EA$9,'Annual-CF'!N$9) -> 0 | O54: =SUMIFS('Monthly-CF'!$L55:$EA55,'Monthly-CF'!$L$9:$EA$9,'Annual-CF'!O$9) -> 0 | P54: =SUMIFS('Monthly-CF'!$L55:$EA55,'Monthly-CF'!$L$9:$EA$9,'Annual-CF'!P$9) -> 0 | Q54: =SUMIFS('Monthly-CF'!$L55:$EA55,'Monthly-CF'!$L$9:$EA$9,'Annual-CF'!Q$9) -> 0 | R54: =SUMIFS('Monthly-CF'!$L55:$EA55,'Monthly-CF'!$L$9:$EA$9,'Annual-CF'!R$9) -> 0 | S54: =SUMIFS('Monthly-CF'!$L55:$EA55,'Monthly-CF'!$L$9:$EA$9,'Annual-CF'!S$9) -> 0 | ... U54: =SUMIFS('Monthly-CF'!$L55:$EA55,'Monthly-CF'!$L$9:$EA$9,'Annual-CF'!U$9) -> 0 | W54: x
D55: Operating Income | I55: =SUM(K55:U55) -> 0 | L55: =SUM(L52:L54) -> 0 | M55: =SUM(M52:M54) -> 0 | N55: =SUM(N52:N54) -> 0 | O55: =SUM(O52:O54) -> 0 | P55: =SUM(P52:P54) -> 0 | Q55: =SUM(Q52:Q54) -> 0 | R55: =SUM(R52:R54) -> 0 | S55: =SUM(S52:S54) -> 0 | ... U55: =SUM(U52:U54) -> 0 | W55: x
D56: Capital Reserve | I56: =SUM(K56:U56) -> 0 | L56: =SUMIFS('Monthly-CF'!$L57:$EA57,'Monthly-CF'!$L$9:$EA$9,'Annual-CF'!L$9) -> 0 | M56: =SUMIFS('Monthly-CF'!$L57:$EA57,'Monthly-CF'!$L$9:$EA$9,'Annual-CF'!M$9) -> 0 | N56: =SUMIFS('Monthly-CF'!$L57:$EA57,'Monthly-CF'!$L$9:$EA$9,'Annual-CF'!N$9) -> 0 | O56: =SUMIFS('Monthly-CF'!$L57:$EA57,'Monthly-CF'!$L$9:$EA$9,'Annual-CF'!O$9) -> 0 | P56: =SUMIFS('Monthly-CF'!$L57:$EA57,'Monthly-CF'!$L$9:$EA$9,'Annual-CF'!P$9) -> 0 | Q56: =SUMIFS('Monthly-CF'!$L57:$EA57,'Monthly-CF'!$L$9:$EA$9,'Annual-CF'!Q$9) -> 0 | R56: =SUMIFS('Monthly-CF'!$L57:$EA57,'Monthly-CF'!$L$9:$EA$9,'Annual-CF'!R$9) -> 0 | S56: =SUMIFS('Monthly-CF'!$L57:$EA57,'Monthly-CF'!$L$9:$EA$9,'Annual-CF'!S$9) -> 0 | ... U56: =SUMIFS('Monthly-CF'!$L57:$EA57,'Monthly-CF'!$L$9:$EA$9,'Annual-CF'!U$9) -> 0 | W56: x
D57: Operating Cash Flow - Commercial | I57: =SUM(K57:U57) -> 0 | L57: =SUM(L55:L56) -> 0 | M57: =SUM(M55:M56) -> 0 | N57: =SUM(N55:N56) -> 0 | O57: =SUM(O55:O56) -> 0 | P57: =SUM(P55:P56) -> 0 | Q57: =SUM(Q55:Q56) -> 0 | R57: =SUM(R55:R56) -> 0 | S57: =SUM(S55:S56) -> 0 | ... U57: =SUM(U55:U56) -> 0 | W57: x
W58: x
D59: Residential | W59: x
D60: Valuation | L60: =IF(L44>0,L44/Assumptions!$M$55,0) -> 0 | M60: =IF(M44>0,M44/Assumptions!$M$55,0) -> 13831629 | N60: =IF(N44>0,N44/Assumptions!$M$55,0) -> 63586394 | O60: =IF(O44>0,O44/Assumptions!$M$55,0) -> 82437807 | P60: =IF(P44>0,P44/Assumptions!$M$55,0) -> 83082249 | Q60: =IF(Q44>0,Q44/Assumptions!$M$55,0) -> 83473147 | R60: =IF(R44>0,R44/Assumptions!$M$55,0) -> 84151325 | S60: =IF(S44>0,S44/Assumptions!$M$55,0) -> 86334283 | ... U60: =IF(U44>0,U44/Assumptions!$M$55,0) -> 86504554 | W60: x
D61: Sale (incl sales cost) | I61: =SUM(K61:U61) -> 85423247 | L61: =SUMIFS('Monthly-CF'!$L62:$EA62,'Monthly-CF'!$L$9:$EA$9,'Annual-CF'!L$9) -> 0 | M61: =SUMIFS('Monthly-CF'!$L62:$EA62,'Monthly-CF'!$L$9:$EA$9,'Annual-CF'!M$9) -> 0 | N61: =SUMIFS('Monthly-CF'!$L62:$EA62,'Monthly-CF'!$L$9:$EA$9,'Annual-CF'!N$9) -> 0 | O61: =SUMIFS('Monthly-CF'!$L62:$EA62,'Monthly-CF'!$L$9:$EA$9,'Annual-CF'!O$9) -> 0 | P61: =SUMIFS('Monthly-CF'!$L62:$EA62,'Monthly-CF'!$L$9:$EA$9,'Annual-CF'!P$9) -> 0 | Q61: =SUMIFS('Monthly-CF'!$L62:$EA62,'Monthly-CF'!$L$9:$EA$9,'Annual-CF'!Q$9) -> 0 | R61: =SUMIFS('Monthly-CF'!$L62:$EA62,'Monthly-CF'!$L$9:$EA$9,'Annual-CF'!R$9) -> 0 | S61: =SUMIFS('Monthly-CF'!$L62:$EA62,'Monthly-CF'!$L$9:$EA$9,'Annual-CF'!S$9) -> 0 | ... U61: =SUMIFS('Monthly-CF'!$L62:$EA62,'Monthly-CF'!$L$9:$EA$9,'Annual-CF'!U$9) -> 85423247 | W61: x
W62: x
D63: Commercial | W63: x
D64: Valuation | L64: =_xlfn.MAXIFS('Monthly-CF'!$L65:$EA65,'Monthly-CF'!$L$9:$EA$9,'Annual-CF'!L$9) -> 0 | M64: =_xlfn.MAXIFS('Monthly-CF'!$L65:$EA65,'Monthly-CF'!$L$9:$EA$9,'Annual-CF'!M$9) -> 0 | N64: =_xlfn.MAXIFS('Monthly-CF'!$L65:$EA65,'Monthly-CF'!$L$9:$EA$9,'Annual-CF'!N$9) -> 0 | O64: =_xlfn.MAXIFS('Monthly-CF'!$L65:$EA65,'Monthly-CF'!$L$9:$EA$9,'Annual-CF'!O$9) -> 0 | P64: =_xlfn.MAXIFS('Monthly-CF'!$L65:$EA65,'Monthly-CF'!$L$9:$EA$9,'Annual-CF'!P$9) -> 0 | Q64: =_xlfn.MAXIFS('Monthly-CF'!$L65:$EA65,'Monthly-CF'!$L$9:$EA$9,'Annual-CF'!Q$9) -> 0 | R64: =_xlfn.MAXIFS('Monthly-CF'!$L65:$EA65,'Monthly-CF'!$L$9:$EA$9,'Annual-CF'!R$9) -> 0 | S64: =_xlfn.MAXIFS('Monthly-CF'!$L65:$EA65,'Monthly-CF'!$L$9:$EA$9,'Annual-CF'!S$9) -> 0 | ... U64: =_xlfn.MAXIFS('Monthly-CF'!$L65:$EA65,'Monthly-CF'!$L$9:$EA$9,'Annual-CF'!U$9) -> 0 | W64: x
D65: Sale (incl sales cost) | I65: =SUM(K65:U65) -> 0 | L65: =SUMIFS('Monthly-CF'!$L66:$EA66,'Monthly-CF'!$L$9:$EA$9,'Annual-CF'!L$9) -> 0 | M65: =SUMIFS('Monthly-CF'!$L66:$EA66,'Monthly-CF'!$L$9:$EA$9,'Annual-CF'!M$9) -> 0 | N65: =SUMIFS('Monthly-CF'!$L66:$EA66,'Monthly-CF'!$L$9:$EA$9,'Annual-CF'!N$9) -> 0 | O65: =SUMIFS('Monthly-CF'!$L66:$EA66,'Monthly-CF'!$L$9:$EA$9,'Annual-CF'!O$9) -> 0 | P65: =SUMIFS('Monthly-CF'!$L66:$EA66,'Monthly-CF'!$L$9:$EA$9,'Annual-CF'!P$9) -> 0 | Q65: =SUMIFS('Monthly-CF'!$L66:$EA66,'Monthly-CF'!$L$9:$EA$9,'Annual-CF'!Q$9) -> 0 | R65: =SUMIFS('Monthly-CF'!$L66:$EA66,'Monthly-CF'!$L$9:$EA$9,'Annual-CF'!R$9) -> 0 | S65: =SUMIFS('Monthly-CF'!$L66:$EA66,'Monthly-CF'!$L$9:$EA$9,'Annual-CF'!S$9) -> 0 | ... U65: =SUMIFS('Monthly-CF'!$L66:$EA66,'Monthly-CF'!$L$9:$EA$9,'Annual-CF'!U$9) -> 0 | W65: x
W66: x
D67: Project Costs Phase 1: | W67: x
D68: Land | I68: =SUM(K68:U68) -> -5200000 | L68: =SUMIFS('Monthly-CF'!$L69:$EA69,'Monthly-CF'!$L$9:$EA$9,'Annual-CF'!L$9) -> -5200000 | M68: =SUMIFS('Monthly-CF'!$L69:$EA69,'Monthly-CF'!$L$9:$EA$9,'Annual-CF'!M$9) -> 0 | N68: =SUMIFS('Monthly-CF'!$L69:$EA69,'Monthly-CF'!$L$9:$EA$9,'Annual-CF'!N$9) -> 0 | O68: =SUMIFS('Monthly-CF'!$L69:$EA69,'Monthly-CF'!$L$9:$EA$9,'Annual-CF'!O$9) -> 0 | P68: =SUMIFS('Monthly-CF'!$L69:$EA69,'Monthly-CF'!$L$9:$EA$9,'Annual-CF'!P$9) -> 0 | Q68: =SUMIFS('Monthly-CF'!$L69:$EA69,'Monthly-CF'!$L$9:$EA$9,'Annual-CF'!Q$9) -> 0 | R68: =SUMIFS('Monthly-CF'!$L69:$EA69,'Monthly-CF'!$L$9:$EA$9,'Annual-CF'!R$9) -> 0 | S68: =SUMIFS('Monthly-CF'!$L69:$EA69,'Monthly-CF'!$L$9:$EA$9,'Annual-CF'!S$9) -> 0 | ... U68: =SUMIFS('Monthly-CF'!$L69:$EA69,'Monthly-CF'!$L$9:$EA$9,'Annual-CF'!U$9) -> 0 | W68: x
D69: Hard Costs | I69: =SUM(K69:U69) -> -38440298 | L69: =SUMIFS('Monthly-CF'!$L70:$EA70,'Monthly-CF'!$L$9:$EA$9,'Annual-CF'!L$9) -> -22611940 | M69: =SUMIFS('Monthly-CF'!$L70:$EA70,'Monthly-CF'!$L$9:$EA$9,'Annual-CF'!M$9) -> -15828358 | N69: =SUMIFS('Monthly-CF'!$L70:$EA70,'Monthly-CF'!$L$9:$EA$9,'Annual-CF'!N$9) -> 0 | O69: =SUMIFS('Monthly-CF'!$L70:$EA70,'Monthly-CF'!$L$9:$EA$9,'Annual-CF'!O$9) -> 0 | P69: =SUMIFS('Monthly-CF'!$L70:$EA70,'Monthly-CF'!$L$9:$EA$9,'Annual-CF'!P$9) -> 0 | Q69: =SUMIFS('Monthly-CF'!$L70:$EA70,'Monthly-CF'!$L$9:$EA$9,'Annual-CF'!Q$9) -> 0 | R69: =SUMIFS('Monthly-CF'!$L70:$EA70,'Monthly-CF'!$L$9:$EA$9,'Annual-CF'!R$9) -> 0 | S69: =SUMIFS('Monthly-CF'!$L70:$EA70,'Monthly-CF'!$L$9:$EA$9,'Annual-CF'!S$9) -> 0 | ... U69: =SUMIFS('Monthly-CF'!$L70:$EA70,'Monthly-CF'!$L$9:$EA$9,'Annual-CF'!U$9) -> 0 | W69: x
D70: Soft Costs (Excl. D/S) | I70: =SUM(K70:U70) -> -6649601.1 | L70: =SUMIFS('Monthly-CF'!$L71:$EA71,'Monthly-CF'!$L$9:$EA$9,'Annual-CF'!L$9) -> -4302683.1 | M70: =SUMIFS('Monthly-CF'!$L71:$EA71,'Monthly-CF'!$L$9:$EA$9,'Annual-CF'!M$9) -> -2346918 | N70: =SUMIFS('Monthly-CF'!$L71:$EA71,'Monthly-CF'!$L$9:$EA$9,'Annual-CF'!N$9) -> 0 | O70: =SUMIFS('Monthly-CF'!$L71:$EA71,'Monthly-CF'!$L$9:$EA$9,'Annual-CF'!O$9) -> 0 | P70: =SUMIFS('Monthly-CF'!$L71:$EA71,'Monthly-CF'!$L$9:$EA$9,'Annual-CF'!P$9) -> 0 | Q70: =SUMIFS('Monthly-CF'!$L71:$EA71,'Monthly-CF'!$L$9:$EA$9,'Annual-CF'!Q$9) -> 0 | R70: =SUMIFS('Monthly-CF'!$L71:$EA71,'Monthly-CF'!$L$9:$EA$9,'Annual-CF'!R$9) -> 0 | S70: =SUMIFS('Monthly-CF'!$L71:$EA71,'Monthly-CF'!$L$9:$EA$9,'Annual-CF'!S$9) -> 0 | ... U70: =SUMIFS('Monthly-CF'!$L71:$EA71,'Monthly-CF'!$L$9:$EA$9,'Annual-CF'!U$9) -> 0 | W70: x
D71: Dev Fees | I71: =SUM(K71:U71) -> -1672635.6 | L71: =SUMIFS('Monthly-CF'!$L72:$EA72,'Monthly-CF'!$L$9:$EA$9,'Annual-CF'!L$9) -> -983903.32 | M71: =SUMIFS('Monthly-CF'!$L72:$EA72,'Monthly-CF'!$L$9:$EA$9,'Annual-CF'!M$9) -> -688732.32 | N71: =SUMIFS('Monthly-CF'!$L72:$EA72,'Monthly-CF'!$L$9:$EA$9,'Annual-CF'!N$9) -> 0 | O71: =SUMIFS('Monthly-CF'!$L72:$EA72,'Monthly-CF'!$L$9:$EA$9,'Annual-CF'!O$9) -> 0 | P71: =SUMIFS('Monthly-CF'!$L72:$EA72,'Monthly-CF'!$L$9:$EA$9,'Annual-CF'!P$9) -> 0 | Q71: =SUMIFS('Monthly-CF'!$L72:$EA72,'Monthly-CF'!$L$9:$EA$9,'Annual-CF'!Q$9) -> 0 | R71: =SUMIFS('Monthly-CF'!$L72:$EA72,'Monthly-CF'!$L$9:$EA$9,'Annual-CF'!R$9) -> 0 | S71: =SUMIFS('Monthly-CF'!$L72:$EA72,'Monthly-CF'!$L$9:$EA$9,'Annual-CF'!S$9) -> 0 | ... U71: =SUMIFS('Monthly-CF'!$L72:$EA72,'Monthly-CF'!$L$9:$EA$9,'Annual-CF'!U$9) -> 0 | W71: x
D72: Loan Fees | I72: =SUM(K72:U72) -> -247429.15 | L72: =SUMIFS('Monthly-CF'!$L73:$EA73,'Monthly-CF'!$L$9:$EA$9,'Annual-CF'!L$9) -> -247429.15 | M72: =SUMIFS('Monthly-CF'!$L73:$EA73,'Monthly-CF'!$L$9:$EA$9,'Annual-CF'!M$9) -> 0 | N72: =SUMIFS('Monthly-CF'!$L73:$EA73,'Monthly-CF'!$L$9:$EA$9,'Annual-CF'!N$9) -> 0 | O72: =SUMIFS('Monthly-CF'!$L73:$EA73,'Monthly-CF'!$L$9:$EA$9,'Annual-CF'!O$9) -> 0 | P72: =SUMIFS('Monthly-CF'!$L73:$EA73,'Monthly-CF'!$L$9:$EA$9,'Annual-CF'!P$9) -> 0 | Q72: =SUMIFS('Monthly-CF'!$L73:$EA73,'Monthly-CF'!$L$9:$EA$9,'Annual-CF'!Q$9) -> 0 | R72: =SUMIFS('Monthly-CF'!$L73:$EA73,'Monthly-CF'!$L$9:$EA$9,'Annual-CF'!R$9) -> 0 | S72: =SUMIFS('Monthly-CF'!$L73:$EA73,'Monthly-CF'!$L$9:$EA$9,'Annual-CF'!S$9) -> 0 | ... U72: =SUMIFS('Monthly-CF'!$L73:$EA73,'Monthly-CF'!$L$9:$EA$9,'Annual-CF'!U$9) -> 0 | W72: x
D73: Interest | I73: =SUM(K73:U73) -> -2474291.5 | L73: =SUMIFS('Monthly-CF'!$L74:$EA74,'Monthly-CF'!$L$9:$EA$9,'Annual-CF'!L$9) -> -651129.34 | M73: =SUMIFS('Monthly-CF'!$L74:$EA74,'Monthly-CF'!$L$9:$EA$9,'Annual-CF'!M$9) -> -1562710.4 | N73: =SUMIFS('Monthly-CF'!$L74:$EA74,'Monthly-CF'!$L$9:$EA$9,'Annual-CF'!N$9) -> -260451.74 | O73: =SUMIFS('Monthly-CF'!$L74:$EA74,'Monthly-CF'!$L$9:$EA$9,'Annual-CF'!O$9) -> 0 | P73: =SUMIFS('Monthly-CF'!$L74:$EA74,'Monthly-CF'!$L$9:$EA$9,'Annual-CF'!P$9) -> 0 | Q73: =SUMIFS('Monthly-CF'!$L74:$EA74,'Monthly-CF'!$L$9:$EA$9,'Annual-CF'!Q$9) -> 0 | R73: =SUMIFS('Monthly-CF'!$L74:$EA74,'Monthly-CF'!$L$9:$EA$9,'Annual-CF'!R$9) -> 0 | S73: =SUMIFS('Monthly-CF'!$L74:$EA74,'Monthly-CF'!$L$9:$EA$9,'Annual-CF'!S$9) -> 0 | ... U73: =SUMIFS('Monthly-CF'!$L74:$EA74,'Monthly-CF'!$L$9:$EA$9,'Annual-CF'!U$9) -> 0 | W73: x
D74: Lease Up Costs | I74: =SUM(K74:U74) -> -300000 | L74: =SUMIFS('Monthly-CF'!$L75:$EA75,'Monthly-CF'!$L$9:$EA$9,'Annual-CF'!L$9) -> 0 | M74: =SUMIFS('Monthly-CF'!$L75:$EA75,'Monthly-CF'!$L$9:$EA$9,'Annual-CF'!M$9) -> -300000 | N74: =SUMIFS('Monthly-CF'!$L75:$EA75,'Monthly-CF'!$L$9:$EA$9,'Annual-CF'!N$9) -> 0 | O74: =SUMIFS('Monthly-CF'!$L75:$EA75,'Monthly-CF'!$L$9:$EA$9,'Annual-CF'!O$9) -> 0 | P74: =SUMIFS('Monthly-CF'!$L75:$EA75,'Monthly-CF'!$L$9:$EA$9,'Annual-CF'!P$9) -> 0 | Q74: =SUMIFS('Monthly-CF'!$L75:$EA75,'Monthly-CF'!$L$9:$EA$9,'Annual-CF'!Q$9) -> 0 | R74: =SUMIFS('Monthly-CF'!$L75:$EA75,'Monthly-CF'!$L$9:$EA$9,'Annual-CF'!R$9) -> 0 | S74: =SUMIFS('Monthly-CF'!$L75:$EA75,'Monthly-CF'!$L$9:$EA$9,'Annual-CF'!S$9) -> 0 | ... U74: =SUMIFS('Monthly-CF'!$L75:$EA75,'Monthly-CF'!$L$9:$EA$9,'Annual-CF'!U$9) -> 0 | W74: x
D75: Phase 1 Development Costs | I75: =SUM(K75:U75) -> -54984255 | L75: =SUM(L68:L74) -> -33997085 | M75: =SUM(M68:M74) -> -20726719 | N75: =SUM(N68:N74) -> -260451.74 | O75: =SUM(O68:O74) -> 0 | P75: =SUM(P68:P74) -> 0 | Q75: =SUM(Q68:Q74) -> 0 | R75: =SUM(R68:R74) -> 0 | S75: =SUM(S68:S74) -> 0 | ... U75: =SUM(U68:U74) -> 0 | W75: x
W76: x
D77: Project Costs Phase 2: | W77: x
D78: Land | I78: =SUM(K78:U78) -> 0 | L78: =SUMIFS('Monthly-CF'!$L79:$EA79,'Monthly-CF'!$L$9:$EA$9,'Annual-CF'!L$9) -> 0 | M78: =SUMIFS('Monthly-CF'!$L79:$EA79,'Monthly-CF'!$L$9:$EA$9,'Annual-CF'!M$9) -> 0 | N78: =SUMIFS('Monthly-CF'!$L79:$EA79,'Monthly-CF'!$L$9:$EA$9,'Annual-CF'!N$9) -> 0 | O78: =SUMIFS('Monthly-CF'!$L79:$EA79,'Monthly-CF'!$L$9:$EA$9,'Annual-CF'!O$9) -> 0 | P78: =SUMIFS('Monthly-CF'!$L79:$EA79,'Monthly-CF'!$L$9:$EA$9,'Annual-CF'!P$9) -> 0 | Q78: =SUMIFS('Monthly-CF'!$L79:$EA79,'Monthly-CF'!$L$9:$EA$9,'Annual-CF'!Q$9) -> 0 | R78: =SUMIFS('Monthly-CF'!$L79:$EA79,'Monthly-CF'!$L$9:$EA$9,'Annual-CF'!R$9) -> 0 | S78: =SUMIFS('Monthly-CF'!$L79:$EA79,'Monthly-CF'!$L$9:$EA$9,'Annual-CF'!S$9) -> 0 | ... U78: =SUMIFS('Monthly-CF'!$L79:$EA79,'Monthly-CF'!$L$9:$EA$9,'Annual-CF'!U$9) -> 0 | W78: x
D79: Hard Costs | I79: =SUM(K79:U79) -> 0 | L79: =SUMIFS('Monthly-CF'!$L80:$EA80,'Monthly-CF'!$L$9:$EA$9,'Annual-CF'!L$9) -> 0 | M79: =SUMIFS('Monthly-CF'!$L80:$EA80,'Monthly-CF'!$L$9:$EA$9,'Annual-CF'!M$9) -> 0 | N79: =SUMIFS('Monthly-CF'!$L80:$EA80,'Monthly-CF'!$L$9:$EA$9,'Annual-CF'!N$9) -> 0 | O79: =SUMIFS('Monthly-CF'!$L80:$EA80,'Monthly-CF'!$L$9:$EA$9,'Annual-CF'!O$9) -> 0 | P79: =SUMIFS('Monthly-CF'!$L80:$EA80,'Monthly-CF'!$L$9:$EA$9,'Annual-CF'!P$9) -> 0 | Q79: =SUMIFS('Monthly-CF'!$L80:$EA80,'Monthly-CF'!$L$9:$EA$9,'Annual-CF'!Q$9) -> 0 | R79: =SUMIFS('Monthly-CF'!$L80:$EA80,'Monthly-CF'!$L$9:$EA$9,'Annual-CF'!R$9) -> 0 | S79: =SUMIFS('Monthly-CF'!$L80:$EA80,'Monthly-CF'!$L$9:$EA$9,'Annual-CF'!S$9) -> 0 | ... U79: =SUMIFS('Monthly-CF'!$L80:$EA80,'Monthly-CF'!$L$9:$EA$9,'Annual-CF'!U$9) -> 0 | W79: x
D80: Soft Costs (Excl. D/S) | I80: =SUM(K80:U80) -> 0 | L80: =SUMIFS('Monthly-CF'!$L81:$EA81,'Monthly-CF'!$L$9:$EA$9,'Annual-CF'!L$9) -> 0 | M80: =SUMIFS('Monthly-CF'!$L81:$EA81,'Monthly-CF'!$L$9:$EA$9,'Annual-CF'!M$9) -> 0 | N80: =SUMIFS('Monthly-CF'!$L81:$EA81,'Monthly-CF'!$L$9:$EA$9,'Annual-CF'!N$9) -> 0 | O80: =SUMIFS('Monthly-CF'!$L81:$EA81,'Monthly-CF'!$L$9:$EA$9,'Annual-CF'!O$9) -> 0 | P80: =SUMIFS('Monthly-CF'!$L81:$EA81,'Monthly-CF'!$L$9:$EA$9,'Annual-CF'!P$9) -> 0 | Q80: =SUMIFS('Monthly-CF'!$L81:$EA81,'Monthly-CF'!$L$9:$EA$9,'Annual-CF'!Q$9) -> 0 | R80: =SUMIFS('Monthly-CF'!$L81:$EA81,'Monthly-CF'!$L$9:$EA$9,'Annual-CF'!R$9) -> 0 | S80: =SUMIFS('Monthly-CF'!$L81:$EA81,'Monthly-CF'!$L$9:$EA$9,'Annual-CF'!S$9) -> 0 | ... U80: =SUMIFS('Monthly-CF'!$L81:$EA81,'Monthly-CF'!$L$9:$EA$9,'Annual-CF'!U$9) -> 0 | W80: x
D81: Dev Fees | I81: =SUM(K81:U81) -> 0 | L81: =SUMIFS('Monthly-CF'!$L82:$EA82,'Monthly-CF'!$L$9:$EA$9,'Annual-CF'!L$9) -> 0 | M81: =SUMIFS('Monthly-CF'!$L82:$EA82,'Monthly-CF'!$L$9:$EA$9,'Annual-CF'!M$9) -> 0 | N81: =SUMIFS('Monthly-CF'!$L82:$EA82,'Monthly-CF'!$L$9:$EA$9,'Annual-CF'!N$9) -> 0 | O81: =SUMIFS('Monthly-CF'!$L82:$EA82,'Monthly-CF'!$L$9:$EA$9,'Annual-CF'!O$9) -> 0 | P81: =SUMIFS('Monthly-CF'!$L82:$EA82,'Monthly-CF'!$L$9:$EA$9,'Annual-CF'!P$9) -> 0 | Q81: =SUMIFS('Monthly-CF'!$L82:$EA82,'Monthly-CF'!$L$9:$EA$9,'Annual-CF'!Q$9) -> 0 | R81: =SUMIFS('Monthly-CF'!$L82:$EA82,'Monthly-CF'!$L$9:$EA$9,'Annual-CF'!R$9) -> 0 | S81: =SUMIFS('Monthly-CF'!$L82:$EA82,'Monthly-CF'!$L$9:$EA$9,'Annual-CF'!S$9) -> 0 | ... U81: =SUMIFS('Monthly-CF'!$L82:$EA82,'Monthly-CF'!$L$9:$EA$9,'Annual-CF'!U$9) -> 0 | W81: x
D82: Loan Fees | I82: =SUM(K82:U82) -> 0 | L82: =SUMIFS('Monthly-CF'!$L83:$EA83,'Monthly-CF'!$L$9:$EA$9,'Annual-CF'!L$9) -> 0 | M82: =SUMIFS('Monthly-CF'!$L83:$EA83,'Monthly-CF'!$L$9:$EA$9,'Annual-CF'!M$9) -> 0 | N82: =SUMIFS('Monthly-CF'!$L83:$EA83,'Monthly-CF'!$L$9:$EA$9,'Annual-CF'!N$9) -> 0 | O82: =SUMIFS('Monthly-CF'!$L83:$EA83,'Monthly-CF'!$L$9:$EA$9,'Annual-CF'!O$9) -> 0 | P82: =SUMIFS('Monthly-CF'!$L83:$EA83,'Monthly-CF'!$L$9:$EA$9,'Annual-CF'!P$9) -> 0 | Q82: =SUMIFS('Monthly-CF'!$L83:$EA83,'Monthly-CF'!$L$9:$EA$9,'Annual-CF'!Q$9) -> 0 | R82: =SUMIFS('Monthly-CF'!$L83:$EA83,'Monthly-CF'!$L$9:$EA$9,'Annual-CF'!R$9) -> 0 | S82: =SUMIFS('Monthly-CF'!$L83:$EA83,'Monthly-CF'!$L$9:$EA$9,'Annual-CF'!S$9) -> 0 | ... U82: =SUMIFS('Monthly-CF'!$L83:$EA83,'Monthly-CF'!$L$9:$EA$9,'Annual-CF'!U$9) -> 0 | W82: x
D83: Interest | I83: =SUM(K83:U83) -> 0 | L83: =SUMIFS('Monthly-CF'!$L84:$EA84,'Monthly-CF'!$L$9:$EA$9,'Annual-CF'!L$9) -> 0 | M83: =SUMIFS('Monthly-CF'!$L84:$EA84,'Monthly-CF'!$L$9:$EA$9,'Annual-CF'!M$9) -> 0 | N83: =SUMIFS('Monthly-CF'!$L84:$EA84,'Monthly-CF'!$L$9:$EA$9,'Annual-CF'!N$9) -> 0 | O83: =SUMIFS('Monthly-CF'!$L84:$EA84,'Monthly-CF'!$L$9:$EA$9,'Annual-CF'!O$9) -> 0 | P83: =SUMIFS('Monthly-CF'!$L84:$EA84,'Monthly-CF'!$L$9:$EA$9,'Annual-CF'!P$9) -> 0 | Q83: =SUMIFS('Monthly-CF'!$L84:$EA84,'Monthly-CF'!$L$9:$EA$9,'Annual-CF'!Q$9) -> 0 | R83: =SUMIFS('Monthly-CF'!$L84:$EA84,'Monthly-CF'!$L$9:$EA$9,'Annual-CF'!R$9) -> 0 | S83: =SUMIFS('Monthly-CF'!$L84:$EA84,'Monthly-CF'!$L$9:$EA$9,'Annual-CF'!S$9) -> 0 | ... U83: =SUMIFS('Monthly-CF'!$L84:$EA84,'Monthly-CF'!$L$9:$EA$9,'Annual-CF'!U$9) -> 0 | W83: x
D84: Lease Up Costs | I84: =SUM(K84:U84) -> 0 | L84: =SUMIFS('Monthly-CF'!$L85:$EA85,'Monthly-CF'!$L$9:$EA$9,'Annual-CF'!L$9) -> 0 | M84: =SUMIFS('Monthly-CF'!$L85:$EA85,'Monthly-CF'!$L$9:$EA$9,'Annual-CF'!M$9) -> 0 | N84: =SUMIFS('Monthly-CF'!$L85:$EA85,'Monthly-CF'!$L$9:$EA$9,'Annual-CF'!N$9) -> 0 | O84: =SUMIFS('Monthly-CF'!$L85:$EA85,'Monthly-CF'!$L$9:$EA$9,'Annual-CF'!O$9) -> 0 | P84: =SUMIFS('Monthly-CF'!$L85:$EA85,'Monthly-CF'!$L$9:$EA$9,'Annual-CF'!P$9) -> 0 | Q84: =SUMIFS('Monthly-CF'!$L85:$EA85,'Monthly-CF'!$L$9:$EA$9,'Annual-CF'!Q$9) -> 0 | R84: =SUMIFS('Monthly-CF'!$L85:$EA85,'Monthly-CF'!$L$9:$EA$9,'Annual-CF'!R$9) -> 0 | S84: =SUMIFS('Monthly-CF'!$L85:$EA85,'Monthly-CF'!$L$9:$EA$9,'Annual-CF'!S$9) -> 0 | ... U84: =SUMIFS('Monthly-CF'!$L85:$EA85,'Monthly-CF'!$L$9:$EA$9,'Annual-CF'!U$9) -> 0 | W84: x
D85: Phase 2 Development Costs | I85: =SUM(K85:U85) -> 0 | L85: =SUM(L78:L84) -> 0 | M85: =SUM(M78:M84) -> 0 | N85: =SUM(N78:N84) -> 0 | O85: =SUM(O78:O84) -> 0 | P85: =SUM(P78:P84) -> 0 | Q85: =SUM(Q78:Q84) -> 0 | R85: =SUM(R78:R84) -> 0 | S85: =SUM(S78:S84) -> 0 | ... U85: =SUM(U78:U84) -> 0 | W85: x
W86: x
D87: Project Costs Combined: | W87: x
D88: Land | I88: =SUM(K88:U88) -> -5200000 | L88: =L68+L78 -> -5200000 | M88: =M68+M78 -> 0 | N88: =N68+N78 -> 0 | O88: =O68+O78 -> 0 | P88: =P68+P78 -> 0 | Q88: =Q68+Q78 -> 0 | R88: =R68+R78 -> 0 | S88: =S68+S78 -> 0 | ... U88: =U68+U78 -> 0 | W88: x
D89: Hard Costs | I89: =SUM(K89:U89) -> -38440298 | L89: =L69+L79 -> -22611940 | M89: =M69+M79 -> -15828358 | N89: =N69+N79 -> 0 | O89: =O69+O79 -> 0 | P89: =P69+P79 -> 0 | Q89: =Q69+Q79 -> 0 | R89: =R69+R79 -> 0 | S89: =S69+S79 -> 0 | ... U89: =U69+U79 -> 0 | W89: x
D90: Soft Costs | I90: =SUM(K90:U90) -> -6649601.1 | L90: =L70+L80 -> -4302683.1 | M90: =M70+M80 -> -2346918 | N90: =N70+N80 -> 0 | O90: =O70+O80 -> 0 | P90: =P70+P80 -> 0 | Q90: =Q70+Q80 -> 0 | R90: =R70+R80 -> 0 | S90: =S70+S80 -> 0 | ... U90: =U70+U80 -> 0 | W90: x
D91: Dev Fees | I91: =SUM(K91:U91) -> -1672635.6 | L91: =L71+L81 -> -983903.32 | M91: =M71+M81 -> -688732.32 | N91: =N71+N81 -> 0 | O91: =O71+O81 -> 0 | P91: =P71+P81 -> 0 | Q91: =Q71+Q81 -> 0 | R91: =R71+R81 -> 0 | S91: =S71+S81 -> 0 | ... U91: =U71+U81 -> 0 | W91: x
D92: Loan Fees | I92: =SUM(K92:U92) -> -247429.15 | L92: =L72+L82 -> -247429.15 | M92: =M72+M82 -> 0 | N92: =N72+N82 -> 0 | O92: =O72+O82 -> 0 | P92: =P72+P82 -> 0 | Q92: =Q72+Q82 -> 0 | R92: =R72+R82 -> 0 | S92: =S72+S82 -> 0 | ... U92: =U72+U82 -> 0 | W92: x
D93: Interest | I93: =SUM(K93:U93) -> -2474291.5 | L93: =L73+L83 -> -651129.34 | M93: =M73+M83 -> -1562710.4 | N93: =N73+N83 -> -260451.74 | O93: =O73+O83 -> 0 | P93: =P73+P83 -> 0 | Q93: =Q73+Q83 -> 0 | R93: =R73+R83 -> 0 | S93: =S73+S83 -> 0 | ... U93: =U73+U83 -> 0 | W93: x
D94: Lease Up Costs | I94: =SUM(K94:U94) -> -300000 | L94: =L74+L84 -> 0 | M94: =M74+M84 -> -300000 | N94: =N74+N84 -> 0 | O94: =O74+O84 -> 0 | P94: =P74+P84 -> 0 | Q94: =Q74+Q84 -> 0 | R94: =R74+R84 -> 0 | S94: =S74+S84 -> 0 | ... U94: =U74+U84 -> 0 | W94: x
D95: Total Project Costs | I95: =SUM(K95:U95) -> -54984255 | L95: =SUM(L88:L94) -> -33997085 | M95: =SUM(M88:M94) -> -20726719 | N95: =SUM(N88:N94) -> -260451.74 | O95: =SUM(O88:O94) -> 0 | P95: =SUM(P88:P94) -> 0 | Q95: =SUM(Q88:Q94) -> 0 | R95: =SUM(R88:R94) -> 0 | S95: =SUM(S88:S94) -> 0 | ... U95: =SUM(U88:U94) -> 0 | W95: x
D96: Operating Cash Flow (Pre-Lease Up Costs) | I96: =SUM(K96:U96) -> 0 | W96: x
D97: Unlevered Cash Flows | H97: =I97-'Monthly-CF'!I98 -> 0 | I97: =SUM(K97:U97) -> 65495876 | L97: =L37+L95+L61+L57+L65+L44 -> -33997085 | M97: =M37+M95+M61+M57+M65+M44 -> -20000558 | N97: =N37+N95+N61+N57+N65+N44 -> 3077833.9 | O97: =O37+O95+O61+O57+O65+O44 -> 4327984.8 | P97: =P37+P95+P61+P57+P65+P44 -> 4361818.1 | Q97: =Q37+Q95+Q61+Q57+Q65+Q44 -> 4382340.2 | R97: =R37+R95+R61+R57+R65+R44 -> 4417944.5 | S97: =S37+S95+S61+S57+S65+S44 -> 4532549.9 | ... U97: =U37+U95+U61+U57+U65+U44 -> 89964736 | W97: x
W98: x
W99: x
W100: x
D101: Capital Sources: | W101: x
...

Sheet Monthly-CF
EC1: x
EC2: x
EC3: x
EC4: x
C5: Monthly Cash Flow | EC5: x
EC6: x
EC7: x
L8: 45107 | M8: =EOMONTH(L8,1) -> 45138 | N8: =EOMONTH(M8,1) -> 45169 | O8: =EOMONTH(N8,1) -> 45199 | P8: =EOMONTH(O8,1) -> 45230 | Q8: =EOMONTH(P8,1) -> 45260 | R8: =EOMONTH(Q8,1) -> 45291 | S8: =EOMONTH(R8,1) -> 45322 | T8: =EOMONTH(S8,1) -> 45351 | ... EA8: =EOMONTH(DZ8,1) -> 48730 | EC8: x
L9: =ROUNDUP(L10/12,0) -> 1 | M9: =ROUNDUP(M10/12,0) -> 1 | N9: =ROUNDUP(N10/12,0) -> 1 | O9: =ROUNDUP(O10/12,0) -> 1 | P9: =ROUNDUP(P10/12,0) -> 1 | Q9: =ROUNDUP(Q10/12,0) -> 1 | R9: =ROUNDUP(R10/12,0) -> 1 | S9: =ROUNDUP(S10/12,0) -> 1 | ... EA9: =ROUNDUP(EA10/12,0) -> 10 | EC9: x
I10: Total | K10: Initial | L10: 1 | M10: =L10+1 -> 2 | N10: =M10+1 -> 3 | O10: =N10+1 -> 4 | P10: =O10+1 -> 5 | Q10: =P10+1 -> 6 | R10: =Q10+1 -> 7 | S10: =R10+1 -> 8 | T10: =S10+1 -> 9 | ... EA10: =DZ10+1 -> 120 | EC10: x
D11: Residential Summary
D12: Occupancy | EC12: x
D13: Occ - Multi-Family Ph.1 | I13: =MAX(L13:EA13) -> 0 | L13: =IF(L$8<=Assumptions!$M$58,IF(SUM($K$70:K$70)=$I$70,IF(K13=0,Assumptions!$H$59,MIN('Monthly-CF'!K13+Assumptions!$I$59,Assumptions!$J$59)),0),0) -> 0 | M13: =IF(M$8<=Assumptions!$M$58,IF(SUM($K$70:L$70)=$I$70,IF(L13=0,Assumptions!$H$59,MIN('Monthly-CF'!L13+Assumptions!$I$59,Assumptions!$J$59)),0),0) -> 0 | N13: =IF(N$8<=Assumptions!$M$58,IF(SUM($K$70:M$70)=$I$70,IF(M13=0,Assumptions!$H$59,MIN('Monthly-CF'!M13+Assumptions!$I$59,Assumptions!$J$59)),0),0) -> 0 | O13: =IF(O$8<=Assumptions!$M$58,IF(SUM($K$70:N$70)=$I$70,IF(N13=0,Assumptions!$H$59,MIN('Monthly-CF'!N13+Assumptions!$I$59,Assumptions!$J$59)),0),0) -> 0 | P13: =IF(P$8<=Assumptions!$M$58,IF(SUM($K$70:O$70)=$I$70,IF(O13=0,Assumptions!$H$59,MIN('Monthly-CF'!O13+Assumptions!$I$59,Assumptions!$J$59)),0),0) -> 0 | Q13: =IF(Q$8<=Assumptions!$M$58,IF(SUM($K$70:P$70)=$I$70,IF(P13=0,Assumptions!$H$59,MIN('Monthly-CF'!P13+Assumptions!$I$59,Assumptions!$J$59)),0),0) -> 0 | R13: =IF(R$8<=Assumptions!$M$58,IF(SUM($K$70:Q$70)=$I$70,IF(Q13=0,Assumptions!$H$59,MIN('Monthly-CF'!Q13+Assumptions!$I$59,Assumptions!$J$59)),0),0) -> 0 | S13: =IF(S$8<=Assumptions!$M$58,IF(SUM($K$70:R$70)=$I$70,IF(R13=0,Assumptions!$H$59,MIN('Monthly-CF'!R13+Assumptions!$I$59,Assumptions!$J$59)),0),0) -> 0 | ... EA13: =IF(EA$8<=Assumptions!$M$58,IF(SUM($K$70:DZ$70)=$I$70,IF(DZ13=0,Assumptions!$H$59,MIN('Monthly-CF'!DZ13+Assumptions!$I$59,Assumptions!$J$59)),0),0) -> 0 | EC13: x
D14: Occ - Multi-Family Ph.2 | I14: =MAX(L14:EA14) -> 0 | EC14: x
D15: =CONCATENATE("Occ - ",Assumptions!$J$54) -> Occ - Ancillary Fees | I15: =MAX(L15:EA15) -> 0 | L15: =IF(L13>0,IF(K15=0,Assumptions!$H$61,MIN('Monthly-CF'!K15+Assumptions!$I$61,Assumptions!$J$61)),0) -> 0 | M15: =IF(M13>0,IF(L15=0,Assumptions!$H$61,MIN('Monthly-CF'!L15+Assumptions!$I$61,Assumptions!$J$61)),0) -> 0 | N15: =IF(N13>0,IF(M15=0,Assumptions!$H$61,MIN('Monthly-CF'!M15+Assumptions!$I$61,Assumptions!$J$61)),0) -> 0 | O15: =IF(O13>0,IF(N15=0,Assumptions!$H$61,MIN('Monthly-CF'!N15+Assumptions!$I$61,Assumptions!$J$61)),0) -> 0 | P15: =IF(P13>0,IF(O15=0,Assumptions!$H$61,MIN('Monthly-CF'!O15+Assumptions!$I$61,Assumptions!$J$61)),0) -> 0 | Q15: =IF(Q13>0,IF(P15=0,Assumptions!$H$61,MIN('Monthly-CF'!P15+Assumptions!$I$61,Assumptions!$J$61)),0) -> 0 | R15: =IF(R13>0,IF(Q15=0,Assumptions!$H$61,MIN('Monthly-CF'!Q15+Assumptions!$I$61,Assumptions!$J$61)),0) -> 0 | S15: =IF(S13>0,IF(R15=0,Assumptions!$H$61,MIN('Monthly-CF'!R15+Assumptions!$I$61,Assumptions!$J$61)),0) -> 0 | ... EA15: =IF(EA13>0,IF(DZ15=0,Assumptions!$H$61,MIN('Monthly-CF'!DZ15+Assumptions!$I$61,Assumptions!$J$61)),0) -> 0 | EC15: x
EC16: x
D17: Leased SF | E17: Total SF | G17: Escalator | L17: =INDEX('Annual-CF'!$L$17:$U$17,MATCH('Monthly-CF'!L$9,'Annual-CF'!$L$9:$U$9,0)) -> 0 | M17: =INDEX('Annual-CF'!$L$17:$U$17,MATCH('Monthly-CF'!M$9,'Annual-CF'!$L$9:$U$9,0)) -> 0 | N17: =INDEX('Annual-CF'!$L$17:$U$17,MATCH('Monthly-CF'!N$9,'Annual-CF'!$L$9:$U$9,0)) -> 0 | O17: =INDEX('Annual-CF'!$L$17:$U$17,MATCH('Monthly-CF'!O$9,'Annual-CF'!$L$9:$U$9,0)) -> 0 | P17: =INDEX('Annual-CF'!$L$17:$U$17,MATCH('Monthly-CF'!P$9,'Annual-CF'!$L$9:$U$9,0)) -> 0 | Q17: =INDEX('Annual-CF'!$L$17:$U$17,MATCH('Monthly-CF'!Q$9,'Annual-CF'!$L$9:$U$9,0)) -> 0 | R17: =INDEX('Annual-CF'!$L$17:$U$17,MATCH('Monthly-CF'!R$9,'Annual-CF'!$L$9:$U$9,0)) -> 0 | S17: =INDEX('Annual-CF'!$L$17:$U$17,MATCH('Monthly-CF'!S$9,'Annual-CF'!$L$9:$U$9,0)) -> 0 | ... EA17: =INDEX('Annual-CF'!$L$17:$U$17,MATCH('Monthly-CF'!EA$9,'Annual-CF'!$L$9:$U$9,0)) -> 0.42331181 | EC17: x
D18: PSF - Multi-Family Ph.1 | E18: =Assumptions!F34 -> 103297 | G18: =Assumptions!H56 -> 0.04 | I18: =MAX(L18:EA18) -> 0 | L18: =L13*$E18 -> 0 | M18: =M13*$E18 -> 0 | N18: =N13*$E18 -> 0 | O18: =O13*$E18 -> 0 | P18: =P13*$E18 -> 0 | Q18: =Q13*$E18 -> 0 | R18: =R13*$E18 -> 0 | S18: =S13*$E18 -> 0 | ... EA18: =EA13*$E18 -> 0 | EC18: x
D19: PSF - Multi-Family Ph.2 | I19: =MAX(L19:EA19) -> 0 | L19: =L14*$E19 -> 0 | M19: =M14*$E19 -> 0 | N19: =N14*$E19 -> 0 | O19: =O14*$E19 -> 0 | P19: =P14*$E19 -> 0 | Q19: =Q14*$E19 -> 0 | R19: =R14*$E19 -> 0 | S19: =S14*$E19 -> 0 | ... EA19: =EA14*$E19 -> 0 | EC19: x
D20: =CONCATENATE("PSF - ",Assumptions!J54) -> PSF - Ancillary Fees | E20: =SUM(E18:E19) -> 103297 | G20: =Assumptions!J56 -> 0.04 | I20: =MAX(L20:EA20) -> 0 | L20: =L15*$E20 -> 0 | M20: =M15*$E20 -> 0 | N20: =N15*$E20 -> 0 | O20: =O15*$E20 -> 0 | P20: =P15*$E20 -> 0 | Q20: =Q15*$E20 -> 0 | R20: =R15*$E20 -> 0 | S20: =S15*$E20 -> 0 | ... EA20: =EA15*$E20 -> 0 | EC20: x
EC21: x
D22: Revenue | E22: Rent PSF / Mo | EC22: x
D23: Revenue - Multi-Family Ph.1 | E23: =Assumptions!H55 -> 2.7909813 | I23: =SUM(K23:EA23) -> 0 | L23: =IF(AND(L9>=1,L$9<=Assumptions!$M$57),(1+L17)*L13*$E$18*$E$23,0) -> 0 | M23: =IF(AND(M9>=1,M$9<=Assumptions!$M$57),(1+M17)*M13*$E$18*$E$23,0) -> 0 | N23: =IF(AND(N9>=1,N$9<=Assumptions!$M$57),(1+N17)*N13*$E$18*$E$23,0) -> 0 | O23: =IF(AND(O9>=1,O$9<=Assumptions!$M$57),(1+O17)*O13*$E$18*$E$23,0) -> 0 | P23: =IF(AND(P9>=1,P$9<=Assumptions!$M$57),(1+P17)*P13*$E$18*$E$23,0) -> 0 | Q23: =IF(AND(Q9>=1,Q$9<=Assumptions!$M$57),(1+Q17)*Q13*$E$18*$E$23,0) -> 0 | R23: =IF(AND(R9>=1,R$9<=Assumptions!$M$57),(1+R17)*R13*$E$18*$E$23,0) -> 0 | S23: =IF(AND(S9>=1,S$9<=Assumptions!$M$57),(1+S17)*S13*$E$18*$E$23,0) -> 0 | ... EA23: =IF(AND(EA9>=1,EA$9<=Assumptions!$M$57),(1+EA17)*EA13*$E$18*$E$23,0) -> 0 | EC23: x
D24: Revenue - Multi-Family Ph.2 | E24: =Assumptions!H55 -> 2.7909813 | I24: =SUM(K24:EA24) -> 0 | M24: =IF(AND(M10>=1,M$9<=Assumptions!$M$57),(1+M17)*M14*$E$19*$E$24,0) -> 0 | N24: =IF(AND(N10>=1,N$9<=Assumptions!$M$57),(1+N17)*N14*$E$19*$E$24,0) -> 0 | O24: =IF(AND(O10>=1,O$9<=Assumptions!$M$57),(1+O17)*O14*$E$19*$E$24,0) -> 0 | P24: =IF(AND(P10>=1,P$9<=Assumptions!$M$57),(1+P17)*P14*$E$19*$E$24,0) -> 0 | Q24: =IF(AND(Q10>=1,Q$9<=Assumptions!$M$57),(1+Q17)*Q14*$E$19*$E$24,0) -> 0 | R24: =IF(AND(R10>=1,R$9<=Assumptions!$M$57),(1+R17)*R14*$E$19*$E$24,0) -> 0 | S24: =IF(AND(S10>=1,S$9<=Assumptions!$M$57),(1+S17)*S14*$E$19*$E$24,0) -> 0 | T24: =IF(AND(T10>=1,T$9<=Assumptions!$M$57),(1+T17)*T14*$E$19*$E$24,0) -> 0 | ... EA24: =IF(AND(EA10>=1,EA$9<=Assumptions!$M$57),(1+EA17)*EA14*$E$19*$E$24,0) -> 0 | EC24: x
D25: =CONCATENATE("Revenue - ",Assumptions!J$54) -> Revenue - Ancillary Fees | E25: =Assumptions!J55 -> 0.18144767 | I25: =SUM(K25:EA25) -> 0 | L25: =IF(AND(L9>=1,L$9<=Assumptions!$M$57),(1+L17)*L15*$E$20*$E$25,0) -> 0 | M25: =IF(AND(M9>=1,M$9<=Assumptions!$M$57),(1+M17)*M15*$E$20*$E$25,0) -> 0 | N25: =IF(AND(N9>=1,N$9<=Assumptions!$M$57),(1+N17)*N15*$E$20*$E$25,0) -> 0 | O25: =IF(AND(O9>=1,O$9<=Assumptions!$M$57),(1+O17)*O15*$E$20*$E$25,0) -> 0 | P25: =IF(AND(P9>=1,P$9<=Assumptions!$M$57),(1+P17)*P15*$E$20*$E$25,0) -> 0 | Q25: =IF(AND(Q9>=1,Q$9<=Assumptions!$M$57),(1+Q17)*Q15*$E$20*$E$25,0) -> 0 | R25: =IF(AND(R9>=1,R$9<=Assumptions!$M$57),(1+R17)*R15*$E$20*$E$25,0) -> 0 | S25: =IF(AND(S9>=1,S$9<=Assumptions!$M$57),(1+S17)*S15*$E$20*$E$25,0) -> 0 | ... BQ25: =IF(AND(BQ9>=1,BQ$9<=Assumptions!$M$57),(1+BQ17)*BQ15*$E$20*$E$25,0) -> 0 | BR25: =IF(AND(BR9>=1,BR$8<=Assumptions!$M$58),(1+BR17)*BR15*$E$20*$E$25,0) -> 0 | BS25: =IF(AND(BS9>=1,BS$8<=Assumptions!$M$58),(1+BS17)*BS15*$E$20*$E$25,0) -> 0 | BT25: =IF(AND(BT9>=1,BT$9<=Assumptions!$M$57),(1+BT17)*BT15*$E$20*$E$25,0) -> 0 | BU25: =IF(AND(BU9>=1,BU$9<=Assumptions!$M$57),(1+BU17)*BU15*$E$20*$E$25,0) -> 0 | BV25: =IF(AND(BV9>=1,BV$9<=Assumptions!$M$57),(1+BV17)*BV15*$E$20*$E$25,0) -> 0 | BW25: =IF(AND(BW9>=1,BW$9<=Assumptions!$M$57),(1+BW17)*BW15*$E$20*$E$25,0) -> 0 | BX25: =IF(AND(BX9>=1,BX$9<=Assumptions!$M$57),(1+BX17)*BX15*$E$20*$E$25,0) -> 0 | BY25: =IF(AND(BY9>=1,BY$9<=Assumptions!$M$57),(1+BY17)*BY15*$E$20*$E$25,0) -> 0 | BZ25: =IF(AND(BZ9>=1,BZ$9<=Assumptions!$M$57),(1+BZ17)*BZ15*$E$20*$E$25,0) -> 0 | CA25: =IF(AND(CA9>=1,CA$9<=Assumptions!$M$57),(1+CA17)*CA15*$E$20*$E$25,0) -> 0 | ... EA25: =IF(AND(EA9>=1,EA$9<=Assumptions!$M$57),(1+EA17)*EA15*$E$20*$E$25,0) -> 0 | EC25: x
EC26: x
D27: Rent Concessions | I27: =SUM(K27:EA27) -> 0 | L27: =-IF(L9<=Assumptions!$M$57,(((L18-K18)*Assumptions!$I$77*$E$23*(1+L$17))+((L19-K19)*Assumptions!$I$77*$E$24*(1+L$17))),0) -> 0 | M27: =-IF(M9<=Assumptions!$M$57,(((M18-L18)*Assumptions!$I$77*$E$23*(1+M$17))+((M19-L19)*Assumptions!$I$77*$E$24*(1+M$17))),0) -> 0 | N27: =-IF(N9<=Assumptions!$M$57,(((N18-M18)*Assumptions!$I$77*$E$23*(1+N$17))+((N19-M19)*Assumptions!$I$77*$E$24*(1+N$17))),0) -> 0 | O27: =-IF(O9<=Assumptions!$M$57,(((O18-N18)*Assumptions!$I$77*$E$23*(1+O$17))+((O19-N19)*Assumptions!$I$77*$E$24*(1+O$17))),0) -> 0 | P27: =-IF(P9<=Assumptions!$M$57,(((P18-O18)*Assumptions!$I$77*$E$23*(1+P$17))+((P19-O19)*Assumptions!$I$77*$E$24*(1+P$17))),0) -> 0 | Q27: =-IF(Q9<=Assumptions!$M$57,(((Q18-P18)*Assumptions!$I$77*$E$23*(1+Q$17))+((Q19-P19)*Assumptions!$I$77*$E$24*(1+Q$17))),0) -> 0 | R27: =-IF(R9<=Assumptions!$M$57,(((R18-Q18)*Assumptions!$I$77*$E$23*(1+R$17))+((R19-Q19)*Assumptions!$I$77*$E$24*(1+R$17))),0) -> 0 | S27: =-IF(S9<=Assumptions!$M$57,(((S18-R18)*Assumptions!$I$77*$E$23*(1+S$17))+((S19-R19)*Assumptions!$I$77*$E$24*(1+S$17))),0) -> 0 | ... EA27: =-IF(EA9<=Assumptions!$M$57,(((EA18-DZ18)*Assumptions!$I$77*$E$23*(1+EA$17))+((EA19-DZ19)*Assumptions!$I$77*$E$24*(1+EA$17))),0) -> 0 | EC27: x
D28: Net Revenue | I28: =SUM(K28:EA28) -> 0 | L28: =SUM(L23:L25)+SUM(L27:L27) -> 0 | M28: =SUM(M23:M25)+SUM(M27:M27) -> 0 | N28: =SUM(N23:N25)+SUM(N27:N27) -> 0 | O28: =SUM(O23:O25)+SUM(O27:O27) -> 0 | P28: =SUM(P23:P25)+SUM(P27:P27) -> 0 | Q28: =SUM(Q23:Q25)+SUM(Q27:Q27) -> 0 | R28: =SUM(R23:R25)+SUM(R27:R27) -> 0 | S28: =SUM(S23:S25)+SUM(S27:S27) -> 0 | ... EA28: =SUM(EA23:EA25)+SUM(EA27:EA27) -> 0 | EC28: x
EC29: x
E30: Cost PSF / Mo | G30: Exp. Inc. | L30: =INDEX('Annual-CF'!$L$30:$U$30,MATCH('Monthly-CF'!L$9,'Annual-CF'!$L$9:$U$9,0)) -> 0 | M30: =INDEX('Annual-CF'!$L$30:$U$30,MATCH('Monthly-CF'!M$9,'Annual-CF'!$L$9:$U$9,0)) -> 0 | N30: =INDEX('Annual-CF'!$L$30:$U$30,MATCH('Monthly-CF'!N$9,'Annual-CF'!$L$9:$U$9,0)) -> 0 | O30: =INDEX('Annual-CF'!$L$30:$U$30,MATCH('Monthly-CF'!O$9,'Annual-CF'!$L$9:$U$9,0)) -> 0 | P30: =INDEX('Annual-CF'!$L$30:$U$30,MATCH('Monthly-CF'!P$9,'Annual-CF'!$L$9:$U$9,0)) -> 0 | Q30: =INDEX('Annual-CF'!$L$30:$U$30,MATCH('Monthly-CF'!Q$9,'Annual-CF'!$L$9:$U$9,0)) -> 0 | R30: =INDEX('Annual-CF'!$L$30:$U$30,MATCH('Monthly-CF'!R$9,'Annual-CF'!$L$9:$U$9,0)) -> 0 | S30: =INDEX('Annual-CF'!$L$30:$U$30,MATCH('Monthly-CF'!S$9,'Annual-CF'!$L$9:$U$9,0)) -> 0 | ... EA30: =INDEX('Annual-CF'!$L$30:$U$30,MATCH('Monthly-CF'!EA$9,'Annual-CF'!$L$9:$U$9,0)) -> 0.30477318 | EC30: x
D31: Op Exp - Multi-Family Ph.1 | E31: =Assumptions!I80 -> 0.87766697 | G31: =Assumptions!I81 -> 0.03 | I31: =SUM(K31:EA31) -> 0 | L31: =-IF(L13=0,0,((1+L$30)*$E31*$E18)) -> 0 | M31: =-IF(M13=0,0,((1+M$30)*$E31*$E18)) -> 0 | N31: =-IF(N13=0,0,((1+N$30)*$E31*$E18)) -> 0 | O31: =-IF(O13=0,0,((1+O$30)*$E31*$E18)) -> 0 | P31: =-IF(P13=0,0,((1+P$30)*$E31*$E18)) -> 0 | Q31: =-IF(Q13=0,0,((1+Q$30)*$E31*$E18)) -> 0 | R31: =-IF(R13=0,0,((1+R$30)*$E31*$E18)) -> 0 | S31: =-IF(S13=0,0,((1+S$30)*$E31*$E18)) -> 0 | ... EA31: =-IF(EA13=0,0,((1+EA$30)*$E31*$E18)) -> 0 | EC31: x
D32: Op Exp - Multi-Family Ph. 2 | E32: =E31 -> 0.87766697 | G32: =G31 -> 0.03 | I32: =SUM(K32:EA32) -> 0 | L32: =-IF(L14=0,0,((1+L$30)*$E32*$E19)) -> 0 | M32: =-IF(M14=0,0,((1+M$30)*$E32*$E19)) -> 0 | N32: =-IF(N14=0,0,((1+N$30)*$E32*$E19)) -> 0 | O32: =-IF(O14=0,0,((1+O$30)*$E32*$E19)) -> 0 | P32: =-IF(P14=0,0,((1+P$30)*$E32*$E19)) -> 0 | Q32: =-IF(Q14=0,0,((1+Q$30)*$E32*$E19)) -> 0 | R32: =-IF(R14=0,0,((1+R$30)*$E32*$E19)) -> 0 | S32: =-IF(S14=0,0,((1+S$30)*$E32*$E19)) -> 0 | ... EA32: =-IF(EA14=0,0,((1+EA$30)*$E32*$E19)) -> 0
D33: Total Operating Expenses | I33: =SUM(K33:EA33) -> 0 | L33: =SUM(L31:L32) -> 0 | M33: =SUM(M31:M32) -> 0 | N33: =SUM(N31:N32) -> 0 | O33: =SUM(O31:O32) -> 0 | P33: =SUM(P31:P32) -> 0 | Q33: =SUM(Q31:Q32) -> 0 | R33: =SUM(R31:R32) -> 0 | S33: =SUM(S31:S32) -> 0 | ... EA33: =SUM(EA31:EA32) -> 0 | EC33: x
D34: Operating Income | I34: =SUM(K34:EA34) -> 0 | L34: =L28+L33 -> 0 | M34: =M28+M33 -> 0 | N34: =N28+N33 -> 0 | O34: =O28+O33 -> 0 | P34: =P28+P33 -> 0 | Q34: =Q28+Q33 -> 0 | R34: =R28+R33 -> 0 | S34: =S28+S33 -> 0 | ... EA34: =EA28+EA33 -> 0 | EC34: x
EC35: x
D36: Capital Reserve | I36: =SUM(K36:EA36) -> 0 | L36: =-IFERROR((IF(L13>0,Assumptions!$C$55*(Assumptions!$I$78/12),0)),0) -> 0 | M36: =-IFERROR((IF(M13>0,Assumptions!$C$55*(Assumptions!$I$78/12),0)),0) -> 0 | N36: =-IFERROR((IF(N13>0,Assumptions!$C$55*(Assumptions!$I$78/12),0)),0) -> 0 | O36: =-IFERROR((IF(O13>0,Assumptions!$C$55*(Assumptions!$I$78/12),0)),0) -> 0 | P36: =-IFERROR((IF(P13>0,Assumptions!$C$55*(Assumptions!$I$78/12),0)),0) -> 0 | Q36: =-IFERROR((IF(Q13>0,Assumptions!$C$55*(Assumptions!$I$78/12),0)),0) -> 0 | R36: =-IFERROR((IF(R13>0,Assumptions!$C$55*(Assumptions!$I$78/12),0)),0) -> 0 | S36: =-IFERROR((IF(S13>0,Assumptions!$C$55*(Assumptions!$I$78/12),0)),0) -> 0 | ... EA36: =-IFERROR((IF(EA13>0,Assumptions!$C$55*(Assumptions!$I$78/12),0)),0) -> 0 | EC36: x
D37: Operating Cash flow - Residential | I37: =SUM(K37:EA37) -> 0 | L37: =L34+L36 -> 0 | M37: =M34+M36 -> 0 | N37: =N34+N36 -> 0 | O37: =O34+O36 -> 0 | P37: =P34+P36 -> 0 | Q37: =Q34+Q36 -> 0 | R37: =R34+R36 -> 0 | S37: =S34+S36 -> 0 | ... EA37: =EA34+EA36 -> 0 | EC37: x
EC38: x
D39: Residential Summary - STR / MF | EC39: x
EC40: x
D41: Income to Owner - After FF&E | I41: =SUM(K41:EA41) -> 42410997 | L41: =IF(L8<=Assumptions!$M$58,SUMIFS('Cash Flow MH'!$D$91:$DS$91,'Cash Flow MH'!$D$8:$DS$8,'Monthly-CF'!L8),0) -> 0 | M41: =IF(M8<=Assumptions!$M$58,SUMIFS('Cash Flow MH'!$D$91:$DS$91,'Cash Flow MH'!$D$8:$DS$8,'Monthly-CF'!M8),0) -> 0 | N41: =IF(N8<=Assumptions!$M$58,SUMIFS('Cash Flow MH'!$D$91:$DS$91,'Cash Flow MH'!$D$8:$DS$8,'Monthly-CF'!N8),0) -> 0 | O41: =IF(O8<=Assumptions!$M$58,SUMIFS('Cash Flow MH'!$D$91:$DS$91,'Cash Flow MH'!$D$8:$DS$8,'Monthly-CF'!O8),0) -> 0 | P41: =IF(P8<=Assumptions!$M$58,SUMIFS('Cash Flow MH'!$D$91:$DS$91,'Cash Flow MH'!$D$8:$DS$8,'Monthly-CF'!P8),0) -> 0 | Q41: =IF(Q8<=Assumptions!$M$58,SUMIFS('Cash Flow MH'!$D$91:$DS$91,'Cash Flow MH'!$D$8:$DS$8,'Monthly-CF'!Q8),0) -> 0 | R41: =IF(R8<=Assumptions!$M$58,SUMIFS('Cash Flow MH'!$D$91:$DS$91,'Cash Flow MH'!$D$8:$DS$8,'Monthly-CF'!R8),0) -> 0 | S41: =IF(S8<=Assumptions!$M$58,SUMIFS('Cash Flow MH'!$D$91:$DS$91,'Cash Flow MH'!$D$8:$DS$8,'Monthly-CF'!S8),0) -> 0 | ... EA41: =IF(EA8<=Assumptions!$M$58,SUMIFS('Cash Flow MH'!$D$91:$DS$91,'Cash Flow MH'!$D$8:$DS$8,'Monthly-CF'!EA8),0) -> 552751.8 | EC41: x
D42: Less: Insurance | I42: =SUM(K42:EA42) -> -2713323.9 | L42: =IF(L41>0,(-Assumptions!$I$82*Assumptions!$C$34)*(1+'Monthly-CF'!L30),0) -> 0 | M42: =IF(M41>0,(-Assumptions!$I$82*Assumptions!$C$34)*(1+'Monthly-CF'!M30),0) -> 0 | N42: =IF(N41>0,(-Assumptions!$I$82*Assumptions!$C$34)*(1+'Monthly-CF'!N30),0) -> 0 | O42: =IF(O41>0,(-Assumptions!$I$82*Assumptions!$C$34)*(1+'Monthly-CF'!O30),0) -> 0 | P42: =IF(P41>0,(-Assumptions!$I$82*Assumptions!$C$34)*(1+'Monthly-CF'!P30),0) -> 0 | Q42: =IF(Q41>0,(-Assumptions!$I$82*Assumptions!$C$34)*(1+'Monthly-CF'!Q30),0) -> 0 | R42: =IF(R41>0,(-Assumptions!$I$82*Assumptions!$C$34)*(1+'Monthly-CF'!R30),0) -> 0 | S42: =IF(S41>0,(-Assumptions!$I$82*Assumptions!$C$34)*(1+'Monthly-CF'!S30),0) -> 0 | ... EA42: =IF(EA41>0,(-Assumptions!$I$82*Assumptions!$C$34)*(1+'Monthly-CF'!EA30),0) -> -29911.925 | EC42: x
D43: Less: RE Tax | I43: =SUM(K43:EA43) -> -4640788.6 | L43: =-IF(SUM(K$70:$L70)=$I$70,INDEX('RE Tax'!$D$43:$P$43,MATCH('Monthly-CF'!L9,'RE Tax'!$D$11:$P$11,0))/12,0) -> 0 | M43: =-IF(SUM($L$70:L70)=$I$70,INDEX('RE Tax'!$D$43:$P$43,MATCH('Monthly-CF'!M9,'RE Tax'!$D$11:$P$11,0))/12,0) -> 0 | N43: =-IF(SUM($L$70:M70)=$I$70,INDEX('RE Tax'!$D$43:$P$43,MATCH('Monthly-CF'!N9,'RE Tax'!$D$11:$P$11,0))/12,0) -> 0 | O43: =-IF(SUM($L$70:N70)=$I$70,INDEX('RE Tax'!$D$43:$P$43,MATCH('Monthly-CF'!O9,'RE Tax'!$D$11:$P$11,0))/12,0) -> 0 | P43: =-IF(SUM($L$70:O70)=$I$70,INDEX('RE Tax'!$D$43:$P$43,MATCH('Monthly-CF'!P9,'RE Tax'!$D$11:$P$11,0))/12,0) -> 0 | Q43: =-IF(SUM($L$70:P70)=$I$70,INDEX('RE Tax'!$D$43:$P$43,MATCH('Monthly-CF'!Q9,'RE Tax'!$D$11:$P$11,0))/12,0) -> 0 | R43: =-IF(SUM($L$70:Q70)=$I$70,INDEX('RE Tax'!$D$43:$P$43,MATCH('Monthly-CF'!R9,'RE Tax'!$D$11:$P$11,0))/12,0) -> 0 | S43: =-IF(SUM($L$70:R70)=$I$70,INDEX('RE Tax'!$D$43:$P$43,MATCH('Monthly-CF'!S9,'RE Tax'!$D$11:$P$11,0))/12,0) -> 0 | T43: =-IF(SUM($L$70:S70)=$I$70,INDEX('RE Tax'!$D$43:$P$43,MATCH('Monthly-CF'!T9,'RE Tax'!$D$11:$P$11,0))/12,0) -> 0 | ... EA43: =-IF(SUM($L$70:DZ70)=$I$70,INDEX('RE Tax'!$D$43:$P$43,MATCH('Monthly-CF'!EA9,'RE Tax'!$D$11:$P$11,0))/12,0) -> -63910.261 | EC43: x
D44: Income to Owner - After FF&E & RE Tax | I44: =SUM(K44:EA44) -> 35056884 | L44: =SUM(L41:L43) -> 0 | M44: =SUM(M41:M43) -> 0 | N44: =SUM(N41:N43) -> 0 | O44: =SUM(O41:O43) -> 0 | P44: =SUM(P41:P43) -> 0 | Q44: =SUM(Q41:Q43) -> 0 | R44: =SUM(R41:R43) -> 0 | S44: =SUM(S41:S43) -> 0 | ... EA44: =SUM(EA41:EA43) -> 458929.62 | EC44: x
EC45: x
D46: Commercial Summary | EC46: x
EC47: x
D48: =CONCATENATE("Occ - ",Assumptions!$D$54) -> Occ - Commercial | I48: =MAX(L48:EA48) -> 0 | L48: =IF(L$8<=Assumptions!$M$58,IF(SUM($K$70:K$70)=$I$70,IF(K48=0,Assumptions!$H$60,MIN('Monthly-CF'!K48+Assumptions!$I$60,Assumptions!$J$60)),0),0) -> 0 | M48: =IF(M$8<=Assumptions!$M$58,IF(SUM($K$70:L$70)=$I$70,IF(L48=0,Assumptions!$H$60,MIN('Monthly-CF'!L48+Assumptions!$I$60,Assumptions!$J$60)),0),0) -> 0 | N48: =IF(N$8<=Assumptions!$M$58,IF(SUM($K$70:M$70)=$I$70,IF(M48=0,Assumptions!$H$60,MIN('Monthly-CF'!M48+Assumptions!$I$60,Assumptions!$J$60)),0),0) -> 0 | O48: =IF(O$8<=Assumptions!$M$58,IF(SUM($K$70:N$70)=$I$70,IF(N48=0,Assumptions!$H$60,MIN('Monthly-CF'!N48+Assumptions!$I$60,Assumptions!$J$60)),0),0) -> 0 | P48: =IF(P$8<=Assumptions!$M$58,IF(SUM($K$70:O$70)=$I$70,IF(O48=0,Assumptions!$H$60,MIN('Monthly-CF'!O48+Assumptions!$I$60,Assumptions!$J$60)),0),0) -> 0 | Q48: =IF(Q$8<=Assumptions!$M$58,IF(SUM($K$70:P$70)=$I$70,IF(P48=0,Assumptions!$H$60,MIN('Monthly-CF'!P48+Assumptions!$I$60,Assumptions!$J$60)),0),0) -> 0 | R48: =IF(R$8<=Assumptions!$M$58,IF(SUM($K$70:Q$70)=$I$70,IF(Q48=0,Assumptions!$H$60,MIN('Monthly-CF'!Q48+Assumptions!$I$60,Assumptions!$J$60)),0),0) -> 0 | S48: =IF(S$8<=Assumptions!$M$58,IF(SUM($K$70:R$70)=$I$70,IF(R48=0,Assumptions!$H$60,MIN('Monthly-CF'!R48+Assumptions!$I$60,Assumptions!$J$60)),0),0) -> 0 | ... EA48: =IF(EA$8<=Assumptions!$M$58,IF(SUM($K$70:DZ$70)=$I$70,IF(DZ48=0,Assumptions!$H$60,MIN('Monthly-CF'!DZ48+Assumptions!$I$60,Assumptions!$J$60)),0),0) -> 0 | EC48: x
D49: =CONCATENATE("PSF - ",Assumptions!I54) -> PSF - Commercial | E49: =Assumptions!D55 -> 0 | G49: =Assumptions!I56 -> 0.04 | I49: =MAX(L49:EA49) -> 0 | L49: =L48*$E49 -> 0 | M49: =M48*$E49 -> 0 | N49: =N48*$E49 -> 0 | O49: =O48*$E49 -> 0 | P49: =P48*$E49 -> 0 | Q49: =Q48*$E49 -> 0 | R49: =R48*$E49 -> 0 | S49: =S48*$E49 -> 0 | ... EA49: =EA48*$E49 -> 0 | EC49: x
EC50: x
D51: =CONCATENATE("Revenue - ",Assumptions!$I$54) -> Revenue - Commercial | E51: =Assumptions!I55 -> 2.75 | I51: =SUM(K51:EA51) -> 0 | L51: =IF(AND(L9>=1,L$9<=Assumptions!$M$57),(1+L17)*L48*$E$49*$E$51,0) -> 0 | M51: =IF(AND(M9>=1,M$9<=Assumptions!$M$57),(1+M17)*M48*$E$49*$E$51,0) -> 0 | N51: =IF(AND(N9>=1,N$9<=Assumptions!$M$57),(1+N17)*N48*$E$49*$E$51,0) -> 0 | O51: =IF(AND(O9>=1,O$9<=Assumptions!$M$57),(1+O17)*O48*$E$49*$E$51,0) -> 0 | P51: =IF(AND(P9>=1,P$9<=Assumptions!$M$57),(1+P17)*P48*$E$49*$E$51,0) -> 0 | Q51: =IF(AND(Q9>=1,Q$9<=Assumptions!$M$57),(1+Q17)*Q48*$E$49*$E$51,0) -> 0 | R51: =IF(AND(R9>=1,R$9<=Assumptions!$M$57),(1+R17)*R48*$E$49*$E$51,0) -> 0 | S51: =IF(AND(S9>=1,S$9<=Assumptions!$M$57),(1+S17)*S48*$E$49*$E$51,0) -> 0 | ... EA51: =IF(AND(EA9>=1,EA$9<=Assumptions!$M$57),(1+EA17)*EA48*$E$49*$E$51,0) -> 0 | EC51: x
D52: CAM | I52: =SUM(K52:EA52) -> 0 | L52: =-L55 -> 0 | M52: =-M55 -> 0 | N52: =-N55 -> 0 | O52: =-O55 -> 0 | P52: =-P55 -> 0 | Q52: =-Q55 -> 0 | R52: =-R55 -> 0 | S52: =-S55 -> 0 | ... EA52: =-EA55 -> 0 | EC52: x
D53: Net Revenue | I53: =SUM(K53:EA53) -> 0 | L53: =SUM(L51:L52) -> 0 | M53: =SUM(M51:M52) -> 0 | N53: =SUM(N51:N52) -> 0 | O53: =SUM(O51:O52) -> 0 | P53: =SUM(P51:P52) -> 0 | Q53: =SUM(Q51:Q52) -> 0 | R53: =SUM(R51:R52) -> 0 | S53: =SUM(S51:S52) -> 0 | ... EA53: =SUM(EA51:EA52) -> 0 | EC53: x
D54: Commissions | I54: =SUM(K54:EA54) -> 0 | L54: =IF(L49-K49>0,((L49-K49)*(-$E$51*12))*Assumptions!$J$76,0) -> 0 | M54: =IF(M49-L49>0,((M49-L49)*(-$E$51*12))*Assumptions!$J$76,0) -> 0 | N54: =IF(N49-M49>0,((N49-M49)*(-$E$51*12))*Assumptions!$J$76,0) -> 0 | O54: =IF(O49-N49>0,((O49-N49)*(-$E$51*12))*Assumptions!$J$76,0) -> 0 | P54: =IF(P49-O49>0,((P49-O49)*(-$E$51*12))*Assumptions!$J$76,0) -> 0 | Q54: =IF(Q49-P49>0,((Q49-P49)*(-$E$51*12))*Assumptions!$J$76,0) -> 0 | R54: =IF(R49-Q49>0,((R49-Q49)*(-$E$51*12))*Assumptions!$J$76,0) -> 0 | S54: =IF(S49-R49>0,((S49-R49)*(-$E$51*12))*Assumptions!$J$76,0) -> 0 | ... EA54: =IF(EA49-DZ49>0,((EA49-DZ49)*(-$E$51*12))*Assumptions!$J$76,0) -> 0 | EC54: x
D55: =CONCATENATE("Op Exp - ",Assumptions!D$54) -> Op Exp - Commercial | E55: =Assumptions!J80 -> 0.6875 | G55: =+Assumptions!J81 -> 0.03 | I55: =SUM(K55:EA55) -> 0 | L55: =-IF(L48=0,0,((1+L$30)*$E55*$E49)) -> 0 | M55: =-IF(M48=0,0,((1+M$30)*$E55*$E49)) -> 0 | N55: =-IF(N48=0,0,((1+N$30)*$E55*$E49)) -> 0 | O55: =-IF(O48=0,0,((1+O$30)*$E55*$E49)) -> 0 | P55: =-IF(P48=0,0,((1+P$30)*$E55*$E49)) -> 0 | Q55: =-IF(Q48=0,0,((1+Q$30)*$E55*$E49)) -> 0 | R55: =-IF(R48=0,0,((1+R$30)*$E55*$E49)) -> 0 | S55: =-IF(S48=0,0,((1+S$30)*$E55*$E49)) -> 0 | ... EA55: =-IF(EA48=0,0,((1+EA$30)*$E55*$E49)) -> 0 | EC55: x
D56: Operating Income | I56: =SUM(K56:EA56) -> 0 | L56: =L53+L54+L55 -> 0 | M56: =M53+M54+M55 -> 0 | N56: =N53+N54+N55 -> 0 | O56: =O53+O54+O55 -> 0 | P56: =P53+P54+P55 -> 0 | Q56: =Q53+Q54+Q55 -> 0 | R56: =R53+R54+R55 -> 0 | S56: =S53+S54+S55 -> 0 | ... EA56: =EA53+EA54+EA55 -> 0 | EC56: x
D57: Capital Reserve | I57: =SUM(K57:EA57) -> 0 | L57: =-IFERROR(IF(L48>0,Assumptions!$D$55*Assumptions!$J$78,0)/12,0) -> 0 | M57: =-IFERROR(IF(M48>0,Assumptions!$D$55*Assumptions!$J$78,0)/12,0) -> 0 | N57: =-IFERROR(IF(N48>0,Assumptions!$D$55*Assumptions!$J$78,0)/12,0) -> 0 | O57: =-IFERROR(IF(O48>0,Assumptions!$D$55*Assumptions!$J$78,0)/12,0) -> 0 | P57: =-IFERROR(IF(P48>0,Assumptions!$D$55*Assumptions!$J$78,0)/12,0) -> 0 | Q57: =-IFERROR(IF(Q48>0,Assumptions!$D$55*Assumptions!$J$78,0)/12,0) -> 0 | R57: =-IFERROR(IF(R48>0,Assumptions!$D$55*Assumptions!$J$78,0)/12,0) -> 0 | S57: =-IFERROR(IF(S48>0,Assumptions!$D$55*Assumptions!$J$78,0)/12,0) -> 0 | ... EA57: =-IFERROR(IF(EA48>0,Assumptions!$D$55*Assumptions!$J$78,0)/12,0) -> 0 | EC57: x
D58: Operating Cash Flow - Commercial | I58: =SUM(K58:EA58) -> 0 | L58: =L56+L57 -> 0 | M58: =M56+M57 -> 0 | N58: =N56+N57 -> 0 | O58: =O56+O57 -> 0 | P58: =P56+P57 -> 0 | Q58: =Q56+Q57 -> 0 | R58: =R56+R57 -> 0 | S58: =S56+S57 -> 0 | ... EA58: =EA56+EA57 -> 0 | EC58: x
EC59: x
D60: Residential | EC60: x
D61: Valuation | L61: =INDEX('Annual-CF'!$L$60:$U$60,MATCH('Monthly-CF'!L9,'Annual-CF'!$L$9:$U$9,0)) -> 0 | M61: =INDEX('Annual-CF'!$L$60:$U$60,MATCH('Monthly-CF'!M9,'Annual-CF'!$L$9:$U$9,0)) -> 0 | N61: =INDEX('Annual-CF'!$L$60:$U$60,MATCH('Monthly-CF'!N9,'Annual-CF'!$L$9:$U$9,0)) -> 0 | O61: =INDEX('Annual-CF'!$L$60:$U$60,MATCH('Monthly-CF'!O9,'Annual-CF'!$L$9:$U$9,0)) -> 0 | P61: =INDEX('Annual-CF'!$L$60:$U$60,MATCH('Monthly-CF'!P9,'Annual-CF'!$L$9:$U$9,0)) -> 0 | Q61: =INDEX('Annual-CF'!$L$60:$U$60,MATCH('Monthly-CF'!Q9,'Annual-CF'!$L$9:$U$9,0)) -> 0 | R61: =INDEX('Annual-CF'!$L$60:$U$60,MATCH('Monthly-CF'!R9,'Annual-CF'!$L$9:$U$9,0)) -> 0 | S61: =INDEX('Annual-CF'!$L$60:$U$60,MATCH('Monthly-CF'!S9,'Annual-CF'!$L$9:$U$9,0)) -> 0 | ... EA61: =INDEX('Annual-CF'!$L$60:$U$60,MATCH('Monthly-CF'!EA9,'Annual-CF'!$L$9:$U$9,0)) -> 86504554 | EC61: x
D62: Sale (incl sales cost) | I62: =SUM(K62:EA62) -> 85423247 | L62: =IF(Assumptions!$M$58='Monthly-CF'!L$8,L61*(1-Assumptions!$M$56),0) -> 0 | M62: =IF(Assumptions!$M$58='Monthly-CF'!M$8,M61*(1-Assumptions!$M$56),0) -> 0 | N62: =IF(Assumptions!$M$58='Monthly-CF'!N$8,N61*(1-Assumptions!$M$56),0) -> 0 | O62: =IF(Assumptions!$M$58='Monthly-CF'!O$8,O61*(1-Assumptions!$M$56),0) -> 0 | P62: =IF(Assumptions!$M$58='Monthly-CF'!P$8,P61*(1-Assumptions!$M$56),0) -> 0 | Q62: =IF(Assumptions!$M$58='Monthly-CF'!Q$8,Q61*(1-Assumptions!$M$56),0) -> 0 | R62: =IF(Assumptions!$M$58='Monthly-CF'!R$8,R61*(1-Assumptions!$M$56),0) -> 0 | S62: =IF(Assumptions!$M$58='Monthly-CF'!S$8,S61*(1-Assumptions!$M$56),0) -> 0 | ... EA62: =IF(Assumptions!$M$58='Monthly-CF'!EA$8,EA61*(1-Assumptions!$M$56),0) -> 85423247 | EC62: x
EC63: x
D64: Commercial | EC64: x
D65: Valuation | L65: =IFERROR(IF(L9<=Assumptions!$M$62,('Monthly-CF'!L56*12)/Assumptions!$M$60,0),0) -> 0 | M65: =IFERROR(IF(M9<=Assumptions!$M$62,('Monthly-CF'!M56*12)/Assumptions!$M$60,0),0) -> 0 | N65: =IFERROR(IF(N9<=Assumptions!$M$62,('Monthly-CF'!N56*12)/Assumptions!$M$60,0),0) -> 0 | O65: =IFERROR(IF(O9<=Assumptions!$M$62,('Monthly-CF'!O56*12)/Assumptions!$M$60,0),0) -> 0 | P65: =IFERROR(IF(P9<=Assumptions!$M$62,('Monthly-CF'!P56*12)/Assumptions!$M$60,0),0) -> 0 | Q65: =IFERROR(IF(Q9<=Assumptions!$M$62,('Monthly-CF'!Q56*12)/Assumptions!$M$60,0),0) -> 0 | R65: =IFERROR(IF(R9<=Assumptions!$M$62,('Monthly-CF'!R56*12)/Assumptions!$M$60,0),0) -> 0 | S65: =IFERROR(IF(S9<=Assumptions!$M$62,('Monthly-CF'!S56*12)/Assumptions!$M$60,0),0) -> 0 | ... EA65: =IFERROR(IF(EA9<=Assumptions!$M$62,('Monthly-CF'!EA56*12)/Assumptions!$M$60,0),0) -> 0 | EC65: x
D66: Sale (incl sales cost) | F66: -2594174.5 | G66: =F66-I74 -> -119882.96 | I66: =SUM(K66:EA66) -> 0 | L66: =IFERROR(IF(Assumptions!$M$63='Monthly-CF'!L$8,L65*(1-Assumptions!$M$61),0),0) -> 0 | M66: =IFERROR(IF(Assumptions!$M$63='Monthly-CF'!M$8,M65*(1-Assumptions!$M$61),0),0) -> 0 | N66: =IFERROR(IF(Assumptions!$M$63='Monthly-CF'!N$8,N65*(1-Assumptions!$M$61),0),0) -> 0 | O66: =IFERROR(IF(Assumptions!$M$63='Monthly-CF'!O$8,O65*(1-Assumptions!$M$61),0),0) -> 0 | P66: =IFERROR(IF(Assumptions!$M$63='Monthly-CF'!P$8,P65*(1-Assumptions!$M$61),0),0) -> 0 | Q66: =IFERROR(IF(Assumptions!$M$63='Monthly-CF'!Q$8,Q65*(1-Assumptions!$M$61),0),0) -> 0 | R66: =IFERROR(IF(Assumptions!$M$63='Monthly-CF'!R$8,R65*(1-Assumptions!$M$61),0),0) -> 0 | S66: =IFERROR(IF(Assumptions!$M$63='Monthly-CF'!S$8,S65*(1-Assumptions!$M$61),0),0) -> 0 | ... EA66: =IFERROR(IF(Assumptions!$M$63='Monthly-CF'!EA$8,EA65*(1-Assumptions!$M$61),0),0) -> 0 | EC66: x
EC67: x
D68: Project Costs Phase 1: | E68: Budget | F68: Start | G68: Dur. | H68: End | EC68: x
D69: Land | E69: =-SUMIFS('Budget Detail'!$K$9:$K$77,'Budget Detail'!$D$9:$D$77,'Monthly-CF'!D69) -> -5200000 | F69: 0 | G69: 1 | H69: =F69+G69 -> 1 | I69: =SUM(K69:EA69) -> -5200000 | L69: =IF(AND(L$10>='Monthly-CF'!$F69,L$10<='Monthly-CF'!$H69),'Monthly-CF'!$E69/('Monthly-CF'!$G69),0) -> -5200000 | M69: =IF(AND(M$10>='Monthly-CF'!$F69,M$10<='Monthly-CF'!$H69),'Monthly-CF'!$E69/('Monthly-CF'!$G69),0) -> 0 | N69: =IF(AND(N$10>='Monthly-CF'!$F69,N$10<='Monthly-CF'!$H69),'Monthly-CF'!$E69/('Monthly-CF'!$G69),0) -> 0 | O69: =IF(AND(O$10>='Monthly-CF'!$F69,O$10<='Monthly-CF'!$H69),'Monthly-CF'!$E69/('Monthly-CF'!$G69),0) -> 0 | P69: =IF(AND(P$10>='Monthly-CF'!$F69,P$10<='Monthly-CF'!$H69),'Monthly-CF'!$E69/('Monthly-CF'!$G69),0) -> 0 | Q69: =IF(AND(Q$10>='Monthly-CF'!$F69,Q$10<='Monthly-CF'!$H69),'Monthly-CF'!$E69/('Monthly-CF'!$G69),0) -> 0 | R69: =IF(AND(R$10>='Monthly-CF'!$F69,R$10<='Monthly-CF'!$H69),'Monthly-CF'!$E69/('Monthly-CF'!$G69),0) -> 0 | S69: =IF(AND(S$10>='Monthly-CF'!$F69,S$10<='Monthly-CF'!$H69),'Monthly-CF'!$E69/('Monthly-CF'!$G69),0) -> 0 | ... EA69: =IF(AND(EA$10>='Monthly-CF'!$F69,EA$10<='Monthly-CF'!$H69),'Monthly-CF'!$E69/('Monthly-CF'!$G69),0) -> 0 | EC69: x
D70: Hard Costs | E70: =-SUMIFS('Budget Detail'!$K$9:$K$77,'Budget Detail'!$D$9:$D$77,'Monthly-CF'!D70) -> -38440298 | F70: 3 | G70: 16 | H70: =F70+G70 -> 19 | I70: =SUM(K70:EA70) -> -38440298 | L70: =IF(AND(L$10>='Monthly-CF'!$F70,L$10<='Monthly-CF'!$H70),'Monthly-CF'!$E70/('Monthly-CF'!$G70+1),0) -> 0 | M70: =IF(AND(M$10>='Monthly-CF'!$F70,M$10<='Monthly-CF'!$H70),'Monthly-CF'!$E70/('Monthly-CF'!$G70+1),0) -> 0 | N70: =IF(AND(N$10>='Monthly-CF'!$F70,N$10<='Monthly-CF'!$H70),'Monthly-CF'!$E70/('Monthly-CF'!$G70+1),0) -> -2261194 | O70: =IF(AND(O$10>='Monthly-CF'!$F70,O$10<='Monthly-CF'!$H70),'Monthly-CF'!$E70/('Monthly-CF'!$G70+1),0) -> -2261194 | P70: =IF(AND(P$10>='Monthly-CF'!$F70,P$10<='Monthly-CF'!$H70),'Monthly-CF'!$E70/('Monthly-CF'!$G70+1),0) -> -2261194 | Q70: =IF(AND(Q$10>='Monthly-CF'!$F70,Q$10<='Monthly-CF'!$H70),'Monthly-CF'!$E70/('Monthly-CF'!$G70+1),0) -> -2261194 | R70: =IF(AND(R$10>='Monthly-CF'!$F70,R$10<='Monthly-CF'!$H70),'Monthly-CF'!$E70/('Monthly-CF'!$G70+1),0) -> -2261194 | S70: =IF(AND(S$10>='Monthly-CF'!$F70,S$10<='Monthly-CF'!$H70),'Monthly-CF'!$E70/('Monthly-CF'!$G70+1),0) -> -2261194 | ... EA70: =IF(AND(EA$10>='Monthly-CF'!$F70,EA$10<='Monthly-CF'!$H70),'Monthly-CF'!$E70/('Monthly-CF'!$G70+1),0) -> 0 | EC70: x
D71: Soft Costs (Excl. D/S) | E71: =-SUMIFS('Budget Detail'!$K$9:$K$77,'Budget Detail'!$D$9:$D$77,'Monthly-CF'!D71) -> -6649601.1 | F71: 2 | G71: 16 | H71: =F71+G71 -> 18 | I71: =SUM(K71:EA71) -> -6649601.1 | L71: =IF(AND(L$10>='Monthly-CF'!$F71,L$10<='Monthly-CF'!$H71),'Monthly-CF'!$E71/('Monthly-CF'!$G71+1),0) -> 0 | M71: =IF(AND(M$10>='Monthly-CF'!$F71,M$10<='Monthly-CF'!$H71),'Monthly-CF'!$E71/('Monthly-CF'!$G71+1),0) -> -391153.01 | N71: =IF(AND(N$10>='Monthly-CF'!$F71,N$10<='Monthly-CF'!$H71),'Monthly-CF'!$E71/('Monthly-CF'!$G71+1),0) -> -391153.01 | O71: =IF(AND(O$10>='Monthly-CF'!$F71,O$10<='Monthly-CF'!$H71),'Monthly-CF'!$E71/('Monthly-CF'!$G71+1),0) -> -391153.01 | P71: =IF(AND(P$10>='Monthly-CF'!$F71,P$10<='Monthly-CF'!$H71),'Monthly-CF'!$E71/('Monthly-CF'!$G71+1),0) -> -391153.01 | Q71: =IF(AND(Q$10>='Monthly-CF'!$F71,Q$10<='Monthly-CF'!$H71),'Monthly-CF'!$E71/('Monthly-CF'!$G71+1),0) -> -391153.01 | R71: =IF(AND(R$10>='Monthly-CF'!$F71,R$10<='Monthly-CF'!$H71),'Monthly-CF'!$E71/('Monthly-CF'!$G71+1),0) -> -391153.01 | S71: =IF(AND(S$10>='Monthly-CF'!$F71,S$10<='Monthly-CF'!$H71),'Monthly-CF'!$E71/('Monthly-CF'!$G71+1),0) -> -391153.01 | ... EA71: =IF(AND(EA$10>='Monthly-CF'!$F71,EA$10<='Monthly-CF'!$H71),'Monthly-CF'!$E71/('Monthly-CF'!$G71+1),0) -> 0 | EC71: x
D72: Dev Fess | E72: =-SUMIFS('Budget Detail'!$K$9:$K$77,'Budget Detail'!$D$9:$D$77,'Monthly-CF'!D72) -> -1672635.6 | F72: =F70 -> 3 | G72: =G70 -> 16 | H72: =F72+G72 -> 19 | I72: =SUM(K72:EA72) -> -1672635.6 | L72: =IF(AND(L$10>='Monthly-CF'!$F72,L$10<='Monthly-CF'!$H72),'Monthly-CF'!$E72/('Monthly-CF'!$G72+1),0) -> 0 | M72: =IF(AND(M$10>='Monthly-CF'!$F72,M$10<='Monthly-CF'!$H72),'Monthly-CF'!$E72/('Monthly-CF'!$G72+1),0) -> 0 | N72: =IF(AND(N$10>='Monthly-CF'!$F72,N$10<='Monthly-CF'!$H72),'Monthly-CF'!$E72/('Monthly-CF'!$G72+1),0) -> -98390.332 | O72: =IF(AND(O$10>='Monthly-CF'!$F72,O$10<='Monthly-CF'!$H72),'Monthly-CF'!$E72/('Monthly-CF'!$G72+1),0) -> -98390.332 | P72: =IF(AND(P$10>='Monthly-CF'!$F72,P$10<='Monthly-CF'!$H72),'Monthly-CF'!$E72/('Monthly-CF'!$G72+1),0) -> -98390.332 | Q72: =IF(AND(Q$10>='Monthly-CF'!$F72,Q$10<='Monthly-CF'!$H72),'Monthly-CF'!$E72/('Monthly-CF'!$G72+1),0) -> -98390.332 | R72: =IF(AND(R$10>='Monthly-CF'!$F72,R$10<='Monthly-CF'!$H72),'Monthly-CF'!$E72/('Monthly-CF'!$G72+1),0) -> -98390.332 | S72: =IF(AND(S$10>='Monthly-CF'!$F72,S$10<='Monthly-CF'!$H72),'Monthly-CF'!$E72/('Monthly-CF'!$G72+1),0) -> -98390.332 | ... EA72: =IF(AND(EA$10>='Monthly-CF'!$F72,EA$10<='Monthly-CF'!$H72),'Monthly-CF'!$E72/('Monthly-CF'!$G72+1),0) -> 0 | EC72: x
D73: Loan Fees | E73: =Assumptions!E62 -> 0.0075 | I73: =SUM(K73:EA73) -> -247429.15 | L73: =IF(L107=1,-$I$109*$E$73,0) -> 0 | M73: =IF(M107=1,-$I$109*$E$73,0) -> 0 | N73: =IF(N107=1,-$I$109*$E$73,0) -> 0 | O73: =IF(O107=1,-$I$109*$E$73,0) -> 0 | P73: =IF(P107=1,-$I$109*$E$73,0) -> 0 | Q73: =IF(Q107=1,-$I$109*$E$73,0) -> 0 | R73: =IF(R107=1,-$I$109*$E$73,0) -> 0 | S73: =IF(S107=1,-$I$109*$E$73,0) -> -247429.15 | ... EA73: =IF(EA107=1,-$I$109*$E$73,0) -> 0 | EC73: x
D74: Interest | E74: =-'Budget Detail'!K23 -> -2474291.5 | F74: 8 | G74: 18 | H74: =F74+G74 -> 26 | I74: =SUM(K74:EA74) -> -2474291.5 | L74: =IF(AND(L$10>='Monthly-CF'!$F74,L$10<='Monthly-CF'!$H74),'Monthly-CF'!$E74/('Monthly-CF'!$G74+1),0) -> 0 | M74: =IF(AND(M$10>='Monthly-CF'!$F74,M$10<='Monthly-CF'!$H74),'Monthly-CF'!$E74/('Monthly-CF'!$G74+1),0) -> 0 | N74: =IF(AND(N$10>='Monthly-CF'!$F74,N$10<='Monthly-CF'!$H74),'Monthly-CF'!$E74/('Monthly-CF'!$G74+1),0) -> 0 | O74: =IF(AND(O$10>='Monthly-CF'!$F74,O$10<='Monthly-CF'!$H74),'Monthly-CF'!$E74/('Monthly-CF'!$G74+1),0) -> 0 | P74: =IF(AND(P$10>='Monthly-CF'!$F74,P$10<='Monthly-CF'!$H74),'Monthly-CF'!$E74/('Monthly-CF'!$G74+1),0) -> 0 | Q74: =IF(AND(Q$10>='Monthly-CF'!$F74,Q$10<='Monthly-CF'!$H74),'Monthly-CF'!$E74/('Monthly-CF'!$G74+1),0) -> 0 | R74: =IF(AND(R$10>='Monthly-CF'!$F74,R$10<='Monthly-CF'!$H74),'Monthly-CF'!$E74/('Monthly-CF'!$G74+1),0) -> 0 | S74: =IF(AND(S$10>='Monthly-CF'!$F74,S$10<='Monthly-CF'!$H74),'Monthly-CF'!$E74/('Monthly-CF'!$G74+1),0) -> -130225.87 | ... EA74: =IF(AND(EA$10>='Monthly-CF'!$F74,EA$10<='Monthly-CF'!$H74),'Monthly-CF'!$E74/('Monthly-CF'!$G74+1),0) -> 0 | EC74: x
D75: Lease Up Costs | E75: =-'Budget Detail'!K28 -> -300000 | F75: 16 | G75: 3 | H75: =F75+G75 -> 19 | I75: =SUM(K75:EA75) -> -300000 | L75: =IF(AND(L$10>='Monthly-CF'!$F75,L$10<='Monthly-CF'!$H75),'Monthly-CF'!$E75/('Monthly-CF'!$G75+1),0) -> 0 | M75: =IF(AND(M$10>='Monthly-CF'!$F75,M$10<='Monthly-CF'!$H75),'Monthly-CF'!$E75/('Monthly-CF'!$G75+1),0) -> 0 | N75: =IF(AND(N$10>='Monthly-CF'!$F75,N$10<='Monthly-CF'!$H75),'Monthly-CF'!$E75/('Monthly-CF'!$G75+1),0) -> 0 | O75: =IF(AND(O$10>='Monthly-CF'!$F75,O$10<='Monthly-CF'!$H75),'Monthly-CF'!$E75/('Monthly-CF'!$G75+1),0) -> 0 | P75: =IF(AND(P$10>='Monthly-CF'!$F75,P$10<='Monthly-CF'!$H75),'Monthly-CF'!$E75/('Monthly-CF'!$G75+1),0) -> 0 | Q75: =IF(AND(Q$10>='Monthly-CF'!$F75,Q$10<='Monthly-CF'!$H75),'Monthly-CF'!$E75/('Monthly-CF'!$G75+1),0) -> 0 | R75: =IF(AND(R$10>='Monthly-CF'!$F75,R$10<='Monthly-CF'!$H75),'Monthly-CF'!$E75/('Monthly-CF'!$G75+1),0) -> 0 | S75: =IF(AND(S$10>='Monthly-CF'!$F75,S$10<='Monthly-CF'!$H75),'Monthly-CF'!$E75/('Monthly-CF'!$G75+1),0) -> 0 | ... EA75: =IF(AND(EA$10>='Monthly-CF'!$F75,EA$10<='Monthly-CF'!$H75),'Monthly-CF'!$E75/('Monthly-CF'!$G75+1),0) -> 0 | EC75: x
D76: Phase 1 Development Costs | I76: =SUM(K76:EA76) -> -54984255 | L76: =SUM(L69:L75) -> -5200000 | M76: =SUM(M69:M75) -> -391153.01 | N76: =SUM(N69:N75) -> -2750737.3 | O76: =SUM(O69:O75) -> -2750737.3 | P76: =SUM(P69:P75) -> -2750737.3 | Q76: =SUM(Q69:Q75) -> -2750737.3 | R76: =SUM(R69:R75) -> -2750737.3 | S76: =SUM(S69:S75) -> -3128392.3 | ... EA76: =SUM(EA69:EA75) -> 0 | EC76: x
EC77: x
D78: Project Costs Phase 2: | F78: Start | G78: Dur. | H78: End | EC78: x
D79: Land | E79: =-SUMIFS('Budget Detail'!$J$9:$J$77,'Budget Detail'!$D$9:$D$77,'Monthly-CF'!D79) -> 0 | F79: 0 | G79: 0 | H79: =F79+G79 -> 0 | I79: =SUM(K79:EA79) -> 0 | L79: =IF(AND(L$10>='Monthly-CF'!$F79,L$10<='Monthly-CF'!$H79),'Monthly-CF'!$E79/('Monthly-CF'!$G79),0) -> 0 | M79: =IF(AND(M$10>='Monthly-CF'!$F79,M$10<='Monthly-CF'!$H79),'Monthly-CF'!$E79/('Monthly-CF'!$G79),0) -> 0 | N79: =IF(AND(N$10>='Monthly-CF'!$F79,N$10<='Monthly-CF'!$H79),'Monthly-CF'!$E79/('Monthly-CF'!$G79),0) -> 0 | O79: =IF(AND(O$10>='Monthly-CF'!$F79,O$10<='Monthly-CF'!$H79),'Monthly-CF'!$E79/('Monthly-CF'!$G79),0) -> 0 | P79: =IF(AND(P$10>='Monthly-CF'!$F79,P$10<='Monthly-CF'!$H79),'Monthly-CF'!$E79/('Monthly-CF'!$G79),0) -> 0 | Q79: =IF(AND(Q$10>='Monthly-CF'!$F79,Q$10<='Monthly-CF'!$H79),'Monthly-CF'!$E79/('Monthly-CF'!$G79),0) -> 0 | R79: =IF(AND(R$10>='Monthly-CF'!$F79,R$10<='Monthly-CF'!$H79),'Monthly-CF'!$E79/('Monthly-CF'!$G79),0) -> 0 | S79: =IF(AND(S$10>='Monthly-CF'!$F79,S$10<='Monthly-CF'!$H79),'Monthly-CF'!$E79/('Monthly-CF'!$G79),0) -> 0 | ... EA79: =IF(AND(EA$10>='Monthly-CF'!$F79,EA$10<='Monthly-CF'!$H79),'Monthly-CF'!$E79/('Monthly-CF'!$G79),0) -> 0 | EC79: x
D80: Hard Costs | E80: =-SUMIFS('Budget Detail'!$J$9:$J$77,'Budget Detail'!$D$9:$D$77,'Monthly-CF'!D80) -> 0 | F80: 0 | G80: 0 | H80: =F80+G80 -> 0 | I80: =SUM(K80:EA80) -> 0 | L80: =IF(AND(L$10>='Monthly-CF'!$F80,L$10<='Monthly-CF'!$H80),'Monthly-CF'!$E80/('Monthly-CF'!$G80+1),0) -> 0 | M80: =IF(AND(M$10>='Monthly-CF'!$F80,M$10<='Monthly-CF'!$H80),'Monthly-CF'!$E80/('Monthly-CF'!$G80+1),0) -> 0 | N80: =IF(AND(N$10>='Monthly-CF'!$F80,N$10<='Monthly-CF'!$H80),'Monthly-CF'!$E80/('Monthly-CF'!$G80+1),0) -> 0 | O80: =IF(AND(O$10>='Monthly-CF'!$F80,O$10<='Monthly-CF'!$H80),'Monthly-CF'!$E80/('Monthly-CF'!$G80+1),0) -> 0 | P80: =IF(AND(P$10>='Monthly-CF'!$F80,P$10<='Monthly-CF'!$H80),'Monthly-CF'!$E80/('Monthly-CF'!$G80+1),0) -> 0 | Q80: =IF(AND(Q$10>='Monthly-CF'!$F80,Q$10<='Monthly-CF'!$H80),'Monthly-CF'!$E80/('Monthly-CF'!$G80+1),0) -> 0 | R80: =IF(AND(R$10>='Monthly-CF'!$F80,R$10<='Monthly-CF'!$H80),'Monthly-CF'!$E80/('Monthly-CF'!$G80+1),0) -> 0 | S80: =IF(AND(S$10>='Monthly-CF'!$F80,S$10<='Monthly-CF'!$H80),'Monthly-CF'!$E80/('Monthly-CF'!$G80+1),0) -> 0 | ... EA80: =IF(AND(EA$10>='Monthly-CF'!$F80,EA$10<='Monthly-CF'!$H80),'Monthly-CF'!$E80/('Monthly-CF'!$G80+1),0) -> 0 | EC80: x
D81: Soft Costs (Excl. D/S) | E81: =-SUMIFS('Budget Detail'!$J$9:$J$77,'Budget Detail'!$D$9:$D$77,'Monthly-CF'!D81) -> 0 | F81: 0 | G81: 0 | H81: =F81+G81 -> 0 | I81: =SUM(K81:EA81) -> 0 | L81: =IF(AND(L$10>='Monthly-CF'!$F81,L$10<='Monthly-CF'!$H81),'Monthly-CF'!$E81/('Monthly-CF'!$G81+1),0) -> 0 | EC81: x
D82: Dev Fess | E82: =-SUMIFS('Budget Detail'!$J$9:$J$77,'Budget Detail'!$D$9:$D$77,'Monthly-CF'!D82) -> 0 | F82: =F80 -> 0 | G82: =G80 -> 0 | H82: =F82+G82 -> 0 | I82: =SUM(K82:EA82) -> 0 | L82: =IF(AND(L$10>='Monthly-CF'!$F82,L$10<='Monthly-CF'!$H82),'Monthly-CF'!$E82/('Monthly-CF'!$G82+1),0) -> 0 | M82: =IF(AND(M$10>='Monthly-CF'!$F82,M$10<='Monthly-CF'!$H82),'Monthly-CF'!$E82/('Monthly-CF'!$G82+1),0) -> 0 | N82: =IF(AND(N$10>='Monthly-CF'!$F82,N$10<='Monthly-CF'!$H82),'Monthly-CF'!$E82/('Monthly-CF'!$G82+1),0) -> 0 | O82: =IF(AND(O$10>='Monthly-CF'!$F82,O$10<='Monthly-CF'!$H82),'Monthly-CF'!$E82/('Monthly-CF'!$G82+1),0) -> 0 | P82: =IF(AND(P$10>='Monthly-CF'!$F82,P$10<='Monthly-CF'!$H82),'Monthly-CF'!$E82/('Monthly-CF'!$G82+1),0) -> 0 | Q82: =IF(AND(Q$10>='Monthly-CF'!$F82,Q$10<='Monthly-CF'!$H82),'Monthly-CF'!$E82/('Monthly-CF'!$G82+1),0) -> 0 | R82: =IF(AND(R$10>='Monthly-CF'!$F82,R$10<='Monthly-CF'!$H82),'Monthly-CF'!$E82/('Monthly-CF'!$G82+1),0) -> 0 | S82: =IF(AND(S$10>='Monthly-CF'!$F82,S$10<='Monthly-CF'!$H82),'Monthly-CF'!$E82/('Monthly-CF'!$G82+1),0) -> 0 | ... EA82: =IF(AND(EA$10>='Monthly-CF'!$F82,EA$10<='Monthly-CF'!$H82),'Monthly-CF'!$E82/('Monthly-CF'!$G82+1),0) -> 0 | EC82: x
D83: Loan Fees | E83: =Assumptions!E62 -> 0.0075 | I83: =SUM(K83:EA83) -> 0 | L83: =IF(L114=1,-$I$116*$E$83,0) -> 0 | EC83: x
D84: Interest | E84: =Assumptions!E63 -> 0 | I84: =SUM(K84:EA84) -> 0 | L84: =-L115*($E$84/12) -> 0 | EC84: x
D85: Lease Up Costs | I85: =SUM(K85:EA85) -> 0 | EC85: x
D86: Phase 2 Development Costs | I86: =SUM(K86:EA86) -> 0 | L86: =SUM(L79:L85) -> 0 | M86: =SUM(M79:M85) -> 0 | N86: =SUM(N79:N85) -> 0 | O86: =SUM(O79:O85) -> 0 | P86: =SUM(P79:P85) -> 0 | Q86: =SUM(Q79:Q85) -> 0 | R86: =SUM(R79:R85) -> 0 | S86: =SUM(S79:S85) -> 0 | ... EA86: =SUM(EA79:EA85) -> 0 | EC86: x
EC87: x
D88: Project Costs Combined: | EC88: x
D89: Land | I89: =SUM(K89:EA89) -> -5200000 | K89: =K69+K79 -> 0 | L89: =L69+L79 -> -5200000 | M89: =M69+M79 -> 0 | N89: =N69+N79 -> 0 | O89: =O69+O79 -> 0 | P89: =P69+P79 -> 0 | Q89: =Q69+Q79 -> 0 | R89: =R69+R79 -> 0 | ... EA89: =EA69+EA79 -> 0 | EC89: x
D90: Hard Costs | I90: =SUM(K90:EA90) -> -38440298 | K90: =K70+K80 -> 0 | L90: =L70+L80 -> 0 | M90: =M70+M80 -> 0 | N90: =N70+N80 -> -2261194 | O90: =O70+O80 -> -2261194 | P90: =P70+P80 -> -2261194 | Q90: =Q70+Q80 -> -2261194 | R90: =R70+R80 -> -2261194 | ... EA90: =EA70+EA80 -> 0 | EC90: x
D91: Soft Costs | I91: =SUM(K91:EA91) -> -6649601.1 | K91: =K71+K81 -> 0 | L91: =L71+L81 -> 0 | M91: =M71+M81 -> -391153.01 | N91: =N71+N81 -> -391153.01 | O91: =O71+O81 -> -391153.01 | P91: =P71+P81 -> -391153.01 | Q91: =Q71+Q81 -> -391153.01 | R91: =R71+R81 -> -391153.01 | ... EA91: =EA71+EA81 -> 0 | EC91: x
D92: Dev Fess | I92: =SUM(K92:EA92) -> -1672635.6 | K92: =K72+K82 -> 0 | L92: =L72+L82 -> 0 | M92: =M72+M82 -> 0 | N92: =N72+N82 -> -98390.332 | O92: =O72+O82 -> -98390.332 | P92: =P72+P82 -> -98390.332 | Q92: =Q72+Q82 -> -98390.332 | R92: =R72+R82 -> -98390.332 | ... EA92: =EA72+EA82 -> 0 | EC92: x
D93: Loan Fees | I93: =SUM(K93:EA93) -> -247429.15 | K93: =K73+K83 -> 0 | L93: =L73+L83 -> 0 | M93: =M73+M83 -> 0 | N93: =N73+N83 -> 0 | O93: =O73+O83 -> 0 | P93: =P73+P83 -> 0 | Q93: =Q73+Q83 -> 0 | R93: =R73+R83 -> 0 | ... EA93: =EA73+EA83 -> 0 | EC93: x
D94: Interest | I94: =SUM(K94:EA94) -> -2474291.5 | K94: =K74+K84 -> 0 | L94: =L74+L84 -> 0 | M94: =M74+M84 -> 0 | N94: =N74+N84 -> 0 | O94: =O74+O84 -> 0 | P94: =P74+P84 -> 0 | Q94: =Q74+Q84 -> 0 | R94: =R74+R84 -> 0 | ... EA94: =EA74+EA84 -> 0 | EC94: x
D95: Lease Up Costs | I95: =SUM(K95:EA95) -> -300000 | K95: =K75+K85 -> 0 | L95: =L75+L85 -> 0 | M95: =M75+M85 -> 0 | N95: =N75+N85 -> 0 | O95: =O75+O85 -> 0 | P95: =P75+P85 -> 0 | Q95: =Q75+Q85 -> 0 | R95: =R75+R85 -> 0 | ... EA95: =EA75+EA85 -> 0 | EC95: x
D96: Total Project Costs | I96: =SUM(K96:EA96) -> -54984255 | K96: =SUM(K89:K95) -> 0 | L96: =SUM(L89:L95) -> -5200000 | M96: =SUM(M89:M95) -> -391153.01 | N96: =SUM(N89:N95) -> -2750737.3 | O96: =SUM(O89:O95) -> -2750737.3 | P96: =SUM(P89:P95) -> -2750737.3 | Q96: =SUM(Q89:Q95) -> -2750737.3 | R96: =SUM(R89:R95) -> -2750737.3 | ... EA96: =SUM(EA89:EA95) -> 0 | EC96: x
EC97: x
D98: Unlevered Cash Flows | I98: =SUM(K98:EA98) -> 65495876 | K98: =K37+K96+K62+K58+K66 -> 0 | L98: =L37+L96+L62+L58+L66+L44 -> -5200000 | M98: =M37+M96+M62+M58+M66+M44 -> -391153.01 | N98: =N37+N96+N62+N58+N66+N44 -> -2750737.3 | O98: =O37+O96+O62+O58+O66+O44 -> -2750737.3 | P98: =P37+P96+P62+P58+P66+P44 -> -2750737.3 | Q98: =Q37+Q96+Q62+Q58+Q66+Q44 -> -2750737.3 | R98: =R37+R96+R62+R58+R66+R44 -> -2750737.3 | S98: =S37+S96+S62+S58+S66+S44 -> -3128392.3 | ... EA98: =EA37+EA96+EA62+EA58+EA66+EA44 -> 85882177 | EC98: x
D99: Unlevered IRR | E99: =XIRR(L98:EA98,L8:EA8) -> 0.10644599 | EC99: x
D100: Unlevered EQM | E100: =(F105+I98)/I98 -> 1.3358029 | EC100: x
...

Sheet Cash Flow MH
DT1: x
B2: ='Assumptions MH'!$B$2 -> 1425 4th Ave (Nashville, TN) | Mint House Management Agreement Model | DT2: x
B3: Cash Flow MH | DT3: x
DT4: x
B5: Year # | D5: =ROUNDUP(D7/12,) -> 1 | E5: =ROUNDUP(E7/12,) -> 1 | F5: =ROUNDUP(F7/12,) -> 1 | G5: =ROUNDUP(G7/12,) -> 1 | H5: =ROUNDUP(H7/12,) -> 1 | I5: =ROUNDUP(I7/12,) -> 1 | J5: =ROUNDUP(J7/12,) -> 1 | K5: =ROUNDUP(K7/12,) -> 1 | ... DS5: =ROUNDUP(DS7/12,) -> 10 | DT5: x
B6: Year | D6: =YEAR(D8) -> 2025 | E6: =YEAR(E8) -> 2025 | F6: =YEAR(F8) -> 2025 | G6: =YEAR(G8) -> 2025 | H6: =YEAR(H8) -> 2025 | I6: =YEAR(I8) -> 2025 | J6: =YEAR(J8) -> 2025 | K6: =YEAR(K8) -> 2025 | ... DS6: =YEAR(DS8) -> 2034 | DT6: x
B7: Month # | D7: =COUNTA($D8:D8) -> 1 | E7: =COUNTA($D8:E8) -> 2 | F7: =COUNTA($D8:F8) -> 3 | G7: =COUNTA($D8:G8) -> 4 | H7: =COUNTA($D8:H8) -> 5 | I7: =COUNTA($D8:I8) -> 6 | J7: =COUNTA($D8:J8) -> 7 | K7: =COUNTA($D8:K8) -> 8 | ... DS7: =COUNTA($D8:DS8) -> 120 | DT7: x
B8: Month Ending | D8: =EOMONTH('Assumptions MH'!G20,0) -> 45688 | E8: =EOMONTH(D8,1) -> 45716 | F8: =EOMONTH(E8,1) -> 45747 | G8: =EOMONTH(F8,1) -> 45777 | H8: =EOMONTH(G8,1) -> 45808 | I8: =EOMONTH(H8,1) -> 45838 | J8: =EOMONTH(I8,1) -> 45869 | K8: =EOMONTH(J8,1) -> 45900 | L8: =EOMONTH(K8,1) -> 45930 | ... DS8: =EOMONTH(DR8,1) -> 49309 | DT8: x
DT9: x
A10: x | B10: General Underwriting & Growth Assumptions | DT10: x
B11: Multifamily Rent Growth | D11: ='Assumptions MH'!$T7 -> 0.03 | E11: ='Assumptions MH'!$T7 -> 0.03 | F11: ='Assumptions MH'!$T7 -> 0.03 | G11: ='Assumptions MH'!$T7 -> 0.03 | H11: ='Assumptions MH'!$T7 -> 0.03 | I11: ='Assumptions MH'!$T7 -> 0.03 | J11: ='Assumptions MH'!$T7 -> 0.03 | K11: ='Assumptions MH'!$T7 -> 0.03 | ... DS11: ='Assumptions MH'!$T7 -> 0.03 | DT11: x
B12: Other Revenue Growth | D12: ='Assumptions MH'!$T8 -> 0.03 | E12: ='Assumptions MH'!$T8 -> 0.03 | F12: ='Assumptions MH'!$T8 -> 0.03 | G12: ='Assumptions MH'!$T8 -> 0.03 | H12: ='Assumptions MH'!$T8 -> 0.03 | I12: ='Assumptions MH'!$T8 -> 0.03 | J12: ='Assumptions MH'!$T8 -> 0.03 | K12: ='Assumptions MH'!$T8 -> 0.03 | ... DS12: ='Assumptions MH'!$T8 -> 0.03 | DT12: x
B13: Expense Growth | D13: ='Assumptions MH'!$T9 -> 0.03 | E13: ='Assumptions MH'!$T9 -> 0.03 | F13: ='Assumptions MH'!$T9 -> 0.03 | G13: ='Assumptions MH'!$T9 -> 0.03 | H13: ='Assumptions MH'!$T9 -> 0.03 | I13: ='Assumptions MH'!$T9 -> 0.03 | J13: ='Assumptions MH'!$T9 -> 0.03 | K13: ='Assumptions MH'!$T9 -> 0.03 | ... DS13: ='Assumptions MH'!$T9 -> 0.03 | DT13: x
B14: Min. Monthly Payment | D14: ='Assumptions MH'!$Z6 -> 0.03 | E14: ='Assumptions MH'!$Z6 -> 0.03 | F14: ='Assumptions MH'!$Z6 -> 0.03 | G14: ='Assumptions MH'!$Z6 -> 0.03 | H14: ='Assumptions MH'!$Z6 -> 0.03 | I14: ='Assumptions MH'!$Z6 -> 0.03 | J14: ='Assumptions MH'!$Z6 -> 0.03 | K14: ='Assumptions MH'!$Z6 -> 0.03 | ... DS14: ='Assumptions MH'!$Z6 -> 0.03 | DT14: x
B15: ADR Growth | D15: =INDEX('Assumptions MH'!$T$14:$T$23,MATCH('Cash Flow MH'!D$5,'Assumptions MH'!$S$14:$S$23,)) -> 0.03 | E15: =INDEX('Assumptions MH'!$T$14:$T$23,MATCH('Cash Flow MH'!E$5,'Assumptions MH'!$S$14:$S$23,)) -> 0.03 | F15: =INDEX('Assumptions MH'!$T$14:$T$23,MATCH('Cash Flow MH'!F$5,'Assumptions MH'!$S$14:$S$23,)) -> 0.03 | G15: =INDEX('Assumptions MH'!$T$14:$T$23,MATCH('Cash Flow MH'!G$5,'Assumptions MH'!$S$14:$S$23,)) -> 0.03 | H15: =INDEX('Assumptions MH'!$T$14:$T$23,MATCH('Cash Flow MH'!H$5,'Assumptions MH'!$S$14:$S$23,)) -> 0.03 | I15: =INDEX('Assumptions MH'!$T$14:$T$23,MATCH('Cash Flow MH'!I$5,'Assumptions MH'!$S$14:$S$23,)) -> 0.03 | J15: =INDEX('Assumptions MH'!$T$14:$T$23,MATCH('Cash Flow MH'!J$5,'Assumptions MH'!$S$14:$S$23,)) -> 0.03 | K15: =INDEX('Assumptions MH'!$T$14:$T$23,MATCH('Cash Flow MH'!K$5,'Assumptions MH'!$S$14:$S$23,)) -> 0.03 | ... DS15: =INDEX('Assumptions MH'!$T$14:$T$23,MATCH('Cash Flow MH'!DS$5,'Assumptions MH'!$S$14:$S$23,)) -> 0.03 | DT15: x
B16: Average Length of Stay (ALOS) | D16: =INDEX('Assumptions MH'!$T$27:$T$36,MATCH('Cash Flow MH'!D$5,'Assumptions MH'!$S$27:$S$36,)) -> 6 | E16: =INDEX('Assumptions MH'!$T$27:$T$36,MATCH('Cash Flow MH'!E$5,'Assumptions MH'!$S$27:$S$36,)) -> 6 | F16: =INDEX('Assumptions MH'!$T$27:$T$36,MATCH('Cash Flow MH'!F$5,'Assumptions MH'!$S$27:$S$36,)) -> 6 | G16: =INDEX('Assumptions MH'!$T$27:$T$36,MATCH('Cash Flow MH'!G$5,'Assumptions MH'!$S$27:$S$36,)) -> 6 | H16: =INDEX('Assumptions MH'!$T$27:$T$36,MATCH('Cash Flow MH'!H$5,'Assumptions MH'!$S$27:$S$36,)) -> 6 | I16: =INDEX('Assumptions MH'!$T$27:$T$36,MATCH('Cash Flow MH'!I$5,'Assumptions MH'!$S$27:$S$36,)) -> 6 | J16: =INDEX('Assumptions MH'!$T$27:$T$36,MATCH('Cash Flow MH'!J$5,'Assumptions MH'!$S$27:$S$36,)) -> 6 | K16: =INDEX('Assumptions MH'!$T$27:$T$36,MATCH('Cash Flow MH'!K$5,'Assumptions MH'!$S$27:$S$36,)) -> 6 | ... DS16: =INDEX('Assumptions MH'!$T$27:$T$36,MATCH('Cash Flow MH'!DS$5,'Assumptions MH'!$S$27:$S$36,)) -> 6 | DT16: x
DT17: x
A18: x | B18: Ramp Assumptions | DT18: x
B19: Stabilized Occupancy | D19: =+'Assumptions MH'!$O$9 -> 0.7 | E19: =+'Assumptions MH'!$O$9 -> 0.7 | F19: =+'Assumptions MH'!$O$9 -> 0.7 | G19: =+'Assumptions MH'!$O$9 -> 0.7 | H19: =+'Assumptions MH'!$O$9 -> 0.7 | I19: =+'Assumptions MH'!$O$9 -> 0.7 | J19: =+'Assumptions MH'!$O$9 -> 0.7 | K19: =+'Assumptions MH'!$O$9 -> 0.7 | ... DS19: =+'Assumptions MH'!$O$9 -> 0.7 | DT19: x
B20: Percent of Stabilized Occupancy | D20: =+'Assumptions MH'!L31 -> 0.35 | E20: =IFERROR(MIN(D20+IF(AND(E$7>='Assumptions MH'!$I$34,'Cash Flow MH'!E$7<='Assumptions MH'!$J$34),'Assumptions MH'!$K$34,'Assumptions MH'!$K$35),1),1) -> 0.4125 | F20: =IFERROR(MIN(E20+IF(AND(F$7>='Assumptions MH'!$I$34,'Cash Flow MH'!F$7<='Assumptions MH'!$J$34),'Assumptions MH'!$K$34,'Assumptions MH'!$K$35),1),1) -> 0.475 | G20: =IFERROR(MIN(F20+IF(AND(G$7>='Assumptions MH'!$I$34,'Cash Flow MH'!G$7<='Assumptions MH'!$J$34),'Assumptions MH'!$K$34,'Assumptions MH'!$K$35),1),1) -> 0.5375 | H20: =IFERROR(MIN(G20+IF(AND(H$7>='Assumptions MH'!$I$34,'Cash Flow MH'!H$7<='Assumptions MH'!$J$34),'Assumptions MH'!$K$34,'Assumptions MH'!$K$35),1),1) -> 0.6 | I20: =IFERROR(MIN(H20+IF(AND(I$7>='Assumptions MH'!$I$34,'Cash Flow MH'!I$7<='Assumptions MH'!$J$34),'Assumptions MH'!$K$34,'Assumptions MH'!$K$35),1),1) -> 0.6625 | J20: =IFERROR(MIN(I20+IF(AND(J$7>='Assumptions MH'!$I$34,'Cash Flow MH'!J$7<='Assumptions MH'!$J$34),'Assumptions MH'!$K$34,'Assumptions MH'!$K$35),1),1) -> 0.725 | K20: =IFERROR(MIN(J20+IF(AND(K$7>='Assumptions MH'!$I$34,'Cash Flow MH'!K$7<='Assumptions MH'!$J$34),'Assumptions MH'!$K$34,'Assumptions MH'!$K$35),1),1) -> 0.7875 | L20: =IFERROR(MIN(K20+IF(AND(L$7>='Assumptions MH'!$I$34,'Cash Flow MH'!L$7<='Assumptions MH'!$J$34),'Assumptions MH'!$K$34,'Assumptions MH'!$K$35),1),1) -> 0.80875 | ... DS20: =IFERROR(MIN(DR20+IF(AND(DS$7>='Assumptions MH'!$I$34,'Cash Flow MH'!DS$7<='Assumptions MH'!$J$34),'Assumptions MH'!$K$34,'Assumptions MH'!$K$35),1),1) -> 1 | DT20: x
B21: Occupancy Seasonality | D21: =INDEX('Seasonality MH'!$C$9:$N$9,MATCH(MONTH('Cash Flow MH'!D$8),'Seasonality MH'!$C$7:$N$7,)) -> 0.78405741 | E21: =INDEX('Seasonality MH'!$C$9:$N$9,MATCH(MONTH('Cash Flow MH'!E$8),'Seasonality MH'!$C$7:$N$7,)) -> 0.95399205 | F21: =INDEX('Seasonality MH'!$C$9:$N$9,MATCH(MONTH('Cash Flow MH'!F$8),'Seasonality MH'!$C$7:$N$7,)) -> 1.0660003 | G21: =INDEX('Seasonality MH'!$C$9:$N$9,MATCH(MONTH('Cash Flow MH'!G$8),'Seasonality MH'!$C$7:$N$7,)) -> 1.0713828 | H21: =INDEX('Seasonality MH'!$C$9:$N$9,MATCH(MONTH('Cash Flow MH'!H$8),'Seasonality MH'!$C$7:$N$7,)) -> 1.0662566 | I21: =INDEX('Seasonality MH'!$C$9:$N$9,MATCH(MONTH('Cash Flow MH'!I$8),'Seasonality MH'!$C$7:$N$7,)) -> 1.0598488 | J21: =INDEX('Seasonality MH'!$C$9:$N$9,MATCH(MONTH('Cash Flow MH'!J$8),'Seasonality MH'!$C$7:$N$7,)) -> 1.0229399 | K21: =INDEX('Seasonality MH'!$C$9:$N$9,MATCH(MONTH('Cash Flow MH'!K$8),'Seasonality MH'!$C$7:$N$7,)) -> 1.0083301 | ... DS21: =INDEX('Seasonality MH'!$C$9:$N$9,MATCH(MONTH('Cash Flow MH'!DS$8),'Seasonality MH'!$C$7:$N$7,)) -> 0.84147123 | DT21: x
B22: Base ADR | D22: =+'Assumptions MH'!$O$8*(1+D15)^(D5-1) -> 271 | E22: =+'Assumptions MH'!$O$8*(1+E15)^(E5-1) -> 271 | F22: =+'Assumptions MH'!$O$8*(1+F15)^(F5-1) -> 271 | G22: =+'Assumptions MH'!$O$8*(1+G15)^(G5-1) -> 271 | H22: =+'Assumptions MH'!$O$8*(1+H15)^(H5-1) -> 271 | I22: =+'Assumptions MH'!$O$8*(1+I15)^(I5-1) -> 271 | J22: =+'Assumptions MH'!$O$8*(1+J15)^(J5-1) -> 271 | K22: =+'Assumptions MH'!$O$8*(1+K15)^(K5-1) -> 271 | ... DS22: =+'Assumptions MH'!$O$8*(1+DS15)^(DS5-1) -> 353.59353 | DT22: x
B23: ADR Seasonality | D23: =INDEX('Seasonality MH'!$C$15:$N$15,MATCH(MONTH('Cash Flow MH'!D$8),'Seasonality MH'!$C$13:$N$13,)) -> 0.88111218 | E23: =INDEX('Seasonality MH'!$C$15:$N$15,MATCH(MONTH('Cash Flow MH'!E$8),'Seasonality MH'!$C$13:$N$13,)) -> 0.96163585 | F23: =INDEX('Seasonality MH'!$C$15:$N$15,MATCH(MONTH('Cash Flow MH'!F$8),'Seasonality MH'!$C$13:$N$13,)) -> 1.0162554 | G23: =INDEX('Seasonality MH'!$C$15:$N$15,MATCH(MONTH('Cash Flow MH'!G$8),'Seasonality MH'!$C$13:$N$13,)) -> 1.034366 | H23: =INDEX('Seasonality MH'!$C$15:$N$15,MATCH(MONTH('Cash Flow MH'!H$8),'Seasonality MH'!$C$13:$N$13,)) -> 1.0278752 | I23: =INDEX('Seasonality MH'!$C$15:$N$15,MATCH(MONTH('Cash Flow MH'!I$8),'Seasonality MH'!$C$13:$N$13,)) -> 1.0840336 | J23: =INDEX('Seasonality MH'!$C$15:$N$15,MATCH(MONTH('Cash Flow MH'!J$8),'Seasonality MH'!$C$13:$N$13,)) -> 0.95598679 | K23: =INDEX('Seasonality MH'!$C$15:$N$15,MATCH(MONTH('Cash Flow MH'!K$8),'Seasonality MH'!$C$13:$N$13,)) -> 0.96444178 | ... DS23: =INDEX('Seasonality MH'!$C$15:$N$15,MATCH(MONTH('Cash Flow MH'!DS$8),'Seasonality MH'!$C$13:$N$13,)) -> 0.93331739 | DT23: x
B24: Mint House Units Onboarded | D24: =+'Assumptions MH'!$G31*(D$7=1) -> 131 | E24: =+'Assumptions MH'!$G31*(E$7=1) -> 0 | F24: =+'Assumptions MH'!$G31*(F$7=1) -> 0 | G24: =+'Assumptions MH'!$G31*(G$7=1) -> 0 | H24: =+'Assumptions MH'!$G31*(H$7=1) -> 0 | I24: =+'Assumptions MH'!$G31*(I$7=1) -> 0 | J24: =+'Assumptions MH'!$G31*(J$7=1) -> 0 | K24: =+'Assumptions MH'!$G31*(K$7=1) -> 0 | ... DS24: =+'Assumptions MH'!$G31*(DS$7=1) -> 0 | DT24: x
DT25: x
A26: x | B26: Revenue Drivers | DT26: x
B27: Units | D27: =SUM($D24:D24) -> 131 | E27: =SUM($D24:E24) -> 131 | F27: =SUM($D24:F24) -> 131 | G27: =SUM($D24:G24) -> 131 | H27: =SUM($D24:H24) -> 131 | I27: =SUM($D24:I24) -> 131 | J27: =SUM($D24:J24) -> 131 | K27: =SUM($D24:K24) -> 131 | ... DS27: =SUM($D24:DS24) -> 131 | DT27: x
B28: Nights per Month | D28: =+_xlfn.DAYS(D8,'Assumptions MH'!$G$20-1) -> 31 | E28: =+_xlfn.DAYS(E8,D8) -> 28 | F28: =+_xlfn.DAYS(F8,E8) -> 31 | G28: =+_xlfn.DAYS(G8,F8) -> 30 | H28: =+_xlfn.DAYS(H8,G8) -> 31 | I28: =+_xlfn.DAYS(I8,H8) -> 30 | J28: =+_xlfn.DAYS(J8,I8) -> 31 | K28: =+_xlfn.DAYS(K8,J8) -> 31 | L28: =+_xlfn.DAYS(L8,K8) -> 30 | ... DS28: =+_xlfn.DAYS(DS8,DR8) -> 31 | DT28: x
B29: Available Room Nights | D29: =D28*D27 -> 4061 | E29: =E28*E27 -> 3668 | F29: =+_xlfn.DAYS(F8,E8)*F27 -> 4061 | G29: =+_xlfn.DAYS(G8,F8)*G27 -> 3930 | H29: =+_xlfn.DAYS(H8,G8)*H27 -> 4061 | I29: =+_xlfn.DAYS(I8,H8)*I27 -> 3930 | J29: =+_xlfn.DAYS(J8,I8)*J27 -> 4061 | K29: =+_xlfn.DAYS(K8,J8)*K27 -> 4061 | L29: =+_xlfn.DAYS(L8,K8)*L27 -> 3930 | M29: =+_xlfn.DAYS(M8,L8)*M27 -> 4061 | ... DS29: =+_xlfn.DAYS(DS8,DR8)*DS27 -> 4061 | DT29: x
B30: Occupied Room Nights | D30: =MIN(D29,D19*D20*D21*D29) -> 780.094 | E30: =MIN(E29,E19*E20*E21*E29) -> 1010.4064 | F30: =MIN(F29,F19*F20*F21*F29) -> 1439.4015 | G30: =MIN(G29,G19*G20*G21*G29) -> 1584.2136 | H30: =MIN(H29,H19*H20*H21*H29) -> 1818.6285 | I30: =MIN(I29,I19*I20*I21*I29) -> 1931.6141 | J30: =MIN(J29,J19*J20*J21*J29) -> 2108.2356 | K30: =MIN(K29,K19*K20*K21*K29) -> 2257.2743 | ... DS30: =MIN(DS29,DS19*DS20*DS21*DS29) -> 2392.0503 | DT30: x
B31: Occupancy | D31: =+D30/D29 -> 0.19209407 | E31: =+E30/E29 -> 0.27546521 | F31: =+F30/F29 -> 0.35444509 | G31: =+G30/G29 -> 0.40310778 | H31: =+H30/H29 -> 0.44782776 | I31: =+I30/I29 -> 0.49150487 | J31: =+J30/J29 -> 0.519142 | K31: =+K30/K29 -> 0.55584198 | ... DS31: =+DS30/DS29 -> 0.58902986 | DT31: x
B32: ADR | D32: =+D22*D23 -> 238.7814 | E32: =+E22*E23 -> 260.60332 | F32: =+F22*F23 -> 275.40521 | G32: =+G22*G23 -> 280.31319 | H32: =+H22*H23 -> 278.55418 | I32: =+I22*I23 -> 293.7731 | J32: =+J22*J23 -> 259.07242 | K32: =+K22*K23 -> 261.36372 | ... DS32: =+DS22*DS23 -> 330.01499 | DT32: x
B33: RevPAR | D33: =+D31*D32 -> 45.86849 | E33: =+E31*E32 -> 71.787146 | F33: =+F31*F32 -> 97.616024 | G33: =+G31*G32 -> 112.99643 | H33: =+H31*H32 -> 124.74429 | I33: =+I31*I32 -> 144.39091 | J33: =+J31*J32 -> 134.49537 | K33: =+K31*K32 -> 145.27693 | ... DS33: =+DS31*DS32 -> 194.38868 | DT33: x
DT34: x
A35: x | B35: Revenue | DT35: x
B36: Lodging Revenue | D36: =+D33*D29 -> 186271.94 | E36: =+E33*E29 -> 263315.25 | F36: =+F33*F29 -> 396418.67 | G36: =+G33*G29 -> 444075.96 | H36: =+H33*H29 -> 506586.58 | I36: =+I33*I29 -> 567456.27 | J36: =+J33*J29 -> 546185.71 | K36: =+K33*K29 -> 589969.61 | ... DS36: =+DS33*DS29 -> 789412.45 | DT36: x
B37: Parking Revenue | D37: =MIN(D30*'Assumptions MH'!$L$45,'Assumptions MH'!$L$41*'Assumptions MH'!$L$43*'Cash Flow MH'!D28)*'Assumptions MH'!$L$42*(1+D12)^('Cash Flow MH'!D5-1) -> 9361.128 | E37: =MIN(E30*'Assumptions MH'!$L$45,'Assumptions MH'!$L$41*'Assumptions MH'!$L$43*'Cash Flow MH'!E28)*'Assumptions MH'!$L$42*(1+E12)^('Cash Flow MH'!E5-1) -> 12124.876 | F37: =MIN(F30*'Assumptions MH'!$L$45,'Assumptions MH'!$L$41*'Assumptions MH'!$L$43*'Cash Flow MH'!F28)*'Assumptions MH'!$L$42*(1+F12)^('Cash Flow MH'!F5-1) -> 17272.818 | G37: =MIN(G30*'Assumptions MH'!$L$45,'Assumptions MH'!$L$41*'Assumptions MH'!$L$43*'Cash Flow MH'!G28)*'Assumptions MH'!$L$42*(1+G12)^('Cash Flow MH'!G5-1) -> 19010.563 | H37: =MIN(H30*'Assumptions MH'!$L$45,'Assumptions MH'!$L$41*'Assumptions MH'!$L$43*'Cash Flow MH'!H28)*'Assumptions MH'!$L$42*(1+H12)^('Cash Flow MH'!H5-1) -> 21823.542 | I37: =MIN(I30*'Assumptions MH'!$L$45,'Assumptions MH'!$L$41*'Assumptions MH'!$L$43*'Cash Flow MH'!I28)*'Assumptions MH'!$L$42*(1+I12)^('Cash Flow MH'!I5-1) -> 23179.37 | J37: =MIN(J30*'Assumptions MH'!$L$45,'Assumptions MH'!$L$41*'Assumptions MH'!$L$43*'Cash Flow MH'!J28)*'Assumptions MH'!$L$42*(1+J12)^('Cash Flow MH'!J5-1) -> 25298.828 | K37: =MIN(K30*'Assumptions MH'!$L$45,'Assumptions MH'!$L$41*'Assumptions MH'!$L$43*'Cash Flow MH'!K28)*'Assumptions MH'!$L$42*(1+K12)^('Cash Flow MH'!K5-1) -> 27087.292 | ... DS37: =MIN(DS30*'Assumptions MH'!$L$45,'Assumptions MH'!$L$41*'Assumptions MH'!$L$43*'Cash Flow MH'!DS28)*'Assumptions MH'!$L$42*(1+DS12)^('Cash Flow MH'!DS5-1) -> 37452.996 | DT37: x
B38: Total Property Revenue | D38: =SUM(D36:D37) -> 195633.07 | E38: =SUM(E36:E37) -> 275440.13 | F38: =SUM(F36:F37) -> 413691.49 | G38: =SUM(G36:G37) -> 463086.53 | H38: =SUM(H36:H37) -> 528410.12 | I38: =SUM(I36:I37) -> 590635.64 | J38: =SUM(J36:J37) -> 571484.54 | K38: =SUM(K36:K37) -> 617056.9 | ... DS38: =SUM(DS36:DS37) -> 826865.44 | DT38: x
DT39: x
A40: x | B40: Departmental Expenses | DT40: x
B41: Cleanings | D41: =(('Assumptions MH'!$Q$11*'Cash Flow MH'!D30)/D$16*((1+D$13)^('Cash Flow MH'!D5-1))) -> 8451.0184 | E41: =(('Assumptions MH'!$Q$11*'Cash Flow MH'!E30)/E$16*((1+E$13)^('Cash Flow MH'!E5-1))) -> 10946.069 | F41: =(('Assumptions MH'!$Q$11*'Cash Flow MH'!F30)/F$16*((1+F$13)^('Cash Flow MH'!F5-1))) -> 15593.516 | G41: =(('Assumptions MH'!$Q$11*'Cash Flow MH'!G30)/G$16*((1+G$13)^('Cash Flow MH'!G5-1))) -> 17162.314 | H41: =(('Assumptions MH'!$Q$11*'Cash Flow MH'!H30)/H$16*((1+H$13)^('Cash Flow MH'!H5-1))) -> 19701.809 | I41: =(('Assumptions MH'!$Q$11*'Cash Flow MH'!I30)/I$16*((1+I$13)^('Cash Flow MH'!I5-1))) -> 20925.82 | J41: =(('Assumptions MH'!$Q$11*'Cash Flow MH'!J30)/J$16*((1+J$13)^('Cash Flow MH'!J5-1))) -> 22839.22 | K41: =(('Assumptions MH'!$Q$11*'Cash Flow MH'!K30)/K$16*((1+K$13)^('Cash Flow MH'!K5-1))) -> 24453.805 | ... DS41: =(('Assumptions MH'!$Q$11*'Cash Flow MH'!DS30)/DS$16*((1+DS$13)^('Cash Flow MH'!DS5-1))) -> 33811.733 | DT41: x
B42: Consumables | D42: =(('Assumptions MH'!$Q$12*'Cash Flow MH'!D30)/D$16*((1+D$13)^('Cash Flow MH'!D5-1))) -> 1300.1567 | E42: =(('Assumptions MH'!$Q$12*'Cash Flow MH'!E30)/E$16*((1+E$13)^('Cash Flow MH'!E5-1))) -> 1684.0106 | F42: =(('Assumptions MH'!$Q$12*'Cash Flow MH'!F30)/F$16*((1+F$13)^('Cash Flow MH'!F5-1))) -> 2399.0025 | G42: =(('Assumptions MH'!$Q$12*'Cash Flow MH'!G30)/G$16*((1+G$13)^('Cash Flow MH'!G5-1))) -> 2640.356 | H42: =(('Assumptions MH'!$Q$12*'Cash Flow MH'!H30)/H$16*((1+H$13)^('Cash Flow MH'!H5-1))) -> 3031.0475 | I42: =(('Assumptions MH'!$Q$12*'Cash Flow MH'!I30)/I$16*((1+I$13)^('Cash Flow MH'!I5-1))) -> 3219.3569 | J42: =(('Assumptions MH'!$Q$12*'Cash Flow MH'!J30)/J$16*((1+J$13)^('Cash Flow MH'!J5-1))) -> 3513.7261 | K42: =(('Assumptions MH'!$Q$12*'Cash Flow MH'!K30)/K$16*((1+K$13)^('Cash Flow MH'!K5-1))) -> 3762.1238 | ... DS42: =(('Assumptions MH'!$Q$12*'Cash Flow MH'!DS30)/DS$16*((1+DS$13)^('Cash Flow MH'!DS5-1))) -> 5201.8051 | DT42: x
B43: OSE | D43: =(('Assumptions MH'!$Q$13*'Cash Flow MH'!D30)/D$16*((1+D$13)^('Cash Flow MH'!D5-1))) -> 2600.3133 | E43: =(('Assumptions MH'!$Q$13*'Cash Flow MH'!E30)/E$16*((1+E$13)^('Cash Flow MH'!E5-1))) -> 3368.0212 | F43: =(('Assumptions MH'!$Q$13*'Cash Flow MH'!F30)/F$16*((1+F$13)^('Cash Flow MH'!F5-1))) -> 4798.005 | G43: =(('Assumptions MH'!$Q$13*'Cash Flow MH'!G30)/G$16*((1+G$13)^('Cash Flow MH'!G5-1))) -> 5280.7119 | H43: =(('Assumptions MH'!$Q$13*'Cash Flow MH'!H30)/H$16*((1+H$13)^('Cash Flow MH'!H5-1))) -> 6062.0951 | I43: =(('Assumptions MH'!$Q$13*'Cash Flow MH'!I30)/I$16*((1+I$13)^('Cash Flow MH'!I5-1))) -> 6438.7138 | J43: =(('Assumptions MH'!$Q$13*'Cash Flow MH'!J30)/J$16*((1+J$13)^('Cash Flow MH'!J5-1))) -> 7027.4522 | K43: =(('Assumptions MH'!$Q$13*'Cash Flow MH'!K30)/K$16*((1+K$13)^('Cash Flow MH'!K5-1))) -> 7524.2477 | ... DS43: =(('Assumptions MH'!$Q$13*'Cash Flow MH'!DS30)/DS$16*((1+DS$13)^('Cash Flow MH'!DS5-1))) -> 10403.61 | DT43: x
B44: Guest Services - Labor | D44: ='Cash Flow MH'!D$27*'Assumptions MH'!$Q14*((1+D$13)^('Cash Flow MH'!D$5-1)) -> 39161.972 | E44: ='Cash Flow MH'!E$27*'Assumptions MH'!$Q14*((1+E$13)^('Cash Flow MH'!E$5-1)) -> 39161.972 | F44: ='Cash Flow MH'!F$27*'Assumptions MH'!$Q14*((1+F$13)^('Cash Flow MH'!F$5-1)) -> 39161.972 | G44: ='Cash Flow MH'!G$27*'Assumptions MH'!$Q14*((1+G$13)^('Cash Flow MH'!G$5-1)) -> 39161.972 | H44: ='Cash Flow MH'!H$27*'Assumptions MH'!$Q14*((1+H$13)^('Cash Flow MH'!H$5-1)) -> 39161.972 | I44: ='Cash Flow MH'!I$27*'Assumptions MH'!$Q14*((1+I$13)^('Cash Flow MH'!I$5-1)) -> 39161.972 | J44: ='Cash Flow MH'!J$27*'Assumptions MH'!$Q14*((1+J$13)^('Cash Flow MH'!J$5-1)) -> 39161.972 | K44: ='Cash Flow MH'!K$27*'Assumptions MH'!$Q14*((1+K$13)^('Cash Flow MH'!K$5-1)) -> 39161.972 | ... DS44: ='Cash Flow MH'!DS$27*'Assumptions MH'!$Q14*((1+DS$13)^('Cash Flow MH'!DS$5-1)) -> 51097.49 | DT44: x
B45: Parking | D45: =+D37*(1-'Assumptions MH'!$L$44) -> 1404.1692 | E45: =+E37*(1-'Assumptions MH'!$L$44) -> 1818.7315 | F45: =+F37*(1-'Assumptions MH'!$L$44) -> 2590.9227 | G45: =+G37*(1-'Assumptions MH'!$L$44) -> 2851.5844 | H45: =+H37*(1-'Assumptions MH'!$L$44) -> 3273.5313 | I45: =+I37*(1-'Assumptions MH'!$L$44) -> 3476.9054 | J45: =+J37*(1-'Assumptions MH'!$L$44) -> 3794.8242 | K45: =+K37*(1-'Assumptions MH'!$L$44) -> 4063.0937 | ... DS45: =+DS37*(1-'Assumptions MH'!$L$44) -> 5617.9495 | DT45: x
B46: Total Departmental Expenses | D46: =SUM(D41:D45) -> 52917.629 | E46: =SUM(E41:E45) -> 56978.804 | F46: =SUM(F41:F45) -> 64543.418 | G46: =SUM(G41:G45) -> 67096.938 | H46: =SUM(H41:H45) -> 71230.455 | I46: =SUM(I41:I45) -> 73222.768 | J46: =SUM(J41:J45) -> 76337.194 | K46: =SUM(K41:K45) -> 78965.242 | ... DS46: =SUM(DS41:DS45) -> 106132.59 | DT46: x
DT47: x
A48: x | B48: Department Profit | D48: =D38-D46 -> 142715.44 | E48: =E38-E46 -> 218461.32 | F48: =F38-F46 -> 349148.07 | G48: =G38-G46 -> 395989.59 | H48: =H38-H46 -> 457179.67 | I48: =I38-I46 -> 517412.87 | J48: =J38-J46 -> 495147.35 | K48: =K38-K46 -> 538091.66 | ... DS48: =DS38-DS46 -> 720732.86 | DT48: x
B49: Department Profit | D49: =D48/D38 -> 0.7295057 | E49: =E48/E38 -> 0.79313543 | F49: =F48/F38 -> 0.84398176 | G49: =G48/G38 -> 0.85510929 | H49: =H48/H38 -> 0.86519854 | I49: =I48/I38 -> 0.87602718 | J49: =J48/J38 -> 0.86642299 | K49: =K48/K38 -> 0.87202924 | ... DS49: =DS48/DS38 -> 0.87164467 | DT49: x
DT50: x
A51: x | B51: Undistributed Operating Expenses | DT51: x
B52: G&A: Salaries / Benefits | D52: ='Cash Flow MH'!D$27*'Assumptions MH'!$Q15*((1+D$13)^('Cash Flow MH'!D$5-1)) -> 37178.13 | E52: ='Cash Flow MH'!E$27*'Assumptions MH'!$Q15*((1+E$13)^('Cash Flow MH'!E$5-1)) -> 37178.13 | F52: ='Cash Flow MH'!F$27*'Assumptions MH'!$Q15*((1+F$13)^('Cash Flow MH'!F$5-1)) -> 37178.13 | G52: ='Cash Flow MH'!G$27*'Assumptions MH'!$Q15*((1+G$13)^('Cash Flow MH'!G$5-1)) -> 37178.13 | H52: ='Cash Flow MH'!H$27*'Assumptions MH'!$Q15*((1+H$13)^('Cash Flow MH'!H$5-1)) -> 37178.13 | I52: ='Cash Flow MH'!I$27*'Assumptions MH'!$Q15*((1+I$13)^('Cash Flow MH'!I$5-1)) -> 37178.13 | J52: ='Cash Flow MH'!J$27*'Assumptions MH'!$Q15*((1+J$13)^('Cash Flow MH'!J$5-1)) -> 37178.13 | K52: ='Cash Flow MH'!K$27*'Assumptions MH'!$Q15*((1+K$13)^('Cash Flow MH'!K$5-1)) -> 37178.13 | ... DS52: ='Cash Flow MH'!DS$27*'Assumptions MH'!$Q15*((1+DS$13)^('Cash Flow MH'!DS$5-1)) -> 48509.027 | DT52: x
B53: G&A: Operating Supplies | D53: ='Cash Flow MH'!D$27*'Assumptions MH'!$Q16*((1+D$13)^('Cash Flow MH'!D$5-1)) -> 655 | E53: ='Cash Flow MH'!E$27*'Assumptions MH'!$Q16*((1+E$13)^('Cash Flow MH'!E$5-1)) -> 655 | F53: ='Cash Flow MH'!F$27*'Assumptions MH'!$Q16*((1+F$13)^('Cash Flow MH'!F$5-1)) -> 655 | G53: ='Cash Flow MH'!G$27*'Assumptions MH'!$Q16*((1+G$13)^('Cash Flow MH'!G$5-1)) -> 655 | H53: ='Cash Flow MH'!H$27*'Assumptions MH'!$Q16*((1+H$13)^('Cash Flow MH'!H$5-1)) -> 655 | I53: ='Cash Flow MH'!I$27*'Assumptions MH'!$Q16*((1+I$13)^('Cash Flow MH'!I$5-1)) -> 655 | J53: ='Cash Flow MH'!J$27*'Assumptions MH'!$Q16*((1+J$13)^('Cash Flow MH'!J$5-1)) -> 655 | K53: ='Cash Flow MH'!K$27*'Assumptions MH'!$Q16*((1+K$13)^('Cash Flow MH'!K$5-1)) -> 655 | ... DS53: ='Cash Flow MH'!DS$27*'Assumptions MH'!$Q16*((1+DS$13)^('Cash Flow MH'!DS$5-1)) -> 854.62644 | DT53: x
B54: G&A: Shared Services | D54: ='Cash Flow MH'!D$27*'Assumptions MH'!$Q20*((1+D$13)^('Cash Flow MH'!D$5-1)) -> 19650 | E54: ='Cash Flow MH'!E$27*'Assumptions MH'!$Q20*((1+E$13)^('Cash Flow MH'!E$5-1)) -> 19650 | F54: ='Cash Flow MH'!F$27*'Assumptions MH'!$Q20*((1+F$13)^('Cash Flow MH'!F$5-1)) -> 19650 | G54: ='Cash Flow MH'!G$27*'Assumptions MH'!$Q20*((1+G$13)^('Cash Flow MH'!G$5-1)) -> 19650 | H54: ='Cash Flow MH'!H$27*'Assumptions MH'!$Q20*((1+H$13)^('Cash Flow MH'!H$5-1)) -> 19650 | I54: ='Cash Flow MH'!I$27*'Assumptions MH'!$Q20*((1+I$13)^('Cash Flow MH'!I$5-1)) -> 19650 | J54: ='Cash Flow MH'!J$27*'Assumptions MH'!$Q20*((1+J$13)^('Cash Flow MH'!J$5-1)) -> 19650 | K54: ='Cash Flow MH'!K$27*'Assumptions MH'!$Q20*((1+K$13)^('Cash Flow MH'!K$5-1)) -> 19650 | ... DS54: ='Cash Flow MH'!DS$27*'Assumptions MH'!$Q20*((1+DS$13)^('Cash Flow MH'!DS$5-1)) -> 25638.793 | DT54: x
B55: G&A: Liability, FF&E Insurance / Permits | D55: =('Cash Flow MH'!D$27*'Assumptions MH'!$Q$29*((1+D$13)^('Cash Flow MH'!D$5-1))) -> 5240 | E55: =('Cash Flow MH'!E$27*'Assumptions MH'!$Q$29*((1+E$13)^('Cash Flow MH'!E$5-1))) -> 5240 | F55: =('Cash Flow MH'!F$27*'Assumptions MH'!$Q$29*((1+F$13)^('Cash Flow MH'!F$5-1))) -> 5240 | G55: =('Cash Flow MH'!G$27*'Assumptions MH'!$Q$29*((1+G$13)^('Cash Flow MH'!G$5-1))) -> 5240 | H55: =('Cash Flow MH'!H$27*'Assumptions MH'!$Q$29*((1+H$13)^('Cash Flow MH'!H$5-1))) -> 5240 | I55: =('Cash Flow MH'!I$27*'Assumptions MH'!$Q$29*((1+I$13)^('Cash Flow MH'!I$5-1))) -> 5240 | J55: =('Cash Flow MH'!J$27*'Assumptions MH'!$Q$29*((1+J$13)^('Cash Flow MH'!J$5-1))) -> 5240 | K55: =('Cash Flow MH'!K$27*'Assumptions MH'!$Q$29*((1+K$13)^('Cash Flow MH'!K$5-1))) -> 5240 | ... DS55: =('Cash Flow MH'!DS$27*'Assumptions MH'!$Q$29*((1+DS$13)^('Cash Flow MH'!DS$5-1))) -> 6837.0115 | DT55: x
B56: Credit Card Fees | D56: ='Cash Flow MH'!D$38*'Assumptions MH'!$Q17 -> 5868.992 | E56: ='Cash Flow MH'!E$38*'Assumptions MH'!$Q17 -> 8263.2038 | F56: ='Cash Flow MH'!F$38*'Assumptions MH'!$Q17 -> 12410.745 | G56: ='Cash Flow MH'!G$38*'Assumptions MH'!$Q17 -> 13892.596 | H56: ='Cash Flow MH'!H$38*'Assumptions MH'!$Q17 -> 15852.304 | I56: ='Cash Flow MH'!I$38*'Assumptions MH'!$Q17 -> 17719.069 | J56: ='Cash Flow MH'!J$38*'Assumptions MH'!$Q17 -> 17144.536 | K56: ='Cash Flow MH'!K$38*'Assumptions MH'!$Q17 -> 18511.707 | ... DS56: ='Cash Flow MH'!DS$38*'Assumptions MH'!$Q17 -> 24805.963 | DT56: x
B57: Sales & Marketing - Payroll | D57: =('Cash Flow MH'!D$27*'Assumptions MH'!$Q21*((1+D$13)^('Cash Flow MH'!D$5-1))) -> 12766.656 | E57: =('Cash Flow MH'!E$27*'Assumptions MH'!$Q21*((1+E$13)^('Cash Flow MH'!E$5-1))) -> 12766.656 | F57: =('Cash Flow MH'!F$27*'Assumptions MH'!$Q21*((1+F$13)^('Cash Flow MH'!F$5-1))) -> 12766.656 | G57: =('Cash Flow MH'!G$27*'Assumptions MH'!$Q21*((1+G$13)^('Cash Flow MH'!G$5-1))) -> 12766.656 | H57: =('Cash Flow MH'!H$27*'Assumptions MH'!$Q21*((1+H$13)^('Cash Flow MH'!H$5-1))) -> 12766.656 | I57: =('Cash Flow MH'!I$27*'Assumptions MH'!$Q21*((1+I$13)^('Cash Flow MH'!I$5-1))) -> 12766.656 | J57: =('Cash Flow MH'!J$27*'Assumptions MH'!$Q21*((1+J$13)^('Cash Flow MH'!J$5-1))) -> 12766.656 | K57: =('Cash Flow MH'!K$27*'Assumptions MH'!$Q21*((1+K$13)^('Cash Flow MH'!K$5-1))) -> 12766.656 | ... DS57: =('Cash Flow MH'!DS$27*'Assumptions MH'!$Q21*((1+DS$13)^('Cash Flow MH'!DS$5-1))) -> 16657.591 | DT57: x
B58: Sales & Marketing - Direct to Consumer | D58: ='Cash Flow MH'!D$38*'Assumptions MH'!$Q22 -> 978.16534 | E58: ='Cash Flow MH'!E$38*'Assumptions MH'!$Q22 -> 1377.2006 | F58: ='Cash Flow MH'!F$38*'Assumptions MH'!$Q22 -> 2068.4574 | G58: ='Cash Flow MH'!G$38*'Assumptions MH'!$Q22 -> 2315.4326 | H58: ='Cash Flow MH'!H$38*'Assumptions MH'!$Q22 -> 2642.0506 | I58: ='Cash Flow MH'!I$38*'Assumptions MH'!$Q22 -> 2953.1782 | J58: ='Cash Flow MH'!J$38*'Assumptions MH'!$Q22 -> 2857.4227 | K58: ='Cash Flow MH'!K$38*'Assumptions MH'!$Q22 -> 3085.2845 | ... DS58: ='Cash Flow MH'!DS$38*'Assumptions MH'!$Q22 -> 4134.3272 | DT58: x
B59: Platform Fees / Customer Acquisition | D59: ='Cash Flow MH'!D$38*'Assumptions MH'!$Q23 -> 13694.315 | E59: ='Cash Flow MH'!E$38*'Assumptions MH'!$Q23 -> 19280.809 | F59: ='Cash Flow MH'!F$38*'Assumptions MH'!$Q23 -> 28958.404 | G59: ='Cash Flow MH'!G$38*'Assumptions MH'!$Q23 -> 32416.057 | H59: ='Cash Flow MH'!H$38*'Assumptions MH'!$Q23 -> 36988.708 | I59: ='Cash Flow MH'!I$38*'Assumptions MH'!$Q23 -> 41344.495 | J59: ='Cash Flow MH'!J$38*'Assumptions MH'!$Q23 -> 40003.918 | K59: ='Cash Flow MH'!K$38*'Assumptions MH'!$Q23 -> 43193.983 | ... DS59: ='Cash Flow MH'!DS$38*'Assumptions MH'!$Q23 -> 57880.581 | DT59: x
B60: In-Unit Maintenance | D60: ='Cash Flow MH'!D$27*'Assumptions MH'!$Q19*((1+D$13)^('Cash Flow MH'!D$5-1)) -> 3930 | E60: ='Cash Flow MH'!E$27*'Assumptions MH'!$Q19*((1+E$13)^('Cash Flow MH'!E$5-1)) -> 3930 | F60: ='Cash Flow MH'!F$27*'Assumptions MH'!$Q19*((1+F$13)^('Cash Flow MH'!F$5-1)) -> 3930 | G60: ='Cash Flow MH'!G$27*'Assumptions MH'!$Q19*((1+G$13)^('Cash Flow MH'!G$5-1)) -> 3930 | H60: ='Cash Flow MH'!H$27*'Assumptions MH'!$Q19*((1+H$13)^('Cash Flow MH'!H$5-1)) -> 3930 | I60: ='Cash Flow MH'!I$27*'Assumptions MH'!$Q19*((1+I$13)^('Cash Flow MH'!I$5-1)) -> 3930 | J60: ='Cash Flow MH'!J$27*'Assumptions MH'!$Q19*((1+J$13)^('Cash Flow MH'!J$5-1)) -> 3930 | K60: ='Cash Flow MH'!K$27*'Assumptions MH'!$Q19*((1+K$13)^('Cash Flow MH'!K$5-1)) -> 3930 | ... DS60: ='Cash Flow MH'!DS$27*'Assumptions MH'!$Q19*((1+DS$13)^('Cash Flow MH'!DS$5-1)) -> 5127.7586 | DT60: x
B61: Property Maintenance, Supplies, Subcontracting | D61: =('Cash Flow MH'!D$27*'Assumptions MH'!$Q$31*((1+D$13)^('Cash Flow MH'!D$5-1))) -> 11790 | E61: =('Cash Flow MH'!E$27*'Assumptions MH'!$Q$31*((1+E$13)^('Cash Flow MH'!E$5-1))) -> 11790 | F61: =('Cash Flow MH'!F$27*'Assumptions MH'!$Q$31*((1+F$13)^('Cash Flow MH'!F$5-1))) -> 11790 | G61: =('Cash Flow MH'!G$27*'Assumptions MH'!$Q$31*((1+G$13)^('Cash Flow MH'!G$5-1))) -> 11790 | H61: =('Cash Flow MH'!H$27*'Assumptions MH'!$Q$31*((1+H$13)^('Cash Flow MH'!H$5-1))) -> 11790 | I61: =('Cash Flow MH'!I$27*'Assumptions MH'!$Q$31*((1+I$13)^('Cash Flow MH'!I$5-1))) -> 11790 | J61: =('Cash Flow MH'!J$27*'Assumptions MH'!$Q$31*((1+J$13)^('Cash Flow MH'!J$5-1))) -> 11790 | K61: =('Cash Flow MH'!K$27*'Assumptions MH'!$Q$31*((1+K$13)^('Cash Flow MH'!K$5-1))) -> 11790 | ... DS61: =('Cash Flow MH'!DS$27*'Assumptions MH'!$Q$31*((1+DS$13)^('Cash Flow MH'!DS$5-1))) -> 15383.276 | DT61: x
B62: Utility Costs | D62: ='Cash Flow MH'!D$27*'Assumptions MH'!$Q18*((1+D$13)^('Cash Flow MH'!D$5-1)) -> 13100 | E62: ='Cash Flow MH'!E$27*'Assumptions MH'!$Q18*((1+E$13)^('Cash Flow MH'!E$5-1)) -> 13100 | F62: ='Cash Flow MH'!F$27*'Assumptions MH'!$Q18*((1+F$13)^('Cash Flow MH'!F$5-1)) -> 13100 | G62: ='Cash Flow MH'!G$27*'Assumptions MH'!$Q18*((1+G$13)^('Cash Flow MH'!G$5-1)) -> 13100 | H62: ='Cash Flow MH'!H$27*'Assumptions MH'!$Q18*((1+H$13)^('Cash Flow MH'!H$5-1)) -> 13100 | I62: ='Cash Flow MH'!I$27*'Assumptions MH'!$Q18*((1+I$13)^('Cash Flow MH'!I$5-1)) -> 13100 | J62: ='Cash Flow MH'!J$27*'Assumptions MH'!$Q18*((1+J$13)^('Cash Flow MH'!J$5-1)) -> 13100 | K62: ='Cash Flow MH'!K$27*'Assumptions MH'!$Q18*((1+K$13)^('Cash Flow MH'!K$5-1)) -> 13100 | ... DS62: ='Cash Flow MH'!DS$27*'Assumptions MH'!$Q18*((1+DS$13)^('Cash Flow MH'!DS$5-1)) -> 17092.529 | DT62: x
B63: Wifi / Cable | D63: ='Cash Flow MH'!D$27*'Assumptions MH'!$Q24*((1+D$13)^('Cash Flow MH'!D$5-1)) -> 9825 | E63: ='Cash Flow MH'!E$27*'Assumptions MH'!$Q24*((1+E$13)^('Cash Flow MH'!E$5-1)) -> 9825 | F63: ='Cash Flow MH'!F$27*'Assumptions MH'!$Q24*((1+F$13)^('Cash Flow MH'!F$5-1)) -> 9825 | G63: ='Cash Flow MH'!G$27*'Assumptions MH'!$Q24*((1+G$13)^('Cash Flow MH'!G$5-1)) -> 9825 | H63: ='Cash Flow MH'!H$27*'Assumptions MH'!$Q24*((1+H$13)^('Cash Flow MH'!H$5-1)) -> 9825 | I63: ='Cash Flow MH'!I$27*'Assumptions MH'!$Q24*((1+I$13)^('Cash Flow MH'!I$5-1)) -> 9825 | J63: ='Cash Flow MH'!J$27*'Assumptions MH'!$Q24*((1+J$13)^('Cash Flow MH'!J$5-1)) -> 9825 | K63: ='Cash Flow MH'!K$27*'Assumptions MH'!$Q24*((1+K$13)^('Cash Flow MH'!K$5-1)) -> 9825 | ... DS63: ='Cash Flow MH'!DS$27*'Assumptions MH'!$Q24*((1+DS$13)^('Cash Flow MH'!DS$5-1)) -> 12819.397 | DT63: x
B64: Information Technology | D64: ='Cash Flow MH'!D$38*'Assumptions MH'!$Q27 -> 3912.6614 | E64: ='Cash Flow MH'!E$38*'Assumptions MH'!$Q27 -> 5508.8025 | F64: ='Cash Flow MH'!F$38*'Assumptions MH'!$Q27 -> 8273.8298 | G64: ='Cash Flow MH'!G$38*'Assumptions MH'!$Q27 -> 9261.7305 | H64: ='Cash Flow MH'!H$38*'Assumptions MH'!$Q27 -> 10568.202 | I64: ='Cash Flow MH'!I$38*'Assumptions MH'!$Q27 -> 11812.713 | J64: ='Cash Flow MH'!J$38*'Assumptions MH'!$Q27 -> 11429.691 | K64: ='Cash Flow MH'!K$38*'Assumptions MH'!$Q27 -> 12341.138 | ... DS64: ='Cash Flow MH'!DS$38*'Assumptions MH'!$Q27 -> 16537.309 | DT64: x
B65: Total Undistributed Operating Expenses | D65: =SUM(D52:D64) -> 138588.92 | E65: =SUM(E52:E64) -> 148564.8 | F65: =SUM(F52:F64) -> 165846.22 | G65: =SUM(G52:G64) -> 172020.6 | H65: =SUM(H52:H64) -> 180186.05 | I65: =SUM(I52:I64) -> 187964.24 | J65: =SUM(J52:J64) -> 185570.35 | K65: =SUM(K52:K64) -> 191266.9 | ... DS65: =SUM(DS52:DS64) -> 252278.19 | DT65: x
B66: Percent of Revenue | D66: =D65/D38 -> 0.70841254 | E66: =E65/E38 -> 0.5393724 | F66: =F65/F38 -> 0.40089348 | G66: =G65/G38 -> 0.37146536 | H66: =H65/H38 -> 0.34099659 | I66: =I65/I38 -> 0.3182406 | J66: =J65/J38 -> 0.32471631 | K66: =K65/K38 -> 0.30996639 | ... DS66: =DS65/DS38 -> 0.30510186 | DT66: x
DT67: x
A68: x | B68: Gross Operating Profit | D68: =D48-D65 -> 4126.5192 | E68: =E48-E65 -> 69896.522 | F68: =F48-F65 -> 183301.85 | G68: =G48-G65 -> 223968.99 | H68: =H48-H65 -> 276993.62 | I68: =I48-I65 -> 329448.63 | J68: =J48-J65 -> 309576.99 | K68: =K48-K65 -> 346824.76 | ... DS68: =DS48-DS65 -> 468454.67 | DT68: x
B69: Gross Operating Profit Margin | D69: =D68/D38 -> 0.021093158 | E69: =E68/E38 -> 0.25376303 | F69: =F68/F38 -> 0.44308828 | G69: =G68/G38 -> 0.48364393 | H69: =H68/H38 -> 0.52420195 | I69: =I68/I38 -> 0.55778658 | J69: =J68/J38 -> 0.54170668 | K69: =K68/K38 -> 0.56206285 | ... DS69: =DS68/DS38 -> 0.5665428 | DT69: x
DT70: x
A71: x | B71: Base Management Fee | D71: =('Cash Flow MH'!D$38*D72) -> 9781.6534 | E71: =('Cash Flow MH'!E$38*E72) -> 13772.006 | F71: =('Cash Flow MH'!F$38*F72) -> 20684.574 | G71: =('Cash Flow MH'!G$38*G72) -> 23154.326 | H71: =('Cash Flow MH'!H$38*H72) -> 26420.506 | I71: =('Cash Flow MH'!I$38*I72) -> 29531.782 | J71: =('Cash Flow MH'!J$38*J72) -> 28574.227 | K71: =('Cash Flow MH'!K$38*K72) -> 30852.845 | ... DS71: =('Cash Flow MH'!DS$38*DS72) -> 41343.272 | DT71: x
B72: Percent of Revenue | D72: =+'Assumptions MH'!$Q28 -> 0.05 | E72: =+'Assumptions MH'!$Q28 -> 0.05 | F72: =+'Assumptions MH'!$Q28 -> 0.05 | G72: =+'Assumptions MH'!$Q28 -> 0.05 | H72: =+'Assumptions MH'!$Q28 -> 0.05 | I72: =+'Assumptions MH'!$Q28 -> 0.05 | J72: =+'Assumptions MH'!$Q28 -> 0.05 | K72: =+'Assumptions MH'!$Q28 -> 0.05 | ... DS72: =+'Assumptions MH'!$Q28 -> 0.05 | DT72: x
DT73: x
B74: Minimum Monthly Payment | D74: =+'Assumptions MH'!$G$45*D75*(1+'Assumptions MH'!$Z$6)^('Cash Flow MH'!D$5-1) -> 188157.55 | E74: =+'Assumptions MH'!$G$45*E75*(1+'Assumptions MH'!$Z$6)^('Cash Flow MH'!E$5-1) -> 188157.55 | F74: =+'Assumptions MH'!$G$45*F75*(1+'Assumptions MH'!$Z$6)^('Cash Flow MH'!F$5-1) -> 188157.55 | G74: =+'Assumptions MH'!$G$45*G75*(1+'Assumptions MH'!$Z$6)^('Cash Flow MH'!G$5-1) -> 188157.55 | H74: =+'Assumptions MH'!$G$45*H75*(1+'Assumptions MH'!$Z$6)^('Cash Flow MH'!H$5-1) -> 188157.55 | I74: =+'Assumptions MH'!$G$45*I75*(1+'Assumptions MH'!$Z$6)^('Cash Flow MH'!I$5-1) -> 188157.55 | J74: =+'Assumptions MH'!$G$45*J75*(1+'Assumptions MH'!$Z$6)^('Cash Flow MH'!J$5-1) -> 188157.55 | K74: =+'Assumptions MH'!$G$45*K75*(1+'Assumptions MH'!$Z$6)^('Cash Flow MH'!K$5-1) -> 188157.55 | ... DS74: =+'Assumptions MH'!$G$45*DS75*(1+'Assumptions MH'!$Z$6)^('Cash Flow MH'!DS$5-1) -> 163668.62 | DT74: x
B75: Percent of Rent | D75: =INDEX('Assumptions MH'!$Z$12:$Z$21,MATCH('Cash Flow MH'!D$5,'Assumptions MH'!$Y$12:$Y$21,)) -> 0.6 | E75: =INDEX('Assumptions MH'!$Z$12:$Z$21,MATCH('Cash Flow MH'!E$5,'Assumptions MH'!$Y$12:$Y$21,)) -> 0.6 | F75: =INDEX('Assumptions MH'!$Z$12:$Z$21,MATCH('Cash Flow MH'!F$5,'Assumptions MH'!$Y$12:$Y$21,)) -> 0.6 | G75: =INDEX('Assumptions MH'!$Z$12:$Z$21,MATCH('Cash Flow MH'!G$5,'Assumptions MH'!$Y$12:$Y$21,)) -> 0.6 | H75: =INDEX('Assumptions MH'!$Z$12:$Z$21,MATCH('Cash Flow MH'!H$5,'Assumptions MH'!$Y$12:$Y$21,)) -> 0.6 | I75: =INDEX('Assumptions MH'!$Z$12:$Z$21,MATCH('Cash Flow MH'!I$5,'Assumptions MH'!$Y$12:$Y$21,)) -> 0.6 | J75: =INDEX('Assumptions MH'!$Z$12:$Z$21,MATCH('Cash Flow MH'!J$5,'Assumptions MH'!$Y$12:$Y$21,)) -> 0.6 | K75: =INDEX('Assumptions MH'!$Z$12:$Z$21,MATCH('Cash Flow MH'!K$5,'Assumptions MH'!$Y$12:$Y$21,)) -> 0.6 | ... DS75: =INDEX('Assumptions MH'!$Z$12:$Z$21,MATCH('Cash Flow MH'!DS$5,'Assumptions MH'!$Y$12:$Y$21,)) -> 0.4 | DT75: x
DT76: x
A77: x | B77: Adjusted Gross Operating Profit | D77: =+D68-D71-D74 -> -193812.68 | E77: =+E68-E71-E74 -> -132033.03 | F77: =+F68-F71-F74 -> -25540.273 | G77: =+G68-G71-G74 -> 12657.113 | H77: =+H68-H71-H74 -> 62415.561 | I77: =+I68-I71-I74 -> 111759.3 | J77: =+J68-J71-J74 -> 92845.217 | K77: =+K68-K71-K74 -> 127814.37 | ... DS77: =+DS68-DS71-DS74 -> 263442.78 | DT77: x
B78: Percent of Revenue | D78: =D77/D38 -> -0.9906949 | E78: =E77/E38 -> -0.47935293 | F78: =F77/F38 -> -0.061737487 | G78: =G77/G38 -> 0.027332069 | H78: =H77/H38 -> 0.11811954 | I78: =I77/I38 -> 0.18921869 | J78: =J77/J38 -> 0.16246322 | K78: =K77/K38 -> 0.20713547 | ... DS78: =DS77/DS38 -> 0.31860417 | DT78: x
DT79: x
B80: Profit Share - Owner | D80: =+MAX(0,D77)*D81 -> 0 | E80: =+MAX(0,E77)*E81 -> 0 | F80: =+MAX(0,F77)*F81 -> 0 | G80: =+MAX(0,G77)*G81 -> 11391.401 | H80: =+MAX(0,H77)*H81 -> 56174.005 | I80: =+MAX(0,I77)*I81 -> 100583.37 | J80: =+MAX(0,J77)*J81 -> 83560.695 | K80: =+MAX(0,K77)*K81 -> 115032.93 | ... DS80: =+MAX(0,DS77)*DS81 -> 237098.5 | DT80: x
B81: Share of Profit | D81: =INDEX('Assumptions MH'!$Z$25:$Z$34,MATCH(D5,'Assumptions MH'!$Y$25:$Y$34,)) -> 0.9 | E81: =INDEX('Assumptions MH'!$Z$25:$Z$34,MATCH(E5,'Assumptions MH'!$Y$25:$Y$34,)) -> 0.9 | F81: =INDEX('Assumptions MH'!$Z$25:$Z$34,MATCH(F5,'Assumptions MH'!$Y$25:$Y$34,)) -> 0.9 | G81: =INDEX('Assumptions MH'!$Z$25:$Z$34,MATCH(G5,'Assumptions MH'!$Y$25:$Y$34,)) -> 0.9 | H81: =INDEX('Assumptions MH'!$Z$25:$Z$34,MATCH(H5,'Assumptions MH'!$Y$25:$Y$34,)) -> 0.9 | I81: =INDEX('Assumptions MH'!$Z$25:$Z$34,MATCH(I5,'Assumptions MH'!$Y$25:$Y$34,)) -> 0.9 | J81: =INDEX('Assumptions MH'!$Z$25:$Z$34,MATCH(J5,'Assumptions MH'!$Y$25:$Y$34,)) -> 0.9 | K81: =INDEX('Assumptions MH'!$Z$25:$Z$34,MATCH(K5,'Assumptions MH'!$Y$25:$Y$34,)) -> 0.9 | ... DS81: =INDEX('Assumptions MH'!$Z$25:$Z$34,MATCH(DS5,'Assumptions MH'!$Y$25:$Y$34,)) -> 0.9 | DT81: x
B82: Profit Share - Mint House | D82: =+MAX(0,D77)*D83 -> 0 | E82: =+MAX(0,E77)*E83 -> 0 | F82: =+MAX(0,F77)*F83 -> 0 | G82: =+MAX(0,G77)*G83 -> 1265.7113 | H82: =+MAX(0,H77)*H83 -> 6241.5561 | I82: =+MAX(0,I77)*I83 -> 11175.93 | J82: =+MAX(0,J77)*J83 -> 9284.5217 | K82: =+MAX(0,K77)*K83 -> 12781.437 | ... DS82: =+MAX(0,DS77)*DS83 -> 26344.278 | DT82: x
B83: Share of Profit | D83: =1-D81 -> 0.1 | E83: =1-E81 -> 0.1 | F83: =1-F81 -> 0.1 | G83: =1-G81 -> 0.1 | H83: =1-H81 -> 0.1 | I83: =1-I81 -> 0.1 | J83: =1-J81 -> 0.1 | K83: =1-K81 -> 0.1 | ... DS83: =1-DS81 -> 0.1 | DT83: x
G84: =G77-G80-G82 -> 0 | H84: =H77-H80-H82 -> 0 | I84: =I77-I80-I82 -> 0 | J84: =J77-J80-J82 -> 0 | K84: =K77-K80-K82 -> 0 | L84: =L77-L80-L82 -> 0 | M84: =M77-M80-M82 -> 0 | N84: =N77-N80-N82 -> 0 | ... DS84: =DS77-DS80-DS82 -> 0 | DT84: x
B85: Income to Owner - Before FF&E | D85: =D74+D80 -> 188157.55 | E85: =E74+E80 -> 188157.55 | F85: =F74+F80 -> 188157.55 | G85: =G74+G80 -> 199548.95 | H85: =H74+H80 -> 244331.55 | I85: =I74+I80 -> 288740.92 | J85: =J74+J80 -> 271718.24 | K85: =K74+K80 -> 303190.48 | ... DS85: =DS74+DS80 -> 400767.12 | DT85: x
B86: Percent of Revenue | DT86: x
DT87: x
B88: FF&E Reserve | D88: ='Cash Flow MH'!D$38*D89 -> 0 | E88: ='Cash Flow MH'!E$38*E89 -> 0 | F88: ='Cash Flow MH'!F$38*F89 -> 0 | G88: ='Cash Flow MH'!G$38*G89 -> 0 | H88: ='Cash Flow MH'!H$38*H89 -> 0 | I88: ='Cash Flow MH'!I$38*I89 -> 0 | J88: ='Cash Flow MH'!J$38*J89 -> 0 | K88: ='Cash Flow MH'!K$38*K89 -> 0 | ... DS88: ='Cash Flow MH'!DS$38*DS89 -> 41343.272 | DT88: x
B89: Percent of Revenue | D89: =INDEX('Assumptions MH'!$T$40:$T$49,MATCH('Cash Flow MH'!D$5,'Assumptions MH'!$S$40:$S$49,)) -> 0 | E89: =INDEX('Assumptions MH'!$T$40:$T$49,MATCH('Cash Flow MH'!E$5,'Assumptions MH'!$S$40:$S$49,)) -> 0 | F89: =INDEX('Assumptions MH'!$T$40:$T$49,MATCH('Cash Flow MH'!F$5,'Assumptions MH'!$S$40:$S$49,)) -> 0 | G89: =INDEX('Assumptions MH'!$T$40:$T$49,MATCH('Cash Flow MH'!G$5,'Assumptions MH'!$S$40:$S$49,)) -> 0 | H89: =INDEX('Assumptions MH'!$T$40:$T$49,MATCH('Cash Flow MH'!H$5,'Assumptions MH'!$S$40:$S$49,)) -> 0 | I89: =INDEX('Assumptions MH'!$T$40:$T$49,MATCH('Cash Flow MH'!I$5,'Assumptions MH'!$S$40:$S$49,)) -> 0 | J89: =INDEX('Assumptions MH'!$T$40:$T$49,MATCH('Cash Flow MH'!J$5,'Assumptions MH'!$S$40:$S$49,)) -> 0 | K89: =INDEX('Assumptions MH'!$T$40:$T$49,MATCH('Cash Flow MH'!K$5,'Assumptions MH'!$S$40:$S$49,)) -> 0 | ... DS89: =INDEX('Assumptions MH'!$T$40:$T$49,MATCH('Cash Flow MH'!DS$5,'Assumptions MH'!$S$40:$S$49,)) -> 0.05 | DT89: x
DT90: x
A91: x | B91: Income to Owner - After FF&E | D91: =+D85-D88 -> 188157.55 | E91: =+E85-E88 -> 188157.55 | F91: =+F85-F88 -> 188157.55 | G91: =+G85-G88 -> 199548.95 | H91: =+H85-H88 -> 244331.55 | I91: =+I85-I88 -> 288740.92 | J91: =+J85-J88 -> 271718.24 | K91: =+K85-K88 -> 303190.48 | ... DS91: =+DS85-DS88 -> 359423.85 | DT91: x
DT92: x
D93: =D71+D74+D80+D82 -> 197939.2 | E93: =E71+E74+E80+E82 -> 201929.55 | F93: =F71+F74+F80+F82 -> 208842.12 | G93: =G71+G74+G80+G82 -> 223968.99 | H93: =H71+H74+H80+H82 -> 276993.62 | I93: =I71+I74+I80+I82 -> 329448.63 | J93: =J71+J74+J80+J82 -> 309576.99 | K93: =K71+K74+K80+K82 -> 346824.76 | ... DS93: =DS71+DS74+DS80+DS82 -> 468454.67 | DT93: x
D94: =D93-D68 -> 193812.68 | E94: =E93-E68 -> 132033.03 | F94: =F93-F68 -> 25540.273 | G94: =G93-G68 -> 0 | H94: =H93-H68 -> 0 | I94: =I93-I68 -> 0 | J94: =J93-J68 -> 0 | K94: =K93-K68 -> 0 | ... DS94: =DS93-DS68 -> 0 | DT94: x
DT95: x
DT96: x
DT97: x
DT98: x
DT99: x
DT100: x
...

Sheet Monthly-Waterfall
C5: Equity Waterfall | EB5: x
I7: Hurdle Rate | J7: Outside Investor | K7: Sponsor Investors | L7: Sponsor
I8: (up to) | K8: Pro Rata | L8: Promote
D9: 1. Preferred Return | I9: 0.08 | J9: 0.9 | K9: =1-J9 -> 0.1 | L9: 0
D10: 2. First Tier | I10: 0.12 | J10: =(1-$L10)*J$9 -> 0.72 | K10: =(1-$L10)*K$9 -> 0.08 | L10: 0.2
D11: 3. Second Tier | I11: 0.15 | J11: =(1-$L11)*J$9 -> 0.63 | K11: =(1-$L11)*K$9 -> 0.07 | L11: 0.3
D12: 4. Third Tier | J12: =(1-$L12)*J$9 -> 0.5625 | K12: =(1-$L12)*K$9 -> 0.0625 | L12: 0.375
J14: ='Monthly-CF'!L8 -> 45107 | K14: =EOMONTH(J14,1) -> 45138 | L14: =EOMONTH(K14,1) -> 45169 | M14: =EOMONTH(L14,1) -> 45199 | N14: =EOMONTH(M14,1) -> 45230 | O14: =EOMONTH(N14,1) -> 45260 | P14: =EOMONTH(O14,1) -> 45291 | Q14: =EOMONTH(P14,1) -> 45322 | R14: =EOMONTH(Q14,1) -> 45351 | ... DY14: =EOMONTH(DX14,1) -> 48730
J15: =ROUNDUP(J16/12,0) -> 1 | K15: =ROUNDUP(K16/12,0) -> 1 | L15: =ROUNDUP(L16/12,0) -> 1 | M15: =ROUNDUP(M16/12,0) -> 1 | N15: =ROUNDUP(N16/12,0) -> 1 | O15: =ROUNDUP(O16/12,0) -> 1 | P15: =ROUNDUP(P16/12,0) -> 1 | Q15: =ROUNDUP(Q16/12,0) -> 1 | ... DY15: =ROUNDUP(DY16/12,0) -> 10
G16: Total | I16: Initial | J16: 1 | K16: =J16+1 -> 2 | L16: =K16+1 -> 3 | M16: =L16+1 -> 4 | N16: =M16+1 -> 5 | O16: =N16+1 -> 6 | P16: =O16+1 -> 7 | Q16: =P16+1 -> 8 | R16: =Q16+1 -> 9 | ... DY16: =DX16+1 -> 120
B18: =G18-'Monthly-CF'!I129 -> 0 | D18: Leveraged Cash Flows (Linked to Monthly CF) | G18: =SUM(I18:DY18) -> 49098976 | J18: ='Monthly-CF'!L138 -> -5200000 | K18: ='Monthly-CF'!M138 -> -391153.01 | L18: ='Monthly-CF'!N138 -> -2750737.3 | M18: ='Monthly-CF'!O138 -> -2750737.3 | N18: ='Monthly-CF'!P138 -> -2750737.3 | O18: ='Monthly-CF'!Q138 -> -2750737.3 | P18: ='Monthly-CF'!R138 -> -2750737.3 | Q18: ='Monthly-CF'!S138 -> -2648862.4 | ... DY18: ='Monthly-CF'!EA138 -> 52169766
D19: Levered IRR | E19: =XIRR(J18:DY18,J14:DY14) -> 0.17306911
D21: Equity Draws
D22: =J7 -> Outside Investor | E22: =J9 -> 0.9 | G22: =SUM(I22:DY22) -> -19794332 | I22: =$I$18*E22 -> 0 | J22: =IF(J18<0,J18*$J$9,0) -> -4680000 | K22: =IF(K18<0,K18*$J$9,0) -> -352037.71 | L22: =IF(L18<0,L18*$J$9,0) -> -2475663.6 | M22: =IF(M18<0,M18*$J$9,0) -> -2475663.6 | N22: =IF(N18<0,N18*$J$9,0) -> -2475663.6 | O22: =IF(O18<0,O18*$J$9,0) -> -2475663.6 | P22: =IF(P18<0,P18*$J$9,0) -> -2475663.6 | Q22: =IF(Q18<0,Q18*$J$9,0) -> -2383976.2 | ... DY22: =IF(DY18<0,DY18*$J$9,0) -> 0
D23: =K7 -> Sponsor Investors | E23: =1-E22 -> 0.1 | G23: =SUM(I23:DY23) -> -2199370.2 | I23: =$I$18*E23 -> 0 | J23: =IF(J18<0,J18*$K$9,0) -> -520000 | K23: =IF(K18<0,K18*$K$9,0) -> -39115.301 | L23: =IF(L18<0,L18*$K$9,0) -> -275073.73 | M23: =IF(M18<0,M18*$K$9,0) -> -275073.73 | N23: =IF(N18<0,N18*$K$9,0) -> -275073.73 | O23: =IF(O18<0,O18*$K$9,0) -> -275073.73 | P23: =IF(P18<0,P18*$K$9,0) -> -275073.73 | Q23: =IF(Q18<0,Q18*$K$9,0) -> -264886.24 | ... DY23: =IF(DY18<0,DY18*$K$9,0) -> 0
D24: Total | E24: =G24+Dashboard!D43 -> 0 | G24: =SUM(I24:DY24) -> -21993702 | I24: =SUM(I22:I23) -> 0 | J24: =SUM(J22:J23) -> -5200000 | K24: =SUM(K22:K23) -> -391153.01 | L24: =SUM(L22:L23) -> -2750737.3 | M24: =SUM(M22:M23) -> -2750737.3 | N24: =SUM(N22:N23) -> -2750737.3 | O24: =SUM(O22:O23) -> -2750737.3 | P24: =SUM(P22:P23) -> -2750737.3 | ... DY24: =SUM(DY22:DY23) -> 0
J25: =J24-J18 -> 0 | K25: =K24-K18 -> 0 | L25: =L24-L18 -> 0 | M25: =M24-M18 -> 0 | N25: =N24-N18 -> 0 | O25: =O24-O18 -> 0 | P25: =P24-P18 -> 0 | Q25: =Q24-Q18 -> 0 | ... AA25: =AA24-AA18 -> 0
D26: 1. Preferred Return
D27: =CONCATENATE($J$7&" (Pro Rata)") -> Outside Investor (Pro Rata) | E27: =SUM(I27:DY27)/SUM(I$29:DY$29) -> 0.9 | G27: =SUM(I27:DY27) -> 31781818 | I27: =I77 -> 0 | J27: =J77 -> 0 | K27: =K77 -> 0 | L27: =L77 -> 0 | M27: =M77 -> 0 | N27: =N77 -> 0 | O27: =O77 -> 0 | P27: =P77 -> 0 | ... DY27: =DY77 -> 14751197
D28: =CONCATENATE($K$7&" (Pro Rata)") -> Sponsor Investors (Pro Rata) | E28: =SUM(I28:DY28)/SUM(I$29:DY$29) -> 0.1 | G28: =SUM(I28:DY28) -> 3531313.1 | I28: =(I27/$J$9)*$K$9 -> 0 | J28: =(J27/$J$9)*$K$9 -> 0 | K28: =(K27/$J$9)*$K$9 -> 0 | L28: =(L27/$J$9)*$K$9 -> 0 | M28: =(M27/$J$9)*$K$9 -> 0 | N28: =(N27/$J$9)*$K$9 -> 0 | O28: =(O27/$J$9)*$K$9 -> 0 | P28: =(P27/$J$9)*$K$9 -> 0 | ... DY28: =(DY27/$J$9)*$K$9 -> 1639021.9
D29: Total | E29: =SUM(I29:DY29)/SUM(I$29:DY$29) -> 1 | G29: =SUM(I29:DY29) -> 35313131 | I29: =SUM(I27:I28) -> 0 | J29: =SUM(J27:J28) -> 0 | K29: =SUM(K27:K28) -> 0 | L29: =SUM(L27:L28) -> 0 | M29: =SUM(M27:M28) -> 0 | N29: =SUM(N27:N28) -> 0 | O29: =SUM(O27:O28) -> 0 | P29: =SUM(P27:P28) -> 0 | ... DY29: =SUM(DY27:DY28) -> 16390219
D31: Remaining Cash Flow | G31: =SUM(I31:DY31) -> 35779547 | I31: =IF(I18>0,I18-I29,0) -> 0 | J31: =IF(J18>0,J18-J29,0) -> 0 | K31: =IF(K18>0,K18-K29,0) -> 0 | L31: =IF(L18>0,L18-L29,0) -> 0 | M31: =IF(M18>0,M18-M29,0) -> 0 | N31: =IF(N18>0,N18-N29,0) -> 0 | O31: =IF(O18>0,O18-O29,0) -> 0 | P31: =IF(P18>0,P18-P29,0) -> 0 | ... DY31: =IF(DY18>0,DY18-DY29,0) -> 35779547
D33: 2. First Tier
D34: =CONCATENATE($J$7&" (Pro Rata)") -> Outside Investor (Pro Rata) | G34: =SUM(I34:DY34) -> 10645432 | I34: =I87 -> 0 | J34: =J87 -> 0 | K34: =K87 -> 0 | L34: =L87 -> 0 | M34: =M87 -> 0 | N34: =N87 -> 0 | O34: =O87 -> 0 | P34: =P87 -> 0 | ... DY34: =DY87 -> 10645432
D35: =CONCATENATE($K$7&" (Pro Rata)") -> Sponsor Investors (Pro Rata) | G35: =SUM(I35:DY35) -> 1182825.7 | I35: =(I34/$J$10)*$K$10 -> 0 | J35: =(J34/$J$10)*$K$10 -> 0 | K35: =(K34/$J$10)*$K$10 -> 0 | L35: =(L34/$J$10)*$K$10 -> 0 | M35: =(M34/$J$10)*$K$10 -> 0 | N35: =(N34/$J$10)*$K$10 -> 0 | O35: =(O34/$J$10)*$K$10 -> 0 | P35: =(P34/$J$10)*$K$10 -> 0 | ... DY35: =(DY34/$J$10)*$K$10 -> 1182825.7
D36: =CONCATENATE("Promote to "&$L$7) -> Promote to Sponsor | G36: =SUM(I36:DY36) -> 2957064.3 | I36: =(I34/$J$10)*$L$10 -> 0 | J36: =(J34/$J$10)*$L$10 -> 0 | K36: =(K34/$J$10)*$L$10 -> 0 | L36: =(L34/$J$10)*$L$10 -> 0 | M36: =(M34/$J$10)*$L$10 -> 0 | N36: =(N34/$J$10)*$L$10 -> 0 | O36: =(O34/$J$10)*$L$10 -> 0 | P36: =(P34/$J$10)*$L$10 -> 0 | ... DY36: =(DY34/$J$10)*$L$10 -> 2957064.3
D37: Total | G37: =SUM(I37:DY37) -> 14785322 | I37: =SUM(I34:I36) -> 0 | J37: =SUM(J34:J36) -> 0 | K37: =SUM(K34:K36) -> 0 | L37: =SUM(L34:L36) -> 0 | M37: =SUM(M34:M36) -> 0 | N37: =SUM(N34:N36) -> 0 | O37: =SUM(O34:O36) -> 0 | P37: =SUM(P34:P36) -> 0 | ... DY37: =SUM(DY34:DY36) -> 14785322
D39: Remaining Cash Flow | G39: =SUM(I39:DY39) -> 20994225 | I39: =I31-I37 -> 0 | J39: =J31-J37 -> 0 | K39: =K31-K37 -> 0 | L39: =L31-L37 -> 0 | M39: =M31-M37 -> 0 | N39: =N31-N37 -> 0 | O39: =O31-O37 -> 0 | P39: =P31-P37 -> 0 | ... DY39: =DY31-DY37 -> 20994225
D41: 3. Second Tier
D42: =CONCATENATE($J$7&" (Pro Rata)") -> Outside Investor (Pro Rata) | G42: =SUM(I42:DY42) -> 10955339 | I42: =I98 -> 0 | J42: =J98 -> 0 | K42: =K98 -> 0 | L42: =L98 -> 0 | M42: =M98 -> 0 | N42: =N98 -> 0 | O42: =O98 -> 0 | P42: =P98 -> 0 | ... DY42: =DY98 -> 10955339
D43: =CONCATENATE($K$7&" (Pro Rata)") -> Sponsor Investors (Pro Rata) | G43: =SUM(I43:DY43) -> 1217259.9 | I43: =(I42/$J$11)*$K$11 -> 0 | J43: =(J42/$J$11)*$K$11 -> 0 | K43: =(K42/$J$11)*$K$11 -> 0 | L43: =(L42/$J$11)*$K$11 -> 0 | M43: =(M42/$J$11)*$K$11 -> 0 | N43: =(N42/$J$11)*$K$11 -> 0 | O43: =(O42/$J$11)*$K$11 -> 0 | P43: =(P42/$J$11)*$K$11 -> 0 | ... DY43: =(DY42/$J$11)*$K$11 -> 1217259.9
D44: =CONCATENATE("Promote to "&$L$7) -> Promote to Sponsor | G44: =SUM(I44:DY44) -> 5216828.3 | I44: =(I42/$J$11)*$L$11 -> 0 | J44: =(J42/$J$11)*$L$11 -> 0 | K44: =(K42/$J$11)*$L$11 -> 0 | L44: =(L42/$J$11)*$L$11 -> 0 | M44: =(M42/$J$11)*$L$11 -> 0 | N44: =(N42/$J$11)*$L$11 -> 0 | O44: =(O42/$J$11)*$L$11 -> 0 | P44: =(P42/$J$11)*$L$11 -> 0 | ... DY44: =(DY42/$J$11)*$L$11 -> 5216828.3
D45: Total | G45: =SUM(I45:DY45) -> 17389428 | I45: =SUM(I42:I44) -> 0 | J45: =SUM(J42:J44) -> 0 | K45: =SUM(K42:K44) -> 0 | L45: =SUM(L42:L44) -> 0 | M45: =SUM(M42:M44) -> 0 | N45: =SUM(N42:N44) -> 0 | O45: =SUM(O42:O44) -> 0 | P45: =SUM(P42:P44) -> 0 | ... DY45: =SUM(DY42:DY44) -> 17389428
D47: Remaining Cash Flow | G47: =SUM(I47:DY47) -> 3604797.7 | I47: =I39-I45 -> 0 | J47: =J39-J45 -> 0 | K47: =K39-K45 -> 0 | L47: =L39-L45 -> 0 | M47: =M39-M45 -> 0 | N47: =N39-N45 -> 0 | O47: =O39-O45 -> 0 | P47: =P39-P45 -> 0 | ... DY47: =DY39-DY45 -> 3604797.7
D49: 4. Third Tier
D50: =CONCATENATE($J$7&" (Pro Rata)") -> Outside Investor (Pro Rata) | G50: =SUM(I50:DY50) -> 2027698.7 | I50: =I47*$J$12 -> 0 | J50: =J47*$J$12 -> 0 | K50: =K47*$J$12 -> 0 | L50: =L47*$J$12 -> 0 | M50: =M47*$J$12 -> 0 | N50: =N47*$J$12 -> 0 | O50: =O47*$J$12 -> 0 | P50: =P47*$J$12 -> 0 | ... DY50: =DY47*$J$12 -> 2027698.7
D51: =CONCATENATE($K$7&" (Pro Rata)") -> Sponsor Investors (Pro Rata) | G51: =SUM(I51:DY51) -> 225299.86 | I51: =I47*$K$12 -> 0 | J51: =J47*$K$12 -> 0 | K51: =K47*$K$12 -> 0 | L51: =L47*$K$12 -> 0 | M51: =M47*$K$12 -> 0 | N51: =N47*$K$12 -> 0 | O51: =O47*$K$12 -> 0 | P51: =P47*$K$12 -> 0 | ... DY51: =DY47*$K$12 -> 225299.86
D52: =CONCATENATE("Promote to "&$L$7) -> Promote to Sponsor | G52: =SUM(I52:DY52) -> 1351799.2 | I52: =I47*$L$12 -> 0 | J52: =J47*$L$12 -> 0 | K52: =K47*$L$12 -> 0 | L52: =L47*$L$12 -> 0 | M52: =M47*$L$12 -> 0 | N52: =N47*$L$12 -> 0 | O52: =O47*$L$12 -> 0 | P52: =P47*$L$12 -> 0 | ... DY52: =DY47*$L$12 -> 1351799.2
D53: Total | G53: =SUM(I53:DY53) -> 3604797.7 | I53: =SUM(I50:I52) -> 0 | J53: =SUM(J50:J52) -> 0 | K53: =SUM(K50:K52) -> 0 | L53: =SUM(L50:L52) -> 0 | M53: =SUM(M50:M52) -> 0 | N53: =SUM(N50:N52) -> 0 | O53: =SUM(O50:O52) -> 0 | P53: =SUM(P50:P52) -> 0 | ... DY53: =SUM(DY50:DY52) -> 3604797.7
D55: Remaining Cash Flow | I55: =I47-I53 -> 0 | J55: =J47-J53 -> 0 | K55: =K47-K53 -> 0 | L55: =L47-L53 -> 0 | M55: =M47-M53 -> 0 | N55: =N47-N53 -> 0 | O55: =O47-O53 -> 0 | P55: =P47-P53 -> 0 | ... DY55: =DY47-DY53 -> 0
D57: TOTAL NET CASH FLOWS
B58: =-SUMIFS('Monthly-Waterfall'!I58:DY58,'Monthly-Waterfall'!I58:DY58,"<"&0) -> 19794332 | D58: =J7 -> Outside Investor | E58: =+XIRR(J58:DY58,J14:DY14) -> 0.15477971 | G58: =SUM(I58:DY58) -> 35615956 | I58: =I22+I27+I34+I42+I50 -> 0 | J58: =J22+J27+J34+J42+J50 -> -4680000 | K58: =K22+K27+K34+K42+K50 -> -352037.71 | L58: =L22+L27+L34+L42+L50 -> -2475663.6 | M58: =M22+M27+M34+M42+M50 -> -2475663.6 | N58: =N22+N27+N34+N42+N50 -> -2475663.6 | O58: =O22+O27+O34+O42+O50 -> -2475663.6 | P58: =P22+P27+P34+P42+P50 -> -2475663.6 | ... DY58: =DY22+DY27+DY34+DY42+DY50 -> 38379667
D59: =K7 -> Sponsor Investors | E59: =+XIRR(J59:DY59,J14:DY14) -> 0.15477971 | G59: =SUM(I59:DY59) -> 3957328.4 | I59: =I23+I28+I35+I43+I51 -> 0 | J59: =J23+J28+J35+J43+J51 -> -520000 | K59: =K23+K28+K35+K43+K51 -> -39115.301 | L59: =L23+L28+L35+L43+L51 -> -275073.73 | M59: =M23+M28+M35+M43+M51 -> -275073.73 | N59: =N23+N28+N35+N43+N51 -> -275073.73 | O59: =O23+O28+O35+O43+O51 -> -275073.73 | P59: =P23+P28+P35+P43+P51 -> -275073.73 | ... DY59: =DY23+DY28+DY35+DY43+DY51 -> 4264407.4
D60: Subtotal | G60: =SUM(I60:DY60) -> 39573284 | I60: =SUM(I58:I59) -> 0 | J60: =SUM(J58:J59) -> -5200000 | K60: =SUM(K58:K59) -> -391153.01 | L60: =SUM(L58:L59) -> -2750737.3 | M60: =SUM(M58:M59) -> -2750737.3 | N60: =SUM(N58:N59) -> -2750737.3 | O60: =SUM(O58:O59) -> -2750737.3 | P60: =SUM(P58:P59) -> -2750737.3 | ... DY60: =SUM(DY58:DY59) -> 42644074
D61: Promote | G61: =SUM(I61:DY61) -> 9525691.8 | I61: =I36+I44+I52 -> 0 | J61: =J36+J44+J52 -> 0 | K61: =K36+K44+K52 -> 0 | L61: =L36+L44+L52 -> 0 | M61: =M36+M44+M52 -> 0 | N61: =N36+N44+N52 -> 0 | O61: =O36+O44+O52 -> 0 | P61: =P36+P44+P52 -> 0 | ... DY61: =DY36+DY44+DY52 -> 9525691.8
D62: Total | E62: =XIRR(J62:DY62,J14:DY14) -> 0.17306911 | G62: =SUM(I62:DY62) -> 49098976 | I62: =SUM(I60:I61) -> 0 | J62: =SUM(J60:J61) -> -5200000 | K62: =SUM(K60:K61) -> -391153.01 | L62: =SUM(L60:L61) -> -2750737.3 | M62: =SUM(M60:M61) -> -2750737.3 | N62: =SUM(N60:N61) -> -2750737.3 | O62: =SUM(O60:O61) -> -2750737.3 | P62: =SUM(P60:P61) -> -2750737.3 | ... DY62: =SUM(DY60:DY61) -> 52169766
D63: Sponsor Total | E63: =XIRR(J63:DY63,J14:DY14) -> 0.27251419 | G63: =SUM(I63:DY63) -> 13483020 | I63: =I61+I59 -> 0 | J63: =J61+J59 -> -520000 | K63: =K61+K59 -> -39115.301 | L63: =L61+L59 -> -275073.73 | M63: =M61+M59 -> -275073.73 | N63: =N61+N59 -> -275073.73 | O63: =O61+O59 -> -275073.73 | P63: =P61+P59 -> -275073.73 | ... DY63: =DY61+DY59 -> 13790099
D65: Outside Investor IRR | E65: =IF(ISERROR(XIRR(I58:DY58,I14:DY14)),"N/A",XIRR(I58:DY58,$I$14:$DY$14)) -> 2.9802322e-09 | I65: ROI Multiple on Equity Investment | K65: =(SUM(I58:DY58)-SUM(I22:DY22))/-SUM(I22:DY22) -> 2.7993007 | L65: Total Promote
D66: =CONCATENATE(K7&" IRR") -> Sponsor Investors IRR | E66: =E65 -> 2.9802322e-09 | I66: =CONCATENATE(K7&" ROI Multiple") -> Sponsor Investors ROI Multiple | K66: =(SUM(I63:DY63)-SUM(I23:DY23))/-SUM(I23:DY23) -> 7.1304005 | L66: =CONCATENATE("Promote to "&L7) -> Promote to Sponsor
D67: Deal IRR | E67: =IF(ISERROR(XIRR(I62:DY62,I14:DY14)),"N/A",XIRR(I62:DY62,$I$14:$DY$14)) -> 2.9802322e-09 | I67: Deal-Level ROI Multiple | K67: =(SUM(I62:DY62)-SUM(I24:DY24))/-SUM(I24:DY24) -> 3.2324107 | L67: Promote to Landowner
D70: CAPITAL DISTRIBUTIONS: | I70: Initial
D72: 1. Preferred Return | E72: =I9 -> 0.08
D73: Beginning Balance | I73: 0 | J73: =I78 -> 0 | K73: =J78 -> -4680000 | L73: =K78 -> -5062728.3 | M73: =L78 -> -7571592.4 | N73: =M78 -> -10095302 | O73: =N78 -> -12637169 | P73: =O78 -> -15193023 | Q73: =P78 -> -17768320 | ... DY73: =DX78 -> -14655091
D74: Equity Draws | I74: =+I22 -> 0 | J74: =J22 -> -4680000 | K74: =K22 -> -352037.71 | L74: =L22 -> -2475663.6 | M74: =M22 -> -2475663.6 | N74: =N22 -> -2475663.6 | O74: =O22 -> -2475663.6 | P74: =P22 -> -2475663.6 | Q74: =Q22 -> -2383976.2 | ... DY74: =DY22 -> 0
D75: Accrual | J75: =J73*(((1+$E72)^((J$14-I$14)/365))-1) -> 0 | K75: =K73*(((1+$E72)^((K$14-J$14)/365))-1) -> -30690.627 | L75: =L73*(((1+$E72)^((L$14-K$14)/365))-1) -> -33200.492 | M75: =M73*(((1+$E72)^((M$14-L$14)/365))-1) -> -48046.4 | N75: =N73*(((1+$E72)^((N$14-M$14)/365))-1) -> -66203.239 | O75: =O73*(((1+$E72)^((O$14-N$14)/365))-1) -> -80190.594 | P75: =P73*(((1+$E72)^((P$14-O$14)/365))-1) -> -99633.207 | Q75: =Q73*(((1+$E72)^((Q$14-P$14)/365))-1) -> -116521.56 | ... DY75: =DY73*(((1+$E72)^((DY$14-DX$14)/365))-1) -> -96105.542
D76: Subtotal | I76: =SUM(I73:I75) -> 0 | J76: =SUM(J73:J75) -> -4680000 | K76: =SUM(K73:K75) -> -5062728.3 | L76: =SUM(L73:L75) -> -7571592.4 | M76: =SUM(M73:M75) -> -10095302 | N76: =SUM(N73:N75) -> -12637169 | O76: =SUM(O73:O75) -> -15193023 | P76: =SUM(P73:P75) -> -17768320 | ... DY76: =SUM(DY73:DY75) -> -14751197
D77: Preferred Return | G77: =SUM(I77:DY77) -> 31781818 | I77: =IF(I18>0,MIN(I18*($J$9),-I76),0) -> 0 | J77: =IF(J18>0,MIN(J18*($J$9),-J76),0) -> 0 | K77: =IF(K18>0,MIN(K18*($J$9),-K76),0) -> 0 | L77: =IF(L18>0,MIN(L18*($J$9),-L76),0) -> 0 | M77: =IF(M18>0,MIN(M18*($J$9),-M76),0) -> 0 | N77: =IF(N18>0,MIN(N18*($J$9),-N76),0) -> 0 | O77: =IF(O18>0,MIN(O18*($J$9),-O76),0) -> 0 | P77: =IF(P18>0,MIN(P18*($J$9),-P76),0) -> 0 | ... DY77: =IF(DY18>0,MIN(DY18*($J$9),-DY76),0) -> 14751197 | DZ77: =+L77/-L76 -> 0
D78: Ending Balance | I78: =SUM(I76:I77) -> 0 | J78: =SUM(J76:J77) -> -4680000 | K78: =SUM(K76:K77) -> -5062728.3 | L78: =SUM(L76:L77) -> -7571592.4 | M78: =SUM(M76:M77) -> -10095302 | N78: =SUM(N76:N77) -> -12637169 | O78: =SUM(O76:O77) -> -15193023 | P78: =SUM(P76:P77) -> -17768320 | ... DY78: =SUM(DY76:DY77) -> 0
D79: Check | E79: =XIRR(J79:DY79,$J$14:$DY$14) -> 0.079999998 | G79: =SUM(I79:DY79) -> 11987486 | I79: =I74+I77 -> 0 | J79: =J74+J77 -> -4680000 | K79: =K74+K77 -> -352037.71 | L79: =L74+L77 -> -2475663.6 | M79: =M74+M77 -> -2475663.6 | N79: =N74+N77 -> -2475663.6 | O79: =O74+O77 -> -2475663.6 | P79: =P74+P77 -> -2475663.6 | ... DY79: =DY74+DY77 -> 14751197
D81: 2. First Tier | E81: =I10 -> 0.12 | K81: =K84/K82 -> 0.009671647
D82: Beginning Balance | I82: =E88 -> 0 | J82: =I88 -> 0 | K82: =J88 -> -4680000 | L82: =K88 -> -5077301 | M82: =L88 -> -7602070.5 | N82: =M88 -> -10148876 | O82: =N88 -> -12722696 | P82: =O88 -> -15317421 | Q82: =P88 -> -17941229 | ... DY82: =DX88 -> -25153354
D83: Equity Draws | I83: =I74 -> 0 | J83: =J74 -> -4680000 | K83: =K74 -> -352037.71 | L83: =L74 -> -2475663.6 | M83: =M74 -> -2475663.6 | N83: =N74 -> -2475663.6 | O83: =O74 -> -2475663.6 | P83: =P74 -> -2475663.6 | ... DY83: =DY74 -> 0
D84: Accrual | I84: =I82*$E$81 -> 0 | J84: =J82*(((1+$E81)^((J$14-I$14)/365))-1) -> 0 | K84: =K82*(((1+$E81)^((K$14-J$14)/365))-1) -> -45263.308 | L84: =L82*(((1+$E81)^((L$14-K$14)/365))-1) -> -49105.863 | M84: =M82*(((1+$E81)^((M$14-L$14)/365))-1) -> -71141.72 | N84: =N82*(((1+$E81)^((N$14-M$14)/365))-1) -> -98156.344 | O84: =O82*(((1+$E81)^((O$14-N$14)/365))-1) -> -119061.57 | P84: =P82*(((1+$E81)^((P$14-O$14)/365))-1) -> -148144.69 | Q84: =Q82*(((1+$E81)^((Q$14-P$14)/365))-1) -> -173521.24 | ... DY84: =DY82*(((1+$E81)^((DY$14-DX$14)/365))-1) -> -243274.36
D85: Preferred Return Paid | I85: =I77 -> 0 | J85: =J77 -> 0 | K85: =K77 -> 0 | L85: =L77 -> 0 | M85: =M77 -> 0 | N85: =N77 -> 0 | O85: =O77 -> 0 | P85: =P77 -> 0 | ... DY85: =DY77 -> 14751197
D86: Subtotal | I86: =SUM(I82:I85) -> 0 | J86: =SUM(J82:J85) -> -4680000 | K86: =SUM(K82:K85) -> -5077301 | L86: =SUM(L82:L85) -> -7602070.5 | M86: =SUM(M82:M85) -> -10148876 | N86: =SUM(N82:N85) -> -12722696 | O86: =SUM(O82:O85) -> -15317421 | P86: =SUM(P82:P85) -> -17941229 | ... DY86: =SUM(DY82:DY85) -> -10645432
D87: First Tier Paid | G87: =SUM(I87:DY87) -> 10645432 | I87: =MIN(-I86,I31*($J$10)) -> 0 | J87: =MIN(-J86,J31*($J$10)) -> 0 | K87: =MIN(-K86,K31*($J$10)) -> 0 | L87: =MIN(-L86,L31*($J$10)) -> 0 | M87: =MIN(-M86,M31*($J$10)) -> 0 | N87: =MIN(-N86,N31*($J$10)) -> 0 | O87: =MIN(-O86,O31*($J$10)) -> 0 | P87: =MIN(-P86,P31*($J$10)) -> 0 | ... DY87: =MIN(-DY86,DY31*($J$10)) -> 10645432 | DZ87: =+L87/-L86 -> 0
D88: Ending Balance | I88: =SUM(I86:I87) -> 0 | J88: =SUM(J86:J87) -> -4680000 | K88: =SUM(K86:K87) -> -5077301 | L88: =SUM(L86:L87) -> -7602070.5 | M88: =SUM(M86:M87) -> -10148876 | N88: =SUM(N86:N87) -> -12722696 | O88: =SUM(O86:O87) -> -15317421 | P88: =SUM(P86:P87) -> -17941229 | ... DY88: =SUM(DY86:DY87) -> 0
D89: Check | E89: =XIRR(J89:DY89,$J$14:$DY$14) -> 0.12 | G89: =SUM(I89:DY89) -> 22632917 | I89: =+I83+I85+I87 -> 0 | J89: =+J83+J85+J87 -> -4680000 | K89: =+K83+K85+K87 -> -352037.71 | L89: =+L83+L85+L87 -> -2475663.6 | M89: =+M83+M85+M87 -> -2475663.6 | N89: =+N83+N85+N87 -> -2475663.6 | O89: =+O83+O85+O87 -> -2475663.6 | P89: =+P83+P85+P87 -> -2475663.6 | ... DY89: =+DY83+DY85+DY87 -> 25396628
D91: 3. Second Tier | E91: =I11 -> 0.15
D92: Beginning Balance | I92: =E99 -> 0 | J92: =I99 -> 0 | K92: =J99 -> -4680000 | L92: =K99 -> -5087921.2 | M92: =L99 -> -7624339.3 | N92: =M99 -> -10188091 | O92: =N99 -> -12785410 | P92: =O99 -> -15408790 | Q92: =P99 -> -18068448 | ... DY92: =DX99 -> -35923014
D93: Equity Draws | I93: =I83 -> 0 | J93: =J83 -> -4680000 | K93: =K83 -> -352037.71 | L93: =L83 -> -2475663.6 | M93: =M83 -> -2475663.6 | N93: =N83 -> -2475663.6 | O93: =O83 -> -2475663.6 | P93: =P83 -> -2475663.6 | ... DY93: =DY83 -> 0
D94: Accrual | I94: =I92*$E$91 -> 0 | J94: =J92*(((1+$E91)^((J$14-I$14)/365))-1) -> 0 | K94: =K92*(((1+$E91)^((K$14-J$14)/365))-1) -> -55883.518 | L94: =L92*(((1+$E91)^((L$14-K$14)/365))-1) -> -60754.474 | M94: =M92*(((1+$E91)^((M$14-L$14)/365))-1) -> -88087.919 | N94: =N92*(((1+$E91)^((N$14-M$14)/365))-1) -> -121655.2 | O94: =O92*(((1+$E91)^((O$14-N$14)/365))-1) -> -147716.42 | P94: =P92*(((1+$E91)^((P$14-O$14)/365))-1) -> -183995.17 | Q94: =Q92*(((1+$E91)^((Q$14-P$14)/365))-1) -> -215753.95 | ... DY94: =DY92*(((1+$E91)^((DY$14-DX$14)/365))-1) -> -428953.93
D95: Preferred Return Paid | I95: =I85 -> 0 | J95: =J85 -> 0 | K95: =K85 -> 0 | L95: =L85 -> 0 | M95: =M85 -> 0 | N95: =N85 -> 0 | O95: =O85 -> 0 | P95: =P85 -> 0 | ... DY95: =DY85 -> 14751197
D96: First Tier Paid | I96: =I87 -> 0 | J96: =J87 -> 0 | K96: =K87 -> 0 | L96: =L87 -> 0 | M96: =M87 -> 0 | N96: =N87 -> 0 | O96: =O87 -> 0 | P96: =P87 -> 0 | ... DY96: =DY87 -> 10645432
D97: Subtotal | I97: =SUM(I92:I96) -> 0 | J97: =SUM(J92:J96) -> -4680000 | K97: =SUM(K92:K96) -> -5087921.2 | L97: =SUM(L92:L96) -> -7624339.3 | M97: =SUM(M92:M96) -> -10188091 | N97: =SUM(N92:N96) -> -12785410 | O97: =SUM(O92:O96) -> -15408790 | P97: =SUM(P92:P96) -> -18068448 | ... DY97: =SUM(DY92:DY96) -> -10955339
D98: Second Tier Paid | G98: =SUM(I98:DY98) -> 10955339 | I98: =MIN(-I97,I39*($J$11)) -> 0 | J98: =MIN(-J97,J39*($J$11)) -> 0 | K98: =MIN(-K97,K39*($J$11)) -> 0 | L98: =MIN(-L97,L39*($J$11)) -> 0 | M98: =MIN(-M97,M39*($J$11)) -> 0 | N98: =MIN(-N97,N39*($J$11)) -> 0 | O98: =MIN(-O97,O39*($J$11)) -> 0 | P98: =MIN(-P97,P39*($J$11)) -> 0 | ... DY98: =MIN(-DY97,DY39*($J$11)) -> 10955339 | DZ98: =+L98/-L97 -> 0
D99: Ending Balance | I99: =SUM(I97:I98) -> 0 | J99: =SUM(J97:J98) -> -4680000 | K99: =SUM(K97:K98) -> -5087921.2 | L99: =SUM(L97:L98) -> -7624339.3 | M99: =SUM(M97:M98) -> -10188091 | N99: =SUM(N97:N98) -> -12785410 | O99: =SUM(O97:O98) -> -15408790 | P99: =SUM(P97:P98) -> -18068448 | ... DY99: =SUM(DY97:DY98) -> 0
D100: Check | E100: =XIRR(J100:DY100,J14:DY14) -> 0.15000001 | G100: =SUM(I100:DY100) -> 33588257 | I100: =+I93+I95+I96+I98 -> 0 | J100: =+J93+J95+J96+J98 -> -4680000 | K100: =+K93+K95+K96+K98 -> -352037.71 | L100: =+L93+L95+L96+L98 -> -2475663.6 | M100: =+M93+M95+M96+M98 -> -2475663.6 | N100: =+N93+N95+N96+N98 -> -2475663.6 | O100: =+O93+O95+O96+O98 -> -2475663.6 | P100: =+P93+P95+P96+P98 -> -2475663.6 | ... DY100: =+DY93+DY95+DY96+DY98 -> 36351968
D104: ARGENT FUND CALC
D105: Total GP Cash Flow | E105: 1 | G105: =SUM(I105:DY105) -> 13483020 | H105: =H46+H48 -> 0 | J105: =J63 -> -520000 | K105: =K63 -> -39115.301 | L105: =L63 -> -275073.73 | M105: =M63 -> -275073.73 | N105: =N63 -> -275073.73 | O105: =O63 -> -275073.73 | P105: =P63 -> -275073.73 | Q105: =Q63 -> -264886.24 | ... DY105: =DY63 -> 13790099
D106: Fund Investors Cont. | E106: 0.9 | G106: =SUM(I106:DY106) -> -1979433.2 | H106: =IF(H105<0,$E$131*H105,0) -> 0 | J106: =IF(J105<0,$E$106*J105,0) -> -468000 | K106: =IF(K105<0,$E$106*K105,0) -> -35203.771 | L106: =IF(L105<0,$E$106*L105,0) -> -247566.36 | M106: =IF(M105<0,$E$106*M105,0) -> -247566.36 | N106: =IF(N105<0,$E$106*N105,0) -> -247566.36 | O106: =IF(O105<0,$E$106*O105,0) -> -247566.36 | P106: =IF(P105<0,$E$106*P105,0) -> -247566.36 | Q106: =IF(Q105<0,$E$106*Q105,0) -> -238397.62 | ... DY106: =IF(DY105<0,$E$106*DY105,0) -> 0
D107: Sponsor Cont. | E107: =E105-E106 -> 0.1 | G107: =SUM(I107:DY107) -> -219937.02 | H107: =IF(H105<0,$E$132*H105,0) -> 0 | J107: =IF(J105<0,$E$107*J105,0) -> -52000 | K107: =IF(K105<0,$E$107*K105,0) -> -3911.5301 | L107: =IF(L105<0,$E$107*L105,0) -> -27507.373 | M107: =IF(M105<0,$E$107*M105,0) -> -27507.373 | N107: =IF(N105<0,$E$107*N105,0) -> -27507.373 | O107: =IF(O105<0,$E$107*O105,0) -> -27507.373 | P107: =IF(P105<0,$E$107*P105,0) -> -27507.373 | Q107: =IF(Q105<0,$E$107*Q105,0) -> -26488.624 | ... DY107: =IF(DY105<0,$E$107*DY105,0) -> 0
D108: Promote to Sponsor | E108: 0.65
D110: Waterfall:
D112: 1. Preferred Return | E112: 0.1
D113: Beginning Balance | G113: =F118 -> 0 | H113: =G118 -> 0 | J113: =I118 -> 0 | K113: =J118 -> -520000 | L113: =K118 -> -563341.7 | M113: =L118 -> -842994.1 | N113: =M118 -> -1124697.5 | O113: =N118 -> -1408912.5 | P113: =O118 -> -1695066.6 | Q113: =P118 -> -1983917.3 | ... DY113: =DX118 -> -2488987.3
D114: Equity Draws | G114: =SUM(I114:DY114) -> -2199370.2 | H114: =H105 -> 0 | J114: =IF(J105<0,J105,0) -> -520000 | K114: =IF(K105<0,K105,0) -> -39115.301 | L114: =IF(L105<0,L105,0) -> -275073.73 | M114: =IF(M105<0,M105,0) -> -275073.73 | N114: =IF(N105<0,N105,0) -> -275073.73 | O114: =IF(O105<0,O105,0) -> -275073.73 | P114: =IF(P105<0,P105,0) -> -275073.73 | Q114: =IF(Q105<0,Q105,0) -> -264886.24 | ... DY114: =IF(DY105<0,DY105,0) -> 0
D115: Accrual | G115: =SUM(I115:DY115) -> -2012908.8 | H115: =H113*(((1+$E112)^((H$20-G$20)/365))-1) -> 0 | J115: =J113*(((1+$E112)^((J$20-I$20)/365))-1) -> 0 | K115: =K113*(((1+$E112)^((K$14-J$14)/365))-1) -> -4226.3983 | L115: =L113*(((1+$E112)^((L$14-K$14)/365))-1) -> -4578.6661 | M115: =M113*(((1+$E112)^((M$14-L$14)/365))-1) -> -6629.7079 | N115: =N113*(((1+$E112)^((N$14-M$14)/365))-1) -> -9141.1918 | O115: =O113*(((1+$E112)^((O$14-N$14)/365))-1) -> -11080.36 | P115: =P113*(((1+$E112)^((P$14-O$14)/365))-1) -> -13776.974 | Q115: =Q113*(((1+$E112)^((Q$14-P$14)/365))-1) -> -16124.662 | R115: =R113*(((1+$E112)^((R$14-Q$14)/365))-1) -> -17216.476 | ... DY115: =DY113*(((1+$E112)^((DY$14-DX$14)/365))-1) -> -20229.714
